Workbook
Name mydata: Data!$A$1:$P$193
Name Slicer_Departments: #N/A
Name Slicer_Name_Month: #N/A
Name Slicer_Year: #N/A

Sheet DASHBOARD

Sheet DASHBOARD Light

Sheet Processing
A1: Year | B1: =Control!B1 -> 2023
A2: Sales Plans | G2: Departments | M2: Mark | N2: •
A3: Revenue | G3: KPI | M3: CashOptic | N3: =IF(IFERROR(MATCH(M3,Control!$A$38:$A$41,0)>0,0),$N$2,"") -> •
A4: =GETPIVOTDATA("Average of Revenue Plan",Control!$A$3) -> 0.88833333 | B4: =IF(A4<100%,A4,0) -> 0.88833333 | C4: =IF(A4<100%,0,A4-1) -> 0 | D4: =IF(A4<100%,0,1-C4) -> 0 | E4: =IF(A4<100%,100%-B4,0) -> 0.11166667 | G4: =GETPIVOTDATA("Average of KPI",Control!$A$3) -> 0.89958333 | H4: =IF(G4<100%,G4,0) -> 0.89958333 | I4: =IF(G4<100%,0,G4-1) -> 0 | J4: =IF(G4<100%,0,1-I4) -> 0 | K4: =IF(G4<100%,100%-H4,0) -> 0.10041667 | M4: ClientPulse | N4: =IF(IFERROR(MATCH(M4,Control!$A$38:$A$41,0)>0,0),$N$2,"") -> •
A5: Profitability | M5: InnoForge | N5: =IF(IFERROR(MATCH(M5,Control!$A$38:$A$41,0)>0,0),$N$2,"") -> •
A6: =GETPIVOTDATA("Average of Profitability Plan",Control!$A$3) -> 0.65083333 | B6: =IF(A6<100%,A6,0) -> 0.65083333 | C6: =IF(A6<100%,0,A6-1) -> 0 | D6: =IF(A6<100%,0,1-C6) -> 0 | E6: =IF(A6<100%,100%-B6,0) -> 0.34916667 | G6: Factors of Influence | J6: Factors Coefficients | M6: MarketFlow | N6: =IF(IFERROR(MATCH(M6,Control!$A$38:$A$41,0)>0,0),$N$2,"") -> •
A7: Conversion | G7: Factors Ratio | J7: Positive Factors | K7: =GETPIVOTDATA("Average of Positive Factors",Control!$A$3) -> 7.7375
A8: =GETPIVOTDATA("Average of Conversion Plan",Control!$A$3) -> 0.595 | B8: =IF(A8<100%,A8,0) -> 0.595 | C8: =IF(A8<100%,0,A8-1) -> 0 | D8: =IF(A8<100%,0,1-C8) -> 0 | E8: =IF(A8<100%,100%-B8,0) -> 0.405 | G8: =GETPIVOTDATA("Average of Factor ratio",Control!$A$3) -> 0.68151178 | H8: =1-G8 -> 0.31848822 | J8: Negative Factors | K8: =GETPIVOTDATA("Average of Negative Factors",Control!$A$3) -> 3.5458333
A9: Transaction
A10: =GETPIVOTDATA("Average of Transaction Quantity Plan",Control!$A$3) -> 0.635 | B10: =IF(A10<100%,A10,0) -> 0.635 | C10: =IF(A10<100%,0,A10-1) -> 0 | D10: =IF(A10<100%,0,1-C10) -> 0 | E10: =IF(A10<100%,100%-B10,0) -> 0.365
F12: Profit / Loss | H12: 100 | J12: =0-H12 -> -100
C13: Revenue | F13: Profit | G13: Loss | H13: indent1 | I13: profit | J13: indent2 | K13: loss | L13: profit L2 | M13: loss L2 | N13: Labeles | O13: indent1 L2 | P13: indent2 L2 | Q13: dataTop | R13: dataDown | S13: dataTop L2 | T13: dataDown L2
A14: 1 | B14: JAN | C14: =GETPIVOTDATA(""&$C$13,Control!$A$20,"Month",A14) -> 30021 | D14: =IFERROR(GETPIVOTDATA(""&$C$13,Control!$A$3,"Month",A14),NA()) -> #N/A | F14: =GETPIVOTDATA(""&$F$13,Control!$A$20,"Month",A14) -> 1929 | G14: =GETPIVOTDATA(""&$G$13,Control!$A$20,"Month",A14) -> 1517 | H14: =IF(ISNA($D14),$H$12,0) -> 100 | I14: =IF(ISNA($D14),F14,0) -> 1929 | J14: =IF(ISNA($D14),$J$12,0) -> -100 | K14: =IF(ISNA($D14),0-G14,0) -> -1517 | L14: =IF(ISNA($D14),0,F14) -> 0 | M14: =IF(ISNA($D14),0,0-G14) -> 0 | N14: 0 | O14: =IF(ISNA($D14),0,H12) -> 0 | P14: =IF(ISNA($D14),0,$J$12) -> 0 | Q14: =IF(ISNA($D14),F14+$H$12/2,NA()) -> 1979 | R14: =IF(ISNA($D14),0-G14+$J$12/2,NA()) -> -1567 | S14: =IF(ISNA($D14),NA(),F14+$H$12/2) -> #N/A | T14: =IF(ISNA($D14),NA(),0-G14+$J$12/2) -> #N/A
A15: 2 | B15: FEB | C15: =GETPIVOTDATA(""&$C$13,Control!$A$20,"Month",A15) -> 28214 | D15: =IFERROR(GETPIVOTDATA(""&$C$13,Control!$A$3,"Month",A15),NA()) -> #N/A | F15: =GETPIVOTDATA(""&$F$13,Control!$A$20,"Month",A15) -> 1033 | G15: =GETPIVOTDATA(""&$G$13,Control!$A$20,"Month",A15) -> 1745 | H15: =IF(ISNA($D15),$H$12,0) -> 100 | I15: =IF(ISNA($D15),F15,0) -> 1033 | J15: =IF(ISNA($D15),$J$12,0) -> -100 | K15: =IF(ISNA($D15),0-G15,0) -> -1745 | L15: =IF(ISNA($D15),0,F15) -> 0 | M15: =IF(ISNA($D15),0,0-G15) -> 0 | N15: 0 | O15: =IF(ISNA($D15),0,H13) -> 0 | P15: =IF(ISNA($D15),0,$J$12) -> 0 | Q15: =IF(ISNA($D15),F15+$H$12/2,NA()) -> 1083 | R15: =IF(ISNA($D15),0-G15+$J$12/2,NA()) -> -1795 | S15: =IF(ISNA($D15),NA(),F15+$H$12/2) -> #N/A | T15: =IF(ISNA($D15),NA(),0-G15+$J$12/2) -> #N/A
A16: 3 | B16: MAR | C16: =GETPIVOTDATA(""&$C$13,Control!$A$20,"Month",A16) -> 23473 | D16: =IFERROR(GETPIVOTDATA(""&$C$13,Control!$A$3,"Month",A16),NA()) -> #N/A | F16: =GETPIVOTDATA(""&$F$13,Control!$A$20,"Month",A16) -> 2496 | G16: =GETPIVOTDATA(""&$G$13,Control!$A$20,"Month",A16) -> 1041 | H16: =IF(ISNA($D16),$H$12,0) -> 100 | I16: =IF(ISNA($D16),F16,0) -> 2496 | J16: =IF(ISNA($D16),$J$12,0) -> -100 | K16: =IF(ISNA($D16),0-G16,0) -> -1041 | L16: =IF(ISNA($D16),0,F16) -> 0 | M16: =IF(ISNA($D16),0,0-G16) -> 0 | N16: 0 | O16: =IF(ISNA($D16),0,H14) -> 0 | P16: =IF(ISNA($D16),0,$J$12) -> 0 | Q16: =IF(ISNA($D16),F16+$H$12/2,NA()) -> 2546 | R16: =IF(ISNA($D16),0-G16+$J$12/2,NA()) -> -1091 | S16: =IF(ISNA($D16),NA(),F16+$H$12/2) -> #N/A | T16: =IF(ISNA($D16),NA(),0-G16+$J$12/2) -> #N/A
A17: 4 | B17: APR | C17: =GETPIVOTDATA(""&$C$13,Control!$A$20,"Month",A17) -> 25280 | D17: =IFERROR(GETPIVOTDATA(""&$C$13,Control!$A$3,"Month",A17),NA()) -> 25280 | F17: =GETPIVOTDATA(""&$F$13,Control!$A$20,"Month",A17) -> 1937 | G17: =GETPIVOTDATA(""&$G$13,Control!$A$20,"Month",A17) -> 2265 | H17: =IF(ISNA($D17),$H$12,0) -> 0 | I17: =IF(ISNA($D17),F17,0) -> 0 | J17: =IF(ISNA($D17),$J$12,0) -> 0 | K17: =IF(ISNA($D17),0-G17,0) -> 0 | L17: =IF(ISNA($D17),0,F17) -> 1937 | M17: =IF(ISNA($D17),0,0-G17) -> -2265 | N17: 0 | O17: =IF(ISNA($D17),0,H15) -> 100 | P17: =IF(ISNA($D17),0,$J$12) -> -100 | Q17: =IF(ISNA($D17),F17+$H$12/2,NA()) -> #N/A | R17: =IF(ISNA($D17),0-G17+$J$12/2,NA()) -> #N/A | S17: =IF(ISNA($D17),NA(),F17+$H$12/2) -> 1987 | T17: =IF(ISNA($D17),NA(),0-G17+$J$12/2) -> -2315
A18: 5 | B18: MAY | C18: =GETPIVOTDATA(""&$C$13,Control!$A$20,"Month",A18) -> 28374 | D18: =IFERROR(GETPIVOTDATA(""&$C$13,Control!$A$3,"Month",A18),NA()) -> 28374 | F18: =GETPIVOTDATA(""&$F$13,Control!$A$20,"Month",A18) -> 2057 | G18: =GETPIVOTDATA(""&$G$13,Control!$A$20,"Month",A18) -> 1729 | H18: =IF(ISNA($D18),$H$12,0) -> 0 | I18: =IF(ISNA($D18),F18,0) -> 0 | J18: =IF(ISNA($D18),$J$12,0) -> 0 | K18: =IF(ISNA($D18),0-G18,0) -> 0 | L18: =IF(ISNA($D18),0,F18) -> 2057 | M18: =IF(ISNA($D18),0,0-G18) -> -1729 | N18: 0 | O18: =IF(ISNA($D18),0,H16) -> 100 | P18: =IF(ISNA($D18),0,$J$12) -> -100 | Q18: =IF(ISNA($D18),F18+$H$12/2,NA()) -> #N/A | R18: =IF(ISNA($D18),0-G18+$J$12/2,NA()) -> #N/A | S18: =IF(ISNA($D18),NA(),F18+$H$12/2) -> 2107 | T18: =IF(ISNA($D18),NA(),0-G18+$J$12/2) -> -1779
A19: 6 | B19: JUN | C19: =GETPIVOTDATA(""&$C$13,Control!$A$20,"Month",A19) -> 26823 | D19: =IFERROR(GETPIVOTDATA(""&$C$13,Control!$A$3,"Month",A19),NA()) -> 26823 | F19: =GETPIVOTDATA(""&$F$13,Control!$A$20,"Month",A19) -> 2146 | G19: =GETPIVOTDATA(""&$G$13,Control!$A$20,"Month",A19) -> 1751 | H19: =IF(ISNA($D19),$H$12,0) -> 0 | I19: =IF(ISNA($D19),F19,0) -> 0 | J19: =IF(ISNA($D19),$J$12,0) -> 0 | K19: =IF(ISNA($D19),0-G19,0) -> 0 | L19: =IF(ISNA($D19),0,F19) -> 2146 | M19: =IF(ISNA($D19),0,0-G19) -> -1751 | N19: 0 | O19: =IF(ISNA($D19),0,H17) -> 0 | P19: =IF(ISNA($D19),0,$J$12) -> -100 | Q19: =IF(ISNA($D19),F19+$H$12/2,NA()) -> #N/A | R19: =IF(ISNA($D19),0-G19+$J$12/2,NA()) -> #N/A | S19: =IF(ISNA($D19),NA(),F19+$H$12/2) -> 2196 | T19: =IF(ISNA($D19),NA(),0-G19+$J$12/2) -> -1801
A20: 7 | B20: JUL | C20: =GETPIVOTDATA(""&$C$13,Control!$A$20,"Month",A20) -> 32871 | D20: =IFERROR(GETPIVOTDATA(""&$C$13,Control!$A$3,"Month",A20),NA()) -> 32871 | F20: =GETPIVOTDATA(""&$F$13,Control!$A$20,"Month",A20) -> 1613 | G20: =GETPIVOTDATA(""&$G$13,Control!$A$20,"Month",A20) -> 1555 | H20: =IF(ISNA($D20),$H$12,0) -> 0 | I20: =IF(ISNA($D20),F20,0) -> 0 | J20: =IF(ISNA($D20),$J$12,0) -> 0 | K20: =IF(ISNA($D20),0-G20,0) -> 0 | L20: =IF(ISNA($D20),0,F20) -> 1613 | M20: =IF(ISNA($D20),0,0-G20) -> -1555 | N20: 0 | O20: =IF(ISNA($D20),0,H18) -> 0 | P20: =IF(ISNA($D20),0,$J$12) -> -100 | Q20: =IF(ISNA($D20),F20+$H$12/2,NA()) -> #N/A | R20: =IF(ISNA($D20),0-G20+$J$12/2,NA()) -> #N/A | S20: =IF(ISNA($D20),NA(),F20+$H$12/2) -> 1663 | T20: =IF(ISNA($D20),NA(),0-G20+$J$12/2) -> -1605
A21: 8 | B21: AUG | C21: =GETPIVOTDATA(""&$C$13,Control!$A$20,"Month",A21) -> 25108 | D21: =IFERROR(GETPIVOTDATA(""&$C$13,Control!$A$3,"Month",A21),NA()) -> 25108 | F21: =GETPIVOTDATA(""&$F$13,Control!$A$20,"Month",A21) -> 1525 | G21: =GETPIVOTDATA(""&$G$13,Control!$A$20,"Month",A21) -> 1836 | H21: =IF(ISNA($D21),$H$12,0) -> 0 | I21: =IF(ISNA($D21),F21,0) -> 0 | J21: =IF(ISNA($D21),$J$12,0) -> 0 | K21: =IF(ISNA($D21),0-G21,0) -> 0 | L21: =IF(ISNA($D21),0,F21) -> 1525 | M21: =IF(ISNA($D21),0,0-G21) -> -1836 | N21: 0 | O21: =IF(ISNA($D21),0,H19) -> 0 | P21: =IF(ISNA($D21),0,$J$12) -> -100 | Q21: =IF(ISNA($D21),F21+$H$12/2,NA()) -> #N/A | R21: =IF(ISNA($D21),0-G21+$J$12/2,NA()) -> #N/A | S21: =IF(ISNA($D21),NA(),F21+$H$12/2) -> 1575 | T21: =IF(ISNA($D21),NA(),0-G21+$J$12/2) -> -1886
A22: 9 | B22: SEP | C22: =GETPIVOTDATA(""&$C$13,Control!$A$20,"Month",A22) -> 28741 | D22: =IFERROR(GETPIVOTDATA(""&$C$13,Control!$A$3,"Month",A22),NA()) -> 28741 | F22: =GETPIVOTDATA(""&$F$13,Control!$A$20,"Month",A22) -> 2404 | G22: =GETPIVOTDATA(""&$G$13,Control!$A$20,"Month",A22) -> 1711 | H22: =IF(ISNA($D22),$H$12,0) -> 0 | I22: =IF(ISNA($D22),F22,0) -> 0 | J22: =IF(ISNA($D22),$J$12,0) -> 0 | K22: =IF(ISNA($D22),0-G22,0) -> 0 | L22: =IF(ISNA($D22),0,F22) -> 2404 | M22: =IF(ISNA($D22),0,0-G22) -> -1711 | N22: 0 | O22: =IF(ISNA($D22),0,H20) -> 0 | P22: =IF(ISNA($D22),0,$J$12) -> -100 | Q22: =IF(ISNA($D22),F22+$H$12/2,NA()) -> #N/A | R22: =IF(ISNA($D22),0-G22+$J$12/2,NA()) -> #N/A | S22: =IF(ISNA($D22),NA(),F22+$H$12/2) -> 2454 | T22: =IF(ISNA($D22),NA(),0-G22+$J$12/2) -> -1761
A23: 10 | B23: OCT | C23: =GETPIVOTDATA(""&$C$13,Control!$A$20,"Month",A23) -> 25964 | D23: =IFERROR(GETPIVOTDATA(""&$C$13,Control!$A$3,"Month",A23),NA()) -> #N/A | F23: =GETPIVOTDATA(""&$F$13,Control!$A$20,"Month",A23) -> 1565 | G23: =GETPIVOTDATA(""&$G$13,Control!$A$20,"Month",A23) -> 1645 | H23: =IF(ISNA($D23),$H$12,0) -> 100 | I23: =IF(ISNA($D23),F23,0) -> 1565 | J23: =IF(ISNA($D23),$J$12,0) -> -100 | K23: =IF(ISNA($D23),0-G23,0) -> -1645 | L23: =IF(ISNA($D23),0,F23) -> 0 | M23: =IF(ISNA($D23),0,0-G23) -> 0 | N23: 0 | O23: =IF(ISNA($D23),0,H21) -> 0 | P23: =IF(ISNA($D23),0,$J$12) -> 0 | Q23: =IF(ISNA($D23),F23+$H$12/2,NA()) -> 1615 | R23: =IF(ISNA($D23),0-G23+$J$12/2,NA()) -> -1695 | S23: =IF(ISNA($D23),NA(),F23+$H$12/2) -> #N/A | T23: =IF(ISNA($D23),NA(),0-G23+$J$12/2) -> #N/A
A24: 11 | B24: NOV | C24: =GETPIVOTDATA(""&$C$13,Control!$A$20,"Month",A24) -> 29363 | D24: =IFERROR(GETPIVOTDATA(""&$C$13,Control!$A$3,"Month",A24),NA()) -> #N/A | F24: =GETPIVOTDATA(""&$F$13,Control!$A$20,"Month",A24) -> 2975 | G24: =GETPIVOTDATA(""&$G$13,Control!$A$20,"Month",A24) -> 1504 | H24: =IF(ISNA($D24),$H$12,0) -> 100 | I24: =IF(ISNA($D24),F24,0) -> 2975 | J24: =IF(ISNA($D24),$J$12,0) -> -100 | K24: =IF(ISNA($D24),0-G24,0) -> -1504 | L24: =IF(ISNA($D24),0,F24) -> 0 | M24: =IF(ISNA($D24),0,0-G24) -> 0 | N24: 0 | O24: =IF(ISNA($D24),0,H22) -> 0 | P24: =IF(ISNA($D24),0,$J$12) -> 0 | Q24: =IF(ISNA($D24),F24+$H$12/2,NA()) -> 3025 | R24: =IF(ISNA($D24),0-G24+$J$12/2,NA()) -> -1554 | S24: =IF(ISNA($D24),NA(),F24+$H$12/2) -> #N/A | T24: =IF(ISNA($D24),NA(),0-G24+$J$12/2) -> #N/A
A25: 12 | B25: DEC | C25: =GETPIVOTDATA(""&$C$13,Control!$A$20,"Month",A25) -> 26430 | D25: =IFERROR(GETPIVOTDATA(""&$C$13,Control!$A$3,"Month",A25),NA()) -> #N/A | F25: =GETPIVOTDATA(""&$F$13,Control!$A$20,"Month",A25) -> 1019 | G25: =GETPIVOTDATA(""&$G$13,Control!$A$20,"Month",A25) -> 1338 | H25: =IF(ISNA($D25),$H$12,0) -> 100 | I25: =IF(ISNA($D25),F25,0) -> 1019 | J25: =IF(ISNA($D25),$J$12,0) -> -100 | K25: =IF(ISNA($D25),0-G25,0) -> -1338 | L25: =IF(ISNA($D25),0,F25) -> 0 | M25: =IF(ISNA($D25),0,0-G25) -> 0 | N25: 0 | O25: =IF(ISNA($D25),0,H23) -> 0 | P25: =IF(ISNA($D25),0,$J$12) -> 0 | Q25: =IF(ISNA($D25),F25+$H$12/2,NA()) -> 1069 | R25: =IF(ISNA($D25),0-G25+$J$12/2,NA()) -> -1388 | S25: =IF(ISNA($D25),NA(),F25+$H$12/2) -> #N/A | T25: =IF(ISNA($D25),NA(),0-G25+$J$12/2) -> #N/A
D26: =SUMIF(D14:D25,">0") -> 167197 | L26: =SUMIF(L14:L25,">0") -> 11682 | M26: =SUMIF(M14:M25,"<0") -> -10847
B27: Cash Flow | C27: start | D27: end | E27: alt | H27: Total Annual Profit
A28: 1 | B28: =GETPIVOTDATA(""&$B$27,Control!$A$20,"Month",A28) -> 237556 | C28: {=IF(D14=INDEX($D$14:$D$25,MATCH(TRUE,$D$14:$D$25>0,0)),B28,NA())} -> #N/A | D28: {=IF(D14=INDEX($D$14:$D$25,MAX(IFERROR(IF($D$14:$D$25>0,ROW($D$14:$D$25)-MIN(ROW($D$14:$D$25))+1),0))),B28,NA())} -> #N/A | E28: {=IF(OR(D14=INDEX($D$14:$D$25,MATCH(TRUE,$D$14:$D$25>0,0)),D14=INDEX($D$14:$D$25,MAX(IFERROR(IF($D$14:$D$25>0,ROW($D$14:$D$25)-MIN(ROW($D$14:$D$25))+1),0)))),B28,NA())} -> #N/A | F28: =IF(ISNA(D14),D14,B28) -> #N/A | J28: 0 | K28: 0 | L28: 0 | M28: 0 | N28: =IF($B$1=H28,I28,0) -> 0 | O28: {=INDEX(I29:I32,P28-1)} -> 22699 | P28: =MATCH(B1,H29:H32,0)+1 -> 3
A29: 2 | B29: =GETPIVOTDATA(""&$B$27,Control!$A$20,"Month",A29) -> 283339 | C29: {=IF(D15=INDEX($D$14:$D$25,MATCH(TRUE,$D$14:$D$25>0,0)),B29,NA())} -> #N/A | D29: {=IF(D15=INDEX($D$14:$D$25,MAX(IFERROR(IF($D$14:$D$25>0,ROW($D$14:$D$25)-MIN(ROW($D$14:$D$25))+1),0))),B29,NA())} -> #N/A | E29: {=IF(OR(D15=INDEX($D$14:$D$25,MATCH(TRUE,$D$14:$D$25>0,0)),D15=INDEX($D$14:$D$25,MAX(IFERROR(IF($D$14:$D$25>0,ROW($D$14:$D$25)-MIN(ROW($D$14:$D$25))+1),0)))),B29,NA())} -> #N/A | F29: =IF(ISNA(D15),D15,B29) -> #N/A | H29: 2022 | I29: =SUMIF(Data!$A$2:$A$193,H29,Data!$I$2:$I$193) -> 23981 | J29: =IF($B$1=H29,0,I29) -> 23981 | K29: 0 | L29: 0 | M29: 0 | N29: =IF($B$1=H29,I29,0) -> 0
A30: 3 | B30: =GETPIVOTDATA(""&$B$27,Control!$A$20,"Month",A30) -> 281728 | C30: {=IF(D16=INDEX($D$14:$D$25,MATCH(TRUE,$D$14:$D$25>0,0)),B30,NA())} -> #N/A | D30: {=IF(D16=INDEX($D$14:$D$25,MAX(IFERROR(IF($D$14:$D$25>0,ROW($D$14:$D$25)-MIN(ROW($D$14:$D$25))+1),0))),B30,NA())} -> #N/A | E30: {=IF(OR(D16=INDEX($D$14:$D$25,MATCH(TRUE,$D$14:$D$25>0,0)),D16=INDEX($D$14:$D$25,MAX(IFERROR(IF($D$14:$D$25>0,ROW($D$14:$D$25)-MIN(ROW($D$14:$D$25))+1),0)))),B30,NA())} -> #N/A | F30: =IF(ISNA(D16),D16,B30) -> #N/A | H30: 2023 | I30: =SUMIF(Data!$A$2:$A$193,H30,Data!$I$2:$I$193) -> 22699 | J30: 0 | K30: =IF($B$1=H30,0,I30) -> 0 | L30: 0 | M30: 0 | N30: =IF($B$1=H30,I30,0) -> 22699
A31: 4 | B31: =GETPIVOTDATA(""&$B$27,Control!$A$20,"Month",A31) -> 292458 | C31: {=IF(D17=INDEX($D$14:$D$25,MATCH(TRUE,$D$14:$D$25>0,0)),B31,NA())} -> 292458 | D31: {=IF(D17=INDEX($D$14:$D$25,MAX(IFERROR(IF($D$14:$D$25>0,ROW($D$14:$D$25)-MIN(ROW($D$14:$D$25))+1),0))),B31,NA())} -> #N/A | E31: {=IF(OR(D17=INDEX($D$14:$D$25,MATCH(TRUE,$D$14:$D$25>0,0)),D17=INDEX($D$14:$D$25,MAX(IFERROR(IF($D$14:$D$25>0,ROW($D$14:$D$25)-MIN(ROW($D$14:$D$25))+1),0)))),B31,NA())} -> 292458 | F31: =IF(ISNA(D17),D17,B31) -> 292458 | H31: 2024 | I31: =SUMIF(Data!$A$2:$A$193,H31,Data!$I$2:$I$193) -> 24836 | J31: 0 | K31: 0 | L31: =IF($B$1=H31,0,I31) -> 24836 | M31: 0 | N31: =IF($B$1=H31,I31,0) -> 0
A32: 5 | B32: =GETPIVOTDATA(""&$B$27,Control!$A$20,"Month",A32) -> 330740 | C32: {=IF(D18=INDEX($D$14:$D$25,MATCH(TRUE,$D$14:$D$25>0,0)),B32,NA())} -> #N/A | D32: {=IF(D18=INDEX($D$14:$D$25,MAX(IFERROR(IF($D$14:$D$25>0,ROW($D$14:$D$25)-MIN(ROW($D$14:$D$25))+1),0))),B32,NA())} -> #N/A | E32: {=IF(OR(D18=INDEX($D$14:$D$25,MATCH(TRUE,$D$14:$D$25>0,0)),D18=INDEX($D$14:$D$25,MAX(IFERROR(IF($D$14:$D$25>0,ROW($D$14:$D$25)-MIN(ROW($D$14:$D$25))+1),0)))),B32,NA())} -> #N/A | F32: =IF(ISNA(D18),D18,B32) -> 330740 | H32: 2025 | I32: =SUMIF(Data!$A$2:$A$193,H32,Data!$I$2:$I$193) -> 28781 | J32: 0 | K32: 0 | L32: 0 | M32: =IF($B$1=H32,0,I32) -> 28781 | N32: =IF($B$1=H32,I32,0) -> 0
A33: 6 | B33: =GETPIVOTDATA(""&$B$27,Control!$A$20,"Month",A33) -> 339060 | C33: {=IF(D19=INDEX($D$14:$D$25,MATCH(TRUE,$D$14:$D$25>0,0)),B33,NA())} -> #N/A | D33: {=IF(D19=INDEX($D$14:$D$25,MAX(IFERROR(IF($D$14:$D$25>0,ROW($D$14:$D$25)-MIN(ROW($D$14:$D$25))+1),0))),B33,NA())} -> #N/A | E33: {=IF(OR(D19=INDEX($D$14:$D$25,MATCH(TRUE,$D$14:$D$25>0,0)),D19=INDEX($D$14:$D$25,MAX(IFERROR(IF($D$14:$D$25>0,ROW($D$14:$D$25)-MIN(ROW($D$14:$D$25))+1),0)))),B33,NA())} -> #N/A | F33: =IF(ISNA(D19),D19,B33) -> 339060 | J33: 0 | K33: 0 | L33: 0 | M33: 0 | N33: =IF($B$1=H33,I33,0) -> 0
A34: 7 | B34: =GETPIVOTDATA(""&$B$27,Control!$A$20,"Month",A34) -> 296183 | C34: {=IF(D20=INDEX($D$14:$D$25,MATCH(TRUE,$D$14:$D$25>0,0)),B34,NA())} -> #N/A | D34: {=IF(D20=INDEX($D$14:$D$25,MAX(IFERROR(IF($D$14:$D$25>0,ROW($D$14:$D$25)-MIN(ROW($D$14:$D$25))+1),0))),B34,NA())} -> #N/A | E34: {=IF(OR(D20=INDEX($D$14:$D$25,MATCH(TRUE,$D$14:$D$25>0,0)),D20=INDEX($D$14:$D$25,MAX(IFERROR(IF($D$14:$D$25>0,ROW($D$14:$D$25)-MIN(ROW($D$14:$D$25))+1),0)))),B34,NA())} -> #N/A | F34: =IF(ISNA(D20),D20,B34) -> 296183
A35: 8 | B35: =GETPIVOTDATA(""&$B$27,Control!$A$20,"Month",A35) -> 297657 | C35: {=IF(D21=INDEX($D$14:$D$25,MATCH(TRUE,$D$14:$D$25>0,0)),B35,NA())} -> #N/A | D35: {=IF(D21=INDEX($D$14:$D$25,MAX(IFERROR(IF($D$14:$D$25>0,ROW($D$14:$D$25)-MIN(ROW($D$14:$D$25))+1),0))),B35,NA())} -> #N/A | E35: {=IF(OR(D21=INDEX($D$14:$D$25,MATCH(TRUE,$D$14:$D$25>0,0)),D21=INDEX($D$14:$D$25,MAX(IFERROR(IF($D$14:$D$25>0,ROW($D$14:$D$25)-MIN(ROW($D$14:$D$25))+1),0)))),B35,NA())} -> #N/A | F35: =IF(ISNA(D21),D21,B35) -> 297657
A36: 9 | B36: =GETPIVOTDATA(""&$B$27,Control!$A$20,"Month",A36) -> 278300 | C36: {=IF(D22=INDEX($D$14:$D$25,MATCH(TRUE,$D$14:$D$25>0,0)),B36,NA())} -> #N/A | D36: {=IF(D22=INDEX($D$14:$D$25,MAX(IFERROR(IF($D$14:$D$25>0,ROW($D$14:$D$25)-MIN(ROW($D$14:$D$25))+1),0))),B36,NA())} -> 278300 | E36: {=IF(OR(D22=INDEX($D$14:$D$25,MATCH(TRUE,$D$14:$D$25>0,0)),D22=INDEX($D$14:$D$25,MAX(IFERROR(IF($D$14:$D$25>0,ROW($D$14:$D$25)-MIN(ROW($D$14:$D$25))+1),0)))),B36,NA())} -> 278300 | F36: =IF(ISNA(D22),D22,B36) -> 278300
A37: 10 | B37: =GETPIVOTDATA(""&$B$27,Control!$A$20,"Month",A37) -> 284396 | C37: {=IF(D23=INDEX($D$14:$D$25,MATCH(TRUE,$D$14:$D$25>0,0)),B37,NA())} -> #N/A | D37: {=IF(D23=INDEX($D$14:$D$25,MAX(IFERROR(IF($D$14:$D$25>0,ROW($D$14:$D$25)-MIN(ROW($D$14:$D$25))+1),0))),B37,NA())} -> #N/A | E37: {=IF(OR(D23=INDEX($D$14:$D$25,MATCH(TRUE,$D$14:$D$25>0,0)),D23=INDEX($D$14:$D$25,MAX(IFERROR(IF($D$14:$D$25>0,ROW($D$14:$D$25)-MIN(ROW($D$14:$D$25))+1),0)))),B37,NA())} -> #N/A | F37: =IF(ISNA(D23),D23,B37) -> #N/A
A38: 11 | B38: =GETPIVOTDATA(""&$B$27,Control!$A$20,"Month",A38) -> 324839 | C38: {=IF(D24=INDEX($D$14:$D$25,MATCH(TRUE,$D$14:$D$25>0,0)),B38,NA())} -> #N/A | D38: {=IF(D24=INDEX($D$14:$D$25,MAX(IFERROR(IF($D$14:$D$25>0,ROW($D$14:$D$25)-MIN(ROW($D$14:$D$25))+1),0))),B38,NA())} -> #N/A | E38: {=IF(OR(D24=INDEX($D$14:$D$25,MATCH(TRUE,$D$14:$D$25>0,0)),D24=INDEX($D$14:$D$25,MAX(IFERROR(IF($D$14:$D$25>0,ROW($D$14:$D$25)-MIN(ROW($D$14:$D$25))+1),0)))),B38,NA())} -> #N/A | F38: =IF(ISNA(D24),D24,B38) -> #N/A
A39: 12 | B39: =GETPIVOTDATA(""&$B$27,Control!$A$20,"Month",A39) -> 281229 | C39: {=IF(D25=INDEX($D$14:$D$25,MATCH(TRUE,$D$14:$D$25>0,0)),B39,NA())} -> #N/A | D39: {=IF(D25=INDEX($D$14:$D$25,MAX(IFERROR(IF($D$14:$D$25>0,ROW($D$14:$D$25)-MIN(ROW($D$14:$D$25))+1),0))),B39,NA())} -> #N/A | E39: {=IF(OR(D25=INDEX($D$14:$D$25,MATCH(TRUE,$D$14:$D$25>0,0)),D25=INDEX($D$14:$D$25,MAX(IFERROR(IF($D$14:$D$25>0,ROW($D$14:$D$25)-MIN(ROW($D$14:$D$25))+1),0)))),B39,NA())} -> #N/A | F39: =IF(ISNA(D25),D25,B39) -> #N/A
B40: =SUM(B28:B39) -> 3527485 | F40: =SUMIF(F28:F39,">0") -> 1834398

Sheet Data
A1: Year | B1: Month | C1: Name Month | D1: Departments | E1: Revenue Plan | F1: Profitability Plan | G1: Conversion Plan | H1: Transaction Quantity Plan | I1: Profit | J1: Loss | K1: KPI | L1: Positive Factors | M1: Negative Factors | N1: Factor ratio | O1: Cash Flow | P1: Revenue
A2: 2022 | B2: 1 | C2: JAN | D2: InnoForge | E2: 0.88 | F2: 0.65 | G2: 0.43 | H2: 0.95 | I2: 647 | J2: 112 | K2: 1.1 | L2: 7.6 | M2: 4.5 | N2: =L2/(L2+M2) -> 0.62809917 | O2: 54273 | P2: 4713
A3: 2022 | B3: 2 | C3: FEB | D3: InnoForge | E3: 0.93 | F3: 0.75 | G3: 0.57 | H3: 0.81 | I3: 663 | J3: 97 | K3: 0.8 | L3: 6 | M3: 4 | N3: =L3/(L3+M3) -> 0.6 | O3: 70184 | P3: 4660
A4: 2022 | B4: 3 | C4: MAR | D4: InnoForge | E4: 0.92 | F4: 0.79 | G4: 0.75 | H4: 0.58 | I4: 575 | J4: 38 | K4: 1.17 | L4: 5.8 | M4: 4.2 | N4: =L4/(L4+M4) -> 0.58 | O4: 55321 | P4: 6259
A5: 2022 | B5: 4 | C5: APR | D5: InnoForge | E5: 0.92 | F5: 0.53 | G5: 0.56 | H5: 0.95 | I5: 271 | J5: 448 | K5: 0.79 | L5: 5.1 | M5: 3.1 | N5: =L5/(L5+M5) -> 0.62195122 | O5: 44235 | P5: 8885
A6: 2022 | B6: 5 | C6: MAY | D6: InnoForge | E6: 1.05 | F6: 0.6 | G6: 0.51 | H6: 0.63 | I6: 604 | J6: 356 | K6: 1.03 | L6: 8.1 | M6: 3.3 | N6: =L6/(L6+M6) -> 0.71052632 | O6: 44309 | P6: 7606
A7: 2022 | B7: 6 | C7: JUN | D7: InnoForge | E7: 0.87 | F7: 0.54 | G7: 0.68 | H7: 0.58 | I7: 557 | J7: 33 | K7: 0.65 | L7: 9.6 | M7: 3.6 | N7: =L7/(L7+M7) -> 0.72727273 | O7: 70269 | P7: 8541
A8: 2022 | B8: 7 | C8: JUL | D8: InnoForge | E8: 0.9 | F8: 0.81 | G8: 0.47 | H8: 0.7 | I8: 915 | J8: 153 | K8: 0.91 | L8: 9.7 | M8: 2.8 | N8: =L8/(L8+M8) -> 0.776 | O8: 87151 | P8: 6941
A9: 2022 | B9: 8 | C9: AUG | D9: InnoForge | E9: 0.84 | F9: 0.8 | G9: 0.45 | H9: 0.92 | I9: 993 | J9: 240 | K9: 0.96 | L9: 7.4 | M9: 3.2 | N9: =L9/(L9+M9) -> 0.69811321 | O9: 69112 | P9: 7427
A10: 2022 | B10: 9 | C10: SEP | D10: InnoForge | E10: 0.79 | F10: 0.78 | G10: 0.64 | H10: 0.45 | I10: 659 | J10: 374 | K10: 0.9 | L10: 8 | M10: 4.2 | N10: =L10/(L10+M10) -> 0.6557377 | O10: 62321 | P10: 8984
A11: 2022 | B11: 10 | C11: OCT | D11: InnoForge | E11: 1.1 | F11: 0.53 | G11: 0.6 | H11: 0.57 | I11: 219 | J11: 440 | K11: 0.66 | L11: 9.3 | M11: 4.8 | N11: =L11/(L11+M11) -> 0.65957447 | O11: 53127 | P11: 8695
A12: 2022 | B12: 11 | C12: NOV | D12: InnoForge | E12: 0.81 | F12: 0.37 | G12: 0.4 | H12: 0.98 | I12: 762 | J12: 324 | K12: 0.72 | L12: 9.9 | M12: 4.3 | N12: =L12/(L12+M12) -> 0.6971831 | O12: 86122 | P12: 5150
A13: 2022 | B13: 12 | C13: DEC | D13: InnoForge | E13: 1.08 | F13: 0.37 | G13: 0.49 | H13: 0.51 | I13: 939 | J13: 44 | K13: 1.09 | L13: 6.6 | M13: 4.8 | N13: =L13/(L13+M13) -> 0.57894737 | O13: 85271 | P13: 7412
... A193: 2025 | B193: 12 | C193: DEC | D193: ClientPulse | E193: 0.75 | F193: 0.53 | G193: 0.46 | H193: 0.72 | I193: 910 | J193: 393 | K193: 1.09 | L193: 9.2 | M193: 4.4 | N193: =L193/(L193+M193) -> 0.67647059 | O193: 83422 | P193: 6323

Sheet Control
A1: Year | B1: 2023
A3: Row Labels | B3: Average of Revenue Plan | C3: Average of Profitability Plan | D3: Average of Conversion Plan | E3: Average of Transaction Quantity Plan | F3: Sum of Revenue | G3: Average of KPI | H3: Average of Positive Factors | I3: Average of Negative Factors | J3: Average of Factor ratio
A4: 4 | B4: 0.935 | C4: 0.6825 | D4: 0.58 | E4: 0.71 | F4: 25280 | G4: 0.94 | H4: 8.675 | I4: 3.8 | J4: 0.68988834
A5: 5 | B5: 0.785 | C5: 0.5225 | D5: 0.6275 | E5: 0.645 | F5: 28374 | G5: 0.985 | H5: 8.2 | I5: 3 | J5: 0.72488855
A6: 6 | B6: 0.815 | C6: 0.63 | D6: 0.5775 | E6: 0.6825 | F6: 26823 | G6: 0.895 | H6: 6.55 | I6: 3.025 | J6: 0.68226156
A7: 7 | B7: 0.9 | C7: 0.7725 | D7: 0.5825 | E7: 0.61 | F7: 32871 | G7: 0.825 | H7: 8.175 | I7: 3.575 | J7: 0.68693281
A8: 8 | B8: 0.905 | C8: 0.615 | D8: 0.5625 | E8: 0.525 | F8: 25108 | G8: 0.865 | H8: 7.875 | I8: 3.65 | J8: 0.68170669
A9: 9 | B9: 0.99 | C9: 0.6825 | D9: 0.64 | E9: 0.6375 | F9: 28741 | G9: 0.8875 | H9: 6.95 | I9: 4.225 | J9: 0.62339272
A10: Grand Total | B10: 0.88833333 | C10: 0.65083333 | D10: 0.595 | E10: 0.635 | F10: 167197 | G10: 0.89958333 | H10: 7.7375 | I10: 3.5458333 | J10: 0.68151178
A18: Departments | B18: (All)
A20: Row Labels | B20: Sum of Revenue | C20: Sum of Profit | D20: Sum of Loss | E20: Sum of Cash Flow
A21: 1 | B21: 30021 | C21: 1929 | D21: 1517 | E21: 237556
A22: 2 | B22: 28214 | C22: 1033 | D22: 1745 | E22: 283339
A23: 3 | B23: 23473 | C23: 2496 | D23: 1041 | E23: 281728
A24: 4 | B24: 25280 | C24: 1937 | D24: 2265 | E24: 292458
A25: 5 | B25: 28374 | C25: 2057 | D25: 1729 | E25: 330740
A26: 6 | B26: 26823 | C26: 2146 | D26: 1751 | E26: 339060
A27: 7 | B27: 32871 | C27: 1613 | D27: 1555 | E27: 296183
A28: 8 | B28: 25108 | C28: 1525 | D28: 1836 | E28: 297657
A29: 9 | B29: 28741 | C29: 2404 | D29: 1711 | E29: 278300
A30: 10 | B30: 25964 | C30: 1565 | D30: 1645 | E30: 284396
A31: 11 | B31: 29363 | C31: 2975 | D31: 1504 | E31: 324839
A32: 12 | B32: 26430 | C32: 1019 | D32: 1338 | E32: 281229
A33: Grand Total | B33: 330662 | C33: 22699 | D33: 19637 | E33: 3527485
A37: Row Labels
A38: CashOptic
A39: ClientPulse
A40: InnoForge
A41: MarketFlow

Sheet Resources
A2: 47136 | D2: 490 | M2: Business Intelligence Dashboard
A3: 46603 | D3: 553 | M3: BUSINESS INTELLIGENCE DASHBOARD
A4: 62591 | D4: 442 | M4: DASHBOARD
A5: 88850 | D5: 437 | M5: BUSINESS INTELLIGENCE
A6: 76061 | D6: 622
A7: 85413 | D7: 609
A8: 69412 | D8: 727
A9: 74278 | D9: 540
A10: 89848 | D10: 794
A11: 86956 | D11: 840
A12: 51503 | D12: 700
A13: 74124 | D13: 807
