Workbook
Name dborders: 'ALL ORDERS'!$A$3:$X$806
Name Slicer_Month: #N/A
Name Slicer_Year: #N/A

Sheet DASHBOARD

Sheet ALL ORDERS
F2: ALL ORDERS
A3: Registration Date | B3: Day | C3: Month | D3: Year | E3: Manager | F3: Service | G3: Cash | H3: Card | I3: Discount | J3: Total | K3: Date of visit | L3: Day of visit | M3: Month of visit | N3: Year of visit | O3: Visit time | P3: Client | Q3: City | R3: Address | S3: Master | T3: Contact | U3: Channel | V3: Status | W3: Cost | X3: Client rating
A4: 44927 | B4: =DAY(A4) -> 1 | C4: {=INDEX(Processing!$C$11:$C$22,MONTH('ALL ORDERS'!A4))} -> JAN | D4: =YEAR(A4) -> 2023 | E4: Jacob | F4: Dismantling the balcony block | G4: 4500 | H4: 0 | J4: =G4+H4 -> 4500 | K4: 44927 | L4: =DAY(K4) -> 1 | M4: {=INDEX(Processing!$W$6:$W$17,MONTH('ALL ORDERS'!K4))} -> January | N4: =YEAR(K4) -> 2023 | O4: 0.4375 | P4: Client 1 | Q4: Chikago | R4: 123 Elm Street, Apt. 4B | S4: Jack | T4: (917) 555-5616 | U4: Instagram | V4: Completed | W4: 5618 | X4: 5 | Y4: 1467 | Z4: =W4+Y4 -> 7085
A5: 44928 | B5: =DAY(A5) -> 2 | C5: {=INDEX(Processing!$C$11:$C$22,MONTH('ALL ORDERS'!A5))} -> JAN | D5: =YEAR(A5) -> 2023 | E5: Joseph | F5: Laying parquet boards with glue | G5: 10000 | H5: 0 | J5: =G5+H5 -> 10000 | K5: 44928 | L5: =DAY(K5) -> 2 | M5: {=INDEX(Processing!$W$6:$W$17,MONTH('ALL ORDERS'!K5))} -> January | N5: =YEAR(K5) -> 2023 | O5: 0.41666667 | P5: Client 2 | Q5: Chikago | R5: 456 Willow Avenue, Unit 7 | S5: William | T5: (718) 555-8703 | U5: WhatsApp | V5: Completed | W5: 10619 | X5: 4 | Y5: 2073 | Z5: =W5+Y5 -> 12692
A6: 44929 | B6: =DAY(A6) -> 3 | C6: {=INDEX(Processing!$C$11:$C$22,MONTH('ALL ORDERS'!A6))} -> JAN | D6: =YEAR(A6) -> 2023 | E6: Liam | F6: Laying quartz vinyl tiles on a substrate | G6: 5450 | H6: 0 | J6: =G6+H6 -> 5450 | K6: 44929 | L6: =DAY(K6) -> 3 | M6: {=INDEX(Processing!$W$6:$W$17,MONTH('ALL ORDERS'!K6))} -> January | N6: =YEAR(K6) -> 2023 | O6: 0.5 | P6: Client 3 | Q6: New York | R6: 789 Oak Lane, Suite 12 | S6: James | T6: (646) 555-2283 | U6: Facebook | V6: Completed | W6: 8931 | X6: 4 | Y6: 1235 | Z6: =W6+Y6 -> 10166
A7: 44930 | B7: =DAY(A7) -> 4 | C7: {=INDEX(Processing!$C$11:$C$22,MONTH('ALL ORDERS'!A7))} -> JAN | D7: =YEAR(A7) -> 2023 | E7: Isabella | F7: Laying parquet boards on a substrate | G7: 6200 | H7: 0 | J7: =G7+H7 -> 6200 | K7: 44930 | L7: =DAY(K7) -> 4 | M7: {=INDEX(Processing!$W$6:$W$17,MONTH('ALL ORDERS'!K7))} -> January | N7: =YEAR(K7) -> 2023 | O7: 0.66666667 | P7: Client 4 | Q7: Chikago | R7: 234 Pine Road, Apt. 3C | S7: Oliver | T7: (212) 555-7828 | U7: Reddit | V7: Completed | W7: 11848 | X7: 4 | Y7: 1883 | Z7: =W7+Y7 -> 13731
A8: 44957 | B8: =DAY(A8) -> 31 | C8: {=INDEX(Processing!$C$11:$C$22,MONTH('ALL ORDERS'!A8))} -> JAN | D8: =YEAR(A8) -> 2023 | E8: Joseph | F8: Laying parquet boards on a substrate | G8: 5000 | H8: 6250 | J8: =G8+H8 -> 11250 | K8: 44957 | L8: =DAY(K8) -> 31 | M8: {=INDEX(Processing!$W$6:$W$17,MONTH('ALL ORDERS'!K8))} -> January | N8: =YEAR(K8) -> 2023 | O8: 0.70833333 | P8: Client 5 | Q8: Chikago | R8: 235 Pine Road, Apt. 3C | S8: Lucas | T8: (212) 555-7829 | U8: Instagram | V8: Completed | W8: 2176 | X8: 5 | Y8: 921 | Z8: =W8+Y8 -> 3097
A9: 44931 | B9: =DAY(A9) -> 5 | C9: {=INDEX(Processing!$C$11:$C$22,MONTH('ALL ORDERS'!A9))} -> JAN | D9: =YEAR(A9) -> 2023 | E9: Charlotte | F9: Laying solid boards | G9: 4000 | H9: 0 | J9: =G9+H9 -> 4000 | K9: 44931 | L9: =DAY(K9) -> 5 | M9: {=INDEX(Processing!$W$6:$W$17,MONTH('ALL ORDERS'!K9))} -> January | N9: =YEAR(K9) -> 2023 | O9: 0.4375 | P9: Client 5 | Q9: Chikago | R9: 567 Birch Street, Unit 8D | S9: Sofia | T9: (917) 555-4259 | U9: Instagram | V9: Completed | W9: 10588 | X9: 4 | Y9: 1331 | Z9: =W9+Y9 -> 11919
A10: 44958 | B10: =DAY(A10) -> 1 | C10: {=INDEX(Processing!$C$11:$C$22,MONTH('ALL ORDERS'!A10))} -> FEB | D10: =YEAR(A10) -> 2023 | E10: Joseph | F10: Installation of ceiling plinth | G10: 8600 | H10: 0 | I10: 0.05 | J10: =G10+H10 -> 8600 | K10: 44958 | L10: =DAY(K10) -> 1 | M10: {=INDEX(Processing!$W$6:$W$17,MONTH('ALL ORDERS'!K10))} -> February | N10: =YEAR(K10) -> 2023 | O10: 0.4375 | P10: Client 6 | Q10: Chikago | R10: 890 Maple Drive, Apt. 2A | S10: Jack | T10: (718) 555-3394 | U10: WhatsApp | V10: Completed | W10: 10812 | X10: 4 | Y10: 2111 | Z10: =W10+Y10 -> 12923
A11: 44959 | B11: =DAY(A11) -> 2 | C11: {=INDEX(Processing!$C$11:$C$22,MONTH('ALL ORDERS'!A11))} -> FEB | D11: =YEAR(A11) -> 2023 | E11: Jacob | F11: Laying solid boards | G11: 10000 | H11: 0 | J11: =G11+H11 -> 10000 | K11: 44959 | L11: =DAY(K11) -> 2 | M11: {=INDEX(Processing!$W$6:$W$17,MONTH('ALL ORDERS'!K11))} -> February | N11: =YEAR(K11) -> 2023 | O11: 0.41666667 | P11: Client 7 | Q11: Chikago | R11: 345 Cedar Court, Suite 6E | S11: William | T11: (646) 555-6727 | U11: Facebook | V11: Completed | W11: 4615 | X11: 4 | Y11: 785 | Z11: =W11+Y11 -> 5400
A12: 44985 | B12: =DAY(A12) -> 28 | C12: {=INDEX(Processing!$C$11:$C$22,MONTH('ALL ORDERS'!A12))} -> FEB | D12: =YEAR(A12) -> 2023 | E12: Charlotte | F12: Laying solid boards | G12: 0 | H12: 14900 | J12: =G12+H12 -> 14900 | K12: 44985 | L12: =DAY(K12) -> 28 | M12: {=INDEX(Processing!$W$6:$W$17,MONTH('ALL ORDERS'!K12))} -> February | N12: =YEAR(K12) -> 2023 | O12: 0.45833333 | P12: Client 8 | Q12: Chikago | R12: 346 Cedar Court, Suite 6E | S12: James | T12: (646) 555-6728 | U12: Facebook | V12: Completed | W12: 5454 | X12: 5 | Y12: 957 | Z12: =W12+Y12 -> 6411
A13: 44960 | B13: =DAY(A13) -> 3 | C13: {=INDEX(Processing!$C$11:$C$22,MONTH('ALL ORDERS'!A13))} -> FEB | D13: =YEAR(A13) -> 2023 | E13: Liam | F13: Installation of ceiling plinth | G13: 10300 | H13: 0 | J13: =G13+H13 -> 10300 | K13: 44960 | L13: =DAY(K13) -> 3 | M13: {=INDEX(Processing!$W$6:$W$17,MONTH('ALL ORDERS'!K13))} -> February | N13: =YEAR(K13) -> 2023 | O13: 0.5 | P13: Client 8 | Q13: New York | R13: 678 Spruce Lane, Apt. 1F | S13: Oliver | T13: (212) 555-9814 | U13: Reddit | V13: Completed | W13: 11688 | X13: 4 | Y13: 1216 | Z13: =W13+Y13 -> 12904
A14: 44961 | B14: =DAY(A14) -> 4 | C14: {=INDEX(Processing!$C$11:$C$22,MONTH('ALL ORDERS'!A14))} -> FEB | D14: =YEAR(A14) -> 2023 | E14: Isabella | F14: Installation of ceiling plinth | G14: 10300 | H14: 0 | J14: =G14+H14 -> 10300 | K14: 44961 | L14: =DAY(K14) -> 4 | M14: {=INDEX(Processing!$W$6:$W$17,MONTH('ALL ORDERS'!K14))} -> February | N14: =YEAR(K14) -> 2023 | O14: 0.54166667 | P14: Client 9 | Q14: New York | R14: 679 Spruce Lane, Apt. 1F | S14: Lucas | T14: (212) 555-9815 | U14: Instagram | V14: Completed | W14: 6749 | X14: 5 | Y14: 1165 | Z14: =W14+Y14 -> 7914
A15: 44986 | B15: =DAY(A15) -> 1 | C15: {=INDEX(Processing!$C$11:$C$22,MONTH('ALL ORDERS'!A15))} -> MAR | D15: =YEAR(A15) -> 2023 | E15: Isabella | F15: Cutting and installation of additional corners | G15: 13000 | H15: 0 | J15: =G15+H15 -> 13000 | K15: 44986 | L15: =DAY(K15) -> 1 | M15: {=INDEX(Processing!$W$6:$W$17,MONTH('ALL ORDERS'!K15))} -> March | N15: =YEAR(K15) -> 2023 | O15: 0.66666667 | P15: Client 9 | Q15: Chikago | R15: 1234 Redwood Road, Unit 5G | S15: Sofia | T15: (917) 555-7828 | U15: Instagram | V15: Completed | W15: 9627 | X15: 4 | Y15: 2721 | Z15: =W15+Y15 -> 12348
A16: 44987 | B16: =DAY(A16) -> 2 | C16: {=INDEX(Processing!$C$11:$C$22,MONTH('ALL ORDERS'!A16))} -> MAR | D16: =YEAR(A16) -> 2023 | E16: Charlotte | F16: Laying parquet boards on a substrate | G16: 10000 | H16: 0 | J16: =G16+H16 -> 10000 | K16: 44987 | L16: =DAY(K16) -> 2 | M16: {=INDEX(Processing!$W$6:$W$17,MONTH('ALL ORDERS'!K16))} -> March | N16: =YEAR(K16) -> 2023 | O16: 0.4375 | P16: Client 10 | Q16: Chikago | R16: 5678 Juniper Street, Apt. 9H | S16: Oliver | T16: (718) 555-2283 | U16: Reddit | V16: Completed | W16: 5190 | X16: 4 | Y16: 783 | Z16: =W16+Y16 -> 5973
A17: 44988 | B17: =DAY(A17) -> 3 | C17: {=INDEX(Processing!$C$11:$C$22,MONTH('ALL ORDERS'!A17))} -> MAR | D17: =YEAR(A17) -> 2023 | E17: Joseph | F17: Dismantling the balcony block | G17: 2500 | H17: 10000 | I17: 0.1 | J17: =G17+H17 -> 12500 | K17: 44988 | L17: =DAY(K17) -> 3 | M17: {=INDEX(Processing!$W$6:$W$17,MONTH('ALL ORDERS'!K17))} -> March | N17: =YEAR(K17) -> 2023 | O17: 0.4375 | P17: Client 11 | Q17: Chikago | R17: 987 Aspen Avenue, Suite 10I | S17: Lucas | T17: 60900888990 | U17: Facebook | V17: Completed | W17: 9051 | X17: 4 | Y17: 1326 | Z17: =W17+Y17 -> 10377
A18: 44989 | B18: =DAY(A18) -> 4 | C18: {=INDEX(Processing!$C$11:$C$22,MONTH('ALL ORDERS'!A18))} -> MAR | D18: =YEAR(A18) -> 2023 | E18: Jacob | F18: Removing the front door | G18: 0 | H18: 6500 | J18: =G18+H18 -> 6500 | K18: 44989 | L18: =DAY(K18) -> 4 | M18: {=INDEX(Processing!$W$6:$W$17,MONTH('ALL ORDERS'!K18))} -> March | N18: =YEAR(K18) -> 2023 | O18: 0.41666667 | P18: Client 12 | Q18: New York | R18: 654 Pinecone Lane, Unit 11J | S18: Sofia | T18: (212) 555-1173 | U18: Reddit | V18: Completed | W18: 12438 | X18: 4 | Y18: 931 | Z18: =W18+Y18 -> 13369
A19: 44990 | B19: =DAY(A19) -> 5 | C19: {=INDEX(Processing!$C$11:$C$22,MONTH('ALL ORDERS'!A19))} -> MAR | D19: =YEAR(A19) -> 2023 | E19: Isabella | F19: Laying solid boards | G19: 2000 | H19: 0 | J19: =G19+H19 -> 2000 | K19: 44990 | L19: =DAY(K19) -> 5 | M19: {=INDEX(Processing!$W$6:$W$17,MONTH('ALL ORDERS'!K19))} -> March | N19: =YEAR(K19) -> 2023 | O19: 0.45833333 | P19: Client 12 | Q19: Chikago | R19: 320 Acorn Drive, Apt. 12K | S19: Jack | T19: (917) 555-5616 | U19: Reddit | V19: Completed | W19: 8956 | X19: 4 | Y19: 1414 | Z19: =W19+Y19 -> 10370
A20: 45016 | B20: =DAY(A20) -> 31 | C20: {=INDEX(Processing!$C$11:$C$22,MONTH('ALL ORDERS'!A20))} -> MAR | D20: =YEAR(A20) -> 2023 | E20: Liam | F20: Laying solid boards | G20: 12200 | H20: 0 | J20: =G20+H20 -> 12200 | K20: 45016 | L20: =DAY(K20) -> 31 | M20: {=INDEX(Processing!$W$6:$W$17,MONTH('ALL ORDERS'!K20))} -> March | N20: =YEAR(K20) -> 2023 | O20: 0.5 | P20: Client 13 | Q20: Chikago | R20: 321 Acorn Drive, Apt. 12K | S20: William | T20: (917) 555-5617 | U20: Instagram | V20: Completed | W20: 3530 | X20: 5 | Y20: 1323 | Z20: =W20+Y20 -> 4853
A21: 45017 | B21: =DAY(A21) -> 1 | C21: {=INDEX(Processing!$C$11:$C$22,MONTH('ALL ORDERS'!A21))} -> APR | D21: =YEAR(A21) -> 2023 | E21: Charlotte | F21: Installation of ceiling plinth | G21: 0 | H21: 6540 | J21: =G21+H21 -> 6540 | K21: 45017 | L21: =DAY(K21) -> 1 | M21: {=INDEX(Processing!$W$6:$W$17,MONTH('ALL ORDERS'!K21))} -> April | N21: =YEAR(K21) -> 2023 | O21: 0.66666667 | P21: Client 14 | Q21: Miami | R21: 876 Sequoia Road, Suite 13L | S21: James | T21: (718) 555-8704 | U21: Instagram | V21: Completed | W21: 8029 | X21: 5 | Y21: 1329 | Z21: =W21+Y21 -> 9358
A22: 45018 | B22: =DAY(A22) -> 2 | C22: {=INDEX(Processing!$C$11:$C$22,MONTH('ALL ORDERS'!A22))} -> APR | D22: =YEAR(A22) -> 2023 | E22: Joseph | F22: Removing the shower tray | G22: 0 | H22: 4550 | I22: 0.15 | J22: =G22+H22 -> 4550 | K22: 45018 | L22: =DAY(K22) -> 2 | M22: {=INDEX(Processing!$W$6:$W$17,MONTH('ALL ORDERS'!K22))} -> April | N22: =YEAR(K22) -> 2023 | O22: 0.4375 | P22: Client 15 | Q22: Chikago | R22: 543 Willowbrook Lane, Apt. 14M | S22: Oliver | T22: (646) 555-2284 | U22: Instagram | V22: Completed | W22: 6134 | X22: 5 | Y22: 1438 | Z22: =W22+Y22 -> 7572
A23: 45038 | B23: =DAY(A23) -> 22 | C23: {=INDEX(Processing!$C$11:$C$22,MONTH('ALL ORDERS'!A23))} -> APR | D23: =YEAR(A23) -> 2023 | E23: Jacob | F23: Removing the shower tray | G23: 0 | H23: 17710 | J23: =G23+H23 -> 17710 | K23: 45038 | L23: =DAY(K23) -> 22 | M23: {=INDEX(Processing!$W$6:$W$17,MONTH('ALL ORDERS'!K23))} -> April | N23: =YEAR(K23) -> 2023 | O23: 0.47916667 | P23: Client 16 | Q23: Chikago | R23: 544 Willowbrook Lane, Apt. 14M | S23: Lucas | T23: (646) 555-2285 | U23: Facebook | V23: Completed | W23: 4243 | X23: 5 | Y23: 597 | Z23: =W23+Y23 -> 4840
A24: 45039 | B24: =DAY(A24) -> 23 | C24: {=INDEX(Processing!$C$11:$C$22,MONTH('ALL ORDERS'!A24))} -> APR | D24: =YEAR(A24) -> 2023 | E24: Isabella | F24: Removing the shower tray | G24: 10000 | H24: 0 | J24: =G24+H24 -> 10000 | K24: 45039 | L24: =DAY(K24) -> 23 | M24: {=INDEX(Processing!$W$6:$W$17,MONTH('ALL ORDERS'!K24))} -> April | N24: =YEAR(K24) -> 2023 | O24: 0.52083333 | P24: Client 17 | Q24: Chikago | R24: 545 Willowbrook Lane, Apt. 14M | S24: Sofia | T24: (646) 555-2286 | U24: Reddit | V24: Completed | W24: 10772 | X24: 6 | Y24: 1394 | Z24: =W24+Y24 -> 12166
A25: 45040 | B25: =DAY(A25) -> 24 | C25: {=INDEX(Processing!$C$11:$C$22,MONTH('ALL ORDERS'!A25))} -> APR | D25: =YEAR(A25) -> 2023 | E25: Liam | F25: Removing the shower tray | G25: 0 | H25: 10000 | J25: =G25+H25 -> 10000 | K25: 45040 | L25: =DAY(K25) -> 24 | M25: {=INDEX(Processing!$W$6:$W$17,MONTH('ALL ORDERS'!K25))} -> April | N25: =YEAR(K25) -> 2023 | O25: 0.5625 | P25: Client 18 | Q25: Chikago | R25: 546 Willowbrook Lane, Apt. 14M | S25: Jack | T25: (646) 555-2287 | U25: WhatsApp | V25: Completed | W25: 10784 | X25: 7 | Y25: 1259 | Z25: =W25+Y25 -> 12043
A26: 45047 | B26: =DAY(A26) -> 1 | C26: {=INDEX(Processing!$C$11:$C$22,MONTH('ALL ORDERS'!A26))} -> MAY | D26: =YEAR(A26) -> 2023 | E26: Charlotte | F26: Dismantling the balcony block | G26: 0 | H26: 8060 | I26: 0.05 | J26: =G26+H26 -> 8060 | K26: 45047 | L26: =DAY(K26) -> 1 | M26: {=INDEX(Processing!$W$6:$W$17,MONTH('ALL ORDERS'!K26))} -> May | N26: =YEAR(K26) -> 2023 | O26: 0.41666667 | P26: Client 16 | Q26: Chikago | R26: 210 Magnolia Street, Unit 15N | S26: William | T26: (212) 555-7829 | U26: Facebook | V26: Completed | W26: 9985 | X26: 5 | Y26: 2222 | Z26: =W26+Y26 -> 12207
A27: 45048 | B27: =DAY(A27) -> 2 | C27: {=INDEX(Processing!$C$11:$C$22,MONTH('ALL ORDERS'!A27))} -> MAY | D27: =YEAR(A27) -> 2023 | E27: Joseph | F27: Laying parquet boards with glue | G27: 0 | H27: 2450 | J27: =G27+H27 -> 2450 | K27: 45048 | L27: =DAY(K27) -> 2 | M27: {=INDEX(Processing!$W$6:$W$17,MONTH('ALL ORDERS'!K27))} -> May | N27: =YEAR(K27) -> 2023 | O27: 0.5 | P27: Client 17 | Q27: Chikago | R27: 8765 Sycamore Court, Suite 16O | S27: James | T27: (917) 555-4260 | U27: Reddit | V27: Completed | W27: 7141 | X27: 5 | Y27: 1724 | Z27: =W27+Y27 -> 8865
A28: 45049 | B28: =DAY(A28) -> 3 | C28: {=INDEX(Processing!$C$11:$C$22,MONTH('ALL ORDERS'!A28))} -> MAY | D28: =YEAR(A28) -> 2023 | E28: Jacob | F28: Laying quartz vinyl tiles on a substrate | G28: 5000 | H28: 890 | J28: =G28+H28 -> 5890 | K28: 45049 | L28: =DAY(K28) -> 3 | M28: {=INDEX(Processing!$W$6:$W$17,MONTH('ALL ORDERS'!K28))} -> May | N28: =YEAR(K28) -> 2023 | O28: 0.66666667 | P28: Client 18 | Q28: Chikago | R28: 4321 Cedarwood Drive, Apt. 17P | S28: Oliver | T28: (718) 555-3395 | U28: WhatsApp | V28: Completed | W28: 9079 | X28: 3 | Y28: 1824 | Z28: =W28+Y28 -> 10903
A29: 45050 | B29: =DAY(A29) -> 4 | C29: {=INDEX(Processing!$C$11:$C$22,MONTH('ALL ORDERS'!A29))} -> MAY | D29: =YEAR(A29) -> 2023 | E29: Isabella | F29: Laying quartz vinyl tiles on a substrate | G29: 5000 | H29: 0 | J29: =G29+H29 -> 5000 | K29: 45050 | L29: =DAY(K29) -> 4 | M29: {=INDEX(Processing!$W$6:$W$17,MONTH('ALL ORDERS'!K29))} -> May | N29: =YEAR(K29) -> 2023 | O29: 0.70833333 | P29: Client 19 | Q29: Chikago | R29: 4322 Cedarwood Drive, Apt. 17P | S29: Lucas | T29: (718) 555-3396 | U29: WhatsApp | V29: Completed | W29: 7195 | X29: 4 | Y29: 1639 | Z29: =W29+Y29 -> 8834
A30: 45051 | B30: =DAY(A30) -> 5 | C30: {=INDEX(Processing!$C$11:$C$22,MONTH('ALL ORDERS'!A30))} -> MAY | D30: =YEAR(A30) -> 2023 | E30: Liam | F30: Laying quartz vinyl tiles on a substrate | G30: 10000 | H30: 0 | J30: =G30+H30 -> 10000 | K30: 45051 | L30: =DAY(K30) -> 5 | M30: {=INDEX(Processing!$W$6:$W$17,MONTH('ALL ORDERS'!K30))} -> May | N30: =YEAR(K30) -> 2023 | O30: 0.75 | P30: Client 20 | Q30: Chikago | R30: 4323 Cedarwood Drive, Apt. 17P | S30: Sofia | T30: (718) 555-3397 | U30: WhatsApp | V30: Completed | W30: 1645 | X30: 5 | Y30: 1250 | Z30: =W30+Y30 -> 2895
A31: 45078 | B31: =DAY(A31) -> 1 | C31: {=INDEX(Processing!$C$11:$C$22,MONTH('ALL ORDERS'!A31))} -> JUN | D31: =YEAR(A31) -> 2023 | E31: Charlotte | F31: Laying parquet boards on a substrate | G31: 3200 | H31: 0 | J31: =G31+H31 -> 3200 | K31: 45078 | L31: =DAY(K31) -> 1 | M31: {=INDEX(Processing!$W$6:$W$17,MONTH('ALL ORDERS'!K31))} -> June | N31: =YEAR(K31) -> 2023 | O31: 0.4375 | P31: Client 19 | Q31: Chikago | R31: 123 Elm Street, Unit 18Q | S31: Jack | T31: (646) 555-6728 | U31: Facebook | V31: Completed | W31: 5595 | X31: 3 | Y31: 1703 | Z31: =W31+Y31 -> 7298
A32: 45079 | B32: =DAY(A32) -> 2 | C32: {=INDEX(Processing!$C$11:$C$22,MONTH('ALL ORDERS'!A32))} -> JUN | D32: =YEAR(A32) -> 2023 | E32: Joseph | F32: Cutting and installation of additional corners | G32: 5000 | H32: 0 | J32: =G32+H32 -> 5000 | K32: 45079 | L32: =DAY(K32) -> 2 | M32: {=INDEX(Processing!$W$6:$W$17,MONTH('ALL ORDERS'!K32))} -> June | N32: =YEAR(K32) -> 2023 | O32: 0.47916667 | P32: Client 20 | Q32: Chikago | R32: 124 Elm Street, Unit 18Q | S32: William | T32: (646) 555-6729 | U32: WhatsApp | V32: Completed | W32: 9709 | X32: 4 | Y32: 1570 | Z32: =W32+Y32 -> 11279
A33: 45080 | B33: =DAY(A33) -> 3 | C33: {=INDEX(Processing!$C$11:$C$22,MONTH('ALL ORDERS'!A33))} -> JUN | D33: =YEAR(A33) -> 2023 | E33: Jacob | F33: Laying parquet boards on a substrate | G33: 0 | H33: 5000 | J33: =G33+H33 -> 5000 | K33: 45080 | L33: =DAY(K33) -> 3 | M33: {=INDEX(Processing!$W$6:$W$17,MONTH('ALL ORDERS'!K33))} -> June | N33: =YEAR(K33) -> 2023 | O33: 0.52083333 | P33: Client 21 | Q33: Chikago | R33: 125 Elm Street, Unit 18Q | S33: James | T33: (646) 555-6730 | U33: Facebook | V33: Completed | W33: 10307 | X33: 5 | Y33: 1438 | Z33: =W33+Y33 -> 11745
A34: 45081 | B34: =DAY(A34) -> 4 | C34: {=INDEX(Processing!$C$11:$C$22,MONTH('ALL ORDERS'!A34))} -> JUN | D34: =YEAR(A34) -> 2023 | E34: Isabella | F34: Removing the shower tray | G34: 0 | H34: 5000 | J34: =G34+H34 -> 5000 | K34: 45081 | L34: =DAY(K34) -> 4 | M34: {=INDEX(Processing!$W$6:$W$17,MONTH('ALL ORDERS'!K34))} -> June | N34: =YEAR(K34) -> 2023 | O34: 0.5625 | P34: Client 22 | Q34: Chikago | R34: 126 Elm Street, Unit 18Q | S34: Oliver | T34: (646) 555-6731 | U34: Reddit | V34: Completed | W34: 6557 | X34: 6 | Y34: 1891 | Z34: =W34+Y34 -> 8448
A35: 45082 | B35: =DAY(A35) -> 5 | C35: {=INDEX(Processing!$C$11:$C$22,MONTH('ALL ORDERS'!A35))} -> JUN | D35: =YEAR(A35) -> 2023 | E35: Liam | F35: Laying parquet boards on a substrate | G35: 5000 | H35: 0 | J35: =G35+H35 -> 5000 | K35: 45082 | L35: =DAY(K35) -> 5 | M35: {=INDEX(Processing!$W$6:$W$17,MONTH('ALL ORDERS'!K35))} -> June | N35: =YEAR(K35) -> 2023 | O35: 0.60416667 | P35: Client 23 | Q35: Chikago | R35: 127 Elm Street, Unit 18Q | S35: Lucas | T35: (646) 555-6732 | U35: Facebook | V35: Completed | W35: 12381 | X35: 7 | Y35: 1501 | Z35: =W35+Y35 -> 13882
A36: 45108 | B36: =DAY(A36) -> 1 | C36: {=INDEX(Processing!$C$11:$C$22,MONTH('ALL ORDERS'!A36))} -> JUL | D36: =YEAR(A36) -> 2023 | E36: Charlotte | F36: Laying solid boards | G36: 8800 | H36: 0 | J36: =G36+H36 -> 8800 | K36: 45108 | L36: =DAY(K36) -> 1 | M36: {=INDEX(Processing!$W$6:$W$17,MONTH('ALL ORDERS'!K36))} -> July | N36: =YEAR(K36) -> 2023 | O36: 0.4375 | P36: Client 20 | Q36: Chikago | R36: 456 Birch Avenue, Suite 19R | S36: Sofia | T36: (212) 555-9815 | U36: Reddit | V36: Completed | W36: 9211 | X36: 3 | Y36: 1316 | Z36: =W36+Y36 -> 10527
A37: 45109 | B37: =DAY(A37) -> 2 | C37: {=INDEX(Processing!$C$11:$C$22,MONTH('ALL ORDERS'!A37))} -> JUL | D37: =YEAR(A37) -> 2023 | E37: Joseph | F37: Installation of ceiling plinth | G37: 4500 | H37: 0 | J37: =G37+H37 -> 4500 | K37: 45109 | L37: =DAY(K37) -> 2 | M37: {=INDEX(Processing!$W$6:$W$17,MONTH('ALL ORDERS'!K37))} -> July | N37: =YEAR(K37) -> 2023 | O37: 0.41666667 | P37: Client 21 | Q37: New York | R37: 789 Oak Lane, Apt. 20S | S37: Jack | T37: (917) 555-7829 | U37: Reddit | V37: Completed | W37: 8933 | X37: 3 | Y37: 1416 | Z37: =W37+Y37 -> 10349
A38: 45110 | B38: =DAY(A38) -> 3 | C38: {=INDEX(Processing!$C$11:$C$22,MONTH('ALL ORDERS'!A38))} -> JUL | D38: =YEAR(A38) -> 2023 | E38: Jacob | F38: Laying solid boards | G38: 6100 | H38: 0 | I38: 0.05 | J38: =G38+H38 -> 6100 | K38: 45110 | L38: =DAY(K38) -> 3 | M38: {=INDEX(Processing!$W$6:$W$17,MONTH('ALL ORDERS'!K38))} -> July | N38: =YEAR(K38) -> 2023 | O38: 0.5 | P38: Client 22 | Q38: Chikago | R38: 234 Maple Road, Unit 21T | S38: William | T38: (718) 555-2284 | U38: Facebook | V38: Completed | W38: 5412 | X38: 3 | Y38: 919 | Z38: =W38+Y38 -> 6331
A39: 45111 | B39: =DAY(A39) -> 4 | C39: {=INDEX(Processing!$C$11:$C$22,MONTH('ALL ORDERS'!A39))} -> JUL | D39: =YEAR(A39) -> 2023 | E39: Isabella | F39: Installation of ceiling plinth | G39: 600 | H39: 10000 | J39: =G39+H39 -> 10600 | K39: 45111 | L39: =DAY(K39) -> 4 | M39: {=INDEX(Processing!$W$6:$W$17,MONTH('ALL ORDERS'!K39))} -> July | N39: =YEAR(K39) -> 2023 | O39: 0.66666667 | P39: Client 23 | Q39: Chikago | R39: 567 Pine Street, Suite 22U | S39: James | T39: 59900888990 | U39: Reddit | V39: Completed | W39: 8575 | X39: 2 | Y39: 1881 | Z39: =W39+Y39 -> 10456
A40: 45138 | B40: =DAY(A40) -> 31 | C40: {=INDEX(Processing!$C$11:$C$22,MONTH('ALL ORDERS'!A40))} -> JUL | D40: =YEAR(A40) -> 2023 | E40: Liam | F40: Installation of ceiling plinth | G40: 800 | H40: 4000 | I40: 0.05 | J40: =G40+H40 -> 4800 | K40: 45138 | L40: =DAY(K40) -> 31 | M40: {=INDEX(Processing!$W$6:$W$17,MONTH('ALL ORDERS'!K40))} -> July | N40: =YEAR(K40) -> 2023 | O40: 0.70833333 | P40: Client 24 | Q40: Chikago | R40: 568 Pine Street, Suite 22U | S40: Oliver | T40: 59900888991 | U40: WhatsApp | V40: Completed | W40: 2526 | X40: 3 | Y40: 1747 | Z40: =W40+Y40 -> 4273
A41: 45139 | B41: =DAY(A41) -> 1 | C41: {=INDEX(Processing!$C$11:$C$22,MONTH('ALL ORDERS'!A41))} -> AUG | D41: =YEAR(A41) -> 2023 | E41: Charlotte | F41: Cutting and installation of additional corners | G41: 5000 | H41: 0 | J41: =G41+H41 -> 5000 | K41: 45139 | L41: =DAY(K41) -> 1 | M41: {=INDEX(Processing!$W$6:$W$17,MONTH('ALL ORDERS'!K41))} -> August | N41: =YEAR(K41) -> 2023 | O41: 0.4375 | P41: Client 24 | Q41: Chikago | R41: 890 Willow Drive, Apt. 23V | S41: Lucas | T41: (212) 555-1174 | U41: WhatsApp | V41: Completed | W41: 7602 | X41: 3 | Y41: 2543 | Z41: =W41+Y41 -> 10145
A42: 45146 | B42: =DAY(A42) -> 8 | C42: {=INDEX(Processing!$C$11:$C$22,MONTH('ALL ORDERS'!A42))} -> AUG | D42: =YEAR(A42) -> 2023 | E42: Joseph | F42: Removing the front door | G42: 17500 | H42: 0 | J42: =G42+H42 -> 17500 | K42: 45146 | L42: =DAY(K42) -> 8 | M42: {=INDEX(Processing!$W$6:$W$17,MONTH('ALL ORDERS'!K42))} -> August | N42: =YEAR(K42) -> 2023 | O42: 0.47916667 | P42: Client 25 | Q42: Chikago | R42: 891 Willow Drive, Apt. 23V | S42: Sofia | T42: (212) 555-1175 | U42: WhatsApp | V42: Completed | W42: 8515 | X42: 4 | Y42: 1702 | Z42: =W42+Y42 -> 10217
A43: 45147 | B43: =DAY(A43) -> 9 | C43: {=INDEX(Processing!$C$11:$C$22,MONTH('ALL ORDERS'!A43))} -> AUG | D43: =YEAR(A43) -> 2023 | E43: Jacob | F43: Cutting and installation of additional corners | G43: 15000 | H43: 0 | J43: =G43+H43 -> 15000 | K43: 45147 | L43: =DAY(K43) -> 9 | M43: {=INDEX(Processing!$W$6:$W$17,MONTH('ALL ORDERS'!K43))} -> August | N43: =YEAR(K43) -> 2023 | O43: 0.52083333 | P43: Client 26 | Q43: Chikago | R43: 892 Willow Drive, Apt. 23V | S43: Jack | T43: (212) 555-1176 | U43: Reddit | V43: Completed | W43: 7694 | X43: 5 | Y43: 1811 | Z43: =W43+Y43 -> 9505
A44: 45148 | B44: =DAY(A44) -> 10 | C44: {=INDEX(Processing!$C$11:$C$22,MONTH('ALL ORDERS'!A44))} -> AUG | D44: =YEAR(A44) -> 2023 | E44: Isabella | F44: Dismantling the balcony block | G44: 0 | H44: 14000 | J44: =G44+H44 -> 14000 | K44: 45148 | L44: =DAY(K44) -> 10 | M44: {=INDEX(Processing!$W$6:$W$17,MONTH('ALL ORDERS'!K44))} -> August | N44: =YEAR(K44) -> 2023 | O44: 0.5625 | P44: Client 27 | Q44: Chikago | R44: 893 Willow Drive, Apt. 23V | S44: William | T44: (212) 555-1177 | U44: Instagram | V44: Completed | W44: 10465 | X44: 6 | Y44: 1817 | Z44: =W44+Y44 -> 12282
A45: 45149 | B45: =DAY(A45) -> 11 | C45: {=INDEX(Processing!$C$11:$C$22,MONTH('ALL ORDERS'!A45))} -> AUG | D45: =YEAR(A45) -> 2023 | E45: Liam | F45: Cutting and installation of additional corners | G45: 16000 | H45: 0 | J45: =G45+H45 -> 16000 | K45: 45149 | L45: =DAY(K45) -> 11 | M45: {=INDEX(Processing!$W$6:$W$17,MONTH('ALL ORDERS'!K45))} -> August | N45: =YEAR(K45) -> 2023 | O45: 0.60416667 | P45: Client 28 | Q45: Chikago | R45: 894 Willow Drive, Apt. 23V | S45: James | T45: (212) 555-1178 | U45: Instagram | V45: Completed | W45: 8589 | X45: 7 | Y45: 1726 | Z45: =W45+Y45 -> 10315
A46: 45170 | B46: =DAY(A46) -> 1 | C46: {=INDEX(Processing!$C$11:$C$22,MONTH('ALL ORDERS'!A46))} -> SEP | D46: =YEAR(A46) -> 2023 | E46: Charlotte | F46: Installation of ceiling plinth | G46: 25000 | H46: 0 | J46: =G46+H46 -> 25000 | K46: 45170 | L46: =DAY(K46) -> 1 | M46: {=INDEX(Processing!$W$6:$W$17,MONTH('ALL ORDERS'!K46))} -> September | N46: =YEAR(K46) -> 2023 | O46: 0.4375 | P46: Client 25 | Q46: Dallas | R46: 345 Redwood Lane, Unit 24W | S46: Oliver | T46: (917) 555-5618 | U46: Instagram | V46: Completed | W46: 2780 | X46: 4 | Y46: 2209 | Z46: =W46+Y46 -> 4989
A47: 45189 | B47: =DAY(A47) -> 20 | C47: {=INDEX(Processing!$C$11:$C$22,MONTH('ALL ORDERS'!A47))} -> SEP | D47: =YEAR(A47) -> 2023 | E47: Joseph | F47: Laying parquet boards on a substrate | G47: 20000 | H47: 600 | J47: =G47+H47 -> 20600 | K47: 45189 | L47: =DAY(K47) -> 20 | M47: {=INDEX(Processing!$W$6:$W$17,MONTH('ALL ORDERS'!K47))} -> September | N47: =YEAR(K47) -> 2023 | O47: 0.47916667 | P47: Client 26 | Q47: Dallas | R47: 346 Redwood Lane, Unit 24W | S47: Lucas | T47: (917) 555-5619 | U47: Reddit | V47: Completed | W47: 10134 | X47: 5 | Y47: 1814 | Z47: =W47+Y47 -> 11948
A48: 45190 | B48: =DAY(A48) -> 21 | C48: {=INDEX(Processing!$C$11:$C$22,MONTH('ALL ORDERS'!A48))} -> SEP | D48: =YEAR(A48) -> 2023 | E48: Jacob | F48: Dismantling the balcony block | G48: 16400 | H48: 0 | J48: =G48+H48 -> 16400 | K48: 45190 | L48: =DAY(K48) -> 21 | M48: {=INDEX(Processing!$W$6:$W$17,MONTH('ALL ORDERS'!K48))} -> September | N48: =YEAR(K48) -> 2023 | O48: 0.47916667 | P48: Client 26 | Q48: Dallas | R48: 346 Redwood Lane, Unit 24W | S48: Sofia | T48: (917) 555-5619 | U48: Reddit | V48: Completed | W48: 6743 | X48: 5 | Y48: 2358 | Z48: =W48+Y48 -> 9101
A49: 45191 | B49: =DAY(A49) -> 22 | C49: {=INDEX(Processing!$C$11:$C$22,MONTH('ALL ORDERS'!A49))} -> SEP | D49: =YEAR(A49) -> 2023 | E49: Isabella | F49: Laying parquet boards on a substrate | G49: 0 | H49: 10000 | J49: =G49+H49 -> 10000 | K49: 45191 | L49: =DAY(K49) -> 22 | M49: {=INDEX(Processing!$W$6:$W$17,MONTH('ALL ORDERS'!K49))} -> September | N49: =YEAR(K49) -> 2023 | O49: 0.52083333 | P49: Client 27 | Q49: Dallas | R49: 347 Redwood Lane, Unit 24W | S49: Jack | T49: (917) 555-5620 | U49: WhatsApp | V49: Completed | W49: 8349 | X49: 6 | Y49: 419 | Z49: =W49+Y49 -> 8768
A50: 45192 | B50: =DAY(A50) -> 23 | C50: {=INDEX(Processing!$C$11:$C$22,MONTH('ALL ORDERS'!A50))} -> SEP | D50: =YEAR(A50) -> 2023 | E50: Liam | F50: Laying parquet boards on a substrate | G50: 0 | H50: 10000 | J50: =G50+H50 -> 10000 | K50: 45192 | L50: =DAY(K50) -> 23 | M50: {=INDEX(Processing!$W$6:$W$17,MONTH('ALL ORDERS'!K50))} -> September | N50: =YEAR(K50) -> 2023 | O50: 0.5625 | P50: Client 28 | Q50: Dallas | R50: 348 Redwood Lane, Unit 24W | S50: William | T50: (917) 555-5621 | U50: WhatsApp | V50: Completed | W50: 5970 | X50: 7 | Y50: 1975 | Z50: =W50+Y50 -> 7945
A51: 45204 | B51: =DAY(A51) -> 5 | C51: {=INDEX(Processing!$C$11:$C$22,MONTH('ALL ORDERS'!A51))} -> OCT | D51: =YEAR(A51) -> 2023 | E51: Charlotte | F51: Dismantling the balcony block | G51: 15600 | H51: 0 | I51: 0.1 | J51: =G51+H51 -> 15600 | K51: 45204 | L51: =DAY(K51) -> 5 | M51: {=INDEX(Processing!$W$6:$W$17,MONTH('ALL ORDERS'!K51))} -> October | N51: =YEAR(K51) -> 2023 | O51: 0.41666667 | P51: Client 26 | Q51: New York | R51: 678 Spruce Street, Suite 25X | S51: James | T51: (718) 555-8705 | U51: YouTube | V51: Completed | W51: 13669 | X51: 4 | Y51: 1925 | Z51: =W51+Y51 -> 15594
A52: 45205 | B52: =DAY(A52) -> 6 | C52: {=INDEX(Processing!$C$11:$C$22,MONTH('ALL ORDERS'!A52))} -> OCT | D52: =YEAR(A52) -> 2023 | E52: Joseph | F52: Dismantling the balcony block | G52: 24800 | H52: 0 | I52: 0.15 | J52: =G52+H52 -> 24800 | K52: 45205 | L52: =DAY(K52) -> 6 | M52: {=INDEX(Processing!$W$6:$W$17,MONTH('ALL ORDERS'!K52))} -> October | N52: =YEAR(K52) -> 2023 | O52: 0.45833333 | P52: Client 27 | Q52: New York | R52: 679 Spruce Street, Suite 25X | S52: Oliver | T52: (718) 555-8706 | U52: Facebook | V52: Completed | W52: 7635 | X52: 5 | Y52: 2183 | Z52: =W52+Y52 -> 9818
A53: 45206 | B53: =DAY(A53) -> 7 | C53: {=INDEX(Processing!$C$11:$C$22,MONTH('ALL ORDERS'!A53))} -> OCT | D53: =YEAR(A53) -> 2023 | E53: Jacob | F53: Installation of ceiling plinth | G53: 0 | H53: 10000 | I53: 0.15 | J53: =G53+H53 -> 10000 | K53: 45206 | L53: =DAY(K53) -> 7 | M53: {=INDEX(Processing!$W$6:$W$17,MONTH('ALL ORDERS'!K53))} -> October | N53: =YEAR(K53) -> 2023 | O53: 0.5 | P53: Client 28 | Q53: New York | R53: 680 Spruce Street, Suite 25X | S53: Lucas | T53: (718) 555-8707 | U53: WhatsApp | V53: Completed | W53: 6022 | X53: 6 | Y53: 2356 | Z53: =W53+Y53 -> 8378
A54: 45207 | B54: =DAY(A54) -> 8 | C54: {=INDEX(Processing!$C$11:$C$22,MONTH('ALL ORDERS'!A54))} -> OCT | D54: =YEAR(A54) -> 2023 | E54: Isabella | F54: Laying solid boards | G54: 10000 | H54: 0 | I54: 0.15 | J54: =G54+H54 -> 10000 | K54: 45207 | L54: =DAY(K54) -> 8 | M54: {=INDEX(Processing!$W$6:$W$17,MONTH('ALL ORDERS'!K54))} -> October | N54: =YEAR(K54) -> 2023 | O54: 0.54166667 | P54: Client 29 | Q54: New York | R54: 681 Spruce Street, Suite 25X | S54: Sofia | T54: (718) 555-8708 | U54: Facebook | V54: Completed | W54: 7460 | X54: 7 | Y54: 1029 | Z54: =W54+Y54 -> 8489
A55: 45208 | B55: =DAY(A55) -> 9 | C55: {=INDEX(Processing!$C$11:$C$22,MONTH('ALL ORDERS'!A55))} -> OCT | D55: =YEAR(A55) -> 2023 | E55: Liam | F55: Dismantling the balcony block | G55: 0 | H55: 10000 | I55: 0.15 | J55: =G55+H55 -> 10000 | K55: 45208 | L55: =DAY(K55) -> 9 | M55: {=INDEX(Processing!$W$6:$W$17,MONTH('ALL ORDERS'!K55))} -> October | N55: =YEAR(K55) -> 2023 | O55: 0.58333333 | P55: Client 30 | Q55: New York | R55: 682 Spruce Street, Suite 25X | S55: Jack | T55: (718) 555-8709 | U55: Facebook | V55: Completed | W55: 7311 | X55: 8 | Y55: 1809 | Z55: =W55+Y55 -> 9120
A56: 45231 | B56: =DAY(A56) -> 1 | C56: {=INDEX(Processing!$C$11:$C$22,MONTH('ALL ORDERS'!A56))} -> NOV | D56: =YEAR(A56) -> 2023 | E56: Charlotte | F56: Removing the front door | G56: 5800 | H56: 0 | I56: 0.1 | J56: =G56+H56 -> 5800 | K56: 45231 | L56: =DAY(K56) -> 1 | M56: {=INDEX(Processing!$W$6:$W$17,MONTH('ALL ORDERS'!K56))} -> November | N56: =YEAR(K56) -> 2023 | O56: 0.5 | P56: Client 27 | Q56: Chikago | R56: 1234 Aspen Road, Apt. 26Y | S56: William | T56: (646) 555-2285 | U56: Reddit | V56: Completed | W56: 9475 | X56: 5 | Y56: 2219 | Z56: =W56+Y56 -> 11694
A57: 45232 | B57: =DAY(A57) -> 2 | C57: {=INDEX(Processing!$C$11:$C$22,MONTH('ALL ORDERS'!A57))} -> NOV | D57: =YEAR(A57) -> 2023 | E57: Joseph | F57: Laying solid boards | G57: 9000 | H57: 0 | J57: =G57+H57 -> 9000 | K57: 45232 | L57: =DAY(K57) -> 2 | M57: {=INDEX(Processing!$W$6:$W$17,MONTH('ALL ORDERS'!K57))} -> November | N57: =YEAR(K57) -> 2023 | O57: 0.66666667 | P57: Client 28 | Q57: Chikago | R57: 5678 Cedar Drive, Unit 27Z | S57: James | T57: (212) 555-7830 | U57: Reddit | V57: Completed | W57: 12793 | X57: 4 | Y57: 1257 | Z57: =W57+Y57 -> 14050
A58: 45233 | B58: =DAY(A58) -> 3 | C58: {=INDEX(Processing!$C$11:$C$22,MONTH('ALL ORDERS'!A58))} -> NOV | D58: =YEAR(A58) -> 2023 | E58: Jacob | F58: Installation of ceiling plinth | G58: 10000 | H58: 890 | J58: =G58+H58 -> 10890 | K58: 45233 | L58: =DAY(K58) -> 3 | M58: {=INDEX(Processing!$W$6:$W$17,MONTH('ALL ORDERS'!K58))} -> November | N58: =YEAR(K58) -> 2023 | O58: 0.4375 | P58: Client 29 | Q58: Chikago | R58: 987 Pinecone Avenue, Suite 28AA | S58: Oliver | T58: (917) 555-4261 | U58: Facebook | V58: Completed | W58: 7526 | X58: 3 | Y58: 1905 | Z58: =W58+Y58 -> 9431
A59: 45234 | B59: =DAY(A59) -> 4 | C59: {=INDEX(Processing!$C$11:$C$22,MONTH('ALL ORDERS'!A59))} -> NOV | D59: =YEAR(A59) -> 2023 | E59: Isabella | F59: Removing the shower tray | G59: 7000 | H59: 100 | J59: =G59+H59 -> 7100 | K59: 45234 | L59: =DAY(K59) -> 4 | M59: {=INDEX(Processing!$W$6:$W$17,MONTH('ALL ORDERS'!K59))} -> November | N59: =YEAR(K59) -> 2023 | O59: 0.66666667 | P59: Client 30 | Q59: New York | R59: 654 Magnolia Lane, Apt. 29BB | S59: Lucas | T59: (718) 555-3396 | U59: Reddit | V59: Completed | W59: 8890 | X59: 4 | Y59: 1068 | Z59: =W59+Y59 -> 9958
A60: 45260 | B60: =DAY(A60) -> 30 | C60: {=INDEX(Processing!$C$11:$C$22,MONTH('ALL ORDERS'!A60))} -> NOV | D60: =YEAR(A60) -> 2023 | E60: Liam | F60: Removing the shower tray | G60: 0 | H60: 21910 | J60: =G60+H60 -> 21910 | K60: 45260 | L60: =DAY(K60) -> 30 | M60: {=INDEX(Processing!$W$6:$W$17,MONTH('ALL ORDERS'!K60))} -> November | N60: =YEAR(K60) -> 2023 | O60: 0.70833333 | P60: Client 31 | Q60: New York | R60: 655 Magnolia Lane, Apt. 29BB | S60: Sofia | T60: (718) 555-3397 | U60: YouTube | V60: Completed | W60: 6470 | X60: 5 | Y60: 1673 | Z60: =W60+Y60 -> 8143
A61: 45261 | B61: =DAY(A61) -> 1 | C61: {=INDEX(Processing!$C$11:$C$22,MONTH('ALL ORDERS'!A61))} -> DEC | D61: =YEAR(A61) -> 2023 | E61: Isabella | F61: Dismantling the balcony block | G61: 0 | H61: 900 | I61: 0.15 | J61: =G61+H61 -> 900 | K61: 45261 | L61: =DAY(K61) -> 1 | M61: {=INDEX(Processing!$W$6:$W$17,MONTH('ALL ORDERS'!K61))} -> December | N61: =YEAR(K61) -> 2023 | O61: 0.41666667 | P61: Client 43 | Q61: Chikago | R61: 345 Spruce Street, Suite 42OO | S61: Jack | T61: (646) 555-6730 | U61: Instagram | V61: Completed | W61: 1420 | X61: 5 | Y61: 3000 | Z61: =W61-Y61 -> -1580
A62: 45261 | B62: =DAY(A62) -> 1 | C62: {=INDEX(Processing!$C$11:$C$22,MONTH('ALL ORDERS'!A62))} -> DEC | D62: =YEAR(A62) -> 2023 | E62: Jacob | F62: Removing the front door | G62: 2000 | H62: 0 | J62: =G62+H62 -> 2000 | K62: 45261 | L62: =DAY(K62) -> 1 | M62: {=INDEX(Processing!$W$6:$W$17,MONTH('ALL ORDERS'!K62))} -> December | N62: =YEAR(K62) -> 2023 | O62: 0.5 | P62: Client 44 | Q62: New York | R62: 678 Aspen Avenue, Unit 43PP | S62: William | T62: (212) 555-9817 | U62: Reddit | V62: Completed | W62: 435 | X62: 5 | Y62: 1000 | Z62: =W62-Y62 -> -565
A63: 45261 | B63: =DAY(A63) -> 1 | C63: {=INDEX(Processing!$C$11:$C$22,MONTH('ALL ORDERS'!A63))} -> DEC | D63: =YEAR(A63) -> 2023 | E63: Isabella | F63: Laying solid boards | G63: 0 | H63: 2130 | J63: =G63+H63 -> 2130 | K63: 45261 | L63: =DAY(K63) -> 1 | M63: {=INDEX(Processing!$W$6:$W$17,MONTH('ALL ORDERS'!K63))} -> December | N63: =YEAR(K63) -> 2023 | O63: 0.66666667 | P63: Client 45 | Q63: Chikago | R63: 1234 Sequoia Road, Apt. 44QQ | S63: James | T63: (917) 555-7831 | U63: WhatsApp | V63: Completed | W63: 4649 | X63: 5 | Y63: 3000 | Z63: =W63-Y63 -> 1649
A64: 45261 | B64: =DAY(A64) -> 1 | C64: {=INDEX(Processing!$C$11:$C$22,MONTH('ALL ORDERS'!A64))} -> DEC | D64: =YEAR(A64) -> 2023 | E64: Charlotte | F64: Installation of ceiling plinth | G64: 160 | H64: 0 | J64: =G64+H64 -> 160 | K64: 45261 | L64: =DAY(K64) -> 1 | M64: {=INDEX(Processing!$W$6:$W$17,MONTH('ALL ORDERS'!K64))} -> December | N64: =YEAR(K64) -> 2023 | O64: 0.75 | P64: Client 46 | Q64: New York | R64: 5678 Willowbrook Drive, Suite 45RR | S64: Oliver | T64: (718) 555-2286 | U64: YouTube | V64: Completed | W64: 445 | X64: 4 | Y64: 3000 | Z64: =W64-Y64 -> -2555
A65: 45268 | B65: =DAY(A65) -> 8 | C65: {=INDEX(Processing!$C$11:$C$22,MONTH('ALL ORDERS'!A65))} -> DEC | D65: =YEAR(A65) -> 2023 | E65: Isabella | F65: Removing the shower tray | G65: 3510 | H65: 0 | J65: =G65+H65 -> 3510 | K65: 45268 | L65: =DAY(K65) -> 8 | M65: {=INDEX(Processing!$W$6:$W$17,MONTH('ALL ORDERS'!K65))} -> December | N65: =YEAR(K65) -> 2023 | O65: 0.41666667 | P65: Client 47 | Q65: Chikago | R65: 987 Acorn Street, Unit 46SS | S65: Lucas | T65: 57900888990 | U65: Instagram | V65: Completed | W65: 1176 | X65: 4 | Y65: 3000 | Z65: =W65-Y65 -> -1824
A66: 45269 | B66: =DAY(A66) -> 9 | C66: {=INDEX(Processing!$C$11:$C$22,MONTH('ALL ORDERS'!A66))} -> DEC | D66: =YEAR(A66) -> 2023 | E66: Joseph | F66: Removing the front door | G66: 3510 | H66: 0 | J66: =G66+H66 -> 3510 | K66: 45269 | L66: =DAY(K66) -> 9 | M66: {=INDEX(Processing!$W$6:$W$17,MONTH('ALL ORDERS'!K66))} -> December | N66: =YEAR(K66) -> 2023 | O66: 0.5 | P66: Client 48 | Q66: Chikago | R66: 654 Sycamore Avenue, Apt. 47TT | S66: Sofia | T66: (212) 555-1176 | U66: Facebook | V66: Completed | W66: 5422 | X66: 4 | Y66: 3000 | Z66: =W66-Y66 -> 2422
A67: 45270 | B67: =DAY(A67) -> 10 | C67: {=INDEX(Processing!$C$11:$C$22,MONTH('ALL ORDERS'!A67))} -> DEC | D67: =YEAR(A67) -> 2023 | E67: Liam | F67: Removing the sink | G67: 2540 | H67: 0 | J67: =G67+H67 -> 2540 | K67: 45270 | L67: =DAY(K67) -> 10 | M67: {=INDEX(Processing!$W$6:$W$17,MONTH('ALL ORDERS'!K67))} -> December | N67: =YEAR(K67) -> 2023 | O67: 0.66666667 | P67: Client 49 | Q67: Chikago | R67: 321 Cedarwood Lane, Suite 48UU | S67: Jack | T67: (917) 555-5620 | U67: WhatsApp | V67: Completed | W67: 8920 | X67: 4 | Y67: 3000 | Z67: =W67-Y67 -> 5920
A68: 45271 | B68: =DAY(A68) -> 11 | C68: {=INDEX(Processing!$C$11:$C$22,MONTH('ALL ORDERS'!A68))} -> DEC | D68: =YEAR(A68) -> 2023 | E68: Isabella | F68: Dismantling the window block | G68: 0 | H68: 1420 | J68: =G68+H68 -> 1420 | K68: 45271 | L68: =DAY(K68) -> 11 | M68: {=INDEX(Processing!$W$6:$W$17,MONTH('ALL ORDERS'!K68))} -> December | N68: =YEAR(K68) -> 2023 | O68: 0.75 | P68: Client 50 | Q68: New York | R68: 876 Elm Drive, Unit 49VV | S68: William | T68: (718) 555-8707 | U68: Reddit | V68: Completed | W68: 3759 | X68: 4 | Y68: 3000 | Z68: =W68-Y68 -> 759
A69: 45272 | B69: =DAY(A69) -> 12 | C69: {=INDEX(Processing!$C$11:$C$22,MONTH('ALL ORDERS'!A69))} -> DEC | D69: =YEAR(A69) -> 2023 | E69: Isabella | F69: Laying ceramic tiles, porcelain tiles on the floor with grout | G69: 2090 | H69: 0 | J69: =G69+H69 -> 2090 | K69: 45272 | L69: =DAY(K69) -> 12 | M69: {=INDEX(Processing!$W$6:$W$17,MONTH('ALL ORDERS'!K69))} -> December | N69: =YEAR(K69) -> 2023 | O69: 0.41666667 | P69: Client 51 | Q69: Chikago | R69: 543 Birch Road, Apt. 50WW | S69: James | T69: (646) 555-2287 | U69: YouTube | V69: Completed | W69: 2059 | X69: 4 | Y69: 3000 | Z69: =W69-Y69 -> -941
A70: 45273 | B70: =DAY(A70) -> 13 | C70: {=INDEX(Processing!$C$11:$C$22,MONTH('ALL ORDERS'!A70))} -> DEC | D70: =YEAR(A70) -> 2023 | E70: Charlotte | F70: Removing the front door | G70: 3190 | H70: 0 | J70: =G70+H70 -> 3190 | K70: 45273 | L70: =DAY(K70) -> 13 | M70: {=INDEX(Processing!$W$6:$W$17,MONTH('ALL ORDERS'!K70))} -> December | N70: =YEAR(K70) -> 2023 | O70: 0.5 | P70: Client 52 | Q70: Chikago | R70: 210 Oak Lane, Suite 51XX | S70: Oliver | T70: (212) 555-7832 | U70: YouTube | V70: Completed | W70: 3898 | X70: 4 | Y70: 3000 | Z70: =W70-Y70 -> 898
A71: 45273 | B71: =DAY(A71) -> 13 | C71: {=INDEX(Processing!$C$11:$C$22,MONTH('ALL ORDERS'!A71))} -> DEC | D71: =YEAR(A71) -> 2023 | E71: Isabella | F71: Application of decorative plaster | G71: 1280 | H71: 0 | J71: =G71+H71 -> 1280 | K71: 45273 | L71: =DAY(K71) -> 13 | M71: {=INDEX(Processing!$W$6:$W$17,MONTH('ALL ORDERS'!K71))} -> December | N71: =YEAR(K71) -> 2023 | O71: 0.66666667 | P71: Client 53 | Q71: Chikago | R71: 8765 Maple Street, Unit 52YY | S71: Lucas | T71: (917) 555-4263 | U71: Reddit | V71: Completed | W71: 1552 | X71: 4 | Y71: 3000 | Z71: =W71-Y71 -> -1448
A72: 45273 | B72: =DAY(A72) -> 13 | C72: {=INDEX(Processing!$C$11:$C$22,MONTH('ALL ORDERS'!A72))} -> DEC | D72: =YEAR(A72) -> 2023 | E72: Jacob | F72: Laying solid boards | G72: 0 | H72: 3610 | J72: =G72+H72 -> 3610 | K72: 45273 | L72: =DAY(K72) -> 13 | M72: {=INDEX(Processing!$W$6:$W$17,MONTH('ALL ORDERS'!K72))} -> December | N72: =YEAR(K72) -> 2023 | O72: 0.75 | P72: Client 54 | Q72: Chikago | R72: 4321 Pine Street, Apt. 53ZZ | S72: Sofia | T72: (718) 555-3398 | U72: WhatsApp | V72: Completed | W72: 790 | X72: 4 | Y72: 2000 | Z72: =W72-Y72 -> -1210
A73: 45273 | B73: =DAY(A73) -> 13 | C73: {=INDEX(Processing!$C$11:$C$22,MONTH('ALL ORDERS'!A73))} -> DEC | D73: =YEAR(A73) -> 2023 | E73: Liam | F73: Application of decorative plaster | G73: 3320 | H73: 0 | I73: 0.15 | J73: =G73+H73 -> 3320 | K73: 45273 | L73: =DAY(K73) -> 13 | M73: {=INDEX(Processing!$W$6:$W$17,MONTH('ALL ORDERS'!K73))} -> December | N73: =YEAR(K73) -> 2023 | O73: 0.41666667 | P73: Client 55 | Q73: Chikago | R73: 123 Redwood Avenue, Suite 54AAA | S73: Jack | T73: (646) 555-6731 | U73: Reddit | V73: Completed | W73: 937 | X73: 4 | Y73: 2000 | Z73: =W73-Y73 -> -1063
A74: 45274 | B74: =DAY(A74) -> 14 | C74: {=INDEX(Processing!$C$11:$C$22,MONTH('ALL ORDERS'!A74))} -> DEC | D74: =YEAR(A74) -> 2023 | E74: Isabella | F74: Wallpapering | G74: 2960 | H74: 0 | J74: =G74+H74 -> 2960 | K74: 45274 | L74: =DAY(K74) -> 14 | M74: {=INDEX(Processing!$W$6:$W$17,MONTH('ALL ORDERS'!K74))} -> December | N74: =YEAR(K74) -> 2023 | O74: 0.5 | P74: Client 56 | Q74: Chikago | R74: 456 Willow Lane, Unit 55BBB | S74: William | T74: (212) 555-9818 | U74: YouTube | V74: Canceled | W74: 5669 | Y74: 3000 | Z74: =W74-Y74 -> 2669
A75: 45275 | B75: =DAY(A75) -> 15 | C75: {=INDEX(Processing!$C$11:$C$22,MONTH('ALL ORDERS'!A75))} -> DEC | D75: =YEAR(A75) -> 2023 | E75: Isabella | F75: Removing the front door | G75: 2130 | H75: 0 | J75: =G75+H75 -> 2130 | K75: 45275 | L75: =DAY(K75) -> 15 | M75: {=INDEX(Processing!$W$6:$W$17,MONTH('ALL ORDERS'!K75))} -> December | N75: =YEAR(K75) -> 2023 | O75: 0.66666667 | P75: Client 57 | Q75: New York | R75: 789 Magnolia Road, Apt. 56CCC | S75: James | T75: (917) 555-7832 | U75: YouTube | V75: Completed | W75: 4619 | X75: 4 | Y75: 3000 | Z75: =W75-Y75 -> 1619
A76: 45276 | B76: =DAY(A76) -> 16 | C76: {=INDEX(Processing!$C$11:$C$22,MONTH('ALL ORDERS'!A76))} -> DEC | D76: =YEAR(A76) -> 2023 | E76: Charlotte | F76: Cutting and installation of additional corners | G76: 1420 | H76: 0 | J76: =G76+H76 -> 1420 | K76: 45276 | L76: =DAY(K76) -> 16 | M76: {=INDEX(Processing!$W$6:$W$17,MONTH('ALL ORDERS'!K76))} -> December | N76: =YEAR(K76) -> 2023 | O76: 0.75 | P76: Client 58 | Q76: Chikago | R76: 234 Sequoia Street, Suite 57DDD | S76: Oliver | T76: (718) 555-2287 | U76: Reddit | V76: Completed | W76: 2614 | X76: 5 | Y76: 3000 | Z76: =W76-Y76 -> -386
A77: 45271 | B77: =DAY(A77) -> 11 | C77: {=INDEX(Processing!$C$11:$C$22,MONTH('ALL ORDERS'!A77))} -> DEC | D77: =YEAR(A77) -> 2023 | E77: Isabella | F77: Cutting and installation of additional corners | G77: 890 | H77: 0 | J77: =G77+H77 -> 890 | K77: 45271 | L77: =DAY(K77) -> 11 | M77: {=INDEX(Processing!$W$6:$W$17,MONTH('ALL ORDERS'!K77))} -> December | N77: =YEAR(K77) -> 2023 | O77: 0.41666667 | P77: Client 59 | Q77: Chikago | R77: 567 Willowbrook Drive, Unit 58EEE | S77: Lucas | T77: 56900888990 | U77: YouTube | V77: Completed | W77: 7108 | X77: 5 | Y77: 3000 | Z77: =W77-Y77 -> 4108
A78: 45278 | B78: =DAY(A78) -> 18 | C78: {=INDEX(Processing!$C$11:$C$22,MONTH('ALL ORDERS'!A78))} -> DEC | D78: =YEAR(A78) -> 2023 | E78: Joseph | F78: Laying parquet boards with glue | G78: 190 | H78: 0 | J78: =G78+H78 -> 190 | K78: 45278 | L78: =DAY(K78) -> 18 | M78: {=INDEX(Processing!$W$6:$W$17,MONTH('ALL ORDERS'!K78))} -> December | N78: =YEAR(K78) -> 2023 | O78: 0.5 | P78: Client 60 | Q78: Chikago | R78: 890 Acorn Avenue, Apt. 59FFF | S78: Sofia | T78: (212) 555-1177 | U78: WhatsApp | V78: Completed | W78: 1773 | X78: 5 | Y78: 3000 | Z78: =W78-Y78 -> -1227
A79: 45279 | B79: =DAY(A79) -> 19 | C79: {=INDEX(Processing!$C$11:$C$22,MONTH('ALL ORDERS'!A79))} -> DEC | D79: =YEAR(A79) -> 2023 | E79: Liam | F79: Application of decorative plaster | G79: 1310 | H79: 0 | I79: 0.15 | J79: =G79+H79 -> 1310 | K79: 45279 | L79: =DAY(K79) -> 19 | M79: {=INDEX(Processing!$W$6:$W$17,MONTH('ALL ORDERS'!K79))} -> December | N79: =YEAR(K79) -> 2023 | O79: 0.66666667 | P79: Client 61 | Q79: Chikago | R79: 345 Sycamore Lane, Suite 60GGG | S79: Jack | T79: (917) 555-5621 | U79: Facebook | V79: Completed | W79: 308 | X79: 5 | Y79: 500 | Z79: =W79-Y79 -> -192
A80: 45279 | B80: =DAY(A80) -> 19 | C80: {=INDEX(Processing!$C$11:$C$22,MONTH('ALL ORDERS'!A80))} -> DEC | D80: =YEAR(A80) -> 2023 | E80: Isabella | F80: Installation of ceiling plinth | G80: 1610 | H80: 0 | J80: =G80+H80 -> 1610 | K80: 45279 | L80: =DAY(K80) -> 19 | M80: {=INDEX(Processing!$W$6:$W$17,MONTH('ALL ORDERS'!K80))} -> December | N80: =YEAR(K80) -> 2023 | O80: 0.75 | P80: Client 62 | Q80: New York | R80: 678 Cedarwood Road, Unit 61HHH | S80: William | T80: (718) 555-8708 | U80: Instagram | V80: Completed | W80: 1589 | X80: 5 | Y80: 3000 | Z80: =W80-Y80 -> -1411
A81: 45280 | B81: =DAY(A81) -> 20 | C81: {=INDEX(Processing!$C$11:$C$22,MONTH('ALL ORDERS'!A81))} -> DEC | D81: =YEAR(A81) -> 2023 | E81: Charlotte | F81: Laying plywood in 1 layer | G81: 0 | H81: 1960 | J81: =G81+H81 -> 1960 | K81: 45280 | L81: =DAY(K81) -> 20 | M81: {=INDEX(Processing!$W$6:$W$17,MONTH('ALL ORDERS'!K81))} -> December | N81: =YEAR(K81) -> 2023 | O81: 0.41666667 | P81: Client 63 | Q81: Chikago | R81: 123 Elm Street, Apt. 62III | S81: James | T81: (646) 555-2288 | U81: Facebook | V81: Completed | W81: 4908 | X81: 5 | Y81: 3000 | Z81: =W81-Y81 -> 1908
A82: 45281 | B82: =DAY(A82) -> 21 | C82: {=INDEX(Processing!$C$11:$C$22,MONTH('ALL ORDERS'!A82))} -> DEC | D82: =YEAR(A82) -> 2023 | E82: Jacob | F82: Laying linoleum with glue | G82: 0 | H82: 1560 | J82: =G82+H82 -> 1560 | K82: 45281 | L82: =DAY(K82) -> 21 | M82: {=INDEX(Processing!$W$6:$W$17,MONTH('ALL ORDERS'!K82))} -> December | N82: =YEAR(K82) -> 2023 | O82: 0.5 | P82: Client 64 | Q82: Chikago | R82: 456 Birch Avenue, Suite 63JJJ | S82: Oliver | T82: (212) 555-7833 | U82: YouTube | V82: Completed | W82: 2409 | X82: 3 | Y82: 3000 | Z82: =W82-Y82 -> -591
A83: 45282 | B83: =DAY(A83) -> 22 | C83: {=INDEX(Processing!$C$11:$C$22,MONTH('ALL ORDERS'!A83))} -> DEC | D83: =YEAR(A83) -> 2023 | E83: Joseph | F83: Removing the sink | G83: 2960 | H83: 0 | J83: =G83+H83 -> 2960 | K83: 45282 | L83: =DAY(K83) -> 22 | M83: {=INDEX(Processing!$W$6:$W$17,MONTH('ALL ORDERS'!K83))} -> December | N83: =YEAR(K83) -> 2023 | O83: 0.66666667 | P83: Client 65 | Q83: New York | R83: 789 Oak Lane, Unit 64KKK | S83: Lucas | T83: (917) 555-4264 | U83: Reddit | V83: Completed | W83: 3730 | X83: 3 | Y83: 3000 | Z83: =W83-Y83 -> 730
A84: 45283 | B84: =DAY(A84) -> 23 | C84: {=INDEX(Processing!$C$11:$C$22,MONTH('ALL ORDERS'!A84))} -> DEC | D84: =YEAR(A84) -> 2023 | E84: Isabella | F84: Removing the front door | G84: 1520 | H84: 0 | J84: =G84+H84 -> 1520 | K84: 45283 | L84: =DAY(K84) -> 23 | M84: {=INDEX(Processing!$W$6:$W$17,MONTH('ALL ORDERS'!K84))} -> December | N84: =YEAR(K84) -> 2023 | O84: 0.75 | P84: Client 66 | Q84: Chikago | R84: 234 Maple Road, Apt. 65LLL | S84: Sofia | T84: (718) 555-3399 | U84: WhatsApp | V84: Completed | W84: 842 | X84: 2 | Y84: 1000 | Z84: =W84-Y84 -> -158
A85: 45283 | B85: =DAY(A85) -> 23 | C85: {=INDEX(Processing!$C$11:$C$22,MONTH('ALL ORDERS'!A85))} -> DEC | D85: =YEAR(A85) -> 2023 | E85: Charlotte | F85: Dismantling the balcony block | G85: 1290 | H85: 0 | J85: =G85+H85 -> 1290 | K85: 45283 | L85: =DAY(K85) -> 23 | M85: {=INDEX(Processing!$W$6:$W$17,MONTH('ALL ORDERS'!K85))} -> December | N85: =YEAR(K85) -> 2023 | O85: 0.41666667 | P85: Client 67 | Q85: Chikago | R85: 567 Pine Street, Suite 66MMM | S85: Jack | T85: (646) 555-6732 | U85: YouTube | V85: Completed | W85: 4817 | X85: 3 | Y85: 3000 | Z85: =W85-Y85 -> 1817
A86: 45283 | B86: =DAY(A86) -> 23 | C86: {=INDEX(Processing!$C$11:$C$22,MONTH('ALL ORDERS'!A86))} -> DEC | D86: =YEAR(A86) -> 2023 | E86: Isabella | F86: Laying parquet boards with glue | G86: 1410 | H86: 0 | J86: =G86+H86 -> 1410 | K86: 45283 | L86: =DAY(K86) -> 23 | M86: {=INDEX(Processing!$W$6:$W$17,MONTH('ALL ORDERS'!K86))} -> December | N86: =YEAR(K86) -> 2023 | O86: 0.5 | P86: Client 68 | Q86: Chikago | R86: 890 Willow Drive, Unit 67NNN | S86: William | T86: (212) 555-9819 | U86: Instagram | V86: Completed | W86: 5484 | X86: 4 | Y86: 3000 | Z86: =W86-Y86 -> 2484
A87: 45284 | B87: =DAY(A87) -> 24 | C87: {=INDEX(Processing!$C$11:$C$22,MONTH('ALL ORDERS'!A87))} -> DEC | D87: =YEAR(A87) -> 2023 | E87: Jacob | F87: Laying quartz vinyl tiles on a substrate | G87: 1250 | H87: 0 | J87: =G87+H87 -> 1250 | K87: 45284 | L87: =DAY(K87) -> 24 | M87: {=INDEX(Processing!$W$6:$W$17,MONTH('ALL ORDERS'!K87))} -> December | N87: =YEAR(K87) -> 2023 | O87: 0.66666667 | P87: Client 69 | Q87: Chikago | R87: 345 Redwood Lane, Apt. 68OOO | S87: James | T87: (917) 555-7833 | U87: Facebook | V87: Completed | W87: 614 | X87: 3 | Y87: 3000 | Z87: =W87-Y87 -> -2386
A88: 45285 | B88: =DAY(A88) -> 25 | C88: {=INDEX(Processing!$C$11:$C$22,MONTH('ALL ORDERS'!A88))} -> DEC | D88: =YEAR(A88) -> 2023 | E88: Liam | F88: Laying parquet boards on a substrate | G88: 1100 | H88: 0 | J88: =G88+H88 -> 1100 | K88: 45285 | L88: =DAY(K88) -> 25 | M88: {=INDEX(Processing!$W$6:$W$17,MONTH('ALL ORDERS'!K88))} -> December | N88: =YEAR(K88) -> 2023 | O88: 0.75 | P88: Client 70 | Q88: New York | R88: 678 Spruce Street, Suite 69PPP | S88: Oliver | T88: (718) 555-2288 | U88: WhatsApp | V88: Completed | W88: 57 | X88: 4 | Y88: 3000 | Z88: =W88-Y88 -> -2943
A89: 45286 | B89: =DAY(A89) -> 26 | C89: {=INDEX(Processing!$C$11:$C$22,MONTH('ALL ORDERS'!A89))} -> DEC | D89: =YEAR(A89) -> 2023 | E89: Isabella | F89: Laying solid boards | G89: 0 | H89: 1140 | J89: =G89+H89 -> 1140 | K89: 45286 | L89: =DAY(K89) -> 26 | M89: {=INDEX(Processing!$W$6:$W$17,MONTH('ALL ORDERS'!K89))} -> December | N89: =YEAR(K89) -> 2023 | O89: 0.41666667 | P89: Client 71 | Q89: Chikago | R89: 1234 Aspen Road, Unit 70QQQ | S89: Lucas | T89: 55900888990 | U89: Reddit | V89: Completed | W89: 8060 | X89: 5 | Y89: 3000 | Z89: =W89-Y89 -> 5060
A90: 45281 | B90: =DAY(A90) -> 21 | C90: {=INDEX(Processing!$C$11:$C$22,MONTH('ALL ORDERS'!A90))} -> DEC | D90: =YEAR(A90) -> 2023 | E90: Charlotte | F90: Installation of ceiling plinth | G90: 0 | H90: 2810 | J90: =G90+H90 -> 2810 | K90: 45281 | L90: =DAY(K90) -> 21 | M90: {=INDEX(Processing!$W$6:$W$17,MONTH('ALL ORDERS'!K90))} -> December | N90: =YEAR(K90) -> 2023 | O90: 0.5 | P90: Client 72 | Q90: Chikago | R90: 5678 Cedar Drive, Apt. 71RRR | S90: Sofia | T90: (212) 555-1178 | U90: YouTube | V90: Completed | W90: 349 | X90: 4 | Y90: 2000 | Z90: =W90-Y90 -> -1651
A91: 45288 | B91: =DAY(A91) -> 28 | C91: {=INDEX(Processing!$C$11:$C$22,MONTH('ALL ORDERS'!A91))} -> DEC | D91: =YEAR(A91) -> 2023 | E91: Joseph | F91: Removing the front door | G91: 0 | H91: 2680 | J91: =G91+H91 -> 2680 | K91: 45288 | L91: =DAY(K91) -> 28 | M91: {=INDEX(Processing!$W$6:$W$17,MONTH('ALL ORDERS'!K91))} -> December | N91: =YEAR(K91) -> 2023 | O91: 0.66666667 | P91: Client 73 | Q91: Chikago | R91: 987 Pinecone Avenue, Suite 72SSS | S91: Jack | T91: (917) 555-5622 | U91: YouTube | V91: Completed | W91: 1619 | X91: 5 | Y91: 3000 | Z91: =W91-Y91 -> -1381
A92: 45288 | B92: =DAY(A92) -> 28 | C92: {=INDEX(Processing!$C$11:$C$22,MONTH('ALL ORDERS'!A92))} -> DEC | D92: =YEAR(A92) -> 2023 | E92: Isabella | F92: Installation of ceiling plinth | G92: 0 | H92: 220 | J92: =G92+H92 -> 220 | K92: 45288 | L92: =DAY(K92) -> 28 | M92: {=INDEX(Processing!$W$6:$W$17,MONTH('ALL ORDERS'!K92))} -> December | N92: =YEAR(K92) -> 2023 | O92: 0.75 | P92: Client 74 | Q92: New York | R92: 654 Magnolia Lane, Unit 73TTT | S92: William | T92: (718) 555-8709 | U92: Reddit | V92: Canceled | W92: 769 | Y92: 3000 | Z92: =W92-Y92 -> -2231
A93: 45288 | B93: =DAY(A93) -> 28 | C93: {=INDEX(Processing!$C$11:$C$22,MONTH('ALL ORDERS'!A93))} -> DEC | D93: =YEAR(A93) -> 2023 | E93: Charlotte | F93: Cutting and installation of additional corners | G93: 0 | H93: 430 | I93: 0.15 | J93: =G93+H93 -> 430 | K93: 45288 | L93: =DAY(K93) -> 28 | M93: {=INDEX(Processing!$W$6:$W$17,MONTH('ALL ORDERS'!K93))} -> December | N93: =YEAR(K93) -> 2023 | O93: 0.41666667 | P93: Client 75 | Q93: Chikago | R93: 321 Sequoia Street, Apt. 74UUU | S93: James | T93: (646) 555-2289 | U93: WhatsApp | V93: Canceled | W93: 5163 | Y93: 3000 | Z93: =W93-Y93 -> 2163
A94: 45301 | B94: =DAY(A94) -> 10 | C94: {=INDEX(Processing!$C$11:$C$22,MONTH('ALL ORDERS'!A94))} -> JAN | D94: =YEAR(A94) -> 2024 | E94: Isabella | F94: Laying parquet boards on a substrate | G94: 0 | H94: 3340 | J94: =G94+H94 -> 3340 | K94: 45301 | L94: =DAY(K94) -> 10 | M94: {=INDEX(Processing!$W$6:$W$17,MONTH('ALL ORDERS'!K94))} -> January | N94: =YEAR(K94) -> 2024 | O94: 0.5 | P94: Client 76 | Q94: Miami | R94: 876 Willowbrook Drive, Suite 75VVV | S94: Oliver | T94: (212) 555-7834 | U94: Reddit | V94: Canceled | W94: 3164 | Y94: =SUM(Y61:Y93) -> 89500
A95: 45302 | B95: =DAY(A95) -> 11 | C95: {=INDEX(Processing!$C$11:$C$22,MONTH('ALL ORDERS'!A95))} -> JAN | D95: =YEAR(A95) -> 2024 | E95: Jacob | F95: Dismantling the balcony block | G95: 0 | H95: 1150 | J95: =G95+H95 -> 1150 | K95: 45302 | L95: =DAY(K95) -> 11 | M95: {=INDEX(Processing!$W$6:$W$17,MONTH('ALL ORDERS'!K95))} -> January | N95: =YEAR(K95) -> 2024 | O95: 0.66666667 | P95: Client 77 | Q95: Chikago | R95: 543 Acorn Lane, Unit 76WWW | S95: Lucas | T95: (917) 555-4265 | U95: YouTube | V95: Canceled | W95: 666
A96: 45303 | B96: =DAY(A96) -> 12 | C96: {=INDEX(Processing!$C$11:$C$22,MONTH('ALL ORDERS'!A96))} -> JAN | D96: =YEAR(A96) -> 2024 | E96: Liam | F96: Laying parquet boards with glue | G96: 1650 | H96: 0 | J96: =G96+H96 -> 1650 | K96: 45303 | L96: =DAY(K96) -> 12 | M96: {=INDEX(Processing!$W$6:$W$17,MONTH('ALL ORDERS'!K96))} -> January | N96: =YEAR(K96) -> 2024 | O96: 0.75 | P96: Client 78 | Q96: Chikago | R96: 210 Sycamore Road, Apt. 77XXX | S96: Sofia | T96: (718) 555-3400 | U96: YouTube | V96: Canceled | W96: 3961
A97: 45304 | B97: =DAY(A97) -> 13 | C97: {=INDEX(Processing!$C$11:$C$22,MONTH('ALL ORDERS'!A97))} -> JAN | D97: =YEAR(A97) -> 2024 | E97: Isabella | F97: Laying solid boards | G97: 3980 | H97: 0 | J97: =G97+H97 -> 3980 | K97: 45304 | L97: =DAY(K97) -> 13 | M97: {=INDEX(Processing!$W$6:$W$17,MONTH('ALL ORDERS'!K97))} -> January | N97: =YEAR(K97) -> 2024 | O97: 0.41666667 | P97: Client 79 | Q97: Miami | R97: 8765 Cedarwood Street, Suite 78YYY | S97: Jack | T97: (646) 555-6733 | U97: Reddit | V97: Completed | W97: 2948 | X97: 4
A98: 45304 | B98: =DAY(A98) -> 13 | C98: {=INDEX(Processing!$C$11:$C$22,MONTH('ALL ORDERS'!A98))} -> JAN | D98: =YEAR(A98) -> 2024 | E98: Charlotte | F98: Installation of ceiling plinth | G98: 1530 | H98: 0 | J98: =G98+H98 -> 1530 | K98: 45304 | L98: =DAY(K98) -> 13 | M98: {=INDEX(Processing!$W$6:$W$17,MONTH('ALL ORDERS'!K98))} -> January | N98: =YEAR(K98) -> 2024 | O98: 0.5 | P98: Client 80 | Q98: Chikago | R98: 4321 Elm Drive, Unit 79ZZZ | S98: William | T98: (212) 555-9820 | U98: YouTube | V98: Completed | W98: 2171 | X98: 5
A99: 45304 | B99: =DAY(A99) -> 13 | C99: {=INDEX(Processing!$C$11:$C$22,MONTH('ALL ORDERS'!A99))} -> JAN | D99: =YEAR(A99) -> 2024 | E99: Joseph | F99: Removing the front door | G99: 2150 | H99: 0 | J99: =G99+H99 -> 2150 | K99: 45304 | L99: =DAY(K99) -> 13 | M99: {=INDEX(Processing!$W$6:$W$17,MONTH('ALL ORDERS'!K99))} -> January | N99: =YEAR(K99) -> 2024 | O99: 0.66666667 | P99: Client 81 | Q99: Miami | R99: 123 Birch Lane, Apt. 80AAAA | S99: Oliver | T99: (917) 555-7834 | U99: WhatsApp | V99: Completed | W99: 3270 | X99: 5
A100: 45307 | B100: =DAY(A100) -> 16 | C100: {=INDEX(Processing!$C$11:$C$22,MONTH('ALL ORDERS'!A100))} -> JAN | D100: =YEAR(A100) -> 2024 | E100: Jacob | F100: Removing the sink | G100: 810 | H100: 0 | J100: =G100+H100 -> 810 | K100: 45307 | L100: =DAY(K100) -> 16 | M100: {=INDEX(Processing!$W$6:$W$17,MONTH('ALL ORDERS'!K100))} -> January | N100: =YEAR(K100) -> 2024 | O100: 0.75 | P100: Client 82 | Q100: Chikago | R100: 456 Oak Avenue, Suite 81BBBB | S100: Jack | T100: (718) 555-2289 | U100: Facebook | V100: Completed | W100: 952 | X100: 4
A101: 45307 | B101: =DAY(A101) -> 16 | C101: {=INDEX(Processing!$C$11:$C$22,MONTH('ALL ORDERS'!A101))} -> JAN | D101: =YEAR(A101) -> 2024 | E101: Liam | F101: Removing the shower cabin | G101: 0 | H101: 2340 | I101: 0.15 | J101: =G101+H101 -> 2340 | K101: 45307 | L101: =DAY(K101) -> 16 | M101: {=INDEX(Processing!$W$6:$W$17,MONTH('ALL ORDERS'!K101))} -> January | N101: =YEAR(K101) -> 2024 | O101: 0.41666667 | P101: Client 83 | Q101: New York | R101: 789 Maple Street, Unit 82CCCC | S101: James | T101: 54900888990 | U101: Instagram | V101: Completed | W101: 889 | X101: 5
...

Sheet ORDER
F1: Jacob | G1: MANAGER
B3: CUSTOMER | D3: DETAILS | F3: PAYMENT
B5: Client Name | D5: Service | F5: Quantity (pcs, sq.m, etc.)
B8: Contact | D8: Date of Visit | F8: Price
B9: =IFERROR(INDEX('Customer Database'!F4:F103,MATCH(ORDER!B6,'Customer Database'!B4:B103,0)),"") | F9: =Processing!Q19 -> 0
B11: City | D11: Visit Time | F11: Payment Method
B14: Address | D14: Master | F14: Discount
B15: =IFERROR(INDEX('Customer Database'!D4:D103,MATCH(ORDER!B6,'Customer Database'!B4:B103,0)),"")
B17: Channels Attracting | D17: Total Payable
D18: =ROUND(F6*Processing!Q19*(1-F15),2) -> 0

Sheet Control
A3: Row Labels | B3: Sum of Cash | C3: Sum of Card | D3: Sum of Total | E3: Sum of Cost
A4: JAN | B4: 33820 | C4: 43780 | D4: 77600 | E4: 75137
A5: FEB | B5: 28020 | C5: 67080 | D5: 95100 | E5: 102667
A6: MAR | B6: 28020 | C6: 81580 | D6: 109600 | E6: 111307
A7: APR | B7: 18020 | C7: 99080 | D7: 117100 | E7: 110749
A8: MAY | B8: 38290 | C8: 71110 | D8: 109400 | E8: 99947
A9: JUN | B9: 14300 | C9: 81300 | D9: 95600 | E9: 98003
A10: JUL | B10: 5600 | C10: 84100 | D10: 89700 | E10: 98707
A11: AUG | B11: 37130 | C11: 65470 | D11: 102600 | E11: 111153
A12: SEP | B12: 46650 | C12: 77850 | D12: 124500 | E12: 89309
A13: OCT | B13: 55900 | C13: 81300 | D13: 137200 | E13: 93153
A14: NOV | B14: 81000 | C14: 64000 | D14: 145000 | E14: 83973
A15: DEC | B15: 103410 | C15: 30290 | D15: 133700 | E15: 51384
A16: Grand Total | B16: 490160 | C16: 846940 | D16: 1337100 | E16: 1125489
A19: Row Labels | B19: Sum of Cash | C19: Sum of Card | D19: Sum of Total | E19: Sum of Cost | G19: Row Labels | H19: Sum of Total | J19: Row Labels | K19: Count of Client rating | M19: Row Labels | N19: Count of Channel | P19: Row Labels | Q19: Count of Status | S19: Sum of Card | T19: Sum of Cash
A20: JAN | B20: 33820 | C20: 43780 | D20: 77600 | E20: 75137 | G20: Charlotte | H20: 349080 | J20: Jack | K20: 86 | M20: Facebook | N20: 47 | P20: Canceled | Q20: 18 | S20: 846940 | T20: 490160
A21: FEB | B21: 28020 | C21: 67080 | D21: 95100 | E21: 102667 | G21: Isabella | H21: 240940 | J21: James | K21: 73 | M21: Instagram | N21: 98 | P21: Completed | Q21: 326
A22: MAR | B22: 28020 | C22: 81580 | D22: 109600 | E22: 111307 | G22: Jacob | H22: 192980 | J22: Lucas | K22: 37 | M22: Reddit | N22: 79 | P22: Running | Q22: 7
A23: APR | B23: 18020 | C23: 99080 | D23: 117100 | E23: 110749 | G23: Joseph | H23: 254780 | J23: Oliver | K23: 33 | M23: WhatsApp | N23: 42 | P23: Grand Total | Q23: 351
A24: MAY | B24: 38290 | C24: 71110 | D24: 109400 | E24: 99947 | G24: Liam | H24: 299320 | J24: William | K24: 60 | M24: YouTube | N24: 85
A25: JUN | B25: 14300 | C25: 81300 | D25: 95600 | E25: 98003 | G25: Grand Total | H25: 1337100 | J25: Sofia | K25: 37 | M25: Grand Total | N25: 351
A26: JUL | B26: 5600 | C26: 84100 | D26: 89700 | E26: 98707 | J26: Grand Total | K26: 326
A27: AUG | B27: 37130 | C27: 65470 | D27: 102600 | E27: 111153
A28: SEP | B28: 46650 | C28: 77850 | D28: 124500 | E28: 89309
A29: OCT | B29: 55900 | C29: 81300 | D29: 137200 | E29: 93153
A30: NOV | B30: 81000 | C30: 64000 | D30: 145000 | E30: 83973
A31: DEC | B31: 103410 | C31: 30290 | D31: 133700 | E31: 51384
A32: Grand Total | B32: 490160 | C32: 846940 | D32: 1337100 | E32: 1125489
A35: Row Labels
A36: 2025
A41: Row Labels | G41: Row Labels | H41: Count of Service
A42: JAN | G42: Application of decorative plaster | H42: 2
A43: FEB | G43: Cutting and installation of additional corners | H43: 27
A44: MAR | G44: Dismantling the balcony block | H44: 1
A45: APR | G45: Dismantling the window block | H45: 22
A46: MAY | G46: Installation of ceiling plinth | H46: 3
A47: JUN | G47: Installation of PVC skirting boards | H47: 24
A48: JUL | G48: Installation of slatted ceilings | H48: 49
A49: AUG | G49: Laying linoleum with glue | H49: 26
A50: SEP | G50: Laying parquet boards on a substrate | H50: 1
A51: OCT | G51: Laying parquet boards with glue | H51: 49
A52: NOV | G52: Laying plywood in 1 layer | H52: 1
A53: DEC | G53: Laying quartz vinyl tiles on a substrate | H53: 1
G54: Laying quartz vinyl tiles with glue | H54: 22
G55: Laying solid boards | H55: 25
G56: Removing an interior door | H56: 1
G57: Removing the front door | H57: 1
G58: Removing the shower cabin | H58: 1
G59: Removing the shower tray | H59: 1
G60: Threshold installation | H60: 21
G61: Wallpapering | H61: 1
G62: Wallpapering ceilings | H62: 72
G63: Grand Total | H63: 351

Sheet Personnel
I5: =UPPER(Processing!L9) -> MASTERS | K5: SALARY | M5: SALES PLAN | O5: DONE | Q5: KPI % | R5: PRIZE
I7: Jack | K7: =INDEX(Processing!$W$38:$W$48,MATCH(Personnel!I7,Processing!$S$38:$S$48,0),1) -> 24200 | M7: =AVERAGE(KPI!$D$4:$D$39) -> 4 | O7: =INDEX(Processing!$O$18:$P$23,MATCH(Personnel!I7,Processing!$N$18:$N$23,0),1) -> 86 | Q7: =INDEX(Processing!$O$18:$P$23,MATCH(Personnel!I7,Processing!$N$18:$N$23,0),2) -> 1.7916667 | R7: =IF(Q7>=100%,CHOOSE(SUM(Q7>=100%,Q7>130%),3%,5%),0%) -> 0.05
I9: William | K9: =INDEX(Processing!$W$38:$W$48,MATCH(Personnel!I9,Processing!$S$38:$S$48,0),1) -> 24200 | M9: =AVERAGE(KPI!$D$4:$D$39) -> 4 | O9: =INDEX(Processing!$O$18:$P$23,MATCH(Personnel!I9,Processing!$N$18:$N$23,0),1) -> 60 | Q9: =INDEX(Processing!$O$18:$P$23,MATCH(Personnel!I9,Processing!$N$18:$N$23,0),2) -> 1.25 | R9: =IF(Q9>=100%,CHOOSE(SUM(Q9>=100%,Q9>130%),3%,5%),0%) -> 0.03
I11: James | K11: =INDEX(Processing!$W$38:$W$48,MATCH(Personnel!I11,Processing!$S$38:$S$48,0),1) -> 24200 | M11: =AVERAGE(KPI!$D$4:$D$39) -> 4 | O11: =INDEX(Processing!$O$18:$P$23,MATCH(Personnel!I11,Processing!$N$18:$N$23,0),1) -> 73 | Q11: =INDEX(Processing!$O$18:$P$23,MATCH(Personnel!I11,Processing!$N$18:$N$23,0),2) -> 1.5208333 | R11: =IF(Q11>=100%,CHOOSE(SUM(Q11>=100%,Q11>130%),3%,5%),0%) -> 0.05
I13: Oliver | K13: =INDEX(Processing!$W$38:$W$48,MATCH(Personnel!I13,Processing!$S$38:$S$48,0),1) -> 24200 | M13: =AVERAGE(KPI!$D$4:$D$39) -> 4 | O13: =INDEX(Processing!$O$18:$P$23,MATCH(Personnel!I13,Processing!$N$18:$N$23,0),1) -> 33 | Q13: =INDEX(Processing!$O$18:$P$23,MATCH(Personnel!I13,Processing!$N$18:$N$23,0),2) -> 0.6875 | R13: =IF(Q13>=100%,CHOOSE(SUM(Q13>=100%,Q13>130%),3%,5%),0%) -> 0
I15: Lucas | K15: =INDEX(Processing!$W$38:$W$48,MATCH(Personnel!I15,Processing!$S$38:$S$48,0),1) -> 24200 | M15: =AVERAGE(KPI!$D$4:$D$39) -> 4 | O15: =INDEX(Processing!$O$18:$P$23,MATCH(Personnel!I15,Processing!$N$18:$N$23,0),1) -> 37 | Q15: =INDEX(Processing!$O$18:$P$23,MATCH(Personnel!I15,Processing!$N$18:$N$23,0),2) -> 0.77083333 | R15: =IF(Q15>=100%,CHOOSE(SUM(Q15>=100%,Q15>130%),3%,5%),0%) -> 0
I17: Sofia | K17: =INDEX(Processing!$W$38:$W$48,MATCH(Personnel!I17,Processing!$S$38:$S$48,0),1) -> 24200 | M17: =AVERAGE(KPI!$D$4:$D$39) -> 4 | O17: =INDEX(Processing!$O$18:$P$23,MATCH(Personnel!I17,Processing!$N$18:$N$23,0),1) -> 37 | Q17: =INDEX(Processing!$O$18:$P$23,MATCH(Personnel!I17,Processing!$N$18:$N$23,0),2) -> 0.77083333 | R17: =IF(Q17>=100%,CHOOSE(SUM(Q17>=100%,Q17>130%),3%,5%),0%) -> 0
I21: =UPPER(Processing!M9) -> MANAGERS | K21: SALARY | M21: SALES PLAN | O21: DONE | Q21: KPI % | R21: PRIZE
I23: Isabella | K23: =INDEX(Processing!$W$38:$W$48,MATCH(Personnel!I23,Processing!$S$38:$S$48,0),1) -> 31900 | M23: =AVERAGE(KPI!$C$4:$C$39) -> 15000 | O23: =INDEX(Processing!$L$18:$M$22,MATCH(Personnel!I23,Processing!$K$18:$K$22,0),1) -> 240940 | Q23: =INDEX(Processing!$L$18:$M$22,MATCH(Personnel!I23,Processing!$K$18:$K$22,0),2) -> 1.3385556 | R23: =IF(Q23>=100%,CHOOSE(SUM(Q23>=100%,Q23>130%),3%,5%),0%) -> 0.05
I25: Joseph | K25: =INDEX(Processing!$W$38:$W$48,MATCH(Personnel!I25,Processing!$S$38:$S$48,0),1) -> 31900 | M25: =AVERAGE(KPI!$C$4:$C$39) -> 15000 | O25: =INDEX(Processing!$L$18:$M$22,MATCH(Personnel!I25,Processing!$K$18:$K$22,0),1) -> 254780 | Q25: =INDEX(Processing!$L$18:$M$22,MATCH(Personnel!I25,Processing!$K$18:$K$22,0),2) -> 1.4154444 | R25: =IF(Q25>=100%,CHOOSE(SUM(Q25>=100%,Q25>130%),3%,5%),0%) -> 0.05
I27: Liam | K27: =INDEX(Processing!$W$38:$W$48,MATCH(Personnel!I27,Processing!$S$38:$S$48,0),1) -> 31900 | M27: =AVERAGE(KPI!$C$4:$C$39) -> 15000 | O27: =INDEX(Processing!$L$18:$M$22,MATCH(Personnel!I27,Processing!$K$18:$K$22,0),1) -> 299320 | Q27: =INDEX(Processing!$L$18:$M$22,MATCH(Personnel!I27,Processing!$K$18:$K$22,0),2) -> 1.6628889 | R27: =IF(Q27>=100%,CHOOSE(SUM(Q27>=100%,Q27>130%),3%,5%),0%) -> 0.05
I29: Charlotte | K29: =INDEX(Processing!$W$38:$W$48,MATCH(Personnel!I29,Processing!$S$38:$S$48,0),1) -> 31900 | M29: =AVERAGE(KPI!$C$4:$C$39) -> 15000 | O29: =INDEX(Processing!$L$18:$M$22,MATCH(Personnel!I29,Processing!$K$18:$K$22,0),1) -> 349080 | Q29: =INDEX(Processing!$L$18:$M$22,MATCH(Personnel!I29,Processing!$K$18:$K$22,0),2) -> 1.9393333 | R29: =IF(Q29>=100%,CHOOSE(SUM(Q29>=100%,Q29>130%),3%,5%),0%) -> 0.05
I31: Jacob | K31: =INDEX(Processing!$W$38:$W$48,MATCH(Personnel!I31,Processing!$S$38:$S$48,0),1) -> 31900 | M31: =AVERAGE(KPI!$C$4:$C$39) -> 15000 | O31: =INDEX(Processing!$L$18:$M$22,MATCH(Personnel!I31,Processing!$K$18:$K$22,0),1) -> 192980 | Q31: =INDEX(Processing!$L$18:$M$22,MATCH(Personnel!I31,Processing!$K$18:$K$22,0),2) -> 1.0721111 | R31: =IF(Q31>=100%,CHOOSE(SUM(Q31>=100%,Q31>130%),3%,5%),0%) -> 0.03

Sheet Processing
D1: Amount | I1: Services | K1: Indent | L1: =MAX(J2:J6)*0.05 -> 3.6 | O1: Channel | S1: Lable | W1: ToDay | Z1: Current Month | AA1: Time | AC1: 1 | AD1: =K18 -> Isabella | AE1: =M18 -> 1.3385556 | AF1: {=INDEX($AD$1:$AD$5,SMALL(IF($AE$1:$AE$5=AG1,ROW($AE$1:$AE$5)),COUNTIF($AG$1:AG1,AG1)))} -> Charlotte | AG1: =LARGE($AE$1:$AE$5,AC1) -> 1.9393333 | AI1: 1 | AJ1: =N18 -> Jack | AK1: =P18 -> 1.7916667 | AL1: {=INDEX($AJ$1:$AJ$6,SMALL(IF($AK$1:$AK$6=AM1,ROW($AK$1:$AK$6)),COUNTIF($AM$1:AM1,AM1)))} -> Jack | AM1: =LARGE($AK$1:$AK$6,AI1) -> 1.7916667 | AO1: 1 | AP1: =B38 -> Dismantling the balcony block | AQ1: =C38 -> 1 | AR1: {=INDEX($AP$1:$AP$26,SMALL(IF($AQ$1:$AQ$26=AS1,ROW($AQ$1:$AQ$26)),COUNTIF($AS$1:AS1,AS1)))} -> Wallpapering ceilings | AS1: =LARGE($AQ$1:$AQ$26,AO1) -> 72 | AT1: =$AU$1 -> 2.16 | AU1: =MAX(AS1:AS26)*0.03 -> 2.16
A2: Cash | B2: =D2/D4 -> 0.3665844 | C2: =1-B2 -> 0.6334156 | D2: =GETPIVOTDATA("Sum of Cash",Control!$S$19) -> 490160 | I2: =AR1 -> Wallpapering ceilings | J2: =AS1 -> 72 | K2: =$L$1 -> 3.6 | L2: =LEFT(I2,18)&"…" -> Wallpapering ceili… | O2: =Data!M8 -> Facebook | P2: =Q2/$Q$7 -> 0.13390313 | Q2: =IFERROR(GETPIVOTDATA(""&$O$1,Control!$M$19,""&$O$1,""&O2),0) -> 47 | S2: =O2&T1&O3&T1&O4&CHAR(10)&CHAR(10)&O5&T1&O6 -> Facebook Reddit Instagram YouTube WhatsApp | W2: =TODAY() -> 46283 | Y2: 1 | Z2: =DATE(YEAR($W$2),MONTH($W$2),Y2) -> 46266 | AA2: 0.041666667 | AC2: 2 | AD2: =K19 -> Joseph | AE2: =M19 -> 1.4154444 | AF2: {=INDEX($AD$1:$AD$5,SMALL(IF($AE$1:$AE$5=AG2,ROW($AE$1:$AE$5)),COUNTIF($AG$1:AG2,AG2)))} -> Liam | AG2: =LARGE($AE$1:$AE$5,AC2) -> 1.6628889 | AI2: 2 | AJ2: =N19 -> William | AK2: =P19 -> 1.25 | AL2: {=INDEX($AJ$1:$AJ$6,SMALL(IF($AK$1:$AK$6=AM2,ROW($AK$1:$AK$6)),COUNTIF($AM$1:AM2,AM2)))} -> James | AM2: =LARGE($AK$1:$AK$6,AI2) -> 1.5208333 | AO2: 2 | AP2: =B39 -> Laying parquet boards with glue | AQ2: =C39 -> 49 | AR2: {=INDEX($AP$1:$AP$26,SMALL(IF($AQ$1:$AQ$26=AS2,ROW($AQ$1:$AQ$26)),COUNTIF($AS$1:AS2,AS2)))} -> Laying parquet boards with glue | AS2: =LARGE($AQ$1:$AQ$26,AO2) -> 49 | AT2: =$AU$1 -> 2.16
A3: Card | B3: =D3/D4 -> 0.6334156 | C3: =1-B3 -> 0.3665844 | D3: =GETPIVOTDATA("Sum of Card",Control!$S$19) -> 846940 | I3: =AR2 -> Laying parquet boards with glue | J3: =AS2 -> 49 | K3: =$L$1 -> 3.6 | L3: =LEFT(I3,18)&"…" -> Laying parquet boa… | O3: =Data!M9 -> Reddit | P3: =Q3/$Q$7 -> 0.22507123 | Q3: =IFERROR(GETPIVOTDATA(""&$O$1,Control!$M$19,""&$O$1,""&O3),0) -> 79 | W3: {=INDEX(W6:W17,MONTH(W2))&X1&DAY(W2)&X1&YEAR(W2)} -> September 18 2026 | Y3: 2 | Z3: =DATE(YEAR($W$2),MONTH($W$2),Y3) -> 46267 | AA3: 0.083333333 | AC3: 3 | AD3: =K20 -> Liam | AE3: =M20 -> 1.6628889 | AF3: {=INDEX($AD$1:$AD$5,SMALL(IF($AE$1:$AE$5=AG3,ROW($AE$1:$AE$5)),COUNTIF($AG$1:AG3,AG3)))} -> Joseph | AG3: =LARGE($AE$1:$AE$5,AC3) -> 1.4154444 | AI3: 3 | AJ3: =N20 -> James | AK3: =P20 -> 1.5208333 | AL3: {=INDEX($AJ$1:$AJ$6,SMALL(IF($AK$1:$AK$6=AM3,ROW($AK$1:$AK$6)),COUNTIF($AM$1:AM3,AM3)))} -> William | AM3: =LARGE($AK$1:$AK$6,AI3) -> 1.25 | AO3: 3 | AP3: =B40 -> Laying quartz vinyl tiles on a substrate | AQ3: =C40 -> 1 | AR3: {=INDEX($AP$1:$AP$26,SMALL(IF($AQ$1:$AQ$26=AS3,ROW($AQ$1:$AQ$26)),COUNTIF($AS$1:AS3,AS3)))} -> Installation of slatted ceilings | AS3: =LARGE($AQ$1:$AQ$26,AO3) -> 49 | AT3: =$AU$1 -> 2.16
B4: Status | D4: =SUM(D2:D3) -> 1337100 | I4: =AR3 -> Installation of slatted ceilings | J4: =AS3 -> 49 | K4: =$L$1 -> 3.6 | L4: =LEFT(I4,18)&"…" -> Installation of sl… | O4: =Data!M10 -> Instagram | P4: =Q4/$Q$7 -> 0.27920228 | Q4: =IFERROR(GETPIVOTDATA(""&$O$1,Control!$M$19,""&$O$1,""&O4),0) -> 98 | W4: {=INDEX(X6:X12,WEEKDAY(W2))} -> Friday | Y4: 3 | Z4: =DATE(YEAR($W$2),MONTH($W$2),Y4) -> 46268 | AA4: 0.125 | AC4: 4 | AD4: =K21 -> Charlotte | AE4: =M21 -> 1.9393333 | AF4: {=INDEX($AD$1:$AD$5,SMALL(IF($AE$1:$AE$5=AG4,ROW($AE$1:$AE$5)),COUNTIF($AG$1:AG4,AG4)))} -> Isabella | AG4: =LARGE($AE$1:$AE$5,AC4) -> 1.3385556 | AI4: 4 | AJ4: =N21 -> Oliver | AK4: =P21 -> 0.6875 | AL4: {=INDEX($AJ$1:$AJ$6,SMALL(IF($AK$1:$AK$6=AM4,ROW($AK$1:$AK$6)),COUNTIF($AM$1:AM4,AM4)))} -> Lucas | AM4: =LARGE($AK$1:$AK$6,AI4) -> 0.77083333 | AO4: 4 | AP4: =B41 -> Laying parquet boards on a substrate | AQ4: =C41 -> 1 | AR4: {=INDEX($AP$1:$AP$26,SMALL(IF($AQ$1:$AQ$26=AS4,ROW($AQ$1:$AQ$26)),COUNTIF($AS$1:AS4,AS4)))} -> Cutting and installation of additional corners | AS4: =LARGE($AQ$1:$AQ$26,AO4) -> 27 | AT4: =$AU$1 -> 2.16
B5: Completed | C5: =IFERROR(GETPIVOTDATA("Status",Control!$P$19,""&$B$4,""&B5),0) -> 326 | I5: =AR4 -> Cutting and installation of additional corners | J5: =AS4 -> 27 | K5: =$L$1 -> 3.6 | L5: =LEFT(I5,18)&"…" -> Cutting and instal… | O5: =Data!M11 -> YouTube | P5: =Q5/$Q$7 -> 0.24216524 | Q5: =IFERROR(GETPIVOTDATA(""&$O$1,Control!$M$19,""&$O$1,""&O5),0) -> 85 | Y5: 4 | Z5: =DATE(YEAR($W$2),MONTH($W$2),Y5) -> 46269 | AA5: 0.16666667 | AC5: 5 | AD5: =K22 -> Jacob | AE5: =M22 -> 1.0721111 | AF5: {=INDEX($AD$1:$AD$5,SMALL(IF($AE$1:$AE$5=AG5,ROW($AE$1:$AE$5)),COUNTIF($AG$1:AG5,AG5)))} -> Jacob | AG5: =LARGE($AE$1:$AE$5,AC5) -> 1.0721111 | AI5: 5 | AJ5: =N22 -> Lucas | AK5: =P22 -> 0.77083333 | AL5: {=INDEX($AJ$1:$AJ$6,SMALL(IF($AK$1:$AK$6=AM5,ROW($AK$1:$AK$6)),COUNTIF($AM$1:AM5,AM5)))} -> Sofia | AM5: =LARGE($AK$1:$AK$6,AI5) -> 0.77083333 | AO5: 5 | AP5: =B42 -> Laying solid boards | AQ5: =C42 -> 25 | AR5: {=INDEX($AP$1:$AP$26,SMALL(IF($AQ$1:$AQ$26=AS5,ROW($AQ$1:$AQ$26)),COUNTIF($AS$1:AS5,AS5)))} -> Laying linoleum with glue | AS5: =LARGE($AQ$1:$AQ$26,AO5) -> 26 | AT5: =$AU$1 -> 2.16
B6: Canceled | C6: =IFERROR(GETPIVOTDATA("Status",Control!$P$19,""&$B$4,""&B6),0) -> 18 | I6: =AR5 -> Laying linoleum with glue | J6: =AS5 -> 26 | K6: =$L$1 -> 3.6 | L6: =LEFT(I6,18)&"…" -> Laying linoleum wi… | O6: =Data!M12 -> WhatsApp | P6: =Q6/$Q$7 -> 0.11965812 | Q6: =IFERROR(GETPIVOTDATA(""&$O$1,Control!$M$19,""&$O$1,""&O6),0) -> 42 | W6: January | X6: Sunday | Y6: 5 | Z6: =DATE(YEAR($W$2),MONTH($W$2),Y6) -> 46270 | AA6: 0.20833333 | AB6: Managers Top | AI6: 6 | AJ6: =N23 -> Sofia | AK6: =P23 -> 0.77083333 | AL6: {=INDEX($AJ$1:$AJ$6,SMALL(IF($AK$1:$AK$6=AM6,ROW($AK$1:$AK$6)),COUNTIF($AM$1:AM6,AM6)))} -> Oliver | AM6: =LARGE($AK$1:$AK$6,AI6) -> 0.6875 | AO6: 6 | AP6: =B43 -> Installation of ceiling plinth | AQ6: =C43 -> 3 | AR6: {=INDEX($AP$1:$AP$26,SMALL(IF($AQ$1:$AQ$26=AS6,ROW($AQ$1:$AQ$26)),COUNTIF($AS$1:AS6,AS6)))} -> Laying solid boards | AS6: =LARGE($AQ$1:$AQ$26,AO6) -> 25 | AT6: =$AU$1 -> 2.16
B7: Running | C7: =IFERROR(GETPIVOTDATA("Status",Control!$P$19,""&$B$4,""&B7),0) -> 7 | I7: Total | J7: =SUM(J2:J6) -> 223 | Q7: =SUM(Q2:Q6) -> 351 | W7: February | X7: Monday | Y7: 6 | Z7: =DATE(YEAR($W$2),MONTH($W$2),Y7) -> 46271 | AA7: 0.25 | AH7: Masters Top | AO7: 7 | AP7: =B44 -> Cutting and installation of additional corners | AQ7: =C44 -> 27 | AR7: {=INDEX($AP$1:$AP$26,SMALL(IF($AQ$1:$AQ$26=AS7,ROW($AQ$1:$AQ$26)),COUNTIF($AS$1:AS7,AS7)))} -> Installation of PVC skirting boards | AS7: =LARGE($AQ$1:$AQ$26,AO7) -> 24 | AT7: =$AU$1 -> 2.16
L8: KPI | N8: 0.1 | O8: 0.03 | R8: Personnel | W8: March | X8: Tuesday | Y8: 7 | Z8: =DATE(YEAR($W$2),MONTH($W$2),Y8) -> 46272 | AA8: 0.29166667 | AO8: 8 | AP8: =B45 -> Dismantling the balcony block | AQ8: =C45 -> 1 | AR8: {=INDEX($AP$1:$AP$26,SMALL(IF($AQ$1:$AQ$26=AS8,ROW($AQ$1:$AQ$26)),COUNTIF($AS$1:AS8,AS8)))} -> Dismantling the window block | AS8: =LARGE($AQ$1:$AQ$26,AO8) -> 22 | AT8: =$AU$1 -> 2.16
E9: =MAX(D11:D22)*0.05 -> 7250 | H9: =MAX(D11:D22)*0.5 -> 72500 | K9: Indent Left | L9: =T10&"s" -> Masters | M9: =T11&"s" -> Managers | N9: Indent Center | O9: Indents | P9: Indent Right | R9: =L9 -> Masters | S9: =M9 -> Managers | T9: Job Titles | U9: State | W9: April | X9: Wednesday | Y9: 8 | Z9: =DATE(YEAR($W$2),MONTH($W$2),Y9) -> 46273 | AA9: 0.33333333 | AO9: 9 | AP9: =B46 -> Removing the front door | AQ9: =C46 -> 1 | AR9: {=INDEX($AP$1:$AP$26,SMALL(IF($AQ$1:$AQ$26=AS9,ROW($AQ$1:$AQ$26)),COUNTIF($AS$1:AS9,AS9)))} -> Laying quartz vinyl tiles with glue | AS9: =LARGE($AQ$1:$AQ$26,AO9) -> 22 | AT9: =$AU$1 -> 2.16
B10: Number | C10: Month | D10: Total | E10: Indent | F10: Selected M | G10: Selected I | H10: Indent2 | I10: Cost | J10: =SUM(K10:O10) -> 0.87010542 | K10: =0.5-L10 -> 0.24010542 | L10: =AG1/$L$15/2 -> 0.25989458 | M10: =AM1/$L$15/2 -> 0.24010542 | N10: =$N$8 -> 0.1 | O10: =$O$8 -> 0.03 | P10: {=MAX($J$10:$J$14-J10)} -> 0 | R10: =Data!E4 -> Jack | S10: =Data!H4 -> Isabella | T10: =Data!K4 -> Master | U10: fired | W10: May | X10: Thursday | Y10: 9 | Z10: =DATE(YEAR($W$2),MONTH($W$2),Y10) -> 46274 | AA10: 0.375 | AO10: 10 | AP10: =B47 -> Removing the shower tray | AQ10: =C47 -> 1 | AR10: {=INDEX($AP$1:$AP$26,SMALL(IF($AQ$1:$AQ$26=AS10,ROW($AQ$1:$AQ$26)),COUNTIF($AS$1:AS10,AS10)))} -> Threshold installation | AS10: =LARGE($AQ$1:$AQ$26,AO10) -> 21 | AT10: =$AU$1 -> 2.16
B11: 1 | C11: JAN | D11: =GETPIVOTDATA(""&$D$10,Control!$A$3,""&$C$10,""&C11) -> 77600 | E11: =$E$9 -> 7250 | F11: =IFERROR(GETPIVOTDATA(""&$D$10,Control!$A$19,""&$C$10,""&C11),0) -> 77600 | G11: =IF(F11>0,E11,0) -> 7250 | H11: =D11+$H$9 -> 150100 | I11: =GETPIVOTDATA(""&$I$10,Control!$A$3,""&$C$10,""&C11) -> 75137 | J11: =SUM(K11:O11) -> 0.83381042 | K11: =0.5-L11 -> 0.27715239 | L11: =AG2/$L$15/2 -> 0.22284761 | M11: =AM2/$L$15/2 -> 0.20381042 | N11: =$N$8 -> 0.1 | O11: =$O$8 -> 0.03 | P11: {=MAX($J$10:$J$14-J11)} -> 0.036295006 | R11: =Data!E5 -> William | S11: =Data!H5 -> Joseph | T11: =Data!K5 -> Manager | W11: June | X11: Friday | Y11: 10 | Z11: =DATE(YEAR($W$2),MONTH($W$2),Y11) -> 46275 | AA11: 0.41666667 | AO11: 11 | AP11: =B48 -> Removing the sink | AQ11: =C48 -> 0 | AR11: {=INDEX($AP$1:$AP$26,SMALL(IF($AQ$1:$AQ$26=AS11,ROW($AQ$1:$AQ$26)),COUNTIF($AS$1:AS11,AS11)))} -> Installation of ceiling plinth | AS11: =LARGE($AQ$1:$AQ$26,AO11) -> 3 | AT11: =$AU$1 -> 2.16
B12: 2 | C12: FEB | D12: =GETPIVOTDATA(""&$D$10,Control!$A$3,""&$C$10,""&C12) -> 95100 | E12: =$E$9 -> 7250 | F12: =IFERROR(GETPIVOTDATA(""&$D$10,Control!$A$19,""&$C$10,""&C12),0) -> 95100 | G12: =IF(F12>0,E12,0) -> 7250 | H12: =D12+$H$9 -> 167600 | I12: =GETPIVOTDATA(""&$I$10,Control!$A$3,""&$C$10,""&C12) -> 102667 | J12: =SUM(K12:O12) -> 0.79751541 | K12: =0.5-L12 -> 0.31031299 | L12: =AG3/$L$15/2 -> 0.18968701 | M12: =AM3/$L$15/2 -> 0.16751541 | N12: =$N$8 -> 0.1 | O12: =$O$8 -> 0.03 | P12: {=MAX($J$10:$J$14-J12)} -> 0.072590012 | R12: =Data!E6 -> James | S12: =Data!H6 -> Liam | W12: July | X12: Saturday | Y12: 11 | Z12: =DATE(YEAR($W$2),MONTH($W$2),Y12) -> 46276 | AA12: 0.45833333 | AO12: 12 | AP12: =B49 -> Dismantling the window block | AQ12: =C49 -> 22 | AR12: {=INDEX($AP$1:$AP$26,SMALL(IF($AQ$1:$AQ$26=AS12,ROW($AQ$1:$AQ$26)),COUNTIF($AS$1:AS12,AS12)))} -> Application of decorative plaster | AS12: =LARGE($AQ$1:$AQ$26,AO12) -> 2 | AT12: =$AU$1 -> 2.16
B13: 3 | C13: MAR | D13: =GETPIVOTDATA(""&$D$10,Control!$A$3,""&$C$10,""&C13) -> 109600 | E13: =$E$9 -> 7250 | F13: =IFERROR(GETPIVOTDATA(""&$D$10,Control!$A$19,""&$C$10,""&C13),0) -> 109600 | G13: =IF(F13>0,E13,0) -> 7250 | H13: =D13+$H$9 -> 182100 | I13: =GETPIVOTDATA(""&$I$10,Control!$A$3,""&$C$10,""&C13) -> 111307 | J13: =SUM(K13:O13) -> 0.73330117 | K13: =0.5-L13 -> 0.32061705 | L13: =AG4/$L$15/2 -> 0.17938295 | M13: =AM4/$L$15/2 -> 0.10330117 | N13: =$N$8 -> 0.1 | O13: =$O$8 -> 0.03 | P13: {=MAX($J$10:$J$14-J13)} -> 0.13680425 | R13: =Data!E7 -> Oliver | S13: =Data!H7 -> Charlotte | W13: August | Y13: 12 | Z13: =DATE(YEAR($W$2),MONTH($W$2),Y13) -> 46277 | AA13: 0.5 | AO13: 13 | AP13: =B50 -> Laying ceramic tiles, porcelain tiles on the floor with grout | AQ13: =C50 -> 0 | AR13: {=INDEX($AP$1:$AP$26,SMALL(IF($AQ$1:$AQ$26=AS13,ROW($AQ$1:$AQ$26)),COUNTIF($AS$1:AS13,AS13)))} -> Dismantling the balcony block | AS13: =LARGE($AQ$1:$AQ$26,AO13) -> 1 | AT13: =$AU$1 -> 2.16
B14: 4 | C14: APR | D14: =GETPIVOTDATA(""&$D$10,Control!$A$3,""&$C$10,""&C14) -> 117100 | E14: =$E$9 -> 7250 | F14: =IFERROR(GETPIVOTDATA(""&$D$10,Control!$A$19,""&$C$10,""&C14),0) -> 117100 | G14: =IF(F14>0,E14,0) -> 7250 | H14: =D14+$H$9 -> 189600 | I14: =GETPIVOTDATA(""&$I$10,Control!$A$3,""&$C$10,""&C14) -> 110749 | J14: =SUM(K14:O14) -> 0.73330117 | K14: =0.5-L14 -> 0.35632389 | L14: =AG5/$L$15/2 -> 0.14367611 | M14: =AM5/$L$15/2 -> 0.10330117 | N14: =$N$8 -> 0.1 | O14: =$O$8 -> 0.03 | P14: {=MAX($J$10:$J$14-J14)} -> 0.13680425 | R14: =Data!E8 -> Lucas | S14: =Data!H8 -> Jacob | W14: September | Y14: 13 | Z14: =DATE(YEAR($W$2),MONTH($W$2),Y14) -> 46278 | AA14: 0.54166667 | AO14: 14 | AP14: =B51 -> Application of decorative plaster | AQ14: =C51 -> 2 | AR14: {=INDEX($AP$1:$AP$26,SMALL(IF($AQ$1:$AQ$26=AS14,ROW($AQ$1:$AQ$26)),COUNTIF($AS$1:AS14,AS14)))} -> Laying quartz vinyl tiles on a substrate | AS14: =LARGE($AQ$1:$AQ$26,AO14) -> 1 | AT14: =$AU$1 -> 2.16
B15: 5 | C15: MAY | D15: =GETPIVOTDATA(""&$D$10,Control!$A$3,""&$C$10,""&C15) -> 109400 | E15: =$E$9 -> 7250 | F15: =IFERROR(GETPIVOTDATA(""&$D$10,Control!$A$19,""&$C$10,""&C15),0) -> 109400 | G15: =IF(F15>0,E15,0) -> 7250 | H15: =D15+$H$9 -> 181900 | I15: =GETPIVOTDATA(""&$I$10,Control!$A$3,""&$C$10,""&C15) -> 99947 | L15: =MAX(AG1:AG5)+MAX(AM1:AM6) -> 3.731 | R15: =Data!E9 -> Sofia | W15: October | Y15: 14 | Z15: =DATE(YEAR($W$2),MONTH($W$2),Y15) -> 46279 | AA15: 0.58333333 | AO15: 15 | AP15: =B52 -> Wallpapering | AQ15: =C52 -> 1 | AR15: {=INDEX($AP$1:$AP$26,SMALL(IF($AQ$1:$AQ$26=AS15,ROW($AQ$1:$AQ$26)),COUNTIF($AS$1:AS15,AS15)))} -> Laying parquet boards on a substrate | AS15: =LARGE($AQ$1:$AQ$26,AO15) -> 1 | AT15: =$AU$1 -> 2.16
B16: 6 | C16: JUN | D16: =GETPIVOTDATA(""&$D$10,Control!$A$3,""&$C$10,""&C16) -> 95600 | E16: =$E$9 -> 7250 | F16: =IFERROR(GETPIVOTDATA(""&$D$10,Control!$A$19,""&$C$10,""&C16),0) -> 95600 | G16: =IF(F16>0,E16,0) -> 7250 | H16: =D16+$H$9 -> 168100 | I16: =GETPIVOTDATA(""&$I$10,Control!$A$3,""&$C$10,""&C16) -> 98003 | W16: November | Y16: 15 | Z16: =DATE(YEAR($W$2),MONTH($W$2),Y16) -> 46280 | AA16: 0.625 | AO16: 16 | AP16: =B53 -> Laying plywood in 1 layer | AQ16: =C53 -> 1 | AR16: {=INDEX($AP$1:$AP$26,SMALL(IF($AQ$1:$AQ$26=AS16,ROW($AQ$1:$AQ$26)),COUNTIF($AS$1:AS16,AS16)))} -> Dismantling the balcony block | AS16: =LARGE($AQ$1:$AQ$26,AO16) -> 1 | AT16: =$AU$1 -> 2.16
B17: 7 | C17: JUL | D17: =GETPIVOTDATA(""&$D$10,Control!$A$3,""&$C$10,""&C17) -> 89700 | E17: =$E$9 -> 7250 | F17: =IFERROR(GETPIVOTDATA(""&$D$10,Control!$A$19,""&$C$10,""&C17),0) -> 89700 | G17: =IF(F17>0,E17,0) -> 7250 | H17: =D17+$H$9 -> 162200 | I17: =GETPIVOTDATA(""&$I$10,Control!$A$3,""&$C$10,""&C17) -> 98707 | K17: =T11 -> Manager | L17: Total | M17: KPI | N17: =T10 -> Master | O17: Client rating | P17: KPI | Q17: Order | R17: Payment Method | W17: December | Y17: 16 | Z17: =DATE(YEAR($W$2),MONTH($W$2),Y17) -> 46281 | AA17: 0.66666667 | AO17: 17 | AP17: =B54 -> Laying linoleum with glue | AQ17: =C54 -> 26 | AR17: {=INDEX($AP$1:$AP$26,SMALL(IF($AQ$1:$AQ$26=AS17,ROW($AQ$1:$AQ$26)),COUNTIF($AS$1:AS17,AS17)))} -> Removing the front door | AS17: =LARGE($AQ$1:$AQ$26,AO17) -> 1 | AT17: =$AU$1 -> 2.16
B18: 8 | C18: AUG | D18: =GETPIVOTDATA(""&$D$10,Control!$A$3,""&$C$10,""&C18) -> 102600 | E18: =$E$9 -> 7250 | F18: =IFERROR(GETPIVOTDATA(""&$D$10,Control!$A$19,""&$C$10,""&C18),0) -> 102600 | G18: =IF(F18>0,E18,0) -> 7250 | H18: =D18+$H$9 -> 175100 | I18: =GETPIVOTDATA(""&$I$10,Control!$A$3,""&$C$10,""&C18) -> 111153 | K18: =S10 -> Isabella | L18: =IFERROR(GETPIVOTDATA(""&$L$17,Control!$G$19,""&$K$17,""&K18),0) -> 240940 | M18: =L18/$L$31 -> 1.3385556 | N18: =R10 -> Jack | O18: =IFERROR(GETPIVOTDATA(""&$O$17,Control!$J$19,""&$N$17,""&N18),0) -> 86 | P18: =O18/$N$31 -> 1.7916667 | Q18: Get Price | R18: =Data!M4 -> Cash Money | Y18: 17 | Z18: =DATE(YEAR($W$2),MONTH($W$2),Y18) -> 46282 | AA18: 0.70833333 | AO18: 18 | AP18: =B55 -> Removing the shower cabin | AQ18: =C55 -> 1 | AR18: {=INDEX($AP$1:$AP$26,SMALL(IF($AQ$1:$AQ$26=AS18,ROW($AQ$1:$AQ$26)),COUNTIF($AS$1:AS18,AS18)))} -> Removing the shower tray | AS18: =LARGE($AQ$1:$AQ$26,AO18) -> 1 | AT18: =$AU$1 -> 2.16
B19: 9 | C19: SEP | D19: =GETPIVOTDATA(""&$D$10,Control!$A$3,""&$C$10,""&C19) -> 124500 | E19: =$E$9 -> 7250 | F19: =IFERROR(GETPIVOTDATA(""&$D$10,Control!$A$19,""&$C$10,""&C19),0) -> 124500 | G19: =IF(F19>0,E19,0) -> 7250 | H19: =D19+$H$9 -> 197000 | I19: =GETPIVOTDATA(""&$I$10,Control!$A$3,""&$C$10,""&C19) -> 89309 | K19: =S11 -> Joseph | L19: =IFERROR(GETPIVOTDATA(""&$L$17,Control!$G$19,""&$K$17,""&K19),0) -> 254780 | M19: =L19/$L$31 -> 1.4154444 | N19: =R11 -> William | O19: =IFERROR(GETPIVOTDATA(""&$O$17,Control!$J$19,""&$N$17,""&N19),0) -> 60 | P19: =O19/$N$31 -> 1.25 | Q19: =INDEX(Data!$C$4:$C$30,MATCH(ORDER!$D$6,Data!$B$4:$B$30,0)) -> 0 | R19: =Data!M5 -> Credit Cards | Y19: 18 | Z19: =DATE(YEAR($W$2),MONTH($W$2),Y19) -> 46283 | AA19: 0.75 | AO19: 19 | AP19: =B56 -> Installation of thermal vapor barrier of the ceiling | AQ19: =C56 -> 0 | AR19: {=INDEX($AP$1:$AP$26,SMALL(IF($AQ$1:$AQ$26=AS19,ROW($AQ$1:$AQ$26)),COUNTIF($AS$1:AS19,AS19)))} -> Wallpapering | AS19: =LARGE($AQ$1:$AQ$26,AO19) -> 1 | AT19: =$AU$1 -> 2.16
B20: 10 | C20: OCT | D20: =GETPIVOTDATA(""&$D$10,Control!$A$3,""&$C$10,""&C20) -> 137200 | E20: =$E$9 -> 7250 | F20: =IFERROR(GETPIVOTDATA(""&$D$10,Control!$A$19,""&$C$10,""&C20),0) -> 137200 | G20: =IF(F20>0,E20,0) -> 7250 | H20: =D20+$H$9 -> 209700 | I20: =GETPIVOTDATA(""&$I$10,Control!$A$3,""&$C$10,""&C20) -> 93153 | K20: =S12 -> Liam | L20: =IFERROR(GETPIVOTDATA(""&$L$17,Control!$G$19,""&$K$17,""&K20),0) -> 299320 | M20: =L20/$L$31 -> 1.6628889 | N20: =R12 -> James | O20: =IFERROR(GETPIVOTDATA(""&$O$17,Control!$J$19,""&$N$17,""&N20),0) -> 73 | P20: =O20/$N$31 -> 1.5208333 | Q20: =IF(ORDER!F6>0,ORDER!F6*Processing!Q19,"Error: Enetr Count") -> Error: Enetr Count | Y20: 19 | Z20: =DATE(YEAR($W$2),MONTH($W$2),Y20) -> 46284 | AA20: 0.79166667 | AO20: 20 | AP20: =B57 -> Laying quartz vinyl tiles with glue | AQ20: =C57 -> 22 | AR20: {=INDEX($AP$1:$AP$26,SMALL(IF($AQ$1:$AQ$26=AS20,ROW($AQ$1:$AQ$26)),COUNTIF($AS$1:AS20,AS20)))} -> Laying plywood in 1 layer | AS20: =LARGE($AQ$1:$AQ$26,AO20) -> 1 | AT20: =$AU$1 -> 2.16
B21: 11 | C21: NOV | D21: =GETPIVOTDATA(""&$D$10,Control!$A$3,""&$C$10,""&C21) -> 145000 | E21: =$E$9 -> 7250 | F21: =IFERROR(GETPIVOTDATA(""&$D$10,Control!$A$19,""&$C$10,""&C21),0) -> 145000 | G21: =IF(F21>0,E21,0) -> 7250 | H21: =D21+$H$9 -> 217500 | I21: =GETPIVOTDATA(""&$I$10,Control!$A$3,""&$C$10,""&C21) -> 83973 | K21: =S13 -> Charlotte | L21: =IFERROR(GETPIVOTDATA(""&$L$17,Control!$G$19,""&$K$17,""&K21),0) -> 349080 | M21: =L21/$L$31 -> 1.9393333 | N21: =R13 -> Oliver | O21: =IFERROR(GETPIVOTDATA(""&$O$17,Control!$J$19,""&$N$17,""&N21),0) -> 33 | P21: =O21/$N$31 -> 0.6875 | Y21: 20 | Z21: =DATE(YEAR($W$2),MONTH($W$2),Y21) -> 46285 | AA21: 0.83333333 | AO21: 21 | AP21: =B58 -> Threshold installation | AQ21: =C58 -> 21 | AR21: {=INDEX($AP$1:$AP$26,SMALL(IF($AQ$1:$AQ$26=AS21,ROW($AQ$1:$AQ$26)),COUNTIF($AS$1:AS21,AS21)))} -> Removing the shower cabin | AS21: =LARGE($AQ$1:$AQ$26,AO21) -> 1 | AT21: =$AU$1 -> 2.16
B22: 12 | C22: DEC | D22: =GETPIVOTDATA(""&$D$10,Control!$A$3,""&$C$10,""&C22) -> 133700 | E22: =$E$9 -> 7250 | F22: =IFERROR(GETPIVOTDATA(""&$D$10,Control!$A$19,""&$C$10,""&C22),0) -> 133700 | G22: =IF(F22>0,E22,0) -> 7250 | H22: =D22+$H$9 -> 206200 | I22: =GETPIVOTDATA(""&$I$10,Control!$A$3,""&$C$10,""&C22) -> 51384 | K22: =S14 -> Jacob | L22: =IFERROR(GETPIVOTDATA(""&$L$17,Control!$G$19,""&$K$17,""&K22),0) -> 192980 | M22: =L22/$L$31 -> 1.0721111 | N22: =R14 -> Lucas | O22: =IFERROR(GETPIVOTDATA(""&$O$17,Control!$J$19,""&$N$17,""&N22),0) -> 37 | P22: =O22/$N$31 -> 0.77083333 | Y22: 21 | Z22: =DATE(YEAR($W$2),MONTH($W$2),Y22) -> 46286 | AA22: 0.875 | AO22: 22 | AP22: =B59 -> Production and installation of suspended ceilings (matte, glossy) | AQ22: =C59 -> 0 | AR22: {=INDEX($AP$1:$AP$26,SMALL(IF($AQ$1:$AQ$26=AS22,ROW($AQ$1:$AQ$26)),COUNTIF($AS$1:AS22,AS22)))} -> Removing an interior door | AS22: =LARGE($AQ$1:$AQ$26,AO22) -> 1 | AT22: =$AU$1 -> 2.16
N23: =R15 -> Sofia | O23: =IFERROR(GETPIVOTDATA(""&$O$17,Control!$J$19,""&$N$17,""&N23),0) -> 37 | P23: =O23/$N$31 -> 0.77083333 | Y23: 22 | Z23: =DATE(YEAR($W$2),MONTH($W$2),Y23) -> 46287 | AA23: 0.91666667 | AO23: 23 | AP23: =B60 -> Wallpapering ceilings | AQ23: =C60 -> 72 | AR23: {=INDEX($AP$1:$AP$26,SMALL(IF($AQ$1:$AQ$26=AS23,ROW($AQ$1:$AQ$26)),COUNTIF($AS$1:AS23,AS23)))} -> Removing the sink | AS23: =LARGE($AQ$1:$AQ$26,AO23) -> 0 | AT23: =$AU$1 -> 2.16
Y24: 23 | Z24: =DATE(YEAR($W$2),MONTH($W$2),Y24) -> 46288 | AA24: 0.95833333 | AO24: 24 | AP24: =B61 -> Installation of PVC skirting boards | AQ24: =C61 -> 24 | AR24: {=INDEX($AP$1:$AP$26,SMALL(IF($AQ$1:$AQ$26=AS24,ROW($AQ$1:$AQ$26)),COUNTIF($AS$1:AS24,AS24)))} -> Laying ceramic tiles, porcelain tiles on the floor with grout | AS24: =LARGE($AQ$1:$AQ$26,AO24) -> 0 | AT24: =$AU$1 -> 2.16
F25: Map | Y25: 24 | Z25: =DATE(YEAR($W$2),MONTH($W$2),Y25) -> 46289 | AA25: 1 | AO25: 25 | AP25: =B62 -> Installation of slatted ceilings | AQ25: =C62 -> 49 | AR25: {=INDEX($AP$1:$AP$26,SMALL(IF($AQ$1:$AQ$26=AS25,ROW($AQ$1:$AQ$26)),COUNTIF($AS$1:AS25,AS25)))} -> Installation of thermal vapor barrier of the ceiling | AS25: =LARGE($AQ$1:$AQ$26,AO25) -> 0 | AT25: =$AU$1 -> 2.16
F26: City | G26: Done % | H26: Running % | R26: $ | S26: % | Y26: 25 | Z26: =DATE(YEAR($W$2),MONTH($W$2),Y26) -> 46290 | AO26: 26 | AP26: =B63 -> Removing an interior door | AQ26: =C63 -> 1 | AR26: {=INDEX($AP$1:$AP$26,SMALL(IF($AQ$1:$AQ$26=AS26,ROW($AQ$1:$AQ$26)),COUNTIF($AS$1:AS26,AS26)))} -> Production and installation of suspended ceilings (matte, glossy) | AS26: =LARGE($AQ$1:$AQ$26,AO26) -> 0 | AT26: =$AU$1 -> 2.16
F27: =Data!Q4 -> New York | G27: =100-H27 -> 72 | H27: 28 | Q27: Margin | R27: =T28-T29 -> 211611 | S27: =R27/T28 -> 0.15826116 | T27: =1-S27 -> 0.84173884 | U27: Visual | Y27: 26 | Z27: =DATE(YEAR($W$2),MONTH($W$2),Y27) -> 46291
F28: =Data!Q5 -> Miami | G28: =100-H28 -> 100 | H28: 0 | Q28: $ | R28: =GETPIVOTDATA("Sum of Cash",Control!$S$19) -> 490160 | S28: =GETPIVOTDATA("Sum of Card",Control!$S$19) -> 846940 | T28: =GETPIVOTDATA("Sum of Total",Control!$A$19) -> 1337100 | U28: Total cach flow | Y28: 27 | Z28: =DATE(YEAR($W$2),MONTH($W$2),Y28) -> 46292
F29: =Data!Q6 -> Chikago | G29: =100-H29 -> 28 | H29: 72 | T29: =GETPIVOTDATA("Sum of Cost",Control!$A$19) -> 1125489 | U29: Total Cost | Y29: 28 | Z29: =DATE(YEAR($W$2),MONTH($W$2),Y29) -> 46293
F30: =Data!Q7 -> Dallas | G30: =100-H30 -> 10 | H30: 90 | L30: KPI PLAN | N30: KPI PLAN | Y30: 29 | Z30: =DATE(YEAR($W$2),MONTH($W$2),Y30) -> 46294
F31: =Data!Q8 -> New Orleans | G31: =100-H31 -> 75 | H31: 25 | L31: =DSUM(KPI!A3:G39,L32,J32:K68) -> 180000 | N31: =DSUM(KPI!A3:G39,N32,J32:K68) -> 48 | Y31: 30 | Z31: =DATE(YEAR($W$2),MONTH($W$2),Y31) -> 46295
J32: Year | K32: Month | L32: Managers Sales | N32: Masters Order Quantity | P32: Year | Y32: 31 | Z32: =DATE(YEAR($W$2),MONTH($W$2),Y32) -> 46296
J33: =Control!$A$36 -> 2025 | K33: =Control!A42 -> JAN | P33: =Control!A36 -> 2025
J34: =Control!$A$36 -> 2025 | K34: =Control!A43 -> FEB | P34: =Control!A37 -> 0 | Q34: SALARY
J35: =Control!$A$36 -> 2025 | K35: =Control!A44 -> MAR | P35: =Control!A38 -> 0 | T35: 1 | U35: 2 | V35: 3
J36: =Control!$A$36 -> 2025 | K36: =Control!A45 -> APR | T36: =IF(IFERROR(MATCH(T37,$P$33:$P$35,0),0),T35,NA()) -> #N/A | U36: =IF(IFERROR(MATCH(U37,$P$33:$P$35,0),0),U35,NA()) -> #N/A | V36: =IF(IFERROR(MATCH(V37,$P$33:$P$35,0),0),V35,NA()) -> 3
B37: Service | J37: =Control!$A$36 -> 2025 | K37: =Control!A46 -> MAY | Q37: Count Years | R37: Count Month | S37: Employee | T37: 2023 | U37: 2024 | V37: 2025 | W37: Total | X37: =SUM(W38:W48) -> 304700 | Y37: Prize | Z37: Rank | AA37: 1 | AB37: 2 | AC37: 3 | AD37: 4 | AE37: 5 | AF37: 6 | AG37: 7 | AH37: 8 | AI37: 9 | AJ37: 10
B38: =Data!B4 -> Dismantling the balcony block | C38: =IFERROR(GETPIVOTDATA(""&$B$37,Control!$G$41,""&$B$37,""&B38),0) -> 1 | J38: =Control!$A$36 -> 2025 | K38: =Control!A47 -> JUN | Q38: {=SUM(1/COUNTIF(J33:J68,J33:J68))-1} -> 1 | R38: {=SUM(1/COUNTIF(K33:K68,K33:K68))-1} -> 11 | S38: ='Employee Database'!B4 -> Jack | T38: {=IFERROR(INDEX('Employee Database'!$F$4:$H$14,MATCH(Processing!$S38,'Employee Database'!$B$4:$B$14,0),T$36)*$R$38,0)} -> 0 | U38: {=IFERROR(INDEX('Employee Database'!$F$4:$H$14,MATCH(Processing!$S38,'Employee Database'!$B$4:$B$14,0),U$36)*$R$38,0)} -> 0 | V38: {=IFERROR(INDEX('Employee Database'!$F$4:$H$14,MATCH(Processing!$S38,'Employee Database'!$B$4:$B$14,0),V$36)*$R$38,0)} -> 24200 | W38: =SUM(T38:V38) -> 24200 | X38: =INDEX(_xlfn.VSTACK($P$18:$P$23,$M$18:$M$22),MATCH(S38,$S$38:$S$48,0),1) -> #NAME? | Y38: =IF(X38>100%,CHOOSE(SUM(X38>=100%,X38>130%),3%,5%)*W38+W38,W38) -> #NAME? | Z38: =ROUND(COUNTIF($X$38:$X$48,">=100%")/COUNT($X$38:$X$48),1)*10 -> #DIV/0! | AA38: =IF($Z$38<AA37,0,0.5) -> #DIV/0! | AB38: =IF($Z$38<AB37,0,0.5) -> #DIV/0! | AC38: =IF($Z$38<AC37,0,0.5) -> #DIV/0! | AD38: =IF($Z$38<AD37,0,0.5) -> #DIV/0! | AE38: =IF($Z$38<AE37,0,0.5) -> #DIV/0! | AF38: =IF($Z$38<AF37,0,0.5) -> #DIV/0! | AG38: =IF($Z$38<AG37,0,0.5) -> #DIV/0! | AH38: =IF($Z$38<AH37,0,0.5) -> #DIV/0! | ... AJ38: =IF($Z$38<AJ37,0,0.5) -> #DIV/0!
B39: =Data!B5 -> Laying parquet boards with glue | C39: =IFERROR(GETPIVOTDATA(""&$B$37,Control!$G$41,""&$B$37,""&B39),0) -> 49 | J39: =Control!$A$36 -> 2025 | K39: =Control!A48 -> JUL | S39: ='Employee Database'!B5 -> William | T39: {=IFERROR(INDEX('Employee Database'!$F$4:$H$14,MATCH(Processing!$S39,'Employee Database'!$B$4:$B$14,0),T$36)*$R$38,0)} -> 0 | U39: {=IFERROR(INDEX('Employee Database'!$F$4:$H$14,MATCH(Processing!$S39,'Employee Database'!$B$4:$B$14,0),U$36)*$R$38,0)} -> 0 | V39: {=IFERROR(INDEX('Employee Database'!$F$4:$H$14,MATCH(Processing!$S39,'Employee Database'!$B$4:$B$14,0),V$36)*$R$38,0)} -> 24200 | W39: =SUM(T39:V39) -> 24200 | X39: =INDEX(_xlfn.VSTACK($P$18:$P$23,$M$18:$M$22),MATCH(S39,$S$38:$S$48,0),1) -> #NAME? | Y39: =IF(X39>100%,CHOOSE(SUM(X39>=100%,X39>130%),3%,5%)*W39+W39,W39) -> #NAME?
B40: =Data!B6 -> Laying quartz vinyl tiles on a substrate | C40: =IFERROR(GETPIVOTDATA(""&$B$37,Control!$G$41,""&$B$37,""&B40),0) -> 1 | J40: =Control!$A$36 -> 2025 | K40: =Control!A49 -> AUG | S40: ='Employee Database'!B6 -> James | T40: {=IFERROR(INDEX('Employee Database'!$F$4:$H$14,MATCH(Processing!$S40,'Employee Database'!$B$4:$B$14,0),T$36)*$R$38,0)} -> 0 | U40: {=IFERROR(INDEX('Employee Database'!$F$4:$H$14,MATCH(Processing!$S40,'Employee Database'!$B$4:$B$14,0),U$36)*$R$38,0)} -> 0 | V40: {=IFERROR(INDEX('Employee Database'!$F$4:$H$14,MATCH(Processing!$S40,'Employee Database'!$B$4:$B$14,0),V$36)*$R$38,0)} -> 24200 | W40: =SUM(T40:V40) -> 24200 | X40: =INDEX(_xlfn.VSTACK($P$18:$P$23,$M$18:$M$22),MATCH(S40,$S$38:$S$48,0),1) -> #NAME? | Y40: =IF(X40>100%,CHOOSE(SUM(X40>=100%,X40>130%),3%,5%)*W40+W40,W40) -> #NAME?
B41: =Data!B7 -> Laying parquet boards on a substrate | C41: =IFERROR(GETPIVOTDATA(""&$B$37,Control!$G$41,""&$B$37,""&B41),0) -> 1 | J41: =Control!$A$36 -> 2025 | K41: =Control!A50 -> SEP | S41: ='Employee Database'!B7 -> Isabella | T41: {=IFERROR(INDEX('Employee Database'!$F$4:$H$14,MATCH(Processing!$S41,'Employee Database'!$B$4:$B$14,0),T$36)*$R$38,0)} -> 0 | U41: {=IFERROR(INDEX('Employee Database'!$F$4:$H$14,MATCH(Processing!$S41,'Employee Database'!$B$4:$B$14,0),U$36)*$R$38,0)} -> 0 | V41: {=IFERROR(INDEX('Employee Database'!$F$4:$H$14,MATCH(Processing!$S41,'Employee Database'!$B$4:$B$14,0),V$36)*$R$38,0)} -> 31900 | W41: =SUM(T41:V41) -> 31900 | X41: =INDEX(_xlfn.VSTACK($P$18:$P$23,$M$18:$M$22),MATCH(S41,$S$38:$S$48,0),1) -> #NAME? | Y41: =IF(X41>100%,CHOOSE(SUM(X41>=100%,X41>130%),3%,5%)*W41+W41,W41) -> #NAME?
B42: =Data!B8 -> Laying solid boards | C42: =IFERROR(GETPIVOTDATA(""&$B$37,Control!$G$41,""&$B$37,""&B42),0) -> 25 | J42: =Control!$A$36 -> 2025 | K42: =Control!A51 -> OCT | S42: ='Employee Database'!B8 -> Joseph | T42: {=IFERROR(INDEX('Employee Database'!$F$4:$H$14,MATCH(Processing!$S42,'Employee Database'!$B$4:$B$14,0),T$36)*$R$38,0)} -> 0 | U42: {=IFERROR(INDEX('Employee Database'!$F$4:$H$14,MATCH(Processing!$S42,'Employee Database'!$B$4:$B$14,0),U$36)*$R$38,0)} -> 0 | V42: {=IFERROR(INDEX('Employee Database'!$F$4:$H$14,MATCH(Processing!$S42,'Employee Database'!$B$4:$B$14,0),V$36)*$R$38,0)} -> 31900 | W42: =SUM(T42:V42) -> 31900 | X42: =INDEX(_xlfn.VSTACK($P$18:$P$23,$M$18:$M$22),MATCH(S42,$S$38:$S$48,0),1) -> #NAME? | Y42: =IF(X42>100%,CHOOSE(SUM(X42>=100%,X42>130%),3%,5%)*W42+W42,W42) -> #NAME?
B43: =Data!B9 -> Installation of ceiling plinth | C43: =IFERROR(GETPIVOTDATA(""&$B$37,Control!$G$41,""&$B$37,""&B43),0) -> 3 | J43: =Control!$A$36 -> 2025 | K43: =Control!A52 -> NOV | S43: ='Employee Database'!B9 -> Liam | T43: {=IFERROR(INDEX('Employee Database'!$F$4:$H$14,MATCH(Processing!$S43,'Employee Database'!$B$4:$B$14,0),T$36)*$R$38,0)} -> 0 | U43: {=IFERROR(INDEX('Employee Database'!$F$4:$H$14,MATCH(Processing!$S43,'Employee Database'!$B$4:$B$14,0),U$36)*$R$38,0)} -> 0 | V43: {=IFERROR(INDEX('Employee Database'!$F$4:$H$14,MATCH(Processing!$S43,'Employee Database'!$B$4:$B$14,0),V$36)*$R$38,0)} -> 31900 | W43: =SUM(T43:V43) -> 31900 | X43: =INDEX(_xlfn.VSTACK($P$18:$P$23,$M$18:$M$22),MATCH(S43,$S$38:$S$48,0),1) -> #NAME? | Y43: =IF(X43>100%,CHOOSE(SUM(X43>=100%,X43>130%),3%,5%)*W43+W43,W43) -> #NAME?
B44: =Data!B10 -> Cutting and installation of additional corners | C44: =IFERROR(GETPIVOTDATA(""&$B$37,Control!$G$41,""&$B$37,""&B44),0) -> 27 | J44: =Control!$A$36 -> 2025 | K44: =Control!A53 -> DEC | S44: ='Employee Database'!B10 -> Oliver | T44: {=IFERROR(INDEX('Employee Database'!$F$4:$H$14,MATCH(Processing!$S44,'Employee Database'!$B$4:$B$14,0),T$36)*$R$38,0)} -> 0 | U44: {=IFERROR(INDEX('Employee Database'!$F$4:$H$14,MATCH(Processing!$S44,'Employee Database'!$B$4:$B$14,0),U$36)*$R$38,0)} -> 0 | V44: {=IFERROR(INDEX('Employee Database'!$F$4:$H$14,MATCH(Processing!$S44,'Employee Database'!$B$4:$B$14,0),V$36)*$R$38,0)} -> 24200 | W44: =SUM(T44:V44) -> 24200 | X44: =INDEX(_xlfn.VSTACK($P$18:$P$23,$M$18:$M$22),MATCH(S44,$S$38:$S$48,0),1) -> #NAME? | Y44: =IF(X44>100%,CHOOSE(SUM(X44>=100%,X44>130%),3%,5%)*W44+W44,W44) -> #NAME?
B45: =Data!B11 -> Dismantling the balcony block | C45: =IFERROR(GETPIVOTDATA(""&$B$37,Control!$G$41,""&$B$37,""&B45),0) -> 1 | J45: =Control!$A$37 -> 0 | K45: =Control!A42 -> JAN | S45: ='Employee Database'!B11 -> Lucas | T45: {=IFERROR(INDEX('Employee Database'!$F$4:$H$14,MATCH(Processing!$S45,'Employee Database'!$B$4:$B$14,0),T$36)*$R$38,0)} -> 0 | U45: {=IFERROR(INDEX('Employee Database'!$F$4:$H$14,MATCH(Processing!$S45,'Employee Database'!$B$4:$B$14,0),U$36)*$R$38,0)} -> 0 | V45: {=IFERROR(INDEX('Employee Database'!$F$4:$H$14,MATCH(Processing!$S45,'Employee Database'!$B$4:$B$14,0),V$36)*$R$38,0)} -> 24200 | W45: =SUM(T45:V45) -> 24200 | X45: =INDEX(_xlfn.VSTACK($P$18:$P$23,$M$18:$M$22),MATCH(S45,$S$38:$S$48,0),1) -> #NAME? | Y45: =IF(X45>100%,CHOOSE(SUM(X45>=100%,X45>130%),3%,5%)*W45+W45,W45) -> #NAME?
B46: =Data!B12 -> Removing the front door | C46: =IFERROR(GETPIVOTDATA(""&$B$37,Control!$G$41,""&$B$37,""&B46),0) -> 1 | J46: =Control!$A$37 -> 0 | K46: =Control!A43 -> FEB | S46: ='Employee Database'!B12 -> Sofia | T46: {=IFERROR(INDEX('Employee Database'!$F$4:$H$14,MATCH(Processing!$S46,'Employee Database'!$B$4:$B$14,0),T$36)*$R$38,0)} -> 0 | U46: {=IFERROR(INDEX('Employee Database'!$F$4:$H$14,MATCH(Processing!$S46,'Employee Database'!$B$4:$B$14,0),U$36)*$R$38,0)} -> 0 | V46: {=IFERROR(INDEX('Employee Database'!$F$4:$H$14,MATCH(Processing!$S46,'Employee Database'!$B$4:$B$14,0),V$36)*$R$38,0)} -> 24200 | W46: =SUM(T46:V46) -> 24200 | X46: =INDEX(_xlfn.VSTACK($P$18:$P$23,$M$18:$M$22),MATCH(S46,$S$38:$S$48,0),1) -> #NAME? | Y46: =IF(X46>100%,CHOOSE(SUM(X46>=100%,X46>130%),3%,5%)*W46+W46,W46) -> #NAME?
B47: =Data!B13 -> Removing the shower tray | C47: =IFERROR(GETPIVOTDATA(""&$B$37,Control!$G$41,""&$B$37,""&B47),0) -> 1 | J47: =Control!$A$37 -> 0 | K47: =Control!A44 -> MAR | S47: ='Employee Database'!B13 -> Charlotte | T47: {=IFERROR(INDEX('Employee Database'!$F$4:$H$14,MATCH(Processing!$S47,'Employee Database'!$B$4:$B$14,0),T$36)*$R$38,0)} -> 0 | U47: {=IFERROR(INDEX('Employee Database'!$F$4:$H$14,MATCH(Processing!$S47,'Employee Database'!$B$4:$B$14,0),U$36)*$R$38,0)} -> 0 | V47: {=IFERROR(INDEX('Employee Database'!$F$4:$H$14,MATCH(Processing!$S47,'Employee Database'!$B$4:$B$14,0),V$36)*$R$38,0)} -> 31900 | W47: =SUM(T47:V47) -> 31900 | X47: =INDEX(_xlfn.VSTACK($P$18:$P$23,$M$18:$M$22),MATCH(S47,$S$38:$S$48,0),1) -> #NAME? | Y47: =IF(X47>100%,CHOOSE(SUM(X47>=100%,X47>130%),3%,5%)*W47+W47,W47) -> #NAME?
B48: =Data!B14 -> Removing the sink | C48: =IFERROR(GETPIVOTDATA(""&$B$37,Control!$G$41,""&$B$37,""&B48),0) -> 0 | J48: =Control!$A$37 -> 0 | K48: =Control!A45 -> APR | S48: ='Employee Database'!B14 -> Jacob | T48: {=IFERROR(INDEX('Employee Database'!$F$4:$H$14,MATCH(Processing!$S48,'Employee Database'!$B$4:$B$14,0),T$36)*$R$38,0)} -> 0 | U48: {=IFERROR(INDEX('Employee Database'!$F$4:$H$14,MATCH(Processing!$S48,'Employee Database'!$B$4:$B$14,0),U$36)*$R$38,0)} -> 0 | V48: {=IFERROR(INDEX('Employee Database'!$F$4:$H$14,MATCH(Processing!$S48,'Employee Database'!$B$4:$B$14,0),V$36)*$R$38,0)} -> 31900 | W48: =SUM(T48:V48) -> 31900 | X48: =INDEX(_xlfn.VSTACK($P$18:$P$23,$M$18:$M$22),MATCH(S48,$S$38:$S$48,0),1) -> #NAME? | Y48: =IF(X48>100%,CHOOSE(SUM(X48>=100%,X48>130%),3%,5%)*W48+W48,W48) -> #NAME?
B49: =Data!B15 -> Dismantling the window block | C49: =IFERROR(GETPIVOTDATA(""&$B$37,Control!$G$41,""&$B$37,""&B49),0) -> 22 | J49: =Control!$A$37 -> 0 | K49: =Control!A46 -> MAY | W49: =SUM(Y38:Y48) -> #NAME?
B50: =Data!B16 -> Laying ceramic tiles, porcelain tiles on the floor with grout | C50: =IFERROR(GETPIVOTDATA(""&$B$37,Control!$G$41,""&$B$37,""&B50),0) -> 0 | J50: =Control!$A$37 -> 0 | K50: =Control!A47 -> JUN
B51: =Data!B17 -> Application of decorative plaster | C51: =IFERROR(GETPIVOTDATA(""&$B$37,Control!$G$41,""&$B$37,""&B51),0) -> 2 | J51: =Control!$A$37 -> 0 | K51: =Control!A48 -> JUL | V51: Total Order Today
B52: =Data!B18 -> Wallpapering | C52: =IFERROR(GETPIVOTDATA(""&$B$37,Control!$G$41,""&$B$37,""&B52),0) -> 1 | J52: =Control!$A$37 -> 0 | K52: =Control!A49 -> AUG | V52: =SUM('ALL ORDERS'!J806:J810) -> 4100
B53: =Data!B19 -> Laying plywood in 1 layer | C53: =IFERROR(GETPIVOTDATA(""&$B$37,Control!$G$41,""&$B$37,""&B53),0) -> 1 | J53: =Control!$A$37 -> 0 | K53: =Control!A50 -> SEP
B54: =Data!B20 -> Laying linoleum with glue | C54: =IFERROR(GETPIVOTDATA(""&$B$37,Control!$G$41,""&$B$37,""&B54),0) -> 26 | J54: =Control!$A$37 -> 0 | K54: =Control!A51 -> OCT
B55: =Data!B21 -> Removing the shower cabin | C55: =IFERROR(GETPIVOTDATA(""&$B$37,Control!$G$41,""&$B$37,""&B55),0) -> 1 | J55: =Control!$A$37 -> 0 | K55: =Control!A52 -> NOV
B56: =Data!B22 -> Installation of thermal vapor barrier of the ceiling | C56: =IFERROR(GETPIVOTDATA(""&$B$37,Control!$G$41,""&$B$37,""&B56),0) -> 0 | J56: =Control!$A$37 -> 0 | K56: =Control!A53 -> DEC
B57: =Data!B23 -> Laying quartz vinyl tiles with glue | C57: =IFERROR(GETPIVOTDATA(""&$B$37,Control!$G$41,""&$B$37,""&B57),0) -> 22 | J57: =Control!$A$38 -> 0 | K57: =Control!A42 -> JAN
B58: =Data!B24 -> Threshold installation | C58: =IFERROR(GETPIVOTDATA(""&$B$37,Control!$G$41,""&$B$37,""&B58),0) -> 21 | J58: =Control!$A$38 -> 0 | K58: =Control!A43 -> FEB
B59: =Data!B25 -> Production and installation of suspended ceilings (matte, glossy) | C59: =IFERROR(GETPIVOTDATA(""&$B$37,Control!$G$41,""&$B$37,""&B59),0) -> 0 | J59: =Control!$A$38 -> 0 | K59: =Control!A44 -> MAR
B60: =Data!B26 -> Wallpapering ceilings | C60: =IFERROR(GETPIVOTDATA(""&$B$37,Control!$G$41,""&$B$37,""&B60),0) -> 72 | J60: =Control!$A$38 -> 0 | K60: =Control!A45 -> APR
B61: =Data!B27 -> Installation of PVC skirting boards | C61: =IFERROR(GETPIVOTDATA(""&$B$37,Control!$G$41,""&$B$37,""&B61),0) -> 24 | J61: =Control!$A$38 -> 0 | K61: =Control!A46 -> MAY
B62: =Data!B28 -> Installation of slatted ceilings | C62: =IFERROR(GETPIVOTDATA(""&$B$37,Control!$G$41,""&$B$37,""&B62),0) -> 49 | J62: =Control!$A$38 -> 0 | K62: =Control!A47 -> JUN
B63: =Data!B29 -> Removing an interior door | C63: =IFERROR(GETPIVOTDATA(""&$B$37,Control!$G$41,""&$B$37,""&B63),0) -> 1 | J63: =Control!$A$38 -> 0 | K63: =Control!A48 -> JUL
J64: =Control!$A$38 -> 0 | K64: =Control!A49 -> AUG
J65: =Control!$A$38 -> 0 | K65: =Control!A50 -> SEP
J66: =Control!$A$38 -> 0 | K66: =Control!A51 -> OCT
J67: =Control!$A$38 -> 0 | K67: =Control!A52 -> NOV
J68: =Control!$A$38 -> 0 | K68: =Control!A53 -> DEC

Sheet Today
C2: =NOW()-TODAY() -> 0.66658449
E14: CLIENT | G14: CONTACT | I14: TIME | J14: SERVICE | N14: MASTER | O14: PRIСE
D17: =E17>0 -> TRUE | E17: ='ALL ORDERS'!P806 -> Client 56 | G17: ='ALL ORDERS'!T806 -> (917) 555-5678 | I17: ='ALL ORDERS'!O806 -> 0.66666667 | J17: ='ALL ORDERS'!R806 -> 456 Willow Lane, Unit 55BBB | N17: ='ALL ORDERS'!S806 -> William | O17: ='ALL ORDERS'!J806 -> 500
E19: ='ALL ORDERS'!P807 -> Client 96 | G19: ='ALL ORDERS'!T807 -> (718) 555-8765 | I19: ='ALL ORDERS'!O807 -> 0.70833333 | J19: ='ALL ORDERS'!R807 -> 210 Oak Lane, Apt. 95PPPP | N19: ='ALL ORDERS'!S807 -> Oliver | O19: ='ALL ORDERS'!J807 -> 2300
D22: =E22>0 -> TRUE | E22: ='ALL ORDERS'!P808 -> Client 70 | G22: ='ALL ORDERS'!T806 -> (917) 555-5678 | I22: ='ALL ORDERS'!O808 -> 0.75 | J22: ='ALL ORDERS'!R808 -> 678 Spruce Street, Suite 69PPP | N22: ='ALL ORDERS'!S808 -> Jack | O22: ='ALL ORDERS'!J808 -> 300
E24: ='ALL ORDERS'!P809 -> Client 30 | G24: ='ALL ORDERS'!T809 -> (212) 555-7890 | I24: ='ALL ORDERS'!O809 -> 0.79166667 | J24: ='ALL ORDERS'!R809 -> 654 Magnolia Lane, Apt. 29BB | N24: ='ALL ORDERS'!S809 -> James | O24: ='ALL ORDERS'!J809 -> 700
D27: =E27>0 -> TRUE | E27: ='ALL ORDERS'!P810 -> Client 31 | G27: ='ALL ORDERS'!T810 -> (212) 555-7891 | I27: ='ALL ORDERS'!O810 -> 0.83333333 | J27: ='ALL ORDERS'!R810 -> 655 Magnolia Lane, Apt. 29BB | N27: ='ALL ORDERS'!S810 -> Lucas | O27: ='ALL ORDERS'!J810 -> 300
D32: =E32>0 -> FALSE

Sheet Data
E2: PERSONNEL | M2: ORDER
B3: LIST OF SERVICES PROVIDED | C3: PRICE | E3: MASTERS | F3: CONTACT | H3: MANAGERS | I3: CONTACT | K3: JOB TITLES | M3: PAYMENT METHOD | O3: STATE | Q3: CITYs
B4: Dismantling the balcony block | C4: 2500 | E4: Jack | F4: (917) 555-4321 | H4: Isabella | I4: (212) 555-1234 | K4: Master | M4: Cash Money | O4: Running | Q4: New York
B5: Laying parquet boards with glue | C5: 3400 | E5: William | F5: (718) 555-3456 | H5: Joseph | I5: (917) 555-5678 | K5: Manager | M5: Credit Cards | O5: Completed | Q5: Miami
B6: Laying quartz vinyl tiles on a substrate | C6: 1200 | E6: James | F6: (646) 555-6789 | H6: Liam | I6: (718) 555-8765 | O6: Canceled | Q6: Chikago
B7: Laying parquet boards on a substrate | C7: 500 | E7: Oliver | F7: (212) 555-9876 | H7: Charlotte | I7: (646) 555-2345 | K7: STATE | M7: CHANELS | Q7: Dallas
B8: Laying solid boards | C8: 560 | E8: Lucas | F8: (917) 555-7890 | H8: Jacob | I8: (212) 555-7890 | K8: fired | M8: Facebook | O8: DISCOUNT | Q8: New Orleans
B9: Installation of ceiling plinth | C9: 670 | E9: Sofia | F9: (718) 555-2345 | M9: Reddit | O9: 0.05
B10: Cutting and installation of additional corners | C10: 740 | M10: Instagram | O10: 0.1
B11: Dismantling the balcony block | C11: 1450 | M11: YouTube | O11: 0.15
B12: Removing the front door | C12: 800 | M12: WhatsApp
B13: Removing the shower tray | C13: 980
B14: Removing the sink | C14: 1400
B15: Dismantling the window block | C15: 2400
B16: Laying ceramic tiles, porcelain tiles on the floor with grout | C16: 3200
B17: Application of decorative plaster | C17: 4300
B18: Wallpapering | C18: 5300
B19: Laying plywood in 1 layer | C19: 2000
B20: Laying linoleum with glue | C20: 1200
B21: Removing the shower cabin | C21: 200
B22: Installation of thermal vapor barrier of the ceiling | C22: 4500
B23: Laying quartz vinyl tiles with glue | C23: 250
B24: Threshold installation | C24: 600
... B29: Removing an interior door | C29: 700
B30: 0

Sheet EMPLOYEES
C2: EMPLOYEES | I2: SALARY
B3: Num | C3: Name | D3: Date of Birth | E3: Job Titles | F3: Hiring Date | G3: Termination Date | H3: State | I3: 2023 | J3: 2024 | K3: 2025
B4: 1 | C4: Isabella | D4: 33765 | E4: Manager | F4: 45165 | I4: 10000 | J4: 12000 | K4: 15000
B5: 2 | C5: Joseph | D5: 27666 | E5: Manager | F5: 45165 | I5: 10000 | J5: 12000 | K5: 15000
B6: 3 | C6: Liam | D6: 25521 | E6: Manager | F6: 45180 | I6: 10000 | J6: 12000 | K6: 15000
B7: 4 | C7: Luna | D7: 34094 | E7: Manager | F7: 45180 | G7: 45536 | H7: fired | I7: 10000 | J7: 12000 | K7: 15000
B8: 5 | C8: William | D8: 30177 | E8: Master | F8: 45180 | I8: 10000 | J8: 12000 | K8: 15000
B9: 6 | C9: James | D9: 35906 | E9: Master | F9: 45180 | I9: 8000 | J9: 10000 | K9: 12000
B10: 7 | C10: Oliver | D10: 30371 | E10: Master | F10: 45571 | I10: 12000 | J10: 15000 | K10: 18000
B11: 8 | C11: Lucas | D11: 35436 | E11: Master | F11: 45165 | I11: 12000 | J11: 15000 | K11: 18000
B12: 9 | C12: Charlotte | D12: 33756 | E12: Manager | F12: 45165 | I12: 12000 | J12: 15000 | K12: 18000
B13: 10 | C13: Jacob | D13: 32109 | E13: Manager | F13: 45165 | I13: 12000 | J13: 15000 | K13: 18000
B14: 11 | C14: Emma | D14: 34230 | E14: Manager | F14: 45165 | G14: 45521 | H14: fired | I14: 12000 | J14: 15000 | K14: 18000
B15: 12 | C15: Jack | D15: 35683 | E15: Master | F15: 45538 | I15: 10000 | J15: 10000 | K15: 16000
B16: 13 | C16: Sofia | D16: 33003 | E16: Master | F16: 45538 | I16: 10000 | J16: 10000 | K16: 14000

Sheet BALANCE
D3: =Processing!$T$28 -> 1337100 | G3: INCOME AND EXPENSES | K3: =Processing!$T$29 -> 1125489

Sheet SERVICES PROVIDED
G2: SERVICES PROVIDED

Sheet ADDEMPLOYEES
C6: Full Name | K6: Contact
C8: Joy | K8: 151515
C11: Date of Birth | K11: Age
C13: 35920 | K13: =IF(ISBLANK(C13),0,YEAR(TODAY())-YEAR(C13)) -> 28
C16: Job Title | K16: Salary
C18: Manager | K18: 3000
C21: Hiring Date
C23: =TODAY() -> 46283

Sheet Customer Database
A3: Registration Date | B3: Client | C3: City | D3: Address | E3: Master | F3: Contact | G3: Channel | H3: Discount | I3: Manager
A4: 44927 | B4: Client 1 | C4: Chikago | D4: 123 Elm Street, Apt. 4B | E4: Jack | F4: (917) 555-5616 | G4: Reddit | I4: Isabella
A5: 44928 | B5: Client 2 | C5: Chikago | D5: 456 Willow Avenue, Unit 7 | E5: William | F5: (718) 555-8703 | G5: Reddit | I5: Joseph
A6: 44929 | B6: Client 3 | C6: New York | D6: 789 Oak Lane, Suite 12 | E6: James | F6: (646) 555-2283 | G6: Facebook | I6: Liam
A7: 44930 | B7: Client 4 | C7: Chikago | D7: 234 Pine Road, Apt. 3C | E7: Oliver | F7: (212) 555-7828 | G7: Reddit | I7: Isabella
A8: 44931 | B8: Client 5 | C8: Chikago | D8: 567 Birch Street, Unit 8D | E8: James | F8: (917) 555-4259 | G8: Reddit | I8: Charlotte
A9: 44958 | B9: Client 6 | C9: Chikago | D9: 890 Maple Drive, Apt. 2A | E9: Lucas | F9: (718) 555-3394 | G9: Reddit | H9: 0.05 | I9: Joseph
A10: 44959 | B10: Client 7 | C10: Chikago | D10: 345 Cedar Court, Suite 6E | E10: Oliver | F10: (646) 555-6727 | G10: Facebook | I10: Jacob
A11: 44960 | B11: Client 8 | C11: New York | D11: 678 Spruce Lane, Apt. 1F | E11: Jack | F11: (212) 555-9814 | G11: Reddit | I11: Liam
A12: 44986 | B12: Client 9 | C12: Chikago | D12: 1234 Redwood Road, Unit 5G | E12: Oliver | F12: (917) 555-7828 | G12: Reddit | I12: Isabella
A13: 44987 | B13: Client 10 | C13: Chikago | D13: 5678 Juniper Street, Apt. 9H | E13: James | F13: (718) 555-2283 | G13: Reddit | I13: Charlotte
A14: 44988 | B14: Client 11 | C14: Chikago | D14: 987 Aspen Avenue, Suite 10I | E14: Lucas | F14: 60900888990 | G14: Facebook | H14: 0.1 | I14: Isabella
A15: 44989 | B15: Client 12 | C15: New York | D15: 654 Pinecone Lane, Unit 11J | E15: Oliver | F15: (212) 555-1173 | G15: Reddit | I15: Jacob
A16: 44990 | B16: Client 13 | C16: Chikago | D16: 321 Acorn Drive, Apt. 12K | E16: Jack | F16: (917) 555-5617 | G16: Reddit | I16: Isabella
A17: 45017 | B17: Client 14 | C17: Miami | D17: 876 Sequoia Road, Suite 13L | E17: James | F17: (718) 555-8704 | G17: Reddit | I17: Charlotte
A18: 45018 | B18: Client 15 | C18: Chikago | D18: 543 Willowbrook Lane, Apt. 14M | E18: Lucas | F18: (646) 555-2284 | G18: Reddit | H18: 0.15 | I18: Isabella
A19: 45047 | B19: Client 16 | C19: Chikago | D19: 210 Magnolia Street, Unit 15N | E19: Oliver | F19: (212) 555-7829 | G19: Facebook | H19: 0.05 | I19: Isabella
A20: 45048 | B20: Client 17 | C20: Chikago | D20: 8765 Sycamore Court, Suite 16O | E20: Jack | F20: (917) 555-4260 | G20: Reddit | I20: Joseph
A21: 45049 | B21: Client 18 | C21: Chikago | D21: 4321 Cedarwood Drive, Apt. 17P | E21: James | F21: (718) 555-3395 | G21: Reddit | I21: Liam
A22: 45078 | B22: Client 19 | C22: Chikago | D22: 123 Elm Street, Unit 18Q | E22: Oliver | F22: (646) 555-6728 | G22: Facebook | I22: Isabella
A23: 44927 | B23: Client 20 | C23: Chikago | D23: 456 Birch Avenue, Suite 19R | E23: James | F23: (212) 555-9815 | G23: Reddit | I23: Charlotte
A24: 44928 | B24: Client 21 | C24: New York | D24: 789 Oak Lane, Apt. 20S | E24: Lucas | F24: (917) 555-7829 | G24: Reddit | I24: Jacob
A25: 44929 | B25: Client 22 | C25: Chikago | D25: 234 Maple Road, Unit 21T | E25: Oliver | F25: (718) 555-2284 | G25: Facebook | H25: 0.05 | I25: Joseph
A26: 44930 | B26: Client 23 | C26: Chikago | D26: 567 Pine Street, Suite 22U | E26: Jack | F26: 59900888990 | G26: Reddit | I26: Liam
A27: 45139 | B27: Client 24 | C27: Chikago | D27: 890 Willow Drive, Apt. 23V | E27: Oliver | F27: (212) 555-1174 | G27: Reddit | I27: Isabella
A28: 45170 | B28: Client 25 | C28: Dallas | D28: 345 Redwood Lane, Unit 24W | E28: James | F28: (917) 555-5618 | G28: Reddit | I28: Charlotte
A29: 45200 | B29: Client 26 | C29: New York | D29: 678 Spruce Street, Suite 25X | E29: Lucas | F29: (718) 555-8705 | G29: Facebook | H29: 0.1 | I29: Isabella
A30: 45231 | B30: Client 27 | C30: Chikago | D30: 1234 Aspen Road, Apt. 26Y | E30: Oliver | F30: (646) 555-2285 | G30: Reddit | H30: 0.1 | I30: Joseph
A31: 45232 | B31: Client 28 | C31: Chikago | D31: 5678 Cedar Drive, Unit 27Z | E31: Jack | F31: (212) 555-7830 | G31: Reddit | I31: Isabella
A32: 45233 | B32: Client 29 | C32: Chikago | D32: 987 Pinecone Avenue, Suite 28AA | E32: James | F32: (917) 555-4261 | G32: Facebook | I32: Charlotte
A33: 45234 | B33: Client 30 | C33: New York | D33: 654 Magnolia Lane, Apt. 29BB | E33: Lucas | F33: (718) 555-3396 | G33: Reddit | I33: Isabella
A34: 45261 | B34: Client 31 | C34: Chikago | D34: 321 Sequoia Street, Unit 30CC | E34: Oliver | F34: (646) 555-6729 | G34: YouTube | H34: 0.15 | I34: Jacob
A35: 45261 | B35: Client 32 | C35: Miami | D35: 876 Willowbrook Drive, Suite 31DD | E35: Jack | F35: (212) 555-9816 | G35: Reddit | H35: 0.15 | I35: Liam
A36: 45261 | B36: Client 33 | C36: Chikago | D36: 543 Acorn Lane, Apt. 32EE | E36: William | F36: (917) 555-7830 | G36: Reddit | I36: Isabella
A37: 45262 | B37: Client 34 | C37: Chikago | D37: 210 Sycamore Road, Unit 33FF | E37: Jack | F37: (718) 555-2285 | G37: Reddit | I37: Isabella
A38: 45262 | B38: Client 35 | C38: Miami | D38: 8765 Cedarwood Street, Suite 34GG | E38: James | F38: 58900888990 | G38: YouTube | I38: Charlotte
A39: 45262 | B39: Client 36 | C39: Chikago | D39: 4321 Elm Drive, Apt. 35HH | E39: Lucas | F39: (212) 555-1175 | G39: YouTube | I39: Isabella
A40: 45263 | B40: Client 37 | C40: #N/A | D40: 123 Birch Lane, Suite 36II | E40: Oliver | F40: (917) 555-5619 | G40: Reddit | I40: Joseph
A41: 45263 | B41: Client 38 | C41: Chikago | D41: 456 Oak Avenue, Unit 37JJ | E41: Jack | F41: (718) 555-8706 | G41: YouTube | I41: Liam
A42: 45263 | B42: Client 39 | C42: New York | D42: 789 Maple Street, Apt. 38KK | E42: Jack | F42: (646) 555-2286 | G42: WhatsApp | I42: Joseph
A43: 45264 | B43: Client 40 | C43: Chikago | D43: 234 Pine Road, Suite 39LL | E43: William | F43: (212) 555-7831 | G43: Facebook | H43: 0.15 | I43: Liam
A44: 45265 | B44: Client 41 | C44: Chikago | D44: 567 Willow Drive, Unit 40MM | E44: James | F44: (917) 555-4262 | G44: Instagram | H44: 0.15 | I44: Isabella
A45: 45266 | B45: Client 42 | C45: Chikago | D45: 890 Redwood Lane, Apt. 41NN | E45: Lucas | F45: (718) 555-3397 | G45: Facebook | H45: 0.15 | I45: Charlotte
A46: 45261 | B46: Client 43 | C46: Chikago | D46: 345 Spruce Street, Suite 42OO | E46: Lucas | F46: (646) 555-6730 | G46: Instagram | H46: 0.15 | I46: Isabella
A47: 45261 | B47: Client 44 | C47: New York | D47: 678 Aspen Avenue, Unit 43PP | E47: Jack | F47: (212) 555-9817 | G47: Reddit | I47: Jacob
A48: 45261 | B48: Client 45 | C48: Chikago | D48: 1234 Sequoia Road, Apt. 44QQ | E48: Jack | F48: (917) 555-7831 | G48: Reddit | I48: Isabella
A49: 45261 | B49: Client 46 | C49: New York | D49: 5678 Willowbrook Drive, Suite 45RR | E49: William | F49: (718) 555-2286 | G49: YouTube | I49: Charlotte
A50: 45268 | B50: Client 47 | C50: Chikago | D50: 987 Acorn Street, Unit 46SS | E50: Jack | F50: 57900888990 | G50: Instagram | I50: Isabella
A51: 45269 | B51: Client 48 | C51: Chikago | D51: 654 Sycamore Avenue, Apt. 47TT | E51: James | F51: (212) 555-1176 | G51: Facebook | I51: Joseph
A52: 45270 | B52: Client 49 | C52: Chikago | D52: 321 Cedarwood Lane, Suite 48UU | E52: Lucas | F52: (917) 555-5620 | G52: WhatsApp | I52: Liam
A53: 45271 | B53: Client 50 | C53: New York | D53: 876 Elm Drive, Unit 49VV | E53: Oliver | F53: (718) 555-8707 | G53: Reddit | I53: Isabella
A54: 45272 | B54: Client 51 | C54: Chikago | D54: 543 Birch Road, Apt. 50WW | E54: Jack | F54: (646) 555-2287 | G54: YouTube | I54: Isabella
A55: 45273 | B55: Client 52 | C55: Chikago | D55: 210 Oak Lane, Suite 51XX | E55: Jack | F55: (212) 555-7832 | G55: YouTube | I55: Charlotte
A56: 45273 | B56: Client 53 | C56: Chikago | D56: 8765 Maple Street, Unit 52YY | E56: William | F56: (917) 555-4263 | G56: Reddit | I56: Isabella
A57: 45273 | B57: Client 54 | C57: Chikago | D57: 4321 Pine Street, Apt. 53ZZ | E57: James | F57: (718) 555-3398 | G57: Reddit | I57: Jacob
A58: 45273 | B58: Client 55 | C58: Chikago | D58: 123 Redwood Avenue, Suite 54AAA | E58: Lucas | F58: (646) 555-6731 | G58: Reddit | H58: 0.15 | I58: Liam
A59: 45274 | B59: Client 56 | C59: Chikago | D59: 456 Willow Lane, Unit 55BBB | E59: Jack | F59: (212) 555-9818 | G59: YouTube | I59: Isabella
A60: 45275 | B60: Client 57 | C60: New York | D60: 789 Magnolia Road, Apt. 56CCC | E60: Jack | F60: (917) 555-7832 | G60: YouTube | I60: Isabella
A61: 45276 | B61: Client 58 | C61: Chikago | D61: 234 Sequoia Street, Suite 57DDD | E61: Jack | F61: (718) 555-2287 | G61: Reddit | I61: Charlotte
A62: 45271 | B62: Client 59 | C62: Chikago | D62: 567 Willowbrook Drive, Unit 58EEE | E62: William | F62: 56900888990 | G62: YouTube | I62: Isabella
A63: 45278 | B63: Client 60 | C63: Chikago | D63: 890 Acorn Avenue, Apt. 59FFF | E63: Jack | F63: (212) 555-1177 | G63: WhatsApp | I63: Joseph
A64: 45279 | B64: Client 61 | C64: Chikago | D64: 345 Sycamore Lane, Suite 60GGG | E64: James | F64: (917) 555-5621 | G64: Facebook | H64: 0.15 | I64: Liam
A65: 45279 | B65: Client 62 | C65: New York | D65: 678 Cedarwood Road, Unit 61HHH | E65: Lucas | F65: (718) 555-8708 | G65: Instagram | I65: Isabella
A66: 45280 | B66: Client 63 | C66: Chikago | D66: 123 Elm Street, Apt. 62III | E66: Oliver | F66: (646) 555-2288 | G66: Facebook | I66: Charlotte
A67: 45281 | B67: Client 64 | C67: Chikago | D67: 456 Birch Avenue, Suite 63JJJ | E67: Jack | F67: (212) 555-7833 | G67: YouTube | I67: Jacob
A68: 45282 | B68: Client 65 | C68: New York | D68: 789 Oak Lane, Unit 64KKK | E68: Jack | F68: (917) 555-4264 | G68: Reddit | I68: Joseph
A69: 45283 | B69: Client 66 | C69: Chikago | D69: 234 Maple Road, Apt. 65LLL | E69: William | F69: (718) 555-3399 | G69: Reddit | I69: Isabella
A70: 45283 | B70: Client 67 | C70: Chikago | D70: 567 Pine Street, Suite 66MMM | E70: James | F70: (646) 555-6732 | G70: YouTube | I70: Charlotte
A71: 45283 | B71: Client 68 | C71: Chikago | D71: 890 Willow Drive, Unit 67NNN | E71: Lucas | F71: (212) 555-9819 | G71: Instagram | I71: Isabella
A72: 45284 | B72: Client 69 | C72: Chikago | D72: 345 Redwood Lane, Apt. 68OOO | E72: Jack | F72: (917) 555-7833 | G72: Facebook | I72: Jacob
A73: 45285 | B73: Client 70 | C73: New York | D73: 678 Spruce Street, Suite 69PPP | E73: Jack | F73: (718) 555-2288 | G73: WhatsApp | I73: Liam
A74: 45286 | B74: Client 71 | C74: Chikago | D74: 1234 Aspen Road, Unit 70QQQ | E74: Jack | F74: 55900888990 | G74: Reddit | I74: Isabella
A75: 45281 | B75: Client 72 | C75: Chikago | D75: 5678 Cedar Drive, Apt. 71RRR | E75: William | F75: (212) 555-1178 | G75: YouTube | I75: Charlotte
A76: 45288 | B76: Client 73 | C76: Chikago | D76: 987 Pinecone Avenue, Suite 72SSS | E76: Jack | F76: (917) 555-5622 | G76: YouTube | I76: Joseph
A77: 45288 | B77: Client 74 | C77: New York | D77: 654 Magnolia Lane, Unit 73TTT | E77: James | F77: (718) 555-8709 | G77: Reddit | I77: Isabella
A78: 45288 | B78: Client 75 | C78: Chikago | D78: 321 Sequoia Street, Apt. 74UUU | E78: Lucas | F78: (646) 555-2289 | G78: Reddit | H78: 0.15 | I78: Charlotte
A79: 45301 | B79: Client 76 | C79: Miami | D79: 876 Willowbrook Drive, Suite 75VVV | E79: Oliver | F79: (212) 555-7834 | G79: Reddit | I79: Isabella
A80: 45302 | B80: Client 77 | C80: Chikago | D80: 543 Acorn Lane, Unit 76WWW | E80: William | F80: (917) 555-4265 | G80: YouTube | I80: Jacob
A81: 45303 | B81: Client 78 | C81: Chikago | D81: 210 Sycamore Road, Apt. 77XXX | E81: Jack | F81: (718) 555-3400 | G81: YouTube | I81: Liam
A82: 45304 | B82: Client 79 | C82: Miami | D82: 8765 Cedarwood Street, Suite 78YYY | E82: Jack | F82: (646) 555-6733 | G82: Reddit | I82: Isabella
A83: 45304 | B83: Client 80 | C83: Chikago | D83: 4321 Elm Drive, Unit 79ZZZ | E83: William | F83: (212) 555-9820 | G83: YouTube | I83: Charlotte
A84: 45304 | B84: Client 81 | C84: #N/A | D84: 123 Birch Lane, Apt. 80AAAA | E84: William | F84: (917) 555-7834 | G84: WhatsApp | I84: Joseph
A85: 45307 | B85: Client 82 | C85: Chikago | D85: 456 Oak Avenue, Suite 81BBBB | E85: Jack | F85: (718) 555-2289 | G85: Facebook | I85: Jacob
A86: 45307 | B86: Client 83 | C86: New York | D86: 789 Maple Street, Unit 82CCCC | E86: James | F86: 54900888990 | G86: Instagram | H86: 0.15 | I86: Liam
A87: 45309 | B87: Client 84 | C87: Chikago | D87: 234 Pine Road, Apt. 83DDDD | E87: Lucas | F87: (212) 555-1179 | G87: Facebook | I87: Isabella
A88: 45310 | B88: Client 85 | C88: Chikago | D88: 567 Willow Drive, Suite 84EEEE | E88: Oliver | F88: (917) 555-5623 | G88: YouTube | I88: Charlotte
A89: 45311 | B89: Client 86 | C89: Chikago | D89: 890 Redwood Lane, Unit 85FFFF | E89: Jack | F89: (718) 555-8710 | G89: Reddit | I89: Isabella
A90: 45311 | B90: Client 87 | C90: Chikago | D90: 345 Spruce Street, Apt. 86GGGG | E90: Jack | F90: (646) 555-2290 | G90: Reddit | I90: Joseph
A91: 45311 | B91: Client 88 | C91: New York | D91: 678 Aspen Avenue, Suite 87HHHH | E91: William | F91: (212) 555-7835 | G91: YouTube | I91: Liam
A92: 45314 | B92: Client 89 | C92: Chikago | D92: 1234 Sequoia Road, Unit 88IIII | E92: James | F92: (917) 555-4266 | G92: Instagram | I92: Isabella
A93: 45314 | B93: Client 90 | C93: Chikago | D93: 5678 Willowbrook Drive, Apt. 89JJJJ | E93: Lucas | F93: (718) 555-3401 | G93: Facebook | I93: Charlotte
A94: 45316 | B94: Client 91 | C94: Chikago | D94: 987 Acorn Street, Suite 90KKKK | E94: William | F94: (646) 555-6734 | G94: WhatsApp | I94: Jacob
A95: 45317 | B95: Client 92 | C95: New York | D95: 654 Sycamore Avenue, Unit 91LLLL | E95: Jack | F95: (212) 555-9821 | G95: Reddit | H95: 0.15 | I95: Joseph
A96: 45312 | B96: Client 93 | C96: Chikago | D96: 321 Cedarwood Lane, Apt. 92MMMM | E96: William | F96: (917) 555-7835 | G96: YouTube | I96: Liam
A97: 45312 | B97: Client 94 | C97: New York | D97: 876 Elm Drive, Suite 93NNNN | E97: William | F97: (718) 555-2290 | G97: Reddit | I97: Isabella
A98: 45312 | B98: Client 95 | C98: Chikago | D98: 543 Birch Road, Unit 94OOOO | E98: Jack | F98: 53900888990 | G98: Reddit | I98: Charlotte
A99: 45321 | B99: Client 96 | C99: Chikago | D99: 210 Oak Lane, Apt. 95PPPP | E99: James | F99: (212) 555-1180 | G99: Reddit | I99: Isabella
A100: 45322 | B100: Client 97 | C100: New Orleans | D100: 8765 Maple Street, Suite 96QQQQ | E100: Lucas | F100: (917) 555-5624 | G100: YouTube | H100: 0.15 | I100: Jacob
A101: 45323 | B101: Client 98 | C101: Chikago | D101: 4321 Pine Street, Unit 97RRRR | E101: Oliver | F101: (718) 555-8711 | G101: YouTube | I101: Liam
A102: 45323 | B102: Client 99 | C102: Chikago | D102: 123 Redwood Avenue, Apt. 98SSSS | E102: William | F102: (646) 555-2291 | G102: Reddit | I102: Isabella
...

Sheet Employee Database
C2: EMPLOYEE DATABASE | F2: SALARY
A3: Hiring Date | B3: Name | C3: Date of Birth | D3: Age | E3: Job Title | F3: 2023 | G3: 2024 | H3: 2025 | I3: Contact
A4: 44896 | B4: Jack | C4: 30296 | D4: 41 | E4: Master | F4: 1800 | G4: 2000 | H4: 2200 | I4: (917) 555-4321
A5: 44896 | B5: William | C5: 28471 | D5: 46 | E5: Master | F5: 1800 | G5: 2000 | H5: 2200 | I5: (718) 555-3456
A6: 44912 | B6: James | C6: 32137 | D6: 36 | E6: Master | F6: 1800 | G6: 2000 | H6: 2200 | I6: (646) 555-6789
A7: 44913 | B7: Isabella | C7: 30678 | D7: 40 | E7: Manager | F7: 2500 | G7: 2700 | H7: 2900 | I7: (212) 555-1234
A8: 44914 | B8: Joseph | C8: 34694 | D8: 29 | E8: Manager | F8: 2500 | G8: 2700 | H8: 2900 | I8: (917) 555-5678
A9: 44911 | B9: Liam | C9: 33596 | D9: 32 | E9: Manager | F9: 2500 | G9: 2700 | H9: 2900 | I9: (718) 555-8765
A10: 44915 | B10: Oliver | C10: 32140 | D10: 36 | E10: Master | F10: 1800 | G10: 2000 | H10: 2200 | I10: (212) 555-9876
A11: 44917 | B11: Lucas | C11: 31412 | D11: 38 | E11: Master | F11: 1800 | G11: 2000 | H11: 2200 | I11: (917) 555-7890
A12: 44918 | B12: Sofia | C12: 32873 | D12: 34 | E12: Master | F12: 1800 | G12: 2000 | H12: 2200 | I12: (718) 555-2345
A13: 44925 | B13: Charlotte | C13: 32150 | D13: 35 | E13: Manager | F13: 2500 | G13: 2700 | H13: 2900 | I13: (646) 555-2345
A14: 44925 | B14: Jacob | C14: 29595 | D14: 42 | E14: Manager | F14: 2500 | G14: 2700 | H14: 2900 | I14: (212) 555-7890
A15: =ADDEMPLOYEES!C23 -> 46283 | B15: =ADDEMPLOYEES!C8 -> Joy | C15: =ADDEMPLOYEES!C13 -> 35920 | D15: =ADDEMPLOYEES!K13 -> 28 | E15: =ADDEMPLOYEES!C18 -> Manager | F15: =ADDEMPLOYEES!K18 -> 3000 | I15: =ADDEMPLOYEES!K8 -> 151515

Sheet KPI
C2: KPI PLAN | E2: REWARD
A3: Year | B3: Month | C3: Managers Sales | D3: Masters Order Quantity | E3: <100% | F3: >100% | G3: >120%
A4: 2023 | B4: JAN | C4: 15000 | D4: 4 | E4: 0 | F4: 0.03 | G4: 0.05
A5: 2023 | B5: FEB | C5: 15000 | D5: 4 | E5: 0 | F5: 0.03 | G5: 0.05
A6: 2023 | B6: MAR | C6: 15000 | D6: 4 | E6: 0 | F6: 0.03 | G6: 0.05
A7: 2023 | B7: APR | C7: 15000 | D7: 4 | E7: 0 | F7: 0.03 | G7: 0.05
A8: 2023 | B8: MAY | C8: 15000 | D8: 4 | E8: 0 | F8: 0.03 | G8: 0.05
A9: 2023 | B9: JUN | C9: 15000 | D9: 4 | E9: 0 | F9: 0.03 | G9: 0.05
A10: 2023 | B10: JUL | C10: 15000 | D10: 4 | E10: 0 | F10: 0.03 | G10: 0.05
A11: 2023 | B11: AUG | C11: 15000 | D11: 4 | E11: 0 | F11: 0.03 | G11: 0.05
A12: 2023 | B12: SEP | C12: 15000 | D12: 4 | E12: 0 | F12: 0.03 | G12: 0.05
A13: 2023 | B13: OCT | C13: 15000 | D13: 4 | E13: 0 | F13: 0.03 | G13: 0.05
A14: 2023 | B14: NOV | C14: 15000 | D14: 4 | E14: 0 | F14: 0.03 | G14: 0.05
A15: 2023 | B15: DEC | C15: 15000 | D15: 4 | E15: 0 | F15: 0.03 | G15: 0.05
... A39: 2025 | B39: DEC | C39: 15000 | D39: 4 | E39: 0 | F39: 0.03 | G39: 0.05
