Workbook
Name Slicer_Month: #N/A
Name Slicer_Year: #N/A

Sheet DASHBOARD

Sheet Visitors & Buyers

Sheet Conversion

Sheet Profit

Sheet Tasks

Sheet Processing
A1: Menu | F1: 72 | G1: 72 | H1: 72 | I1: 72 | J1: 72
A2: Visitors & Buyers | B2: =GETPIVOTDATA("Sum of Visitors",Control!$A$3) -> 8333 | F2: 72 | G2: 72 | H2: 72 | I2: 72 | J2: 72
A3: Conversion | B3: =GETPIVOTDATA("Average of Conversion",Control!$A$3) -> 0.16 | C3: =100%-B3 -> 0.84 | F3: 72 | G3: 72 | H3: 72 | I3: 72 | J3: 72
A4: Profit | B4: =L29 -> 5000
A5: Tasks | B5: =AVERAGE(B8:B12) -> 0.132 | C5: 0.05 | D5: =100%-B5 -> 0.868
F6: Funding Sources by Tasks
A7: Task Manager | D7: Indent | G7: Equity | H7: Debt
A8: Task 1 | B8: =GETPIVOTDATA(""&A8,Control!$A$3) -> 0.05 | C8: =100%-B8 -> 0.95 | D8: =$D$13 -> 0.023 | F8: Task 1 | G8: =GETPIVOTDATA(LEFT(G$7,1)&$F8,Control!$A$3) -> 36741 | H8: =GETPIVOTDATA(LEFT(H$7,1)&$F8,Control!$A$3) -> 23004
A9: Task 2 | B9: =GETPIVOTDATA(""&A9,Control!$A$3) -> 0.21 | C9: =100%-B9 -> 0.79 | D9: =$D$13 -> 0.023 | F9: Task 2 | G9: =GETPIVOTDATA(LEFT(G$7,1)&$F9,Control!$A$3) -> 24078 | H9: =GETPIVOTDATA(LEFT(H$7,1)&$F9,Control!$A$3) -> 21742
A10: Task 3 | B10: =GETPIVOTDATA(""&A10,Control!$A$3) -> 0.13 | C10: =100%-B10 -> 0.87 | D10: =$D$13 -> 0.023 | F10: Task 3 | G10: =GETPIVOTDATA(LEFT(G$7,1)&$F10,Control!$A$3) -> 15139 | H10: =GETPIVOTDATA(LEFT(H$7,1)&$F10,Control!$A$3) -> 26701
A11: Task 4 | B11: =GETPIVOTDATA(""&A11,Control!$A$3) -> 0.16 | C11: =100%-B11 -> 0.84 | D11: =$D$13 -> 0.023 | F11: Task 4 | G11: =GETPIVOTDATA(LEFT(G$7,1)&$F11,Control!$A$3) -> 29492 | H11: =GETPIVOTDATA(LEFT(H$7,1)&$F11,Control!$A$3) -> 34641
A12: Task 5 | B12: =GETPIVOTDATA(""&A12,Control!$A$3) -> 0.11 | C12: =100%-B12 -> 0.89 | D12: =$D$13 -> 0.023 | F12: Task 5 | G12: =GETPIVOTDATA(LEFT(G$7,1)&$F12,Control!$A$3) -> 45372 | H12: =GETPIVOTDATA(LEFT(H$7,1)&$F12,Control!$A$3) -> 36988
D13: 0.023 | G13: =SUM(G8:G12) -> 150822 | H13: =SUM(H8:H12) -> 143076
B15: Visitors & Buyers | H15: Profit Performance
B16: Visitors | C16: Buyers | D16: Cursor V | E16: Cursor B | H16: Profit | I16: Plan | J16: Break-Even Point | K16: Debt | L16: Cursor
A17: JAN | B17: =GETPIVOTDATA(""&B$16,Control!$A$20,"Month",""&$A17) -> 8333 | C17: =GETPIVOTDATA(""&C$16,Control!$A$20,"Month",""&$A17) -> 4500 | D17: =IFERROR(GETPIVOTDATA(""&B$16,Control!$A$3,"Month",""&$A17),NA()) -> 8333 | E17: =IFERROR(GETPIVOTDATA(""&C$16,Control!$A$3,"Month",""&$A17),NA()) -> 4500 | G17: JAN | H17: =GETPIVOTDATA(""&H$16,Control!$A$20,"Month",""&$G17) -> 5000 | I17: =GETPIVOTDATA(""&I$16,Control!$A$20,"Month",""&$G17) -> 8200 | J17: =GETPIVOTDATA(""&J$16,Control!$A$20,"Month",""&$G17) -> 5350 | K17: =GETPIVOTDATA(""&K$16,Control!$A$20,"Month",""&$G17) -> 7600 | L17: =IFERROR(GETPIVOTDATA("Sum of Profit",Control!$A$3,"Month",""&G17),NA()) -> 5000
A18: FEB | B18: =GETPIVOTDATA(""&B$16,Control!$A$20,"Month",""&$A18) -> 10021 | C18: =GETPIVOTDATA(""&C$16,Control!$A$20,"Month",""&$A18) -> 5311 | D18: =IFERROR(GETPIVOTDATA(""&B$16,Control!$A$3,"Month",""&$A18),NA()) -> #N/A | E18: =IFERROR(GETPIVOTDATA(""&C$16,Control!$A$3,"Month",""&$A18),NA()) -> #N/A | G18: FEB | H18: =GETPIVOTDATA(""&H$16,Control!$A$20,"Month",""&$G18) -> 5900 | I18: =GETPIVOTDATA(""&I$16,Control!$A$20,"Month",""&$G18) -> 6700 | J18: =GETPIVOTDATA(""&J$16,Control!$A$20,"Month",""&$G18) -> 4100 | K18: =GETPIVOTDATA(""&K$16,Control!$A$20,"Month",""&$G18) -> 6900 | L18: =IFERROR(GETPIVOTDATA("Sum of Profit",Control!$A$3,"Month",""&G18),NA()) -> #N/A
A19: MAR | B19: =GETPIVOTDATA(""&B$16,Control!$A$20,"Month",""&$A19) -> 11177 | C19: =GETPIVOTDATA(""&C$16,Control!$A$20,"Month",""&$A19) -> 6147 | D19: =IFERROR(GETPIVOTDATA(""&B$16,Control!$A$3,"Month",""&$A19),NA()) -> #N/A | E19: =IFERROR(GETPIVOTDATA(""&C$16,Control!$A$3,"Month",""&$A19),NA()) -> #N/A | G19: MAR | H19: =GETPIVOTDATA(""&H$16,Control!$A$20,"Month",""&$G19) -> 7300 | I19: =GETPIVOTDATA(""&I$16,Control!$A$20,"Month",""&$G19) -> 6000 | J19: =GETPIVOTDATA(""&J$16,Control!$A$20,"Month",""&$G19) -> 4700 | K19: =GETPIVOTDATA(""&K$16,Control!$A$20,"Month",""&$G19) -> 6100 | L19: =IFERROR(GETPIVOTDATA("Sum of Profit",Control!$A$3,"Month",""&G19),NA()) -> #N/A
A20: APR | B20: =GETPIVOTDATA(""&B$16,Control!$A$20,"Month",""&$A20) -> 11427 | C20: =GETPIVOTDATA(""&C$16,Control!$A$20,"Month",""&$A20) -> 5256 | D20: =IFERROR(GETPIVOTDATA(""&B$16,Control!$A$3,"Month",""&$A20),NA()) -> #N/A | E20: =IFERROR(GETPIVOTDATA(""&C$16,Control!$A$3,"Month",""&$A20),NA()) -> #N/A | G20: APR | H20: =GETPIVOTDATA(""&H$16,Control!$A$20,"Month",""&$G20) -> 9000 | I20: =GETPIVOTDATA(""&I$16,Control!$A$20,"Month",""&$G20) -> 6200 | J20: =GETPIVOTDATA(""&J$16,Control!$A$20,"Month",""&$G20) -> 5200 | K20: =GETPIVOTDATA(""&K$16,Control!$A$20,"Month",""&$G20) -> 6400 | L20: =IFERROR(GETPIVOTDATA("Sum of Profit",Control!$A$3,"Month",""&G20),NA()) -> #N/A
A21: MAY | B21: =GETPIVOTDATA(""&B$16,Control!$A$20,"Month",""&$A21) -> 10698 | C21: =GETPIVOTDATA(""&C$16,Control!$A$20,"Month",""&$A21) -> 4921 | D21: =IFERROR(GETPIVOTDATA(""&B$16,Control!$A$3,"Month",""&$A21),NA()) -> #N/A | E21: =IFERROR(GETPIVOTDATA(""&C$16,Control!$A$3,"Month",""&$A21),NA()) -> #N/A | G21: MAY | H21: =GETPIVOTDATA(""&H$16,Control!$A$20,"Month",""&$G21) -> 10100 | I21: =GETPIVOTDATA(""&I$16,Control!$A$20,"Month",""&$G21) -> 7400 | J21: =GETPIVOTDATA(""&J$16,Control!$A$20,"Month",""&$G21) -> 5700 | K21: =GETPIVOTDATA(""&K$16,Control!$A$20,"Month",""&$G21) -> 7300 | L21: =IFERROR(GETPIVOTDATA("Sum of Profit",Control!$A$3,"Month",""&G21),NA()) -> #N/A
A22: JUN | B22: =GETPIVOTDATA(""&B$16,Control!$A$20,"Month",""&$A22) -> 9219 | C22: =GETPIVOTDATA(""&C$16,Control!$A$20,"Month",""&$A22) -> 5070 | D22: =IFERROR(GETPIVOTDATA(""&B$16,Control!$A$3,"Month",""&$A22),NA()) -> #N/A | E22: =IFERROR(GETPIVOTDATA(""&C$16,Control!$A$3,"Month",""&$A22),NA()) -> #N/A | G22: JUN | H22: =GETPIVOTDATA(""&H$16,Control!$A$20,"Month",""&$G22) -> 11100 | I22: =GETPIVOTDATA(""&I$16,Control!$A$20,"Month",""&$G22) -> 7900 | J22: =GETPIVOTDATA(""&J$16,Control!$A$20,"Month",""&$G22) -> 5250 | K22: =GETPIVOTDATA(""&K$16,Control!$A$20,"Month",""&$G22) -> 7800 | L22: =IFERROR(GETPIVOTDATA("Sum of Profit",Control!$A$3,"Month",""&G22),NA()) -> #N/A
A23: JUL | B23: =GETPIVOTDATA(""&B$16,Control!$A$20,"Month",""&$A23) -> 7448 | C23: =GETPIVOTDATA(""&C$16,Control!$A$20,"Month",""&$A23) -> 4022 | D23: =IFERROR(GETPIVOTDATA(""&B$16,Control!$A$3,"Month",""&$A23),NA()) -> #N/A | E23: =IFERROR(GETPIVOTDATA(""&C$16,Control!$A$3,"Month",""&$A23),NA()) -> #N/A | G23: JUL | H23: =GETPIVOTDATA(""&H$16,Control!$A$20,"Month",""&$G23) -> 10900 | I23: =GETPIVOTDATA(""&I$16,Control!$A$20,"Month",""&$G23) -> 7100 | J23: =GETPIVOTDATA(""&J$16,Control!$A$20,"Month",""&$G23) -> 5750 | K23: =GETPIVOTDATA(""&K$16,Control!$A$20,"Month",""&$G23) -> 7400 | L23: =IFERROR(GETPIVOTDATA("Sum of Profit",Control!$A$3,"Month",""&G23),NA()) -> #N/A
A24: AUG | B24: =GETPIVOTDATA(""&B$16,Control!$A$20,"Month",""&$A24) -> 5969 | C24: =GETPIVOTDATA(""&C$16,Control!$A$20,"Month",""&$A24) -> 3462 | D24: =IFERROR(GETPIVOTDATA(""&B$16,Control!$A$3,"Month",""&$A24),NA()) -> #N/A | E24: =IFERROR(GETPIVOTDATA(""&C$16,Control!$A$3,"Month",""&$A24),NA()) -> #N/A | G24: AUG | H24: =GETPIVOTDATA(""&H$16,Control!$A$20,"Month",""&$G24) -> 9800 | I24: =GETPIVOTDATA(""&I$16,Control!$A$20,"Month",""&$G24) -> 6500 | J24: =GETPIVOTDATA(""&J$16,Control!$A$20,"Month",""&$G24) -> 4800 | K24: =GETPIVOTDATA(""&K$16,Control!$A$20,"Month",""&$G24) -> 6800 | L24: =IFERROR(GETPIVOTDATA("Sum of Profit",Control!$A$3,"Month",""&G24),NA()) -> #N/A
A25: SEP | B25: =GETPIVOTDATA(""&B$16,Control!$A$20,"Month",""&$A25) -> 5240 | C25: =GETPIVOTDATA(""&C$16,Control!$A$20,"Month",""&$A25) -> 2987 | D25: =IFERROR(GETPIVOTDATA(""&B$16,Control!$A$3,"Month",""&$A25),NA()) -> #N/A | E25: =IFERROR(GETPIVOTDATA(""&C$16,Control!$A$3,"Month",""&$A25),NA()) -> #N/A | G25: SEP | H25: =GETPIVOTDATA(""&H$16,Control!$A$20,"Month",""&$G25) -> 8200 | I25: =GETPIVOTDATA(""&I$16,Control!$A$20,"Month",""&$G25) -> 7000 | J25: =GETPIVOTDATA(""&J$16,Control!$A$20,"Month",""&$G25) -> 5300 | K25: =GETPIVOTDATA(""&K$16,Control!$A$20,"Month",""&$G25) -> 7200 | L25: =IFERROR(GETPIVOTDATA("Sum of Profit",Control!$A$3,"Month",""&G25),NA()) -> #N/A
A26: OCT | B26: =GETPIVOTDATA(""&B$16,Control!$A$20,"Month",""&$A26) -> 5490 | C26: =GETPIVOTDATA(""&C$16,Control!$A$20,"Month",""&$A26) -> 3020 | D26: =IFERROR(GETPIVOTDATA(""&B$16,Control!$A$3,"Month",""&$A26),NA()) -> #N/A | E26: =IFERROR(GETPIVOTDATA(""&C$16,Control!$A$3,"Month",""&$A26),NA()) -> #N/A | G26: OCT | H26: =GETPIVOTDATA(""&H$16,Control!$A$20,"Month",""&$G26) -> 6700 | I26: =GETPIVOTDATA(""&I$16,Control!$A$20,"Month",""&$G26) -> 8100 | J26: =GETPIVOTDATA(""&J$16,Control!$A$20,"Month",""&$G26) -> 5000 | K26: =GETPIVOTDATA(""&K$16,Control!$A$20,"Month",""&$G26) -> 8000 | L26: =IFERROR(GETPIVOTDATA("Sum of Profit",Control!$A$3,"Month",""&G26),NA()) -> #N/A
A27: NOV | B27: =GETPIVOTDATA(""&B$16,Control!$A$20,"Month",""&$A27) -> 6646 | C27: =GETPIVOTDATA(""&C$16,Control!$A$20,"Month",""&$A27) -> 3722 | D27: =IFERROR(GETPIVOTDATA(""&B$16,Control!$A$3,"Month",""&$A27),NA()) -> #N/A | E27: =IFERROR(GETPIVOTDATA(""&C$16,Control!$A$3,"Month",""&$A27),NA()) -> #N/A | G27: NOV | H27: =GETPIVOTDATA(""&H$16,Control!$A$20,"Month",""&$G27) -> 5450 | I27: =GETPIVOTDATA(""&I$16,Control!$A$20,"Month",""&$G27) -> 8800 | J27: =GETPIVOTDATA(""&J$16,Control!$A$20,"Month",""&$G27) -> 5300 | K27: =GETPIVOTDATA(""&K$16,Control!$A$20,"Month",""&$G27) -> 7700 | L27: =IFERROR(GETPIVOTDATA("Sum of Profit",Control!$A$3,"Month",""&G27),NA()) -> #N/A
A28: DEC | B28: =GETPIVOTDATA(""&B$16,Control!$A$20,"Month",""&$A28) -> 8333 | C28: =GETPIVOTDATA(""&C$16,Control!$A$20,"Month",""&$A28) -> 3750 | D28: =IFERROR(GETPIVOTDATA(""&B$16,Control!$A$3,"Month",""&$A28),NA()) -> #N/A | E28: =IFERROR(GETPIVOTDATA(""&C$16,Control!$A$3,"Month",""&$A28),NA()) -> #N/A | G28: DEC | H28: =GETPIVOTDATA(""&H$16,Control!$A$20,"Month",""&$G28) -> 8181 | I28: =GETPIVOTDATA(""&I$16,Control!$A$20,"Month",""&$G28) -> 6969 | J28: =GETPIVOTDATA(""&J$16,Control!$A$20,"Month",""&$G28) -> 5151 | K28: =GETPIVOTDATA(""&K$16,Control!$A$20,"Month",""&$G28) -> 7171 | L28: =IFERROR(GETPIVOTDATA("Sum of Profit",Control!$A$3,"Month",""&G28),NA()) -> #N/A
D29: =GETPIVOTDATA("Sum of Visitors",Control!$A$3) -> 8333 | E29: =GETPIVOTDATA("Sum of Buyers",Control!$A$3) -> 4500 | H29: =GETPIVOTDATA(""&H16,Control!$A$3) -> 5000 | I29: =GETPIVOTDATA(""&I16,Control!$A$3)+J29 -> 13550 | J29: =GETPIVOTDATA(""&J16,Control!$A$3) -> 5350 | K29: =GETPIVOTDATA(""&K16,Control!$A$3) -> 7600 | L29: =GETPIVOTDATA("Sum of Profit",Control!$A$3) -> 5000

Sheet Control
A3: Row Labels | B3: Sum of Visitors | C3: Sum of Buyers | D3: Average of Conversion | E3: Sum of Profit | F3: Sum of Plan | G3: Sum of Break-Even Point | H3: Sum of Debt | I3: Sum of ETask 1 | J3: Sum of ETask 2 | K3: Sum of ETask 3 | L3: Sum of ETask 4 | M3: Sum of ETask 5 | N3: Sum of DTask 1 | O3: Sum of DTask 2 | P3: Sum of DTask 3 | Q3: Sum of DTask 4 | R3: Sum of DTask 5 | S3: Average of Task 1 | T3: Average of Task 2 | U3: Average of Task 3 | V3: Average of Task 4 | W3: Average of Task 5
A4: JAN | B4: 8333 | C4: 4500 | D4: 0.16 | E4: 5000 | F4: 8200 | G4: 5350 | H4: 7600 | I4: 36741 | J4: 24078 | K4: 15139 | L4: 29492 | M4: 45372 | N4: 23004 | O4: 21742 | P4: 26701 | Q4: 34641 | R4: 36988 | S4: 0.05 | T4: 0.21 | U4: 0.13 | V4: 0.16 | W4: 0.11
A5: Grand Total | B5: 8333 | C5: 4500 | D5: 0.16 | E5: 5000 | F5: 8200 | G5: 5350 | H5: 7600 | I5: 36741 | J5: 24078 | K5: 15139 | L5: 29492 | M5: 45372 | N5: 23004 | O5: 21742 | P5: 26701 | Q5: 34641 | R5: 36988 | S5: 0.05 | T5: 0.21 | U5: 0.13 | V5: 0.16 | W5: 0.11
A20: Row Labels | B20: Sum of Visitors | C20: Sum of Buyers | D20: Sum of Profit | E20: Sum of Plan | F20: Sum of Break-Even Point | G20: Sum of Debt
A21: JAN | B21: 8333 | C21: 4500 | D21: 5000 | E21: 8200 | F21: 5350 | G21: 7600
A22: FEB | B22: 10021 | C22: 5311 | D22: 5900 | E22: 6700 | F22: 4100 | G22: 6900
A23: MAR | B23: 11177 | C23: 6147 | D23: 7300 | E23: 6000 | F23: 4700 | G23: 6100
A24: APR | B24: 11427 | C24: 5256 | D24: 9000 | E24: 6200 | F24: 5200 | G24: 6400
A25: MAY | B25: 10698 | C25: 4921 | D25: 10100 | E25: 7400 | F25: 5700 | G25: 7300
A26: JUN | B26: 9219 | C26: 5070 | D26: 11100 | E26: 7900 | F26: 5250 | G26: 7800
A27: JUL | B27: 7448 | C27: 4022 | D27: 10900 | E27: 7100 | F27: 5750 | G27: 7400
A28: AUG | B28: 5969 | C28: 3462 | D28: 9800 | E28: 6500 | F28: 4800 | G28: 6800
A29: SEP | B29: 5240 | C29: 2987 | D29: 8200 | E29: 7000 | F29: 5300 | G29: 7200
A30: OCT | B30: 5490 | C30: 3020 | D30: 6700 | E30: 8100 | F30: 5000 | G30: 8000
A31: NOV | B31: 6646 | C31: 3722 | D31: 5450 | E31: 8800 | F31: 5300 | G31: 7700
A32: DEC | B32: 8333 | C32: 3750 | D32: 8181 | E32: 6969 | F32: 5151 | G32: 7171
A33: Grand Total | B33: 100001 | C33: 52168 | D33: 97631 | E33: 86869 | F33: 61601 | G33: 86371

Sheet Data
C1: Visitors & Buyers | F1: Profit Performance | J1: Equity | O1: Debt | T1: Task Manager
A2: Year | B2: Month | C2: Visitors | D2: Buyers | E2: Conversion | F2: Profit | G2: Plan | H2: Break-Even Point | I2: Debt | J2: ETask 1 | K2: ETask 2 | L2: ETask 3 | M2: ETask 4 | N2: ETask 5 | O2: DTask 1 | P2: DTask 2 | Q2: DTask 3 | R2: DTask 4 | S2: DTask 5 | T2: Task 1 | U2: Task 2 | V2: Task 3 | W2: Task 4 | X2: Task 5
A3: 2025 | B3: JAN | C3: 5270 | D3: 816 | E3: 0.13 | F3: 8080 | G3: 7575 | H3: 4545 | I3: 7070 | J3: 47096 | K3: 28182 | L3: 13507 | M3: 32366 | N3: 46241 | O3: 37321 | P3: 28729 | Q3: 20315 | R3: 29726 | S3: 39202 | T3: 0.13 | U3: 0.17 | V3: 0.05 | W3: 0.12 | X3: 0.07
A4: 2025 | B4: FEB | C4: 5270 | D4: 2080 | E4: 0.1 | F4: 6443.8 | G4: 8484 | H4: 5050 | I4: 8181 | J4: 33425 | K4: 35068 | L4: 26642 | M4: 24449 | N4: 34073 | O4: 29349 | P4: 28895 | Q4: 23165 | R4: 26403 | S4: 34380 | T4: 0.14 | U4: 0.19 | V4: 0.09 | W4: 0.14 | X4: 0.09
A5: 2025 | B5: MAR | C5: 7150 | D5: 1200 | E5: 0.12 | F5: 5322.7 | G5: 8888 | H5: 5050 | I5: 7575 | J5: 31885 | K5: 16048 | L5: 29495 | M5: 41274 | N5: 31697 | O5: 27610 | P5: 21140 | Q5: 25957 | R5: 35532 | S5: 34006 | T5: 0.26 | U5: 0.31 | V5: 0.13 | W5: 0.26 | X5: 0.21
A6: 2025 | B6: APR | C6: 7150 | D6: 3440 | E6: 0.12 | F6: 5080.3 | G6: 8282 | H6: 5555 | I6: 7979 | J6: 22137 | K6: 23255 | L6: 38004 | M6: 36927 | N6: 22468 | O6: 22753 | P6: 21567 | Q6: 29541 | R6: 35391 | S6: 35639 | T6: 0.29 | U6: 0.33 | V6: 0.33 | W6: 0.28 | X6: 0.23
A7: 2025 | B7: MAY | C7: 8000 | D7: 2640 | E7: 0.08 | F7: 5787.3 | G7: 6767 | H7: 4040 | I7: 6969 | J7: 24618 | K7: 25243 | L7: 35565 | M7: 35034 | N7: 26135 | O7: 21495 | P7: 26087 | Q7: 33496 | R7: 33233 | S7: 30826 | T7: 0.3 | U7: 0.35 | V7: 0.35 | W7: 0.3 | X7: 0.25
A8: 2025 | B8: JUN | C8: 8000 | D8: 3752 | E8: 0.15 | F8: 7221.5 | G8: 5959 | H8: 4545 | I8: 6161 | J8: 30192 | K8: 35630 | L8: 34117 | M8: 25597 | N8: 23426 | O8: 21890 | P8: 31229 | Q8: 34093 | R8: 28849 | S8: 23972 | T8: 0.33 | U8: 0.37 | V8: 0.47 | W8: 0.32 | X8: 0.27
A9: 2025 | B9: JUL | C9: 9620 | D9: 5080 | E9: 0.16 | F9: 8938.5 | G9: 6060 | H9: 5050 | I9: 6363 | J9: 35662 | K9: 44346 | L9: 36069 | M9: 17107 | N9: 19982 | O9: 24628 | P9: 37241 | Q9: 31466 | R9: 23634 | S9: 22879 | T9: 0.65 | U9: 0.68 | V9: 0.49 | W9: 0.63 | X9: 0.58
A10: 2025 | B10: AUG | C10: 9620 | D10: 4120 | E10: 0.08 | F10: 10372.7 | G10: 7272 | H10: 5555 | I10: 7171 | J10: 33610 | K10: 47170 | L10: 43682 | M10: 17055 | N10: 19915 | O10: 30652 | P10: 39310 | Q10: 28760 | R10: 21834 | S10: 22740 | T10: 0.7 | U10: 0.72 | V10: 0.51 | W10: 0.67 | X10: 0.62
A11: 2025 | B11: SEP | C11: 10270 | D11: 5496 | E11: 0.14 | F11: 11079.7 | G11: 7827.5 | H11: 5050 | I11: 7676 | J11: 24123 | K11: 38184 | L11: 49500 | M11: 25194 | N11: 21174 | O11: 36033 | P11: 39496 | Q11: 23447 | R11: 20036 | S11: 25161 | T11: 0.83 | U11: 0.84 | V11: 0.53 | W11: 0.79 | X11: 0.74
A12: 2025 | B12: OCT | C12: 10270 | D12: 6680 | E12: 0.16 | F12: 10837.3 | G12: 7019.5 | H12: 5555 | I12: 7272 | J12: 19319 | K12: 26910 | L12: 47133 | M12: 38235 | N12: 27042 | O12: 35598 | P12: 34070 | Q12: 21694 | R12: 20990 | S12: 28479 | T12: 0.9 | U12: 0.9 | V12: 0.84 | W12: 0.85 | X12: 0.8
A13: 2025 | B13: NOV | C13: 10970 | D13: 5000 | E13: 0.12 | F13: 9716.2 | G13: 6413.5 | H13: 4545 | I13: 6666 | J13: 20157 | K13: 21395 | L13: 37271 | M13: 43962 | N13: 32890 | O13: 31843 | P13: 26922 | Q13: 20419 | R13: 23808 | S13: 32786 | T13: 0.93 | U13: 0.93 | V13: 0.88 | W13: 0.88 | X13: 0.83
A14: 2025 | B14: DEC | C14: 10970 | D14: 6400 | E14: 0.15 | F14: 5600 | G14: 8500 | H14: 5200 | I14: 7500 | J14: 26580 | K14: 20295 | L14: 24594 | M14: 40417 | N14: 39835 | O14: 27075 | P14: 23262 | Q14: 21889 | R14: 28863 | S14: 36582 | T14: 1 | U14: 1 | V14: 1 | W14: 0.95 | X14: 0.9
... A50: 2028 | B50: DEC | C50: 7800 | D50: 3432 | E50: 0.14 | F50: 5151 | G50: 8938.5 | H50: 5403.5 | I50: 7423.5 | J50: 30878 | K50: 26284 | L50: 31862 | M50: 31846 | N50: 26150 | O50: 23325 | P50: 29676 | Q50: 35309 | R50: 33641 | S50: 24033 | T50: 0.96 | U50: 1 | V50: 1 | W50: 0.95 | X50: 0.9

Sheet Resource
B1: 067D70 | E1: [>=1000000]#,, "M";[>=1000]#,"k";#
B2: 249987
B3: 3FA48E
B4: 49AA91
A6: Line | B6: #73C3AE
B8: #068275
B9: 6966
A11: Line | B11: #9FE1D8 | C11: 0.54
B13: #70D2C3
B14: #329E8F
B15: #C2F1C8
B16: 00C9AD
B18: 95B1AF
B19: #156082
B21: 2C78A7
B22: 8377
B23: CE2C35
B24: FA7E31
B25: 99699
A27: Line | B27: #9482D7
B28: #F181F2
A29: Line | B29: #297F73
