Workbook
Name Slicer_Year: #N/A

Sheet DASHBOARD
A5: 49
E8: =Processing!A1 -> Expense | I8: =Processing!C1 -> Markup | J8: Revenue | M8: Profit | R8: =Processing!C5 -> Margin
E10: =Processing!B6 -> 751576.82 | I10: =A5/100 -> 0.49 | J10: =Processing!C4 -> 890325.41 | M10: =J10-E10 -> 138748.59 | Q10: =IF(Processing!C6>Processing!C9,"↑","↓") -> ↑ | R10: =Processing!C6 -> 0.15584031

Sheet Processing
A1: Expense | C1: Markup | F1: Credit Capacity | G1: Use Loan Capital | H1: Indent | J1: Debt Service Ratio | M1: 1 | N1: -1
A2: Debt | B2: =G5+G5*F8 -> 369602.82 | C2: =DASHBOARD!I10 -> 0.49 | E2: 1 | F2: =E2-E4 -> 0.5 | G2: =E4 -> 0.5 | H2: 0.1 | J2: =B2/C4 -> 0.41513228 | K2: =100%-J2-L2 -> 0.4290274 | L2: =C6 -> 0.15584031 | M2: =SIN((J2+0.75)*2*PI())*M1 -> 0.86116482 | N2: =COS((K2+L2+0.75)*2*PI())*N1 -> 0.50832583 | O2: Light 1
A3: Marketing | B3: =GETPIVOTDATA(""&A3,Control!$A$3) -> 81480 | C3: Revenue | E3: 5 | F3: =$H$2 -> 0.1 | G3: =$H$2 -> 0.1 | M3: =SIN((J2+K2+0.75)*2*PI())*M1 -> -0.55770871 | N3: =COS((L2+0.75)*2*PI())*N1 -> -0.83003674 | O3: Light 2
A4: Operating | B4: =GETPIVOTDATA(""&A4,Control!$A$3) -> 214945 | C4: =GETPIVOTDATA("Sum of Revenue",Control!$A$3)+(G5+G5*C2) -> 890325.41 | E4: =E2/10*E3 -> 0.5 | F4: =100%-F2 -> 0.5 | G4: =F2 -> 0.5 | M4: X | N4: Y
A5: Other | B5: =GETPIVOTDATA(""&A5,Control!$A$3) -> 85549 | C5: Margin | F5: =GETPIVOTDATA("Sum of Credit Capacity",Control!$A$3)*Processing!F2 -> 324213 | G5: =GETPIVOTDATA("Sum of Credit Capacity",Control!$A$3)*Processing!G2 -> 324213
A6: Total | B6: =SUM(B2:B5) -> 751576.82 | C6: =(C4-B6)/C4 -> 0.15584031
F7: Loan Interest | G7: Loan Body | H7: Indent
C8: Margin Without Loan Impact | F8: =GETPIVOTDATA("Average of Interest Rate",Control!$A$3) -> 0.14 | G8: =100%-F8 -> 0.86 | H8: 0.1
C9: =(GETPIVOTDATA("Sum of Revenue",Control!$A$3)-SUM(B3:B5))/GETPIVOTDATA("Sum of Revenue",Control!$A$3) -> 0.062060557 | G9: =$H$8 -> 0.1
G10: =100%-G8 -> 0.14
G11: =$H$8 -> 0.1

Sheet Control
A3: Row Labels | B3: Sum of Credit Capacity | C3: Average of Interest Rate | D3: Sum of Revenue | E3: Sum of Marketing | F3: Sum of Operating | G3: Sum of Other
A4: 2026 | B4: 648426 | C4: 0.14 | D4: 407248.04 | E4: 81480 | F4: 214945 | G4: 85549
A5: Grand Total | B5: 648426 | C5: 0.14 | D5: 407248.04 | E5: 81480 | F5: 214945 | G5: 85549

Sheet Data
A1: Year | B1: Credit Capacity | C1: Interest Rate | D1: Revenue | E1: Marketing | F1: Operating | G1: Other
A2: 2025 | B2: 345005 | C2: 0.15 | D2: 293774.13 | E2: 61673 | F2: 145136 | G2: 62186
A3: 2026 | B3: 648426 | C3: 0.14 | D3: 407248.04 | E3: 81480 | F3: 214945 | G3: 85549
A4: 2027 | B4: 878224 | C4: 0.13 | D4: 477287.21 | E4: 108868 | F4: 255634 | G4: 94374
A5: 2028 | B5: 656592 | C5: 0.12 | D5: 373908.68 | E5: 86495 | F5: 201531 | G5: 85782

Sheet R
B2: #F94A1A
B4: #1AFFD5
B5: #00B491
B7: #0088FE
B8: #005DB2
B10: #23272D
B11: #13171A
B13: #2E353B
