Workbook
Name bigdata: 'Structuring Data'!$A$1:$BB$399
Name Slicer_Day1: #N/A
Name Slicer_Month1: #N/A

Sheet DASHBOARD

Sheet DASHBOARD Light

Sheet Budgeting

Sheet Budgeting Light

Sheet Income

Sheet Income Light

Sheet Expenses

Sheet Expenses Light

Sheet Investments

Sheet Investments Light

Sheet Debts

Sheet Debts Light
G51: https://exceltable.com/en/templates/download-personal-finances-template

Sheet Financial Goals
G51: https://exceltable.com/en/templates/download-personal-finances-template
H53: https://exceltable.com/en/templates/download-personal-finances-template

Sheet Financial Goals Light

Sheet Processing
A1: Dashboard | B1: Year | C1: ='Structuring Data'!C2 -> 2024 | D1: Month | E1: =Control!B2 -> 6 | F1: Calendar | G1: Today: | H1: {="Today: "&DAY(I1)&" "&INDEX(B4:B15,MONTH(I1))&" "&YEAR(I1)} -> Today: 18 SEPTEMBER 2026 | I1: =TODAY() -> 46283 | K1: Balance: | L1: {=SUM(Data!$BN$2:$BN$367*(--(Data!$A$2:$A$367=DATE(Processing!$C$1,Processing!$E$1,MAX($L$26:$L$56)))))} -> 714 | N1: Budget Plan | Q1: Labels | R1: Pie Chart | S1: Budgeting
A2: =C3&" & "&D3 -> Income & Expenses | E2: {=INDEX($B$4:$B$15,E1)} -> JUNE | F2: Personal Finance | H2: Ratio Income | N2: Non-Fixed Incom | O2: =P2/($P$8+$P$9) -> 0.20678704 | P2: =GETPIVOTDATA(""&N2,Control!$A$7) -> 11590 | R2: =$O$2 -> 0.20678704 | S2: =$O$3 -> 0.26768127 | T2: =$O$4 -> 0.082393663 | U2: =$O$5 -> 0.16114759 | V2: =$O$6 -> 0.21544034 | W2: =$O$7 -> 0.0665501
A3: № | B3: Month | C3: Income | D3: Expenses | E3: Income | F3: Expenses | H3: Income | I3: Expenses | N3: Fixed Incom | O3: =P3/($P$8+$P$9) -> 0.26768127 | P3: =GETPIVOTDATA(""&N3,Control!$A$7) -> 15003 | Q3: =P8 -> 31211 | R3: =$O$2 -> 0.20678704 | S3: =$O$3 -> 0.26768127 | T3: =$O$4 -> 0.082393663 | U3: =$O$5 -> 0.16114759 | V3: =$O$6 -> 0.21544034 | W3: =$O$7 -> 0.0665501
A4: 1 | B4: JANUARY | C4: =SUMIF('Structuring Data'!$D$2:$D$399,B4,'Structuring Data'!$F$2:$F$399) -> 18166 | D4: =SUMIF('Structuring Data'!$D$2:$D$399,B4,'Structuring Data'!$G$2:$G$399) -> 20397 | E4: =C4/SUM(C4:D4) -> 0.47107331 | F4: =D4/SUM(C4:D4) -> 0.52892669 | H4: {=INDEX(E4:E15,$E$1)} -> 0.55686198 | I4: {=INDEX(F4:F15,$E$1)} -> 0.44313802 | N4: Other Income | O4: =P4/($P$8+$P$9) -> 0.082393663 | P4: =GETPIVOTDATA(""&N4,Control!$A$7) -> 4618 | Q4: =N2&CHAR(10)&N3&CHAR(10)&N4&CHAR(10)&CHAR(10)&CHAR(10)&CHAR(10)&N5&CHAR(10)&N6&CHAR(10)&N7 -> Non-Fixed Incom Fixed Incom Other Income Non-Fixed Cost Fixed Costs Other Cost | R4: =$O$2 -> 0.20678704 | S4: =$O$3 -> 0.26768127 | T4: =$O$4 -> 0.082393663 | U4: =$O$5 -> 0.16114759 | V4: =$O$6 -> 0.21544034 | W4: =$O$7 -> 0.0665501
A5: 2 | B5: FEBRUARY | C5: =SUMIF('Structuring Data'!$D$2:$D$399,B5,'Structuring Data'!$F$2:$F$399) -> 19801 | D5: =SUMIF('Structuring Data'!$D$2:$D$399,B5,'Structuring Data'!$G$2:$G$399) -> 26548 | E5: =C5/SUM(C5:D5) -> 0.42721526 | F5: =D5/SUM(C5:D5) -> 0.57278474 | N5: Non-Fixed Cost | O5: =P5/($P$8+$P$9) -> 0.16114759 | P5: =GETPIVOTDATA(""&N5,Control!$A$7) -> 9032 | Q5: =TEXT(O2,"0%")&CHAR(10)&TEXT(O3,"0%")&CHAR(10)&TEXT(O4,"0%")&CHAR(10)&CHAR(10)&CHAR(10)&CHAR(10)&TEXT(O5,"0%")&CHAR(10)&TEXT(O6,"0%")&CHAR(10)&TEXT(O7,"0%") -> 21% 27% 8% 16% 22% 7%
A6: 3 | B6: MARCH | C6: =SUMIF('Structuring Data'!$D$2:$D$399,B6,'Structuring Data'!$F$2:$F$399) -> 22196 | D6: =SUMIF('Structuring Data'!$D$2:$D$399,B6,'Structuring Data'!$G$2:$G$399) -> 22099 | E6: =C6/SUM(C6:D6) -> 0.50109493 | F6: =D6/SUM(C6:D6) -> 0.49890507 | H6: Cursors | N6: Fixed Costs | O6: =P6/($P$8+$P$9) -> 0.21544034 | P6: =GETPIVOTDATA(""&N6,Control!$A$7) -> 12075 | Q6: =TEXT(P2,"$ 0 0")&CHAR(10)&TEXT(P3,"$ 0 0")&CHAR(10)&TEXT(P4,"$ 0 0")&CHAR(10)&CHAR(10)&CHAR(10)&CHAR(10)&TEXT(P5,"$ 0 0")&CHAR(10)&TEXT(P6,"$ 0 0")&CHAR(10)&TEXT($P7,"$ 0 0") -> $ 11 590 $ 15 003 $ 4 618 $ 9 032 $ 12 075 $ 3 730
A7: 4 | B7: APRIL | C7: =SUMIF('Structuring Data'!$D$2:$D$399,B7,'Structuring Data'!$F$2:$F$399) -> 25558 | D7: =SUMIF('Structuring Data'!$D$2:$D$399,B7,'Structuring Data'!$G$2:$G$399) -> 19614 | E7: =C7/SUM(C7:D7) -> 0.56579297 | F7: =D7/SUM(C7:D7) -> 0.43420703 | H7: X | I7: Y | K7: X | L7: Y | N7: Other Cost | O7: =P7/($P$8+$P$9) -> 0.0665501 | P7: =GETPIVOTDATA(""&N7,Control!$A$7) -> 3730 | Q7: Used Budget
A8: 5 | B8: MAY | C8: =SUMIF('Structuring Data'!$D$2:$D$399,B8,'Structuring Data'!$F$2:$F$399) -> 31043 | D8: =SUMIF('Structuring Data'!$D$2:$D$399,B8,'Structuring Data'!$G$2:$G$399) -> 24519 | E8: =C8/SUM(C8:D8) -> 0.55870919 | F8: =D8/SUM(C8:D8) -> 0.44129081 | G8: Income | H8: =E1 -> 6 | I8: {=INDEX(C4:C15,$E$1)} -> 31211 | K8: 0 | L8: 1 | N8: Total Incom | O8: =O2+O3+O4 -> 0.55686198 | P8: =P2+P3+P4 -> 31211 | Q8: =J58 -> 0.79577713 | R8: =1-Q8 -> 0.20422287
A9: 6 | B9: JUNE | C9: =SUMIF('Structuring Data'!$D$2:$D$399,B9,'Structuring Data'!$F$2:$F$399) -> 31211 | D9: =SUMIF('Structuring Data'!$D$2:$D$399,B9,'Structuring Data'!$G$2:$G$399) -> 24837 | E9: =C9/SUM(C9:D9) -> 0.55686198 | F9: =D9/SUM(C9:D9) -> 0.44313802 | G9: Expenses | H9: =E1 -> 6 | I9: {=INDEX(D4:D15,$E$1)} -> 24837 | K9: =SIN(H4*2*PI()) -> -0.34972198 | L9: =COS(I4*2*PI()) -> -0.93685353 | N9: Total Expenses | O9: =O5+O6+O7 -> 0.44313802 | P9: =P5+P6+P7 -> 24837
A10: 7 | B10: JULY | C10: =SUMIF('Structuring Data'!$D$2:$D$399,B10,'Structuring Data'!$F$2:$F$399) -> 30268 | D10: =SUMIF('Structuring Data'!$D$2:$D$399,B10,'Structuring Data'!$G$2:$G$399) -> 21183 | E10: =C10/SUM(C10:D10) -> 0.58828789 | F10: =D10/SUM(C10:D10) -> 0.41171211
A11: 8 | B11: AUGUST | C11: =SUMIF('Structuring Data'!$D$2:$D$399,B11,'Structuring Data'!$F$2:$F$399) -> 35419 | D11: =SUMIF('Structuring Data'!$D$2:$D$399,B11,'Structuring Data'!$G$2:$G$399) -> 22263 | E11: =C11/SUM(C11:D11) -> 0.61403904 | F11: =D11/SUM(C11:D11) -> 0.38596096
A12: 9 | B12: SEPTEMBER | C12: =SUMIF('Structuring Data'!$D$2:$D$399,B12,'Structuring Data'!$F$2:$F$399) -> 35296 | D12: =SUMIF('Structuring Data'!$D$2:$D$399,B12,'Structuring Data'!$G$2:$G$399) -> 25507 | E12: =C12/SUM(C12:D12) -> 0.58049767 | F12: =D12/SUM(C12:D12) -> 0.41950233 | Q12: Financial Goals
A13: 10 | B13: OCTOBER | C13: =SUMIF('Structuring Data'!$D$2:$D$399,B13,'Structuring Data'!$F$2:$F$399) -> 33397 | D13: =SUMIF('Structuring Data'!$D$2:$D$399,B13,'Structuring Data'!$G$2:$G$399) -> 20455 | E13: =C13/SUM(C13:D13) -> 0.62016267 | F13: =D13/SUM(C13:D13) -> 0.37983733 | R13: Goal Decomposition | T13: label
A14: 11 | B14: NOVEMBER | C14: =SUMIF('Structuring Data'!$D$2:$D$399,B14,'Structuring Data'!$F$2:$F$399) -> 33613 | D14: =SUMIF('Structuring Data'!$D$2:$D$399,B14,'Structuring Data'!$G$2:$G$399) -> 26772 | E14: =C14/SUM(C14:D14) -> 0.55664486 | F14: =D14/SUM(C14:D14) -> 0.44335514 | Q14: 217000 | R14: 0.4425 | T14: =Q14*R15 -> 64665.195
A15: 12 | B15: DECEMBER | C15: =SUMIF('Structuring Data'!$D$2:$D$399,B15,'Structuring Data'!$F$2:$F$399) -> 36231 | D15: =SUMIF('Structuring Data'!$D$2:$D$399,B15,'Structuring Data'!$G$2:$G$399) -> 24419 | E15: =C15/SUM(C15:D15) -> 0.5973784 | F15: =D15/SUM(C15:D15) -> 0.4026216 | Q15: 8 | R15: =AVERAGE(R18:X18) -> 0.29799629 | T15: =X22&CHAR(10)&V22&CHAR(10)&T22&CHAR(10)&R22 -> Goal 1 Goal 2 Goal 3 Goal 4
H16: Investments | I16: =SUM(H17:H21) -> 89000 | Q16: =AVERAGE(AA21:AD21) -> 0.74675325 | T16: =TEXT(W29,"$0 0")&CHAR(10)&TEXT(V29,"$0 0")&CHAR(10)&TEXT(X29,"$0 0")&CHAR(10)&TEXT(Y29,"$0 0") -> $65 000 $77 000 $58 000 $30 000
A17: Debts | B17: Interest Rate | C17: Amount of Debt | E17: Top | G17: Business | H17: {=SUM(Data!$AZ$2:$AZ$367*(--(Data!$A$2:$A$367=DATE(Processing!$C$1,Processing!$E$1,MAX($L$26:$L$56)))))} -> 27590 | I17: =H17/$I$16 -> 0.31 | J17: =$I17 -> 0.31 | K17: =$I17 -> 0.31 | L17: =$I17 -> 0.31 | M17: =$I17 -> 0.31 | Q17: Plan ON | R17: TRUE | AA17: Goal Management
A18: {=INDEX($A$23:$B$26,MATCH($C18,$C$23:$C$26,0),COLUMN())} -> Mortgage | B18: {=INDEX($A$23:$B$26,MATCH($C18,$C$23:$C$26,0),COLUMN())} -> 0.03 | C18: =LARGE($C$23:$C$26,D18) -> 29000 | D18: 1 | E18: =C18/SUM($C$27:$C$28) -> 0.2815534 | G18: Securities | H18: {=SUM(Data!$BA$2:$BA$367*(--(Data!$A$2:$A$367=DATE(Processing!$C$1,Processing!$E$1,MAX($L$26:$L$56)))))} -> 12460 | I18: =H18/$I$16 -> 0.14 | J18: =$I18 -> 0.14 | K18: =$I18 -> 0.14 | L18: =$I18 -> 0.14 | M18: =$I18 -> 0.14 | Q18: =IF(R17,Q16,NA()) -> 0.74675325 | R18: =(1-R20)*Y27/Y29 -> 0.15554545 | S18: =R18 -> 0.15554545 | T18: =(1-T20)*X27/X29 -> 0.27824675 | U18: =T18 -> 0.27824675 | V18: =(1-V20)*W27/W29 -> 0.29564935 | W18: =V18 -> 0.29564935 | X18: =(1-X20)*V27/V29 -> 0.62709091 | Y18: Done | Z18: Finish | AA18: =V29 -> 77000 | AB18: =W29 -> 65000 | AC18: =X29 -> 58000 | AD18: =Y29 -> 30000
A19: {=INDEX($A$23:$B$26,MATCH($C19,$C$23:$C$26,0),COLUMN())} -> Credit Card | B19: {=INDEX($A$23:$B$26,MATCH($C19,$C$23:$C$26,0),COLUMN())} -> 0.095 | C19: =LARGE($C$23:$C$26,D19) -> 17694 | D19: 2 | G19: Gold | H19: {=SUM(Data!$BB$2:$BB$367*(--(Data!$A$2:$A$367=DATE(Processing!$C$1,Processing!$E$1,MAX($L$26:$L$56)))))} -> 22250 | I19: =H19/$I$16 -> 0.25 | J19: =$I19 -> 0.25 | K19: =$I19 -> 0.25 | L19: =$I19 -> 0.25 | M19: =$I19 -> 0.25 | Q19: =IF(R17,1%,NA()) -> 0.01 | R19: =(1-R20)-R18 -> 0.23406494 | S19: =R19 -> 0.23406494 | T19: =(1-T20)-T18 -> 0.475 | U19: =T19 -> 0.475 | V19: =(1-V20)-V18 -> 0.54850649 | W19: =V19 -> 0.54850649 | X19: =(1-X20)-X18 -> 0.37290909 | Y19: Running | Z19: Start | AA19: =V27 -> 48286 | AB19: =W27 -> 22765 | AC19: =X27 -> 21425 | AD19: =Y27 -> 11977
A20: {=INDEX($A$23:$B$26,MATCH($C20,$C$23:$C$26,0),COLUMN())} -> Car Leasing | B20: {=INDEX($A$23:$B$26,MATCH($C20,$C$23:$C$26,0),COLUMN())} -> 0.05 | C20: =LARGE($C$23:$C$26,D20) -> 13750 | D20: 3 | G20: Real estate | H20: {=SUM(Data!$BC$2:$BC$367*(--(Data!$A$2:$A$367=DATE(Processing!$C$1,Processing!$E$1,MAX($L$26:$L$56)))))} -> 13350 | I20: =H20/$I$16 -> 0.15 | J20: =$I20 -> 0.15 | K20: =$I20 -> 0.15 | L20: =$I20 -> 0.15 | M20: =$I20 -> 0.15 | Q20: =1-SUM(Q18:Q19) -> 0.24324675 | R20: =1-Y29/V30 -> 0.61038961 | S20: =R20 -> 0.61038961 | T20: =1-X29/V30 -> 0.24675325 | U20: =T20 -> 0.24675325 | V20: =1-W29/V30 -> 0.15584416 | W20: =V20 -> 0.15584416 | X20: =1-V29/V30 -> 0 | Y20: Reserve | AA20: Goal 1 | AB20: Goal 2 | AC20: Goal 3 | AD20: Goal 4
A21: {=INDEX($A$23:$B$26,MATCH($C21,$C$23:$C$26,0),COLUMN())} -> Consumer Credit | B21: {=INDEX($A$23:$B$26,MATCH($C21,$C$23:$C$26,0),COLUMN())} -> 0.07 | C21: =LARGE($C$23:$C$26,D21) -> 6498 | D21: 4 | G21: Cryptocurrency | H21: {=SUM(Data!$BD$2:$BD$367*(--(Data!$A$2:$A$367=DATE(Processing!$C$1,Processing!$E$1,MAX($L$26:$L$56)))))} -> 13350 | I21: =H21/$I$16 -> 0.15 | J21: =$I21 -> 0.15 | K21: =$I21 -> 0.15 | L21: =$I21 -> 0.15 | M21: =$I21 -> 0.15 | Q21: =IF(R17,R21,NA()) -> 0.34 | R21: 0.34 | S21: =R21 -> 0.34 | T21: 0.34 | U21: =T21 -> 0.34 | V21: 0.34 | W21: =V21 -> 0.34 | X21: 0.34 | AA21: =R18+R19 -> 0.38961039 | AB21: =T18+T19 -> 0.75324675 | AC21: =V18+V19 -> 0.84415584 | AD21: =X18+X19 -> 1
A22: Total Debt Amount | I22: =SUM(I17:I21) -> 1 | J22: =SUM(J17:J21) -> 1 | K22: =SUM(K17:K21) -> 1 | L22: =SUM(L17:L21) -> 1 | M22: =SUM(M17:M21) -> 1 | R22: Goal 4 | T22: Goal 3 | V22: Goal 2 | X22: Goal 1
A23: Mortgage | B23: 0.03 | C23: {=SUM(Data!$BE$2:$BE$367*(--(Data!$A$2:$A$367=DATE(Processing!$C$1,Processing!$E$1,MAX($L$26:$L$56)))))} -> 29000 | D23: =C23/SUM($C$27:$C$28) -> 0.2815534 | S23: =Y28/Y29 -> 0.60076667
A24: Car Leasing | B24: 0.05 | C24: {=SUM(Data!$BF$2:$BF$367*(--(Data!$A$2:$A$367=DATE(Processing!$C$1,Processing!$E$1,MAX($L$26:$L$56)))))} -> 13750 | D24: =C24/SUM($C$27:$C$28) -> 0.13349515 | I24: Income Budget | J24: Expenses Budget | L24: Portfolio Capitalization | O24: {=INDEX(Data!$AY$2:$AY$367,MATCH(TRUE,Data!$AY$2:$AY$367>0,0))} -> 117000 | S24: =Y29/V29 -> 0.38961039 | AH24: Incom by Days
A25: Consumer Credit | B25: 0.07 | C25: {=SUM(Data!$BG$2:$BG$367*(--(Data!$A$2:$A$367=DATE(Processing!$C$1,Processing!$E$1,MAX($L$26:$L$56)))))} -> 6498 | D25: =C25/SUM($C$27:$C$28) -> 0.063087379 | H25: Day | K25: back | L25: Select Days | M25: Days | N25: Price | O25: Start Price | P25: Mirror | Q25: Days | R25: Closing Debts | T25: back | V25: Implementation | Z25: Check List | AA25: Distribution | AG25: Day | AH25: Fixed Incom | AI25: Non-Fixed Incom | AJ25: back | AL25: Day | AM25: Fixed Cost | AN25: Non-Fixed Cost | AO25: back
A26: Credit Card | B26: 0.095 | C26: {=SUM(Data!$BH$2:$BH$367*(--(Data!$A$2:$A$367=DATE(Processing!$C$1,Processing!$E$1,MAX($L$26:$L$56)))))} -> 17694 | D26: =C26/SUM($C$27:$C$28) -> 0.17178641 | F26: JANUARY | G26: =DAY(EOMONTH(DATE($C$1,H26,1),0)) -> 31 | H26: 1 | I26: {=IFERROR(GETPIVOTDATA(""&$N$2,Control!$A$7,""&$H$25,H26)+GETPIVOTDATA(""&$N$3,Control!$A$7,""&$H$25,H26)+GETPIVOTDATA(""&$N$4,Control!$A$7,""&$H$25,H26),NA())} -> 1117 | J26: {=IFERROR(GETPIVOTDATA(""&$N$5,Control!$A$7,""&$H$25,H26)+GETPIVOTDATA(""&$N$6,Control!$A$7,""&$H$25,H26)+GETPIVOTDATA(""&$N$7,Control!$A$7,""&$H$25,H26),NA())} -> 833 | K26: {=SUM(Data!$D$2:$F$367*(--(Data!$A$2:$A$367=DATE(Processing!$C$1,Processing!$E$1,Processing!H26))))} -> 1117 | L26: =IF(ISNA(I26),0,H26) -> 1 | M26: =H26 -> 1 | N26: {=IF(ISNA(I26),NA(),SUM(Data!$AY$2:$AY$367*(--(Data!$A$2:$A$367=DATE(Processing!$C$1,Processing!$E$1,Processing!H26)))))} -> 106000 | O26: {=INDEX(Data!$AY$2:$AY$367,MATCH(TRUE,Data!$AY$2:$AY$367>0,0))} -> 117000 | P26: {=IFERROR(IF(NOT(ISNA(I26)),NA(),SUM(Data!$AY$2:$AY$367*(--(Data!$A$2:$A$367=DATE(Processing!$C$1,Processing!$E$1,Processing!H26))))),NA())} -> #N/A | Q26: =H26 -> 1 | R26: {=IF(ISNA(I26),NA(),SUM(Data!$BE$2:$BH$367*(--(Data!$A$2:$A$367=DATE(Processing!$C$1,Processing!$E$1,Processing!H26)))))} -> 74443 | S26: =(R26>0)*$C$28 -> 36058 | T26: {=ISNUMBER(Q26)*SUM(Data!$BE$2:$BH$367*(--(Data!$A$2:$A$367=DATE(Processing!$C$1,Processing!$E$1,Processing!H26))))} -> 74443 | U26: Goals | V26: 1 | W26: 2 | X26: 3 | Y26: 4 | Z26: Total | AA26: Goal 1 | AB26: Goal 2 | AC26: Goal 3 | AD26: Goal 4 | AG26: =H26 -> 1 | AH26: {=IF(ISNA(I26),NA(),SUM(Data!$J$2:$S$367*(--(Data!$A$2:$A$367=DATE(Processing!$C$1,Processing!$E$1,Processing!H26)))))} -> 1117 | AI26: {=IF(ISNA(I26),NA(),SUM(Data!$O$2:$S$367*(--(Data!$A$2:$A$367=DATE(Processing!$C$1,Processing!$E$1,Processing!H26)))))} -> 385 | AJ26: {=SUM(Data!$J$2:$S$367*(--(Data!$A$2:$A$367=DATE(Processing!$C$1,Processing!$E$1,Processing!H26))))} -> 1117 | AL26: =H26 -> 1 | AM26: {=IF(ISNA(I26),NA(),SUM(Data!$T$2:$AX$367*(--(Data!$A$2:$A$367=DATE(Processing!$C$1,Processing!$E$1,Processing!H26)))))} -> 833 | AN26: {=IF(ISNA(I26),NA(),SUM(Data!$AP$2:$AX$367*(--(Data!$A$2:$A$367=DATE(Processing!$C$1,Processing!$E$1,Processing!H26)))))} -> 295 | AO26: {=SUM(Data!$T$2:$AX$367*(--(Data!$A$2:$A$367=DATE(Processing!$C$1,Processing!$E$1,Processing!H26))))} -> 833
A27: Total: | B27: Credit Funds | C27: =SUM(C23:C26) -> 66942 | F27: FEBRUARY | G27: =DAY(EOMONTH(DATE($C$1,H27,1),0)) -> 29 | H27: 2 | I27: {=IFERROR(GETPIVOTDATA(""&$N$2,Control!$A$7,""&$H$25,H27)+GETPIVOTDATA(""&$N$3,Control!$A$7,""&$H$25,H27)+GETPIVOTDATA(""&$N$4,Control!$A$7,""&$H$25,H27),NA())} -> 1093 | J27: {=IFERROR(GETPIVOTDATA(""&$N$5,Control!$A$7,""&$H$25,H27)+GETPIVOTDATA(""&$N$6,Control!$A$7,""&$H$25,H27)+GETPIVOTDATA(""&$N$7,Control!$A$7,""&$H$25,H27),NA())} -> 846 | K27: {=SUM(Data!$D$2:$F$367*(--(Data!$A$2:$A$367=DATE(Processing!$C$1,Processing!$E$1,Processing!H27))))} -> 1093 | L27: =IF(ISNA(I27),0,H27) -> 2 | M27: =H27 -> 2 | N27: {=IF(ISNA(I27),NA(),SUM(Data!$AY$2:$AY$367*(--(Data!$A$2:$A$367=DATE(Processing!$C$1,Processing!$E$1,Processing!H27)))))} -> 105333.5 | O27: {=INDEX(Data!$AY$2:$AY$367,MATCH(TRUE,Data!$AY$2:$AY$367>0,0))} -> 117000 | P27: {=IFERROR(IF(NOT(ISNA(I27)),NA(),SUM(Data!$AY$2:$AY$367*(--(Data!$A$2:$A$367=DATE(Processing!$C$1,Processing!$E$1,Processing!H27))))),NA())} -> #N/A | Q27: =H27 -> 2 | R27: {=IF(ISNA(I27),NA(),SUM(Data!$BE$2:$BH$367*(--(Data!$A$2:$A$367=DATE(Processing!$C$1,Processing!$E$1,Processing!H27)))))} -> 72807 | S27: =(R27>0)*$C$28 -> 36058 | T27: {=ISNUMBER(Q27)*SUM(Data!$BE$2:$BH$367*(--(Data!$A$2:$A$367=DATE(Processing!$C$1,Processing!$E$1,Processing!H27))))} -> 72807 | U27: Done | V27: {=INDEX($AA$33:$AD$44,$E$1,V26)} -> 48286 | W27: {=INDEX($AA$33:$AD$44,$E$1,W26)} -> 22765 | X27: {=INDEX($AA$33:$AD$44,$E$1,X26)} -> 21425 | Y27: {=INDEX($AA$33:$AD$44,$E$1,Y26)} -> 11977 | Z27: =SUM(V27:Y27) -> 104453 | AA27: =V27 -> 48286 | AB27: =W27 -> 22765 | AC27: =X27 -> 21425 | AD27: =Y27 -> 11977 | AG27: =H27 -> 2 | AH27: {=IF(ISNA(I27),NA(),SUM(Data!$J$2:$S$367*(--(Data!$A$2:$A$367=DATE(Processing!$C$1,Processing!$E$1,Processing!H27)))))} -> 1093 | AI27: {=IF(ISNA(I27),NA(),SUM(Data!$O$2:$S$367*(--(Data!$A$2:$A$367=DATE(Processing!$C$1,Processing!$E$1,Processing!H27)))))} -> 506 | AJ27: {=SUM(Data!$J$2:$S$367*(--(Data!$A$2:$A$367=DATE(Processing!$C$1,Processing!$E$1,Processing!H27))))} -> 1093 | AL27: =H27 -> 2 | AM27: {=IF(ISNA(I27),NA(),SUM(Data!$T$2:$AX$367*(--(Data!$A$2:$A$367=DATE(Processing!$C$1,Processing!$E$1,Processing!H27)))))} -> 846 | AN27: {=IF(ISNA(I27),NA(),SUM(Data!$AP$2:$AX$367*(--(Data!$A$2:$A$367=DATE(Processing!$C$1,Processing!$E$1,Processing!H27)))))} -> 333 | AO27: {=SUM(Data!$T$2:$AX$367*(--(Data!$A$2:$A$367=DATE(Processing!$C$1,Processing!$E$1,Processing!H27))))} -> 846
A28: Repayment | B28: Redeemed | C28: =C29-C27 -> 36058 | D28: =C28/SUM($C$27:$C$28) -> 0.35007767 | F28: MARCH | G28: =DAY(EOMONTH(DATE($C$1,H28,1),0)) -> 31 | H28: 3 | I28: {=IFERROR(GETPIVOTDATA(""&$N$2,Control!$A$7,""&$H$25,H28)+GETPIVOTDATA(""&$N$3,Control!$A$7,""&$H$25,H28)+GETPIVOTDATA(""&$N$4,Control!$A$7,""&$H$25,H28),NA())} -> 1063 | J28: {=IFERROR(GETPIVOTDATA(""&$N$5,Control!$A$7,""&$H$25,H28)+GETPIVOTDATA(""&$N$6,Control!$A$7,""&$H$25,H28)+GETPIVOTDATA(""&$N$7,Control!$A$7,""&$H$25,H28),NA())} -> 856 | K28: {=SUM(Data!$D$2:$F$367*(--(Data!$A$2:$A$367=DATE(Processing!$C$1,Processing!$E$1,Processing!H28))))} -> 1063 | L28: =IF(ISNA(I28),0,H28) -> 3 | M28: =H28 -> 3 | N28: {=IF(ISNA(I28),NA(),SUM(Data!$AY$2:$AY$367*(--(Data!$A$2:$A$367=DATE(Processing!$C$1,Processing!$E$1,Processing!H28)))))} -> 105201.7 | O28: {=INDEX(Data!$AY$2:$AY$367,MATCH(TRUE,Data!$AY$2:$AY$367>0,0))} -> 117000 | P28: {=IFERROR(IF(NOT(ISNA(I28)),NA(),SUM(Data!$AY$2:$AY$367*(--(Data!$A$2:$A$367=DATE(Processing!$C$1,Processing!$E$1,Processing!H28))))),NA())} -> #N/A | Q28: =H28 -> 3 | R28: {=IF(ISNA(I28),NA(),SUM(Data!$BE$2:$BH$367*(--(Data!$A$2:$A$367=DATE(Processing!$C$1,Processing!$E$1,Processing!H28)))))} -> 72807 | S28: =(R28>0)*$C$28 -> 36058 | T28: {=ISNUMBER(Q28)*SUM(Data!$BE$2:$BH$367*(--(Data!$A$2:$A$367=DATE(Processing!$C$1,Processing!$E$1,Processing!H28))))} -> 72807 | U28: Left | V28: =V29-V27 -> 28714 | W28: =W29-W27 -> 42235 | X28: =X29-X27 -> 36575 | Y28: =Y29-Y27 -> 18023 | Z28: =SUM(V28:Y28) -> 125547 | AG28: =H28 -> 3 | AH28: {=IF(ISNA(I28),NA(),SUM(Data!$J$2:$S$367*(--(Data!$A$2:$A$367=DATE(Processing!$C$1,Processing!$E$1,Processing!H28)))))} -> 1063 | AI28: {=IF(ISNA(I28),NA(),SUM(Data!$O$2:$S$367*(--(Data!$A$2:$A$367=DATE(Processing!$C$1,Processing!$E$1,Processing!H28)))))} -> 335 | AJ28: {=SUM(Data!$J$2:$S$367*(--(Data!$A$2:$A$367=DATE(Processing!$C$1,Processing!$E$1,Processing!H28))))} -> 1063 | AL28: =H28 -> 3 | AM28: {=IF(ISNA(I28),NA(),SUM(Data!$T$2:$AX$367*(--(Data!$A$2:$A$367=DATE(Processing!$C$1,Processing!$E$1,Processing!H28)))))} -> 856 | AN28: {=IF(ISNA(I28),NA(),SUM(Data!$AP$2:$AX$367*(--(Data!$A$2:$A$367=DATE(Processing!$C$1,Processing!$E$1,Processing!H28)))))} -> 272 | AO28: {=SUM(Data!$T$2:$AX$367*(--(Data!$A$2:$A$367=DATE(Processing!$C$1,Processing!$E$1,Processing!H28))))} -> 856
B29: Start Debt | C29: =SUM(Data!BE2:BH2) -> 103000 | F29: APRIL | G29: =DAY(EOMONTH(DATE($C$1,H29,1),0)) -> 30 | H29: 4 | I29: {=IFERROR(GETPIVOTDATA(""&$N$2,Control!$A$7,""&$H$25,H29)+GETPIVOTDATA(""&$N$3,Control!$A$7,""&$H$25,H29)+GETPIVOTDATA(""&$N$4,Control!$A$7,""&$H$25,H29),NA())} -> 1045 | J29: {=IFERROR(GETPIVOTDATA(""&$N$5,Control!$A$7,""&$H$25,H29)+GETPIVOTDATA(""&$N$6,Control!$A$7,""&$H$25,H29)+GETPIVOTDATA(""&$N$7,Control!$A$7,""&$H$25,H29),NA())} -> 859 | K29: {=SUM(Data!$D$2:$F$367*(--(Data!$A$2:$A$367=DATE(Processing!$C$1,Processing!$E$1,Processing!H29))))} -> 1045 | L29: =IF(ISNA(I29),0,H29) -> 4 | M29: =H29 -> 4 | N29: {=IF(ISNA(I29),NA(),SUM(Data!$AY$2:$AY$367*(--(Data!$A$2:$A$367=DATE(Processing!$C$1,Processing!$E$1,Processing!H29)))))} -> 105333.2 | O29: {=INDEX(Data!$AY$2:$AY$367,MATCH(TRUE,Data!$AY$2:$AY$367>0,0))} -> 117000 | P29: {=IFERROR(IF(NOT(ISNA(I29)),NA(),SUM(Data!$AY$2:$AY$367*(--(Data!$A$2:$A$367=DATE(Processing!$C$1,Processing!$E$1,Processing!H29))))),NA())} -> #N/A | Q29: =H29 -> 4 | R29: {=IF(ISNA(I29),NA(),SUM(Data!$BE$2:$BH$367*(--(Data!$A$2:$A$367=DATE(Processing!$C$1,Processing!$E$1,Processing!H29)))))} -> 72807 | S29: =(R29>0)*$C$28 -> 36058 | T29: {=ISNUMBER(Q29)*SUM(Data!$BE$2:$BH$367*(--(Data!$A$2:$A$367=DATE(Processing!$C$1,Processing!$E$1,Processing!H29))))} -> 72807 | U29: Plan | V29: 77000 | W29: 65000 | X29: 58000 | Y29: 30000 | Z29: =SUM(Z27:Z28) -> 230000 | AG29: =H29 -> 4 | AH29: {=IF(ISNA(I29),NA(),SUM(Data!$J$2:$S$367*(--(Data!$A$2:$A$367=DATE(Processing!$C$1,Processing!$E$1,Processing!H29)))))} -> 1045 | AI29: {=IF(ISNA(I29),NA(),SUM(Data!$O$2:$S$367*(--(Data!$A$2:$A$367=DATE(Processing!$C$1,Processing!$E$1,Processing!H29)))))} -> 399 | AJ29: {=SUM(Data!$J$2:$S$367*(--(Data!$A$2:$A$367=DATE(Processing!$C$1,Processing!$E$1,Processing!H29))))} -> 1045 | AL29: =H29 -> 4 | AM29: {=IF(ISNA(I29),NA(),SUM(Data!$T$2:$AX$367*(--(Data!$A$2:$A$367=DATE(Processing!$C$1,Processing!$E$1,Processing!H29)))))} -> 859 | AN29: {=IF(ISNA(I29),NA(),SUM(Data!$AP$2:$AX$367*(--(Data!$A$2:$A$367=DATE(Processing!$C$1,Processing!$E$1,Processing!H29)))))} -> 387 | AO29: {=SUM(Data!$T$2:$AX$367*(--(Data!$A$2:$A$367=DATE(Processing!$C$1,Processing!$E$1,Processing!H29))))} -> 859
A30: Total Values | B30: Used Credit Funds | D30: X | E30: Y | F30: MAY | G30: =DAY(EOMONTH(DATE($C$1,H30,1),0)) -> 31 | H30: 5 | I30: {=IFERROR(GETPIVOTDATA(""&$N$2,Control!$A$7,""&$H$25,H30)+GETPIVOTDATA(""&$N$3,Control!$A$7,""&$H$25,H30)+GETPIVOTDATA(""&$N$4,Control!$A$7,""&$H$25,H30),NA())} -> 1035 | J30: {=IFERROR(GETPIVOTDATA(""&$N$5,Control!$A$7,""&$H$25,H30)+GETPIVOTDATA(""&$N$6,Control!$A$7,""&$H$25,H30)+GETPIVOTDATA(""&$N$7,Control!$A$7,""&$H$25,H30),NA())} -> 860 | K30: {=SUM(Data!$D$2:$F$367*(--(Data!$A$2:$A$367=DATE(Processing!$C$1,Processing!$E$1,Processing!H30))))} -> 1035 | L30: =IF(ISNA(I30),0,H30) -> 5 | M30: =H30 -> 5 | N30: {=IF(ISNA(I30),NA(),SUM(Data!$AY$2:$AY$367*(--(Data!$A$2:$A$367=DATE(Processing!$C$1,Processing!$E$1,Processing!H30)))))} -> 106914.78 | O30: {=INDEX(Data!$AY$2:$AY$367,MATCH(TRUE,Data!$AY$2:$AY$367>0,0))} -> 117000 | P30: {=IFERROR(IF(NOT(ISNA(I30)),NA(),SUM(Data!$AY$2:$AY$367*(--(Data!$A$2:$A$367=DATE(Processing!$C$1,Processing!$E$1,Processing!H30))))),NA())} -> #N/A | Q30: =H30 -> 5 | R30: {=IF(ISNA(I30),NA(),SUM(Data!$BE$2:$BH$367*(--(Data!$A$2:$A$367=DATE(Processing!$C$1,Processing!$E$1,Processing!H30)))))} -> 72807 | S30: =(R30>0)*$C$28 -> 36058 | T30: {=ISNUMBER(Q30)*SUM(Data!$BE$2:$BH$367*(--(Data!$A$2:$A$367=DATE(Processing!$C$1,Processing!$E$1,Processing!H30))))} -> 72807 | U30: MAX | V30: =MAX(V29:Y29) -> 77000 | AG30: =H30 -> 5 | AH30: {=IF(ISNA(I30),NA(),SUM(Data!$J$2:$S$367*(--(Data!$A$2:$A$367=DATE(Processing!$C$1,Processing!$E$1,Processing!H30)))))} -> 1035 | AI30: {=IF(ISNA(I30),NA(),SUM(Data!$O$2:$S$367*(--(Data!$A$2:$A$367=DATE(Processing!$C$1,Processing!$E$1,Processing!H30)))))} -> 523 | AJ30: {=SUM(Data!$J$2:$S$367*(--(Data!$A$2:$A$367=DATE(Processing!$C$1,Processing!$E$1,Processing!H30))))} -> 1035 | AL30: =H30 -> 5 | AM30: {=IF(ISNA(I30),NA(),SUM(Data!$T$2:$AX$367*(--(Data!$A$2:$A$367=DATE(Processing!$C$1,Processing!$E$1,Processing!H30)))))} -> 860 | AN30: {=IF(ISNA(I30),NA(),SUM(Data!$AP$2:$AX$367*(--(Data!$A$2:$A$367=DATE(Processing!$C$1,Processing!$E$1,Processing!H30)))))} -> 231 | AO30: {=SUM(Data!$T$2:$AX$367*(--(Data!$A$2:$A$367=DATE(Processing!$C$1,Processing!$E$1,Processing!H30))))} -> 860
A31: Balance | B31: =1-C31 -> 0.64992233 | C31: =C28/SUM(C27:C28) -> 0.35007767 | D31: 0 | E31: 1 | F31: JUNE | G31: =DAY(EOMONTH(DATE($C$1,H31,1),0)) -> 30 | H31: 6 | I31: {=IFERROR(GETPIVOTDATA(""&$N$2,Control!$A$7,""&$H$25,H31)+GETPIVOTDATA(""&$N$3,Control!$A$7,""&$H$25,H31)+GETPIVOTDATA(""&$N$4,Control!$A$7,""&$H$25,H31),NA())} -> 1031 | J31: {=IFERROR(GETPIVOTDATA(""&$N$5,Control!$A$7,""&$H$25,H31)+GETPIVOTDATA(""&$N$6,Control!$A$7,""&$H$25,H31)+GETPIVOTDATA(""&$N$7,Control!$A$7,""&$H$25,H31),NA())} -> 858 | K31: {=SUM(Data!$D$2:$F$367*(--(Data!$A$2:$A$367=DATE(Processing!$C$1,Processing!$E$1,Processing!H31))))} -> 1031 | L31: =IF(ISNA(I31),0,H31) -> 6 | M31: =H31 -> 6 | N31: {=IF(ISNA(I31),NA(),SUM(Data!$AY$2:$AY$367*(--(Data!$A$2:$A$367=DATE(Processing!$C$1,Processing!$E$1,Processing!H31)))))} -> 109081.24 | O31: {=INDEX(Data!$AY$2:$AY$367,MATCH(TRUE,Data!$AY$2:$AY$367>0,0))} -> 117000 | P31: {=IFERROR(IF(NOT(ISNA(I31)),NA(),SUM(Data!$AY$2:$AY$367*(--(Data!$A$2:$A$367=DATE(Processing!$C$1,Processing!$E$1,Processing!H31))))),NA())} -> #N/A | Q31: =H31 -> 6 | R31: {=IF(ISNA(I31),NA(),SUM(Data!$BE$2:$BH$367*(--(Data!$A$2:$A$367=DATE(Processing!$C$1,Processing!$E$1,Processing!H31)))))} -> 72807 | S31: =(R31>0)*$C$28 -> 36058 | T31: {=ISNUMBER(Q31)*SUM(Data!$BE$2:$BH$367*(--(Data!$A$2:$A$367=DATE(Processing!$C$1,Processing!$E$1,Processing!H31))))} -> 72807 | V31: Activity | AG31: =H31 -> 6 | AH31: {=IF(ISNA(I31),NA(),SUM(Data!$J$2:$S$367*(--(Data!$A$2:$A$367=DATE(Processing!$C$1,Processing!$E$1,Processing!H31)))))} -> 1031 | AI31: {=IF(ISNA(I31),NA(),SUM(Data!$O$2:$S$367*(--(Data!$A$2:$A$367=DATE(Processing!$C$1,Processing!$E$1,Processing!H31)))))} -> 555 | AJ31: {=SUM(Data!$J$2:$S$367*(--(Data!$A$2:$A$367=DATE(Processing!$C$1,Processing!$E$1,Processing!H31))))} -> 1031 | AL31: =H31 -> 6 | AM31: {=IF(ISNA(I31),NA(),SUM(Data!$T$2:$AX$367*(--(Data!$A$2:$A$367=DATE(Processing!$C$1,Processing!$E$1,Processing!H31)))))} -> 858 | AN31: {=IF(ISNA(I31),NA(),SUM(Data!$AP$2:$AX$367*(--(Data!$A$2:$A$367=DATE(Processing!$C$1,Processing!$E$1,Processing!H31)))))} -> 352 | AO31: {=SUM(Data!$T$2:$AX$367*(--(Data!$A$2:$A$367=DATE(Processing!$C$1,Processing!$E$1,Processing!H31))))} -> 858
A32: Loan Portfolio Distribution | D32: =SIN(B31*2*PI()) -> -0.80873005 | E32: =COS(C31*2*PI()) -> -0.58817999 | F32: JULY | G32: =DAY(EOMONTH(DATE($C$1,H32,1),0)) -> 31 | H32: 7 | I32: {=IFERROR(GETPIVOTDATA(""&$N$2,Control!$A$7,""&$H$25,H32)+GETPIVOTDATA(""&$N$3,Control!$A$7,""&$H$25,H32)+GETPIVOTDATA(""&$N$4,Control!$A$7,""&$H$25,H32),NA())} -> 1037 | J32: {=IFERROR(GETPIVOTDATA(""&$N$5,Control!$A$7,""&$H$25,H32)+GETPIVOTDATA(""&$N$6,Control!$A$7,""&$H$25,H32)+GETPIVOTDATA(""&$N$7,Control!$A$7,""&$H$25,H32),NA())} -> 843 | K32: {=SUM(Data!$D$2:$F$367*(--(Data!$A$2:$A$367=DATE(Processing!$C$1,Processing!$E$1,Processing!H32))))} -> 1037 | L32: =IF(ISNA(I32),0,H32) -> 7 | M32: =H32 -> 7 | N32: {=IF(ISNA(I32),NA(),SUM(Data!$AY$2:$AY$367*(--(Data!$A$2:$A$367=DATE(Processing!$C$1,Processing!$E$1,Processing!H32)))))} -> 112591.84 | O32: {=INDEX(Data!$AY$2:$AY$367,MATCH(TRUE,Data!$AY$2:$AY$367>0,0))} -> 117000 | P32: {=IFERROR(IF(NOT(ISNA(I32)),NA(),SUM(Data!$AY$2:$AY$367*(--(Data!$A$2:$A$367=DATE(Processing!$C$1,Processing!$E$1,Processing!H32))))),NA())} -> #N/A | Q32: =H32 -> 7 | R32: {=IF(ISNA(I32),NA(),SUM(Data!$BE$2:$BH$367*(--(Data!$A$2:$A$367=DATE(Processing!$C$1,Processing!$E$1,Processing!H32)))))} -> 81746 | S32: =(R32>0)*$C$28 -> 36058 | T32: {=ISNUMBER(Q32)*SUM(Data!$BE$2:$BH$367*(--(Data!$A$2:$A$367=DATE(Processing!$C$1,Processing!$E$1,Processing!H32))))} -> 81746 | U32: Months | V32: Goal 1 | W32: Goal 2 | X32: Goal 3 | Y32: Goal 4 | Z32: Monthly Plan | AA32: Goal 1 | AB32: Goal 2 | AC32: Goal 3 | AD32: Goal 4 | AE32: Months | AF32: % Fact Plan | AG32: =H32 -> 7 | AH32: {=IF(ISNA(I32),NA(),SUM(Data!$J$2:$S$367*(--(Data!$A$2:$A$367=DATE(Processing!$C$1,Processing!$E$1,Processing!H32)))))} -> 1037 | AI32: {=IF(ISNA(I32),NA(),SUM(Data!$O$2:$S$367*(--(Data!$A$2:$A$367=DATE(Processing!$C$1,Processing!$E$1,Processing!H32)))))} -> 402 | AJ32: {=SUM(Data!$J$2:$S$367*(--(Data!$A$2:$A$367=DATE(Processing!$C$1,Processing!$E$1,Processing!H32))))} -> 1037 | AL32: =H32 -> 7 | AM32: {=IF(ISNA(I32),NA(),SUM(Data!$T$2:$AX$367*(--(Data!$A$2:$A$367=DATE(Processing!$C$1,Processing!$E$1,Processing!H32)))))} -> 843 | AN32: {=IF(ISNA(I32),NA(),SUM(Data!$AP$2:$AX$367*(--(Data!$A$2:$A$367=DATE(Processing!$C$1,Processing!$E$1,Processing!H32)))))} -> 338 | AO32: {=SUM(Data!$T$2:$AX$367*(--(Data!$A$2:$A$367=DATE(Processing!$C$1,Processing!$E$1,Processing!H32))))} -> 843
A33: =$D$24 -> 0.13349515 | B33: =$D$23 -> 0.2815534 | C33: =$D$25 -> 0.063087379 | D33: =$D$26 -> 0.17178641 | E33: =$D$28 -> 0.35007767 | F33: AUGUST | G33: =DAY(EOMONTH(DATE($C$1,H33,1),0)) -> 31 | H33: 8 | I33: {=IFERROR(GETPIVOTDATA(""&$N$2,Control!$A$7,""&$H$25,H33)+GETPIVOTDATA(""&$N$3,Control!$A$7,""&$H$25,H33)+GETPIVOTDATA(""&$N$4,Control!$A$7,""&$H$25,H33),NA())} -> 1056 | J33: {=IFERROR(GETPIVOTDATA(""&$N$5,Control!$A$7,""&$H$25,H33)+GETPIVOTDATA(""&$N$6,Control!$A$7,""&$H$25,H33)+GETPIVOTDATA(""&$N$7,Control!$A$7,""&$H$25,H33),NA())} -> 826 | K33: {=SUM(Data!$D$2:$F$367*(--(Data!$A$2:$A$367=DATE(Processing!$C$1,Processing!$E$1,Processing!H33))))} -> 1056 | L33: =IF(ISNA(I33),0,H33) -> 8 | M33: =H33 -> 8 | N33: {=IF(ISNA(I33),NA(),SUM(Data!$AY$2:$AY$367*(--(Data!$A$2:$A$367=DATE(Processing!$C$1,Processing!$E$1,Processing!H33)))))} -> 116459.95 | O33: {=INDEX(Data!$AY$2:$AY$367,MATCH(TRUE,Data!$AY$2:$AY$367>0,0))} -> 117000 | P33: {=IFERROR(IF(NOT(ISNA(I33)),NA(),SUM(Data!$AY$2:$AY$367*(--(Data!$A$2:$A$367=DATE(Processing!$C$1,Processing!$E$1,Processing!H33))))),NA())} -> #N/A | Q33: =H33 -> 8 | R33: {=IF(ISNA(I33),NA(),SUM(Data!$BE$2:$BH$367*(--(Data!$A$2:$A$367=DATE(Processing!$C$1,Processing!$E$1,Processing!H33)))))} -> 81746 | S33: =(R33>0)*$C$28 -> 36058 | T33: {=ISNUMBER(Q33)*SUM(Data!$BE$2:$BH$367*(--(Data!$A$2:$A$367=DATE(Processing!$C$1,Processing!$E$1,Processing!H33))))} -> 81746 | U33: JAN | V33: =AA33/$Z33 -> 0.41003448 | W33: =AB33/$Z33 -> 0.12 | X33: =AC33/$Z33 -> 0.17 | Y33: =AD33/$Z33 -> 0.060034483 | Z33: {=SUM(Data!BM$2:BM$367*(--(Data!$A$2:$A$367=DATE(Processing!$C$1,$AE33,1))))} -> 29000 | AA33: {=SUM(Data!BI$2:BI$367*(--(Data!$A$2:$A$367=DATE(Processing!$C$1,$AE33,1))))} -> 11891 | AB33: {=SUM(Data!BJ$2:BJ$367*(--(Data!$A$2:$A$367=DATE(Processing!$C$1,$AE33,1))))} -> 3480 | AC33: {=SUM(Data!BK$2:BK$367*(--(Data!$A$2:$A$367=DATE(Processing!$C$1,$AE33,1))))} -> 4930 | AD33: {=SUM(Data!BL$2:BL$367*(--(Data!$A$2:$A$367=DATE(Processing!$C$1,$AE33,1))))} -> 1741 | AE33: 1 | AF33: =IF(AE33=$E$1,SUM(V33:Y33),NA()) -> #N/A | AG33: =H33 -> 8 | AH33: {=IF(ISNA(I33),NA(),SUM(Data!$J$2:$S$367*(--(Data!$A$2:$A$367=DATE(Processing!$C$1,Processing!$E$1,Processing!H33)))))} -> 1056 | AI33: {=IF(ISNA(I33),NA(),SUM(Data!$O$2:$S$367*(--(Data!$A$2:$A$367=DATE(Processing!$C$1,Processing!$E$1,Processing!H33)))))} -> 448 | AJ33: {=SUM(Data!$J$2:$S$367*(--(Data!$A$2:$A$367=DATE(Processing!$C$1,Processing!$E$1,Processing!H33))))} -> 1056 | AL33: =H33 -> 8 | AM33: {=IF(ISNA(I33),NA(),SUM(Data!$T$2:$AX$367*(--(Data!$A$2:$A$367=DATE(Processing!$C$1,Processing!$E$1,Processing!H33)))))} -> 826 | AN33: {=IF(ISNA(I33),NA(),SUM(Data!$AP$2:$AX$367*(--(Data!$A$2:$A$367=DATE(Processing!$C$1,Processing!$E$1,Processing!H33)))))} -> 269 | AO33: {=SUM(Data!$T$2:$AX$367*(--(Data!$A$2:$A$367=DATE(Processing!$C$1,Processing!$E$1,Processing!H33))))} -> 826
A34: =$D$24 -> 0.13349515 | B34: =$D$23 -> 0.2815534 | C34: =$D$25 -> 0.063087379 | D34: =$D$26 -> 0.17178641 | E34: =$D$28 -> 0.35007767 | F34: SEPTEMBER | G34: =DAY(EOMONTH(DATE($C$1,H34,1),0)) -> 30 | H34: 9 | I34: {=IFERROR(GETPIVOTDATA(""&$N$2,Control!$A$7,""&$H$25,H34)+GETPIVOTDATA(""&$N$3,Control!$A$7,""&$H$25,H34)+GETPIVOTDATA(""&$N$4,Control!$A$7,""&$H$25,H34),NA())} -> 1082 | J34: {=IFERROR(GETPIVOTDATA(""&$N$5,Control!$A$7,""&$H$25,H34)+GETPIVOTDATA(""&$N$6,Control!$A$7,""&$H$25,H34)+GETPIVOTDATA(""&$N$7,Control!$A$7,""&$H$25,H34),NA())} -> 800 | K34: {=SUM(Data!$D$2:$F$367*(--(Data!$A$2:$A$367=DATE(Processing!$C$1,Processing!$E$1,Processing!H34))))} -> 1082 | L34: =IF(ISNA(I34),0,H34) -> 9 | M34: =H34 -> 9 | N34: {=IF(ISNA(I34),NA(),SUM(Data!$AY$2:$AY$367*(--(Data!$A$2:$A$367=DATE(Processing!$C$1,Processing!$E$1,Processing!H34)))))} -> 119624.63 | O34: {=INDEX(Data!$AY$2:$AY$367,MATCH(TRUE,Data!$AY$2:$AY$367>0,0))} -> 117000 | P34: {=IFERROR(IF(NOT(ISNA(I34)),NA(),SUM(Data!$AY$2:$AY$367*(--(Data!$A$2:$A$367=DATE(Processing!$C$1,Processing!$E$1,Processing!H34))))),NA())} -> #N/A | Q34: =H34 -> 9 | R34: {=IF(ISNA(I34),NA(),SUM(Data!$BE$2:$BH$367*(--(Data!$A$2:$A$367=DATE(Processing!$C$1,Processing!$E$1,Processing!H34)))))} -> 81746 | S34: =(R34>0)*$C$28 -> 36058 | T34: {=ISNUMBER(Q34)*SUM(Data!$BE$2:$BH$367*(--(Data!$A$2:$A$367=DATE(Processing!$C$1,Processing!$E$1,Processing!H34))))} -> 81746 | U34: FEB | V34: =AA34/$Z34 -> 0.58321053 | W34: =AB34/$Z34 -> 0.15107895 | X34: =AC34/$Z34 -> 0.14002632 | Y34: =AD34/$Z34 -> 0.050052632 | Z34: {=SUM(Data!BM$2:BM$367*(--(Data!$A$2:$A$367=DATE(Processing!$C$1,$AE34,1))))} -> 38000 | AA34: {=SUM(Data!BI$2:BI$367*(--(Data!$A$2:$A$367=DATE(Processing!$C$1,$AE34,1))))} -> 22162 | AB34: {=SUM(Data!BJ$2:BJ$367*(--(Data!$A$2:$A$367=DATE(Processing!$C$1,$AE34,1))))} -> 5741 | AC34: {=SUM(Data!BK$2:BK$367*(--(Data!$A$2:$A$367=DATE(Processing!$C$1,$AE34,1))))} -> 5321 | AD34: {=SUM(Data!BL$2:BL$367*(--(Data!$A$2:$A$367=DATE(Processing!$C$1,$AE34,1))))} -> 1902 | AE34: 2 | AF34: =IF(AE34=$E$1,SUM(V34:Y34),NA()) -> #N/A | AG34: =H34 -> 9 | AH34: {=IF(ISNA(I34),NA(),SUM(Data!$J$2:$S$367*(--(Data!$A$2:$A$367=DATE(Processing!$C$1,Processing!$E$1,Processing!H34)))))} -> 1082 | AI34: {=IF(ISNA(I34),NA(),SUM(Data!$O$2:$S$367*(--(Data!$A$2:$A$367=DATE(Processing!$C$1,Processing!$E$1,Processing!H34)))))} -> 474 | AJ34: {=SUM(Data!$J$2:$S$367*(--(Data!$A$2:$A$367=DATE(Processing!$C$1,Processing!$E$1,Processing!H34))))} -> 1082 | AL34: =H34 -> 9 | AM34: {=IF(ISNA(I34),NA(),SUM(Data!$T$2:$AX$367*(--(Data!$A$2:$A$367=DATE(Processing!$C$1,Processing!$E$1,Processing!H34)))))} -> 800 | AN34: {=IF(ISNA(I34),NA(),SUM(Data!$AP$2:$AX$367*(--(Data!$A$2:$A$367=DATE(Processing!$C$1,Processing!$E$1,Processing!H34)))))} -> 288 | AO34: {=SUM(Data!$T$2:$AX$367*(--(Data!$A$2:$A$367=DATE(Processing!$C$1,Processing!$E$1,Processing!H34))))} -> 800
A35: =$D$24 -> 0.13349515 | B35: =$D$23 -> 0.2815534 | C35: =$D$25 -> 0.063087379 | D35: =$D$26 -> 0.17178641 | E35: =$D$28 -> 0.35007767 | F35: OCTOBER | G35: =DAY(EOMONTH(DATE($C$1,H35,1),0)) -> 31 | H35: 10 | I35: {=IFERROR(GETPIVOTDATA(""&$N$2,Control!$A$7,""&$H$25,H35)+GETPIVOTDATA(""&$N$3,Control!$A$7,""&$H$25,H35)+GETPIVOTDATA(""&$N$4,Control!$A$7,""&$H$25,H35),NA())} -> 1095 | J35: {=IFERROR(GETPIVOTDATA(""&$N$5,Control!$A$7,""&$H$25,H35)+GETPIVOTDATA(""&$N$6,Control!$A$7,""&$H$25,H35)+GETPIVOTDATA(""&$N$7,Control!$A$7,""&$H$25,H35),NA())} -> 772 | K35: {=SUM(Data!$D$2:$F$367*(--(Data!$A$2:$A$367=DATE(Processing!$C$1,Processing!$E$1,Processing!H35))))} -> 1095 | L35: =IF(ISNA(I35),0,H35) -> 10 | M35: =H35 -> 10 | N35: {=IF(ISNA(I35),NA(),SUM(Data!$AY$2:$AY$367*(--(Data!$A$2:$A$367=DATE(Processing!$C$1,Processing!$E$1,Processing!H35)))))} -> 121950.66 | O35: {=INDEX(Data!$AY$2:$AY$367,MATCH(TRUE,Data!$AY$2:$AY$367>0,0))} -> 117000 | P35: {=IFERROR(IF(NOT(ISNA(I35)),NA(),SUM(Data!$AY$2:$AY$367*(--(Data!$A$2:$A$367=DATE(Processing!$C$1,Processing!$E$1,Processing!H35))))),NA())} -> #N/A | Q35: =H35 -> 10 | R35: {=IF(ISNA(I35),NA(),SUM(Data!$BE$2:$BH$367*(--(Data!$A$2:$A$367=DATE(Processing!$C$1,Processing!$E$1,Processing!H35)))))} -> 81746 | S35: =(R35>0)*$C$28 -> 36058 | T35: {=ISNUMBER(Q35)*SUM(Data!$BE$2:$BH$367*(--(Data!$A$2:$A$367=DATE(Processing!$C$1,Processing!$E$1,Processing!H35))))} -> 81746 | U35: MAR | V35: =AA35/$Z35 -> 0.62495918 | W35: =AB35/$Z35 -> 0.178 | X35: =AC35/$Z35 -> 0.12595918 | Y35: =AD35/$Z35 -> 0.043734694 | Z35: {=SUM(Data!BM$2:BM$367*(--(Data!$A$2:$A$367=DATE(Processing!$C$1,$AE35,1))))} -> 49000 | AA35: {=SUM(Data!BI$2:BI$367*(--(Data!$A$2:$A$367=DATE(Processing!$C$1,$AE35,1))))} -> 30623 | AB35: {=SUM(Data!BJ$2:BJ$367*(--(Data!$A$2:$A$367=DATE(Processing!$C$1,$AE35,1))))} -> 8722 | AC35: {=SUM(Data!BK$2:BK$367*(--(Data!$A$2:$A$367=DATE(Processing!$C$1,$AE35,1))))} -> 6172 | AD35: {=SUM(Data!BL$2:BL$367*(--(Data!$A$2:$A$367=DATE(Processing!$C$1,$AE35,1))))} -> 2143 | AE35: 3 | AF35: =IF(AE35=$E$1,SUM(V35:Y35),NA()) -> #N/A | AG35: =H35 -> 10 | AH35: {=IF(ISNA(I35),NA(),SUM(Data!$J$2:$S$367*(--(Data!$A$2:$A$367=DATE(Processing!$C$1,Processing!$E$1,Processing!H35)))))} -> 1095 | AI35: {=IF(ISNA(I35),NA(),SUM(Data!$O$2:$S$367*(--(Data!$A$2:$A$367=DATE(Processing!$C$1,Processing!$E$1,Processing!H35)))))} -> 385 | AJ35: {=SUM(Data!$J$2:$S$367*(--(Data!$A$2:$A$367=DATE(Processing!$C$1,Processing!$E$1,Processing!H35))))} -> 1095 | AL35: =H35 -> 10 | AM35: {=IF(ISNA(I35),NA(),SUM(Data!$T$2:$AX$367*(--(Data!$A$2:$A$367=DATE(Processing!$C$1,Processing!$E$1,Processing!H35)))))} -> 772 | AN35: {=IF(ISNA(I35),NA(),SUM(Data!$AP$2:$AX$367*(--(Data!$A$2:$A$367=DATE(Processing!$C$1,Processing!$E$1,Processing!H35)))))} -> 272 | AO35: {=SUM(Data!$T$2:$AX$367*(--(Data!$A$2:$A$367=DATE(Processing!$C$1,Processing!$E$1,Processing!H35))))} -> 772
F36: NOVEMBER | G36: =DAY(EOMONTH(DATE($C$1,H36,1),0)) -> 30 | H36: 11 | I36: {=IFERROR(GETPIVOTDATA(""&$N$2,Control!$A$7,""&$H$25,H36)+GETPIVOTDATA(""&$N$3,Control!$A$7,""&$H$25,H36)+GETPIVOTDATA(""&$N$4,Control!$A$7,""&$H$25,H36),NA())} -> 1101 | J36: {=IFERROR(GETPIVOTDATA(""&$N$5,Control!$A$7,""&$H$25,H36)+GETPIVOTDATA(""&$N$6,Control!$A$7,""&$H$25,H36)+GETPIVOTDATA(""&$N$7,Control!$A$7,""&$H$25,H36),NA())} -> 749 | K36: {=SUM(Data!$D$2:$F$367*(--(Data!$A$2:$A$367=DATE(Processing!$C$1,Processing!$E$1,Processing!H36))))} -> 1101 | L36: =IF(ISNA(I36),0,H36) -> 11 | M36: =H36 -> 11 | N36: {=IF(ISNA(I36),NA(),SUM(Data!$AY$2:$AY$367*(--(Data!$A$2:$A$367=DATE(Processing!$C$1,Processing!$E$1,Processing!H36)))))} -> 122466.82 | O36: {=INDEX(Data!$AY$2:$AY$367,MATCH(TRUE,Data!$AY$2:$AY$367>0,0))} -> 117000 | P36: {=IFERROR(IF(NOT(ISNA(I36)),NA(),SUM(Data!$AY$2:$AY$367*(--(Data!$A$2:$A$367=DATE(Processing!$C$1,Processing!$E$1,Processing!H36))))),NA())} -> #N/A | Q36: =H36 -> 11 | R36: {=IF(ISNA(I36),NA(),SUM(Data!$BE$2:$BH$367*(--(Data!$A$2:$A$367=DATE(Processing!$C$1,Processing!$E$1,Processing!H36)))))} -> 81746 | S36: =(R36>0)*$C$28 -> 36058 | T36: {=ISNUMBER(Q36)*SUM(Data!$BE$2:$BH$367*(--(Data!$A$2:$A$367=DATE(Processing!$C$1,Processing!$E$1,Processing!H36))))} -> 81746 | U36: APR | V36: =AA36/$Z36 -> 0.49672222 | W36: =AB36/$Z36 -> 0.19059722 | X36: =AC36/$Z36 -> 0.12004167 | Y36: =AD36/$Z36 -> 0.080055556 | Z36: {=SUM(Data!BM$2:BM$367*(--(Data!$A$2:$A$367=DATE(Processing!$C$1,$AE36,1))))} -> 72000 | AA36: {=SUM(Data!BI$2:BI$367*(--(Data!$A$2:$A$367=DATE(Processing!$C$1,$AE36,1))))} -> 35764 | AB36: {=SUM(Data!BJ$2:BJ$367*(--(Data!$A$2:$A$367=DATE(Processing!$C$1,$AE36,1))))} -> 13723 | AC36: {=SUM(Data!BK$2:BK$367*(--(Data!$A$2:$A$367=DATE(Processing!$C$1,$AE36,1))))} -> 8643 | AD36: {=SUM(Data!BL$2:BL$367*(--(Data!$A$2:$A$367=DATE(Processing!$C$1,$AE36,1))))} -> 5764 | AE36: 4 | AF36: =IF(AE36=$E$1,SUM(V36:Y36),NA()) -> #N/A | AG36: =H36 -> 11 | AH36: {=IF(ISNA(I36),NA(),SUM(Data!$J$2:$S$367*(--(Data!$A$2:$A$367=DATE(Processing!$C$1,Processing!$E$1,Processing!H36)))))} -> 1101 | AI36: {=IF(ISNA(I36),NA(),SUM(Data!$O$2:$S$367*(--(Data!$A$2:$A$367=DATE(Processing!$C$1,Processing!$E$1,Processing!H36)))))} -> 421 | AJ36: {=SUM(Data!$J$2:$S$367*(--(Data!$A$2:$A$367=DATE(Processing!$C$1,Processing!$E$1,Processing!H36))))} -> 1101 | AL36: =H36 -> 11 | AM36: {=IF(ISNA(I36),NA(),SUM(Data!$T$2:$AX$367*(--(Data!$A$2:$A$367=DATE(Processing!$C$1,Processing!$E$1,Processing!H36)))))} -> 749 | AN36: {=IF(ISNA(I36),NA(),SUM(Data!$AP$2:$AX$367*(--(Data!$A$2:$A$367=DATE(Processing!$C$1,Processing!$E$1,Processing!H36)))))} -> 283 | AO36: {=SUM(Data!$T$2:$AX$367*(--(Data!$A$2:$A$367=DATE(Processing!$C$1,Processing!$E$1,Processing!H36))))} -> 749
F37: DECEMBER | G37: =DAY(EOMONTH(DATE($C$1,H37,1),0)) -> 31 | H37: 12 | I37: {=IFERROR(GETPIVOTDATA(""&$N$2,Control!$A$7,""&$H$25,H37)+GETPIVOTDATA(""&$N$3,Control!$A$7,""&$H$25,H37)+GETPIVOTDATA(""&$N$4,Control!$A$7,""&$H$25,H37),NA())} -> 1101 | J37: {=IFERROR(GETPIVOTDATA(""&$N$5,Control!$A$7,""&$H$25,H37)+GETPIVOTDATA(""&$N$6,Control!$A$7,""&$H$25,H37)+GETPIVOTDATA(""&$N$7,Control!$A$7,""&$H$25,H37),NA())} -> 730 | K37: {=SUM(Data!$D$2:$F$367*(--(Data!$A$2:$A$367=DATE(Processing!$C$1,Processing!$E$1,Processing!H37))))} -> 1101 | L37: =IF(ISNA(I37),0,H37) -> 12 | M37: =H37 -> 12 | N37: {=IF(ISNA(I37),NA(),SUM(Data!$AY$2:$AY$367*(--(Data!$A$2:$A$367=DATE(Processing!$C$1,Processing!$E$1,Processing!H37)))))} -> 122640.18 | O37: {=INDEX(Data!$AY$2:$AY$367,MATCH(TRUE,Data!$AY$2:$AY$367>0,0))} -> 117000 | P37: {=IFERROR(IF(NOT(ISNA(I37)),NA(),SUM(Data!$AY$2:$AY$367*(--(Data!$A$2:$A$367=DATE(Processing!$C$1,Processing!$E$1,Processing!H37))))),NA())} -> #N/A | Q37: =H37 -> 12 | R37: {=IF(ISNA(I37),NA(),SUM(Data!$BE$2:$BH$367*(--(Data!$A$2:$A$367=DATE(Processing!$C$1,Processing!$E$1,Processing!H37)))))} -> 81746 | S37: =(R37>0)*$C$28 -> 36058 | T37: {=ISNUMBER(Q37)*SUM(Data!$BE$2:$BH$367*(--(Data!$A$2:$A$367=DATE(Processing!$C$1,Processing!$E$1,Processing!H37))))} -> 81746 | U37: MAY | V37: =AA37/$Z37 -> 0.39212264 | W37: =AB37/$Z37 -> 0.17569811 | X37: =AC37/$Z37 -> 0.12003774 | Y37: =AD37/$Z37 -> 0.09004717 | Z37: {=SUM(Data!BM$2:BM$367*(--(Data!$A$2:$A$367=DATE(Processing!$C$1,$AE37,1))))} -> 106000 | AA37: {=SUM(Data!BI$2:BI$367*(--(Data!$A$2:$A$367=DATE(Processing!$C$1,$AE37,1))))} -> 41565 | AB37: {=SUM(Data!BJ$2:BJ$367*(--(Data!$A$2:$A$367=DATE(Processing!$C$1,$AE37,1))))} -> 18624 | AC37: {=SUM(Data!BK$2:BK$367*(--(Data!$A$2:$A$367=DATE(Processing!$C$1,$AE37,1))))} -> 12724 | AD37: {=SUM(Data!BL$2:BL$367*(--(Data!$A$2:$A$367=DATE(Processing!$C$1,$AE37,1))))} -> 9545 | AE37: 5 | AF37: =IF(AE37=$E$1,SUM(V37:Y37),NA()) -> #N/A | AG37: =H37 -> 12 | AH37: {=IF(ISNA(I37),NA(),SUM(Data!$J$2:$S$367*(--(Data!$A$2:$A$367=DATE(Processing!$C$1,Processing!$E$1,Processing!H37)))))} -> 1101 | AI37: {=IF(ISNA(I37),NA(),SUM(Data!$O$2:$S$367*(--(Data!$A$2:$A$367=DATE(Processing!$C$1,Processing!$E$1,Processing!H37)))))} -> 401 | AJ37: {=SUM(Data!$J$2:$S$367*(--(Data!$A$2:$A$367=DATE(Processing!$C$1,Processing!$E$1,Processing!H37))))} -> 1101 | AL37: =H37 -> 12 | AM37: {=IF(ISNA(I37),NA(),SUM(Data!$T$2:$AX$367*(--(Data!$A$2:$A$367=DATE(Processing!$C$1,Processing!$E$1,Processing!H37)))))} -> 730 | AN37: {=IF(ISNA(I37),NA(),SUM(Data!$AP$2:$AX$367*(--(Data!$A$2:$A$367=DATE(Processing!$C$1,Processing!$E$1,Processing!H37)))))} -> 223 | AO37: {=SUM(Data!$T$2:$AX$367*(--(Data!$A$2:$A$367=DATE(Processing!$C$1,Processing!$E$1,Processing!H37))))} -> 730
A38: Income | B38: Fixed vs Non-Fixed | H38: 13 | I38: {=IFERROR(GETPIVOTDATA(""&$N$2,Control!$A$7,""&$H$25,H38)+GETPIVOTDATA(""&$N$3,Control!$A$7,""&$H$25,H38)+GETPIVOTDATA(""&$N$4,Control!$A$7,""&$H$25,H38),NA())} -> 1097 | J38: {=IFERROR(GETPIVOTDATA(""&$N$5,Control!$A$7,""&$H$25,H38)+GETPIVOTDATA(""&$N$6,Control!$A$7,""&$H$25,H38)+GETPIVOTDATA(""&$N$7,Control!$A$7,""&$H$25,H38),NA())} -> 722 | K38: {=SUM(Data!$D$2:$F$367*(--(Data!$A$2:$A$367=DATE(Processing!$C$1,Processing!$E$1,Processing!H38))))} -> 1097 | L38: =IF(ISNA(I38),0,H38) -> 13 | M38: =H38 -> 13 | N38: {=IF(ISNA(I38),NA(),SUM(Data!$AY$2:$AY$367*(--(Data!$A$2:$A$367=DATE(Processing!$C$1,Processing!$E$1,Processing!H38)))))} -> 121944.95 | O38: {=INDEX(Data!$AY$2:$AY$367,MATCH(TRUE,Data!$AY$2:$AY$367>0,0))} -> 117000 | P38: {=IFERROR(IF(NOT(ISNA(I38)),NA(),SUM(Data!$AY$2:$AY$367*(--(Data!$A$2:$A$367=DATE(Processing!$C$1,Processing!$E$1,Processing!H38))))),NA())} -> #N/A | Q38: =H38 -> 13 | R38: {=IF(ISNA(I38),NA(),SUM(Data!$BE$2:$BH$367*(--(Data!$A$2:$A$367=DATE(Processing!$C$1,Processing!$E$1,Processing!H38)))))} -> 81746 | S38: =(R38>0)*$C$28 -> 36058 | T38: {=ISNUMBER(Q38)*SUM(Data!$BE$2:$BH$367*(--(Data!$A$2:$A$367=DATE(Processing!$C$1,Processing!$E$1,Processing!H38))))} -> 81746 | U38: JUN | V38: =AA38/$Z38 -> 0.38322222 | W38: =AB38/$Z38 -> 0.1806746 | X38: =AC38/$Z38 -> 0.17003968 | Y38: =AD38/$Z38 -> 0.095055556 | Z38: {=SUM(Data!BM$2:BM$367*(--(Data!$A$2:$A$367=DATE(Processing!$C$1,$AE38,1))))} -> 126000 | AA38: {=SUM(Data!BI$2:BI$367*(--(Data!$A$2:$A$367=DATE(Processing!$C$1,$AE38,1))))} -> 48286 | AB38: {=SUM(Data!BJ$2:BJ$367*(--(Data!$A$2:$A$367=DATE(Processing!$C$1,$AE38,1))))} -> 22765 | AC38: {=SUM(Data!BK$2:BK$367*(--(Data!$A$2:$A$367=DATE(Processing!$C$1,$AE38,1))))} -> 21425 | AD38: {=SUM(Data!BL$2:BL$367*(--(Data!$A$2:$A$367=DATE(Processing!$C$1,$AE38,1))))} -> 11977 | AE38: 6 | AF38: =IF(AE38=$E$1,SUM(V38:Y38),NA()) -> 0.82899206 | AG38: =H38 -> 13 | AH38: {=IF(ISNA(I38),NA(),SUM(Data!$J$2:$S$367*(--(Data!$A$2:$A$367=DATE(Processing!$C$1,Processing!$E$1,Processing!H38)))))} -> 1097 | AI38: {=IF(ISNA(I38),NA(),SUM(Data!$O$2:$S$367*(--(Data!$A$2:$A$367=DATE(Processing!$C$1,Processing!$E$1,Processing!H38)))))} -> 624 | AJ38: {=SUM(Data!$J$2:$S$367*(--(Data!$A$2:$A$367=DATE(Processing!$C$1,Processing!$E$1,Processing!H38))))} -> 1097 | AL38: =H38 -> 13 | AM38: {=IF(ISNA(I38),NA(),SUM(Data!$T$2:$AX$367*(--(Data!$A$2:$A$367=DATE(Processing!$C$1,Processing!$E$1,Processing!H38)))))} -> 722 | AN38: {=IF(ISNA(I38),NA(),SUM(Data!$AP$2:$AX$367*(--(Data!$A$2:$A$367=DATE(Processing!$C$1,Processing!$E$1,Processing!H38)))))} -> 221 | AO38: {=SUM(Data!$T$2:$AX$367*(--(Data!$A$2:$A$367=DATE(Processing!$C$1,Processing!$E$1,Processing!H38))))} -> 722
B39: Business | C39: Securities | D39: Gold | E39: Real estate | F39: Cryptocurrency | G39: Total | H39: 14 | I39: {=IFERROR(GETPIVOTDATA(""&$N$2,Control!$A$7,""&$H$25,H39)+GETPIVOTDATA(""&$N$3,Control!$A$7,""&$H$25,H39)+GETPIVOTDATA(""&$N$4,Control!$A$7,""&$H$25,H39),NA())} -> 1079 | J39: {=IFERROR(GETPIVOTDATA(""&$N$5,Control!$A$7,""&$H$25,H39)+GETPIVOTDATA(""&$N$6,Control!$A$7,""&$H$25,H39)+GETPIVOTDATA(""&$N$7,Control!$A$7,""&$H$25,H39),NA())} -> 719 | K39: {=SUM(Data!$D$2:$F$367*(--(Data!$A$2:$A$367=DATE(Processing!$C$1,Processing!$E$1,Processing!H39))))} -> 1079 | L39: =IF(ISNA(I39),0,H39) -> 14 | M39: =H39 -> 14 | N39: {=IF(ISNA(I39),NA(),SUM(Data!$AY$2:$AY$367*(--(Data!$A$2:$A$367=DATE(Processing!$C$1,Processing!$E$1,Processing!H39)))))} -> 120740.64 | O39: {=INDEX(Data!$AY$2:$AY$367,MATCH(TRUE,Data!$AY$2:$AY$367>0,0))} -> 117000 | P39: {=IFERROR(IF(NOT(ISNA(I39)),NA(),SUM(Data!$AY$2:$AY$367*(--(Data!$A$2:$A$367=DATE(Processing!$C$1,Processing!$E$1,Processing!H39))))),NA())} -> #N/A | Q39: =H39 -> 14 | R39: {=IF(ISNA(I39),NA(),SUM(Data!$BE$2:$BH$367*(--(Data!$A$2:$A$367=DATE(Processing!$C$1,Processing!$E$1,Processing!H39)))))} -> 81746 | S39: =(R39>0)*$C$28 -> 36058 | T39: {=ISNUMBER(Q39)*SUM(Data!$BE$2:$BH$367*(--(Data!$A$2:$A$367=DATE(Processing!$C$1,Processing!$E$1,Processing!H39))))} -> 81746 | U39: JUL | V39: =AA39/$Z39 -> 0.37020301 | W39: =AB39/$Z39 -> 0.22989474 | X39: =AC39/$Z39 -> 0.18004511 | Y39: =AD39/$Z39 -> 0.10425564 | Z39: {=SUM(Data!BM$2:BM$367*(--(Data!$A$2:$A$367=DATE(Processing!$C$1,$AE39,1))))} -> 133000 | AA39: {=SUM(Data!BI$2:BI$367*(--(Data!$A$2:$A$367=DATE(Processing!$C$1,$AE39,1))))} -> 49237 | AB39: {=SUM(Data!BJ$2:BJ$367*(--(Data!$A$2:$A$367=DATE(Processing!$C$1,$AE39,1))))} -> 30576 | AC39: {=SUM(Data!BK$2:BK$367*(--(Data!$A$2:$A$367=DATE(Processing!$C$1,$AE39,1))))} -> 23946 | AD39: {=SUM(Data!BL$2:BL$367*(--(Data!$A$2:$A$367=DATE(Processing!$C$1,$AE39,1))))} -> 13866 | AE39: 7 | AF39: =IF(AE39=$E$1,SUM(V39:Y39),NA()) -> #N/A | AG39: =H39 -> 14 | AH39: {=IF(ISNA(I39),NA(),SUM(Data!$J$2:$S$367*(--(Data!$A$2:$A$367=DATE(Processing!$C$1,Processing!$E$1,Processing!H39)))))} -> 1079 | AI39: {=IF(ISNA(I39),NA(),SUM(Data!$O$2:$S$367*(--(Data!$A$2:$A$367=DATE(Processing!$C$1,Processing!$E$1,Processing!H39)))))} -> 620 | AJ39: {=SUM(Data!$J$2:$S$367*(--(Data!$A$2:$A$367=DATE(Processing!$C$1,Processing!$E$1,Processing!H39))))} -> 1079 | AL39: =H39 -> 14 | AM39: {=IF(ISNA(I39),NA(),SUM(Data!$T$2:$AX$367*(--(Data!$A$2:$A$367=DATE(Processing!$C$1,Processing!$E$1,Processing!H39)))))} -> 719 | AN39: {=IF(ISNA(I39),NA(),SUM(Data!$AP$2:$AX$367*(--(Data!$A$2:$A$367=DATE(Processing!$C$1,Processing!$E$1,Processing!H39)))))} -> 220 | AO39: {=SUM(Data!$T$2:$AX$367*(--(Data!$A$2:$A$367=DATE(Processing!$C$1,Processing!$E$1,Processing!H39))))} -> 719
A40: Fixed Incom | B40: =GETPIVOTDATA(""&$A$40&" "&B39,Control!$A$7) -> 8115 | C40: =GETPIVOTDATA(""&$A$40&" "&C39,Control!$A$7) -> 4310 | D40: =GETPIVOTDATA(""&$A$40&" "&D39,Control!$A$7) -> 2141 | E40: =GETPIVOTDATA(""&$A$40&" "&E39,Control!$A$7) -> 2205 | F40: =GETPIVOTDATA(""&$A$40&" "&F39,Control!$A$7) -> 1151 | G40: =SUM(B40:F40) -> 17922 | H40: 15 | I40: {=IFERROR(GETPIVOTDATA(""&$N$2,Control!$A$7,""&$H$25,H40)+GETPIVOTDATA(""&$N$3,Control!$A$7,""&$H$25,H40)+GETPIVOTDATA(""&$N$4,Control!$A$7,""&$H$25,H40),NA())} -> 1048 | J40: {=IFERROR(GETPIVOTDATA(""&$N$5,Control!$A$7,""&$H$25,H40)+GETPIVOTDATA(""&$N$6,Control!$A$7,""&$H$25,H40)+GETPIVOTDATA(""&$N$7,Control!$A$7,""&$H$25,H40),NA())} -> 723 | K40: {=SUM(Data!$D$2:$F$367*(--(Data!$A$2:$A$367=DATE(Processing!$C$1,Processing!$E$1,Processing!H40))))} -> 1048 | L40: =IF(ISNA(I40),0,H40) -> 15 | M40: =H40 -> 15 | N40: {=IF(ISNA(I40),NA(),SUM(Data!$AY$2:$AY$367*(--(Data!$A$2:$A$367=DATE(Processing!$C$1,Processing!$E$1,Processing!H40)))))} -> 119050.54 | O40: {=INDEX(Data!$AY$2:$AY$367,MATCH(TRUE,Data!$AY$2:$AY$367>0,0))} -> 117000 | P40: {=IFERROR(IF(NOT(ISNA(I40)),NA(),SUM(Data!$AY$2:$AY$367*(--(Data!$A$2:$A$367=DATE(Processing!$C$1,Processing!$E$1,Processing!H40))))),NA())} -> #N/A | Q40: =H40 -> 15 | R40: {=IF(ISNA(I40),NA(),SUM(Data!$BE$2:$BH$367*(--(Data!$A$2:$A$367=DATE(Processing!$C$1,Processing!$E$1,Processing!H40)))))} -> 78246 | S40: =(R40>0)*$C$28 -> 36058 | T40: {=ISNUMBER(Q40)*SUM(Data!$BE$2:$BH$367*(--(Data!$A$2:$A$367=DATE(Processing!$C$1,Processing!$E$1,Processing!H40))))} -> 78246 | U40: AUG | V40: =AA40/$Z40 -> 0.34816216 | W40: =AB40/$Z40 -> 0.27329054 | X40: =AC40/$Z40 -> 0.1900473 | Y40: =AD40/$Z40 -> 0.12377703 | Z40: {=SUM(Data!BM$2:BM$367*(--(Data!$A$2:$A$367=DATE(Processing!$C$1,$AE40,1))))} -> 148000 | AA40: {=SUM(Data!BI$2:BI$367*(--(Data!$A$2:$A$367=DATE(Processing!$C$1,$AE40,1))))} -> 51528 | AB40: {=SUM(Data!BJ$2:BJ$367*(--(Data!$A$2:$A$367=DATE(Processing!$C$1,$AE40,1))))} -> 40447 | AC40: {=SUM(Data!BK$2:BK$367*(--(Data!$A$2:$A$367=DATE(Processing!$C$1,$AE40,1))))} -> 28127 | AD40: {=SUM(Data!BL$2:BL$367*(--(Data!$A$2:$A$367=DATE(Processing!$C$1,$AE40,1))))} -> 18319 | AE40: 8 | AF40: =IF(AE40=$E$1,SUM(V40:Y40),NA()) -> #N/A | AG40: =H40 -> 15 | AH40: {=IF(ISNA(I40),NA(),SUM(Data!$J$2:$S$367*(--(Data!$A$2:$A$367=DATE(Processing!$C$1,Processing!$E$1,Processing!H40)))))} -> 1048 | AI40: {=IF(ISNA(I40),NA(),SUM(Data!$O$2:$S$367*(--(Data!$A$2:$A$367=DATE(Processing!$C$1,Processing!$E$1,Processing!H40)))))} -> 420 | AJ40: {=SUM(Data!$J$2:$S$367*(--(Data!$A$2:$A$367=DATE(Processing!$C$1,Processing!$E$1,Processing!H40))))} -> 1048 | AL40: =H40 -> 15 | AM40: {=IF(ISNA(I40),NA(),SUM(Data!$T$2:$AX$367*(--(Data!$A$2:$A$367=DATE(Processing!$C$1,Processing!$E$1,Processing!H40)))))} -> 723 | AN40: {=IF(ISNA(I40),NA(),SUM(Data!$AP$2:$AX$367*(--(Data!$A$2:$A$367=DATE(Processing!$C$1,Processing!$E$1,Processing!H40)))))} -> 261 | AO40: {=SUM(Data!$T$2:$AX$367*(--(Data!$A$2:$A$367=DATE(Processing!$C$1,Processing!$E$1,Processing!H40))))} -> 723
A41: Non-Fixed Incom | B41: =GETPIVOTDATA(""&$A$41&" "&B39,Control!$A$7) -> 5373 | C41: =GETPIVOTDATA(""&$A$41&" "&C39,Control!$A$7) -> 1964 | D41: =GETPIVOTDATA(""&$A$41&" "&D39,Control!$A$7) -> 1046 | E41: =GETPIVOTDATA(""&$A$41&" "&E39,Control!$A$7) -> 1201 | F41: =GETPIVOTDATA(""&$A$41&" "&F39,Control!$A$7) -> 3705 | G41: =SUM(B41:F41) -> 13289 | H41: 16 | I41: {=IFERROR(GETPIVOTDATA(""&$N$2,Control!$A$7,""&$H$25,H41)+GETPIVOTDATA(""&$N$3,Control!$A$7,""&$H$25,H41)+GETPIVOTDATA(""&$N$4,Control!$A$7,""&$H$25,H41),NA())} -> 1018 | J41: {=IFERROR(GETPIVOTDATA(""&$N$5,Control!$A$7,""&$H$25,H41)+GETPIVOTDATA(""&$N$6,Control!$A$7,""&$H$25,H41)+GETPIVOTDATA(""&$N$7,Control!$A$7,""&$H$25,H41),NA())} -> 737 | K41: {=SUM(Data!$D$2:$F$367*(--(Data!$A$2:$A$367=DATE(Processing!$C$1,Processing!$E$1,Processing!H41))))} -> 1018 | L41: =IF(ISNA(I41),0,H41) -> 16 | M41: =H41 -> 16 | N41: {=IF(ISNA(I41),NA(),SUM(Data!$AY$2:$AY$367*(--(Data!$A$2:$A$367=DATE(Processing!$C$1,Processing!$E$1,Processing!H41)))))} -> 116743.36 | O41: {=INDEX(Data!$AY$2:$AY$367,MATCH(TRUE,Data!$AY$2:$AY$367>0,0))} -> 117000 | P41: {=IFERROR(IF(NOT(ISNA(I41)),NA(),SUM(Data!$AY$2:$AY$367*(--(Data!$A$2:$A$367=DATE(Processing!$C$1,Processing!$E$1,Processing!H41))))),NA())} -> #N/A | Q41: =H41 -> 16 | R41: {=IF(ISNA(I41),NA(),SUM(Data!$BE$2:$BH$367*(--(Data!$A$2:$A$367=DATE(Processing!$C$1,Processing!$E$1,Processing!H41)))))} -> 59862 | S41: =(R41>0)*$C$28 -> 36058 | T41: {=ISNUMBER(Q41)*SUM(Data!$BE$2:$BH$367*(--(Data!$A$2:$A$367=DATE(Processing!$C$1,Processing!$E$1,Processing!H41))))} -> 59862 | U41: SEP | V41: =AA41/$Z41 -> 0.32560963 | W41: =AB41/$Z41 -> 0.25490909 | X41: =AC41/$Z41 -> 0.18641176 | Y41: =AD41/$Z41 -> 0.12389305 | Z41: {=SUM(Data!BM$2:BM$367*(--(Data!$A$2:$A$367=DATE(Processing!$C$1,$AE41,1))))} -> 187000 | AA41: {=SUM(Data!BI$2:BI$367*(--(Data!$A$2:$A$367=DATE(Processing!$C$1,$AE41,1))))} -> 60889 | AB41: {=SUM(Data!BJ$2:BJ$367*(--(Data!$A$2:$A$367=DATE(Processing!$C$1,$AE41,1))))} -> 47668 | AC41: {=SUM(Data!BK$2:BK$367*(--(Data!$A$2:$A$367=DATE(Processing!$C$1,$AE41,1))))} -> 34859 | AD41: {=SUM(Data!BL$2:BL$367*(--(Data!$A$2:$A$367=DATE(Processing!$C$1,$AE41,1))))} -> 23168 | AE41: 9 | AF41: =IF(AE41=$E$1,SUM(V41:Y41),NA()) -> #N/A | AG41: =H41 -> 16 | AH41: {=IF(ISNA(I41),NA(),SUM(Data!$J$2:$S$367*(--(Data!$A$2:$A$367=DATE(Processing!$C$1,Processing!$E$1,Processing!H41)))))} -> 1018 | AI41: {=IF(ISNA(I41),NA(),SUM(Data!$O$2:$S$367*(--(Data!$A$2:$A$367=DATE(Processing!$C$1,Processing!$E$1,Processing!H41)))))} -> 485 | AJ41: {=SUM(Data!$J$2:$S$367*(--(Data!$A$2:$A$367=DATE(Processing!$C$1,Processing!$E$1,Processing!H41))))} -> 1018 | AL41: =H41 -> 16 | AM41: {=IF(ISNA(I41),NA(),SUM(Data!$T$2:$AX$367*(--(Data!$A$2:$A$367=DATE(Processing!$C$1,Processing!$E$1,Processing!H41)))))} -> 737 | AN41: {=IF(ISNA(I41),NA(),SUM(Data!$AP$2:$AX$367*(--(Data!$A$2:$A$367=DATE(Processing!$C$1,Processing!$E$1,Processing!H41)))))} -> 232 | AO41: {=SUM(Data!$T$2:$AX$367*(--(Data!$A$2:$A$367=DATE(Processing!$C$1,Processing!$E$1,Processing!H41))))} -> 737
B42: Business | C42: Securities | D42: Gold | E42: Real estate | F42: Cryptocurrency | G42: =SUM(G40:G41) -> 31211 | H42: 17 | I42: {=IFERROR(GETPIVOTDATA(""&$N$2,Control!$A$7,""&$H$25,H42)+GETPIVOTDATA(""&$N$3,Control!$A$7,""&$H$25,H42)+GETPIVOTDATA(""&$N$4,Control!$A$7,""&$H$25,H42),NA())} -> 995 | J42: {=IFERROR(GETPIVOTDATA(""&$N$5,Control!$A$7,""&$H$25,H42)+GETPIVOTDATA(""&$N$6,Control!$A$7,""&$H$25,H42)+GETPIVOTDATA(""&$N$7,Control!$A$7,""&$H$25,H42),NA())} -> 764 | K42: {=SUM(Data!$D$2:$F$367*(--(Data!$A$2:$A$367=DATE(Processing!$C$1,Processing!$E$1,Processing!H42))))} -> 995 | L42: =IF(ISNA(I42),0,H42) -> 17 | M42: =H42 -> 17 | N42: {=IF(ISNA(I42),NA(),SUM(Data!$AY$2:$AY$367*(--(Data!$A$2:$A$367=DATE(Processing!$C$1,Processing!$E$1,Processing!H42)))))} -> 113560.6 | O42: {=INDEX(Data!$AY$2:$AY$367,MATCH(TRUE,Data!$AY$2:$AY$367>0,0))} -> 117000 | P42: {=IFERROR(IF(NOT(ISNA(I42)),NA(),SUM(Data!$AY$2:$AY$367*(--(Data!$A$2:$A$367=DATE(Processing!$C$1,Processing!$E$1,Processing!H42))))),NA())} -> #N/A | Q42: =H42 -> 17 | R42: {=IF(ISNA(I42),NA(),SUM(Data!$BE$2:$BH$367*(--(Data!$A$2:$A$367=DATE(Processing!$C$1,Processing!$E$1,Processing!H42)))))} -> 59862 | S42: =(R42>0)*$C$28 -> 36058 | T42: {=ISNUMBER(Q42)*SUM(Data!$BE$2:$BH$367*(--(Data!$A$2:$A$367=DATE(Processing!$C$1,Processing!$E$1,Processing!H42))))} -> 59862 | U42: OCT | V42: =AA42/$Z42 -> 0.32897949 | W42: =AB42/$Z42 -> 0.25491795 | X42: =AC42/$Z42 -> 0.20388718 | Y42: =AD42/$Z42 -> 0.12435897 | Z42: {=SUM(Data!BM$2:BM$367*(--(Data!$A$2:$A$367=DATE(Processing!$C$1,$AE42,1))))} -> 195000 | AA42: {=SUM(Data!BI$2:BI$367*(--(Data!$A$2:$A$367=DATE(Processing!$C$1,$AE42,1))))} -> 64151 | AB42: {=SUM(Data!BJ$2:BJ$367*(--(Data!$A$2:$A$367=DATE(Processing!$C$1,$AE42,1))))} -> 49709 | AC42: {=SUM(Data!BK$2:BK$367*(--(Data!$A$2:$A$367=DATE(Processing!$C$1,$AE42,1))))} -> 39758 | AD42: {=SUM(Data!BL$2:BL$367*(--(Data!$A$2:$A$367=DATE(Processing!$C$1,$AE42,1))))} -> 24250 | AE42: 10 | AF42: =IF(AE42=$E$1,SUM(V42:Y42),NA()) -> #N/A | AG42: =H42 -> 17 | AH42: {=IF(ISNA(I42),NA(),SUM(Data!$J$2:$S$367*(--(Data!$A$2:$A$367=DATE(Processing!$C$1,Processing!$E$1,Processing!H42)))))} -> 995 | AI42: {=IF(ISNA(I42),NA(),SUM(Data!$O$2:$S$367*(--(Data!$A$2:$A$367=DATE(Processing!$C$1,Processing!$E$1,Processing!H42)))))} -> 394 | AJ42: {=SUM(Data!$J$2:$S$367*(--(Data!$A$2:$A$367=DATE(Processing!$C$1,Processing!$E$1,Processing!H42))))} -> 995 | AL42: =H42 -> 17 | AM42: {=IF(ISNA(I42),NA(),SUM(Data!$T$2:$AX$367*(--(Data!$A$2:$A$367=DATE(Processing!$C$1,Processing!$E$1,Processing!H42)))))} -> 764 | AN42: {=IF(ISNA(I42),NA(),SUM(Data!$AP$2:$AX$367*(--(Data!$A$2:$A$367=DATE(Processing!$C$1,Processing!$E$1,Processing!H42)))))} -> 218 | AO42: {=SUM(Data!$T$2:$AX$367*(--(Data!$A$2:$A$367=DATE(Processing!$C$1,Processing!$E$1,Processing!H42))))} -> 764
A43: Income Share | B43: Total | D43: Ratio Income | H43: 18 | I43: {=IFERROR(GETPIVOTDATA(""&$N$2,Control!$A$7,""&$H$25,H43)+GETPIVOTDATA(""&$N$3,Control!$A$7,""&$H$25,H43)+GETPIVOTDATA(""&$N$4,Control!$A$7,""&$H$25,H43),NA())} -> 986 | J43: {=IFERROR(GETPIVOTDATA(""&$N$5,Control!$A$7,""&$H$25,H43)+GETPIVOTDATA(""&$N$6,Control!$A$7,""&$H$25,H43)+GETPIVOTDATA(""&$N$7,Control!$A$7,""&$H$25,H43),NA())} -> 796 | K43: {=SUM(Data!$D$2:$F$367*(--(Data!$A$2:$A$367=DATE(Processing!$C$1,Processing!$E$1,Processing!H43))))} -> 986 | L43: =IF(ISNA(I43),0,H43) -> 18 | M43: =H43 -> 18 | N43: {=IF(ISNA(I43),NA(),SUM(Data!$AY$2:$AY$367*(--(Data!$A$2:$A$367=DATE(Processing!$C$1,Processing!$E$1,Processing!H43)))))} -> 110530.71 | O43: {=INDEX(Data!$AY$2:$AY$367,MATCH(TRUE,Data!$AY$2:$AY$367>0,0))} -> 117000 | P43: {=IFERROR(IF(NOT(ISNA(I43)),NA(),SUM(Data!$AY$2:$AY$367*(--(Data!$A$2:$A$367=DATE(Processing!$C$1,Processing!$E$1,Processing!H43))))),NA())} -> #N/A | Q43: =H43 -> 18 | R43: {=IF(ISNA(I43),NA(),SUM(Data!$BE$2:$BH$367*(--(Data!$A$2:$A$367=DATE(Processing!$C$1,Processing!$E$1,Processing!H43)))))} -> 59862 | S43: =(R43>0)*$C$28 -> 36058 | T43: {=ISNUMBER(Q43)*SUM(Data!$BE$2:$BH$367*(--(Data!$A$2:$A$367=DATE(Processing!$C$1,Processing!$E$1,Processing!H43))))} -> 59862 | U43: NOV | V43: =AA43/$Z43 -> 0.34353922 | W43: =AB43/$Z43 -> 0.26327941 | X43: =AC43/$Z43 -> 0.22063725 | Y43: =AD43/$Z43 -> 0.14059314 | Z43: {=SUM(Data!BM$2:BM$367*(--(Data!$A$2:$A$367=DATE(Processing!$C$1,$AE43,1))))} -> 204000 | AA43: {=SUM(Data!BI$2:BI$367*(--(Data!$A$2:$A$367=DATE(Processing!$C$1,$AE43,1))))} -> 70082 | AB43: {=SUM(Data!BJ$2:BJ$367*(--(Data!$A$2:$A$367=DATE(Processing!$C$1,$AE43,1))))} -> 53709 | AC43: {=SUM(Data!BK$2:BK$367*(--(Data!$A$2:$A$367=DATE(Processing!$C$1,$AE43,1))))} -> 45010 | AD43: {=SUM(Data!BL$2:BL$367*(--(Data!$A$2:$A$367=DATE(Processing!$C$1,$AE43,1))))} -> 28681 | AE43: 11 | AF43: =IF(AE43=$E$1,SUM(V43:Y43),NA()) -> #N/A | AG43: =H43 -> 18 | AH43: {=IF(ISNA(I43),NA(),SUM(Data!$J$2:$S$367*(--(Data!$A$2:$A$367=DATE(Processing!$C$1,Processing!$E$1,Processing!H43)))))} -> 986 | AI43: {=IF(ISNA(I43),NA(),SUM(Data!$O$2:$S$367*(--(Data!$A$2:$A$367=DATE(Processing!$C$1,Processing!$E$1,Processing!H43)))))} -> 354 | AJ43: {=SUM(Data!$J$2:$S$367*(--(Data!$A$2:$A$367=DATE(Processing!$C$1,Processing!$E$1,Processing!H43))))} -> 986 | AL43: =H43 -> 18 | AM43: {=IF(ISNA(I43),NA(),SUM(Data!$T$2:$AX$367*(--(Data!$A$2:$A$367=DATE(Processing!$C$1,Processing!$E$1,Processing!H43)))))} -> 796 | AN43: {=IF(ISNA(I43),NA(),SUM(Data!$AP$2:$AX$367*(--(Data!$A$2:$A$367=DATE(Processing!$C$1,Processing!$E$1,Processing!H43)))))} -> 263 | AO43: {=SUM(Data!$T$2:$AX$367*(--(Data!$A$2:$A$367=DATE(Processing!$C$1,Processing!$E$1,Processing!H43))))} -> 796
A44: =B39 -> Business | B44: =B40+B41 -> 13488 | D44: Fixed Incom | E44: Non-Fixed Incom | H44: 19 | I44: {=IFERROR(GETPIVOTDATA(""&$N$2,Control!$A$7,""&$H$25,H44)+GETPIVOTDATA(""&$N$3,Control!$A$7,""&$H$25,H44)+GETPIVOTDATA(""&$N$4,Control!$A$7,""&$H$25,H44),NA())} -> 983 | J44: {=IFERROR(GETPIVOTDATA(""&$N$5,Control!$A$7,""&$H$25,H44)+GETPIVOTDATA(""&$N$6,Control!$A$7,""&$H$25,H44)+GETPIVOTDATA(""&$N$7,Control!$A$7,""&$H$25,H44),NA())} -> 841 | K44: {=SUM(Data!$D$2:$F$367*(--(Data!$A$2:$A$367=DATE(Processing!$C$1,Processing!$E$1,Processing!H44))))} -> 983 | L44: =IF(ISNA(I44),0,H44) -> 19 | M44: =H44 -> 19 | N44: {=IF(ISNA(I44),NA(),SUM(Data!$AY$2:$AY$367*(--(Data!$A$2:$A$367=DATE(Processing!$C$1,Processing!$E$1,Processing!H44)))))} -> 106921.42 | O44: {=INDEX(Data!$AY$2:$AY$367,MATCH(TRUE,Data!$AY$2:$AY$367>0,0))} -> 117000 | P44: {=IFERROR(IF(NOT(ISNA(I44)),NA(),SUM(Data!$AY$2:$AY$367*(--(Data!$A$2:$A$367=DATE(Processing!$C$1,Processing!$E$1,Processing!H44))))),NA())} -> #N/A | Q44: =H44 -> 19 | R44: {=IF(ISNA(I44),NA(),SUM(Data!$BE$2:$BH$367*(--(Data!$A$2:$A$367=DATE(Processing!$C$1,Processing!$E$1,Processing!H44)))))} -> 59862 | S44: =(R44>0)*$C$28 -> 36058 | T44: {=ISNUMBER(Q44)*SUM(Data!$BE$2:$BH$367*(--(Data!$A$2:$A$367=DATE(Processing!$C$1,Processing!$E$1,Processing!H44))))} -> 59862 | U44: DEC | V44: =AA44/$Z44 -> 0.3287087 | W44: =AB44/$Z44 -> 0.27478696 | X44: =AC44/$Z44 -> 0.2413087 | Y44: =AD44/$Z44 -> 0.13043478 | Z44: {=SUM(Data!BM$2:BM$367*(--(Data!$A$2:$A$367=DATE(Processing!$C$1,$AE44,1))))} -> 230000 | AA44: {=SUM(Data!BI$2:BI$367*(--(Data!$A$2:$A$367=DATE(Processing!$C$1,$AE44,1))))} -> 75603 | AB44: {=SUM(Data!BJ$2:BJ$367*(--(Data!$A$2:$A$367=DATE(Processing!$C$1,$AE44,1))))} -> 63201 | AC44: {=SUM(Data!BK$2:BK$367*(--(Data!$A$2:$A$367=DATE(Processing!$C$1,$AE44,1))))} -> 55501 | AD44: {=SUM(Data!BL$2:BL$367*(--(Data!$A$2:$A$367=DATE(Processing!$C$1,$AE44,1))))} -> 30000 | AE44: 12 | AF44: =IF(AE44=$E$1,SUM(V44:Y44),NA()) -> #N/A | AG44: =H44 -> 19 | AH44: {=IF(ISNA(I44),NA(),SUM(Data!$J$2:$S$367*(--(Data!$A$2:$A$367=DATE(Processing!$C$1,Processing!$E$1,Processing!H44)))))} -> 983 | AI44: {=IF(ISNA(I44),NA(),SUM(Data!$O$2:$S$367*(--(Data!$A$2:$A$367=DATE(Processing!$C$1,Processing!$E$1,Processing!H44)))))} -> 395 | AJ44: {=SUM(Data!$J$2:$S$367*(--(Data!$A$2:$A$367=DATE(Processing!$C$1,Processing!$E$1,Processing!H44))))} -> 983 | AL44: =H44 -> 19 | AM44: {=IF(ISNA(I44),NA(),SUM(Data!$T$2:$AX$367*(--(Data!$A$2:$A$367=DATE(Processing!$C$1,Processing!$E$1,Processing!H44)))))} -> 841 | AN44: {=IF(ISNA(I44),NA(),SUM(Data!$AP$2:$AX$367*(--(Data!$A$2:$A$367=DATE(Processing!$C$1,Processing!$E$1,Processing!H44)))))} -> 286 | AO44: {=SUM(Data!$T$2:$AX$367*(--(Data!$A$2:$A$367=DATE(Processing!$C$1,Processing!$E$1,Processing!H44))))} -> 841
A45: =C39 -> Securities | B45: =C40+C41 -> 6274 | D45: =G40/(G40+G41) -> 0.57422063 | E45: =1-D45 -> 0.42577937 | H45: 20 | I45: {=IFERROR(GETPIVOTDATA(""&$N$2,Control!$A$7,""&$H$25,H45)+GETPIVOTDATA(""&$N$3,Control!$A$7,""&$H$25,H45)+GETPIVOTDATA(""&$N$4,Control!$A$7,""&$H$25,H45),NA())} -> 985 | J45: {=IFERROR(GETPIVOTDATA(""&$N$5,Control!$A$7,""&$H$25,H45)+GETPIVOTDATA(""&$N$6,Control!$A$7,""&$H$25,H45)+GETPIVOTDATA(""&$N$7,Control!$A$7,""&$H$25,H45),NA())} -> 874 | K45: {=SUM(Data!$D$2:$F$367*(--(Data!$A$2:$A$367=DATE(Processing!$C$1,Processing!$E$1,Processing!H45))))} -> 985 | L45: =IF(ISNA(I45),0,H45) -> 20 | M45: =H45 -> 20 | N45: {=IF(ISNA(I45),NA(),SUM(Data!$AY$2:$AY$367*(--(Data!$A$2:$A$367=DATE(Processing!$C$1,Processing!$E$1,Processing!H45)))))} -> 103518.88 | O45: {=INDEX(Data!$AY$2:$AY$367,MATCH(TRUE,Data!$AY$2:$AY$367>0,0))} -> 117000 | P45: {=IFERROR(IF(NOT(ISNA(I45)),NA(),SUM(Data!$AY$2:$AY$367*(--(Data!$A$2:$A$367=DATE(Processing!$C$1,Processing!$E$1,Processing!H45))))),NA())} -> #N/A | Q45: =H45 -> 20 | R45: {=IF(ISNA(I45),NA(),SUM(Data!$BE$2:$BH$367*(--(Data!$A$2:$A$367=DATE(Processing!$C$1,Processing!$E$1,Processing!H45)))))} -> 59862 | S45: =(R45>0)*$C$28 -> 36058 | T45: {=ISNUMBER(Q45)*SUM(Data!$BE$2:$BH$367*(--(Data!$A$2:$A$367=DATE(Processing!$C$1,Processing!$E$1,Processing!H45))))} -> 59862 | AG45: =H45 -> 20 | AH45: {=IF(ISNA(I45),NA(),SUM(Data!$J$2:$S$367*(--(Data!$A$2:$A$367=DATE(Processing!$C$1,Processing!$E$1,Processing!H45)))))} -> 985 | AI45: {=IF(ISNA(I45),NA(),SUM(Data!$O$2:$S$367*(--(Data!$A$2:$A$367=DATE(Processing!$C$1,Processing!$E$1,Processing!H45)))))} -> 359 | AJ45: {=SUM(Data!$J$2:$S$367*(--(Data!$A$2:$A$367=DATE(Processing!$C$1,Processing!$E$1,Processing!H45))))} -> 985 | AL45: =H45 -> 20 | AM45: {=IF(ISNA(I45),NA(),SUM(Data!$T$2:$AX$367*(--(Data!$A$2:$A$367=DATE(Processing!$C$1,Processing!$E$1,Processing!H45)))))} -> 874 | AN45: {=IF(ISNA(I45),NA(),SUM(Data!$AP$2:$AX$367*(--(Data!$A$2:$A$367=DATE(Processing!$C$1,Processing!$E$1,Processing!H45)))))} -> 255 | AO45: {=SUM(Data!$T$2:$AX$367*(--(Data!$A$2:$A$367=DATE(Processing!$C$1,Processing!$E$1,Processing!H45))))} -> 874
A46: =D39 -> Gold | B46: =D40+D41 -> 3187 | H46: 21 | I46: {=IFERROR(GETPIVOTDATA(""&$N$2,Control!$A$7,""&$H$25,H46)+GETPIVOTDATA(""&$N$3,Control!$A$7,""&$H$25,H46)+GETPIVOTDATA(""&$N$4,Control!$A$7,""&$H$25,H46),NA())} -> 998 | J46: {=IFERROR(GETPIVOTDATA(""&$N$5,Control!$A$7,""&$H$25,H46)+GETPIVOTDATA(""&$N$6,Control!$A$7,""&$H$25,H46)+GETPIVOTDATA(""&$N$7,Control!$A$7,""&$H$25,H46),NA())} -> 902 | K46: {=SUM(Data!$D$2:$F$367*(--(Data!$A$2:$A$367=DATE(Processing!$C$1,Processing!$E$1,Processing!H46))))} -> 998 | L46: =IF(ISNA(I46),0,H46) -> 21 | M46: =H46 -> 21 | N46: {=IF(ISNA(I46),NA(),SUM(Data!$AY$2:$AY$367*(--(Data!$A$2:$A$367=DATE(Processing!$C$1,Processing!$E$1,Processing!H46)))))} -> 100306.4 | O46: {=INDEX(Data!$AY$2:$AY$367,MATCH(TRUE,Data!$AY$2:$AY$367>0,0))} -> 117000 | P46: {=IFERROR(IF(NOT(ISNA(I46)),NA(),SUM(Data!$AY$2:$AY$367*(--(Data!$A$2:$A$367=DATE(Processing!$C$1,Processing!$E$1,Processing!H46))))),NA())} -> #N/A | Q46: =H46 -> 21 | R46: {=IF(ISNA(I46),NA(),SUM(Data!$BE$2:$BH$367*(--(Data!$A$2:$A$367=DATE(Processing!$C$1,Processing!$E$1,Processing!H46)))))} -> 59862 | S46: =(R46>0)*$C$28 -> 36058 | T46: {=ISNUMBER(Q46)*SUM(Data!$BE$2:$BH$367*(--(Data!$A$2:$A$367=DATE(Processing!$C$1,Processing!$E$1,Processing!H46))))} -> 59862 | V46: 13409 | W46: 4153 | X46: 3743 | Y46: 487 | Z46: =SUM(V46:Y46) -> 21792 | AA46: =Z46/Z33 -> 0.75144828 | AB46: =Z46/AA46 -> 29000 | AG46: =H46 -> 21 | AH46: {=IF(ISNA(I46),NA(),SUM(Data!$J$2:$S$367*(--(Data!$A$2:$A$367=DATE(Processing!$C$1,Processing!$E$1,Processing!H46)))))} -> 998 | AI46: {=IF(ISNA(I46),NA(),SUM(Data!$O$2:$S$367*(--(Data!$A$2:$A$367=DATE(Processing!$C$1,Processing!$E$1,Processing!H46)))))} -> 432 | AJ46: {=SUM(Data!$J$2:$S$367*(--(Data!$A$2:$A$367=DATE(Processing!$C$1,Processing!$E$1,Processing!H46))))} -> 998 | AL46: =H46 -> 21 | AM46: {=IF(ISNA(I46),NA(),SUM(Data!$T$2:$AX$367*(--(Data!$A$2:$A$367=DATE(Processing!$C$1,Processing!$E$1,Processing!H46)))))} -> 902 | AN46: {=IF(ISNA(I46),NA(),SUM(Data!$AP$2:$AX$367*(--(Data!$A$2:$A$367=DATE(Processing!$C$1,Processing!$E$1,Processing!H46)))))} -> 218 | AO46: {=SUM(Data!$T$2:$AX$367*(--(Data!$A$2:$A$367=DATE(Processing!$C$1,Processing!$E$1,Processing!H46))))} -> 902
A47: =E39 -> Real estate | B47: =E40+E41 -> 3406 | H47: 22 | I47: {=IFERROR(GETPIVOTDATA(""&$N$2,Control!$A$7,""&$H$25,H47)+GETPIVOTDATA(""&$N$3,Control!$A$7,""&$H$25,H47)+GETPIVOTDATA(""&$N$4,Control!$A$7,""&$H$25,H47),NA())} -> 1032 | J47: {=IFERROR(GETPIVOTDATA(""&$N$5,Control!$A$7,""&$H$25,H47)+GETPIVOTDATA(""&$N$6,Control!$A$7,""&$H$25,H47)+GETPIVOTDATA(""&$N$7,Control!$A$7,""&$H$25,H47),NA())} -> 910 | K47: {=SUM(Data!$D$2:$F$367*(--(Data!$A$2:$A$367=DATE(Processing!$C$1,Processing!$E$1,Processing!H47))))} -> 1032 | L47: =IF(ISNA(I47),0,H47) -> 22 | M47: =H47 -> 22 | N47: {=IF(ISNA(I47),NA(),SUM(Data!$AY$2:$AY$367*(--(Data!$A$2:$A$367=DATE(Processing!$C$1,Processing!$E$1,Processing!H47)))))} -> 97147.53 | O47: {=INDEX(Data!$AY$2:$AY$367,MATCH(TRUE,Data!$AY$2:$AY$367>0,0))} -> 117000 | P47: {=IFERROR(IF(NOT(ISNA(I47)),NA(),SUM(Data!$AY$2:$AY$367*(--(Data!$A$2:$A$367=DATE(Processing!$C$1,Processing!$E$1,Processing!H47))))),NA())} -> #N/A | Q47: =H47 -> 22 | R47: {=IF(ISNA(I47),NA(),SUM(Data!$BE$2:$BH$367*(--(Data!$A$2:$A$367=DATE(Processing!$C$1,Processing!$E$1,Processing!H47)))))} -> 59862 | S47: =(R47>0)*$C$28 -> 36058 | T47: {=ISNUMBER(Q47)*SUM(Data!$BE$2:$BH$367*(--(Data!$A$2:$A$367=DATE(Processing!$C$1,Processing!$E$1,Processing!H47))))} -> 59862 | V47: 15546 | W47: 6648 | X47: 5071 | Y47: 1132 | Z47: =SUM(V47:Y47) -> 28397 | AA47: =Z47/Z34 -> 0.74728947 | AB47: =Z47/AA47 -> 38000 | AG47: =H47 -> 22 | AH47: {=IF(ISNA(I47),NA(),SUM(Data!$J$2:$S$367*(--(Data!$A$2:$A$367=DATE(Processing!$C$1,Processing!$E$1,Processing!H47)))))} -> 1032 | AI47: {=IF(ISNA(I47),NA(),SUM(Data!$O$2:$S$367*(--(Data!$A$2:$A$367=DATE(Processing!$C$1,Processing!$E$1,Processing!H47)))))} -> 434 | AJ47: {=SUM(Data!$J$2:$S$367*(--(Data!$A$2:$A$367=DATE(Processing!$C$1,Processing!$E$1,Processing!H47))))} -> 1032 | AL47: =H47 -> 22 | AM47: {=IF(ISNA(I47),NA(),SUM(Data!$T$2:$AX$367*(--(Data!$A$2:$A$367=DATE(Processing!$C$1,Processing!$E$1,Processing!H47)))))} -> 910 | AN47: {=IF(ISNA(I47),NA(),SUM(Data!$AP$2:$AX$367*(--(Data!$A$2:$A$367=DATE(Processing!$C$1,Processing!$E$1,Processing!H47)))))} -> 324 | AO47: {=SUM(Data!$T$2:$AX$367*(--(Data!$A$2:$A$367=DATE(Processing!$C$1,Processing!$E$1,Processing!H47))))} -> 910
A48: =F39 -> Cryptocurrency | B48: =F40+F41 -> 4856 | H48: 23 | I48: {=IFERROR(GETPIVOTDATA(""&$N$2,Control!$A$7,""&$H$25,H48)+GETPIVOTDATA(""&$N$3,Control!$A$7,""&$H$25,H48)+GETPIVOTDATA(""&$N$4,Control!$A$7,""&$H$25,H48),NA())} -> 1047 | J48: {=IFERROR(GETPIVOTDATA(""&$N$5,Control!$A$7,""&$H$25,H48)+GETPIVOTDATA(""&$N$6,Control!$A$7,""&$H$25,H48)+GETPIVOTDATA(""&$N$7,Control!$A$7,""&$H$25,H48),NA())} -> 912 | K48: {=SUM(Data!$D$2:$F$367*(--(Data!$A$2:$A$367=DATE(Processing!$C$1,Processing!$E$1,Processing!H48))))} -> 1047 | L48: =IF(ISNA(I48),0,H48) -> 23 | M48: =H48 -> 23 | N48: {=IF(ISNA(I48),NA(),SUM(Data!$AY$2:$AY$367*(--(Data!$A$2:$A$367=DATE(Processing!$C$1,Processing!$E$1,Processing!H48)))))} -> 94622.43 | O48: {=INDEX(Data!$AY$2:$AY$367,MATCH(TRUE,Data!$AY$2:$AY$367>0,0))} -> 117000 | P48: {=IFERROR(IF(NOT(ISNA(I48)),NA(),SUM(Data!$AY$2:$AY$367*(--(Data!$A$2:$A$367=DATE(Processing!$C$1,Processing!$E$1,Processing!H48))))),NA())} -> #N/A | Q48: =H48 -> 23 | R48: {=IF(ISNA(I48),NA(),SUM(Data!$BE$2:$BH$367*(--(Data!$A$2:$A$367=DATE(Processing!$C$1,Processing!$E$1,Processing!H48)))))} -> 69253 | S48: =(R48>0)*$C$28 -> 36058 | T48: {=ISNUMBER(Q48)*SUM(Data!$BE$2:$BH$367*(--(Data!$A$2:$A$367=DATE(Processing!$C$1,Processing!$E$1,Processing!H48))))} -> 69253 | V48: 25279 | W48: 8272 | X48: 6286.2 | Y48: 1857 | Z48: =SUM(V48:Y48) -> 41694.2 | AA48: =Z48/Z35 -> 0.85090204 | AB48: =Z48/AA48 -> 49000 | AD48: 25168 | AG48: =H48 -> 23 | AH48: {=IF(ISNA(I48),NA(),SUM(Data!$J$2:$S$367*(--(Data!$A$2:$A$367=DATE(Processing!$C$1,Processing!$E$1,Processing!H48)))))} -> 1047 | AI48: {=IF(ISNA(I48),NA(),SUM(Data!$O$2:$S$367*(--(Data!$A$2:$A$367=DATE(Processing!$C$1,Processing!$E$1,Processing!H48)))))} -> 466 | AJ48: {=SUM(Data!$J$2:$S$367*(--(Data!$A$2:$A$367=DATE(Processing!$C$1,Processing!$E$1,Processing!H48))))} -> 1047 | AL48: =H48 -> 23 | AM48: {=IF(ISNA(I48),NA(),SUM(Data!$T$2:$AX$367*(--(Data!$A$2:$A$367=DATE(Processing!$C$1,Processing!$E$1,Processing!H48)))))} -> 912 | AN48: {=IF(ISNA(I48),NA(),SUM(Data!$AP$2:$AX$367*(--(Data!$A$2:$A$367=DATE(Processing!$C$1,Processing!$E$1,Processing!H48)))))} -> 335 | AO48: {=SUM(Data!$T$2:$AX$367*(--(Data!$A$2:$A$367=DATE(Processing!$C$1,Processing!$E$1,Processing!H48))))} -> 912
H49: 24 | I49: {=IFERROR(GETPIVOTDATA(""&$N$2,Control!$A$7,""&$H$25,H49)+GETPIVOTDATA(""&$N$3,Control!$A$7,""&$H$25,H49)+GETPIVOTDATA(""&$N$4,Control!$A$7,""&$H$25,H49),NA())} -> 1051 | J49: {=IFERROR(GETPIVOTDATA(""&$N$5,Control!$A$7,""&$H$25,H49)+GETPIVOTDATA(""&$N$6,Control!$A$7,""&$H$25,H49)+GETPIVOTDATA(""&$N$7,Control!$A$7,""&$H$25,H49),NA())} -> 912 | K49: {=SUM(Data!$D$2:$F$367*(--(Data!$A$2:$A$367=DATE(Processing!$C$1,Processing!$E$1,Processing!H49))))} -> 1051 | L49: =IF(ISNA(I49),0,H49) -> 24 | M49: =H49 -> 24 | N49: {=IF(ISNA(I49),NA(),SUM(Data!$AY$2:$AY$367*(--(Data!$A$2:$A$367=DATE(Processing!$C$1,Processing!$E$1,Processing!H49)))))} -> 92322.58 | O49: {=INDEX(Data!$AY$2:$AY$367,MATCH(TRUE,Data!$AY$2:$AY$367>0,0))} -> 117000 | P49: {=IFERROR(IF(NOT(ISNA(I49)),NA(),SUM(Data!$AY$2:$AY$367*(--(Data!$A$2:$A$367=DATE(Processing!$C$1,Processing!$E$1,Processing!H49))))),NA())} -> #N/A | Q49: =H49 -> 24 | R49: {=IF(ISNA(I49),NA(),SUM(Data!$BE$2:$BH$367*(--(Data!$A$2:$A$367=DATE(Processing!$C$1,Processing!$E$1,Processing!H49)))))} -> 66942 | S49: =(R49>0)*$C$28 -> 36058 | T49: {=ISNUMBER(Q49)*SUM(Data!$BE$2:$BH$367*(--(Data!$A$2:$A$367=DATE(Processing!$C$1,Processing!$E$1,Processing!H49))))} -> 66942 | V49: 35398 | W49: 12892 | X49: 7144 | Y49: 1345 | Z49: =SUM(V49:Y49) -> 56779 | AA49: =Z49/Z36 -> 0.78859722 | AB49: =Z49/AA49 -> 72000 | AG49: =H49 -> 24 | AH49: {=IF(ISNA(I49),NA(),SUM(Data!$J$2:$S$367*(--(Data!$A$2:$A$367=DATE(Processing!$C$1,Processing!$E$1,Processing!H49)))))} -> 1051 | AI49: {=IF(ISNA(I49),NA(),SUM(Data!$O$2:$S$367*(--(Data!$A$2:$A$367=DATE(Processing!$C$1,Processing!$E$1,Processing!H49)))))} -> 539 | AJ49: {=SUM(Data!$J$2:$S$367*(--(Data!$A$2:$A$367=DATE(Processing!$C$1,Processing!$E$1,Processing!H49))))} -> 1051 | AL49: =H49 -> 24 | AM49: {=IF(ISNA(I49),NA(),SUM(Data!$T$2:$AX$367*(--(Data!$A$2:$A$367=DATE(Processing!$C$1,Processing!$E$1,Processing!H49)))))} -> 912 | AN49: {=IF(ISNA(I49),NA(),SUM(Data!$AP$2:$AX$367*(--(Data!$A$2:$A$367=DATE(Processing!$C$1,Processing!$E$1,Processing!H49)))))} -> 225 | AO49: {=SUM(Data!$T$2:$AX$367*(--(Data!$A$2:$A$367=DATE(Processing!$C$1,Processing!$E$1,Processing!H49))))} -> 912
H50: 25 | I50: {=IFERROR(GETPIVOTDATA(""&$N$2,Control!$A$7,""&$H$25,H50)+GETPIVOTDATA(""&$N$3,Control!$A$7,""&$H$25,H50)+GETPIVOTDATA(""&$N$4,Control!$A$7,""&$H$25,H50),NA())} -> 1051 | J50: {=IFERROR(GETPIVOTDATA(""&$N$5,Control!$A$7,""&$H$25,H50)+GETPIVOTDATA(""&$N$6,Control!$A$7,""&$H$25,H50)+GETPIVOTDATA(""&$N$7,Control!$A$7,""&$H$25,H50),NA())} -> 905 | K50: {=SUM(Data!$D$2:$F$367*(--(Data!$A$2:$A$367=DATE(Processing!$C$1,Processing!$E$1,Processing!H50))))} -> 1051 | L50: =IF(ISNA(I50),0,H50) -> 25 | M50: =H50 -> 25 | N50: {=IF(ISNA(I50),NA(),SUM(Data!$AY$2:$AY$367*(--(Data!$A$2:$A$367=DATE(Processing!$C$1,Processing!$E$1,Processing!H50)))))} -> 90855.14 | O50: {=INDEX(Data!$AY$2:$AY$367,MATCH(TRUE,Data!$AY$2:$AY$367>0,0))} -> 117000 | P50: {=IFERROR(IF(NOT(ISNA(I50)),NA(),SUM(Data!$AY$2:$AY$367*(--(Data!$A$2:$A$367=DATE(Processing!$C$1,Processing!$E$1,Processing!H50))))),NA())} -> #N/A | Q50: =H50 -> 25 | R50: {=IF(ISNA(I50),NA(),SUM(Data!$BE$2:$BH$367*(--(Data!$A$2:$A$367=DATE(Processing!$C$1,Processing!$E$1,Processing!H50)))))} -> 66942 | S50: =(R50>0)*$C$28 -> 36058 | T50: {=ISNUMBER(Q50)*SUM(Data!$BE$2:$BH$367*(--(Data!$A$2:$A$367=DATE(Processing!$C$1,Processing!$E$1,Processing!H50))))} -> 66942 | V50: 42350 | W50: 24624.6 | X50: 9286.2 | Y50: 2340.8 | Z50: =SUM(V50:Y50) -> 78601.6 | AA50: =Z50/Z37 -> 0.74152453 | AB50: =Z50/AA50 -> 106000 | AD50: 11977 | AG50: =H50 -> 25 | AH50: {=IF(ISNA(I50),NA(),SUM(Data!$J$2:$S$367*(--(Data!$A$2:$A$367=DATE(Processing!$C$1,Processing!$E$1,Processing!H50)))))} -> 1051 | AI50: {=IF(ISNA(I50),NA(),SUM(Data!$O$2:$S$367*(--(Data!$A$2:$A$367=DATE(Processing!$C$1,Processing!$E$1,Processing!H50)))))} -> 408 | AJ50: {=SUM(Data!$J$2:$S$367*(--(Data!$A$2:$A$367=DATE(Processing!$C$1,Processing!$E$1,Processing!H50))))} -> 1051 | AL50: =H50 -> 25 | AM50: {=IF(ISNA(I50),NA(),SUM(Data!$T$2:$AX$367*(--(Data!$A$2:$A$367=DATE(Processing!$C$1,Processing!$E$1,Processing!H50)))))} -> 905 | AN50: {=IF(ISNA(I50),NA(),SUM(Data!$AP$2:$AX$367*(--(Data!$A$2:$A$367=DATE(Processing!$C$1,Processing!$E$1,Processing!H50)))))} -> 221 | AO50: {=SUM(Data!$T$2:$AX$367*(--(Data!$A$2:$A$367=DATE(Processing!$C$1,Processing!$E$1,Processing!H50))))} -> 905
A51: Id | B51: COUNTIF | C51: Number | D51: Income Ranking | E51: =A38 -> Income | H51: 26 | I51: {=IFERROR(GETPIVOTDATA(""&$N$2,Control!$A$7,""&$H$25,H51)+GETPIVOTDATA(""&$N$3,Control!$A$7,""&$H$25,H51)+GETPIVOTDATA(""&$N$4,Control!$A$7,""&$H$25,H51),NA())} -> 1039 | J51: {=IFERROR(GETPIVOTDATA(""&$N$5,Control!$A$7,""&$H$25,H51)+GETPIVOTDATA(""&$N$6,Control!$A$7,""&$H$25,H51)+GETPIVOTDATA(""&$N$7,Control!$A$7,""&$H$25,H51),NA())} -> 897 | K51: {=SUM(Data!$D$2:$F$367*(--(Data!$A$2:$A$367=DATE(Processing!$C$1,Processing!$E$1,Processing!H51))))} -> 1039 | L51: =IF(ISNA(I51),0,H51) -> 26 | M51: =H51 -> 26 | N51: {=IF(ISNA(I51),NA(),SUM(Data!$AY$2:$AY$367*(--(Data!$A$2:$A$367=DATE(Processing!$C$1,Processing!$E$1,Processing!H51)))))} -> 89632.88 | O51: {=INDEX(Data!$AY$2:$AY$367,MATCH(TRUE,Data!$AY$2:$AY$367>0,0))} -> 117000 | P51: {=IFERROR(IF(NOT(ISNA(I51)),NA(),SUM(Data!$AY$2:$AY$367*(--(Data!$A$2:$A$367=DATE(Processing!$C$1,Processing!$E$1,Processing!H51))))),NA())} -> #N/A | Q51: =H51 -> 26 | R51: {=IF(ISNA(I51),NA(),SUM(Data!$BE$2:$BH$367*(--(Data!$A$2:$A$367=DATE(Processing!$C$1,Processing!$E$1,Processing!H51)))))} -> 66942 | S51: =(R51>0)*$C$28 -> 36058 | T51: {=ISNUMBER(Q51)*SUM(Data!$BE$2:$BH$367*(--(Data!$A$2:$A$367=DATE(Processing!$C$1,Processing!$E$1,Processing!H51))))} -> 66942 | V51: 44252 | W51: 29143 | X51: 24054 | Y51: 5985 | Z51: =SUM(V51:Y51) -> 103434 | AA51: =Z51/Z38 -> 0.82090476 | AB51: =Z51/AA51 -> 126000 | AG51: =H51 -> 26 | AH51: {=IF(ISNA(I51),NA(),SUM(Data!$J$2:$S$367*(--(Data!$A$2:$A$367=DATE(Processing!$C$1,Processing!$E$1,Processing!H51)))))} -> 1039 | AI51: {=IF(ISNA(I51),NA(),SUM(Data!$O$2:$S$367*(--(Data!$A$2:$A$367=DATE(Processing!$C$1,Processing!$E$1,Processing!H51)))))} -> 501 | AJ51: {=SUM(Data!$J$2:$S$367*(--(Data!$A$2:$A$367=DATE(Processing!$C$1,Processing!$E$1,Processing!H51))))} -> 1039 | AL51: =H51 -> 26 | AM51: {=IF(ISNA(I51),NA(),SUM(Data!$T$2:$AX$367*(--(Data!$A$2:$A$367=DATE(Processing!$C$1,Processing!$E$1,Processing!H51)))))} -> 897 | AN51: {=IF(ISNA(I51),NA(),SUM(Data!$AP$2:$AX$367*(--(Data!$A$2:$A$367=DATE(Processing!$C$1,Processing!$E$1,Processing!H51)))))} -> 227 | AO51: {=SUM(Data!$T$2:$AX$367*(--(Data!$A$2:$A$367=DATE(Processing!$C$1,Processing!$E$1,Processing!H51))))} -> 897
A52: =B44&"-"&B52 -> 13488-1 | B52: =COUNTIF($B$44:B44,B44) -> 1 | C52: 1 | D52: =INDEX($A$44:$A$48,MATCH(IF(E52=E51,E52&"-"&COUNTIF($E$52:E52,E52),E52&"-1"),$A$52:$A$56,0)) -> Business | E52: =LARGE($B$44:$B$48,C52) -> 13488 | G52: ="Investments "&D52 -> Investments Business | H52: 27 | I52: {=IFERROR(GETPIVOTDATA(""&$N$2,Control!$A$7,""&$H$25,H52)+GETPIVOTDATA(""&$N$3,Control!$A$7,""&$H$25,H52)+GETPIVOTDATA(""&$N$4,Control!$A$7,""&$H$25,H52),NA())} -> 1022 | J52: {=IFERROR(GETPIVOTDATA(""&$N$5,Control!$A$7,""&$H$25,H52)+GETPIVOTDATA(""&$N$6,Control!$A$7,""&$H$25,H52)+GETPIVOTDATA(""&$N$7,Control!$A$7,""&$H$25,H52),NA())} -> 882 | K52: {=SUM(Data!$D$2:$F$367*(--(Data!$A$2:$A$367=DATE(Processing!$C$1,Processing!$E$1,Processing!H52))))} -> 1022 | L52: =IF(ISNA(I52),0,H52) -> 27 | M52: =H52 -> 27 | N52: {=IF(ISNA(I52),NA(),SUM(Data!$AY$2:$AY$367*(--(Data!$A$2:$A$367=DATE(Processing!$C$1,Processing!$E$1,Processing!H52)))))} -> 88936.97 | O52: {=INDEX(Data!$AY$2:$AY$367,MATCH(TRUE,Data!$AY$2:$AY$367>0,0))} -> 117000 | P52: {=IFERROR(IF(NOT(ISNA(I52)),NA(),SUM(Data!$AY$2:$AY$367*(--(Data!$A$2:$A$367=DATE(Processing!$C$1,Processing!$E$1,Processing!H52))))),NA())} -> #N/A | Q52: =H52 -> 27 | R52: {=IF(ISNA(I52),NA(),SUM(Data!$BE$2:$BH$367*(--(Data!$A$2:$A$367=DATE(Processing!$C$1,Processing!$E$1,Processing!H52)))))} -> 66942 | S52: =(R52>0)*$C$28 -> 36058 | T52: {=ISNUMBER(Q52)*SUM(Data!$BE$2:$BH$367*(--(Data!$A$2:$A$367=DATE(Processing!$C$1,Processing!$E$1,Processing!H52))))} -> 66942 | V52: 47108 | W52: 32976 | X52: 28051 | Y52: 7852 | Z52: =SUM(V52:Y52) -> 115987 | AA52: =Z52/Z39 -> 0.87208271 | AB52: =Z52/AA52 -> 133000 | AG52: =H52 -> 27 | AH52: {=IF(ISNA(I52),NA(),SUM(Data!$J$2:$S$367*(--(Data!$A$2:$A$367=DATE(Processing!$C$1,Processing!$E$1,Processing!H52)))))} -> 1022 | AI52: {=IF(ISNA(I52),NA(),SUM(Data!$O$2:$S$367*(--(Data!$A$2:$A$367=DATE(Processing!$C$1,Processing!$E$1,Processing!H52)))))} -> 441 | AJ52: {=SUM(Data!$J$2:$S$367*(--(Data!$A$2:$A$367=DATE(Processing!$C$1,Processing!$E$1,Processing!H52))))} -> 1022 | AL52: =H52 -> 27 | AM52: {=IF(ISNA(I52),NA(),SUM(Data!$T$2:$AX$367*(--(Data!$A$2:$A$367=DATE(Processing!$C$1,Processing!$E$1,Processing!H52)))))} -> 882 | AN52: {=IF(ISNA(I52),NA(),SUM(Data!$AP$2:$AX$367*(--(Data!$A$2:$A$367=DATE(Processing!$C$1,Processing!$E$1,Processing!H52)))))} -> 288 | AO52: {=SUM(Data!$T$2:$AX$367*(--(Data!$A$2:$A$367=DATE(Processing!$C$1,Processing!$E$1,Processing!H52))))} -> 882
A53: =B45&"-"&B53 -> 6274-1 | B53: =COUNTIF($B$44:B45,B45) -> 1 | C53: 2 | D53: =INDEX($A$44:$A$48,MATCH(IF(E53=E52,E53&"-"&COUNTIF($E$52:E53,E53),E53&"-1"),$A$52:$A$56,0)) -> Securities | E53: =LARGE($B$44:$B$48,C53) -> 6274 | G53: ="Investments "&D53 -> Investments Securities | H53: 28 | I53: {=IFERROR(GETPIVOTDATA(""&$N$2,Control!$A$7,""&$H$25,H53)+GETPIVOTDATA(""&$N$3,Control!$A$7,""&$H$25,H53)+GETPIVOTDATA(""&$N$4,Control!$A$7,""&$H$25,H53),NA())} -> 1000 | J53: {=IFERROR(GETPIVOTDATA(""&$N$5,Control!$A$7,""&$H$25,H53)+GETPIVOTDATA(""&$N$6,Control!$A$7,""&$H$25,H53)+GETPIVOTDATA(""&$N$7,Control!$A$7,""&$H$25,H53),NA())} -> 863 | K53: {=SUM(Data!$D$2:$F$367*(--(Data!$A$2:$A$367=DATE(Processing!$C$1,Processing!$E$1,Processing!H53))))} -> 1000 | L53: =IF(ISNA(I53),0,H53) -> 28 | M53: =H53 -> 28 | N53: {=IF(ISNA(I53),NA(),SUM(Data!$AY$2:$AY$367*(--(Data!$A$2:$A$367=DATE(Processing!$C$1,Processing!$E$1,Processing!H53)))))} -> 88544.83 | O53: {=INDEX(Data!$AY$2:$AY$367,MATCH(TRUE,Data!$AY$2:$AY$367>0,0))} -> 117000 | P53: {=IFERROR(IF(NOT(ISNA(I53)),NA(),SUM(Data!$AY$2:$AY$367*(--(Data!$A$2:$A$367=DATE(Processing!$C$1,Processing!$E$1,Processing!H53))))),NA())} -> #N/A | Q53: =H53 -> 28 | R53: {=IF(ISNA(I53),NA(),SUM(Data!$BE$2:$BH$367*(--(Data!$A$2:$A$367=DATE(Processing!$C$1,Processing!$E$1,Processing!H53)))))} -> 66942 | S53: =(R53>0)*$C$28 -> 36058 | T53: {=ISNUMBER(Q53)*SUM(Data!$BE$2:$BH$367*(--(Data!$A$2:$A$367=DATE(Processing!$C$1,Processing!$E$1,Processing!H53))))} -> 66942 | V53: 51993 | W53: 33859 | X53: 34311 | Y53: 9942 | Z53: =SUM(V53:Y53) -> 130105 | AA53: =Z53/Z40 -> 0.87908784 | AB53: =Z53/AA53 -> 148000 | AG53: =H53 -> 28 | AH53: {=IF(ISNA(I53),NA(),SUM(Data!$J$2:$S$367*(--(Data!$A$2:$A$367=DATE(Processing!$C$1,Processing!$E$1,Processing!H53)))))} -> 1000 | AI53: {=IF(ISNA(I53),NA(),SUM(Data!$O$2:$S$367*(--(Data!$A$2:$A$367=DATE(Processing!$C$1,Processing!$E$1,Processing!H53)))))} -> 388 | AJ53: {=SUM(Data!$J$2:$S$367*(--(Data!$A$2:$A$367=DATE(Processing!$C$1,Processing!$E$1,Processing!H53))))} -> 1000 | AL53: =H53 -> 28 | AM53: {=IF(ISNA(I53),NA(),SUM(Data!$T$2:$AX$367*(--(Data!$A$2:$A$367=DATE(Processing!$C$1,Processing!$E$1,Processing!H53)))))} -> 863 | AN53: {=IF(ISNA(I53),NA(),SUM(Data!$AP$2:$AX$367*(--(Data!$A$2:$A$367=DATE(Processing!$C$1,Processing!$E$1,Processing!H53)))))} -> 220 | AO53: {=SUM(Data!$T$2:$AX$367*(--(Data!$A$2:$A$367=DATE(Processing!$C$1,Processing!$E$1,Processing!H53))))} -> 863
A54: =B46&"-"&B54 -> 3187-1 | B54: =COUNTIF($B$44:B46,B46) -> 1 | C54: 3 | D54: =INDEX($A$44:$A$48,MATCH(IF(E54=E53,E54&"-"&COUNTIF($E$52:E54,E54),E54&"-1"),$A$52:$A$56,0)) -> Cryptocurrency | E54: =LARGE($B$44:$B$48,C54) -> 4856 | G54: ="Investments "&D54 -> Investments Cryptocurrency | H54: {=IF(INDEX($G$26:$G$37,$E$1)>=29,29,"")} -> 29 | I54: {=IFERROR(GETPIVOTDATA(""&$N$2,Control!$A$7,""&$H$25,H54)+GETPIVOTDATA(""&$N$3,Control!$A$7,""&$H$25,H54)+GETPIVOTDATA(""&$N$4,Control!$A$7,""&$H$25,H54),NA())} -> 973 | J54: {=IFERROR(GETPIVOTDATA(""&$N$5,Control!$A$7,""&$H$25,H54)+GETPIVOTDATA(""&$N$6,Control!$A$7,""&$H$25,H54)+GETPIVOTDATA(""&$N$7,Control!$A$7,""&$H$25,H54),NA())} -> 837 | K54: {=SUM(Data!$D$2:$F$367*(--(Data!$A$2:$A$367=DATE(Processing!$C$1,Processing!$E$1,Processing!H54))))} -> 973 | L54: =IF(ISNA(I54),0,H54) -> 29 | M54: =H54 -> 29 | N54: {=IF(ISNA(I54),NA(),SUM(Data!$AY$2:$AY$367*(--(Data!$A$2:$A$367=DATE(Processing!$C$1,Processing!$E$1,Processing!H54)))))} -> 88447.57 | O54: {=ISNUMBER(M54)*INDEX(Data!$AY$2:$AY$367,MATCH(TRUE,Data!$AY$2:$AY$367>0,0))} -> 117000 | P54: {=IFERROR(IF(NOT(ISNA(I54)),NA(),SUM(Data!$AY$2:$AY$367*(--(Data!$A$2:$A$367=DATE(Processing!$C$1,Processing!$E$1,Processing!H54))))),NA())} -> #N/A | Q54: =H54 -> 29 | R54: {=IF(ISNA(I54),NA(),SUM(Data!$BE$2:$BH$367*(--(Data!$A$2:$A$367=DATE(Processing!$C$1,Processing!$E$1,Processing!H54)))))} -> 66942 | S54: =(R54>0)*$C$28 -> 36058 | T54: {=ISNUMBER(Q54)*SUM(Data!$BE$2:$BH$367*(--(Data!$A$2:$A$367=DATE(Processing!$C$1,Processing!$E$1,Processing!H54))))} -> 66942 | V54: 62350 | W54: 36275 | X54: 36337 | Y54: 14333 | Z54: =SUM(V54:Y54) -> 149295 | AA54: =Z54/Z41 -> 0.79836898 | AB54: =Z54/AA54 -> 187000 | AG54: =H54 -> 29 | AH54: {=IF(ISNA(I54),NA(),SUM(Data!$J$2:$S$367*(--(Data!$A$2:$A$367=DATE(Processing!$C$1,Processing!$E$1,Processing!H54)))))} -> 973 | AI54: {=IF(ISNA(I54),NA(),SUM(Data!$O$2:$S$367*(--(Data!$A$2:$A$367=DATE(Processing!$C$1,Processing!$E$1,Processing!H54)))))} -> 360 | AJ54: {=SUM(Data!$J$2:$S$367*(--(Data!$A$2:$A$367=DATE(Processing!$C$1,Processing!$E$1,Processing!H54))))} -> 973 | AL54: =H54 -> 29 | AM54: {=IF(ISNA(I54),NA(),SUM(Data!$T$2:$AX$367*(--(Data!$A$2:$A$367=DATE(Processing!$C$1,Processing!$E$1,Processing!H54)))))} -> 837 | AN54: {=IF(ISNA(I54),NA(),SUM(Data!$AP$2:$AX$367*(--(Data!$A$2:$A$367=DATE(Processing!$C$1,Processing!$E$1,Processing!H54)))))} -> 259 | AO54: {=SUM(Data!$T$2:$AX$367*(--(Data!$A$2:$A$367=DATE(Processing!$C$1,Processing!$E$1,Processing!H54))))} -> 837
A55: =B47&"-"&B55 -> 3406-1 | B55: =COUNTIF($B$44:B47,B47) -> 1 | C55: 4 | D55: =INDEX($A$44:$A$48,MATCH(IF(E55=E54,E55&"-"&COUNTIF($E$52:E55,E55),E55&"-1"),$A$52:$A$56,0)) -> Real estate | E55: =LARGE($B$44:$B$48,C55) -> 3406 | G55: ="Investments "&D55 -> Investments Real estate | H55: {=IF(INDEX($G$26:$G$37,$E$1)>=30,30,"")} -> 30 | I55: {=IFERROR(GETPIVOTDATA(""&$N$2,Control!$A$7,""&$H$25,H55)+GETPIVOTDATA(""&$N$3,Control!$A$7,""&$H$25,H55)+GETPIVOTDATA(""&$N$4,Control!$A$7,""&$H$25,H55),NA())} -> 951 | J55: {=IFERROR(GETPIVOTDATA(""&$N$5,Control!$A$7,""&$H$25,H55)+GETPIVOTDATA(""&$N$6,Control!$A$7,""&$H$25,H55)+GETPIVOTDATA(""&$N$7,Control!$A$7,""&$H$25,H55),NA())} -> 809 | K55: {=SUM(Data!$D$2:$F$367*(--(Data!$A$2:$A$367=DATE(Processing!$C$1,Processing!$E$1,Processing!H55))))} -> 951 | L55: =IF(ISNA(I55),0,H55) -> 30 | M55: =H55 -> 30 | N55: {=IF(ISNA(I55),NA(),SUM(Data!$AY$2:$AY$367*(--(Data!$A$2:$A$367=DATE(Processing!$C$1,Processing!$E$1,Processing!H55)))))} -> 89000 | O55: {=ISNUMBER(M55)*INDEX(Data!$AY$2:$AY$367,MATCH(TRUE,Data!$AY$2:$AY$367>0,0))} -> 117000 | P55: {=IFERROR(IF(NOT(ISNA(I55)),NA(),SUM(Data!$AY$2:$AY$367*(--(Data!$A$2:$A$367=DATE(Processing!$C$1,Processing!$E$1,Processing!H55))))),NA())} -> #N/A | Q55: =H55 -> 30 | R55: {=IF(ISNA(I55),NA(),SUM(Data!$BE$2:$BH$367*(--(Data!$A$2:$A$367=DATE(Processing!$C$1,Processing!$E$1,Processing!H55)))))} -> 66942 | S55: =(R55>0)*$C$28 -> 36058 | T55: {=ISNUMBER(Q55)*SUM(Data!$BE$2:$BH$367*(--(Data!$A$2:$A$367=DATE(Processing!$C$1,Processing!$E$1,Processing!H55))))} -> 66942 | V55: 65416 | W55: 39140 | X55: 38021 | Y55: 15056 | Z55: =SUM(V55:Y55) -> 157633 | AA55: =Z55/Z42 -> 0.80837436 | AB55: =Z55/AA55 -> 195000 | AG55: =H55 -> 30 | AH55: {=IF(ISNA(I55),NA(),SUM(Data!$J$2:$S$367*(--(Data!$A$2:$A$367=DATE(Processing!$C$1,Processing!$E$1,Processing!H55)))))} -> 951 | AI55: {=IF(ISNA(I55),NA(),SUM(Data!$O$2:$S$367*(--(Data!$A$2:$A$367=DATE(Processing!$C$1,Processing!$E$1,Processing!H55)))))} -> 435 | AJ55: {=SUM(Data!$J$2:$S$367*(--(Data!$A$2:$A$367=DATE(Processing!$C$1,Processing!$E$1,Processing!H55))))} -> 951 | AL55: =H55 -> 30 | AM55: {=IF(ISNA(I55),NA(),SUM(Data!$T$2:$AX$367*(--(Data!$A$2:$A$367=DATE(Processing!$C$1,Processing!$E$1,Processing!H55)))))} -> 809 | AN55: {=IF(ISNA(I55),NA(),SUM(Data!$AP$2:$AX$367*(--(Data!$A$2:$A$367=DATE(Processing!$C$1,Processing!$E$1,Processing!H55)))))} -> 248 | AO55: {=SUM(Data!$T$2:$AX$367*(--(Data!$A$2:$A$367=DATE(Processing!$C$1,Processing!$E$1,Processing!H55))))} -> 809
A56: =B48&"-"&B56 -> 4856-1 | B56: =COUNTIF($B$44:B48,B48) -> 1 | C56: 5 | D56: =INDEX($A$44:$A$48,MATCH(IF(E56=E55,E56&"-"&COUNTIF($E$52:E56,E56),E56&"-1"),$A$52:$A$56,0)) -> Gold | E56: =LARGE($B$44:$B$48,C56) -> 3187 | G56: ="Investments "&D56 -> Investments Gold | H56: {=IF(INDEX($G$26:$G$37,$E$1)=31,31,"")} | I56: {=IFERROR(GETPIVOTDATA(""&$N$2,Control!$A$7,""&$H$25,H56)+GETPIVOTDATA(""&$N$3,Control!$A$7,""&$H$25,H56)+GETPIVOTDATA(""&$N$4,Control!$A$7,""&$H$25,H56),NA())} -> #N/A | J56: {=IFERROR(GETPIVOTDATA(""&$N$5,Control!$A$7,""&$H$25,H56)+GETPIVOTDATA(""&$N$6,Control!$A$7,""&$H$25,H56)+GETPIVOTDATA(""&$N$7,Control!$A$7,""&$H$25,H56),NA())} -> #N/A | K56: {=SUM(Data!$D$2:$F$367*(--(Data!$A$2:$A$367=DATE(Processing!$C$1,Processing!$E$1,Processing!H56))))} -> #VALUE! | L56: =IF(ISNA(I56),0,H56) -> 0 | M56: =H56 | N56: {=IF(ISNA(I56),NA(),SUM(Data!$AY$2:$AY$367*(--(Data!$A$2:$A$367=DATE(Processing!$C$1,Processing!$E$1,Processing!H56)))))} -> #N/A | O56: {=ISNUMBER(M56)*INDEX(Data!$AY$2:$AY$367,MATCH(TRUE,Data!$AY$2:$AY$367>0,0))} -> 0 | P56: {=IFERROR(IF(NOT(ISNA(I56)),NA(),SUM(Data!$AY$2:$AY$367*(--(Data!$A$2:$A$367=DATE(Processing!$C$1,Processing!$E$1,Processing!H56))))),NA())} -> #N/A | Q56: =H56 | R56: {=IF(ISNA(I56),NA(),SUM(Data!$BE$2:$BH$367*(--(Data!$A$2:$A$367=DATE(Processing!$C$1,Processing!$E$1,Processing!H56)))))} -> #N/A | S56: =(R56>0)*$C$28 -> #N/A | T56: {=ISNUMBER(Q56)*SUM(Data!$BE$2:$BH$367*(--(Data!$A$2:$A$367=DATE(Processing!$C$1,Processing!$E$1,Processing!H56))))} -> #VALUE! | V56: 71506 | W56: 41680 | X56: 44466 | Y56: 20037 | Z56: =SUM(V56:Y56) -> 177689 | AA56: =Z56/Z43 -> 0.87102451 | AB56: =Z56/AA56 -> 204000 | AG56: =H56 | AH56: {=IF(ISNA(I56),NA(),SUM(Data!$J$2:$S$367*(--(Data!$A$2:$A$367=DATE(Processing!$C$1,Processing!$E$1,Processing!H56)))))} -> #N/A | AI56: {=IF(ISNA(I56),NA(),SUM(Data!$O$2:$S$367*(--(Data!$A$2:$A$367=DATE(Processing!$C$1,Processing!$E$1,Processing!H56)))))} -> #N/A | AJ56: {=SUM(Data!$J$2:$S$367*(--(Data!$A$2:$A$367=DATE(Processing!$C$1,Processing!$E$1,Processing!H56))))} -> #VALUE! | AL56: =H56 | AM56: {=IF(ISNA(I56),NA(),SUM(Data!$T$2:$AX$367*(--(Data!$A$2:$A$367=DATE(Processing!$C$1,Processing!$E$1,Processing!H56)))))} -> #N/A | AN56: {=IF(ISNA(I56),NA(),SUM(Data!$AP$2:$AX$367*(--(Data!$A$2:$A$367=DATE(Processing!$C$1,Processing!$E$1,Processing!H56)))))} -> #N/A | AO56: {=SUM(Data!$T$2:$AX$367*(--(Data!$A$2:$A$367=DATE(Processing!$C$1,Processing!$E$1,Processing!H56))))} -> #VALUE!
H57: Total | I57: =_xlfn.AGGREGATE(9,2,I26:I56) -> 31211 | J57: =_xlfn.AGGREGATE(9,2,J26:J56) -> 24837 | V57: 75121 | W57: 53018 | X57: 57002 | Y57: 31955 | Z57: =SUM(V57:Y57) -> 217096 | AA57: =Z57/Z44 -> 0.94389565 | AB57: =Z57/AA57 -> 230000
H58: Ratio Budget | I58: =1-J57/I57 -> 0.20422287 | J58: =1-I58 -> 0.79577713 | K58: Lable
I59: =IF(I58>0,I58,0) -> 0.20422287 | J59: =1-I59 -> 0.79577713 | AA59: 42350 | AB59: 24624.6 | AC59: 9286.2 | AD59: 2340.8
I60: =IF(I58>1,I58-1,) -> 0 | J60: =1-I60 -> 1
A62: Expenses | B62: Non-Fixed Cost | F62: Id | G62: COUNTIF | H62: Number | I62: Cost Ranking | J62: Cost
A63: Rest | B63: Holidays | C63: =GETPIVOTDATA(""&B63,Control!$A$7) -> 2082 | F63: =C63&"-"&G63 -> 2082-1 | G63: =COUNTIF($C$63:C63,C63) -> 1 | H63: 1 | I63: =INDEX($B$63:$B$95,MATCH(IF(J63=J62,J63&"-"&COUNTIF($J$63:J63,J63),J63&"-1"),$F$63:$F$95,0)) -> Loans | J63: =LARGE($C$63:$C$95,H63) -> 2268
B64: Excursions | C64: =GETPIVOTDATA(""&B64,Control!$A$7) -> 397 | F64: =C64&"-"&G64 -> 397-1 | G64: =COUNTIF($C$63:C64,C64) -> 1 | H64: 2 | I64: =INDEX($B$63:$B$95,MATCH(IF(J64=J63,J64&"-"&COUNTIF($J$63:J64,J64),J64&"-1"),$F$63:$F$95,0)) -> Food | J64: =LARGE($C$63:$C$95,H64) -> 2243
B65: Restaurants | C65: =GETPIVOTDATA(""&B65,Control!$A$7) -> 1521 | F65: =C65&"-"&G65 -> 1521-1 | G65: =COUNTIF($C$63:C65,C65) -> 1 | H65: 3 | I65: =INDEX($B$63:$B$95,MATCH(IF(J65=J64,J65&"-"&COUNTIF($J$63:J65,J65),J65&"-1"),$F$63:$F$95,0)) -> Holidays | J65: =LARGE($C$63:$C$95,H65) -> 2082
B66: Gotheli | C66: =GETPIVOTDATA(""&B66,Control!$A$7) -> 677 | F66: =C66&"-"&G66 -> 677-1 | G66: =COUNTIF($C$63:C66,C66) -> 1 | H66: 4 | I66: =INDEX($B$63:$B$95,MATCH(IF(J66=J65,J66&"-"&COUNTIF($J$63:J66,J66),J66&"-1"),$F$63:$F$95,0)) -> Utility Payments | J66: =LARGE($C$63:$C$95,H66) -> 1674
B67: Bags, packages, boxes | C67: =GETPIVOTDATA(""&B67,Control!$A$7) -> 113 | F67: =C67&"-"&G67 -> 113-1 | G67: =COUNTIF($C$63:C67,C67) -> 1 | H67: 5 | I67: =INDEX($B$63:$B$95,MATCH(IF(J67=J66,J67&"-"&COUNTIF($J$63:J67,J67),J67&"-1"),$F$63:$F$95,0)) -> Hairdresser | J67: =LARGE($C$63:$C$95,H67) -> 1579
B68: Snacks on the way | C68: =GETPIVOTDATA(""&B68,Control!$A$7) -> 1017 | F68: =C68&"-"&G68 -> 1017-1 | G68: =COUNTIF($C$63:C68,C68) -> 1 | H68: 6 | I68: =INDEX($B$63:$B$95,MATCH(IF(J68=J67,J68&"-"&COUNTIF($J$63:J68,J68),J68&"-1"),$F$63:$F$95,0)) -> Restaurants | J68: =LARGE($C$63:$C$95,H68) -> 1521
B69: Alcohol | C69: =GETPIVOTDATA(""&B69,Control!$A$7) -> 559 | F69: =C69&"-"&G69 -> 559-1 | G69: =COUNTIF($C$63:C69,C69) -> 1 | H69: 7 | I69: =INDEX($B$63:$B$95,MATCH(IF(J69=J68,J69&"-"&COUNTIF($J$63:J69,J69),J69&"-1"),$F$63:$F$95,0)) -> Travel public transport | J69: =LARGE($C$63:$C$95,H69) -> 1318
A70: Other | B70: Hobby | C70: =GETPIVOTDATA(""&B70,Control!$A$7) -> 564 | F70: =C70&"-"&G70 -> 564-1 | G70: =COUNTIF($C$63:C70,C70) -> 1 | H70: 8 | I70: =INDEX($B$63:$B$95,MATCH(IF(J70=J69,J70&"-"&COUNTIF($J$63:J70,J70),J70&"-1"),$F$63:$F$95,0)) -> Unexpected expenses | J70: =LARGE($C$63:$C$95,H70) -> 1134
B71: Unexpected expenses | C71: =GETPIVOTDATA(""&B71,Control!$A$7) -> 1134 | F71: =C71&"-"&G71 -> 1134-1 | G71: =COUNTIF($C$63:C71,C71) -> 1 | H71: 9 | I71: =INDEX($B$63:$B$95,MATCH(IF(J71=J70,J71&"-"&COUNTIF($J$63:J71,J71),J71&"-1"),$F$63:$F$95,0)) -> Snacks on the way | J71: =LARGE($C$63:$C$95,H71) -> 1017
F72: =C72&"-"&G72 -> -0 | G72: =COUNTIF($C$63:C72,C72) -> 0 | H72: 10 | I72: =INDEX($B$63:$B$95,MATCH(IF(J72=J71,J72&"-"&COUNTIF($J$63:J72,J72),J72&"-1"),$F$63:$F$95,0)) -> Cosmetics & perfum | J72: =LARGE($C$63:$C$95,H72) -> 930
B73: Fixed Costs | F73: =C73&"-"&G73 -> -0 | G73: =COUNTIF($C$63:C73,C73) -> 0 | H73: 11 | I73: =INDEX($B$63:$B$95,MATCH(IF(J73=J72,J73&"-"&COUNTIF($J$63:J73,J73),J73&"-1"),$F$63:$F$95,0)) -> Furniture & utensils | J73: =LARGE($C$63:$C$95,H73) -> 901
A74: Business | B74: Loans | C74: =GETPIVOTDATA(""&B74,Control!$A$7) -> 2268 | F74: =C74&"-"&G74 -> 2268-1 | G74: =COUNTIF($C$63:C74,C74) -> 1 | H74: 12 | I74: =INDEX($B$63:$B$95,MATCH(IF(J74=J73,J74&"-"&COUNTIF($J$63:J74,J74),J74&"-1"),$F$63:$F$95,0)) -> Clothing & footwear | J74: =LARGE($C$63:$C$95,H74) -> 767
B75: Training courses | C75: =GETPIVOTDATA(""&B75,Control!$A$7) -> 407 | F75: =C75&"-"&G75 -> 407-1 | G75: =COUNTIF($C$63:C75,C75) -> 1 | H75: 13 | I75: =INDEX($B$63:$B$95,MATCH(IF(J75=J74,J75&"-"&COUNTIF($J$63:J75,J75),J75&"-1"),$F$63:$F$95,0)) -> Fuel | J75: =LARGE($C$63:$C$95,H75) -> 736
B76: Travel public transport | C76: =GETPIVOTDATA(""&B76,Control!$A$7) -> 1318 | F76: =C76&"-"&G76 -> 1318-1 | G76: =COUNTIF($C$63:C76,C76) -> 1 | H76: 14 | I76: =INDEX($B$63:$B$95,MATCH(IF(J76=J75,J76&"-"&COUNTIF($J$63:J76,J76),J76&"-1"),$F$63:$F$95,0)) -> Gotheli | J76: =LARGE($C$63:$C$95,H76) -> 677
B77: Mobile connection | C77: =GETPIVOTDATA(""&B77,Control!$A$7) -> 362 | F77: =C77&"-"&G77 -> 362-1 | G77: =COUNTIF($C$63:C77,C77) -> 1 | H77: 15 | I77: =INDEX($B$63:$B$95,MATCH(IF(J77=J76,J77&"-"&COUNTIF($J$63:J77,J77),J77&"-1"),$F$63:$F$95,0)) -> Hobby | J77: =LARGE($C$63:$C$95,H77) -> 564
A78: Home | B78: Food | C78: =GETPIVOTDATA(""&B78,Control!$A$7) -> 2243 | F78: =C78&"-"&G78 -> 2243-1 | G78: =COUNTIF($C$63:C78,C78) -> 1 | H78: 16 | I78: =INDEX($B$63:$B$95,MATCH(IF(J78=J77,J78&"-"&COUNTIF($J$63:J78,J78),J78&"-1"),$F$63:$F$95,0)) -> Alcohol | J78: =LARGE($C$63:$C$95,H78) -> 559
B79: Utility Payments | C79: =GETPIVOTDATA(""&B79,Control!$A$7) -> 1674 | F79: =C79&"-"&G79 -> 1674-1 | G79: =COUNTIF($C$63:C79,C79) -> 1 | H79: 17 | I79: =INDEX($B$63:$B$95,MATCH(IF(J79=J78,J79&"-"&COUNTIF($J$63:J79,J79),J79&"-1"),$F$63:$F$95,0)) -> Insurance | J79: =LARGE($C$63:$C$95,H79) -> 557
B80: Internet & TV | C80: =GETPIVOTDATA(""&B80,Control!$A$7) -> 287 | F80: =C80&"-"&G80 -> 287-1 | G80: =COUNTIF($C$63:C80,C80) -> 1 | H80: 18 | I80: =INDEX($B$63:$B$95,MATCH(IF(J80=J79,J80&"-"&COUNTIF($J$63:J80,J80),J80&"-1"),$F$63:$F$95,0)) -> Washing | J80: =LARGE($C$63:$C$95,H80) -> 472
B81: Household chemicals | C81: =GETPIVOTDATA(""&B81,Control!$A$7) -> 291 | F81: =C81&"-"&G81 -> 291-1 | G81: =COUNTIF($C$63:C81,C81) -> 1 | H81: 19 | I81: =INDEX($B$63:$B$95,MATCH(IF(J81=J80,J81&"-"&COUNTIF($J$63:J81,J81),J81&"-1"),$F$63:$F$95,0)) -> Training courses | J81: =LARGE($C$63:$C$95,H81) -> 407
B82: Furniture & utensils | C82: =GETPIVOTDATA(""&B82,Control!$A$7) -> 901 | F82: =C82&"-"&G82 -> 901-1 | G82: =COUNTIF($C$63:C82,C82) -> 1 | H82: 20 | I82: =INDEX($B$63:$B$95,MATCH(IF(J82=J81,J82&"-"&COUNTIF($J$63:J82,J82),J82&"-1"),$F$63:$F$95,0)) -> Excursions | J82: =LARGE($C$63:$C$95,H82) -> 397
B83: BedLinen & tablecloth | C83: =GETPIVOTDATA(""&B83,Control!$A$7) -> 380 | F83: =C83&"-"&G83 -> 380-1 | G83: =COUNTIF($C$63:C83,C83) -> 1 | H83: 21 | I83: =INDEX($B$63:$B$95,MATCH(IF(J83=J82,J83&"-"&COUNTIF($J$63:J83,J83),J83&"-1"),$F$63:$F$95,0)) -> BedLinen & tablecloth | J83: =LARGE($C$63:$C$95,H83) -> 380
B84: Cat food | C84: =GETPIVOTDATA(""&B84,Control!$A$7) -> 99 | F84: =C84&"-"&G84 -> 99-1 | G84: =COUNTIF($C$63:C84,C84) -> 1 | H84: 22 | I84: =INDEX($B$63:$B$95,MATCH(IF(J84=J83,J84&"-"&COUNTIF($J$63:J84,J84),J84&"-1"),$F$63:$F$95,0)) -> Hygiene products | J84: =LARGE($C$63:$C$95,H84) -> 377
A85: Image | B85: Clothing & footwear | C85: =GETPIVOTDATA(""&B85,Control!$A$7) -> 767 | F85: =C85&"-"&G85 -> 767-1 | G85: =COUNTIF($C$63:C85,C85) -> 1 | H85: 23 | I85: =INDEX($B$63:$B$95,MATCH(IF(J85=J84,J85&"-"&COUNTIF($J$63:J85,J85),J85&"-1"),$F$63:$F$95,0)) -> Gym | J85: =LARGE($C$63:$C$95,H85) -> 370
B86: Gym | C86: =GETPIVOTDATA(""&B86,Control!$A$7) -> 370 | F86: =C86&"-"&G86 -> 370-1 | G86: =COUNTIF($C$63:C86,C86) -> 1 | H86: 24 | I86: =INDEX($B$63:$B$95,MATCH(IF(J86=J85,J86&"-"&COUNTIF($J$63:J86,J86),J86&"-1"),$F$63:$F$95,0)) -> Mobile connection | J86: =LARGE($C$63:$C$95,H86) -> 362
B87: Hygiene products | C87: =GETPIVOTDATA(""&B87,Control!$A$7) -> 377 | F87: =C87&"-"&G87 -> 377-1 | G87: =COUNTIF($C$63:C87,C87) -> 1 | H87: 25 | I87: =INDEX($B$63:$B$95,MATCH(IF(J87=J86,J87&"-"&COUNTIF($J$63:J87,J87),J87&"-1"),$F$63:$F$95,0)) -> Spare parts | J87: =LARGE($C$63:$C$95,H87) -> 356
B88: Medications | C88: =GETPIVOTDATA(""&B88,Control!$A$7) -> 289 | F88: =C88&"-"&G88 -> 289-1 | G88: =COUNTIF($C$63:C88,C88) -> 1 | H88: 26 | I88: =INDEX($B$63:$B$95,MATCH(IF(J88=J87,J88&"-"&COUNTIF($J$63:J88,J88),J88&"-1"),$F$63:$F$95,0)) -> Household chemicals | J88: =LARGE($C$63:$C$95,H88) -> 291
B89: Hairdresser | C89: =GETPIVOTDATA(""&B89,Control!$A$7) -> 1579 | F89: =C89&"-"&G89 -> 1579-1 | G89: =COUNTIF($C$63:C89,C89) -> 1 | H89: 27 | I89: =INDEX($B$63:$B$95,MATCH(IF(J89=J88,J89&"-"&COUNTIF($J$63:J89,J89),J89&"-1"),$F$63:$F$95,0)) -> Medications | J89: =LARGE($C$63:$C$95,H89) -> 289
B90: Cosmetics & perfum | C90: =GETPIVOTDATA(""&B90,Control!$A$7) -> 930 | F90: =C90&"-"&G90 -> 930-1 | G90: =COUNTIF($C$63:C90,C90) -> 1 | H90: 28 | I90: =INDEX($B$63:$B$95,MATCH(IF(J90=J89,J90&"-"&COUNTIF($J$63:J90,J90),J90&"-1"),$F$63:$F$95,0)) -> Internet & TV | J90: =LARGE($C$63:$C$95,H90) -> 287
A91: Car | B91: Fuel | C91: =GETPIVOTDATA(""&B91,Control!$A$7) -> 736 | F91: =C91&"-"&G91 -> 736-1 | G91: =COUNTIF($C$63:C91,C91) -> 1 | H91: 29 | I91: =INDEX($B$63:$B$95,MATCH(IF(J91=J90,J91&"-"&COUNTIF($J$63:J91,J91),J91&"-1"),$F$63:$F$95,0)) -> Bags, packages, boxes | J91: =LARGE($C$63:$C$95,H91) -> 113
B92: Spare parts | C92: =GETPIVOTDATA(""&B92,Control!$A$7) -> 356 | F92: =C92&"-"&G92 -> 356-1 | G92: =COUNTIF($C$63:C92,C92) -> 1 | H92: 30 | I92: =INDEX($B$63:$B$95,MATCH(IF(J92=J91,J92&"-"&COUNTIF($J$63:J92,J92),J92&"-1"),$F$63:$F$95,0)) -> Parking | J92: =LARGE($C$63:$C$95,H92) -> 110
B93: Parking | C93: =GETPIVOTDATA(""&B93,Control!$A$7) -> 110 | F93: =C93&"-"&G93 -> 110-1 | G93: =COUNTIF($C$63:C93,C93) -> 1 | H93: 31 | I93: =INDEX($B$63:$B$95,MATCH(IF(J93=J92,J93&"-"&COUNTIF($J$63:J93,J93),J93&"-1"),$F$63:$F$95,0)) -> Cat food | J93: =LARGE($C$63:$C$95,H93) -> 99
B94: Washing | C94: =GETPIVOTDATA(""&B94,Control!$A$7) -> 472 | F94: =C94&"-"&G94 -> 472-1 | G94: =COUNTIF($C$63:C94,C94) -> 1
B95: Insurance | C95: =GETPIVOTDATA(""&B95,Control!$A$7) -> 557 | F95: =C95&"-"&G95 -> 557-1 | G95: =COUNTIF($C$63:C95,C95) -> 1
A96: Ratio Costs
A97: Fixed Costs | B97: Non-Fixed Cost
A98: =SUM(C74:C95) -> 16773 | B98: =SUM(C63:C71) -> 8064
A99: =A98/(A98+B98) -> 0.67532311 | B99: =1-A99 -> 0.32467689
C100: {=IF(INDEX(B103:B114,$E$1)>0,INDEX(C103:C114,$E$1),"")}
A101: Investment Portfolio | B101: {=INDEX(B103:B114,$E$1)} -> -17000 | C101: {=IF(INDEX(B103:B114,$E$1)<0,INDEX(C103:C114,$E$1),"")} -> -16% | D101: {=INDEX(D103:D114,$E$1)} -> -23,9% | E101: {=INDEX(E103:E114,$E$1)} -> 89000
...

Sheet Structuring Data
A1: RowID | B1: Date | C1: Year | D1: Month | E1: Day | F1: Income | G1: Expenses | H1: Non-Fixed Incom | I1: Fixed Incom | J1: Other Income | K1: Non-Fixed Cost | L1: Fixed Costs | M1: Other Cost | N1: Fixed Incom Business | O1: Fixed Incom Securities | P1: Fixed Incom Real estate | Q1: Fixed Incom Gold | R1: Fixed Incom Cryptocurrency | S1: Non-Fixed Incom Business | T1: Non-Fixed Incom Securities | U1: Non-Fixed Incom Real estate | V1: Non-Fixed Incom Gold | W1: Non-Fixed Incom Cryptocurrency | X1: Loans | Y1: Training courses | Z1: Travel public transport | AA1: Mobile connection | AB1: Food | AC1: Utility Payments | AD1: Internet & TV | AE1: Household chemicals | AF1: Furniture & utensils | AG1: BedLinen & tablecloth | AH1: Cat food | AI1: Clothing & footwear | AJ1: Gym | AK1: Hygiene products | AL1: Medications | AM1: Hairdresser | AN1: Cosmetics & perfum | AO1: Fuel | AP1: Spare parts | AQ1: Parking | AR1: Washing | AS1: Insurance | AT1: Holidays | AU1: Excursions | AV1: Restaurants | AW1: Gotheli | AX1: Bags, packages, boxes | AY1: Snacks on the way | AZ1: Alcohol | BA1: Hobby | BB1: Unexpected expenses
A2: 367 | C2: 2024 | D2: JANUARY | E2: 0.01 | F2: {=INDEX(Data!B$2:B$368,$A2)} -> 0 | G2: {=INDEX(Data!C$2:C$368,$A2)} -> 0 | H2: {=INDEX(Data!D$2:D$368,$A2)} -> 0 | I2: {=INDEX(Data!E$2:E$368,$A2)} -> 0 | J2: {=INDEX(Data!F$2:F$368,$A2)} -> 0 | K2: {=INDEX(Data!G$2:G$368,$A2)} -> 0 | L2: {=INDEX(Data!H$2:H$368,$A2)} -> 0 | M2: {=INDEX(Data!I$2:I$368,$A2)} -> 0 | ... BB2: {=INDEX(Data!AX$2:AX$368,$A2)} -> 0
A3: 1 | B3: 45292 | C3: 2024 | D3: JANUARY | E3: 1 | F3: {=INDEX(Data!B$2:B$368,$A3)} -> 496 | G3: {=INDEX(Data!C$2:C$368,$A3)} -> 575 | H3: {=INDEX(Data!D$2:D$368,$A3)} -> 243 | I3: {=INDEX(Data!E$2:E$368,$A3)} -> 189 | J3: {=INDEX(Data!F$2:F$368,$A3)} -> 64 | K3: {=INDEX(Data!G$2:G$368,$A3)} -> 172 | L3: {=INDEX(Data!H$2:H$368,$A3)} -> 271 | M3: {=INDEX(Data!I$2:I$368,$A3)} -> 132 | ... BB3: {=INDEX(Data!AX$2:AX$368,$A3)} -> 114
A4: 2 | B4: 45293 | C4: 2024 | D4: JANUARY | E4: 2 | F4: {=INDEX(Data!B$2:B$368,$A4)} -> 516 | G4: {=INDEX(Data!C$2:C$368,$A4)} -> 585 | H4: {=INDEX(Data!D$2:D$368,$A4)} -> 268 | I4: {=INDEX(Data!E$2:E$368,$A4)} -> 218 | J4: {=INDEX(Data!F$2:F$368,$A4)} -> 30 | K4: {=INDEX(Data!G$2:G$368,$A4)} -> 286 | L4: {=INDEX(Data!H$2:H$368,$A4)} -> 259 | M4: {=INDEX(Data!I$2:I$368,$A4)} -> 40 | ... BB4: {=INDEX(Data!AX$2:AX$368,$A4)} -> 2
A5: 3 | B5: 45294 | C5: 2024 | D5: JANUARY | E5: 3 | F5: {=INDEX(Data!B$2:B$368,$A5)} -> 539 | G5: {=INDEX(Data!C$2:C$368,$A5)} -> 610 | H5: {=INDEX(Data!D$2:D$368,$A5)} -> 285 | I5: {=INDEX(Data!E$2:E$368,$A5)} -> 131 | J5: {=INDEX(Data!F$2:F$368,$A5)} -> 123 | K5: {=INDEX(Data!G$2:G$368,$A5)} -> 244 | L5: {=INDEX(Data!H$2:H$368,$A5)} -> 318 | M5: {=INDEX(Data!I$2:I$368,$A5)} -> 48 | ... BB5: {=INDEX(Data!AX$2:AX$368,$A5)} -> 0
A6: 4 | B6: 45295 | C6: 2024 | D6: JANUARY | E6: 4 | F6: {=INDEX(Data!B$2:B$368,$A6)} -> 557 | G6: {=INDEX(Data!C$2:C$368,$A6)} -> 641 | H6: {=INDEX(Data!D$2:D$368,$A6)} -> 150 | I6: {=INDEX(Data!E$2:E$368,$A6)} -> 307 | J6: {=INDEX(Data!F$2:F$368,$A6)} -> 100 | K6: {=INDEX(Data!G$2:G$368,$A6)} -> 262 | L6: {=INDEX(Data!H$2:H$368,$A6)} -> 219 | M6: {=INDEX(Data!I$2:I$368,$A6)} -> 160 | ... BB6: {=INDEX(Data!AX$2:AX$368,$A6)} -> 12
A7: 5 | B7: 45296 | C7: 2024 | D7: JANUARY | E7: 5 | F7: {=INDEX(Data!B$2:B$368,$A7)} -> 575 | G7: {=INDEX(Data!C$2:C$368,$A7)} -> 667 | H7: {=INDEX(Data!D$2:D$368,$A7)} -> 132 | I7: {=INDEX(Data!E$2:E$368,$A7)} -> 415 | J7: {=INDEX(Data!F$2:F$368,$A7)} -> 28 | K7: {=INDEX(Data!G$2:G$368,$A7)} -> 153 | L7: {=INDEX(Data!H$2:H$368,$A7)} -> 374 | M7: {=INDEX(Data!I$2:I$368,$A7)} -> 140 | ... BB7: {=INDEX(Data!AX$2:AX$368,$A7)} -> 27
A8: 6 | B8: 45297 | C8: 2024 | D8: JANUARY | E8: 6 | F8: {=INDEX(Data!B$2:B$368,$A8)} -> 586 | G8: {=INDEX(Data!C$2:C$368,$A8)} -> 685 | H8: {=INDEX(Data!D$2:D$368,$A8)} -> 175 | I8: {=INDEX(Data!E$2:E$368,$A8)} -> 335 | J8: {=INDEX(Data!F$2:F$368,$A8)} -> 76 | K8: {=INDEX(Data!G$2:G$368,$A8)} -> 212 | L8: {=INDEX(Data!H$2:H$368,$A8)} -> 336 | M8: {=INDEX(Data!I$2:I$368,$A8)} -> 137 | ... BB8: {=INDEX(Data!AX$2:AX$368,$A8)} -> 0
A9: 7 | B9: 45298 | C9: 2024 | D9: JANUARY | E9: 7 | F9: {=INDEX(Data!B$2:B$368,$A9)} -> 597 | G9: {=INDEX(Data!C$2:C$368,$A9)} -> 690 | H9: {=INDEX(Data!D$2:D$368,$A9)} -> 310 | I9: {=INDEX(Data!E$2:E$368,$A9)} -> 162 | J9: {=INDEX(Data!F$2:F$368,$A9)} -> 125 | K9: {=INDEX(Data!G$2:G$368,$A9)} -> 282 | L9: {=INDEX(Data!H$2:H$368,$A9)} -> 353 | M9: {=INDEX(Data!I$2:I$368,$A9)} -> 55 | ... BB9: {=INDEX(Data!AX$2:AX$368,$A9)} -> 120
A10: 8 | B10: 45299 | C10: 2024 | D10: JANUARY | E10: 8 | F10: {=INDEX(Data!B$2:B$368,$A10)} -> 604 | G10: {=INDEX(Data!C$2:C$368,$A10)} -> 684 | H10: {=INDEX(Data!D$2:D$368,$A10)} -> 217 | I10: {=INDEX(Data!E$2:E$368,$A10)} -> 273 | J10: {=INDEX(Data!F$2:F$368,$A10)} -> 114 | K10: {=INDEX(Data!G$2:G$368,$A10)} -> 307 | L10: {=INDEX(Data!H$2:H$368,$A10)} -> 316 | M10: {=INDEX(Data!I$2:I$368,$A10)} -> 61 | ... BB10: {=INDEX(Data!AX$2:AX$368,$A10)} -> 0
A11: 9 | B11: 45300 | C11: 2024 | D11: JANUARY | E11: 9 | F11: {=INDEX(Data!B$2:B$368,$A11)} -> 606 | G11: {=INDEX(Data!C$2:C$368,$A11)} -> 664 | H11: {=INDEX(Data!D$2:D$368,$A11)} -> 284 | I11: {=INDEX(Data!E$2:E$368,$A11)} -> 262 | J11: {=INDEX(Data!F$2:F$368,$A11)} -> 60 | K11: {=INDEX(Data!G$2:G$368,$A11)} -> 232 | L11: {=INDEX(Data!H$2:H$368,$A11)} -> 346 | M11: {=INDEX(Data!I$2:I$368,$A11)} -> 86 | ... BB11: {=INDEX(Data!AX$2:AX$368,$A11)} -> 30
A12: 10 | B12: 45301 | C12: 2024 | D12: JANUARY | E12: 10 | F12: {=INDEX(Data!B$2:B$368,$A12)} -> 602 | G12: {=INDEX(Data!C$2:C$368,$A12)} -> 625 | H12: {=INDEX(Data!D$2:D$368,$A12)} -> 258 | I12: {=INDEX(Data!E$2:E$368,$A12)} -> 314 | J12: {=INDEX(Data!F$2:F$368,$A12)} -> 30 | K12: {=INDEX(Data!G$2:G$368,$A12)} -> 131 | L12: {=INDEX(Data!H$2:H$368,$A12)} -> 451 | M12: {=INDEX(Data!I$2:I$368,$A12)} -> 43 | ... BB12: {=INDEX(Data!AX$2:AX$368,$A12)} -> 34
A13: 11 | B13: 45302 | C13: 2024 | D13: JANUARY | E13: 11 | F13: {=INDEX(Data!B$2:B$368,$A13)} -> 584 | G13: {=INDEX(Data!C$2:C$368,$A13)} -> 588 | H13: {=INDEX(Data!D$2:D$368,$A13)} -> 186 | I13: {=INDEX(Data!E$2:E$368,$A13)} -> 334 | J13: {=INDEX(Data!F$2:F$368,$A13)} -> 64 | K13: {=INDEX(Data!G$2:G$368,$A13)} -> 158 | L13: {=INDEX(Data!H$2:H$368,$A13)} -> 313 | M13: {=INDEX(Data!I$2:I$368,$A13)} -> 117 | ... BB13: {=INDEX(Data!AX$2:AX$368,$A13)} -> 0
A14: 12 | B14: 45303 | C14: 2024 | D14: JANUARY | E14: 12 | F14: {=INDEX(Data!B$2:B$368,$A14)} -> 560 | G14: {=INDEX(Data!C$2:C$368,$A14)} -> 575 | H14: {=INDEX(Data!D$2:D$368,$A14)} -> 123 | I14: {=INDEX(Data!E$2:E$368,$A14)} -> 348 | J14: {=INDEX(Data!F$2:F$368,$A14)} -> 89 | K14: {=INDEX(Data!G$2:G$368,$A14)} -> 149 | L14: {=INDEX(Data!H$2:H$368,$A14)} -> 369 | M14: {=INDEX(Data!I$2:I$368,$A14)} -> 57 | ... BB14: {=INDEX(Data!AX$2:AX$368,$A14)} -> 0
... A33: 31 | B33: 45322 | C33: 2024 | D33: JANUARY | E33: 31 | F33: {=INDEX(Data!B$2:B$368,$A33)} -> 578 | G33: {=INDEX(Data!C$2:C$368,$A33)} -> 654 | H33: {=INDEX(Data!D$2:D$368,$A33)} -> 306 | I33: {=INDEX(Data!E$2:E$368,$A33)} -> 128 | J33: {=INDEX(Data!F$2:F$368,$A33)} -> 144 | K33: {=INDEX(Data!G$2:G$368,$A33)} -> 248 | L33: {=INDEX(Data!H$2:H$368,$A33)} -> 302 | M33: {=INDEX(Data!I$2:I$368,$A33)} -> 104 | ... BB33: {=INDEX(Data!AX$2:AX$368,$A33)} -> 19
A34: 367 | C34: 2024 | D34: FEBRUARY | E34: 0.01 | F34: {=INDEX(Data!B$2:B$368,$A34)} -> 0 | G34: {=INDEX(Data!C$2:C$368,$A34)} -> 0 | H34: {=INDEX(Data!D$2:D$368,$A34)} -> 0 | I34: {=INDEX(Data!E$2:E$368,$A34)} -> 0 | J34: {=INDEX(Data!F$2:F$368,$A34)} -> 0 | K34: {=INDEX(Data!G$2:G$368,$A34)} -> 0 | L34: {=INDEX(Data!H$2:H$368,$A34)} -> 0 | M34: {=INDEX(Data!I$2:I$368,$A34)} -> 0 | ... BB34: {=INDEX(Data!AX$2:AX$368,$A34)} -> 0
A35: 367 | C35: 2024 | D35: FEBRUARY | E35: 0.02 | F35: {=INDEX(Data!B$2:B$368,$A35)} -> 0 | G35: {=INDEX(Data!C$2:C$368,$A35)} -> 0 | H35: {=INDEX(Data!D$2:D$368,$A35)} -> 0 | I35: {=INDEX(Data!E$2:E$368,$A35)} -> 0 | J35: {=INDEX(Data!F$2:F$368,$A35)} -> 0 | K35: {=INDEX(Data!G$2:G$368,$A35)} -> 0 | L35: {=INDEX(Data!H$2:H$368,$A35)} -> 0 | M35: {=INDEX(Data!I$2:I$368,$A35)} -> 0 | ... BB35: {=INDEX(Data!AX$2:AX$368,$A35)} -> 0
A36: 367 | C36: 2024 | D36: FEBRUARY | E36: 0.03 | F36: {=INDEX(Data!B$2:B$368,$A36)} -> 0 | G36: {=INDEX(Data!C$2:C$368,$A36)} -> 0 | H36: {=INDEX(Data!D$2:D$368,$A36)} -> 0 | I36: {=INDEX(Data!E$2:E$368,$A36)} -> 0 | J36: {=INDEX(Data!F$2:F$368,$A36)} -> 0 | K36: {=INDEX(Data!G$2:G$368,$A36)} -> 0 | L36: {=INDEX(Data!H$2:H$368,$A36)} -> 0 | M36: {=INDEX(Data!I$2:I$368,$A36)} -> 0 | ... BB36: {=INDEX(Data!AX$2:AX$368,$A36)} -> 0
A37: 367 | C37: 2024 | D37: FEBRUARY | E37: 0.04 | F37: {=INDEX(Data!B$2:B$368,$A37)} -> 0 | G37: {=INDEX(Data!C$2:C$368,$A37)} -> 0 | H37: {=INDEX(Data!D$2:D$368,$A37)} -> 0 | I37: {=INDEX(Data!E$2:E$368,$A37)} -> 0 | J37: {=INDEX(Data!F$2:F$368,$A37)} -> 0 | K37: {=INDEX(Data!G$2:G$368,$A37)} -> 0 | L37: {=INDEX(Data!H$2:H$368,$A37)} -> 0 | M37: {=INDEX(Data!I$2:I$368,$A37)} -> 0 | ... BB37: {=INDEX(Data!AX$2:AX$368,$A37)} -> 0
A38: 32 | B38: 45323 | C38: 2024 | D38: FEBRUARY | E38: 1 | F38: {=INDEX(Data!B$2:B$368,$A38)} -> 577 | G38: {=INDEX(Data!C$2:C$368,$A38)} -> 864 | H38: {=INDEX(Data!D$2:D$368,$A38)} -> 236 | I38: {=INDEX(Data!E$2:E$368,$A38)} -> 307 | J38: {=INDEX(Data!F$2:F$368,$A38)} -> 34 | K38: {=INDEX(Data!G$2:G$368,$A38)} -> 259 | L38: {=INDEX(Data!H$2:H$368,$A38)} -> 433 | M38: {=INDEX(Data!I$2:I$368,$A38)} -> 172 | ... BB38: {=INDEX(Data!AX$2:AX$368,$A38)} -> 125
A39: 33 | B39: 45324 | C39: 2024 | D39: FEBRUARY | E39: 2 | F39: {=INDEX(Data!B$2:B$368,$A39)} -> 580 | G39: {=INDEX(Data!C$2:C$368,$A39)} -> 859 | H39: {=INDEX(Data!D$2:D$368,$A39)} -> 284 | I39: {=INDEX(Data!E$2:E$368,$A39)} -> 262 | J39: {=INDEX(Data!F$2:F$368,$A39)} -> 34 | K39: {=INDEX(Data!G$2:G$368,$A39)} -> 249 | L39: {=INDEX(Data!H$2:H$368,$A39)} -> 525 | M39: {=INDEX(Data!I$2:I$368,$A39)} -> 85 | ... BB39: {=INDEX(Data!AX$2:AX$368,$A39)} -> 20
A40: 34 | B40: 45325 | C40: 2024 | D40: FEBRUARY | E40: 3 | F40: {=INDEX(Data!B$2:B$368,$A40)} -> 587 | G40: {=INDEX(Data!C$2:C$368,$A40)} -> 840 | H40: {=INDEX(Data!D$2:D$368,$A40)} -> 176 | I40: {=INDEX(Data!E$2:E$368,$A40)} -> 265 | J40: {=INDEX(Data!F$2:F$368,$A40)} -> 146 | K40: {=INDEX(Data!G$2:G$368,$A40)} -> 411 | L40: {=INDEX(Data!H$2:H$368,$A40)} -> 337 | M40: {=INDEX(Data!I$2:I$368,$A40)} -> 92 | ... BB40: {=INDEX(Data!AX$2:AX$368,$A40)} -> 105
A41: 35 | B41: 45326 | C41: 2024 | D41: FEBRUARY | E41: 4 | F41: {=INDEX(Data!B$2:B$368,$A41)} -> 602 | G41: {=INDEX(Data!C$2:C$368,$A41)} -> 800 | H41: {=INDEX(Data!D$2:D$368,$A41)} -> 313 | I41: {=INDEX(Data!E$2:E$368,$A41)} -> 187 | J41: {=INDEX(Data!F$2:F$368,$A41)} -> 102 | K41: {=INDEX(Data!G$2:G$368,$A41)} -> 320 | L41: {=INDEX(Data!H$2:H$368,$A41)} -> 344 | M41: {=INDEX(Data!I$2:I$368,$A41)} -> 136 | ... BB41: {=INDEX(Data!AX$2:AX$368,$A41)} -> 0
A42: 36 | B42: 45327 | C42: 2024 | D42: FEBRUARY | E42: 5 | F42: {=INDEX(Data!B$2:B$368,$A42)} -> 618 | G42: {=INDEX(Data!C$2:C$368,$A42)} -> 775 | H42: {=INDEX(Data!D$2:D$368,$A42)} -> 135 | I42: {=INDEX(Data!E$2:E$368,$A42)} -> 378 | J42: {=INDEX(Data!F$2:F$368,$A42)} -> 105 | K42: {=INDEX(Data!G$2:G$368,$A42)} -> 255 | L42: {=INDEX(Data!H$2:H$368,$A42)} -> 404 | M42: {=INDEX(Data!I$2:I$368,$A42)} -> 116 | ... BB42: {=INDEX(Data!AX$2:AX$368,$A42)} -> 0
A43: 37 | B43: 45328 | C43: 2024 | D43: FEBRUARY | E43: 6 | F43: {=INDEX(Data!B$2:B$368,$A43)} -> 643 | G43: {=INDEX(Data!C$2:C$368,$A43)} -> 763 | H43: {=INDEX(Data!D$2:D$368,$A43)} -> 250 | I43: {=INDEX(Data!E$2:E$368,$A43)} -> 316 | J43: {=INDEX(Data!F$2:F$368,$A43)} -> 77 | K43: {=INDEX(Data!G$2:G$368,$A43)} -> 381 | L43: {=INDEX(Data!H$2:H$368,$A43)} -> 260 | M43: {=INDEX(Data!I$2:I$368,$A43)} -> 122 | ... BB43: {=INDEX(Data!AX$2:AX$368,$A43)} -> 91
A44: 38 | B44: 45329 | C44: 2024 | D44: FEBRUARY | E44: 7 | F44: {=INDEX(Data!B$2:B$368,$A44)} -> 671 | G44: {=INDEX(Data!C$2:C$368,$A44)} -> 761 | H44: {=INDEX(Data!D$2:D$368,$A44)} -> 328 | I44: {=INDEX(Data!E$2:E$368,$A44)} -> 243 | J44: {=INDEX(Data!F$2:F$368,$A44)} -> 100 | K44: {=INDEX(Data!G$2:G$368,$A44)} -> 334 | L44: {=INDEX(Data!H$2:H$368,$A44)} -> 237 | M44: {=INDEX(Data!I$2:I$368,$A44)} -> 190 | ... BB44: {=INDEX(Data!AX$2:AX$368,$A44)} -> 0
A45: 39 | B45: 45330 | C45: 2024 | D45: FEBRUARY | E45: 8 | F45: {=INDEX(Data!B$2:B$368,$A45)} -> 697 | G45: {=INDEX(Data!C$2:C$368,$A45)} -> 773 | H45: {=INDEX(Data!D$2:D$368,$A45)} -> 174 | I45: {=INDEX(Data!E$2:E$368,$A45)} -> 370 | J45: {=INDEX(Data!F$2:F$368,$A45)} -> 153 | K45: {=INDEX(Data!G$2:G$368,$A45)} -> 247 | L45: {=INDEX(Data!H$2:H$368,$A45)} -> 426 | M45: {=INDEX(Data!I$2:I$368,$A45)} -> 100 | ... BB45: {=INDEX(Data!AX$2:AX$368,$A45)} -> 52
A46: 40 | B46: 45331 | C46: 2024 | D46: FEBRUARY | E46: 9 | F46: {=INDEX(Data!B$2:B$368,$A46)} -> 716 | G46: {=INDEX(Data!C$2:C$368,$A46)} -> 794 | H46: {=INDEX(Data!D$2:D$368,$A46)} -> 372 | I46: {=INDEX(Data!E$2:E$368,$A46)} -> 194 | J46: {=INDEX(Data!F$2:F$368,$A46)} -> 150 | K46: {=INDEX(Data!G$2:G$368,$A46)} -> 325 | L46: {=INDEX(Data!H$2:H$368,$A46)} -> 422 | M46: {=INDEX(Data!I$2:I$368,$A46)} -> 47 | ... BB46: {=INDEX(Data!AX$2:AX$368,$A46)} -> 106
A47: 41 | B47: 45332 | C47: 2024 | D47: FEBRUARY | E47: 10 | F47: {=INDEX(Data!B$2:B$368,$A47)} -> 734 | G47: {=INDEX(Data!C$2:C$368,$A47)} -> 844 | H47: {=INDEX(Data!D$2:D$368,$A47)} -> 161 | I47: {=INDEX(Data!E$2:E$368,$A47)} -> 485 | J47: {=INDEX(Data!F$2:F$368,$A47)} -> 88 | K47: {=INDEX(Data!G$2:G$368,$A47)} -> 388 | L47: {=INDEX(Data!H$2:H$368,$A47)} -> 313 | M47: {=INDEX(Data!I$2:I$368,$A47)} -> 143 | ... BB47: {=INDEX(Data!AX$2:AX$368,$A47)} -> 0
A48: 42 | B48: 45333 | C48: 2024 | D48: FEBRUARY | E48: 11 | F48: {=INDEX(Data!B$2:B$368,$A48)} -> 746 | G48: {=INDEX(Data!C$2:C$368,$A48)} -> 912 | H48: {=INDEX(Data!D$2:D$368,$A48)} -> 283 | I48: {=INDEX(Data!E$2:E$368,$A48)} -> 419 | J48: {=INDEX(Data!F$2:F$368,$A48)} -> 44 | K48: {=INDEX(Data!G$2:G$368,$A48)} -> 182 | L48: {=INDEX(Data!H$2:H$368,$A48)} -> 639 | M48: {=INDEX(Data!I$2:I$368,$A48)} -> 91 | ... BB48: {=INDEX(Data!AX$2:AX$368,$A48)} -> 0
A49: 43 | B49: 45334 | C49: 2024 | D49: FEBRUARY | E49: 12 | F49: {=INDEX(Data!B$2:B$368,$A49)} -> 752 | G49: {=INDEX(Data!C$2:C$368,$A49)} -> 972 | H49: {=INDEX(Data!D$2:D$368,$A49)} -> 315 | I49: {=INDEX(Data!E$2:E$368,$A49)} -> 317 | J49: {=INDEX(Data!F$2:F$368,$A49)} -> 120 | K49: {=INDEX(Data!G$2:G$368,$A49)} -> 213 | L49: {=INDEX(Data!H$2:H$368,$A49)} -> 516 | M49: {=INDEX(Data!I$2:I$368,$A49)} -> 243 | ... BB49: {=INDEX(Data!AX$2:AX$368,$A49)} -> 0
... A66: 60 | B66: 45351 | C66: 2024 | D66: FEBRUARY | E66: 29 | F66: {=INDEX(Data!B$2:B$368,$A66)} -> 637 | G66: {=INDEX(Data!C$2:C$368,$A66)} -> 972 | H66: {=INDEX(Data!D$2:D$368,$A66)} -> 152 | I66: {=INDEX(Data!E$2:E$368,$A66)} -> 371 | J66: {=INDEX(Data!F$2:F$368,$A66)} -> 114 | K66: {=INDEX(Data!G$2:G$368,$A66)} -> 417 | L66: {=INDEX(Data!H$2:H$368,$A66)} -> 312 | M66: {=INDEX(Data!I$2:I$368,$A66)} -> 243 | ... BB66: {=INDEX(Data!AX$2:AX$368,$A66)} -> 0
A67: 367 | C67: 2024 | D67: MARCH | E67: 0.01 | F67: {=INDEX(Data!B$2:B$368,$A67)} -> 0 | G67: {=INDEX(Data!C$2:C$368,$A67)} -> 0 | H67: {=INDEX(Data!D$2:D$368,$A67)} -> 0 | I67: {=INDEX(Data!E$2:E$368,$A67)} -> 0 | J67: {=INDEX(Data!F$2:F$368,$A67)} -> 0 | K67: {=INDEX(Data!G$2:G$368,$A67)} -> 0 | L67: {=INDEX(Data!H$2:H$368,$A67)} -> 0 | M67: {=INDEX(Data!I$2:I$368,$A67)} -> 0 | ... BB67: {=INDEX(Data!AX$2:AX$368,$A67)} -> 0
A68: 367 | C68: 2024 | D68: MARCH | E68: 0.02 | F68: {=INDEX(Data!B$2:B$368,$A68)} -> 0 | G68: {=INDEX(Data!C$2:C$368,$A68)} -> 0 | H68: {=INDEX(Data!D$2:D$368,$A68)} -> 0 | I68: {=INDEX(Data!E$2:E$368,$A68)} -> 0 | J68: {=INDEX(Data!F$2:F$368,$A68)} -> 0 | K68: {=INDEX(Data!G$2:G$368,$A68)} -> 0 | L68: {=INDEX(Data!H$2:H$368,$A68)} -> 0 | M68: {=INDEX(Data!I$2:I$368,$A68)} -> 0 | ... BB68: {=INDEX(Data!AX$2:AX$368,$A68)} -> 0
A69: 367 | C69: 2024 | D69: MARCH | E69: 0.03 | F69: {=INDEX(Data!B$2:B$368,$A69)} -> 0 | G69: {=INDEX(Data!C$2:C$368,$A69)} -> 0 | H69: {=INDEX(Data!D$2:D$368,$A69)} -> 0 | I69: {=INDEX(Data!E$2:E$368,$A69)} -> 0 | J69: {=INDEX(Data!F$2:F$368,$A69)} -> 0 | K69: {=INDEX(Data!G$2:G$368,$A69)} -> 0 | L69: {=INDEX(Data!H$2:H$368,$A69)} -> 0 | M69: {=INDEX(Data!I$2:I$368,$A69)} -> 0 | ... BB69: {=INDEX(Data!AX$2:AX$368,$A69)} -> 0
A70: 367 | C70: 2024 | D70: MARCH | E70: 0.04 | F70: {=INDEX(Data!B$2:B$368,$A70)} -> 0 | G70: {=INDEX(Data!C$2:C$368,$A70)} -> 0 | H70: {=INDEX(Data!D$2:D$368,$A70)} -> 0 | I70: {=INDEX(Data!E$2:E$368,$A70)} -> 0 | J70: {=INDEX(Data!F$2:F$368,$A70)} -> 0 | K70: {=INDEX(Data!G$2:G$368,$A70)} -> 0 | L70: {=INDEX(Data!H$2:H$368,$A70)} -> 0 | M70: {=INDEX(Data!I$2:I$368,$A70)} -> 0 | ... BB70: {=INDEX(Data!AX$2:AX$368,$A70)} -> 0
A71: 367 | C71: 2024 | D71: MARCH | E71: 0.05 | F71: {=INDEX(Data!B$2:B$368,$A71)} -> 0 | G71: {=INDEX(Data!C$2:C$368,$A71)} -> 0 | H71: {=INDEX(Data!D$2:D$368,$A71)} -> 0 | I71: {=INDEX(Data!E$2:E$368,$A71)} -> 0 | J71: {=INDEX(Data!F$2:F$368,$A71)} -> 0 | K71: {=INDEX(Data!G$2:G$368,$A71)} -> 0 | L71: {=INDEX(Data!H$2:H$368,$A71)} -> 0 | M71: {=INDEX(Data!I$2:I$368,$A71)} -> 0 | ... BB71: {=INDEX(Data!AX$2:AX$368,$A71)} -> 0
A72: 61 | B72: 45352 | C72: 2024 | D72: MARCH | E72: 1 | F72: {=INDEX(Data!B$2:B$368,$A72)} -> 612 | G72: {=INDEX(Data!C$2:C$368,$A72)} -> 820 | H72: {=INDEX(Data!D$2:D$368,$A72)} -> 189 | I72: {=INDEX(Data!E$2:E$368,$A72)} -> 368 | J72: {=INDEX(Data!F$2:F$368,$A72)} -> 55 | K72: {=INDEX(Data!G$2:G$368,$A72)} -> 434 | L72: {=INDEX(Data!H$2:H$368,$A72)} -> 190 | M72: {=INDEX(Data!I$2:I$368,$A72)} -> 196 | ... BB72: {=INDEX(Data!AX$2:AX$368,$A72)} -> 27
A73: 62 | B73: 45353 | C73: 2024 | D73: MARCH | E73: 2 | F73: {=INDEX(Data!B$2:B$368,$A73)} -> 601 | G73: {=INDEX(Data!C$2:C$368,$A73)} -> 775 | H73: {=INDEX(Data!D$2:D$368,$A73)} -> 144 | I73: {=INDEX(Data!E$2:E$368,$A73)} -> 409 | J73: {=INDEX(Data!F$2:F$368,$A73)} -> 48 | K73: {=INDEX(Data!G$2:G$368,$A73)} -> 302 | L73: {=INDEX(Data!H$2:H$368,$A73)} -> 427 | M73: {=INDEX(Data!I$2:I$368,$A73)} -> 46 | ... BB73: {=INDEX(Data!AX$2:AX$368,$A73)} -> 0
A74: 63 | B74: 45354 | C74: 2024 | D74: MARCH | E74: 3 | F74: {=INDEX(Data!B$2:B$368,$A74)} -> 597 | G74: {=INDEX(Data!C$2:C$368,$A74)} -> 727 | H74: {=INDEX(Data!D$2:D$368,$A74)} -> 244 | I74: {=INDEX(Data!E$2:E$368,$A74)} -> 246 | J74: {=INDEX(Data!F$2:F$368,$A74)} -> 107 | K74: {=INDEX(Data!G$2:G$368,$A74)} -> 341 | L74: {=INDEX(Data!H$2:H$368,$A74)} -> 307 | M74: {=INDEX(Data!I$2:I$368,$A74)} -> 79 | ... BB74: {=INDEX(Data!AX$2:AX$368,$A74)} -> 63
A75: 64 | B75: 45355 | C75: 2024 | D75: MARCH | E75: 4 | F75: {=INDEX(Data!B$2:B$368,$A75)} -> 596 | G75: {=INDEX(Data!C$2:C$368,$A75)} -> 693 | H75: {=INDEX(Data!D$2:D$368,$A75)} -> 137 | I75: {=INDEX(Data!E$2:E$368,$A75)} -> 364 | J75: {=INDEX(Data!F$2:F$368,$A75)} -> 95 | K75: {=INDEX(Data!G$2:G$368,$A75)} -> 367 | L75: {=INDEX(Data!H$2:H$368,$A75)} -> 271 | M75: {=INDEX(Data!I$2:I$368,$A75)} -> 55 | ... BB75: {=INDEX(Data!AX$2:AX$368,$A75)} -> 128
A76: 65 | B76: 45356 | C76: 2024 | D76: MARCH | E76: 5 | F76: {=INDEX(Data!B$2:B$368,$A76)} -> 601 | G76: {=INDEX(Data!C$2:C$368,$A76)} -> 677 | H76: {=INDEX(Data!D$2:D$368,$A76)} -> 312 | I76: {=INDEX(Data!E$2:E$368,$A76)} -> 151 | J76: {=INDEX(Data!F$2:F$368,$A76)} -> 138 | K76: {=INDEX(Data!G$2:G$368,$A76)} -> 148 | L76: {=INDEX(Data!H$2:H$368,$A76)} -> 489 | M76: {=INDEX(Data!I$2:I$368,$A76)} -> 40 | ... BB76: {=INDEX(Data!AX$2:AX$368,$A76)} -> 0
A77: 66 | B77: 45357 | C77: 2024 | D77: MARCH | E77: 6 | F77: {=INDEX(Data!B$2:B$368,$A77)} -> 608 | G77: {=INDEX(Data!C$2:C$368,$A77)} -> 674 | H77: {=INDEX(Data!D$2:D$368,$A77)} -> 231 | I77: {=INDEX(Data!E$2:E$368,$A77)} -> 232 | J77: {=INDEX(Data!F$2:F$368,$A77)} -> 145 | K77: {=INDEX(Data!G$2:G$368,$A77)} -> 256 | L77: {=INDEX(Data!H$2:H$368,$A77)} -> 371 | M77: {=INDEX(Data!I$2:I$368,$A77)} -> 47 | ... BB77: {=INDEX(Data!AX$2:AX$368,$A77)} -> 0
A78: 67 | B78: 45358 | C78: 2024 | D78: MARCH | E78: 7 | F78: {=INDEX(Data!B$2:B$368,$A78)} -> 619 | G78: {=INDEX(Data!C$2:C$368,$A78)} -> 683 | H78: {=INDEX(Data!D$2:D$368,$A78)} -> 142 | I78: {=INDEX(Data!E$2:E$368,$A78)} -> 409 | J78: {=INDEX(Data!F$2:F$368,$A78)} -> 68 | K78: {=INDEX(Data!G$2:G$368,$A78)} -> 361 | L78: {=INDEX(Data!H$2:H$368,$A78)} -> 275 | M78: {=INDEX(Data!I$2:I$368,$A78)} -> 47 | ... BB78: {=INDEX(Data!AX$2:AX$368,$A78)} -> 0
A79: 68 | B79: 45359 | C79: 2024 | D79: MARCH | E79: 8 | F79: {=INDEX(Data!B$2:B$368,$A79)} -> 633 | G79: {=INDEX(Data!C$2:C$368,$A79)} -> 706 | H79: {=INDEX(Data!D$2:D$368,$A79)} -> 278 | I79: {=INDEX(Data!E$2:E$368,$A79)} -> 280 | J79: {=INDEX(Data!F$2:F$368,$A79)} -> 75 | K79: {=INDEX(Data!G$2:G$368,$A79)} -> 176 | L79: {=INDEX(Data!H$2:H$368,$A79)} -> 418 | M79: {=INDEX(Data!I$2:I$368,$A79)} -> 112 | ... BB79: {=INDEX(Data!AX$2:AX$368,$A79)} -> 97
A80: 69 | B80: 45360 | C80: 2024 | D80: MARCH | E80: 9 | F80: {=INDEX(Data!B$2:B$368,$A80)} -> 654 | G80: {=INDEX(Data!C$2:C$368,$A80)} -> 744 | H80: {=INDEX(Data!D$2:D$368,$A80)} -> 215 | I80: {=INDEX(Data!E$2:E$368,$A80)} -> 335 | J80: {=INDEX(Data!F$2:F$368,$A80)} -> 104 | K80: {=INDEX(Data!G$2:G$368,$A80)} -> 148 | L80: {=INDEX(Data!H$2:H$368,$A80)} -> 470 | M80: {=INDEX(Data!I$2:I$368,$A80)} -> 126 | ... BB80: {=INDEX(Data!AX$2:AX$368,$A80)} -> 0
A81: 70 | B81: 45361 | C81: 2024 | D81: MARCH | E81: 10 | F81: {=INDEX(Data!B$2:B$368,$A81)} -> 676 | G81: {=INDEX(Data!C$2:C$368,$A81)} -> 778 | H81: {=INDEX(Data!D$2:D$368,$A81)} -> 148 | I81: {=INDEX(Data!E$2:E$368,$A81)} -> 481 | J81: {=INDEX(Data!F$2:F$368,$A81)} -> 47 | K81: {=INDEX(Data!G$2:G$368,$A81)} -> 186 | L81: {=INDEX(Data!H$2:H$368,$A81)} -> 530 | M81: {=INDEX(Data!I$2:I$368,$A81)} -> 62 | ... BB81: {=INDEX(Data!AX$2:AX$368,$A81)} -> 0
A82: 71 | B82: 45362 | C82: 2024 | D82: MARCH | E82: 11 | F82: {=INDEX(Data!B$2:B$368,$A82)} -> 703 | G82: {=INDEX(Data!C$2:C$368,$A82)} -> 792 | H82: {=INDEX(Data!D$2:D$368,$A82)} -> 182 | I82: {=INDEX(Data!E$2:E$368,$A82)} -> 381 | J82: {=INDEX(Data!F$2:F$368,$A82)} -> 140 | K82: {=INDEX(Data!G$2:G$368,$A82)} -> 356 | L82: {=INDEX(Data!H$2:H$368,$A82)} -> 302 | M82: {=INDEX(Data!I$2:I$368,$A82)} -> 134 | ... BB82: {=INDEX(Data!AX$2:AX$368,$A82)} -> 4
A83: 72 | B83: 45363 | C83: 2024 | D83: MARCH | E83: 12 | F83: {=INDEX(Data!B$2:B$368,$A83)} -> 730 | G83: {=INDEX(Data!C$2:C$368,$A83)} -> 796 | H83: {=INDEX(Data!D$2:D$368,$A83)} -> 379 | I83: {=INDEX(Data!E$2:E$368,$A83)} -> 242 | J83: {=INDEX(Data!F$2:F$368,$A83)} -> 109 | K83: {=INDEX(Data!G$2:G$368,$A83)} -> 286 | L83: {=INDEX(Data!H$2:H$368,$A83)} -> 439 | M83: {=INDEX(Data!I$2:I$368,$A83)} -> 71 | ... BB83: {=INDEX(Data!AX$2:AX$368,$A83)} -> 0
... A102: 91 | B102: 45382 | C102: 2024 | D102: MARCH | E102: 31 | F102: {=INDEX(Data!B$2:B$368,$A102)} -> 739 | G102: {=INDEX(Data!C$2:C$368,$A102)} -> 819 | H102: {=INDEX(Data!D$2:D$368,$A102)} -> 347 | I102: {=INDEX(Data!E$2:E$368,$A102)} -> 348 | J102: {=INDEX(Data!F$2:F$368,$A102)} -> 44 | K102: {=INDEX(Data!G$2:G$368,$A102)} -> 368 | L102: {=INDEX(Data!H$2:H$368,$A102)} -> 271 | M102: {=INDEX(Data!I$2:I$368,$A102)} -> 180 | ... BB102: {=INDEX(Data!AX$2:AX$368,$A102)} -> 0
A103: 367 | C103: 2024 | D103: APRIL | E103: 0.01 | F103: {=INDEX(Data!B$2:B$368,$A103)} -> 0 | G103: {=INDEX(Data!C$2:C$368,$A103)} -> 0 | H103: {=INDEX(Data!D$2:D$368,$A103)} -> 0 | I103: {=INDEX(Data!E$2:E$368,$A103)} -> 0 | J103: {=INDEX(Data!F$2:F$368,$A103)} -> 0 | K103: {=INDEX(Data!G$2:G$368,$A103)} -> 0 | L103: {=INDEX(Data!H$2:H$368,$A103)} -> 0 | M103: {=INDEX(Data!I$2:I$368,$A103)} -> 0 | ... BB103: {=INDEX(Data!AX$2:AX$368,$A103)} -> 0
A104: 92 | B104: 45383 | C104: 2024 | D104: APRIL | E104: 1 | F104: {=INDEX(Data!B$2:B$368,$A104)} -> 764 | G104: {=INDEX(Data!C$2:C$368,$A104)} -> 714 | H104: {=INDEX(Data!D$2:D$368,$A104)} -> 168 | I104: {=INDEX(Data!E$2:E$368,$A104)} -> 413 | J104: {=INDEX(Data!F$2:F$368,$A104)} -> 183 | K104: {=INDEX(Data!G$2:G$368,$A104)} -> 214 | L104: {=INDEX(Data!H$2:H$368,$A104)} -> 358 | M104: {=INDEX(Data!I$2:I$368,$A104)} -> 142 | ... BB104: {=INDEX(Data!AX$2:AX$368,$A104)} -> 2
A105: 93 | B105: 45384 | C105: 2024 | D105: APRIL | E105: 2 | F105: {=INDEX(Data!B$2:B$368,$A105)} -> 790 | G105: {=INDEX(Data!C$2:C$368,$A105)} -> 706 | H105: {=INDEX(Data!D$2:D$368,$A105)} -> 410 | I105: {=INDEX(Data!E$2:E$368,$A105)} -> 254 | J105: {=INDEX(Data!F$2:F$368,$A105)} -> 126 | K105: {=INDEX(Data!G$2:G$368,$A105)} -> 176 | L105: {=INDEX(Data!H$2:H$368,$A105)} -> 389 | M105: {=INDEX(Data!I$2:I$368,$A105)} -> 141 | ... BB105: {=INDEX(Data!AX$2:AX$368,$A105)} -> 13
A106: 94 | B106: 45385 | C106: 2024 | D106: APRIL | E106: 3 | F106: {=INDEX(Data!B$2:B$368,$A106)} -> 811 | G106: {=INDEX(Data!C$2:C$368,$A106)} -> 691 | H106: {=INDEX(Data!D$2:D$368,$A106)} -> 202 | I106: {=INDEX(Data!E$2:E$368,$A106)} -> 504 | J106: {=INDEX(Data!F$2:F$368,$A106)} -> 105 | K106: {=INDEX(Data!G$2:G$368,$A106)} -> 283 | L106: {=INDEX(Data!H$2:H$368,$A106)} -> 312 | M106: {=INDEX(Data!I$2:I$368,$A106)} -> 96 | ... BB106: {=INDEX(Data!AX$2:AX$368,$A106)} -> 39
A107: 95 | B107: 45386 | C107: 2024 | D107: APRIL | E107: 4 | F107: {=INDEX(Data!B$2:B$368,$A107)} -> 842 | G107: {=INDEX(Data!C$2:C$368,$A107)} -> 666 | H107: {=INDEX(Data!D$2:D$368,$A107)} -> 311 | I107: {=INDEX(Data!E$2:E$368,$A107)} -> 405 | J107: {=INDEX(Data!F$2:F$368,$A107)} -> 126 | K107: {=INDEX(Data!G$2:G$368,$A107)} -> 339 | L107: {=INDEX(Data!H$2:H$368,$A107)} -> 268 | M107: {=INDEX(Data!I$2:I$368,$A107)} -> 59 | ... BB107: {=INDEX(Data!AX$2:AX$368,$A107)} -> 0
A108: 96 | B108: 45387 | C108: 2024 | D108: APRIL | E108: 5 | F108: {=INDEX(Data!B$2:B$368,$A108)} -> 863 | G108: {=INDEX(Data!C$2:C$368,$A108)} -> 641 | H108: {=INDEX(Data!D$2:D$368,$A108)} -> 241 | I108: {=INDEX(Data!E$2:E$368,$A108)} -> 415 | J108: {=INDEX(Data!F$2:F$368,$A108)} -> 207 | K108: {=INDEX(Data!G$2:G$368,$A108)} -> 326 | L108: {=INDEX(Data!H$2:H$368,$A108)} -> 251 | M108: {=INDEX(Data!I$2:I$368,$A108)} -> 64 | ... BB108: {=INDEX(Data!AX$2:AX$368,$A108)} -> 31
A109: 97 | B109: 45388 | C109: 2024 | D109: APRIL | E109: 6 | F109: {=INDEX(Data!B$2:B$368,$A109)} -> 878 | G109: {=INDEX(Data!C$2:C$368,$A109)} -> 609 | H109: {=INDEX(Data!D$2:D$368,$A109)} -> 219 | I109: {=INDEX(Data!E$2:E$368,$A109)} -> 501 | J109: {=INDEX(Data!F$2:F$368,$A109)} -> 158 | K109: {=INDEX(Data!G$2:G$368,$A109)} -> 213 | L109: {=INDEX(Data!H$2:H$368,$A109)} -> 342 | M109: {=INDEX(Data!I$2:I$368,$A109)} -> 54 | ... BB109: {=INDEX(Data!AX$2:AX$368,$A109)} -> 0
A110: 98 | B110: 45389 | C110: 2024 | D110: APRIL | E110: 7 | F110: {=INDEX(Data!B$2:B$368,$A110)} -> 886 | G110: {=INDEX(Data!C$2:C$368,$A110)} -> 579 | H110: {=INDEX(Data!D$2:D$368,$A110)} -> 336 | I110: {=INDEX(Data!E$2:E$368,$A110)} -> 382 | J110: {=INDEX(Data!F$2:F$368,$A110)} -> 168 | K110: {=INDEX(Data!G$2:G$368,$A110)} -> 121 | L110: {=INDEX(Data!H$2:H$368,$A110)} -> 412 | M110: {=INDEX(Data!I$2:I$368,$A110)} -> 46 | ... BB110: {=INDEX(Data!AX$2:AX$368,$A110)} -> 15
A111: 99 | B111: 45390 | C111: 2024 | D111: APRIL | E111: 8 | F111: {=INDEX(Data!B$2:B$368,$A111)} -> 892 | G111: {=INDEX(Data!C$2:C$368,$A111)} -> 547 | H111: {=INDEX(Data!D$2:D$368,$A111)} -> 463 | I111: {=INDEX(Data!E$2:E$368,$A111)} -> 260 | J111: {=INDEX(Data!F$2:F$368,$A111)} -> 169 | K111: {=INDEX(Data!G$2:G$368,$A111)} -> 125 | L111: {=INDEX(Data!H$2:H$368,$A111)} -> 324 | M111: {=INDEX(Data!I$2:I$368,$A111)} -> 98 | ... BB111: {=INDEX(Data!AX$2:AX$368,$A111)} -> 0
A112: 100 | B112: 45391 | C112: 2024 | D112: APRIL | E112: 9 | F112: {=INDEX(Data!B$2:B$368,$A112)} -> 893 | G112: {=INDEX(Data!C$2:C$368,$A112)} -> 523 | H112: {=INDEX(Data!D$2:D$368,$A112)} -> 178 | I112: {=INDEX(Data!E$2:E$368,$A112)} -> 546 | J112: {=INDEX(Data!F$2:F$368,$A112)} -> 169 | K112: {=INDEX(Data!G$2:G$368,$A112)} -> 188 | L112: {=INDEX(Data!H$2:H$368,$A112)} -> 268 | M112: {=INDEX(Data!I$2:I$368,$A112)} -> 67 | ... BB112: {=INDEX(Data!AX$2:AX$368,$A112)} -> 0
A113: 101 | B113: 45392 | C113: 2024 | D113: APRIL | E113: 10 | F113: {=INDEX(Data!B$2:B$368,$A113)} -> 892 | G113: {=INDEX(Data!C$2:C$368,$A113)} -> 506 | H113: {=INDEX(Data!D$2:D$368,$A113)} -> 454 | I113: {=INDEX(Data!E$2:E$368,$A113)} -> 233 | J113: {=INDEX(Data!F$2:F$368,$A113)} -> 205 | K113: {=INDEX(Data!G$2:G$368,$A113)} -> 111 | L113: {=INDEX(Data!H$2:H$368,$A113)} -> 355 | M113: {=INDEX(Data!I$2:I$368,$A113)} -> 40 | ... BB113: {=INDEX(Data!AX$2:AX$368,$A113)} -> 16
A114: 102 | B114: 45393 | C114: 2024 | D114: APRIL | E114: 11 | F114: {=INDEX(Data!B$2:B$368,$A114)} -> 881 | G114: {=INDEX(Data!C$2:C$368,$A114)} -> 499 | H114: {=INDEX(Data!D$2:D$368,$A114)} -> 220 | I114: {=INDEX(Data!E$2:E$368,$A114)} -> 503 | J114: {=INDEX(Data!F$2:F$368,$A114)} -> 158 | K114: {=INDEX(Data!G$2:G$368,$A114)} -> 159 | L114: {=INDEX(Data!H$2:H$368,$A114)} -> 286 | M114: {=INDEX(Data!I$2:I$368,$A114)} -> 54 | ... BB114: {=INDEX(Data!AX$2:AX$368,$A114)} -> 27
A115: 103 | B115: 45394 | C115: 2024 | D115: APRIL | E115: 12 | F115: {=INDEX(Data!B$2:B$368,$A115)} -> 863 | G115: {=INDEX(Data!C$2:C$368,$A115)} -> 497 | H115: {=INDEX(Data!D$2:D$368,$A115)} -> 431 | I115: {=INDEX(Data!E$2:E$368,$A115)} -> 338 | J115: {=INDEX(Data!F$2:F$368,$A115)} -> 94 | K115: {=INDEX(Data!G$2:G$368,$A115)} -> 104 | L115: {=INDEX(Data!H$2:H$368,$A115)} -> 299 | M115: {=INDEX(Data!I$2:I$368,$A115)} -> 94 | ... BB115: {=INDEX(Data!AX$2:AX$368,$A115)} -> 0
... A133: 121 | B133: 45412 | C133: 2024 | D133: APRIL | E133: 30 | F133: {=INDEX(Data!B$2:B$368,$A133)} -> 987 | G133: {=INDEX(Data!C$2:C$368,$A133)} -> 855 | H133: {=INDEX(Data!D$2:D$368,$A133)} -> 523 | I133: {=INDEX(Data!E$2:E$368,$A133)} -> 405 | J133: {=INDEX(Data!F$2:F$368,$A133)} -> 59 | K133: {=INDEX(Data!G$2:G$368,$A133)} -> 179 | L133: {=INDEX(Data!H$2:H$368,$A133)} -> 540 | M133: {=INDEX(Data!I$2:I$368,$A133)} -> 136 | ... BB133: {=INDEX(Data!AX$2:AX$368,$A133)} -> 88
A134: 367 | C134: 2024 | D134: MAY | E134: 0.01 | F134: {=INDEX(Data!B$2:B$368,$A134)} -> 0 | G134: {=INDEX(Data!C$2:C$368,$A134)} -> 0 | H134: {=INDEX(Data!D$2:D$368,$A134)} -> 0 | I134: {=INDEX(Data!E$2:E$368,$A134)} -> 0 | J134: {=INDEX(Data!F$2:F$368,$A134)} -> 0 | K134: {=INDEX(Data!G$2:G$368,$A134)} -> 0 | L134: {=INDEX(Data!H$2:H$368,$A134)} -> 0 | M134: {=INDEX(Data!I$2:I$368,$A134)} -> 0 | ... BB134: {=INDEX(Data!AX$2:AX$368,$A134)} -> 0
A135: 367 | C135: 2024 | D135: MAY | E135: 0.02 | F135: {=INDEX(Data!B$2:B$368,$A135)} -> 0 | G135: {=INDEX(Data!C$2:C$368,$A135)} -> 0 | H135: {=INDEX(Data!D$2:D$368,$A135)} -> 0 | I135: {=INDEX(Data!E$2:E$368,$A135)} -> 0 | J135: {=INDEX(Data!F$2:F$368,$A135)} -> 0 | K135: {=INDEX(Data!G$2:G$368,$A135)} -> 0 | L135: {=INDEX(Data!H$2:H$368,$A135)} -> 0 | M135: {=INDEX(Data!I$2:I$368,$A135)} -> 0 | ... BB135: {=INDEX(Data!AX$2:AX$368,$A135)} -> 0
A136: 367 | C136: 2024 | D136: MAY | E136: 0.03 | F136: {=INDEX(Data!B$2:B$368,$A136)} -> 0 | G136: {=INDEX(Data!C$2:C$368,$A136)} -> 0 | H136: {=INDEX(Data!D$2:D$368,$A136)} -> 0 | I136: {=INDEX(Data!E$2:E$368,$A136)} -> 0 | J136: {=INDEX(Data!F$2:F$368,$A136)} -> 0 | K136: {=INDEX(Data!G$2:G$368,$A136)} -> 0 | L136: {=INDEX(Data!H$2:H$368,$A136)} -> 0 | M136: {=INDEX(Data!I$2:I$368,$A136)} -> 0 | ... BB136: {=INDEX(Data!AX$2:AX$368,$A136)} -> 0
A137: 122 | B137: 45413 | C137: 2024 | D137: MAY | E137: 1 | F137: {=INDEX(Data!B$2:B$368,$A137)} -> 994 | G137: {=INDEX(Data!C$2:C$368,$A137)} -> 1002 | H137: {=INDEX(Data!D$2:D$368,$A137)} -> 477 | I137: {=INDEX(Data!E$2:E$368,$A137)} -> 269 | J137: {=INDEX(Data!F$2:F$368,$A137)} -> 248 | K137: {=INDEX(Data!G$2:G$368,$A137)} -> 521 | L137: {=INDEX(Data!H$2:H$368,$A137)} -> 401 | M137: {=INDEX(Data!I$2:I$368,$A137)} -> 80 | ... BB137: {=INDEX(Data!AX$2:AX$368,$A137)} -> 52
A138: 123 | B138: 45414 | C138: 2024 | D138: MAY | E138: 2 | F138: {=INDEX(Data!B$2:B$368,$A138)} -> 999 | G138: {=INDEX(Data!C$2:C$368,$A138)} -> 995 | H138: {=INDEX(Data!D$2:D$368,$A138)} -> 249 | I138: {=INDEX(Data!E$2:E$368,$A138)} -> 511 | J138: {=INDEX(Data!F$2:F$368,$A138)} -> 239 | K138: {=INDEX(Data!G$2:G$368,$A138)} -> 348 | L138: {=INDEX(Data!H$2:H$368,$A138)} -> 498 | M138: {=INDEX(Data!I$2:I$368,$A138)} -> 149 | ... BB138: {=INDEX(Data!AX$2:AX$368,$A138)} -> 150
A139: 124 | B139: 45415 | C139: 2024 | D139: MAY | E139: 3 | F139: {=INDEX(Data!B$2:B$368,$A139)} -> 1000 | G139: {=INDEX(Data!C$2:C$368,$A139)} -> 985 | H139: {=INDEX(Data!D$2:D$368,$A139)} -> 420 | I139: {=INDEX(Data!E$2:E$368,$A139)} -> 500 | J139: {=INDEX(Data!F$2:F$368,$A139)} -> 80 | K139: {=INDEX(Data!G$2:G$368,$A139)} -> 206 | L139: {=INDEX(Data!H$2:H$368,$A139)} -> 582 | M139: {=INDEX(Data!I$2:I$368,$A139)} -> 197 | ... BB139: {=INDEX(Data!AX$2:AX$368,$A139)} -> 92
A140: 125 | B140: 45416 | C140: 2024 | D140: MAY | E140: 4 | F140: {=INDEX(Data!B$2:B$368,$A140)} -> 999 | G140: {=INDEX(Data!C$2:C$368,$A140)} -> 972 | H140: {=INDEX(Data!D$2:D$368,$A140)} -> 439 | I140: {=INDEX(Data!E$2:E$368,$A140)} -> 441 | J140: {=INDEX(Data!F$2:F$368,$A140)} -> 119 | K140: {=INDEX(Data!G$2:G$368,$A140)} -> 252 | L140: {=INDEX(Data!H$2:H$368,$A140)} -> 575 | M140: {=INDEX(Data!I$2:I$368,$A140)} -> 145 | ... BB140: {=INDEX(Data!AX$2:AX$368,$A140)} -> 13
A141: 126 | B141: 45417 | C141: 2024 | D141: MAY | E141: 5 | F141: {=INDEX(Data!B$2:B$368,$A141)} -> 987 | G141: {=INDEX(Data!C$2:C$368,$A141)} -> 952 | H141: {=INDEX(Data!D$2:D$368,$A141)} -> 503 | I141: {=INDEX(Data!E$2:E$368,$A141)} -> 376 | J141: {=INDEX(Data!F$2:F$368,$A141)} -> 108 | K141: {=INDEX(Data!G$2:G$368,$A141)} -> 495 | L141: {=INDEX(Data!H$2:H$368,$A141)} -> 258 | M141: {=INDEX(Data!I$2:I$368,$A141)} -> 199 | ... BB141: {=INDEX(Data!AX$2:AX$368,$A141)} -> 58
A142: 127 | B142: 45418 | C142: 2024 | D142: MAY | E142: 6 | F142: {=INDEX(Data!B$2:B$368,$A142)} -> 971 | G142: {=INDEX(Data!C$2:C$368,$A142)} -> 927 | H142: {=INDEX(Data!D$2:D$368,$A142)} -> 446 | I142: {=INDEX(Data!E$2:E$368,$A142)} -> 409 | J142: {=INDEX(Data!F$2:F$368,$A142)} -> 116 | K142: {=INDEX(Data!G$2:G$368,$A142)} -> 333 | L142: {=INDEX(Data!H$2:H$368,$A142)} -> 520 | M142: {=INDEX(Data!I$2:I$368,$A142)} -> 74 | ... BB142: {=INDEX(Data!AX$2:AX$368,$A142)} -> 0
A143: 128 | B143: 45419 | C143: 2024 | D143: MAY | E143: 7 | F143: {=INDEX(Data!B$2:B$368,$A143)} -> 946 | G143: {=INDEX(Data!C$2:C$368,$A143)} -> 900 | H143: {=INDEX(Data!D$2:D$368,$A143)} -> 340 | I143: {=INDEX(Data!E$2:E$368,$A143)} -> 408 | J143: {=INDEX(Data!F$2:F$368,$A143)} -> 198 | K143: {=INDEX(Data!G$2:G$368,$A143)} -> 324 | L143: {=INDEX(Data!H$2:H$368,$A143)} -> 414 | M143: {=INDEX(Data!I$2:I$368,$A143)} -> 162 | ... BB143: {=INDEX(Data!AX$2:AX$368,$A143)} -> 0
A144: 129 | B144: 45420 | C144: 2024 | D144: MAY | E144: 8 | F144: {=INDEX(Data!B$2:B$368,$A144)} -> 920 | G144: {=INDEX(Data!C$2:C$368,$A144)} -> 869 | H144: {=INDEX(Data!D$2:D$368,$A144)} -> 276 | I144: {=INDEX(Data!E$2:E$368,$A144)} -> 571 | J144: {=INDEX(Data!F$2:F$368,$A144)} -> 73 | K144: {=INDEX(Data!G$2:G$368,$A144)} -> 217 | L144: {=INDEX(Data!H$2:H$368,$A144)} -> 566 | M144: {=INDEX(Data!I$2:I$368,$A144)} -> 86 | ... BB144: {=INDEX(Data!AX$2:AX$368,$A144)} -> 64
A145: 130 | B145: 45421 | C145: 2024 | D145: MAY | E145: 9 | F145: {=INDEX(Data!B$2:B$368,$A145)} -> 900 | G145: {=INDEX(Data!C$2:C$368,$A145)} -> 836 | H145: {=INDEX(Data!D$2:D$368,$A145)} -> 333 | I145: {=INDEX(Data!E$2:E$368,$A145)} -> 423 | J145: {=INDEX(Data!F$2:F$368,$A145)} -> 144 | K145: {=INDEX(Data!G$2:G$368,$A145)} -> 250 | L145: {=INDEX(Data!H$2:H$368,$A145)} -> 503 | M145: {=INDEX(Data!I$2:I$368,$A145)} -> 83 | ... BB145: {=INDEX(Data!AX$2:AX$368,$A145)} -> 96
A146: 131 | B146: 45422 | C146: 2024 | D146: MAY | E146: 10 | F146: {=INDEX(Data!B$2:B$368,$A146)} -> 886 | G146: {=INDEX(Data!C$2:C$368,$A146)} -> 801 | H146: {=INDEX(Data!D$2:D$368,$A146)} -> 336 | I146: {=INDEX(Data!E$2:E$368,$A146)} -> 426 | J146: {=INDEX(Data!F$2:F$368,$A146)} -> 124 | K146: {=INDEX(Data!G$2:G$368,$A146)} -> 384 | L146: {=INDEX(Data!H$2:H$368,$A146)} -> 369 | M146: {=INDEX(Data!I$2:I$368,$A146)} -> 48 | ... BB146: {=INDEX(Data!AX$2:AX$368,$A146)} -> 0
A147: 132 | B147: 45423 | C147: 2024 | D147: MAY | E147: 11 | F147: {=INDEX(Data!B$2:B$368,$A147)} -> 883 | G147: {=INDEX(Data!C$2:C$368,$A147)} -> 770 | H147: {=INDEX(Data!D$2:D$368,$A147)} -> 317 | I147: {=INDEX(Data!E$2:E$368,$A147)} -> 372 | J147: {=INDEX(Data!F$2:F$368,$A147)} -> 194 | K147: {=INDEX(Data!G$2:G$368,$A147)} -> 292 | L147: {=INDEX(Data!H$2:H$368,$A147)} -> 440 | M147: {=INDEX(Data!I$2:I$368,$A147)} -> 38 | ... BB147: {=INDEX(Data!AX$2:AX$368,$A147)} -> 0
A148: 133 | B148: 45424 | C148: 2024 | D148: MAY | E148: 12 | F148: {=INDEX(Data!B$2:B$368,$A148)} -> 882 | G148: {=INDEX(Data!C$2:C$368,$A148)} -> 737 | H148: {=INDEX(Data!D$2:D$368,$A148)} -> 379 | I148: {=INDEX(Data!E$2:E$368,$A148)} -> 283 | J148: {=INDEX(Data!F$2:F$368,$A148)} -> 220 | K148: {=INDEX(Data!G$2:G$368,$A148)} -> 353 | L148: {=INDEX(Data!H$2:H$368,$A148)} -> 244 | M148: {=INDEX(Data!I$2:I$368,$A148)} -> 140 | ... BB148: {=INDEX(Data!AX$2:AX$368,$A148)} -> 72
... A167: 152 | B167: 45443 | C167: 2024 | D167: MAY | E167: 31 | F167: {=INDEX(Data!B$2:B$368,$A167)} -> 1131 | G167: {=INDEX(Data!C$2:C$368,$A167)} -> 913 | H167: {=INDEX(Data!D$2:D$368,$A167)} -> 294 | I167: {=INDEX(Data!E$2:E$368,$A167)} -> 679 | J167: {=INDEX(Data!F$2:F$368,$A167)} -> 158 | K167: {=INDEX(Data!G$2:G$368,$A167)} -> 365 | L167: {=INDEX(Data!H$2:H$368,$A167)} -> 475 | M167: {=INDEX(Data!I$2:I$368,$A167)} -> 73 | ... BB167: {=INDEX(Data!AX$2:AX$368,$A167)} -> 91
A168: 367 | C168: 2024 | D168: JUNE | E168: 0.01 | F168: {=INDEX(Data!B$2:B$368,$A168)} -> 0 | G168: {=INDEX(Data!C$2:C$368,$A168)} -> 0 | H168: {=INDEX(Data!D$2:D$368,$A168)} -> 0 | I168: {=INDEX(Data!E$2:E$368,$A168)} -> 0 | J168: {=INDEX(Data!F$2:F$368,$A168)} -> 0 | K168: {=INDEX(Data!G$2:G$368,$A168)} -> 0 | L168: {=INDEX(Data!H$2:H$368,$A168)} -> 0 | M168: {=INDEX(Data!I$2:I$368,$A168)} -> 0 | ... BB168: {=INDEX(Data!AX$2:AX$368,$A168)} -> 0
A169: 367 | C169: 2024 | D169: JUNE | E169: 0.02 | F169: {=INDEX(Data!B$2:B$368,$A169)} -> 0 | G169: {=INDEX(Data!C$2:C$368,$A169)} -> 0 | H169: {=INDEX(Data!D$2:D$368,$A169)} -> 0 | I169: {=INDEX(Data!E$2:E$368,$A169)} -> 0 | J169: {=INDEX(Data!F$2:F$368,$A169)} -> 0 | K169: {=INDEX(Data!G$2:G$368,$A169)} -> 0 | L169: {=INDEX(Data!H$2:H$368,$A169)} -> 0 | M169: {=INDEX(Data!I$2:I$368,$A169)} -> 0 | ... BB169: {=INDEX(Data!AX$2:AX$368,$A169)} -> 0
A170: 367 | C170: 2024 | D170: JUNE | E170: 0.03 | F170: {=INDEX(Data!B$2:B$368,$A170)} -> 0 | G170: {=INDEX(Data!C$2:C$368,$A170)} -> 0 | H170: {=INDEX(Data!D$2:D$368,$A170)} -> 0 | I170: {=INDEX(Data!E$2:E$368,$A170)} -> 0 | J170: {=INDEX(Data!F$2:F$368,$A170)} -> 0 | K170: {=INDEX(Data!G$2:G$368,$A170)} -> 0 | L170: {=INDEX(Data!H$2:H$368,$A170)} -> 0 | M170: {=INDEX(Data!I$2:I$368,$A170)} -> 0 | ... BB170: {=INDEX(Data!AX$2:AX$368,$A170)} -> 0
A171: 367 | C171: 2024 | D171: JUNE | E171: 0.04 | F171: {=INDEX(Data!B$2:B$368,$A171)} -> 0 | G171: {=INDEX(Data!C$2:C$368,$A171)} -> 0 | H171: {=INDEX(Data!D$2:D$368,$A171)} -> 0 | I171: {=INDEX(Data!E$2:E$368,$A171)} -> 0 | J171: {=INDEX(Data!F$2:F$368,$A171)} -> 0 | K171: {=INDEX(Data!G$2:G$368,$A171)} -> 0 | L171: {=INDEX(Data!H$2:H$368,$A171)} -> 0 | M171: {=INDEX(Data!I$2:I$368,$A171)} -> 0 | ... BB171: {=INDEX(Data!AX$2:AX$368,$A171)} -> 0
A172: 367 | C172: 2024 | D172: JUNE | E172: 0.05 | F172: {=INDEX(Data!B$2:B$368,$A172)} -> 0 | G172: {=INDEX(Data!C$2:C$368,$A172)} -> 0 | H172: {=INDEX(Data!D$2:D$368,$A172)} -> 0 | I172: {=INDEX(Data!E$2:E$368,$A172)} -> 0 | J172: {=INDEX(Data!F$2:F$368,$A172)} -> 0 | K172: {=INDEX(Data!G$2:G$368,$A172)} -> 0 | L172: {=INDEX(Data!H$2:H$368,$A172)} -> 0 | M172: {=INDEX(Data!I$2:I$368,$A172)} -> 0 | ... BB172: {=INDEX(Data!AX$2:AX$368,$A172)} -> 0
A173: 367 | C173: 2024 | D173: JUNE | E173: 0.06 | F173: {=INDEX(Data!B$2:B$368,$A173)} -> 0 | G173: {=INDEX(Data!C$2:C$368,$A173)} -> 0 | H173: {=INDEX(Data!D$2:D$368,$A173)} -> 0 | I173: {=INDEX(Data!E$2:E$368,$A173)} -> 0 | J173: {=INDEX(Data!F$2:F$368,$A173)} -> 0 | K173: {=INDEX(Data!G$2:G$368,$A173)} -> 0 | L173: {=INDEX(Data!H$2:H$368,$A173)} -> 0 | M173: {=INDEX(Data!I$2:I$368,$A173)} -> 0 | ... BB173: {=INDEX(Data!AX$2:AX$368,$A173)} -> 0
A174: 153 | B174: 45444 | C174: 2024 | D174: JUNE | E174: 1 | F174: {=INDEX(Data!B$2:B$368,$A174)} -> 1117 | G174: {=INDEX(Data!C$2:C$368,$A174)} -> 833 | H174: {=INDEX(Data!D$2:D$368,$A174)} -> 569 | I174: {=INDEX(Data!E$2:E$368,$A174)} -> 314 | J174: {=INDEX(Data!F$2:F$368,$A174)} -> 234 | K174: {=INDEX(Data!G$2:G$368,$A174)} -> 166 | L174: {=INDEX(Data!H$2:H$368,$A174)} -> 626 | M174: {=INDEX(Data!I$2:I$368,$A174)} -> 41 | ... BB174: {=INDEX(Data!AX$2:AX$368,$A174)} -> 0
A175: 154 | B175: 45445 | C175: 2024 | D175: JUNE | E175: 2 | F175: {=INDEX(Data!B$2:B$368,$A175)} -> 1093 | G175: {=INDEX(Data!C$2:C$368,$A175)} -> 846 | H175: {=INDEX(Data!D$2:D$368,$A175)} -> 327 | I175: {=INDEX(Data!E$2:E$368,$A175)} -> 635 | J175: {=INDEX(Data!F$2:F$368,$A175)} -> 131 | K175: {=INDEX(Data!G$2:G$368,$A175)} -> 253 | L175: {=INDEX(Data!H$2:H$368,$A175)} -> 526 | M175: {=INDEX(Data!I$2:I$368,$A175)} -> 67 | ... BB175: {=INDEX(Data!AX$2:AX$368,$A175)} -> 151
A176: 155 | B176: 45446 | C176: 2024 | D176: JUNE | E176: 3 | F176: {=INDEX(Data!B$2:B$368,$A176)} -> 1063 | G176: {=INDEX(Data!C$2:C$368,$A176)} -> 856 | H176: {=INDEX(Data!D$2:D$368,$A176)} -> 255 | I176: {=INDEX(Data!E$2:E$368,$A176)} -> 575 | J176: {=INDEX(Data!F$2:F$368,$A176)} -> 233 | K176: {=INDEX(Data!G$2:G$368,$A176)} -> 222 | L176: {=INDEX(Data!H$2:H$368,$A176)} -> 583 | M176: {=INDEX(Data!I$2:I$368,$A176)} -> 51 | ... BB176: {=INDEX(Data!AX$2:AX$368,$A176)} -> 26
A177: 156 | B177: 45447 | C177: 2024 | D177: JUNE | E177: 4 | F177: {=INDEX(Data!B$2:B$368,$A177)} -> 1045 | G177: {=INDEX(Data!C$2:C$368,$A177)} -> 859 | H177: {=INDEX(Data!D$2:D$368,$A177)} -> 292 | I177: {=INDEX(Data!E$2:E$368,$A177)} -> 555 | J177: {=INDEX(Data!F$2:F$368,$A177)} -> 198 | K177: {=INDEX(Data!G$2:G$368,$A177)} -> 300 | L177: {=INDEX(Data!H$2:H$368,$A177)} -> 448 | M177: {=INDEX(Data!I$2:I$368,$A177)} -> 111 | ... BB177: {=INDEX(Data!AX$2:AX$368,$A177)} -> 125
A178: 157 | B178: 45448 | C178: 2024 | D178: JUNE | E178: 5 | F178: {=INDEX(Data!B$2:B$368,$A178)} -> 1035 | G178: {=INDEX(Data!C$2:C$368,$A178)} -> 860 | H178: {=INDEX(Data!D$2:D$368,$A178)} -> 227 | I178: {=INDEX(Data!E$2:E$368,$A178)} -> 674 | J178: {=INDEX(Data!F$2:F$368,$A178)} -> 134 | K178: {=INDEX(Data!G$2:G$368,$A178)} -> 378 | L178: {=INDEX(Data!H$2:H$368,$A178)} -> 336 | M178: {=INDEX(Data!I$2:I$368,$A178)} -> 146 | ... BB178: {=INDEX(Data!AX$2:AX$368,$A178)} -> 3
A179: 158 | B179: 45449 | C179: 2024 | D179: JUNE | E179: 6 | F179: {=INDEX(Data!B$2:B$368,$A179)} -> 1031 | G179: {=INDEX(Data!C$2:C$368,$A179)} -> 858 | H179: {=INDEX(Data!D$2:D$368,$A179)} -> 257 | I179: {=INDEX(Data!E$2:E$368,$A179)} -> 661 | J179: {=INDEX(Data!F$2:F$368,$A179)} -> 113 | K179: {=INDEX(Data!G$2:G$368,$A179)} -> 420 | L179: {=INDEX(Data!H$2:H$368,$A179)} -> 224 | M179: {=INDEX(Data!I$2:I$368,$A179)} -> 214 | ... BB179: {=INDEX(Data!AX$2:AX$368,$A179)} -> 167
A180: 159 | B180: 45450 | C180: 2024 | D180: JUNE | E180: 7 | F180: {=INDEX(Data!B$2:B$368,$A180)} -> 1037 | G180: {=INDEX(Data!C$2:C$368,$A180)} -> 843 | H180: {=INDEX(Data!D$2:D$368,$A180)} -> 466 | I180: {=INDEX(Data!E$2:E$368,$A180)} -> 343 | J180: {=INDEX(Data!F$2:F$368,$A180)} -> 228 | K180: {=INDEX(Data!G$2:G$368,$A180)} -> 337 | L180: {=INDEX(Data!H$2:H$368,$A180)} -> 372 | M180: {=INDEX(Data!I$2:I$368,$A180)} -> 134 | ... BB180: {=INDEX(Data!AX$2:AX$368,$A180)} -> 123
A181: 160 | B181: 45451 | C181: 2024 | D181: JUNE | E181: 8 | F181: {=INDEX(Data!B$2:B$368,$A181)} -> 1056 | G181: {=INDEX(Data!C$2:C$368,$A181)} -> 826 | H181: {=INDEX(Data!D$2:D$368,$A181)} -> 464 | I181: {=INDEX(Data!E$2:E$368,$A181)} -> 424 | J181: {=INDEX(Data!F$2:F$368,$A181)} -> 168 | K181: {=INDEX(Data!G$2:G$368,$A181)} -> 396 | L181: {=INDEX(Data!H$2:H$368,$A181)} -> 381 | M181: {=INDEX(Data!I$2:I$368,$A181)} -> 49 | ... BB181: {=INDEX(Data!AX$2:AX$368,$A181)} -> 0
A182: 161 | B182: 45452 | C182: 2024 | D182: JUNE | E182: 9 | F182: {=INDEX(Data!B$2:B$368,$A182)} -> 1082 | G182: {=INDEX(Data!C$2:C$368,$A182)} -> 800 | H182: {=INDEX(Data!D$2:D$368,$A182)} -> 335 | I182: {=INDEX(Data!E$2:E$368,$A182)} -> 574 | J182: {=INDEX(Data!F$2:F$368,$A182)} -> 173 | K182: {=INDEX(Data!G$2:G$368,$A182)} -> 240 | L182: {=INDEX(Data!H$2:H$368,$A182)} -> 448 | M182: {=INDEX(Data!I$2:I$368,$A182)} -> 112 | ... BB182: {=INDEX(Data!AX$2:AX$368,$A182)} -> 64
A183: 162 | B183: 45453 | C183: 2024 | D183: JUNE | E183: 10 | F183: {=INDEX(Data!B$2:B$368,$A183)} -> 1095 | G183: {=INDEX(Data!C$2:C$368,$A183)} -> 772 | H183: {=INDEX(Data!D$2:D$368,$A183)} -> 569 | I183: {=INDEX(Data!E$2:E$368,$A183)} -> 472 | J183: {=INDEX(Data!F$2:F$368,$A183)} -> 54 | K183: {=INDEX(Data!G$2:G$368,$A183)} -> 293 | L183: {=INDEX(Data!H$2:H$368,$A183)} -> 402 | M183: {=INDEX(Data!I$2:I$368,$A183)} -> 77 | ... BB183: {=INDEX(Data!AX$2:AX$368,$A183)} -> 52
A184: 163 | B184: 45454 | C184: 2024 | D184: JUNE | E184: 11 | F184: {=INDEX(Data!B$2:B$368,$A184)} -> 1101 | G184: {=INDEX(Data!C$2:C$368,$A184)} -> 749 | H184: {=INDEX(Data!D$2:D$368,$A184)} -> 319 | I184: {=INDEX(Data!E$2:E$368,$A184)} -> 617 | J184: {=INDEX(Data!F$2:F$368,$A184)} -> 165 | K184: {=INDEX(Data!G$2:G$368,$A184)} -> 367 | L184: {=INDEX(Data!H$2:H$368,$A184)} -> 263 | M184: {=INDEX(Data!I$2:I$368,$A184)} -> 119 | ... BB184: {=INDEX(Data!AX$2:AX$368,$A184)} -> 35
A185: 164 | B185: 45455 | C185: 2024 | D185: JUNE | E185: 12 | F185: {=INDEX(Data!B$2:B$368,$A185)} -> 1101 | G185: {=INDEX(Data!C$2:C$368,$A185)} -> 730 | H185: {=INDEX(Data!D$2:D$368,$A185)} -> 462 | I185: {=INDEX(Data!E$2:E$368,$A185)} -> 518 | J185: {=INDEX(Data!F$2:F$368,$A185)} -> 121 | K185: {=INDEX(Data!G$2:G$368,$A185)} -> 379 | L185: {=INDEX(Data!H$2:H$368,$A185)} -> 286 | M185: {=INDEX(Data!I$2:I$368,$A185)} -> 65 | ... BB185: {=INDEX(Data!AX$2:AX$368,$A185)} -> 0
... A203: 182 | B203: 45473 | C203: 2024 | D203: JUNE | E203: 30 | F203: {=INDEX(Data!B$2:B$368,$A203)} -> 951 | G203: {=INDEX(Data!C$2:C$368,$A203)} -> 809 | H203: {=INDEX(Data!D$2:D$368,$A203)} -> 408 | I203: {=INDEX(Data!E$2:E$368,$A203)} -> 467 | J203: {=INDEX(Data!F$2:F$368,$A203)} -> 76 | K203: {=INDEX(Data!G$2:G$368,$A203)} -> 428 | L203: {=INDEX(Data!H$2:H$368,$A203)} -> 244 | M203: {=INDEX(Data!I$2:I$368,$A203)} -> 137 | ... BB203: {=INDEX(Data!AX$2:AX$368,$A203)} -> 0
A204: 367 | C204: 2024 | D204: JULY | E204: 0.01 | F204: {=INDEX(Data!B$2:B$368,$A204)} -> 0 | G204: {=INDEX(Data!C$2:C$368,$A204)} -> 0 | H204: {=INDEX(Data!D$2:D$368,$A204)} -> 0 | I204: {=INDEX(Data!E$2:E$368,$A204)} -> 0 | J204: {=INDEX(Data!F$2:F$368,$A204)} -> 0 | K204: {=INDEX(Data!G$2:G$368,$A204)} -> 0 | L204: {=INDEX(Data!H$2:H$368,$A204)} -> 0 | M204: {=INDEX(Data!I$2:I$368,$A204)} -> 0 | ... BB204: {=INDEX(Data!AX$2:AX$368,$A204)} -> 0
...

Sheet Data
A1: Date | B1: Income | C1: Expenses | D1: Non-Fixed Incom | E1: Fixed Incom | F1: Other Income | G1: Non-Fixed Cost | H1: Fixed Costs | I1: Other Cost | J1: Fixed Incom Business | K1: Fixed Incom Securities | L1: Fixed Incom Real estate | M1: Fixed Incom Gold | N1: Fixed Incom Cryptocurrency | O1: Non-Fixed Incom Business | P1: Non-Fixed Incom Securities | Q1: Non-Fixed Incom Real estate | R1: Non-Fixed Incom Gold | S1: Non-Fixed Incom Cryptocurrency | T1: Loans | U1: Training courses | V1: Travel public transport | W1: Mobile connection | X1: Food | Y1: Utility Payments | Z1: Internet & TV | AA1: Household chemicals | AB1: Furniture & utensils | AC1: BedLinen & tablecloth | AD1: Cat food | AE1: Clothing & footwear | AF1: Gym | AG1: Hygiene products | AH1: Medications | AI1: Hairdresser | AJ1: Cosmetics & perfum | AK1: Fuel | AL1: Spare parts | AM1: Parking | AN1: Washing | AO1: Insurance | AP1: Holidays | AQ1: Excursions | AR1: Restaurants | AS1: Gotheli | AT1: Bags, packages, boxes | AU1: Snacks on the way | AV1: Alcohol | AW1: Hobby | AX1: Unexpected expenses | AY1: Price Investments Portfolio | AZ1: Investments Business | BA1: Investments Securities | BB1: Investments Cryptocurrency | BC1: Investments Real estate | BD1: Investments Gold | BE1: Mortgage | BF1: Car Leasing | BG1: Consumer Credit | BH1: Credit Card | BI1: Goal 1 | BJ1: Goal 2 | BK1: Goal 3 | BL1: Goal 4 | BM1: Monthly Plan | BN1: Balance
A2: 45292 | B2: 496 | C2: 575 | D2: 243 | E2: 189 | F2: 64 | G2: 172 | H2: 271 | I2: 132 | J2: 104 | K2: 58 | L2: 27 | M2: 46 | N2: 9 | O2: 82 | P2: 62 | Q2: 22 | R2: 24 | S2: 62 | T2: 46 | U2: 0 | V2: 23 | W2: 11 | X2: 34 | Y2: 34 | Z2: 11 | AA2: 5 | AB2: 28 | AC2: 0 | AD2: 0 | AE2: 5 | AF2: 5 | AG2: 17 | AH2: 17 | AI2: 23 | AJ2: 34 | AK2: 11 | AL2: 17 | AM2: 0 | AN2: 0 | AO2: 17 | AP2: 51 | AQ2: 5 | AR2: 17 | AS2: 11 | AT2: 5 | AU2: 17 | AV2: 0 | AW2: 17 | AX2: 114 | AY2: 0 | AZ2: 0 | BA2: 0 | BB2: 0 | BC2: 0 | BD2: 0 | BE2: 50000 | BF2: 20000 | BG2: 8000 | BH2: 25000 | BI2: 11891 | BJ2: 3480 | BK2: 4930 | BL2: 1741 | BM2: 29000 | BN2: 3796
A3: 45293 | B3: 516 | C3: 585 | D3: 268 | E3: 218 | F3: 30 | G3: 286 | H3: 259 | I3: 40 | J3: 118 | K3: 19 | L3: 38 | M3: 19 | N3: 6 | O3: 88 | P3: 27 | Q3: 19 | R3: 29 | S3: 153 | T3: 76 | U3: 17 | V3: 29 | W3: 0 | X3: 46 | Y3: 29 | Z3: 0 | AA3: 17 | AB3: 29 | AC3: 11 | AD3: 5 | AE3: 23 | AF3: 11 | AG3: 0 | AH3: 0 | AI3: 23 | AJ3: 23 | AK3: 5 | AL3: 11 | AM3: 5 | AN3: 17 | AO3: 17 | AP3: 64 | AQ3: 17 | AR3: 40 | AS3: 29 | AT3: 0 | AU3: 23 | AV3: 11 | AW3: 5 | AX3: 2 | AY3: 0 | AZ3: 0 | BA3: 0 | BB3: 0 | BC3: 0 | BD3: 0 | BE3: 50000 | BF3: 20000 | BG3: 8000 | BH3: 25000 | BI3: 11891 | BJ3: 3480 | BK3: 4930 | BL3: 1741 | BM3: 29000 | BN3: 4881
A4: 45294 | B4: 539 | C4: 610 | D4: 285 | E4: 131 | F4: 123 | G4: 244 | H4: 318 | I4: 48 | J4: 177 | K4: 106 | L4: 23 | M4: 16 | N4: 20 | O4: 83 | P4: 18 | Q4: 28 | R4: 28 | S4: 40 | T4: 61 | U4: 6 | V4: 36 | W4: 6 | X4: 61 | Y4: 48 | Z4: 0 | AA4: 18 | AB4: 36 | AC4: 6 | AD4: 6 | AE4: 24 | AF4: 12 | AG4: 12 | AH4: 12 | AI4: 54 | AJ4: 30 | AK4: 30 | AL4: 18 | AM4: 6 | AN4: 6 | AO4: 24 | AP4: 0 | AQ4: 18 | AR4: 14 | AS4: 24 | AT4: 0 | AU4: 30 | AV4: 12 | AW4: 0 | AX4: 0 | AY4: 0 | AZ4: 0 | BA4: 0 | BB4: 0 | BC4: 0 | BD4: 0 | BE4: 50000 | BF4: 20000 | BG4: 8000 | BH4: 25000 | BI4: 11891 | BJ4: 3480 | BK4: 4930 | BL4: 1741 | BM4: 29000 | BN4: 4766
A5: 45295 | B5: 557 | C5: 641 | D5: 150 | E5: 307 | F5: 100 | G5: 262 | H5: 219 | I5: 160 | J5: 176 | K5: 69 | L5: 31 | M5: 24 | N5: 31 | O5: 103 | P5: 52 | Q5: 27 | R5: 29 | S5: 15 | T5: 44 | U5: 12 | V5: 38 | W5: 6 | X5: 44 | Y5: 57 | Z5: 19 | AA5: 0 | AB5: 38 | AC5: 6 | AD5: 0 | AE5: 19 | AF5: 19 | AG5: 19 | AH5: 0 | AI5: 38 | AJ5: 19 | AK5: 32 | AL5: 12 | AM5: 6 | AN5: 12 | AO5: 6 | AP5: 57 | AQ5: 19 | AR5: 25 | AS5: 19 | AT5: 6 | AU5: 19 | AV5: 19 | AW5: 19 | AX5: 12 | AY5: 0 | AZ5: 0 | BA5: 0 | BB5: 0 | BC5: 0 | BD5: 0 | BE5: 50000 | BF5: 20000 | BG5: 8000 | BH5: 25000 | BI5: 11891 | BJ5: 3480 | BK5: 4930 | BL5: 1741 | BM5: 29000 | BN5: 788
A6: 45296 | B6: 575 | C6: 667 | D6: 132 | E6: 415 | F6: 28 | G6: 153 | H6: 374 | I6: 140 | J6: 171 | K6: 99 | L6: 42 | M6: 35 | N6: 21 | O6: 93 | P6: 43 | Q6: 24 | R6: 21 | S6: 26 | T6: 60 | U6: 0 | V6: 46 | W6: 20 | X6: 93 | Y6: 53 | Z6: 20 | AA6: 0 | AB6: 13 | AC6: 20 | AD6: 0 | AE6: 6 | AF6: 13 | AG6: 0 | AH6: 0 | AI6: 26 | AJ6: 46 | AK6: 13 | AL6: 0 | AM6: 0 | AN6: 26 | AO6: 20 | AP6: 73 | AQ6: 6 | AR6: 20 | AS6: 20 | AT6: 0 | AU6: 26 | AV6: 0 | AW6: 20 | AX6: 27 | AY6: 0 | AZ6: 0 | BA6: 0 | BB6: 0 | BC6: 0 | BD6: 0 | BE6: 50000 | BF6: 20000 | BG6: 8000 | BH6: 23668 | BI6: 11891 | BJ6: 3480 | BK6: 4930 | BL6: 1741 | BM6: 29000 | BN6: 4853
A7: 45297 | B7: 586 | C7: 685 | D7: 175 | E7: 335 | F7: 76 | G7: 212 | H7: 336 | I7: 137 | J7: 134 | K7: 21 | L7: 47 | M7: 29 | N7: 14 | O7: 120 | P7: 77 | Q7: 28 | R7: 11 | S7: 105 | T7: 75 | U7: 6 | V7: 34 | W7: 13 | X7: 63 | Y7: 47 | Z7: 20 | AA7: 0 | AB7: 34 | AC7: 6 | AD7: 0 | AE7: 27 | AF7: 0 | AG7: 6 | AH7: 13 | AI7: 47 | AJ7: 47 | AK7: 27 | AL7: 6 | AM7: 0 | AN7: 6 | AO7: 13 | AP7: 68 | AQ7: 13 | AR7: 34 | AS7: 13 | AT7: 6 | AU7: 41 | AV7: 0 | AW7: 20 | AX7: 0 | AY7: 0 | AZ7: 0 | BA7: 0 | BB7: 0 | BC7: 0 | BD7: 0 | BE7: 50000 | BF7: 20000 | BG7: 8000 | BH7: 23668 | BI7: 11891 | BJ7: 3480 | BK7: 4930 | BL7: 1741 | BM7: 29000 | BN7: 3534
A8: 45298 | B8: 597 | C8: 690 | D8: 310 | E8: 162 | F8: 125 | G8: 282 | H8: 353 | I8: 55 | J8: 166 | K8: 122 | L8: 37 | M8: 22 | N8: 18 | O8: 77 | P8: 74 | Q8: 27 | R8: 34 | S8: 20 | T8: 75 | U8: 0 | V8: 27 | W8: 6 | X8: 75 | Y8: 48 | Z8: 6 | AA8: 13 | AB8: 41 | AC8: 20 | AD8: 0 | AE8: 6 | AF8: 20 | AG8: 0 | AH8: 13 | AI8: 48 | AJ8: 6 | AK8: 6 | AL8: 0 | AM8: 0 | AN8: 13 | AO8: 6 | AP8: 55 | AQ8: 6 | AR8: 48 | AS8: 6 | AT8: 6 | AU8: 20 | AV8: 0 | AW8: 0 | AX8: 120 | AY8: 0 | AZ8: 0 | BA8: 0 | BB8: 0 | BC8: 0 | BD8: 0 | BE8: 50000 | BF8: 20000 | BG8: 8000 | BH8: 23668 | BI8: 11891 | BJ8: 3480 | BK8: 4930 | BL8: 1741 | BM8: 29000 | BN8: 7918
A9: 45299 | B9: 604 | C9: 684 | D9: 217 | E9: 273 | F9: 114 | G9: 307 | H9: 316 | I9: 61 | J9: 149 | K9: 101 | L9: 48 | M9: 37 | N9: 7 | O9: 126 | P9: 59 | Q9: 25 | R9: 11 | S9: 41 | T9: 54 | U9: 13 | V9: 47 | W9: 13 | X9: 9 | Y9: 54 | Z9: 13 | AA9: 20 | AB9: 13 | AC9: 13 | AD9: 0 | AE9: 34 | AF9: 20 | AG9: 6 | AH9: 20 | AI9: 41 | AJ9: 34 | AK9: 34 | AL9: 20 | AM9: 6 | AN9: 13 | AO9: 13 | AP9: 61 | AQ9: 13 | AR9: 27 | AS9: 34 | AT9: 6 | AU9: 41 | AV9: 6 | AW9: 6 | AX9: 0 | AY9: 0 | AZ9: 0 | BA9: 0 | BB9: 0 | BC9: 0 | BD9: 0 | BE9: 50000 | BF9: 20000 | BG9: 8000 | BH9: 23668 | BI9: 11891 | BJ9: 3480 | BK9: 4930 | BL9: 1741 | BM9: 29000 | BN9: 520
A10: 45300 | B10: 606 | C10: 664 | D10: 284 | E10: 262 | F10: 60 | G10: 232 | H10: 346 | I10: 86 | J10: 157 | K10: 127 | L10: 56 | M10: 26 | N10: 33 | O10: 89 | P10: 64 | Q10: 20 | R10: 34 | S10: 0 | T10: 86 | U10: 0 | V10: 19 | W10: 19 | X10: 59 | Y10: 59 | Z10: 19 | AA10: 6 | AB10: 39 | AC10: 0 | AD10: 0 | AE10: 19 | AF10: 19 | AG10: 19 | AH10: 6 | AI10: 46 | AJ10: 6 | AK10: 26 | AL10: 0 | AM10: 6 | AN10: 19 | AO10: 13 | AP10: 66 | AQ10: 19 | AR10: 19 | AS10: 13 | AT10: 0 | AU10: 13 | AV10: 19 | AW10: 0 | AX10: 30 | AY10: 0 | AZ10: 0 | BA10: 0 | BB10: 0 | BC10: 0 | BD10: 0 | BE10: 50000 | BF10: 20000 | BG10: 8000 | BH10: 23668 | BI10: 11891 | BJ10: 3480 | BK10: 4930 | BL10: 1741 | BM10: 29000 | BN10: 6207
A11: 45301 | B11: 602 | C11: 625 | D11: 258 | E11: 314 | F11: 30 | G11: 131 | H11: 451 | I11: 43 | J11: 160 | K11: 97 | L11: 52 | M11: 18 | N11: 14 | O11: 86 | P11: 16 | Q11: 18 | R11: 13 | S11: 128 | T11: 25 | U11: 0 | V11: 43 | W11: 18 | X11: 75 | Y11: 56 | Z11: 18 | AA11: 0 | AB11: 12 | AC11: 0 | AD11: 0 | AE11: 6 | AF11: 6 | AG11: 0 | AH11: 6 | AI11: 43 | AJ11: 43 | AK11: 6 | AL11: 12 | AM11: 0 | AN11: 12 | AO11: 18 | AP11: 62 | AQ11: 12 | AR11: 50 | AS11: 31 | AT11: 0 | AU11: 25 | AV11: 0 | AW11: 12 | AX11: 34 | AY11: 0 | AZ11: 0 | BA11: 0 | BB11: 0 | BC11: 0 | BD11: 0 | BE11: 50000 | BF11: 20000 | BG11: 8000 | BH11: 23668 | BI11: 11891 | BJ11: 3480 | BK11: 4930 | BL11: 1741 | BM11: 29000 | BN11: 4999
A12: 45302 | B12: 584 | C12: 588 | D12: 186 | E12: 334 | F12: 64 | G12: 158 | H12: 313 | I12: 117 | J12: 188 | K12: 86 | L12: 36 | M12: 18 | N12: 18 | O12: 79 | P12: 17 | Q12: 33 | R12: 19 | S12: 90 | T12: 58 | U12: 0 | V12: 35 | W12: 17 | X12: 23 | Y12: 35 | Z12: 11 | AA12: 5 | AB12: 17 | AC12: 17 | AD12: 5 | AE12: 17 | AF12: 5 | AG12: 5 | AH12: 17 | AI12: 52 | AJ12: 23 | AK12: 23 | AL12: 11 | AM12: 0 | AN12: 23 | AO12: 17 | AP12: 41 | AQ12: 5 | AR12: 52 | AS12: 11 | AT12: 0 | AU12: 29 | AV12: 17 | AW12: 17 | AX12: 0 | AY12: 0 | AZ12: 0 | BA12: 0 | BB12: 0 | BC12: 0 | BD12: 0 | BE12: 50000 | BF12: 20000 | BG12: 8000 | BH12: 23668 | BI12: 11891 | BJ12: 3480 | BK12: 4930 | BL12: 1741 | BM12: 29000 | BN12: 1124
A13: 45303 | B13: 560 | C13: 575 | D13: 123 | E13: 348 | F13: 89 | G13: 149 | H13: 369 | I13: 57 | J13: 156 | K13: 27 | L13: 34 | M13: 24 | N13: 24 | O13: 85 | P13: 36 | Q13: 19 | R13: 29 | S13: 126 | T13: 63 | U13: 17 | V13: 40 | W13: 5 | X13: 33 | Y13: 51 | Z13: 17 | AA13: 17 | AB13: 11 | AC13: 5 | AD13: 0 | AE13: 17 | AF13: 11 | AG13: 17 | AH13: 0 | AI13: 28 | AJ13: 23 | AK13: 28 | AL13: 0 | AM13: 0 | AN13: 5 | AO13: 17 | AP13: 40 | AQ13: 17 | AR13: 51 | AS13: 11 | AT13: 0 | AU13: 11 | AV13: 17 | AW13: 23 | AX13: 0 | AY13: 0 | AZ13: 0 | BA13: 0 | BB13: 0 | BC13: 0 | BD13: 0 | BE13: 50000 | BF13: 10000 | BG13: 5000 | BH13: 12386 | BI13: 11891 | BJ13: 3480 | BK13: 4930 | BL13: 1741 | BM13: 29000 | BN13: 5206
... A367: 45657 | B367: 1140 | C367: 881 | D367: 319 | E367: 628 | F367: 193 | G367: 308 | H367: 415 | I367: 158 | J367: 348 | K367: 226 | L367: 63 | M367: 84 | N367: 35 | O367: 186 | P367: 95 | Q367: 60 | R367: 43 | S367: 0 | T367: 35 | U367: 0 | V367: 26 | W367: 0 | X367: 61 | Y367: 79 | Z367: 0 | AA367: 17 | AB367: 44 | AC367: 0 | AD367: 8 | AE367: 26 | AF367: 0 | AG367: 17 | AH367: 17 | AI367: 79 | AJ367: 61 | AK367: 17 | AL367: 0 | AM367: 0 | AN367: 8 | AO367: 26 | AP367: 61 | AQ367: 26 | AR367: 35 | AS367: 17 | AT367: 8 | AU367: 61 | AV367: 35 | AW367: 26 | AX367: 91 | AY367: 182062.56 | AZ367: 47336.27 | BA367: 41874.39 | BB367: 45515.64 | BC367: 45515.64 | BD367: 1820.63 | BE367: 8000 | BF367: 6250 | BG367: 3353 | BH367: 7058 | BI367: 75603 | BJ367: 63201 | BK367: 55501 | BL367: 30000 | BM367: 230000 | BN367: 8202
