Workbook
Name Slicer_Buttons: #N/A
Name Slicer_Buttons1: #N/A
Name Slicer_Month: #N/A
Name Slicer_Year: #N/A

Sheet DASHBOARD

Sheet DASHBOARD Light

Sheet Financial Goals

Sheet Financial Goals Light

Sheet Income Expenses

Sheet Income Expenses Light

Sheet Essential Costs

Sheet Essential Costs Light

Sheet Processing
C1: Target 1 | D1: Target 2 | E1: Target 3 | F1: Target 4 | G1: Target 5 | I1: Year | O1: Design Customization | S1: Budget | T1: Cost | U1: Budget Plan | V1: Years
A2: Number | B2: Month | H2: Cursor | I2: =MAX(Control!A52:A55) -> 2028 | J2: Targets | L2: Start | M2: Process | N2: End | O2: First | P2: Middle | Q2: Last | S2: {=SUM(W2:W5*U2:U5)} -> 50000 | T2: =SUM(F18:INDEX(F18:F29,I4)) -> 17954 | U2: 40000 | V2: 2027 | W2: =ISNUMBER(MATCH(V2,Control!$A$52:$A$55,0)) -> FALSE
A3: 1 | B3: JAN | C3: =GETPIVOTDATA(""&C$1,Control!$A$20,"Month",""&$B3) -> 400 | D3: =GETPIVOTDATA(""&D$1,Control!$A$20,"Month",""&$B3) -> 0 | E3: =GETPIVOTDATA(""&E$1,Control!$A$20,"Month",""&$B3) -> 0 | F3: =GETPIVOTDATA(""&F$1,Control!$A$20,"Month",""&$B3) -> 0 | G3: =GETPIVOTDATA(""&G$1,Control!$A$20,"Month",""&$B3) -> 0 | H3: =IF(ISNUMBER(GETPIVOTDATA("Num Month",Control!$A$3,"Month",""&B3)),100%,NA()) -> #N/A | I3: Month | J3: Target 1 | K3: =GETPIVOTDATA(""&J3,Control!$A$3) -> 0 | L3: {=COUNTIFS(INDEX($C$1:$G$1,1,A3):INDEX($C$2:$G$14,MATCH(TRUE,INDEX($C$2:$G$14,,A3)>0,0)-1,A3),0)+O3} -> 0.2 | M3: =COUNTIF(INDEX($C$3:$G$14,,A3),">0")-P3 -> 1.8 | N3: =12-SUM(L3:M3) -> 10 | O3: 0.2 | P3: 0.2 | Q3: 0 | S3: =1-T3 -> 0.64092 | T3: =T2/S2 -> 0.35908 | U3: 50000 | V3: 2028 | W3: =ISNUMBER(MATCH(V3,Control!$A$52:$A$55,0)) -> TRUE
A4: 2 | B4: FEB | C4: =GETPIVOTDATA(""&C$1,Control!$A$20,"Month",""&$B4) -> 400 | D4: =GETPIVOTDATA(""&D$1,Control!$A$20,"Month",""&$B4) -> 500 | E4: =GETPIVOTDATA(""&E$1,Control!$A$20,"Month",""&$B4) -> 0 | F4: =GETPIVOTDATA(""&F$1,Control!$A$20,"Month",""&$B4) -> 0 | G4: =GETPIVOTDATA(""&G$1,Control!$A$20,"Month",""&$B4) -> 0 | H4: =IF(ISNUMBER(GETPIVOTDATA("Num Month",Control!$A$3,"Month",""&B4)),100%,NA()) -> #N/A | I4: =GETPIVOTDATA("Max of Num Month",Control!$A$3) -> 6 | J4: Target 2 | K4: =GETPIVOTDATA(""&J4,Control!$A$3) -> 500 | L4: {=COUNTIFS(INDEX($C$1:$G$1,1,A4):INDEX($C$2:$G$14,MATCH(TRUE,INDEX($C$2:$G$14,,A4)>0,0)-1,A4),0)+O4} -> 1 | M4: =COUNTIF(INDEX($C$3:$G$14,,A4),">0")-P4 -> 3 | N4: =12-SUM(L4:M4) -> 8 | O4: 0 | P4: 0 | Q4: 0 | S4: Cursors | U4: 50000 | V4: 2029 | W4: =ISNUMBER(MATCH(V4,Control!$A$52:$A$55,0)) -> FALSE
A5: 3 | B5: MAR | C5: =GETPIVOTDATA(""&C$1,Control!$A$20,"Month",""&$B5) -> 0 | D5: =GETPIVOTDATA(""&D$1,Control!$A$20,"Month",""&$B5) -> 500 | E5: =GETPIVOTDATA(""&E$1,Control!$A$20,"Month",""&$B5) -> 0 | F5: =GETPIVOTDATA(""&F$1,Control!$A$20,"Month",""&$B5) -> 0 | G5: =GETPIVOTDATA(""&G$1,Control!$A$20,"Month",""&$B5) -> 0 | H5: =IF(ISNUMBER(GETPIVOTDATA("Num Month",Control!$A$3,"Month",""&B5)),100%,NA()) -> #N/A | I5: {=INDEX(B3:B14,I4)} -> JUN | J5: Target 3 | K5: =GETPIVOTDATA(""&J5,Control!$A$3) -> 1400 | L5: {=COUNTIFS(INDEX($C$1:$G$1,1,A5):INDEX($C$2:$G$14,MATCH(TRUE,INDEX($C$2:$G$14,,A5)>0,0)-1,A5),0)+O5} -> 3 | M5: =COUNTIF(INDEX($C$3:$G$14,,A5),">0")-P5 -> 2 | N5: =12-SUM(L5:M5) -> 7 | O5: 0 | P5: 0 | Q5: 0 | S5: X | T5: Y | U5: 60000 | V5: 2030 | W5: =ISNUMBER(MATCH(V5,Control!$A$52:$A$55,0)) -> FALSE
A6: 4 | B6: APR | C6: =GETPIVOTDATA(""&C$1,Control!$A$20,"Month",""&$B6) -> 0 | D6: =GETPIVOTDATA(""&D$1,Control!$A$20,"Month",""&$B6) -> 500 | E6: =GETPIVOTDATA(""&E$1,Control!$A$20,"Month",""&$B6) -> 700 | F6: =GETPIVOTDATA(""&F$1,Control!$A$20,"Month",""&$B6) -> 0 | G6: =GETPIVOTDATA(""&G$1,Control!$A$20,"Month",""&$B6) -> 0 | H6: =IF(ISNUMBER(GETPIVOTDATA("Num Month",Control!$A$3,"Month",""&B6)),100%,NA()) -> 1 | I6: Label | J6: Target 4 | K6: =GETPIVOTDATA(""&J6,Control!$A$3) -> 1000 | L6: {=COUNTIFS(INDEX($C$1:$G$1,1,A6):INDEX($C$2:$G$14,MATCH(TRUE,INDEX($C$2:$G$14,,A6)>0,0)-1,A6),0)+O6} -> 4 | M6: =COUNTIF(INDEX($C$3:$G$14,,A6),">0")-P6 -> 4 | N6: =12-SUM(L6:M6) -> 4 | O6: 0 | P6: 0 | Q6: 0 | S6: 0 | T6: 1
A7: 5 | B7: MAY | C7: =GETPIVOTDATA(""&C$1,Control!$A$20,"Month",""&$B7) -> 0 | D7: =GETPIVOTDATA(""&D$1,Control!$A$20,"Month",""&$B7) -> 0 | E7: =GETPIVOTDATA(""&E$1,Control!$A$20,"Month",""&$B7) -> 700 | F7: =GETPIVOTDATA(""&F$1,Control!$A$20,"Month",""&$B7) -> 500 | G7: =GETPIVOTDATA(""&G$1,Control!$A$20,"Month",""&$B7) -> 0 | H7: =IF(ISNUMBER(GETPIVOTDATA("Num Month",Control!$A$3,"Month",""&B7)),100%,NA()) -> 1 | I7: =B3&I8&B4&I8&B5&I8&B6&I8&B7&I8&B8&I8&B9&I8&B10&I8&B11&I8&B12&I8&B13&I8&B14 -> JAN FEB MAR APR MAY JUN JUL AUG SEP OCT NOV DEC | J7: Target 5 | K7: =GETPIVOTDATA(""&J7,Control!$A$3) -> 0 | L7: {=COUNTIFS(INDEX($C$1:$G$1,1,A7):INDEX($C$2:$G$14,MATCH(TRUE,INDEX($C$2:$G$14,,A7)>0,0)-1,A7),0)+O7} -> 7 | M7: =COUNTIF(INDEX($C$3:$G$14,,A7),">0")-P7 -> 4.8 | N7: =12-SUM(L7:M7) -> 0.2 | O7: 0 | P7: 0.2 | Q7: 0.2 | S7: =SIN(S3*2*PI()) -> -0.774185 | T7: =COS(T3*2*PI()) -> -0.63295939
A8: 6 | B8: JUN | C8: =GETPIVOTDATA(""&C$1,Control!$A$20,"Month",""&$B8) -> 0 | D8: =GETPIVOTDATA(""&D$1,Control!$A$20,"Month",""&$B8) -> 0 | E8: =GETPIVOTDATA(""&E$1,Control!$A$20,"Month",""&$B8) -> 0 | F8: =GETPIVOTDATA(""&F$1,Control!$A$20,"Month",""&$B8) -> 500 | G8: =GETPIVOTDATA(""&G$1,Control!$A$20,"Month",""&$B8) -> 0 | H8: =IF(ISNUMBER(GETPIVOTDATA("Num Month",Control!$A$3,"Month",""&B8)),100%,NA()) -> 1
A9: 7 | B9: JUL | C9: =GETPIVOTDATA(""&C$1,Control!$A$20,"Month",""&$B9) -> 0 | D9: =GETPIVOTDATA(""&D$1,Control!$A$20,"Month",""&$B9) -> 0 | E9: =GETPIVOTDATA(""&E$1,Control!$A$20,"Month",""&$B9) -> 0 | F9: =GETPIVOTDATA(""&F$1,Control!$A$20,"Month",""&$B9) -> 500 | G9: =GETPIVOTDATA(""&G$1,Control!$A$20,"Month",""&$B9) -> 0 | H9: =IF(ISNUMBER(GETPIVOTDATA("Num Month",Control!$A$3,"Month",""&B9)),100%,NA()) -> #N/A | J9: heatmap
A10: 8 | B10: AUG | C10: =GETPIVOTDATA(""&C$1,Control!$A$20,"Month",""&$B10) -> 0 | D10: =GETPIVOTDATA(""&D$1,Control!$A$20,"Month",""&$B10) -> 0 | E10: =GETPIVOTDATA(""&E$1,Control!$A$20,"Month",""&$B10) -> 0 | F10: =GETPIVOTDATA(""&F$1,Control!$A$20,"Month",""&$B10) -> 500 | G10: =GETPIVOTDATA(""&G$1,Control!$A$20,"Month",""&$B10) -> 300 | H10: =IF(ISNUMBER(GETPIVOTDATA("Num Month",Control!$A$3,"Month",""&B10)),100%,NA()) -> #N/A | J10: W/D | K10: 1 | L10: 2 | M10: 3 | N10: 4 | O10: 5 | P10: 6 | Q10: 7
A11: 9 | B11: SEP | C11: =GETPIVOTDATA(""&C$1,Control!$A$20,"Month",""&$B11) -> 0 | D11: =GETPIVOTDATA(""&D$1,Control!$A$20,"Month",""&$B11) -> 0 | E11: =GETPIVOTDATA(""&E$1,Control!$A$20,"Month",""&$B11) -> 0 | F11: =GETPIVOTDATA(""&F$1,Control!$A$20,"Month",""&$B11) -> 0 | G11: =GETPIVOTDATA(""&G$1,Control!$A$20,"Month",""&$B11) -> 300 | H11: =IF(ISNUMBER(GETPIVOTDATA("Num Month",Control!$A$3,"Month",""&B11)),100%,NA()) -> #N/A | J11: 1 | K11: {=INDEX('heatmap-DATA'!$D$2:$J$289,MATCH($I$2&$I$4&$J11,'heatmap-DATA'!$A$2:$A$289&'heatmap-DATA'!$B$2:$B$289&'heatmap-DATA'!$C$2:$C$289,0),COLUMN(A$1))} -> 1 | L11: {=INDEX('heatmap-DATA'!$D$2:$J$289,MATCH($I$2&$I$4&$J11,'heatmap-DATA'!$A$2:$A$289&'heatmap-DATA'!$B$2:$B$289&'heatmap-DATA'!$C$2:$C$289,0),COLUMN(B$1))} -> 1 | M11: {=INDEX('heatmap-DATA'!$D$2:$J$289,MATCH($I$2&$I$4&$J11,'heatmap-DATA'!$A$2:$A$289&'heatmap-DATA'!$B$2:$B$289&'heatmap-DATA'!$C$2:$C$289,0),COLUMN(C$1))} -> 1 | N11: {=INDEX('heatmap-DATA'!$D$2:$J$289,MATCH($I$2&$I$4&$J11,'heatmap-DATA'!$A$2:$A$289&'heatmap-DATA'!$B$2:$B$289&'heatmap-DATA'!$C$2:$C$289,0),COLUMN(D$1))} -> 1 | O11: {=INDEX('heatmap-DATA'!$D$2:$J$289,MATCH($I$2&$I$4&$J11,'heatmap-DATA'!$A$2:$A$289&'heatmap-DATA'!$B$2:$B$289&'heatmap-DATA'!$C$2:$C$289,0),COLUMN(E$1))} -> 3 | P11: {=INDEX('heatmap-DATA'!$D$2:$J$289,MATCH($I$2&$I$4&$J11,'heatmap-DATA'!$A$2:$A$289&'heatmap-DATA'!$B$2:$B$289&'heatmap-DATA'!$C$2:$C$289,0),COLUMN(F$1))} -> 2 | Q11: {=INDEX('heatmap-DATA'!$D$2:$J$289,MATCH($I$2&$I$4&$J11,'heatmap-DATA'!$A$2:$A$289&'heatmap-DATA'!$B$2:$B$289&'heatmap-DATA'!$C$2:$C$289,0),COLUMN(G$1))} -> 3
A12: 10 | B12: OCT | C12: =GETPIVOTDATA(""&C$1,Control!$A$20,"Month",""&$B12) -> 0 | D12: =GETPIVOTDATA(""&D$1,Control!$A$20,"Month",""&$B12) -> 0 | E12: =GETPIVOTDATA(""&E$1,Control!$A$20,"Month",""&$B12) -> 0 | F12: =GETPIVOTDATA(""&F$1,Control!$A$20,"Month",""&$B12) -> 0 | G12: =GETPIVOTDATA(""&G$1,Control!$A$20,"Month",""&$B12) -> 300 | H12: =IF(ISNUMBER(GETPIVOTDATA("Num Month",Control!$A$3,"Month",""&B12)),100%,NA()) -> #N/A | J12: 2 | K12: {=INDEX('heatmap-DATA'!$D$2:$J$289,MATCH($I$2&$I$4&$J12,'heatmap-DATA'!$A$2:$A$289&'heatmap-DATA'!$B$2:$B$289&'heatmap-DATA'!$C$2:$C$289,0),COLUMN(A$15))} -> 2 | L12: {=INDEX('heatmap-DATA'!$D$2:$J$289,MATCH($I$2&$I$4&$J12,'heatmap-DATA'!$A$2:$A$289&'heatmap-DATA'!$B$2:$B$289&'heatmap-DATA'!$C$2:$C$289,0),COLUMN(B$1))} -> 2 | M12: {=INDEX('heatmap-DATA'!$D$2:$J$289,MATCH($I$2&$I$4&$J12,'heatmap-DATA'!$A$2:$A$289&'heatmap-DATA'!$B$2:$B$289&'heatmap-DATA'!$C$2:$C$289,0),COLUMN(C$1))} -> 2 | N12: {=INDEX('heatmap-DATA'!$D$2:$J$289,MATCH($I$2&$I$4&$J12,'heatmap-DATA'!$A$2:$A$289&'heatmap-DATA'!$B$2:$B$289&'heatmap-DATA'!$C$2:$C$289,0),COLUMN(D$1))} -> 2 | O12: {=INDEX('heatmap-DATA'!$D$2:$J$289,MATCH($I$2&$I$4&$J12,'heatmap-DATA'!$A$2:$A$289&'heatmap-DATA'!$B$2:$B$289&'heatmap-DATA'!$C$2:$C$289,0),COLUMN(E$1))} -> 2 | P12: {=INDEX('heatmap-DATA'!$D$2:$J$289,MATCH($I$2&$I$4&$J12,'heatmap-DATA'!$A$2:$A$289&'heatmap-DATA'!$B$2:$B$289&'heatmap-DATA'!$C$2:$C$289,0),COLUMN(F$1))} -> 2 | Q12: {=INDEX('heatmap-DATA'!$D$2:$J$289,MATCH($I$2&$I$4&$J12,'heatmap-DATA'!$A$2:$A$289&'heatmap-DATA'!$B$2:$B$289&'heatmap-DATA'!$C$2:$C$289,0),COLUMN(G$1))} -> 3
A13: 11 | B13: NOV | C13: =GETPIVOTDATA(""&C$1,Control!$A$20,"Month",""&$B13) -> 0 | D13: =GETPIVOTDATA(""&D$1,Control!$A$20,"Month",""&$B13) -> 0 | E13: =GETPIVOTDATA(""&E$1,Control!$A$20,"Month",""&$B13) -> 0 | F13: =GETPIVOTDATA(""&F$1,Control!$A$20,"Month",""&$B13) -> 0 | G13: =GETPIVOTDATA(""&G$1,Control!$A$20,"Month",""&$B13) -> 300 | H13: =IF(ISNUMBER(GETPIVOTDATA("Num Month",Control!$A$3,"Month",""&B13)),100%,NA()) -> #N/A | J13: 3 | K13: {=INDEX('heatmap-DATA'!$D$2:$J$289,MATCH($I$2&$I$4&$J13,'heatmap-DATA'!$A$2:$A$289&'heatmap-DATA'!$B$2:$B$289&'heatmap-DATA'!$C$2:$C$289,0),COLUMN(A$15))} -> 3 | L13: {=INDEX('heatmap-DATA'!$D$2:$J$289,MATCH($I$2&$I$4&$J13,'heatmap-DATA'!$A$2:$A$289&'heatmap-DATA'!$B$2:$B$289&'heatmap-DATA'!$C$2:$C$289,0),COLUMN(B$1))} -> 2 | M13: {=INDEX('heatmap-DATA'!$D$2:$J$289,MATCH($I$2&$I$4&$J13,'heatmap-DATA'!$A$2:$A$289&'heatmap-DATA'!$B$2:$B$289&'heatmap-DATA'!$C$2:$C$289,0),COLUMN(C$1))} -> 3 | N13: {=INDEX('heatmap-DATA'!$D$2:$J$289,MATCH($I$2&$I$4&$J13,'heatmap-DATA'!$A$2:$A$289&'heatmap-DATA'!$B$2:$B$289&'heatmap-DATA'!$C$2:$C$289,0),COLUMN(D$1))} -> 3 | O13: {=INDEX('heatmap-DATA'!$D$2:$J$289,MATCH($I$2&$I$4&$J13,'heatmap-DATA'!$A$2:$A$289&'heatmap-DATA'!$B$2:$B$289&'heatmap-DATA'!$C$2:$C$289,0),COLUMN(E$1))} -> 3 | P13: {=INDEX('heatmap-DATA'!$D$2:$J$289,MATCH($I$2&$I$4&$J13,'heatmap-DATA'!$A$2:$A$289&'heatmap-DATA'!$B$2:$B$289&'heatmap-DATA'!$C$2:$C$289,0),COLUMN(F$1))} -> 2 | Q13: {=INDEX('heatmap-DATA'!$D$2:$J$289,MATCH($I$2&$I$4&$J13,'heatmap-DATA'!$A$2:$A$289&'heatmap-DATA'!$B$2:$B$289&'heatmap-DATA'!$C$2:$C$289,0),COLUMN(G$1))} -> 2
A14: 12 | B14: DEC | C14: =GETPIVOTDATA(""&C$1,Control!$A$20,"Month",""&$B14) -> 0 | D14: =GETPIVOTDATA(""&D$1,Control!$A$20,"Month",""&$B14) -> 0 | E14: =GETPIVOTDATA(""&E$1,Control!$A$20,"Month",""&$B14) -> 0 | F14: =GETPIVOTDATA(""&F$1,Control!$A$20,"Month",""&$B14) -> 0 | G14: =GETPIVOTDATA(""&G$1,Control!$A$20,"Month",""&$B14) -> 300 | H14: =IF(ISNUMBER(GETPIVOTDATA("Num Month",Control!$A$3,"Month",""&B14)),100%,NA()) -> #N/A | J14: 4 | K14: {=INDEX('heatmap-DATA'!$D$2:$J$289,MATCH($I$2&$I$4&$J14,'heatmap-DATA'!$A$2:$A$289&'heatmap-DATA'!$B$2:$B$289&'heatmap-DATA'!$C$2:$C$289,0),COLUMN(A$15))} -> 3 | L14: {=INDEX('heatmap-DATA'!$D$2:$J$289,MATCH($I$2&$I$4&$J14,'heatmap-DATA'!$A$2:$A$289&'heatmap-DATA'!$B$2:$B$289&'heatmap-DATA'!$C$2:$C$289,0),COLUMN(B$1))} -> 3 | M14: {=INDEX('heatmap-DATA'!$D$2:$J$289,MATCH($I$2&$I$4&$J14,'heatmap-DATA'!$A$2:$A$289&'heatmap-DATA'!$B$2:$B$289&'heatmap-DATA'!$C$2:$C$289,0),COLUMN(C$1))} -> 3 | N14: {=INDEX('heatmap-DATA'!$D$2:$J$289,MATCH($I$2&$I$4&$J14,'heatmap-DATA'!$A$2:$A$289&'heatmap-DATA'!$B$2:$B$289&'heatmap-DATA'!$C$2:$C$289,0),COLUMN(D$1))} -> 2 | O14: {=INDEX('heatmap-DATA'!$D$2:$J$289,MATCH($I$2&$I$4&$J14,'heatmap-DATA'!$A$2:$A$289&'heatmap-DATA'!$B$2:$B$289&'heatmap-DATA'!$C$2:$C$289,0),COLUMN(E$1))} -> 4 | P14: {=INDEX('heatmap-DATA'!$D$2:$J$289,MATCH($I$2&$I$4&$J14,'heatmap-DATA'!$A$2:$A$289&'heatmap-DATA'!$B$2:$B$289&'heatmap-DATA'!$C$2:$C$289,0),COLUMN(F$1))} -> 3 | Q14: {=INDEX('heatmap-DATA'!$D$2:$J$289,MATCH($I$2&$I$4&$J14,'heatmap-DATA'!$A$2:$A$289&'heatmap-DATA'!$B$2:$B$289&'heatmap-DATA'!$C$2:$C$289,0),COLUMN(G$1))} -> 3
A15: Financial Goals | B15: =SUM(C3:G14) -> 7200 | C15: Total Progress | D15: =SUM(C3:INDEX(G3:G14,I4)) -> 4700 | E15: =D15/B15 -> 0.65277778 | F15: =1-E15 -> 0.34722222 | G15: Current | H15: =GETPIVOTDATA("Sum of Target 1",Control!$A$3)+GETPIVOTDATA("Sum of Target 2",Control!$A$3)+GETPIVOTDATA("Sum of Target 3",Control!$A$3)+GETPIVOTDATA("Sum of Target 4",Control!$A$3)+GETPIVOTDATA("Sum of Target 5",Control!$A$3) -> 2900 | J15: 5 | K15: {=INDEX('heatmap-DATA'!$D$2:$J$289,MATCH($I$2&$I$4&$J15,'heatmap-DATA'!$A$2:$A$289&'heatmap-DATA'!$B$2:$B$289&'heatmap-DATA'!$C$2:$C$289,0),COLUMN(A$15))} -> 2 | L15: {=INDEX('heatmap-DATA'!$D$2:$J$289,MATCH($I$2&$I$4&$J15,'heatmap-DATA'!$A$2:$A$289&'heatmap-DATA'!$B$2:$B$289&'heatmap-DATA'!$C$2:$C$289,0),COLUMN(B$1))} -> 4 | M15: {=INDEX('heatmap-DATA'!$D$2:$J$289,MATCH($I$2&$I$4&$J15,'heatmap-DATA'!$A$2:$A$289&'heatmap-DATA'!$B$2:$B$289&'heatmap-DATA'!$C$2:$C$289,0),COLUMN(C$1))} -> 2 | N15: {=INDEX('heatmap-DATA'!$D$2:$J$289,MATCH($I$2&$I$4&$J15,'heatmap-DATA'!$A$2:$A$289&'heatmap-DATA'!$B$2:$B$289&'heatmap-DATA'!$C$2:$C$289,0),COLUMN(D$1))} -> 2 | O15: {=INDEX('heatmap-DATA'!$D$2:$J$289,MATCH($I$2&$I$4&$J15,'heatmap-DATA'!$A$2:$A$289&'heatmap-DATA'!$B$2:$B$289&'heatmap-DATA'!$C$2:$C$289,0),COLUMN(E$1))} -> 2 | P15: {=INDEX('heatmap-DATA'!$D$2:$J$289,MATCH($I$2&$I$4&$J15,'heatmap-DATA'!$A$2:$A$289&'heatmap-DATA'!$B$2:$B$289&'heatmap-DATA'!$C$2:$C$289,0),COLUMN(F$1))} -> 2 | Q15: {=INDEX('heatmap-DATA'!$D$2:$J$289,MATCH($I$2&$I$4&$J15,'heatmap-DATA'!$A$2:$A$289&'heatmap-DATA'!$B$2:$B$289&'heatmap-DATA'!$C$2:$C$289,0),COLUMN(G$1))} -> 1
A16: Income & Expenses | J16: 6 | K16: {=INDEX('heatmap-DATA'!$D$2:$J$289,MATCH($I$2&$I$4&$J16,'heatmap-DATA'!$A$2:$A$289&'heatmap-DATA'!$B$2:$B$289&'heatmap-DATA'!$C$2:$C$289,0),COLUMN(A$15))} -> 1 | L16: {=INDEX('heatmap-DATA'!$D$2:$J$289,MATCH($I$2&$I$4&$J16,'heatmap-DATA'!$A$2:$A$289&'heatmap-DATA'!$B$2:$B$289&'heatmap-DATA'!$C$2:$C$289,0),COLUMN(B$1))} -> 1 | M16: {=INDEX('heatmap-DATA'!$D$2:$J$289,MATCH($I$2&$I$4&$J16,'heatmap-DATA'!$A$2:$A$289&'heatmap-DATA'!$B$2:$B$289&'heatmap-DATA'!$C$2:$C$289,0),COLUMN(C$1))} -> 1 | N16: {=INDEX('heatmap-DATA'!$D$2:$J$289,MATCH($I$2&$I$4&$J16,'heatmap-DATA'!$A$2:$A$289&'heatmap-DATA'!$B$2:$B$289&'heatmap-DATA'!$C$2:$C$289,0),COLUMN(D$1))} -> 1 | O16: {=INDEX('heatmap-DATA'!$D$2:$J$289,MATCH($I$2&$I$4&$J16,'heatmap-DATA'!$A$2:$A$289&'heatmap-DATA'!$B$2:$B$289&'heatmap-DATA'!$C$2:$C$289,0),COLUMN(E$1))} -> 1 | P16: {=INDEX('heatmap-DATA'!$D$2:$J$289,MATCH($I$2&$I$4&$J16,'heatmap-DATA'!$A$2:$A$289&'heatmap-DATA'!$B$2:$B$289&'heatmap-DATA'!$C$2:$C$289,0),COLUMN(F$1))} -> 1 | Q16: {=INDEX('heatmap-DATA'!$D$2:$J$289,MATCH($I$2&$I$4&$J16,'heatmap-DATA'!$A$2:$A$289&'heatmap-DATA'!$B$2:$B$289&'heatmap-DATA'!$C$2:$C$289,0),COLUMN(G$1))} -> 1
A17: Month | B17: indent | C17: Income | D17: indent Cursor | E17: Cursor | F17: Expenses | G17: Markers | H17: Labels | K17: Calendar | L17: 1 | N17: =IF(L17,"ON","") -> ON | O17: =IF(L17,"","OFF")
A18: JAN | B18: =$B$30 -> 242.05 | C18: =GETPIVOTDATA(""&C$17,Control!$A$20,"Month",""&$A18) -> 2075 | D18: =B18 -> 242.05 | E18: =IFERROR(GETPIVOTDATA(""&C$17,Control!$A$3,"Month",""&$A18),NA()) -> #N/A | F18: =GETPIVOTDATA(""&F$17,Control!$A$20,"Month",""&$A18) -> 2412 | G18: =E18+B18 -> #N/A | H18: =IF(E18>=1000,TEXT(ROUND(E18/1000,0),"0")&"k",E18) -> #N/A | K18: =IF($L$17, IF( AND( (COLUMN() - COLUMN($K$10) + 1) + (ROW() - ROW($K$18)) * 7 - WEEKDAY(DATE($I$2, $I$4, 1), 1) + 1 > 0, (COLUMN() - COLUMN($K$10) + 1) + (ROW() - ROW($K$18)) * 7 - WEEKDAY(DATE($I$2, $I$4, 1), 1) + 1 <= DAY(EOMONTH(DATE($I$2, $I$4, 1), 0)) ), (COLUMN() - COLUMN($K$10) + 1) + (ROW() - ROW($K$18)) * 7 - WEEKDAY(DATE($I$2, $I$4, 1), 1) + 1, "" ), "" ) | L18: =IF($L$17, IF( AND( (COLUMN() - COLUMN($K$10) + 1) + (ROW() - ROW($K$18)) * 7 - WEEKDAY(DATE($I$2, $I$4, 1), 1) + 1 > 0, (COLUMN() - COLUMN($K$10) + 1) + (ROW() - ROW($K$18)) * 7 - WEEKDAY(DATE($I$2, $I$4, 1), 1) + 1 <= DAY(EOMONTH(DATE($I$2, $I$4, 1), 0)) ), (COLUMN() - COLUMN($K$10) + 1) + (ROW() - ROW($K$18)) * 7 - WEEKDAY(DATE($I$2, $I$4, 1), 1) + 1, "" ), "" ) | M18: =IF($L$17, IF( AND( (COLUMN() - COLUMN($K$10) + 1) + (ROW() - ROW($K$18)) * 7 - WEEKDAY(DATE($I$2, $I$4, 1), 1) + 1 > 0, (COLUMN() - COLUMN($K$10) + 1) + (ROW() - ROW($K$18)) * 7 - WEEKDAY(DATE($I$2, $I$4, 1), 1) + 1 <= DAY(EOMONTH(DATE($I$2, $I$4, 1), 0)) ), (COLUMN() - COLUMN($K$10) + 1) + (ROW() - ROW($K$18)) * 7 - WEEKDAY(DATE($I$2, $I$4, 1), 1) + 1, "" ), "" ) | N18: =IF($L$17, IF( AND( (COLUMN() - COLUMN($K$10) + 1) + (ROW() - ROW($K$18)) * 7 - WEEKDAY(DATE($I$2, $I$4, 1), 1) + 1 > 0, (COLUMN() - COLUMN($K$10) + 1) + (ROW() - ROW($K$18)) * 7 - WEEKDAY(DATE($I$2, $I$4, 1), 1) + 1 <= DAY(EOMONTH(DATE($I$2, $I$4, 1), 0)) ), (COLUMN() - COLUMN($K$10) + 1) + (ROW() - ROW($K$18)) * 7 - WEEKDAY(DATE($I$2, $I$4, 1), 1) + 1, "" ), "" ) | O18: =IF($L$17, IF( AND( (COLUMN() - COLUMN($K$10) + 1) + (ROW() - ROW($K$18)) * 7 - WEEKDAY(DATE($I$2, $I$4, 1), 1) + 1 > 0, (COLUMN() - COLUMN($K$10) + 1) + (ROW() - ROW($K$18)) * 7 - WEEKDAY(DATE($I$2, $I$4, 1), 1) + 1 <= DAY(EOMONTH(DATE($I$2, $I$4, 1), 0)) ), (COLUMN() - COLUMN($K$10) + 1) + (ROW() - ROW($K$18)) * 7 - WEEKDAY(DATE($I$2, $I$4, 1), 1) + 1, "" ), "" ) -> 1 | P18: =IF($L$17, IF( AND( (COLUMN() - COLUMN($K$10) + 1) + (ROW() - ROW($K$18)) * 7 - WEEKDAY(DATE($I$2, $I$4, 1), 1) + 1 > 0, (COLUMN() - COLUMN($K$10) + 1) + (ROW() - ROW($K$18)) * 7 - WEEKDAY(DATE($I$2, $I$4, 1), 1) + 1 <= DAY(EOMONTH(DATE($I$2, $I$4, 1), 0)) ), (COLUMN() - COLUMN($K$10) + 1) + (ROW() - ROW($K$18)) * 7 - WEEKDAY(DATE($I$2, $I$4, 1), 1) + 1, "" ), "" ) -> 2 | Q18: =IF($L$17, IF( AND( (COLUMN() - COLUMN($K$10) + 1) + (ROW() - ROW($K$18)) * 7 - WEEKDAY(DATE($I$2, $I$4, 1), 1) + 1 > 0, (COLUMN() - COLUMN($K$10) + 1) + (ROW() - ROW($K$18)) * 7 - WEEKDAY(DATE($I$2, $I$4, 1), 1) + 1 <= DAY(EOMONTH(DATE($I$2, $I$4, 1), 0)) ), (COLUMN() - COLUMN($K$10) + 1) + (ROW() - ROW($K$18)) * 7 - WEEKDAY(DATE($I$2, $I$4, 1), 1) + 1, "" ), "" ) -> 3
A19: FEB | B19: =$B$30 -> 242.05 | C19: =GETPIVOTDATA(""&C$17,Control!$A$20,"Month",""&$A19) -> 3066 | D19: =B19 -> 242.05 | E19: =IFERROR(GETPIVOTDATA(""&C$17,Control!$A$3,"Month",""&$A19),NA()) -> #N/A | F19: =GETPIVOTDATA(""&F$17,Control!$A$20,"Month",""&$A19) -> 1696 | G19: =E19+B19 -> #N/A | H19: =IF(E19>=1000,TEXT(ROUND(E19/1000,0),"0")&"k",E19) -> #N/A | K19: =IF($L$17, IF( AND( (COLUMN() - COLUMN($K$10) + 1) + (ROW() - ROW($K$18)) * 7 - WEEKDAY(DATE($I$2, $I$4, 1), 1) + 1 > 0, (COLUMN() - COLUMN($K$10) + 1) + (ROW() - ROW($K$18)) * 7 - WEEKDAY(DATE($I$2, $I$4, 1), 1) + 1 <= DAY(EOMONTH(DATE($I$2, $I$4, 1), 0)) ), (COLUMN() - COLUMN($K$10) + 1) + (ROW() - ROW($K$18)) * 7 - WEEKDAY(DATE($I$2, $I$4, 1), 1) + 1, "" ), "" ) -> 4 | L19: =IF($L$17, IF( AND( (COLUMN() - COLUMN($K$10) + 1) + (ROW() - ROW($K$18)) * 7 - WEEKDAY(DATE($I$2, $I$4, 1), 1) + 1 > 0, (COLUMN() - COLUMN($K$10) + 1) + (ROW() - ROW($K$18)) * 7 - WEEKDAY(DATE($I$2, $I$4, 1), 1) + 1 <= DAY(EOMONTH(DATE($I$2, $I$4, 1), 0)) ), (COLUMN() - COLUMN($K$10) + 1) + (ROW() - ROW($K$18)) * 7 - WEEKDAY(DATE($I$2, $I$4, 1), 1) + 1, "" ), "" ) -> 5 | M19: =IF($L$17, IF( AND( (COLUMN() - COLUMN($K$10) + 1) + (ROW() - ROW($K$18)) * 7 - WEEKDAY(DATE($I$2, $I$4, 1), 1) + 1 > 0, (COLUMN() - COLUMN($K$10) + 1) + (ROW() - ROW($K$18)) * 7 - WEEKDAY(DATE($I$2, $I$4, 1), 1) + 1 <= DAY(EOMONTH(DATE($I$2, $I$4, 1), 0)) ), (COLUMN() - COLUMN($K$10) + 1) + (ROW() - ROW($K$18)) * 7 - WEEKDAY(DATE($I$2, $I$4, 1), 1) + 1, "" ), "" ) -> 6 | N19: =IF($L$17, IF( AND( (COLUMN() - COLUMN($K$10) + 1) + (ROW() - ROW($K$18)) * 7 - WEEKDAY(DATE($I$2, $I$4, 1), 1) + 1 > 0, (COLUMN() - COLUMN($K$10) + 1) + (ROW() - ROW($K$18)) * 7 - WEEKDAY(DATE($I$2, $I$4, 1), 1) + 1 <= DAY(EOMONTH(DATE($I$2, $I$4, 1), 0)) ), (COLUMN() - COLUMN($K$10) + 1) + (ROW() - ROW($K$18)) * 7 - WEEKDAY(DATE($I$2, $I$4, 1), 1) + 1, "" ), "" ) -> 7 | O19: =IF($L$17, IF( AND( (COLUMN() - COLUMN($K$10) + 1) + (ROW() - ROW($K$18)) * 7 - WEEKDAY(DATE($I$2, $I$4, 1), 1) + 1 > 0, (COLUMN() - COLUMN($K$10) + 1) + (ROW() - ROW($K$18)) * 7 - WEEKDAY(DATE($I$2, $I$4, 1), 1) + 1 <= DAY(EOMONTH(DATE($I$2, $I$4, 1), 0)) ), (COLUMN() - COLUMN($K$10) + 1) + (ROW() - ROW($K$18)) * 7 - WEEKDAY(DATE($I$2, $I$4, 1), 1) + 1, "" ), "" ) -> 8 | P19: =IF($L$17, IF( AND( (COLUMN() - COLUMN($K$10) + 1) + (ROW() - ROW($K$18)) * 7 - WEEKDAY(DATE($I$2, $I$4, 1), 1) + 1 > 0, (COLUMN() - COLUMN($K$10) + 1) + (ROW() - ROW($K$18)) * 7 - WEEKDAY(DATE($I$2, $I$4, 1), 1) + 1 <= DAY(EOMONTH(DATE($I$2, $I$4, 1), 0)) ), (COLUMN() - COLUMN($K$10) + 1) + (ROW() - ROW($K$18)) * 7 - WEEKDAY(DATE($I$2, $I$4, 1), 1) + 1, "" ), "" ) -> 9 | Q19: =IF($L$17, IF( AND( (COLUMN() - COLUMN($K$10) + 1) + (ROW() - ROW($K$18)) * 7 - WEEKDAY(DATE($I$2, $I$4, 1), 1) + 1 > 0, (COLUMN() - COLUMN($K$10) + 1) + (ROW() - ROW($K$18)) * 7 - WEEKDAY(DATE($I$2, $I$4, 1), 1) + 1 <= DAY(EOMONTH(DATE($I$2, $I$4, 1), 0)) ), (COLUMN() - COLUMN($K$10) + 1) + (ROW() - ROW($K$18)) * 7 - WEEKDAY(DATE($I$2, $I$4, 1), 1) + 1, "" ), "" ) -> 10
A20: MAR | B20: =$B$30 -> 242.05 | C20: =GETPIVOTDATA(""&C$17,Control!$A$20,"Month",""&$A20) -> 4626 | D20: =B20 -> 242.05 | E20: =IFERROR(GETPIVOTDATA(""&C$17,Control!$A$3,"Month",""&$A20),NA()) -> #N/A | F20: =GETPIVOTDATA(""&F$17,Control!$A$20,"Month",""&$A20) -> 3544 | G20: =E20+B20 -> #N/A | H20: =IF(E20>=1000,TEXT(ROUND(E20/1000,0),"0")&"k",E20) -> #N/A | K20: =IF($L$17, IF( AND( (COLUMN() - COLUMN($K$10) + 1) + (ROW() - ROW($K$18)) * 7 - WEEKDAY(DATE($I$2, $I$4, 1), 1) + 1 > 0, (COLUMN() - COLUMN($K$10) + 1) + (ROW() - ROW($K$18)) * 7 - WEEKDAY(DATE($I$2, $I$4, 1), 1) + 1 <= DAY(EOMONTH(DATE($I$2, $I$4, 1), 0)) ), (COLUMN() - COLUMN($K$10) + 1) + (ROW() - ROW($K$18)) * 7 - WEEKDAY(DATE($I$2, $I$4, 1), 1) + 1, "" ), "" ) -> 11 | L20: =IF($L$17, IF( AND( (COLUMN() - COLUMN($K$10) + 1) + (ROW() - ROW($K$18)) * 7 - WEEKDAY(DATE($I$2, $I$4, 1), 1) + 1 > 0, (COLUMN() - COLUMN($K$10) + 1) + (ROW() - ROW($K$18)) * 7 - WEEKDAY(DATE($I$2, $I$4, 1), 1) + 1 <= DAY(EOMONTH(DATE($I$2, $I$4, 1), 0)) ), (COLUMN() - COLUMN($K$10) + 1) + (ROW() - ROW($K$18)) * 7 - WEEKDAY(DATE($I$2, $I$4, 1), 1) + 1, "" ), "" ) -> 12 | M20: =IF($L$17, IF( AND( (COLUMN() - COLUMN($K$10) + 1) + (ROW() - ROW($K$18)) * 7 - WEEKDAY(DATE($I$2, $I$4, 1), 1) + 1 > 0, (COLUMN() - COLUMN($K$10) + 1) + (ROW() - ROW($K$18)) * 7 - WEEKDAY(DATE($I$2, $I$4, 1), 1) + 1 <= DAY(EOMONTH(DATE($I$2, $I$4, 1), 0)) ), (COLUMN() - COLUMN($K$10) + 1) + (ROW() - ROW($K$18)) * 7 - WEEKDAY(DATE($I$2, $I$4, 1), 1) + 1, "" ), "" ) -> 13 | N20: =IF($L$17, IF( AND( (COLUMN() - COLUMN($K$10) + 1) + (ROW() - ROW($K$18)) * 7 - WEEKDAY(DATE($I$2, $I$4, 1), 1) + 1 > 0, (COLUMN() - COLUMN($K$10) + 1) + (ROW() - ROW($K$18)) * 7 - WEEKDAY(DATE($I$2, $I$4, 1), 1) + 1 <= DAY(EOMONTH(DATE($I$2, $I$4, 1), 0)) ), (COLUMN() - COLUMN($K$10) + 1) + (ROW() - ROW($K$18)) * 7 - WEEKDAY(DATE($I$2, $I$4, 1), 1) + 1, "" ), "" ) -> 14 | O20: =IF($L$17, IF( AND( (COLUMN() - COLUMN($K$10) + 1) + (ROW() - ROW($K$18)) * 7 - WEEKDAY(DATE($I$2, $I$4, 1), 1) + 1 > 0, (COLUMN() - COLUMN($K$10) + 1) + (ROW() - ROW($K$18)) * 7 - WEEKDAY(DATE($I$2, $I$4, 1), 1) + 1 <= DAY(EOMONTH(DATE($I$2, $I$4, 1), 0)) ), (COLUMN() - COLUMN($K$10) + 1) + (ROW() - ROW($K$18)) * 7 - WEEKDAY(DATE($I$2, $I$4, 1), 1) + 1, "" ), "" ) -> 15 | P20: =IF($L$17, IF( AND( (COLUMN() - COLUMN($K$10) + 1) + (ROW() - ROW($K$18)) * 7 - WEEKDAY(DATE($I$2, $I$4, 1), 1) + 1 > 0, (COLUMN() - COLUMN($K$10) + 1) + (ROW() - ROW($K$18)) * 7 - WEEKDAY(DATE($I$2, $I$4, 1), 1) + 1 <= DAY(EOMONTH(DATE($I$2, $I$4, 1), 0)) ), (COLUMN() - COLUMN($K$10) + 1) + (ROW() - ROW($K$18)) * 7 - WEEKDAY(DATE($I$2, $I$4, 1), 1) + 1, "" ), "" ) -> 16 | Q20: =IF($L$17, IF( AND( (COLUMN() - COLUMN($K$10) + 1) + (ROW() - ROW($K$18)) * 7 - WEEKDAY(DATE($I$2, $I$4, 1), 1) + 1 > 0, (COLUMN() - COLUMN($K$10) + 1) + (ROW() - ROW($K$18)) * 7 - WEEKDAY(DATE($I$2, $I$4, 1), 1) + 1 <= DAY(EOMONTH(DATE($I$2, $I$4, 1), 0)) ), (COLUMN() - COLUMN($K$10) + 1) + (ROW() - ROW($K$18)) * 7 - WEEKDAY(DATE($I$2, $I$4, 1), 1) + 1, "" ), "" ) -> 17
A21: APR | B21: =$B$30 -> 242.05 | C21: =GETPIVOTDATA(""&C$17,Control!$A$20,"Month",""&$A21) -> 4841 | D21: =B21 -> 242.05 | E21: =IFERROR(GETPIVOTDATA(""&C$17,Control!$A$3,"Month",""&$A21),NA()) -> 4841 | F21: =GETPIVOTDATA(""&F$17,Control!$A$20,"Month",""&$A21) -> 2671 | G21: =E21+B21 -> 5083.05 | H21: =IF(E21>=1000,TEXT(ROUND(E21/1000,0),"0")&"k",E21) -> 5k | K21: =IF($L$17, IF( AND( (COLUMN() - COLUMN($K$10) + 1) + (ROW() - ROW($K$18)) * 7 - WEEKDAY(DATE($I$2, $I$4, 1), 1) + 1 > 0, (COLUMN() - COLUMN($K$10) + 1) + (ROW() - ROW($K$18)) * 7 - WEEKDAY(DATE($I$2, $I$4, 1), 1) + 1 <= DAY(EOMONTH(DATE($I$2, $I$4, 1), 0)) ), (COLUMN() - COLUMN($K$10) + 1) + (ROW() - ROW($K$18)) * 7 - WEEKDAY(DATE($I$2, $I$4, 1), 1) + 1, "" ), "" ) -> 18 | L21: =IF($L$17, IF( AND( (COLUMN() - COLUMN($K$10) + 1) + (ROW() - ROW($K$18)) * 7 - WEEKDAY(DATE($I$2, $I$4, 1), 1) + 1 > 0, (COLUMN() - COLUMN($K$10) + 1) + (ROW() - ROW($K$18)) * 7 - WEEKDAY(DATE($I$2, $I$4, 1), 1) + 1 <= DAY(EOMONTH(DATE($I$2, $I$4, 1), 0)) ), (COLUMN() - COLUMN($K$10) + 1) + (ROW() - ROW($K$18)) * 7 - WEEKDAY(DATE($I$2, $I$4, 1), 1) + 1, "" ), "" ) -> 19 | M21: =IF($L$17, IF( AND( (COLUMN() - COLUMN($K$10) + 1) + (ROW() - ROW($K$18)) * 7 - WEEKDAY(DATE($I$2, $I$4, 1), 1) + 1 > 0, (COLUMN() - COLUMN($K$10) + 1) + (ROW() - ROW($K$18)) * 7 - WEEKDAY(DATE($I$2, $I$4, 1), 1) + 1 <= DAY(EOMONTH(DATE($I$2, $I$4, 1), 0)) ), (COLUMN() - COLUMN($K$10) + 1) + (ROW() - ROW($K$18)) * 7 - WEEKDAY(DATE($I$2, $I$4, 1), 1) + 1, "" ), "" ) -> 20 | N21: =IF($L$17, IF( AND( (COLUMN() - COLUMN($K$10) + 1) + (ROW() - ROW($K$18)) * 7 - WEEKDAY(DATE($I$2, $I$4, 1), 1) + 1 > 0, (COLUMN() - COLUMN($K$10) + 1) + (ROW() - ROW($K$18)) * 7 - WEEKDAY(DATE($I$2, $I$4, 1), 1) + 1 <= DAY(EOMONTH(DATE($I$2, $I$4, 1), 0)) ), (COLUMN() - COLUMN($K$10) + 1) + (ROW() - ROW($K$18)) * 7 - WEEKDAY(DATE($I$2, $I$4, 1), 1) + 1, "" ), "" ) -> 21 | O21: =IF($L$17, IF( AND( (COLUMN() - COLUMN($K$10) + 1) + (ROW() - ROW($K$18)) * 7 - WEEKDAY(DATE($I$2, $I$4, 1), 1) + 1 > 0, (COLUMN() - COLUMN($K$10) + 1) + (ROW() - ROW($K$18)) * 7 - WEEKDAY(DATE($I$2, $I$4, 1), 1) + 1 <= DAY(EOMONTH(DATE($I$2, $I$4, 1), 0)) ), (COLUMN() - COLUMN($K$10) + 1) + (ROW() - ROW($K$18)) * 7 - WEEKDAY(DATE($I$2, $I$4, 1), 1) + 1, "" ), "" ) -> 22 | P21: =IF($L$17, IF( AND( (COLUMN() - COLUMN($K$10) + 1) + (ROW() - ROW($K$18)) * 7 - WEEKDAY(DATE($I$2, $I$4, 1), 1) + 1 > 0, (COLUMN() - COLUMN($K$10) + 1) + (ROW() - ROW($K$18)) * 7 - WEEKDAY(DATE($I$2, $I$4, 1), 1) + 1 <= DAY(EOMONTH(DATE($I$2, $I$4, 1), 0)) ), (COLUMN() - COLUMN($K$10) + 1) + (ROW() - ROW($K$18)) * 7 - WEEKDAY(DATE($I$2, $I$4, 1), 1) + 1, "" ), "" ) -> 23 | Q21: =IF($L$17, IF( AND( (COLUMN() - COLUMN($K$10) + 1) + (ROW() - ROW($K$18)) * 7 - WEEKDAY(DATE($I$2, $I$4, 1), 1) + 1 > 0, (COLUMN() - COLUMN($K$10) + 1) + (ROW() - ROW($K$18)) * 7 - WEEKDAY(DATE($I$2, $I$4, 1), 1) + 1 <= DAY(EOMONTH(DATE($I$2, $I$4, 1), 0)) ), (COLUMN() - COLUMN($K$10) + 1) + (ROW() - ROW($K$18)) * 7 - WEEKDAY(DATE($I$2, $I$4, 1), 1) + 1, "" ), "" ) -> 24
A22: MAY | B22: =$B$30 -> 242.05 | C22: =GETPIVOTDATA(""&C$17,Control!$A$20,"Month",""&$A22) -> 4626 | D22: =B22 -> 242.05 | E22: =IFERROR(GETPIVOTDATA(""&C$17,Control!$A$3,"Month",""&$A22),NA()) -> 4626 | F22: =GETPIVOTDATA(""&F$17,Control!$A$20,"Month",""&$A22) -> 3036 | G22: =E22+B22 -> 4868.05 | H22: =IF(E22>=1000,TEXT(ROUND(E22/1000,0),"0")&"k",E22) -> 5k | K22: =IF($L$17, IF( AND( (COLUMN() - COLUMN($K$10) + 1) + (ROW() - ROW($K$18)) * 7 - WEEKDAY(DATE($I$2, $I$4, 1), 1) + 1 > 0, (COLUMN() - COLUMN($K$10) + 1) + (ROW() - ROW($K$18)) * 7 - WEEKDAY(DATE($I$2, $I$4, 1), 1) + 1 <= DAY(EOMONTH(DATE($I$2, $I$4, 1), 0)) ), (COLUMN() - COLUMN($K$10) + 1) + (ROW() - ROW($K$18)) * 7 - WEEKDAY(DATE($I$2, $I$4, 1), 1) + 1, "" ), "" ) -> 25 | L22: =IF($L$17, IF( AND( (COLUMN() - COLUMN($K$10) + 1) + (ROW() - ROW($K$18)) * 7 - WEEKDAY(DATE($I$2, $I$4, 1), 1) + 1 > 0, (COLUMN() - COLUMN($K$10) + 1) + (ROW() - ROW($K$18)) * 7 - WEEKDAY(DATE($I$2, $I$4, 1), 1) + 1 <= DAY(EOMONTH(DATE($I$2, $I$4, 1), 0)) ), (COLUMN() - COLUMN($K$10) + 1) + (ROW() - ROW($K$18)) * 7 - WEEKDAY(DATE($I$2, $I$4, 1), 1) + 1, "" ), "" ) -> 26 | M22: =IF($L$17, IF( AND( (COLUMN() - COLUMN($K$10) + 1) + (ROW() - ROW($K$18)) * 7 - WEEKDAY(DATE($I$2, $I$4, 1), 1) + 1 > 0, (COLUMN() - COLUMN($K$10) + 1) + (ROW() - ROW($K$18)) * 7 - WEEKDAY(DATE($I$2, $I$4, 1), 1) + 1 <= DAY(EOMONTH(DATE($I$2, $I$4, 1), 0)) ), (COLUMN() - COLUMN($K$10) + 1) + (ROW() - ROW($K$18)) * 7 - WEEKDAY(DATE($I$2, $I$4, 1), 1) + 1, "" ), "" ) -> 27 | N22: =IF($L$17, IF( AND( (COLUMN() - COLUMN($K$10) + 1) + (ROW() - ROW($K$18)) * 7 - WEEKDAY(DATE($I$2, $I$4, 1), 1) + 1 > 0, (COLUMN() - COLUMN($K$10) + 1) + (ROW() - ROW($K$18)) * 7 - WEEKDAY(DATE($I$2, $I$4, 1), 1) + 1 <= DAY(EOMONTH(DATE($I$2, $I$4, 1), 0)) ), (COLUMN() - COLUMN($K$10) + 1) + (ROW() - ROW($K$18)) * 7 - WEEKDAY(DATE($I$2, $I$4, 1), 1) + 1, "" ), "" ) -> 28 | O22: =IF($L$17, IF( AND( (COLUMN() - COLUMN($K$10) + 1) + (ROW() - ROW($K$18)) * 7 - WEEKDAY(DATE($I$2, $I$4, 1), 1) + 1 > 0, (COLUMN() - COLUMN($K$10) + 1) + (ROW() - ROW($K$18)) * 7 - WEEKDAY(DATE($I$2, $I$4, 1), 1) + 1 <= DAY(EOMONTH(DATE($I$2, $I$4, 1), 0)) ), (COLUMN() - COLUMN($K$10) + 1) + (ROW() - ROW($K$18)) * 7 - WEEKDAY(DATE($I$2, $I$4, 1), 1) + 1, "" ), "" ) -> 29 | P22: =IF($L$17, IF( AND( (COLUMN() - COLUMN($K$10) + 1) + (ROW() - ROW($K$18)) * 7 - WEEKDAY(DATE($I$2, $I$4, 1), 1) + 1 > 0, (COLUMN() - COLUMN($K$10) + 1) + (ROW() - ROW($K$18)) * 7 - WEEKDAY(DATE($I$2, $I$4, 1), 1) + 1 <= DAY(EOMONTH(DATE($I$2, $I$4, 1), 0)) ), (COLUMN() - COLUMN($K$10) + 1) + (ROW() - ROW($K$18)) * 7 - WEEKDAY(DATE($I$2, $I$4, 1), 1) + 1, "" ), "" ) -> 30 | Q22: =IF($L$17, IF( AND( (COLUMN() - COLUMN($K$10) + 1) + (ROW() - ROW($K$18)) * 7 - WEEKDAY(DATE($I$2, $I$4, 1), 1) + 1 > 0, (COLUMN() - COLUMN($K$10) + 1) + (ROW() - ROW($K$18)) * 7 - WEEKDAY(DATE($I$2, $I$4, 1), 1) + 1 <= DAY(EOMONTH(DATE($I$2, $I$4, 1), 0)) ), (COLUMN() - COLUMN($K$10) + 1) + (ROW() - ROW($K$18)) * 7 - WEEKDAY(DATE($I$2, $I$4, 1), 1) + 1, "" ), "" )
A23: JUN | B23: =$B$30 -> 242.05 | C23: =GETPIVOTDATA(""&C$17,Control!$A$20,"Month",""&$A23) -> 3066 | D23: =B23 -> 242.05 | E23: =IFERROR(GETPIVOTDATA(""&C$17,Control!$A$3,"Month",""&$A23),NA()) -> 3066 | F23: =GETPIVOTDATA(""&F$17,Control!$A$20,"Month",""&$A23) -> 4595 | G23: =E23+B23 -> 3308.05 | H23: =IF(E23>=1000,TEXT(ROUND(E23/1000,0),"0")&"k",E23) -> 3k | K23: =IF($L$17, IF( AND( (COLUMN() - COLUMN($K$10) + 1) + (ROW() - ROW($K$18)) * 7 - WEEKDAY(DATE($I$2, $I$4, 1), 1) + 1 > 0, (COLUMN() - COLUMN($K$10) + 1) + (ROW() - ROW($K$18)) * 7 - WEEKDAY(DATE($I$2, $I$4, 1), 1) + 1 <= DAY(EOMONTH(DATE($I$2, $I$4, 1), 0)) ), (COLUMN() - COLUMN($K$10) + 1) + (ROW() - ROW($K$18)) * 7 - WEEKDAY(DATE($I$2, $I$4, 1), 1) + 1, "" ), "" ) | L23: =IF($L$17, IF( AND( (COLUMN() - COLUMN($K$10) + 1) + (ROW() - ROW($K$18)) * 7 - WEEKDAY(DATE($I$2, $I$4, 1), 1) + 1 > 0, (COLUMN() - COLUMN($K$10) + 1) + (ROW() - ROW($K$18)) * 7 - WEEKDAY(DATE($I$2, $I$4, 1), 1) + 1 <= DAY(EOMONTH(DATE($I$2, $I$4, 1), 0)) ), (COLUMN() - COLUMN($K$10) + 1) + (ROW() - ROW($K$18)) * 7 - WEEKDAY(DATE($I$2, $I$4, 1), 1) + 1, "" ), "" ) | M23: =IF($L$17, IF( AND( (COLUMN() - COLUMN($K$10) + 1) + (ROW() - ROW($K$18)) * 7 - WEEKDAY(DATE($I$2, $I$4, 1), 1) + 1 > 0, (COLUMN() - COLUMN($K$10) + 1) + (ROW() - ROW($K$18)) * 7 - WEEKDAY(DATE($I$2, $I$4, 1), 1) + 1 <= DAY(EOMONTH(DATE($I$2, $I$4, 1), 0)) ), (COLUMN() - COLUMN($K$10) + 1) + (ROW() - ROW($K$18)) * 7 - WEEKDAY(DATE($I$2, $I$4, 1), 1) + 1, "" ), "" ) | N23: =IF($L$17, IF( AND( (COLUMN() - COLUMN($K$10) + 1) + (ROW() - ROW($K$18)) * 7 - WEEKDAY(DATE($I$2, $I$4, 1), 1) + 1 > 0, (COLUMN() - COLUMN($K$10) + 1) + (ROW() - ROW($K$18)) * 7 - WEEKDAY(DATE($I$2, $I$4, 1), 1) + 1 <= DAY(EOMONTH(DATE($I$2, $I$4, 1), 0)) ), (COLUMN() - COLUMN($K$10) + 1) + (ROW() - ROW($K$18)) * 7 - WEEKDAY(DATE($I$2, $I$4, 1), 1) + 1, "" ), "" ) | O23: =IF($L$17, IF( AND( (COLUMN() - COLUMN($K$10) + 1) + (ROW() - ROW($K$18)) * 7 - WEEKDAY(DATE($I$2, $I$4, 1), 1) + 1 > 0, (COLUMN() - COLUMN($K$10) + 1) + (ROW() - ROW($K$18)) * 7 - WEEKDAY(DATE($I$2, $I$4, 1), 1) + 1 <= DAY(EOMONTH(DATE($I$2, $I$4, 1), 0)) ), (COLUMN() - COLUMN($K$10) + 1) + (ROW() - ROW($K$18)) * 7 - WEEKDAY(DATE($I$2, $I$4, 1), 1) + 1, "" ), "" ) | P23: =IF($L$17, IF( AND( (COLUMN() - COLUMN($K$10) + 1) + (ROW() - ROW($K$18)) * 7 - WEEKDAY(DATE($I$2, $I$4, 1), 1) + 1 > 0, (COLUMN() - COLUMN($K$10) + 1) + (ROW() - ROW($K$18)) * 7 - WEEKDAY(DATE($I$2, $I$4, 1), 1) + 1 <= DAY(EOMONTH(DATE($I$2, $I$4, 1), 0)) ), (COLUMN() - COLUMN($K$10) + 1) + (ROW() - ROW($K$18)) * 7 - WEEKDAY(DATE($I$2, $I$4, 1), 1) + 1, "" ), "" ) | Q23: =IF($L$17, IF( AND( (COLUMN() - COLUMN($K$10) + 1) + (ROW() - ROW($K$18)) * 7 - WEEKDAY(DATE($I$2, $I$4, 1), 1) + 1 > 0, (COLUMN() - COLUMN($K$10) + 1) + (ROW() - ROW($K$18)) * 7 - WEEKDAY(DATE($I$2, $I$4, 1), 1) + 1 <= DAY(EOMONTH(DATE($I$2, $I$4, 1), 0)) ), (COLUMN() - COLUMN($K$10) + 1) + (ROW() - ROW($K$18)) * 7 - WEEKDAY(DATE($I$2, $I$4, 1), 1) + 1, "" ), "" ) | T23: =_xlfn.LET(_xlpm.StartDay, WEEKDAY(DATE($I$2, $I$4, 1), 1),_xlpm.DayNum, (COLUMN() - COLUMN($S$18) + 1) + (ROW() - ROW($S$18)) * 7 - _xlpm.StartDay + 1,IF(AND(_xlpm.DayNum > 0, _xlpm.DayNum <= DAY(EOMONTH(DATE($I$2, $I$4, 1), 0))), _xlpm.DayNum, "")) | U23: =_xlfn.LET(_xlpm.StartDay, WEEKDAY(DATE($I$2, $I$4, 1), 1),_xlpm.DayNum, (COLUMN() - COLUMN($S$18) + 1) + (ROW() - ROW($S$18)) * 7 - _xlpm.StartDay + 1,IF(AND(_xlpm.DayNum > 0, _xlpm.DayNum <= DAY(EOMONTH(DATE($I$2, $I$4, 1), 0))), _xlpm.DayNum, "")) | V23: =_xlfn.LET(_xlpm.StartDay, WEEKDAY(DATE($I$2, $I$4, 1), 1),_xlpm.DayNum, (COLUMN() - COLUMN($S$18) + 1) + (ROW() - ROW($S$18)) * 7 - _xlpm.StartDay + 1,IF(AND(_xlpm.DayNum > 0, _xlpm.DayNum <= DAY(EOMONTH(DATE($I$2, $I$4, 1), 0))), _xlpm.DayNum, "")) | W23: =_xlfn.LET(_xlpm.StartDay, WEEKDAY(DATE($I$2, $I$4, 1), 1),_xlpm.DayNum, (COLUMN() - COLUMN($S$18) + 1) + (ROW() - ROW($S$18)) * 7 - _xlpm.StartDay + 1,IF(AND(_xlpm.DayNum > 0, _xlpm.DayNum <= DAY(EOMONTH(DATE($I$2, $I$4, 1), 0))), _xlpm.DayNum, "")) | X23: =_xlfn.LET(_xlpm.StartDay, WEEKDAY(DATE($I$2, $I$4, 1), 1),_xlpm.DayNum, (COLUMN() - COLUMN($S$18) + 1) + (ROW() - ROW($S$18)) * 7 - _xlpm.StartDay + 1,IF(AND(_xlpm.DayNum > 0, _xlpm.DayNum <= DAY(EOMONTH(DATE($I$2, $I$4, 1), 0))), _xlpm.DayNum, "")) | Y23: =_xlfn.LET(_xlpm.StartDay, WEEKDAY(DATE($I$2, $I$4, 1), 1),_xlpm.DayNum, (COLUMN() - COLUMN($S$18) + 1) + (ROW() - ROW($S$18)) * 7 - _xlpm.StartDay + 1,IF(AND(_xlpm.DayNum > 0, _xlpm.DayNum <= DAY(EOMONTH(DATE($I$2, $I$4, 1), 0))), _xlpm.DayNum, ""))
A24: JUL | B24: =$B$30 -> 242.05 | C24: =GETPIVOTDATA(""&C$17,Control!$A$20,"Month",""&$A24) -> 2075 | D24: =B24 -> 242.05 | E24: =IFERROR(GETPIVOTDATA(""&C$17,Control!$A$3,"Month",""&$A24),NA()) -> #N/A | F24: =GETPIVOTDATA(""&F$17,Control!$A$20,"Month",""&$A24) -> 2714 | G24: =E24+B24 -> #N/A | H24: =IF(E24>=1000,TEXT(ROUND(E24/1000,0),"0")&"k",E24) -> #N/A | K24: SU | L24: MO | M24: TU | N24: WE | O24: TH | P24: FR | Q24: SA | R24: Activity | S24: WEEK
A25: AUG | B25: =$B$30 -> 242.05 | C25: =GETPIVOTDATA(""&C$17,Control!$A$20,"Month",""&$A25) -> 3066 | D25: =B25 -> 242.05 | E25: =IFERROR(GETPIVOTDATA(""&C$17,Control!$A$3,"Month",""&$A25),NA()) -> #N/A | F25: =GETPIVOTDATA(""&F$17,Control!$A$20,"Month",""&$A25) -> 3731 | G25: =E25+B25 -> #N/A | H25: =IF(E25>=1000,TEXT(ROUND(E25/1000,0),"0")&"k",E25) -> #N/A | K25: {=INDEX(K$11:K$16,$S25)=$R25} -> TRUE | L25: {=INDEX(L$11:L$16,$S25)=$R25} -> TRUE | M25: {=INDEX(M$11:M$16,$S25)=$R25} -> TRUE | N25: {=INDEX(N$11:N$16,$S25)=$R25} -> TRUE | O25: {=INDEX(O$11:O$16,$S25)=$R25} -> FALSE | P25: {=INDEX(P$11:P$16,$S25)=$R25} -> FALSE | Q25: {=INDEX(Q$11:Q$16,$S25)=$R25} -> FALSE | R25: 1 | S25: =INT((ROW(A1)-1)/4)+1 -> 1
A26: SEP | B26: =$B$30 -> 242.05 | C26: =GETPIVOTDATA(""&C$17,Control!$A$20,"Month",""&$A26) -> 4626 | D26: =B26 -> 242.05 | E26: =IFERROR(GETPIVOTDATA(""&C$17,Control!$A$3,"Month",""&$A26),NA()) -> #N/A | F26: =GETPIVOTDATA(""&F$17,Control!$A$20,"Month",""&$A26) -> 4952 | G26: =E26+B26 -> #N/A | H26: =IF(E26>=1000,TEXT(ROUND(E26/1000,0),"0")&"k",E26) -> #N/A | K26: {=INDEX(K$11:K$16,$S26)=$R26} -> FALSE | L26: {=INDEX(L$11:L$16,$S26)=$R26} -> FALSE | M26: {=INDEX(M$11:M$16,$S26)=$R26} -> FALSE | N26: {=INDEX(N$11:N$16,$S26)=$R26} -> FALSE | O26: {=INDEX(O$11:O$16,$S26)=$R26} -> FALSE | P26: {=INDEX(P$11:P$16,$S26)=$R26} -> TRUE | Q26: {=INDEX(Q$11:Q$16,$S26)=$R26} -> FALSE | R26: 2 | S26: =INT((ROW(A2)-1)/4)+1 -> 1
A27: OCT | B27: =$B$30 -> 242.05 | C27: =GETPIVOTDATA(""&C$17,Control!$A$20,"Month",""&$A27) -> 4841 | D27: =B27 -> 242.05 | E27: =IFERROR(GETPIVOTDATA(""&C$17,Control!$A$3,"Month",""&$A27),NA()) -> #N/A | F27: =GETPIVOTDATA(""&F$17,Control!$A$20,"Month",""&$A27) -> 3544 | G27: =E27+B27 -> #N/A | H27: =IF(E27>=1000,TEXT(ROUND(E27/1000,0),"0")&"k",E27) -> #N/A | K27: {=INDEX(K$11:K$16,$S27)=$R27} -> FALSE | L27: {=INDEX(L$11:L$16,$S27)=$R27} -> FALSE | M27: {=INDEX(M$11:M$16,$S27)=$R27} -> FALSE | N27: {=INDEX(N$11:N$16,$S27)=$R27} -> FALSE | O27: {=INDEX(O$11:O$16,$S27)=$R27} -> TRUE | P27: {=INDEX(P$11:P$16,$S27)=$R27} -> FALSE | Q27: {=INDEX(Q$11:Q$16,$S27)=$R27} -> TRUE | R27: 3 | S27: =INT((ROW(A3)-1)/4)+1 -> 1
A28: NOV | B28: =$B$30 -> 242.05 | C28: =GETPIVOTDATA(""&C$17,Control!$A$20,"Month",""&$A28) -> 4626 | D28: =B28 -> 242.05 | E28: =IFERROR(GETPIVOTDATA(""&C$17,Control!$A$3,"Month",""&$A28),NA()) -> #N/A | F28: =GETPIVOTDATA(""&F$17,Control!$A$20,"Month",""&$A28) -> 4595 | G28: =E28+B28 -> #N/A | H28: =IF(E28>=1000,TEXT(ROUND(E28/1000,0),"0")&"k",E28) -> #N/A | K28: {=INDEX(K$11:K$16,$S28)=$R28} -> FALSE | L28: {=INDEX(L$11:L$16,$S28)=$R28} -> FALSE | M28: {=INDEX(M$11:M$16,$S28)=$R28} -> FALSE | N28: {=INDEX(N$11:N$16,$S28)=$R28} -> FALSE | O28: {=INDEX(O$11:O$16,$S28)=$R28} -> FALSE | P28: {=INDEX(P$11:P$16,$S28)=$R28} -> FALSE | Q28: {=INDEX(Q$11:Q$16,$S28)=$R28} -> FALSE | R28: 4 | S28: =INT((ROW(A4)-1)/4)+1 -> 1
A29: DEC | B29: =$B$30 -> 242.05 | C29: =GETPIVOTDATA(""&C$17,Control!$A$20,"Month",""&$A29) -> 2666 | D29: =B29 -> 242.05 | E29: =IFERROR(GETPIVOTDATA(""&C$17,Control!$A$3,"Month",""&$A29),NA()) -> #N/A | F29: =GETPIVOTDATA(""&F$17,Control!$A$20,"Month",""&$A29) -> 1739 | G29: =E29+B29 -> #N/A | H29: =IF(E29>=1000,TEXT(ROUND(E29/1000,0),"0")&"k",E29) -> #N/A | K29: {=INDEX(K$11:K$16,$S29)=$R29} -> FALSE | L29: {=INDEX(L$11:L$16,$S29)=$R29} -> FALSE | M29: {=INDEX(M$11:M$16,$S29)=$R29} -> FALSE | N29: {=INDEX(N$11:N$16,$S29)=$R29} -> FALSE | O29: {=INDEX(O$11:O$16,$S29)=$R29} -> FALSE | P29: {=INDEX(P$11:P$16,$S29)=$R29} -> FALSE | Q29: {=INDEX(Q$11:Q$16,$S29)=$R29} -> FALSE | R29: 1 | S29: =INT((ROW(A5)-1)/4)+1 -> 2
B30: =MAX(C18:C29)*5% -> 242.05 | E30: {=SUM(IFERROR(E18:E29,0))} -> 12533 | F30: {=SUM(ISNUMBER(E18:E29)*F18:F29)} -> 10302 | K30: {=INDEX(K$11:K$16,$S30)=$R30} -> TRUE | L30: {=INDEX(L$11:L$16,$S30)=$R30} -> TRUE | M30: {=INDEX(M$11:M$16,$S30)=$R30} -> TRUE | N30: {=INDEX(N$11:N$16,$S30)=$R30} -> TRUE | O30: {=INDEX(O$11:O$16,$S30)=$R30} -> TRUE | P30: {=INDEX(P$11:P$16,$S30)=$R30} -> TRUE | Q30: {=INDEX(Q$11:Q$16,$S30)=$R30} -> FALSE | R30: 2 | S30: =INT((ROW(A6)-1)/4)+1 -> 2
E31: Income | F31: Expenses | K31: {=INDEX(K$11:K$16,$S31)=$R31} -> FALSE | L31: {=INDEX(L$11:L$16,$S31)=$R31} -> FALSE | M31: {=INDEX(M$11:M$16,$S31)=$R31} -> FALSE | N31: {=INDEX(N$11:N$16,$S31)=$R31} -> FALSE | O31: {=INDEX(O$11:O$16,$S31)=$R31} -> FALSE | P31: {=INDEX(P$11:P$16,$S31)=$R31} -> FALSE | Q31: {=INDEX(Q$11:Q$16,$S31)=$R31} -> TRUE | R31: 3 | S31: =INT((ROW(A7)-1)/4)+1 -> 2
A32: Source Rating | K32: {=INDEX(K$11:K$16,$S32)=$R32} -> FALSE | L32: {=INDEX(L$11:L$16,$S32)=$R32} -> FALSE | M32: {=INDEX(M$11:M$16,$S32)=$R32} -> FALSE | N32: {=INDEX(N$11:N$16,$S32)=$R32} -> FALSE | O32: {=INDEX(O$11:O$16,$S32)=$R32} -> FALSE | P32: {=INDEX(P$11:P$16,$S32)=$R32} -> FALSE | Q32: {=INDEX(Q$11:Q$16,$S32)=$R32} -> FALSE | R32: 4 | S32: =INT((ROW(A8)-1)/4)+1 -> 2
A33: Sources | B33: indent | C33: Income | D33: Name | E33: indent | F33: Rank | K33: {=INDEX(K$11:K$16,$S33)=$R33} -> FALSE | L33: {=INDEX(L$11:L$16,$S33)=$R33} -> FALSE | M33: {=INDEX(M$11:M$16,$S33)=$R33} -> FALSE | N33: {=INDEX(N$11:N$16,$S33)=$R33} -> FALSE | O33: {=INDEX(O$11:O$16,$S33)=$R33} -> FALSE | P33: {=INDEX(P$11:P$16,$S33)=$R33} -> FALSE | Q33: {=INDEX(Q$11:Q$16,$S33)=$R33} -> FALSE | R33: 1 | S33: =INT((ROW(A9)-1)/4)+1 -> 3
A34: Savings | B34: =$B$38 -> 271.18 | C34: =GETPIVOTDATA(""&A34,Control!$A$3) -> 3874 | D34: {=_xlfn._xlws.SORT(A34:C37,3,-1)} -> Savings | E34: 271.18 | F34: 3874 | K34: {=INDEX(K$11:K$16,$S34)=$R34} -> FALSE | L34: {=INDEX(L$11:L$16,$S34)=$R34} -> TRUE | M34: {=INDEX(M$11:M$16,$S34)=$R34} -> FALSE | N34: {=INDEX(N$11:N$16,$S34)=$R34} -> FALSE | O34: {=INDEX(O$11:O$16,$S34)=$R34} -> FALSE | P34: {=INDEX(P$11:P$16,$S34)=$R34} -> TRUE | Q34: {=INDEX(Q$11:Q$16,$S34)=$R34} -> TRUE | R34: 2 | S34: =INT((ROW(A10)-1)/4)+1 -> 3
A35: Side Job | B35: =$B$38 -> 271.18 | C35: =GETPIVOTDATA(""&A35,Control!$A$3) -> 2607 | D35: Salary | E35: 271.18 | F35: 3546 | K35: {=INDEX(K$11:K$16,$S35)=$R35} -> TRUE | L35: {=INDEX(L$11:L$16,$S35)=$R35} -> FALSE | M35: {=INDEX(M$11:M$16,$S35)=$R35} -> TRUE | N35: {=INDEX(N$11:N$16,$S35)=$R35} -> TRUE | O35: {=INDEX(O$11:O$16,$S35)=$R35} -> TRUE | P35: {=INDEX(P$11:P$16,$S35)=$R35} -> FALSE | Q35: {=INDEX(Q$11:Q$16,$S35)=$R35} -> FALSE | R35: 3 | S35: =INT((ROW(A11)-1)/4)+1 -> 3
A36: Salary | B36: =$B$38 -> 271.18 | C36: =GETPIVOTDATA(""&A36,Control!$A$3) -> 3546 | D36: Side Job | E36: 271.18 | F36: 2607 | K36: {=INDEX(K$11:K$16,$S36)=$R36} -> FALSE | L36: {=INDEX(L$11:L$16,$S36)=$R36} -> FALSE | M36: {=INDEX(M$11:M$16,$S36)=$R36} -> FALSE | N36: {=INDEX(N$11:N$16,$S36)=$R36} -> FALSE | O36: {=INDEX(O$11:O$16,$S36)=$R36} -> FALSE | P36: {=INDEX(P$11:P$16,$S36)=$R36} -> FALSE | Q36: {=INDEX(Q$11:Q$16,$S36)=$R36} -> FALSE | R36: 4 | S36: =INT((ROW(A12)-1)/4)+1 -> 3
A37: Stock | B37: =$B$38 -> 271.18 | C37: =GETPIVOTDATA(""&A37,Control!$A$3) -> 2506 | D37: Stock | E37: 271.18 | F37: 2506 | K37: {=INDEX(K$11:K$16,$S37)=$R37} -> FALSE | L37: {=INDEX(L$11:L$16,$S37)=$R37} -> FALSE | M37: {=INDEX(M$11:M$16,$S37)=$R37} -> FALSE | N37: {=INDEX(N$11:N$16,$S37)=$R37} -> FALSE | O37: {=INDEX(O$11:O$16,$S37)=$R37} -> FALSE | P37: {=INDEX(P$11:P$16,$S37)=$R37} -> FALSE | Q37: {=INDEX(Q$11:Q$16,$S37)=$R37} -> FALSE | R37: 1 | S37: =INT((ROW(A13)-1)/4)+1 -> 4
B38: =MAX(C34:C37)*7% -> 271.18 | K38: {=INDEX(K$11:K$16,$S38)=$R38} -> FALSE | L38: {=INDEX(L$11:L$16,$S38)=$R38} -> FALSE | M38: {=INDEX(M$11:M$16,$S38)=$R38} -> FALSE | N38: {=INDEX(N$11:N$16,$S38)=$R38} -> TRUE | O38: {=INDEX(O$11:O$16,$S38)=$R38} -> FALSE | P38: {=INDEX(P$11:P$16,$S38)=$R38} -> FALSE | Q38: {=INDEX(Q$11:Q$16,$S38)=$R38} -> FALSE | R38: 2 | S38: =INT((ROW(A14)-1)/4)+1 -> 4
A39: Source Rating | K39: {=INDEX(K$11:K$16,$S39)=$R39} -> TRUE | L39: {=INDEX(L$11:L$16,$S39)=$R39} -> TRUE | M39: {=INDEX(M$11:M$16,$S39)=$R39} -> TRUE | N39: {=INDEX(N$11:N$16,$S39)=$R39} -> FALSE | O39: {=INDEX(O$11:O$16,$S39)=$R39} -> FALSE | P39: {=INDEX(P$11:P$16,$S39)=$R39} -> TRUE | Q39: {=INDEX(Q$11:Q$16,$S39)=$R39} -> TRUE | R39: 3 | S39: =INT((ROW(A15)-1)/4)+1 -> 4
A40: Year | B40: Income | C40: Cursor | D40: Labels | K40: {=INDEX(K$11:K$16,$S40)=$R40} -> FALSE | L40: {=INDEX(L$11:L$16,$S40)=$R40} -> FALSE | M40: {=INDEX(M$11:M$16,$S40)=$R40} -> FALSE | N40: {=INDEX(N$11:N$16,$S40)=$R40} -> FALSE | O40: {=INDEX(O$11:O$16,$S40)=$R40} -> TRUE | P40: {=INDEX(P$11:P$16,$S40)=$R40} -> FALSE | Q40: {=INDEX(Q$11:Q$16,$S40)=$R40} -> FALSE | R40: 4 | S40: =INT((ROW(A16)-1)/4)+1 -> 4
A41: 2027 | B41: =GETPIVOTDATA(""&B$40,Control!$A$44,"Year",A41) -> 37965 | C41: =IFERROR(GETPIVOTDATA(""&$B$40,Control!$A$35,"Year",$A41),NA()) -> #N/A | D41: =IF(C41>=1000,TEXT(ROUND(C41/1000,0),"0")&"k",C41) -> #N/A | K41: {=INDEX(K$11:K$16,$S41)=$R41} -> FALSE | L41: {=INDEX(L$11:L$16,$S41)=$R41} -> FALSE | M41: {=INDEX(M$11:M$16,$S41)=$R41} -> FALSE | N41: {=INDEX(N$11:N$16,$S41)=$R41} -> FALSE | O41: {=INDEX(O$11:O$16,$S41)=$R41} -> FALSE | P41: {=INDEX(P$11:P$16,$S41)=$R41} -> FALSE | Q41: {=INDEX(Q$11:Q$16,$S41)=$R41} -> TRUE | R41: 1 | S41: =INT((ROW(A17)-1)/4)+1 -> 5
A42: 2028 | B42: =GETPIVOTDATA(""&B$40,Control!$A$44,"Year",A42) -> 44200 | C42: =IFERROR(GETPIVOTDATA(""&$B$40,Control!$A$35,"Year",$A42),NA()) -> 44200 | D42: =IF(C42>=1000,TEXT(ROUND(C42/1000,0),"0")&"k",C42) -> 44k | K42: {=INDEX(K$11:K$16,$S42)=$R42} -> TRUE | L42: {=INDEX(L$11:L$16,$S42)=$R42} -> FALSE | M42: {=INDEX(M$11:M$16,$S42)=$R42} -> TRUE | N42: {=INDEX(N$11:N$16,$S42)=$R42} -> TRUE | O42: {=INDEX(O$11:O$16,$S42)=$R42} -> TRUE | P42: {=INDEX(P$11:P$16,$S42)=$R42} -> TRUE | Q42: {=INDEX(Q$11:Q$16,$S42)=$R42} -> FALSE | R42: 2 | S42: =INT((ROW(A18)-1)/4)+1 -> 5
A43: 2029 | B43: =GETPIVOTDATA(""&B$40,Control!$A$44,"Year",A43) -> 38780 | C43: =IFERROR(GETPIVOTDATA(""&$B$40,Control!$A$35,"Year",$A43),NA()) -> #N/A | D43: =IF(C43>=1000,TEXT(ROUND(C43/1000,0),"0")&"k",C43) -> #N/A | K43: {=INDEX(K$11:K$16,$S43)=$R43} -> FALSE | L43: {=INDEX(L$11:L$16,$S43)=$R43} -> FALSE | M43: {=INDEX(M$11:M$16,$S43)=$R43} -> FALSE | N43: {=INDEX(N$11:N$16,$S43)=$R43} -> FALSE | O43: {=INDEX(O$11:O$16,$S43)=$R43} -> FALSE | P43: {=INDEX(P$11:P$16,$S43)=$R43} -> FALSE | Q43: {=INDEX(Q$11:Q$16,$S43)=$R43} -> FALSE | R43: 3 | S43: =INT((ROW(A19)-1)/4)+1 -> 5
A44: 2030 | B44: =GETPIVOTDATA(""&B$40,Control!$A$44,"Year",A44) -> 53560 | C44: =IFERROR(GETPIVOTDATA(""&$B$40,Control!$A$35,"Year",$A44),NA()) -> #N/A | D44: =IF(C44>=1000,TEXT(ROUND(C44/1000,0),"0")&"k",C44) -> #N/A | K44: {=INDEX(K$11:K$16,$S44)=$R44} -> FALSE | L44: {=INDEX(L$11:L$16,$S44)=$R44} -> TRUE | M44: {=INDEX(M$11:M$16,$S44)=$R44} -> FALSE | N44: {=INDEX(N$11:N$16,$S44)=$R44} -> FALSE | O44: {=INDEX(O$11:O$16,$S44)=$R44} -> FALSE | P44: {=INDEX(P$11:P$16,$S44)=$R44} -> FALSE | Q44: {=INDEX(Q$11:Q$16,$S44)=$R44} -> FALSE | R44: 4 | S44: =INT((ROW(A20)-1)/4)+1 -> 5
B45: =SUM(B41:B44) -> 174505 | K45: {=INDEX(K$11:K$16,$S45)=$R45} -> TRUE | L45: {=INDEX(L$11:L$16,$S45)=$R45} -> TRUE | M45: {=INDEX(M$11:M$16,$S45)=$R45} -> TRUE | N45: {=INDEX(N$11:N$16,$S45)=$R45} -> TRUE | O45: {=INDEX(O$11:O$16,$S45)=$R45} -> TRUE | P45: {=INDEX(P$11:P$16,$S45)=$R45} -> TRUE | Q45: {=INDEX(Q$11:Q$16,$S45)=$R45} -> TRUE | R45: 1 | S45: =INT((ROW(A21)-1)/4)+1 -> 6
K46: {=INDEX(K$11:K$16,$S46)=$R46} -> FALSE | L46: {=INDEX(L$11:L$16,$S46)=$R46} -> FALSE | M46: {=INDEX(M$11:M$16,$S46)=$R46} -> FALSE | N46: {=INDEX(N$11:N$16,$S46)=$R46} -> FALSE | O46: {=INDEX(O$11:O$16,$S46)=$R46} -> FALSE | P46: {=INDEX(P$11:P$16,$S46)=$R46} -> FALSE | Q46: {=INDEX(Q$11:Q$16,$S46)=$R46} -> FALSE | R46: 2 | S46: =INT((ROW(A22)-1)/4)+1 -> 6
K47: {=INDEX(K$11:K$16,$S47)=$R47} -> FALSE | L47: {=INDEX(L$11:L$16,$S47)=$R47} -> FALSE | M47: {=INDEX(M$11:M$16,$S47)=$R47} -> FALSE | N47: {=INDEX(N$11:N$16,$S47)=$R47} -> FALSE | O47: {=INDEX(O$11:O$16,$S47)=$R47} -> FALSE | P47: {=INDEX(P$11:P$16,$S47)=$R47} -> FALSE | Q47: {=INDEX(Q$11:Q$16,$S47)=$R47} -> FALSE | R47: 3 | S47: =INT((ROW(A23)-1)/4)+1 -> 6
K48: {=INDEX(K$11:K$16,$S48)=$R48} -> FALSE | L48: {=INDEX(L$11:L$16,$S48)=$R48} -> FALSE | M48: {=INDEX(M$11:M$16,$S48)=$R48} -> FALSE | N48: {=INDEX(N$11:N$16,$S48)=$R48} -> FALSE | O48: {=INDEX(O$11:O$16,$S48)=$R48} -> FALSE | P48: {=INDEX(P$11:P$16,$S48)=$R48} -> FALSE | Q48: {=INDEX(Q$11:Q$16,$S48)=$R48} -> FALSE | R48: 4 | S48: =INT((ROW(A24)-1)/4)+1 -> 6
D50: =ISNUMBER(MATCH(D51,Control!$A$59:$A$66,0)) -> FALSE | E50: =ISNUMBER(MATCH(E51,Control!$A$59:$A$66,0)) -> TRUE | F50: =ISNUMBER(MATCH(F51,Control!$A$59:$A$66,0)) -> TRUE | G50: =ISNUMBER(MATCH(G51,Control!$A$59:$A$66,0)) -> TRUE | H50: =ISNUMBER(MATCH(H51,Control!$A$59:$A$66,0)) -> FALSE | J50: Essential Costs
B51: Expense Categories | C51: Buttons | D51: {=TRANSPOSE(_xlfn._xlws.SORT($J$52:$J$56))} -> Entertainment | E51: FoodCourt | F51: Supermarket | G51: Travel | H51: Workplace | I51: Total | J51: Expense Areas | K51: Buttons | L51: Costs
A52: =ISNUMBER(MATCH(B52,Control!$A$68:$A$72,0)) -> TRUE | B52: Eating | C52: =LEFT(B52,1) -> E | D52: =IF($A52,IF(D$50,GETPIVOTDATA($B52&" "&LEFT(D$51,1),Control!$A$3),NA()),0) -> #N/A | E52: =IF($A52,IF(E$50,GETPIVOTDATA($B52&" "&LEFT(E$51,1),Control!$A$3),NA()),0) -> 342 | F52: =IF($A52,IF(F$50,GETPIVOTDATA($B52&" "&LEFT(F$51,1),Control!$A$3),NA()),0) -> 524 | G52: =IF($A52,IF(G$50,GETPIVOTDATA($B52&" "&LEFT(G$51,1),Control!$A$3),NA()),0) -> 238 | H52: =IF($A52,IF(H$50,GETPIVOTDATA($B52&" "&LEFT(H$51,1),Control!$A$3),NA()),0) -> #N/A | I52: {=SUM(IFERROR(D52:H52,0))} -> 1104 | J52: Entertainment | K52: =LEFT(J52,1) -> E | L52: =IF(M52,GETPIVOTDATA(""&J52,Control!$A$3),"") | M52: =ISNUMBER(MATCH(J52,Control!$A$59:$A$63,0)) -> FALSE | N52: =IF(M52,J52,"")
A53: =ISNUMBER(MATCH(B53,Control!$A$68:$A$72,0)) -> TRUE | B53: Fuel | C53: =LEFT(B53,1) -> F | D53: =IF($A53,IF(D$50,GETPIVOTDATA($B53&" "&LEFT(D$51,1),Control!$A$3),NA()),0) -> #N/A | E53: =IF($A53,IF(E$50,GETPIVOTDATA($B53&" "&LEFT(E$51,1),Control!$A$3),NA()),0) -> 298 | F53: =IF($A53,IF(F$50,GETPIVOTDATA($B53&" "&LEFT(F$51,1),Control!$A$3),NA()),0) -> 550 | G53: =IF($A53,IF(G$50,GETPIVOTDATA($B53&" "&LEFT(G$51,1),Control!$A$3),NA()),0) -> 459 | H53: =IF($A53,IF(H$50,GETPIVOTDATA($B53&" "&LEFT(H$51,1),Control!$A$3),NA()),0) -> #N/A | I53: {=SUM(IFERROR(D53:H53,0))} -> 1307 | J53: FoodCourt | K53: =LEFT(J53,1) -> F | L53: =IF(M53,GETPIVOTDATA(""&J53,Control!$A$3),"") -> 1595 | M53: =ISNUMBER(MATCH(J53,Control!$A$59:$A$63,0)) -> TRUE | N53: =IF(M53,J53,"") -> FoodCourt
A54: =ISNUMBER(MATCH(B54,Control!$A$68:$A$72,0)) -> TRUE | B54: Hobbies | C54: =LEFT(B54,1) -> H | D54: =IF($A54,IF(D$50,GETPIVOTDATA($B54&" "&LEFT(D$51,1),Control!$A$3),NA()),0) -> #N/A | E54: =IF($A54,IF(E$50,GETPIVOTDATA($B54&" "&LEFT(E$51,1),Control!$A$3),NA()),0) -> 319 | F54: =IF($A54,IF(F$50,GETPIVOTDATA($B54&" "&LEFT(F$51,1),Control!$A$3),NA()),0) -> 498 | G54: =IF($A54,IF(G$50,GETPIVOTDATA($B54&" "&LEFT(G$51,1),Control!$A$3),NA()),0) -> 370 | H54: =IF($A54,IF(H$50,GETPIVOTDATA($B54&" "&LEFT(H$51,1),Control!$A$3),NA()),0) -> #N/A | I54: {=SUM(IFERROR(D54:H54,0))} -> 1187 | J54: Supermarket | K54: =LEFT(J54,1) -> S | L54: =IF(M54,GETPIVOTDATA(""&J54,Control!$A$3),"") -> 2487 | M54: =ISNUMBER(MATCH(J54,Control!$A$59:$A$63,0)) -> TRUE | N54: =IF(M54,J54,"") -> Supermarket
A55: =ISNUMBER(MATCH(B55,Control!$A$68:$A$72,0)) -> TRUE | B55: Leisure | C55: =LEFT(B55,1) -> L | D55: =IF($A55,IF(D$50,GETPIVOTDATA($B55&" "&LEFT(D$51,1),Control!$A$3),NA()),0) -> #N/A | E55: =IF($A55,IF(E$50,GETPIVOTDATA($B55&" "&LEFT(E$51,1),Control!$A$3),NA()),0) -> 314 | F55: =IF($A55,IF(F$50,GETPIVOTDATA($B55&" "&LEFT(F$51,1),Control!$A$3),NA()),0) -> 406 | G55: =IF($A55,IF(G$50,GETPIVOTDATA($B55&" "&LEFT(G$51,1),Control!$A$3),NA()),0) -> 467 | H55: =IF($A55,IF(H$50,GETPIVOTDATA($B55&" "&LEFT(H$51,1),Control!$A$3),NA()),0) -> #N/A | I55: {=SUM(IFERROR(D55:H55,0))} -> 1187 | J55: Travel | K55: =LEFT(J55,1) -> T | L55: =IF(M55,GETPIVOTDATA(""&J55,Control!$A$3),"") -> 1847 | M55: =ISNUMBER(MATCH(J55,Control!$A$59:$A$63,0)) -> TRUE | N55: =IF(M55,J55,"") -> Travel
A56: =ISNUMBER(MATCH(B56,Control!$A$68:$A$72,0)) -> TRUE | B56: Shopping | C56: =LEFT(B56,1) -> S | D56: =IF($A56,IF(D$50,GETPIVOTDATA($B56&" "&LEFT(D$51,1),Control!$A$3),NA()),0) -> #N/A | E56: =IF($A56,IF(E$50,GETPIVOTDATA($B56&" "&LEFT(E$51,1),Control!$A$3),NA()),0) -> 322 | F56: =IF($A56,IF(F$50,GETPIVOTDATA($B56&" "&LEFT(F$51,1),Control!$A$3),NA()),0) -> 509 | G56: =IF($A56,IF(G$50,GETPIVOTDATA($B56&" "&LEFT(G$51,1),Control!$A$3),NA()),0) -> 313 | H56: =IF($A56,IF(H$50,GETPIVOTDATA($B56&" "&LEFT(H$51,1),Control!$A$3),NA()),0) -> #N/A | I56: {=SUM(IFERROR(D56:H56,0))} -> 1144 | J56: Workplace | K56: =LEFT(J56,1) -> W | L56: =IF(M56,GETPIVOTDATA(""&J56,Control!$A$3),"") | M56: =ISNUMBER(MATCH(J56,Control!$A$59:$A$63,0)) -> FALSE | N56: =IF(M56,J56,"")
C57: Cursor | D57: =SUM(D52:D56) -> #N/A | E57: =SUM(E52:E56) -> 1595 | F57: =SUM(F52:F56) -> 2487 | G57: =SUM(G52:G56) -> 1847 | H57: =SUM(H52:H56) -> #N/A | I57: =SUM(I52:I56) -> 5929 | L57: {=SUM(M52:M56*IFERROR(L52:L56*1,0))} -> 5929
C58: indent Cursor | D58: =D60 -> 174.09 | E58: =E60 -> 174.09 | F58: =F60 -> 174.09 | G58: =G60 -> 174.09 | H58: =H60 -> 174.09
C59: Total | D59: =GETPIVOTDATA(""&D51,Control!$A$3) -> 2311 | E59: =GETPIVOTDATA(""&E51,Control!$A$3) -> 1595 | F59: =GETPIVOTDATA(""&F51,Control!$A$3) -> 2487 | G59: =GETPIVOTDATA(""&G51,Control!$A$3) -> 1847 | H59: =GETPIVOTDATA(""&H51,Control!$A$3) -> 2062
C60: indent | D60: =$I$60 -> 174.09 | E60: =$I$60 -> 174.09 | F60: =$I$60 -> 174.09 | G60: =$I$60 -> 174.09 | H60: =$I$60 -> 174.09 | I60: {=MAX(IFERROR(D59:H59,0))*7%} -> 174.09
C61: Markers | D61: =D57+D58 -> #N/A | E61: =E57+E58 -> 1769.09 | F61: =F57+F58 -> 2661.09 | G61: =G57+G58 -> 2021.09 | H61: =H57+H58 -> #N/A
C62: Labels | D62: =IF(ISNUMBER(D57),IF(D57>=1000,TEXT(ROUND(D57/1000,0),"0")&"k",D57),"") | E62: =IF(ISNUMBER(E57),IF(E57>=1000,TEXT(ROUND(E57/1000,0),"0")&"k",E57),"") -> 2k | F62: =IF(ISNUMBER(F57),IF(F57>=1000,TEXT(ROUND(F57/1000,0),"0")&"k",F57),"") -> 2k | G62: =IF(ISNUMBER(G57),IF(G57>=1000,TEXT(ROUND(G57/1000,0),"0")&"k",G57),"") -> 2k | H62: =IF(ISNUMBER(H57),IF(H57>=1000,TEXT(ROUND(H57/1000,0),"0")&"k",H57),"")
A64: 72 | B64: 72 | C64: 72 | D64: 72 | E64: 72
A65: 72 | B65: 72 | C65: 72 | D65: 72 | E65: 72
A66: 72 | B66: 72 | C66: 72 | D66: 72 | E66: 72
B73: Eating | D73: Entertainment
B74: Fuel | D74: FoodCourt
B75: Hobbies | D75: Supermarket
B76: Leisure | D76: Travel
B77: Shopping | D77: Workplace

Sheet Control
A3: Row Labels | B3: Max of Num Month | C3: Sum of Income | D3: Sum of Expenses | E3: Sum of Savings | F3: Sum of Side Job | G3: Sum of Salary | H3: Sum of Stock | I3: Sum of Travel | J3: Sum of FoodCourt | K3: Sum of Supermarket | L3: Sum of Entertainment | M3: Sum of Workplace | N3: Sum of Eating T | O3: Sum of Fuel T | P3: Sum of Leisure T | Q3: Sum of Shopping T | R3: Sum of Hobbies T | S3: Sum of Eating F | T3: Sum of Fuel F | U3: Sum of Leisure F | V3: Sum of Shopping F | W3: Sum of Hobbies F | X3: Sum of Eating S | Y3: Sum of Eating E | Z3: Sum of Fuel E | AA3: Sum of Leisure E | AB3: Sum of Shopping E | AC3: Sum of Hobbies E | AD3: Sum of Eating W | AE3: Sum of Fuel W | AF3: Sum of Leisure W | AG3: Sum of Shopping W | AH3: Sum of Hobbies W | AI3: Sum of Fuel S | AJ3: Sum of Leisure S | AK3: Sum of Hobbies S | AL3: Sum of Shopping S | AM3: Sum of Target 1 | AN3: Sum of Target 2 | AO3: Sum of Target 3 | AP3: Sum of Target 4 | AQ3: Sum of Target 5
A4: APR | B4: 4 | C4: 4841 | D4: 2671 | E4: 1798 | F4: 1134 | G4: 941 | H4: 968 | I4: 547 | J4: 527 | K4: 646 | L4: 417 | M4: 534 | N4: 54 | O4: 143 | P4: 139 | Q4: 101 | R4: 110 | S4: 85 | T4: 154 | U4: 124 | V4: 58 | W4: 106 | X4: 167 | Y4: 106 | Z4: 48 | AA4: 60 | AB4: 120 | AC4: 83 | AD4: 142 | AE4: 84 | AF4: 107 | AG4: 94 | AH4: 107 | AI4: 88 | AJ4: 153 | AK4: 130 | AL4: 108 | AM4: 0 | AN4: 500 | AO4: 700 | AP4: 0 | AQ4: 0
A5: MAY | B5: 5 | C5: 4626 | D5: 3036 | E5: 931 | F5: 982 | G5: 1787 | H5: 926 | I5: 545 | J5: 632 | K5: 582 | L5: 669 | M5: 608 | N5: 56 | O5: 103 | P5: 161 | Q5: 116 | R5: 109 | S5: 131 | T5: 68 | U5: 147 | V5: 160 | W5: 126 | X5: 91 | Y5: 113 | Z5: 145 | AA5: 159 | AB5: 118 | AC5: 134 | AD5: 112 | AE5: 73 | AF5: 142 | AG5: 160 | AH5: 121 | AI5: 136 | AJ5: 136 | AK5: 116 | AL5: 103 | AM5: 0 | AN5: 0 | AO5: 700 | AP5: 500 | AQ5: 0
A6: JUN | B6: 6 | C6: 3066 | D6: 4595 | E6: 1145 | F6: 491 | G6: 818 | H6: 612 | I6: 755 | J6: 436 | K6: 1259 | L6: 1225 | M6: 920 | N6: 128 | O6: 213 | P6: 167 | Q6: 96 | R6: 151 | S6: 126 | T6: 76 | U6: 43 | V6: 104 | W6: 87 | X6: 266 | Y6: 340 | Z6: 236 | AA6: 197 | AB6: 207 | AC6: 245 | AD6: 184 | AE6: 191 | AF6: 187 | AG6: 174 | AH6: 184 | AI6: 326 | AJ6: 117 | AK6: 252 | AL6: 298 | AM6: 0 | AN6: 0 | AO6: 0 | AP6: 500 | AQ6: 0
A7: Grand Total | B7: 6 | C7: 12533 | D7: 10302 | E7: 3874 | F7: 2607 | G7: 3546 | H7: 2506 | I7: 1847 | J7: 1595 | K7: 2487 | L7: 2311 | M7: 2062 | N7: 238 | O7: 459 | P7: 467 | Q7: 313 | R7: 370 | S7: 342 | T7: 298 | U7: 314 | V7: 322 | W7: 319 | X7: 524 | Y7: 559 | Z7: 429 | AA7: 416 | AB7: 445 | AC7: 462 | AD7: 438 | AE7: 348 | AF7: 436 | AG7: 428 | AH7: 412 | AI7: 550 | AJ7: 406 | AK7: 498 | AL7: 509 | AM7: 0 | AN7: 500 | AO7: 1400 | AP7: 1000 | AQ7: 0
A20: Row Labels | B20: Sum of Target 1 | C20: Sum of Target 2 | D20: Sum of Target 3 | E20: Sum of Target 4 | F20: Sum of Target 5 | G20: Sum of Income | H20: Sum of Expenses
A21: JAN | B21: 400 | C21: 0 | D21: 0 | E21: 0 | F21: 0 | G21: 2075 | H21: 2412
A22: FEB | B22: 400 | C22: 500 | D22: 0 | E22: 0 | F22: 0 | G22: 3066 | H22: 1696
A23: MAR | B23: 0 | C23: 500 | D23: 0 | E23: 0 | F23: 0 | G23: 4626 | H23: 3544
A24: APR | B24: 0 | C24: 500 | D24: 700 | E24: 0 | F24: 0 | G24: 4841 | H24: 2671
A25: MAY | B25: 0 | C25: 0 | D25: 700 | E25: 500 | F25: 0 | G25: 4626 | H25: 3036
A26: JUN | B26: 0 | C26: 0 | D26: 0 | E26: 500 | F26: 0 | G26: 3066 | H26: 4595
A27: JUL | B27: 0 | C27: 0 | D27: 0 | E27: 500 | F27: 0 | G27: 2075 | H27: 2714
A28: AUG | B28: 0 | C28: 0 | D28: 0 | E28: 500 | F28: 300 | G28: 3066 | H28: 3731
A29: SEP | B29: 0 | C29: 0 | D29: 0 | E29: 0 | F29: 300 | G29: 4626 | H29: 4952
A30: OCT | B30: 0 | C30: 0 | D30: 0 | E30: 0 | F30: 300 | G30: 4841 | H30: 3544
A31: NOV | B31: 0 | C31: 0 | D31: 0 | E31: 0 | F31: 300 | G31: 4626 | H31: 4595
A32: DEC | B32: 0 | C32: 0 | D32: 0 | E32: 0 | F32: 300 | G32: 2666 | H32: 1739
A33: Grand Total | B33: 800 | C33: 1500 | D33: 1400 | E33: 2000 | F33: 1500 | G33: 44200 | H33: 39229
A35: Row Labels | B35: Sum of Income
A36: 2028 | B36: 44200
A37: Grand Total | B37: 44200
A44: Row Labels | B44: Sum of Income
A45: 2027 | B45: 37965
A46: 2028 | B46: 44200
A47: 2029 | B47: 38780
A48: 2030 | B48: 53560
A49: Grand Total | B49: 174505
A51: Row Labels
A52: 2028
A58: Row Labels
A59: FoodCourt
A60: Supermarket
A61: Travel
A62: Grand Total
A67: Row Labels
A68: Eating
A69: Fuel
A70: Hobbies
A71: Leisure
A72: Shopping
A73: Grand Total

Sheet Data
A1: Year | B1: Month | C1: Num Month | D1: Target 1 | E1: Target 2 | F1: Target 3 | G1: Target 4 | H1: Target 5 | I1: Income | J1: Expenses | K1: Savings | L1: Side Job | M1: Salary | N1: Stock | O1: Travel | P1: Eating T | Q1: Fuel T | R1: Leisure T | S1: Shopping T | T1: Hobbies T | U1: FoodCourt | V1: Eating F | W1: Fuel F | X1: Leisure F | Y1: Shopping F | Z1: Hobbies F | AA1: Supermarket | AB1: Eating S | AC1: Fuel S | AD1: Leisure S | AE1: Shopping S | AF1: Hobbies S | AG1: Entertainment | AH1: Eating E | AI1: Fuel E | AJ1: Leisure E | AK1: Shopping E | AL1: Hobbies E | AM1: Workplace | AN1: Eating W | AO1: Fuel W | AP1: Leisure W | AQ1: Shopping W | AR1: Hobbies W
A2: 2027 | B2: JAN | C2: 1 | D2: 200 | E2: 0 | F2: 0 | G2: 0 | H2: 0 | I2: 1245 | J2: 1623 | K2: 462 | L2: 195 | M2: 339 | N2: 249 | O2: 315 | P2: 83 | Q2: 43 | R2: 89 | S2: 37 | T2: 63 | U2: 315 | V2: 40 | W2: 83 | X2: 72 | Y2: 57 | Z2: 63 | AA2: 197 | AB2: 47 | AC2: 49 | AD2: 24 | AE2: 38 | AF2: 39 | AG2: 472 | AH2: 114 | AI2: 58 | AJ2: 116 | AK2: 89 | AL2: 95 | AM2: 324 | AN2: 63 | AO2: 73 | AP2: 65 | AQ2: 58 | AR2: 65
A3: 2027 | B3: FEB | C3: 2 | D3: 200 | E3: 100 | F3: 0 | G3: 0 | H3: 0 | I3: 2555 | J3: 2535 | K3: 861 | L3: 707 | M3: 476 | N3: 511 | O3: 664 | P3: 118 | Q3: 138 | R3: 155 | S3: 121 | T3: 132 | U3: 440 | V3: 56 | W3: 116 | X3: 64 | Y3: 116 | Z3: 88 | AA3: 341 | AB3: 46 | AC3: 49 | AD3: 120 | AE3: 57 | AF3: 69 | AG3: 583 | AH3: 116 | AI3: 155 | AJ3: 114 | AK3: 81 | AL3: 117 | AM3: 507 | AN3: 75 | AO3: 108 | AP3: 84 | AQ3: 138 | AR3: 102
A4: 2027 | B4: MAR | C4: 3 | D4: 200 | E4: 100 | F4: 0 | G4: 0 | H4: 0 | I4: 2955 | J4: 1959 | K4: 949 | L4: 365 | M4: 1051 | N4: 590 | O4: 293 | P4: 47 | Q4: 50 | R4: 62 | S4: 76 | T4: 58 | U4: 540 | V4: 103 | W4: 64 | X4: 110 | Y4: 156 | Z4: 107 | AA4: 317 | AB4: 87 | AC4: 38 | AD4: 83 | AE4: 45 | AF4: 64 | AG4: 417 | AH4: 100 | AI4: 85 | AJ4: 52 | AK4: 96 | AL4: 84 | AM4: 392 | AN4: 134 | AO4: 77 | AP4: 54 | AQ4: 48 | AR4: 79
A5: 2027 | B5: APR | C5: 4 | D5: 0 | E5: 100 | F5: 0 | G5: 0 | H5: 0 | I5: 3260 | J5: 2877 | K5: 988 | L5: 771 | M5: 850 | N5: 651 | O5: 506 | P5: 93 | Q5: 105 | R5: 120 | S5: 88 | T5: 100 | U5: 401 | V5: 87 | W5: 106 | X5: 44 | Y5: 84 | Z5: 80 | AA5: 697 | AB5: 109 | AC5: 191 | AD5: 122 | AE5: 135 | AF5: 140 | AG5: 697 | AH5: 93 | AI5: 168 | AJ5: 192 | AK5: 104 | AL5: 140 | AM5: 576 | AN5: 143 | AO5: 118 | AP5: 145 | AQ5: 54 | AR5: 116
A6: 2027 | B6: MAY | C6: 5 | D6: 0 | E6: 100 | F6: 0 | G6: 0 | H6: 0 | I6: 2675 | J6: 1968 | K6: 774 | L6: 665 | M6: 701 | N6: 535 | O6: 285 | P6: 75 | Q6: 69 | R6: 56 | S6: 29 | T6: 56 | U6: 598 | V6: 146 | W6: 73 | X6: 122 | Y6: 137 | Z6: 120 | AA6: 313 | AB6: 82 | AC6: 55 | AD6: 54 | AE6: 60 | AF6: 62 | AG6: 377 | AH6: 112 | AI6: 48 | AJ6: 68 | AK6: 73 | AL6: 76 | AM6: 395 | AN6: 99 | AO6: 72 | AP6: 78 | AQ6: 68 | AR6: 78
A7: 2027 | B7: JUN | C7: 6 | D7: 0 | E7: 100 | F7: 300 | G7: 0 | H7: 0 | I7: 3020 | J7: 3180 | K7: 519 | L7: 1278 | M7: 619 | N7: 604 | O7: 843 | P7: 170 | Q7: 189 | R7: 204 | S7: 111 | T7: 169 | U7: 484 | V7: 77 | W7: 89 | X7: 117 | Y7: 103 | Z7: 98 | AA7: 498 | AB7: 48 | AC7: 96 | AD7: 133 | AE7: 122 | AF7: 99 | AG7: 719 | AH7: 146 | AI7: 180 | AJ7: 79 | AK7: 170 | AL7: 144 | AM7: 636 | AN7: 147 | AO7: 181 | AP7: 89 | AQ7: 92 | AR7: 127
A8: 2027 | B8: JUL | C8: 7 | D8: 0 | E8: 100 | F8: 300 | G8: 200 | H8: 0 | I8: 3655 | J8: 1921 | K8: 851 | L8: 1004 | M8: 1069 | N8: 731 | O8: 421 | P8: 75 | Q8: 51 | R8: 116 | S8: 95 | T8: 84 | U8: 439 | V8: 129 | W8: 79 | X8: 81 | Y8: 62 | Z8: 88 | AA8: 360 | AB8: 77 | AC8: 67 | AD8: 95 | AE8: 49 | AF8: 72 | AG8: 317 | AH8: 55 | AI8: 75 | AJ8: 59 | AK8: 65 | AL8: 63 | AM8: 384 | AN8: 84 | AO8: 107 | AP8: 54 | AQ8: 62 | AR8: 77
A9: 2027 | B9: AUG | C9: 8 | D9: 0 | E9: 0 | F9: 300 | G9: 200 | H9: 0 | I9: 3000 | J9: 3068 | K9: 688 | L9: 1070 | M9: 642 | N9: 600 | O9: 453 | P9: 100 | Q9: 81 | R9: 51 | S9: 130 | T9: 91 | U9: 417 | V9: 67 | W9: 64 | X9: 102 | Y9: 101 | Z9: 83 | AA9: 715 | AB9: 98 | AC9: 192 | AD9: 154 | AE9: 128 | AF9: 143 | AG9: 870 | AH9: 275 | AI9: 205 | AJ9: 100 | AK9: 115 | AL9: 175 | AM9: 613 | AN9: 94 | AO9: 104 | AP9: 155 | AQ9: 138 | AR9: 122
A10: 2027 | B10: SEP | C10: 9 | D10: 0 | E10: 0 | F10: 300 | G10: 200 | H10: 0 | I10: 3445 | J10: 2527 | K10: 1160 | L10: 526 | M10: 1070 | N10: 689 | O10: 382 | P10: 110 | Q10: 56 | R10: 48 | S10: 91 | T10: 77 | U10: 501 | V10: 65 | W10: 140 | X10: 118 | Y10: 77 | Z10: 101 | AA10: 565 | AB10: 82 | AC10: 120 | AD10: 111 | AE10: 139 | AF10: 113 | AG10: 574 | AH10: 86 | AI10: 77 | AJ10: 136 | AK10: 160 | AL10: 115 | AM10: 505 | AN10: 160 | AO10: 90 | AP10: 68 | AQ10: 86 | AR10: 101
A11: 2027 | B11: OCT | C11: 10 | D11: 0 | E11: 0 | F11: 0 | G11: 200 | H11: 100 | I11: 4040 | J11: 3467 | K11: 1237 | L11: 739 | M11: 1256 | N11: 808 | O11: 630 | P11: 177 | Q11: 82 | R11: 125 | S11: 120 | T11: 126 | U11: 683 | V11: 206 | W11: 157 | X11: 77 | Y11: 106 | Z11: 137 | AA11: 911 | AB11: 220 | AC11: 196 | AD11: 132 | AE11: 181 | AF11: 182 | AG11: 549 | AH11: 99 | AI11: 142 | AJ11: 76 | AK11: 122 | AL11: 110 | AM11: 694 | AN11: 165 | AO11: 133 | AP11: 159 | AQ11: 98 | AR11: 139
A12: 2027 | B12: NOV | C12: 11 | D12: 0 | E12: 0 | F12: 0 | G12: 200 | H12: 100 | I12: 3695 | J12: 2716 | K12: 1267 | L12: 880 | M12: 809 | N12: 739 | O12: 377 | P12: 66 | Q12: 72 | R12: 103 | S12: 61 | T12: 75 | U12: 890 | V12: 108 | W12: 170 | X12: 298 | Y12: 137 | Z12: 177 | AA12: 498 | AB12: 114 | AC12: 116 | AD12: 72 | AE12: 96 | AF12: 100 | AG12: 407 | AH12: 61 | AI12: 114 | AJ12: 67 | AK12: 84 | AL12: 81 | AM12: 544 | AN12: 133 | AO12: 120 | AP12: 61 | AQ12: 122 | AR12: 108
A13: 2027 | B13: DEC | C13: 12 | D13: 0 | E13: 0 | F13: 0 | G13: 0 | H13: 100 | I13: 4420 | J13: 3608 | K13: 1572 | L13: 859 | M13: 1105 | N13: 884 | O13: 901 | P13: 195 | Q13: 184 | R13: 168 | S13: 173 | T13: 181 | U13: 817 | V13: 117 | W13: 147 | X13: 246 | Y13: 144 | Z13: 163 | AA13: 746 | AB13: 190 | AC13: 113 | AD13: 127 | AE13: 167 | AF13: 149 | AG13: 422 | AH13: 84 | AI13: 128 | AJ13: 46 | AK13: 80 | AL13: 84 | AM13: 722 | AN13: 170 | AO13: 173 | AP13: 170 | AQ13: 64 | AR13: 145
... A49: 2030 | B49: DEC | C49: 12 | D49: 0 | E49: 0 | F49: 0 | G49: 0 | H49: 500 | I49: 4333 | J49: 5536 | K49: 969 | L49: 1616 | M49: 881 | N49: 867 | O49: 970 | P49: 211 | Q49: 154 | R49: 246 | S49: 165 | T49: 194 | U49: 647 | V49: 182 | W49: 105 | X49: 121 | Y49: 109 | Z49: 130 | AA49: 1866 | AB49: 452 | AC49: 433 | AD49: 257 | AE49: 351 | AF49: 373 | AG49: 945 | AH49: 166 | AI49: 252 | AJ49: 97 | AK49: 241 | AL49: 189 | AM49: 1108 | AN49: 185 | AO49: 200 | AP49: 239 | AQ49: 262 | AR49: 222

Sheet heatmap-DATA
A1: Year | B1: Month | C1: Week | D1: 1 | E1: 2 | F1: 3 | G1: 4 | H1: 5 | I1: 6 | J1: 7 | K1: 1 | L1: 2 | M1: 3 | N1: 4 | O1: 5 | P1: 6 | Q1: 7 | S1: 1 | U1: NON
A2: 2027 | B2: 1 | C2: 1 | D2: 1 | E2: 1 | F2: 3 | G2: 1 | H2: 1 | I2: 2 | J2: 2 | K2: =IF(D2<>1,"ERROR!!!","") | L2: =IF(E2<>1,"ERROR!!!","") | M2: =IF(F2<>1,"ERROR!!!","") -> ERROR!!! | N2: =IF(G2<>1,"ERROR!!!","") | O2: =IF(H2<>1,"ERROR!!!","") | P2: =_xlfn.LET(_xlpm.StartDay, WEEKDAY(DATE($A2, $B2, 1), 1),_xlpm.DayNum, (COLUMN() - COLUMN($K$2) + 1) + (ROW() - ROW($K$2)) * 7 - _xlpm.StartDay + 1,IF(AND(_xlpm.DayNum > 0, _xlpm.DayNum <= DAY(EOMONTH(DATE($A2, $B2, 1), 0))), _xlpm.DayNum, "")) -> 1 | Q2: =_xlfn.LET(_xlpm.StartDay, WEEKDAY(DATE($A2, $B2, 1), 1),_xlpm.DayNum, (COLUMN() - COLUMN($K$2) + 1) + (ROW() - ROW($K$2)) * 7 - _xlpm.StartDay + 1,IF(AND(_xlpm.DayNum > 0, _xlpm.DayNum <= DAY(EOMONTH(DATE($A2, $B2, 1), 0))), _xlpm.DayNum, "")) -> 2 | S2: 2 | U2: LOW
A3: 2027 | B3: 1 | C3: 2 | D3: 3 | E3: 2 | F3: 4 | G3: 2 | H3: 3 | I3: 4 | J3: 2 | K3: =_xlfn.LET(_xlpm.StartDay, WEEKDAY(DATE($A3, $B3, 1), 1),_xlpm.DayNum, (COLUMN() - COLUMN($K$2) + 1) + (ROW() - ROW($K$2)) * 7 - _xlpm.StartDay + 1,IF(AND(_xlpm.DayNum > 0, _xlpm.DayNum <= DAY(EOMONTH(DATE($A3, $B3, 1), 0))), _xlpm.DayNum, "")) -> 3 | L3: =_xlfn.LET(_xlpm.StartDay, WEEKDAY(DATE($A3, $B3, 1), 1),_xlpm.DayNum, (COLUMN() - COLUMN($K$2) + 1) + (ROW() - ROW($K$2)) * 7 - _xlpm.StartDay + 1,IF(AND(_xlpm.DayNum > 0, _xlpm.DayNum <= DAY(EOMONTH(DATE($A3, $B3, 1), 0))), _xlpm.DayNum, "")) -> 4 | M3: =_xlfn.LET(_xlpm.StartDay, WEEKDAY(DATE($A3, $B3, 1), 1),_xlpm.DayNum, (COLUMN() - COLUMN($K$2) + 1) + (ROW() - ROW($K$2)) * 7 - _xlpm.StartDay + 1,IF(AND(_xlpm.DayNum > 0, _xlpm.DayNum <= DAY(EOMONTH(DATE($A3, $B3, 1), 0))), _xlpm.DayNum, "")) -> 5 | N3: =_xlfn.LET(_xlpm.StartDay, WEEKDAY(DATE($A3, $B3, 1), 1),_xlpm.DayNum, (COLUMN() - COLUMN($K$2) + 1) + (ROW() - ROW($K$2)) * 7 - _xlpm.StartDay + 1,IF(AND(_xlpm.DayNum > 0, _xlpm.DayNum <= DAY(EOMONTH(DATE($A3, $B3, 1), 0))), _xlpm.DayNum, "")) -> 6 | O3: =_xlfn.LET(_xlpm.StartDay, WEEKDAY(DATE($A3, $B3, 1), 1),_xlpm.DayNum, (COLUMN() - COLUMN($K$2) + 1) + (ROW() - ROW($K$2)) * 7 - _xlpm.StartDay + 1,IF(AND(_xlpm.DayNum > 0, _xlpm.DayNum <= DAY(EOMONTH(DATE($A3, $B3, 1), 0))), _xlpm.DayNum, "")) -> 7 | P3: =_xlfn.LET(_xlpm.StartDay, WEEKDAY(DATE($A3, $B3, 1), 1),_xlpm.DayNum, (COLUMN() - COLUMN($K$2) + 1) + (ROW() - ROW($K$2)) * 7 - _xlpm.StartDay + 1,IF(AND(_xlpm.DayNum > 0, _xlpm.DayNum <= DAY(EOMONTH(DATE($A3, $B3, 1), 0))), _xlpm.DayNum, "")) -> 8 | Q3: =_xlfn.LET(_xlpm.StartDay, WEEKDAY(DATE($A3, $B3, 1), 1),_xlpm.DayNum, (COLUMN() - COLUMN($K$2) + 1) + (ROW() - ROW($K$2)) * 7 - _xlpm.StartDay + 1,IF(AND(_xlpm.DayNum > 0, _xlpm.DayNum <= DAY(EOMONTH(DATE($A3, $B3, 1), 0))), _xlpm.DayNum, "")) -> 9 | S3: 3 | U3: MIDDLE
A4: 2027 | B4: 1 | C4: 3 | D4: 3 | E4: 3 | F4: 3 | G4: 2 | H4: 2 | I4: 3 | J4: 3 | K4: =_xlfn.LET(_xlpm.StartDay, WEEKDAY(DATE($A4, $B4, 1), 1),_xlpm.DayNum, (COLUMN() - COLUMN($K$2) + 1) + (ROW() - ROW($K$2)) * 7 - _xlpm.StartDay + 1,IF(AND(_xlpm.DayNum > 0, _xlpm.DayNum <= DAY(EOMONTH(DATE($A4, $B4, 1), 0))), _xlpm.DayNum, "")) -> 10 | L4: =_xlfn.LET(_xlpm.StartDay, WEEKDAY(DATE($A4, $B4, 1), 1),_xlpm.DayNum, (COLUMN() - COLUMN($K$2) + 1) + (ROW() - ROW($K$2)) * 7 - _xlpm.StartDay + 1,IF(AND(_xlpm.DayNum > 0, _xlpm.DayNum <= DAY(EOMONTH(DATE($A4, $B4, 1), 0))), _xlpm.DayNum, "")) -> 11 | M4: =_xlfn.LET(_xlpm.StartDay, WEEKDAY(DATE($A4, $B4, 1), 1),_xlpm.DayNum, (COLUMN() - COLUMN($K$2) + 1) + (ROW() - ROW($K$2)) * 7 - _xlpm.StartDay + 1,IF(AND(_xlpm.DayNum > 0, _xlpm.DayNum <= DAY(EOMONTH(DATE($A4, $B4, 1), 0))), _xlpm.DayNum, "")) -> 12 | N4: =_xlfn.LET(_xlpm.StartDay, WEEKDAY(DATE($A4, $B4, 1), 1),_xlpm.DayNum, (COLUMN() - COLUMN($K$2) + 1) + (ROW() - ROW($K$2)) * 7 - _xlpm.StartDay + 1,IF(AND(_xlpm.DayNum > 0, _xlpm.DayNum <= DAY(EOMONTH(DATE($A4, $B4, 1), 0))), _xlpm.DayNum, "")) -> 13 | O4: =_xlfn.LET(_xlpm.StartDay, WEEKDAY(DATE($A4, $B4, 1), 1),_xlpm.DayNum, (COLUMN() - COLUMN($K$2) + 1) + (ROW() - ROW($K$2)) * 7 - _xlpm.StartDay + 1,IF(AND(_xlpm.DayNum > 0, _xlpm.DayNum <= DAY(EOMONTH(DATE($A4, $B4, 1), 0))), _xlpm.DayNum, "")) -> 14 | P4: =_xlfn.LET(_xlpm.StartDay, WEEKDAY(DATE($A4, $B4, 1), 1),_xlpm.DayNum, (COLUMN() - COLUMN($K$2) + 1) + (ROW() - ROW($K$2)) * 7 - _xlpm.StartDay + 1,IF(AND(_xlpm.DayNum > 0, _xlpm.DayNum <= DAY(EOMONTH(DATE($A4, $B4, 1), 0))), _xlpm.DayNum, "")) -> 15 | Q4: =_xlfn.LET(_xlpm.StartDay, WEEKDAY(DATE($A4, $B4, 1), 1),_xlpm.DayNum, (COLUMN() - COLUMN($K$2) + 1) + (ROW() - ROW($K$2)) * 7 - _xlpm.StartDay + 1,IF(AND(_xlpm.DayNum > 0, _xlpm.DayNum <= DAY(EOMONTH(DATE($A4, $B4, 1), 0))), _xlpm.DayNum, "")) -> 16 | S4: 4 | U4: HIGH
A5: 2027 | B5: 1 | C5: 4 | D5: 4 | E5: 2 | F5: 2 | G5: 2 | H5: 2 | I5: 2 | J5: 3 | K5: =_xlfn.LET(_xlpm.StartDay, WEEKDAY(DATE($A5, $B5, 1), 1),_xlpm.DayNum, (COLUMN() - COLUMN($K$2) + 1) + (ROW() - ROW($K$2)) * 7 - _xlpm.StartDay + 1,IF(AND(_xlpm.DayNum > 0, _xlpm.DayNum <= DAY(EOMONTH(DATE($A5, $B5, 1), 0))), _xlpm.DayNum, "")) -> 17 | L5: =_xlfn.LET(_xlpm.StartDay, WEEKDAY(DATE($A5, $B5, 1), 1),_xlpm.DayNum, (COLUMN() - COLUMN($K$2) + 1) + (ROW() - ROW($K$2)) * 7 - _xlpm.StartDay + 1,IF(AND(_xlpm.DayNum > 0, _xlpm.DayNum <= DAY(EOMONTH(DATE($A5, $B5, 1), 0))), _xlpm.DayNum, "")) -> 18 | M5: =_xlfn.LET(_xlpm.StartDay, WEEKDAY(DATE($A5, $B5, 1), 1),_xlpm.DayNum, (COLUMN() - COLUMN($K$2) + 1) + (ROW() - ROW($K$2)) * 7 - _xlpm.StartDay + 1,IF(AND(_xlpm.DayNum > 0, _xlpm.DayNum <= DAY(EOMONTH(DATE($A5, $B5, 1), 0))), _xlpm.DayNum, "")) -> 19 | N5: =_xlfn.LET(_xlpm.StartDay, WEEKDAY(DATE($A5, $B5, 1), 1),_xlpm.DayNum, (COLUMN() - COLUMN($K$2) + 1) + (ROW() - ROW($K$2)) * 7 - _xlpm.StartDay + 1,IF(AND(_xlpm.DayNum > 0, _xlpm.DayNum <= DAY(EOMONTH(DATE($A5, $B5, 1), 0))), _xlpm.DayNum, "")) -> 20 | O5: =_xlfn.LET(_xlpm.StartDay, WEEKDAY(DATE($A5, $B5, 1), 1),_xlpm.DayNum, (COLUMN() - COLUMN($K$2) + 1) + (ROW() - ROW($K$2)) * 7 - _xlpm.StartDay + 1,IF(AND(_xlpm.DayNum > 0, _xlpm.DayNum <= DAY(EOMONTH(DATE($A5, $B5, 1), 0))), _xlpm.DayNum, "")) -> 21 | P5: =_xlfn.LET(_xlpm.StartDay, WEEKDAY(DATE($A5, $B5, 1), 1),_xlpm.DayNum, (COLUMN() - COLUMN($K$2) + 1) + (ROW() - ROW($K$2)) * 7 - _xlpm.StartDay + 1,IF(AND(_xlpm.DayNum > 0, _xlpm.DayNum <= DAY(EOMONTH(DATE($A5, $B5, 1), 0))), _xlpm.DayNum, "")) -> 22 | Q5: =_xlfn.LET(_xlpm.StartDay, WEEKDAY(DATE($A5, $B5, 1), 1),_xlpm.DayNum, (COLUMN() - COLUMN($K$2) + 1) + (ROW() - ROW($K$2)) * 7 - _xlpm.StartDay + 1,IF(AND(_xlpm.DayNum > 0, _xlpm.DayNum <= DAY(EOMONTH(DATE($A5, $B5, 1), 0))), _xlpm.DayNum, "")) -> 23
A6: 2027 | B6: 1 | C6: 5 | D6: 3 | E6: 3 | F6: 3 | G6: 2 | H6: 4 | I6: 3 | J6: 2 | K6: =_xlfn.LET(_xlpm.StartDay, WEEKDAY(DATE($A6, $B6, 1), 1),_xlpm.DayNum, (COLUMN() - COLUMN($K$2) + 1) + (ROW() - ROW($K$2)) * 7 - _xlpm.StartDay + 1,IF(AND(_xlpm.DayNum > 0, _xlpm.DayNum <= DAY(EOMONTH(DATE($A6, $B6, 1), 0))), _xlpm.DayNum, "")) -> 24 | L6: =_xlfn.LET(_xlpm.StartDay, WEEKDAY(DATE($A6, $B6, 1), 1),_xlpm.DayNum, (COLUMN() - COLUMN($K$2) + 1) + (ROW() - ROW($K$2)) * 7 - _xlpm.StartDay + 1,IF(AND(_xlpm.DayNum > 0, _xlpm.DayNum <= DAY(EOMONTH(DATE($A6, $B6, 1), 0))), _xlpm.DayNum, "")) -> 25 | M6: =_xlfn.LET(_xlpm.StartDay, WEEKDAY(DATE($A6, $B6, 1), 1),_xlpm.DayNum, (COLUMN() - COLUMN($K$2) + 1) + (ROW() - ROW($K$2)) * 7 - _xlpm.StartDay + 1,IF(AND(_xlpm.DayNum > 0, _xlpm.DayNum <= DAY(EOMONTH(DATE($A6, $B6, 1), 0))), _xlpm.DayNum, "")) -> 26 | N6: =_xlfn.LET(_xlpm.StartDay, WEEKDAY(DATE($A6, $B6, 1), 1),_xlpm.DayNum, (COLUMN() - COLUMN($K$2) + 1) + (ROW() - ROW($K$2)) * 7 - _xlpm.StartDay + 1,IF(AND(_xlpm.DayNum > 0, _xlpm.DayNum <= DAY(EOMONTH(DATE($A6, $B6, 1), 0))), _xlpm.DayNum, "")) -> 27 | O6: =_xlfn.LET(_xlpm.StartDay, WEEKDAY(DATE($A6, $B6, 1), 1),_xlpm.DayNum, (COLUMN() - COLUMN($K$2) + 1) + (ROW() - ROW($K$2)) * 7 - _xlpm.StartDay + 1,IF(AND(_xlpm.DayNum > 0, _xlpm.DayNum <= DAY(EOMONTH(DATE($A6, $B6, 1), 0))), _xlpm.DayNum, "")) -> 28 | P6: =_xlfn.LET(_xlpm.StartDay, WEEKDAY(DATE($A6, $B6, 1), 1),_xlpm.DayNum, (COLUMN() - COLUMN($K$2) + 1) + (ROW() - ROW($K$2)) * 7 - _xlpm.StartDay + 1,IF(AND(_xlpm.DayNum > 0, _xlpm.DayNum <= DAY(EOMONTH(DATE($A6, $B6, 1), 0))), _xlpm.DayNum, "")) -> 29 | Q6: =_xlfn.LET(_xlpm.StartDay, WEEKDAY(DATE($A6, $B6, 1), 1),_xlpm.DayNum, (COLUMN() - COLUMN($K$2) + 1) + (ROW() - ROW($K$2)) * 7 - _xlpm.StartDay + 1,IF(AND(_xlpm.DayNum > 0, _xlpm.DayNum <= DAY(EOMONTH(DATE($A6, $B6, 1), 0))), _xlpm.DayNum, "")) -> 30
A7: 2027 | B7: 1 | C7: 6 | D7: 3 | E7: 1 | F7: 1 | G7: 1 | H7: 1 | I7: 1 | J7: 1 | K7: =_xlfn.LET(_xlpm.StartDay, WEEKDAY(DATE($A7, $B7, 1), 1),_xlpm.DayNum, (COLUMN() - COLUMN($K$2) + 1) + (ROW() - ROW($K$2)) * 7 - _xlpm.StartDay + 1,IF(AND(_xlpm.DayNum > 0, _xlpm.DayNum <= DAY(EOMONTH(DATE($A7, $B7, 1), 0))), _xlpm.DayNum, "")) -> 31 | L7: =IF(E7<>1,"ERROR!!!","") | M7: =IF(F7<>1,"ERROR!!!","") | N7: =IF(G7<>1,"ERROR!!!","") | O7: =IF(H7<>1,"ERROR!!!","") | P7: =IF(I7<>1,"ERROR!!!","") | Q7: =IF(J7<>1,"ERROR!!!","")
A8: 2027 | B8: 2 | C8: 1 | D8: 1 | E8: 2 | F8: 2 | G8: 2 | H8: 2 | I8: 2 | J8: 2 | K8: =_xlfn.LET(_xlpm.StartDay, WEEKDAY(DATE($A8, $B8, 1), 1),_xlpm.DayNum, (COLUMN() - COLUMN($K$8) + 1) + (ROW() - ROW($K$8)) * 7 - _xlpm.StartDay + 1,IF(AND(_xlpm.DayNum > 0, _xlpm.DayNum <= DAY(EOMONTH(DATE($A8, $B8, 1), 0))), _xlpm.DayNum, "")) | L8: =_xlfn.LET(_xlpm.StartDay, WEEKDAY(DATE($A8, $B8, 1), 1),_xlpm.DayNum, (COLUMN() - COLUMN($K$8) + 1) + (ROW() - ROW($K$8)) * 7 - _xlpm.StartDay + 1,IF(AND(_xlpm.DayNum > 0, _xlpm.DayNum <= DAY(EOMONTH(DATE($A8, $B8, 1), 0))), _xlpm.DayNum, "")) -> 1 | M8: =_xlfn.LET(_xlpm.StartDay, WEEKDAY(DATE($A8, $B8, 1), 1),_xlpm.DayNum, (COLUMN() - COLUMN($K$8) + 1) + (ROW() - ROW($K$8)) * 7 - _xlpm.StartDay + 1,IF(AND(_xlpm.DayNum > 0, _xlpm.DayNum <= DAY(EOMONTH(DATE($A8, $B8, 1), 0))), _xlpm.DayNum, "")) -> 2 | N8: =_xlfn.LET(_xlpm.StartDay, WEEKDAY(DATE($A8, $B8, 1), 1),_xlpm.DayNum, (COLUMN() - COLUMN($K$8) + 1) + (ROW() - ROW($K$8)) * 7 - _xlpm.StartDay + 1,IF(AND(_xlpm.DayNum > 0, _xlpm.DayNum <= DAY(EOMONTH(DATE($A8, $B8, 1), 0))), _xlpm.DayNum, "")) -> 3 | O8: =_xlfn.LET(_xlpm.StartDay, WEEKDAY(DATE($A8, $B8, 1), 1),_xlpm.DayNum, (COLUMN() - COLUMN($K$8) + 1) + (ROW() - ROW($K$8)) * 7 - _xlpm.StartDay + 1,IF(AND(_xlpm.DayNum > 0, _xlpm.DayNum <= DAY(EOMONTH(DATE($A8, $B8, 1), 0))), _xlpm.DayNum, "")) -> 4 | P8: =_xlfn.LET(_xlpm.StartDay, WEEKDAY(DATE($A8, $B8, 1), 1),_xlpm.DayNum, (COLUMN() - COLUMN($K$8) + 1) + (ROW() - ROW($K$8)) * 7 - _xlpm.StartDay + 1,IF(AND(_xlpm.DayNum > 0, _xlpm.DayNum <= DAY(EOMONTH(DATE($A8, $B8, 1), 0))), _xlpm.DayNum, "")) -> 5 | Q8: =_xlfn.LET(_xlpm.StartDay, WEEKDAY(DATE($A8, $B8, 1), 1),_xlpm.DayNum, (COLUMN() - COLUMN($K$8) + 1) + (ROW() - ROW($K$8)) * 7 - _xlpm.StartDay + 1,IF(AND(_xlpm.DayNum > 0, _xlpm.DayNum <= DAY(EOMONTH(DATE($A8, $B8, 1), 0))), _xlpm.DayNum, "")) -> 6
A9: 2027 | B9: 2 | C9: 2 | D9: 4 | E9: 4 | F9: 3 | G9: 2 | H9: 2 | I9: 3 | J9: 2 | K9: =_xlfn.LET(_xlpm.StartDay, WEEKDAY(DATE($A9, $B9, 1), 1),_xlpm.DayNum, (COLUMN() - COLUMN($K$8) + 1) + (ROW() - ROW($K$8)) * 7 - _xlpm.StartDay + 1,IF(AND(_xlpm.DayNum > 0, _xlpm.DayNum <= DAY(EOMONTH(DATE($A9, $B9, 1), 0))), _xlpm.DayNum, "")) -> 7 | L9: =_xlfn.LET(_xlpm.StartDay, WEEKDAY(DATE($A9, $B9, 1), 1),_xlpm.DayNum, (COLUMN() - COLUMN($K$8) + 1) + (ROW() - ROW($K$8)) * 7 - _xlpm.StartDay + 1,IF(AND(_xlpm.DayNum > 0, _xlpm.DayNum <= DAY(EOMONTH(DATE($A9, $B9, 1), 0))), _xlpm.DayNum, "")) -> 8 | M9: =_xlfn.LET(_xlpm.StartDay, WEEKDAY(DATE($A9, $B9, 1), 1),_xlpm.DayNum, (COLUMN() - COLUMN($K$8) + 1) + (ROW() - ROW($K$8)) * 7 - _xlpm.StartDay + 1,IF(AND(_xlpm.DayNum > 0, _xlpm.DayNum <= DAY(EOMONTH(DATE($A9, $B9, 1), 0))), _xlpm.DayNum, "")) -> 9 | N9: =_xlfn.LET(_xlpm.StartDay, WEEKDAY(DATE($A9, $B9, 1), 1),_xlpm.DayNum, (COLUMN() - COLUMN($K$8) + 1) + (ROW() - ROW($K$8)) * 7 - _xlpm.StartDay + 1,IF(AND(_xlpm.DayNum > 0, _xlpm.DayNum <= DAY(EOMONTH(DATE($A9, $B9, 1), 0))), _xlpm.DayNum, "")) -> 10 | O9: =_xlfn.LET(_xlpm.StartDay, WEEKDAY(DATE($A9, $B9, 1), 1),_xlpm.DayNum, (COLUMN() - COLUMN($K$8) + 1) + (ROW() - ROW($K$8)) * 7 - _xlpm.StartDay + 1,IF(AND(_xlpm.DayNum > 0, _xlpm.DayNum <= DAY(EOMONTH(DATE($A9, $B9, 1), 0))), _xlpm.DayNum, "")) -> 11 | P9: =_xlfn.LET(_xlpm.StartDay, WEEKDAY(DATE($A9, $B9, 1), 1),_xlpm.DayNum, (COLUMN() - COLUMN($K$8) + 1) + (ROW() - ROW($K$8)) * 7 - _xlpm.StartDay + 1,IF(AND(_xlpm.DayNum > 0, _xlpm.DayNum <= DAY(EOMONTH(DATE($A9, $B9, 1), 0))), _xlpm.DayNum, "")) -> 12 | Q9: =_xlfn.LET(_xlpm.StartDay, WEEKDAY(DATE($A9, $B9, 1), 1),_xlpm.DayNum, (COLUMN() - COLUMN($K$8) + 1) + (ROW() - ROW($K$8)) * 7 - _xlpm.StartDay + 1,IF(AND(_xlpm.DayNum > 0, _xlpm.DayNum <= DAY(EOMONTH(DATE($A9, $B9, 1), 0))), _xlpm.DayNum, "")) -> 13
A10: 2027 | B10: 2 | C10: 3 | D10: 4 | E10: 3 | F10: 2 | G10: 3 | H10: 4 | I10: 2 | J10: 2 | K10: =_xlfn.LET(_xlpm.StartDay, WEEKDAY(DATE($A10, $B10, 1), 1),_xlpm.DayNum, (COLUMN() - COLUMN($K$8) + 1) + (ROW() - ROW($K$8)) * 7 - _xlpm.StartDay + 1,IF(AND(_xlpm.DayNum > 0, _xlpm.DayNum <= DAY(EOMONTH(DATE($A10, $B10, 1), 0))), _xlpm.DayNum, "")) -> 14 | L10: =_xlfn.LET(_xlpm.StartDay, WEEKDAY(DATE($A10, $B10, 1), 1),_xlpm.DayNum, (COLUMN() - COLUMN($K$8) + 1) + (ROW() - ROW($K$8)) * 7 - _xlpm.StartDay + 1,IF(AND(_xlpm.DayNum > 0, _xlpm.DayNum <= DAY(EOMONTH(DATE($A10, $B10, 1), 0))), _xlpm.DayNum, "")) -> 15 | M10: =_xlfn.LET(_xlpm.StartDay, WEEKDAY(DATE($A10, $B10, 1), 1),_xlpm.DayNum, (COLUMN() - COLUMN($K$8) + 1) + (ROW() - ROW($K$8)) * 7 - _xlpm.StartDay + 1,IF(AND(_xlpm.DayNum > 0, _xlpm.DayNum <= DAY(EOMONTH(DATE($A10, $B10, 1), 0))), _xlpm.DayNum, "")) -> 16 | N10: =_xlfn.LET(_xlpm.StartDay, WEEKDAY(DATE($A10, $B10, 1), 1),_xlpm.DayNum, (COLUMN() - COLUMN($K$8) + 1) + (ROW() - ROW($K$8)) * 7 - _xlpm.StartDay + 1,IF(AND(_xlpm.DayNum > 0, _xlpm.DayNum <= DAY(EOMONTH(DATE($A10, $B10, 1), 0))), _xlpm.DayNum, "")) -> 17 | O10: =_xlfn.LET(_xlpm.StartDay, WEEKDAY(DATE($A10, $B10, 1), 1),_xlpm.DayNum, (COLUMN() - COLUMN($K$8) + 1) + (ROW() - ROW($K$8)) * 7 - _xlpm.StartDay + 1,IF(AND(_xlpm.DayNum > 0, _xlpm.DayNum <= DAY(EOMONTH(DATE($A10, $B10, 1), 0))), _xlpm.DayNum, "")) -> 18 | P10: =_xlfn.LET(_xlpm.StartDay, WEEKDAY(DATE($A10, $B10, 1), 1),_xlpm.DayNum, (COLUMN() - COLUMN($K$8) + 1) + (ROW() - ROW($K$8)) * 7 - _xlpm.StartDay + 1,IF(AND(_xlpm.DayNum > 0, _xlpm.DayNum <= DAY(EOMONTH(DATE($A10, $B10, 1), 0))), _xlpm.DayNum, "")) -> 19 | Q10: =_xlfn.LET(_xlpm.StartDay, WEEKDAY(DATE($A10, $B10, 1), 1),_xlpm.DayNum, (COLUMN() - COLUMN($K$8) + 1) + (ROW() - ROW($K$8)) * 7 - _xlpm.StartDay + 1,IF(AND(_xlpm.DayNum > 0, _xlpm.DayNum <= DAY(EOMONTH(DATE($A10, $B10, 1), 0))), _xlpm.DayNum, "")) -> 20
A11: 2027 | B11: 2 | C11: 4 | D11: 3 | E11: 4 | F11: 2 | G11: 3 | H11: 3 | I11: 3 | J11: 2 | K11: =_xlfn.LET(_xlpm.StartDay, WEEKDAY(DATE($A11, $B11, 1), 1),_xlpm.DayNum, (COLUMN() - COLUMN($K$8) + 1) + (ROW() - ROW($K$8)) * 7 - _xlpm.StartDay + 1,IF(AND(_xlpm.DayNum > 0, _xlpm.DayNum <= DAY(EOMONTH(DATE($A11, $B11, 1), 0))), _xlpm.DayNum, "")) -> 21 | L11: =_xlfn.LET(_xlpm.StartDay, WEEKDAY(DATE($A11, $B11, 1), 1),_xlpm.DayNum, (COLUMN() - COLUMN($K$8) + 1) + (ROW() - ROW($K$8)) * 7 - _xlpm.StartDay + 1,IF(AND(_xlpm.DayNum > 0, _xlpm.DayNum <= DAY(EOMONTH(DATE($A11, $B11, 1), 0))), _xlpm.DayNum, "")) -> 22 | M11: =_xlfn.LET(_xlpm.StartDay, WEEKDAY(DATE($A11, $B11, 1), 1),_xlpm.DayNum, (COLUMN() - COLUMN($K$8) + 1) + (ROW() - ROW($K$8)) * 7 - _xlpm.StartDay + 1,IF(AND(_xlpm.DayNum > 0, _xlpm.DayNum <= DAY(EOMONTH(DATE($A11, $B11, 1), 0))), _xlpm.DayNum, "")) -> 23 | N11: =_xlfn.LET(_xlpm.StartDay, WEEKDAY(DATE($A11, $B11, 1), 1),_xlpm.DayNum, (COLUMN() - COLUMN($K$8) + 1) + (ROW() - ROW($K$8)) * 7 - _xlpm.StartDay + 1,IF(AND(_xlpm.DayNum > 0, _xlpm.DayNum <= DAY(EOMONTH(DATE($A11, $B11, 1), 0))), _xlpm.DayNum, "")) -> 24 | O11: =_xlfn.LET(_xlpm.StartDay, WEEKDAY(DATE($A11, $B11, 1), 1),_xlpm.DayNum, (COLUMN() - COLUMN($K$8) + 1) + (ROW() - ROW($K$8)) * 7 - _xlpm.StartDay + 1,IF(AND(_xlpm.DayNum > 0, _xlpm.DayNum <= DAY(EOMONTH(DATE($A11, $B11, 1), 0))), _xlpm.DayNum, "")) -> 25 | P11: =_xlfn.LET(_xlpm.StartDay, WEEKDAY(DATE($A11, $B11, 1), 1),_xlpm.DayNum, (COLUMN() - COLUMN($K$8) + 1) + (ROW() - ROW($K$8)) * 7 - _xlpm.StartDay + 1,IF(AND(_xlpm.DayNum > 0, _xlpm.DayNum <= DAY(EOMONTH(DATE($A11, $B11, 1), 0))), _xlpm.DayNum, "")) -> 26 | Q11: =_xlfn.LET(_xlpm.StartDay, WEEKDAY(DATE($A11, $B11, 1), 1),_xlpm.DayNum, (COLUMN() - COLUMN($K$8) + 1) + (ROW() - ROW($K$8)) * 7 - _xlpm.StartDay + 1,IF(AND(_xlpm.DayNum > 0, _xlpm.DayNum <= DAY(EOMONTH(DATE($A11, $B11, 1), 0))), _xlpm.DayNum, "")) -> 27
A12: 2027 | B12: 2 | C12: 5 | D12: 3 | E12: 1 | F12: 1 | G12: 1 | H12: 1 | I12: 1 | J12: 1 | K12: =_xlfn.LET(_xlpm.StartDay, WEEKDAY(DATE($A12, $B12, 1), 1),_xlpm.DayNum, (COLUMN() - COLUMN($K$8) + 1) + (ROW() - ROW($K$8)) * 7 - _xlpm.StartDay + 1,IF(AND(_xlpm.DayNum > 0, _xlpm.DayNum <= DAY(EOMONTH(DATE($A12, $B12, 1), 0))), _xlpm.DayNum, "")) -> 28 | L12: =IF(E12<>1,"ERROR!!!","") | M12: =IF(F12<>1,"ERROR!!!","") | N12: =IF(G12<>1,"ERROR!!!","") | O12: =IF(H12<>1,"ERROR!!!","") | P12: =IF(I12<>1,"ERROR!!!","") | Q12: =IF(J12<>1,"ERROR!!!","")
A13: 2027 | B13: 2 | C13: 6 | D13: 1 | E13: 1 | F13: 1 | G13: 1 | H13: 1 | I13: 1 | J13: 1 | K13: =IF(D13<>1,"ERROR!!!","") | L13: =IF(E13<>1,"ERROR!!!","") | M13: =IF(F13<>1,"ERROR!!!","") | N13: =IF(G13<>1,"ERROR!!!","") | O13: =IF(H13<>1,"ERROR!!!","") | P13: =IF(I13<>1,"ERROR!!!","") | Q13: =IF(J13<>1,"ERROR!!!","")
A14: 2027 | B14: 3 | C14: 1 | D14: 1 | E14: 2 | F14: 2 | G14: 2 | H14: 2 | I14: 2 | J14: 3 | K14: =IF(D14<>1,"ERROR!!!","") | L14: =_xlfn.LET(_xlpm.StartDay, WEEKDAY(DATE($A14, $B14, 1), 1),_xlpm.DayNum, (COLUMN() - COLUMN($K$14) + 1) + (ROW() - ROW($K$14)) * 7 - _xlpm.StartDay + 1,IF(AND(_xlpm.DayNum > 0, _xlpm.DayNum <= DAY(EOMONTH(DATE($A14, $B14, 1), 0))), _xlpm.DayNum, "")) -> 1 | M14: =_xlfn.LET(_xlpm.StartDay, WEEKDAY(DATE($A14, $B14, 1), 1),_xlpm.DayNum, (COLUMN() - COLUMN($K$14) + 1) + (ROW() - ROW($K$14)) * 7 - _xlpm.StartDay + 1,IF(AND(_xlpm.DayNum > 0, _xlpm.DayNum <= DAY(EOMONTH(DATE($A14, $B14, 1), 0))), _xlpm.DayNum, "")) -> 2 | N14: =_xlfn.LET(_xlpm.StartDay, WEEKDAY(DATE($A14, $B14, 1), 1),_xlpm.DayNum, (COLUMN() - COLUMN($K$14) + 1) + (ROW() - ROW($K$14)) * 7 - _xlpm.StartDay + 1,IF(AND(_xlpm.DayNum > 0, _xlpm.DayNum <= DAY(EOMONTH(DATE($A14, $B14, 1), 0))), _xlpm.DayNum, "")) -> 3 | O14: =_xlfn.LET(_xlpm.StartDay, WEEKDAY(DATE($A14, $B14, 1), 1),_xlpm.DayNum, (COLUMN() - COLUMN($K$14) + 1) + (ROW() - ROW($K$14)) * 7 - _xlpm.StartDay + 1,IF(AND(_xlpm.DayNum > 0, _xlpm.DayNum <= DAY(EOMONTH(DATE($A14, $B14, 1), 0))), _xlpm.DayNum, "")) -> 4 | P14: =_xlfn.LET(_xlpm.StartDay, WEEKDAY(DATE($A14, $B14, 1), 1),_xlpm.DayNum, (COLUMN() - COLUMN($K$14) + 1) + (ROW() - ROW($K$14)) * 7 - _xlpm.StartDay + 1,IF(AND(_xlpm.DayNum > 0, _xlpm.DayNum <= DAY(EOMONTH(DATE($A14, $B14, 1), 0))), _xlpm.DayNum, "")) -> 5 | Q14: =_xlfn.LET(_xlpm.StartDay, WEEKDAY(DATE($A14, $B14, 1), 1),_xlpm.DayNum, (COLUMN() - COLUMN($K$14) + 1) + (ROW() - ROW($K$14)) * 7 - _xlpm.StartDay + 1,IF(AND(_xlpm.DayNum > 0, _xlpm.DayNum <= DAY(EOMONTH(DATE($A14, $B14, 1), 0))), _xlpm.DayNum, "")) -> 6
A15: 2027 | B15: 3 | C15: 2 | D15: 3 | E15: 4 | F15: 2 | G15: 2 | H15: 2 | I15: 2 | J15: 2 | K15: =_xlfn.LET(_xlpm.StartDay, WEEKDAY(DATE($A15, $B15, 1), 1),_xlpm.DayNum, (COLUMN() - COLUMN($K$14) + 1) + (ROW() - ROW($K$14)) * 7 - _xlpm.StartDay + 1,IF(AND(_xlpm.DayNum > 0, _xlpm.DayNum <= DAY(EOMONTH(DATE($A15, $B15, 1), 0))), _xlpm.DayNum, "")) -> 7 | L15: =_xlfn.LET(_xlpm.StartDay, WEEKDAY(DATE($A15, $B15, 1), 1),_xlpm.DayNum, (COLUMN() - COLUMN($K$14) + 1) + (ROW() - ROW($K$14)) * 7 - _xlpm.StartDay + 1,IF(AND(_xlpm.DayNum > 0, _xlpm.DayNum <= DAY(EOMONTH(DATE($A15, $B15, 1), 0))), _xlpm.DayNum, "")) -> 8 | M15: =_xlfn.LET(_xlpm.StartDay, WEEKDAY(DATE($A15, $B15, 1), 1),_xlpm.DayNum, (COLUMN() - COLUMN($K$14) + 1) + (ROW() - ROW($K$14)) * 7 - _xlpm.StartDay + 1,IF(AND(_xlpm.DayNum > 0, _xlpm.DayNum <= DAY(EOMONTH(DATE($A15, $B15, 1), 0))), _xlpm.DayNum, "")) -> 9 | N15: =_xlfn.LET(_xlpm.StartDay, WEEKDAY(DATE($A15, $B15, 1), 1),_xlpm.DayNum, (COLUMN() - COLUMN($K$14) + 1) + (ROW() - ROW($K$14)) * 7 - _xlpm.StartDay + 1,IF(AND(_xlpm.DayNum > 0, _xlpm.DayNum <= DAY(EOMONTH(DATE($A15, $B15, 1), 0))), _xlpm.DayNum, "")) -> 10 | O15: =_xlfn.LET(_xlpm.StartDay, WEEKDAY(DATE($A15, $B15, 1), 1),_xlpm.DayNum, (COLUMN() - COLUMN($K$14) + 1) + (ROW() - ROW($K$14)) * 7 - _xlpm.StartDay + 1,IF(AND(_xlpm.DayNum > 0, _xlpm.DayNum <= DAY(EOMONTH(DATE($A15, $B15, 1), 0))), _xlpm.DayNum, "")) -> 11 | P15: =_xlfn.LET(_xlpm.StartDay, WEEKDAY(DATE($A15, $B15, 1), 1),_xlpm.DayNum, (COLUMN() - COLUMN($K$14) + 1) + (ROW() - ROW($K$14)) * 7 - _xlpm.StartDay + 1,IF(AND(_xlpm.DayNum > 0, _xlpm.DayNum <= DAY(EOMONTH(DATE($A15, $B15, 1), 0))), _xlpm.DayNum, "")) -> 12 | Q15: =_xlfn.LET(_xlpm.StartDay, WEEKDAY(DATE($A15, $B15, 1), 1),_xlpm.DayNum, (COLUMN() - COLUMN($K$14) + 1) + (ROW() - ROW($K$14)) * 7 - _xlpm.StartDay + 1,IF(AND(_xlpm.DayNum > 0, _xlpm.DayNum <= DAY(EOMONTH(DATE($A15, $B15, 1), 0))), _xlpm.DayNum, "")) -> 13
A16: 2027 | B16: 3 | C16: 3 | D16: 3 | E16: 2 | F16: 4 | G16: 3 | H16: 3 | I16: 2 | J16: 2 | K16: =_xlfn.LET(_xlpm.StartDay, WEEKDAY(DATE($A16, $B16, 1), 1),_xlpm.DayNum, (COLUMN() - COLUMN($K$14) + 1) + (ROW() - ROW($K$14)) * 7 - _xlpm.StartDay + 1,IF(AND(_xlpm.DayNum > 0, _xlpm.DayNum <= DAY(EOMONTH(DATE($A16, $B16, 1), 0))), _xlpm.DayNum, "")) -> 14 | L16: =_xlfn.LET(_xlpm.StartDay, WEEKDAY(DATE($A16, $B16, 1), 1),_xlpm.DayNum, (COLUMN() - COLUMN($K$14) + 1) + (ROW() - ROW($K$14)) * 7 - _xlpm.StartDay + 1,IF(AND(_xlpm.DayNum > 0, _xlpm.DayNum <= DAY(EOMONTH(DATE($A16, $B16, 1), 0))), _xlpm.DayNum, "")) -> 15 | M16: =_xlfn.LET(_xlpm.StartDay, WEEKDAY(DATE($A16, $B16, 1), 1),_xlpm.DayNum, (COLUMN() - COLUMN($K$14) + 1) + (ROW() - ROW($K$14)) * 7 - _xlpm.StartDay + 1,IF(AND(_xlpm.DayNum > 0, _xlpm.DayNum <= DAY(EOMONTH(DATE($A16, $B16, 1), 0))), _xlpm.DayNum, "")) -> 16 | N16: =_xlfn.LET(_xlpm.StartDay, WEEKDAY(DATE($A16, $B16, 1), 1),_xlpm.DayNum, (COLUMN() - COLUMN($K$14) + 1) + (ROW() - ROW($K$14)) * 7 - _xlpm.StartDay + 1,IF(AND(_xlpm.DayNum > 0, _xlpm.DayNum <= DAY(EOMONTH(DATE($A16, $B16, 1), 0))), _xlpm.DayNum, "")) -> 17 | O16: =_xlfn.LET(_xlpm.StartDay, WEEKDAY(DATE($A16, $B16, 1), 1),_xlpm.DayNum, (COLUMN() - COLUMN($K$14) + 1) + (ROW() - ROW($K$14)) * 7 - _xlpm.StartDay + 1,IF(AND(_xlpm.DayNum > 0, _xlpm.DayNum <= DAY(EOMONTH(DATE($A16, $B16, 1), 0))), _xlpm.DayNum, "")) -> 18 | P16: =_xlfn.LET(_xlpm.StartDay, WEEKDAY(DATE($A16, $B16, 1), 1),_xlpm.DayNum, (COLUMN() - COLUMN($K$14) + 1) + (ROW() - ROW($K$14)) * 7 - _xlpm.StartDay + 1,IF(AND(_xlpm.DayNum > 0, _xlpm.DayNum <= DAY(EOMONTH(DATE($A16, $B16, 1), 0))), _xlpm.DayNum, "")) -> 19 | Q16: =_xlfn.LET(_xlpm.StartDay, WEEKDAY(DATE($A16, $B16, 1), 1),_xlpm.DayNum, (COLUMN() - COLUMN($K$14) + 1) + (ROW() - ROW($K$14)) * 7 - _xlpm.StartDay + 1,IF(AND(_xlpm.DayNum > 0, _xlpm.DayNum <= DAY(EOMONTH(DATE($A16, $B16, 1), 0))), _xlpm.DayNum, "")) -> 20
A17: 2027 | B17: 3 | C17: 4 | D17: 2 | E17: 2 | F17: 3 | G17: 3 | H17: 3 | I17: 2 | J17: 2 | K17: =_xlfn.LET(_xlpm.StartDay, WEEKDAY(DATE($A17, $B17, 1), 1),_xlpm.DayNum, (COLUMN() - COLUMN($K$14) + 1) + (ROW() - ROW($K$14)) * 7 - _xlpm.StartDay + 1,IF(AND(_xlpm.DayNum > 0, _xlpm.DayNum <= DAY(EOMONTH(DATE($A17, $B17, 1), 0))), _xlpm.DayNum, "")) -> 21 | L17: =_xlfn.LET(_xlpm.StartDay, WEEKDAY(DATE($A17, $B17, 1), 1),_xlpm.DayNum, (COLUMN() - COLUMN($K$14) + 1) + (ROW() - ROW($K$14)) * 7 - _xlpm.StartDay + 1,IF(AND(_xlpm.DayNum > 0, _xlpm.DayNum <= DAY(EOMONTH(DATE($A17, $B17, 1), 0))), _xlpm.DayNum, "")) -> 22 | M17: =_xlfn.LET(_xlpm.StartDay, WEEKDAY(DATE($A17, $B17, 1), 1),_xlpm.DayNum, (COLUMN() - COLUMN($K$14) + 1) + (ROW() - ROW($K$14)) * 7 - _xlpm.StartDay + 1,IF(AND(_xlpm.DayNum > 0, _xlpm.DayNum <= DAY(EOMONTH(DATE($A17, $B17, 1), 0))), _xlpm.DayNum, "")) -> 23 | N17: =_xlfn.LET(_xlpm.StartDay, WEEKDAY(DATE($A17, $B17, 1), 1),_xlpm.DayNum, (COLUMN() - COLUMN($K$14) + 1) + (ROW() - ROW($K$14)) * 7 - _xlpm.StartDay + 1,IF(AND(_xlpm.DayNum > 0, _xlpm.DayNum <= DAY(EOMONTH(DATE($A17, $B17, 1), 0))), _xlpm.DayNum, "")) -> 24 | O17: =_xlfn.LET(_xlpm.StartDay, WEEKDAY(DATE($A17, $B17, 1), 1),_xlpm.DayNum, (COLUMN() - COLUMN($K$14) + 1) + (ROW() - ROW($K$14)) * 7 - _xlpm.StartDay + 1,IF(AND(_xlpm.DayNum > 0, _xlpm.DayNum <= DAY(EOMONTH(DATE($A17, $B17, 1), 0))), _xlpm.DayNum, "")) -> 25 | P17: =_xlfn.LET(_xlpm.StartDay, WEEKDAY(DATE($A17, $B17, 1), 1),_xlpm.DayNum, (COLUMN() - COLUMN($K$14) + 1) + (ROW() - ROW($K$14)) * 7 - _xlpm.StartDay + 1,IF(AND(_xlpm.DayNum > 0, _xlpm.DayNum <= DAY(EOMONTH(DATE($A17, $B17, 1), 0))), _xlpm.DayNum, "")) -> 26 | Q17: =_xlfn.LET(_xlpm.StartDay, WEEKDAY(DATE($A17, $B17, 1), 1),_xlpm.DayNum, (COLUMN() - COLUMN($K$14) + 1) + (ROW() - ROW($K$14)) * 7 - _xlpm.StartDay + 1,IF(AND(_xlpm.DayNum > 0, _xlpm.DayNum <= DAY(EOMONTH(DATE($A17, $B17, 1), 0))), _xlpm.DayNum, "")) -> 27
A18: 2027 | B18: 3 | C18: 5 | D18: 3 | E18: 2 | F18: 4 | G18: 2 | H18: 1 | I18: 1 | J18: 1 | K18: =_xlfn.LET(_xlpm.StartDay, WEEKDAY(DATE($A18, $B18, 1), 1),_xlpm.DayNum, (COLUMN() - COLUMN($K$14) + 1) + (ROW() - ROW($K$14)) * 7 - _xlpm.StartDay + 1,IF(AND(_xlpm.DayNum > 0, _xlpm.DayNum <= DAY(EOMONTH(DATE($A18, $B18, 1), 0))), _xlpm.DayNum, "")) -> 28 | L18: =_xlfn.LET(_xlpm.StartDay, WEEKDAY(DATE($A18, $B18, 1), 1),_xlpm.DayNum, (COLUMN() - COLUMN($K$14) + 1) + (ROW() - ROW($K$14)) * 7 - _xlpm.StartDay + 1,IF(AND(_xlpm.DayNum > 0, _xlpm.DayNum <= DAY(EOMONTH(DATE($A18, $B18, 1), 0))), _xlpm.DayNum, "")) -> 29 | M18: =_xlfn.LET(_xlpm.StartDay, WEEKDAY(DATE($A18, $B18, 1), 1),_xlpm.DayNum, (COLUMN() - COLUMN($K$14) + 1) + (ROW() - ROW($K$14)) * 7 - _xlpm.StartDay + 1,IF(AND(_xlpm.DayNum > 0, _xlpm.DayNum <= DAY(EOMONTH(DATE($A18, $B18, 1), 0))), _xlpm.DayNum, "")) -> 30 | N18: =_xlfn.LET(_xlpm.StartDay, WEEKDAY(DATE($A18, $B18, 1), 1),_xlpm.DayNum, (COLUMN() - COLUMN($K$14) + 1) + (ROW() - ROW($K$14)) * 7 - _xlpm.StartDay + 1,IF(AND(_xlpm.DayNum > 0, _xlpm.DayNum <= DAY(EOMONTH(DATE($A18, $B18, 1), 0))), _xlpm.DayNum, "")) -> 31 | O18: =IF(H18<>1,"ERROR!!!","") | P18: =IF(I18<>1,"ERROR!!!","") | Q18: =IF(J18<>1,"ERROR!!!","")
A19: 2027 | B19: 3 | C19: 6 | D19: 1 | E19: 1 | F19: 1 | G19: 1 | H19: 1 | I19: 1 | J19: 1 | K19: =IF(D19<>1,"ERROR!!!","") | L19: =IF(E19<>1,"ERROR!!!","") | M19: =IF(F19<>1,"ERROR!!!","") | N19: =IF(G19<>1,"ERROR!!!","") | O19: =IF(H19<>1,"ERROR!!!","") | P19: =IF(I19<>1,"ERROR!!!","") | Q19: =IF(J19<>1,"ERROR!!!","")
A20: 2027 | B20: 4 | C20: 1 | D20: 1 | E20: 1 | F20: 1 | G20: 1 | H20: 2 | I20: 2 | J20: 3 | K20: =IF(D20<>1,"ERROR!!!","") | L20: =IF(E20<>1,"ERROR!!!","") | M20: =IF(F20<>1,"ERROR!!!","") | N20: =IF(G20<>1,"ERROR!!!","") | O20: =_xlfn.LET(_xlpm.StartDay, WEEKDAY(DATE($A20, $B20, 1), 1),_xlpm.DayNum, (COLUMN() - COLUMN($K$20) + 1) + (ROW() - ROW($K$20)) * 7 - _xlpm.StartDay + 1,IF(AND(_xlpm.DayNum > 0, _xlpm.DayNum <= DAY(EOMONTH(DATE($A20, $B20, 1), 0))), _xlpm.DayNum, "")) -> 1 | P20: =_xlfn.LET(_xlpm.StartDay, WEEKDAY(DATE($A20, $B20, 1), 1),_xlpm.DayNum, (COLUMN() - COLUMN($K$20) + 1) + (ROW() - ROW($K$20)) * 7 - _xlpm.StartDay + 1,IF(AND(_xlpm.DayNum > 0, _xlpm.DayNum <= DAY(EOMONTH(DATE($A20, $B20, 1), 0))), _xlpm.DayNum, "")) -> 2 | Q20: =_xlfn.LET(_xlpm.StartDay, WEEKDAY(DATE($A20, $B20, 1), 1),_xlpm.DayNum, (COLUMN() - COLUMN($K$20) + 1) + (ROW() - ROW($K$20)) * 7 - _xlpm.StartDay + 1,IF(AND(_xlpm.DayNum > 0, _xlpm.DayNum <= DAY(EOMONTH(DATE($A20, $B20, 1), 0))), _xlpm.DayNum, "")) -> 3
A21: 2027 | B21: 4 | C21: 2 | D21: 4 | E21: 3 | F21: 2 | G21: 3 | H21: 4 | I21: 3 | J21: 3 | K21: =_xlfn.LET(_xlpm.StartDay, WEEKDAY(DATE($A21, $B21, 1), 1),_xlpm.DayNum, (COLUMN() - COLUMN($K$20) + 1) + (ROW() - ROW($K$20)) * 7 - _xlpm.StartDay + 1,IF(AND(_xlpm.DayNum > 0, _xlpm.DayNum <= DAY(EOMONTH(DATE($A21, $B21, 1), 0))), _xlpm.DayNum, "")) -> 4 | L21: =_xlfn.LET(_xlpm.StartDay, WEEKDAY(DATE($A21, $B21, 1), 1),_xlpm.DayNum, (COLUMN() - COLUMN($K$20) + 1) + (ROW() - ROW($K$20)) * 7 - _xlpm.StartDay + 1,IF(AND(_xlpm.DayNum > 0, _xlpm.DayNum <= DAY(EOMONTH(DATE($A21, $B21, 1), 0))), _xlpm.DayNum, "")) -> 5 | M21: =_xlfn.LET(_xlpm.StartDay, WEEKDAY(DATE($A21, $B21, 1), 1),_xlpm.DayNum, (COLUMN() - COLUMN($K$20) + 1) + (ROW() - ROW($K$20)) * 7 - _xlpm.StartDay + 1,IF(AND(_xlpm.DayNum > 0, _xlpm.DayNum <= DAY(EOMONTH(DATE($A21, $B21, 1), 0))), _xlpm.DayNum, "")) -> 6 | N21: =_xlfn.LET(_xlpm.StartDay, WEEKDAY(DATE($A21, $B21, 1), 1),_xlpm.DayNum, (COLUMN() - COLUMN($K$20) + 1) + (ROW() - ROW($K$20)) * 7 - _xlpm.StartDay + 1,IF(AND(_xlpm.DayNum > 0, _xlpm.DayNum <= DAY(EOMONTH(DATE($A21, $B21, 1), 0))), _xlpm.DayNum, "")) -> 7 | O21: =_xlfn.LET(_xlpm.StartDay, WEEKDAY(DATE($A21, $B21, 1), 1),_xlpm.DayNum, (COLUMN() - COLUMN($K$20) + 1) + (ROW() - ROW($K$20)) * 7 - _xlpm.StartDay + 1,IF(AND(_xlpm.DayNum > 0, _xlpm.DayNum <= DAY(EOMONTH(DATE($A21, $B21, 1), 0))), _xlpm.DayNum, "")) -> 8 | P21: =_xlfn.LET(_xlpm.StartDay, WEEKDAY(DATE($A21, $B21, 1), 1),_xlpm.DayNum, (COLUMN() - COLUMN($K$20) + 1) + (ROW() - ROW($K$20)) * 7 - _xlpm.StartDay + 1,IF(AND(_xlpm.DayNum > 0, _xlpm.DayNum <= DAY(EOMONTH(DATE($A21, $B21, 1), 0))), _xlpm.DayNum, "")) -> 9 | Q21: =_xlfn.LET(_xlpm.StartDay, WEEKDAY(DATE($A21, $B21, 1), 1),_xlpm.DayNum, (COLUMN() - COLUMN($K$20) + 1) + (ROW() - ROW($K$20)) * 7 - _xlpm.StartDay + 1,IF(AND(_xlpm.DayNum > 0, _xlpm.DayNum <= DAY(EOMONTH(DATE($A21, $B21, 1), 0))), _xlpm.DayNum, "")) -> 10
A22: 2027 | B22: 4 | C22: 3 | D22: 3 | E22: 2 | F22: 2 | G22: 2 | H22: 3 | I22: 3 | J22: 2 | K22: =_xlfn.LET(_xlpm.StartDay, WEEKDAY(DATE($A22, $B22, 1), 1),_xlpm.DayNum, (COLUMN() - COLUMN($K$20) + 1) + (ROW() - ROW($K$20)) * 7 - _xlpm.StartDay + 1,IF(AND(_xlpm.DayNum > 0, _xlpm.DayNum <= DAY(EOMONTH(DATE($A22, $B22, 1), 0))), _xlpm.DayNum, "")) -> 11 | L22: =_xlfn.LET(_xlpm.StartDay, WEEKDAY(DATE($A22, $B22, 1), 1),_xlpm.DayNum, (COLUMN() - COLUMN($K$20) + 1) + (ROW() - ROW($K$20)) * 7 - _xlpm.StartDay + 1,IF(AND(_xlpm.DayNum > 0, _xlpm.DayNum <= DAY(EOMONTH(DATE($A22, $B22, 1), 0))), _xlpm.DayNum, "")) -> 12 | M22: =_xlfn.LET(_xlpm.StartDay, WEEKDAY(DATE($A22, $B22, 1), 1),_xlpm.DayNum, (COLUMN() - COLUMN($K$20) + 1) + (ROW() - ROW($K$20)) * 7 - _xlpm.StartDay + 1,IF(AND(_xlpm.DayNum > 0, _xlpm.DayNum <= DAY(EOMONTH(DATE($A22, $B22, 1), 0))), _xlpm.DayNum, "")) -> 13 | N22: =_xlfn.LET(_xlpm.StartDay, WEEKDAY(DATE($A22, $B22, 1), 1),_xlpm.DayNum, (COLUMN() - COLUMN($K$20) + 1) + (ROW() - ROW($K$20)) * 7 - _xlpm.StartDay + 1,IF(AND(_xlpm.DayNum > 0, _xlpm.DayNum <= DAY(EOMONTH(DATE($A22, $B22, 1), 0))), _xlpm.DayNum, "")) -> 14 | O22: =_xlfn.LET(_xlpm.StartDay, WEEKDAY(DATE($A22, $B22, 1), 1),_xlpm.DayNum, (COLUMN() - COLUMN($K$20) + 1) + (ROW() - ROW($K$20)) * 7 - _xlpm.StartDay + 1,IF(AND(_xlpm.DayNum > 0, _xlpm.DayNum <= DAY(EOMONTH(DATE($A22, $B22, 1), 0))), _xlpm.DayNum, "")) -> 15 | P22: =_xlfn.LET(_xlpm.StartDay, WEEKDAY(DATE($A22, $B22, 1), 1),_xlpm.DayNum, (COLUMN() - COLUMN($K$20) + 1) + (ROW() - ROW($K$20)) * 7 - _xlpm.StartDay + 1,IF(AND(_xlpm.DayNum > 0, _xlpm.DayNum <= DAY(EOMONTH(DATE($A22, $B22, 1), 0))), _xlpm.DayNum, "")) -> 16 | Q22: =_xlfn.LET(_xlpm.StartDay, WEEKDAY(DATE($A22, $B22, 1), 1),_xlpm.DayNum, (COLUMN() - COLUMN($K$20) + 1) + (ROW() - ROW($K$20)) * 7 - _xlpm.StartDay + 1,IF(AND(_xlpm.DayNum > 0, _xlpm.DayNum <= DAY(EOMONTH(DATE($A22, $B22, 1), 0))), _xlpm.DayNum, "")) -> 17
A23: 2027 | B23: 4 | C23: 4 | D23: 2 | E23: 3 | F23: 4 | G23: 3 | H23: 3 | I23: 2 | J23: 2 | K23: =_xlfn.LET(_xlpm.StartDay, WEEKDAY(DATE($A23, $B23, 1), 1),_xlpm.DayNum, (COLUMN() - COLUMN($K$20) + 1) + (ROW() - ROW($K$20)) * 7 - _xlpm.StartDay + 1,IF(AND(_xlpm.DayNum > 0, _xlpm.DayNum <= DAY(EOMONTH(DATE($A23, $B23, 1), 0))), _xlpm.DayNum, "")) -> 18 | L23: =_xlfn.LET(_xlpm.StartDay, WEEKDAY(DATE($A23, $B23, 1), 1),_xlpm.DayNum, (COLUMN() - COLUMN($K$20) + 1) + (ROW() - ROW($K$20)) * 7 - _xlpm.StartDay + 1,IF(AND(_xlpm.DayNum > 0, _xlpm.DayNum <= DAY(EOMONTH(DATE($A23, $B23, 1), 0))), _xlpm.DayNum, "")) -> 19 | M23: =_xlfn.LET(_xlpm.StartDay, WEEKDAY(DATE($A23, $B23, 1), 1),_xlpm.DayNum, (COLUMN() - COLUMN($K$20) + 1) + (ROW() - ROW($K$20)) * 7 - _xlpm.StartDay + 1,IF(AND(_xlpm.DayNum > 0, _xlpm.DayNum <= DAY(EOMONTH(DATE($A23, $B23, 1), 0))), _xlpm.DayNum, "")) -> 20 | N23: =_xlfn.LET(_xlpm.StartDay, WEEKDAY(DATE($A23, $B23, 1), 1),_xlpm.DayNum, (COLUMN() - COLUMN($K$20) + 1) + (ROW() - ROW($K$20)) * 7 - _xlpm.StartDay + 1,IF(AND(_xlpm.DayNum > 0, _xlpm.DayNum <= DAY(EOMONTH(DATE($A23, $B23, 1), 0))), _xlpm.DayNum, "")) -> 21 | O23: =_xlfn.LET(_xlpm.StartDay, WEEKDAY(DATE($A23, $B23, 1), 1),_xlpm.DayNum, (COLUMN() - COLUMN($K$20) + 1) + (ROW() - ROW($K$20)) * 7 - _xlpm.StartDay + 1,IF(AND(_xlpm.DayNum > 0, _xlpm.DayNum <= DAY(EOMONTH(DATE($A23, $B23, 1), 0))), _xlpm.DayNum, "")) -> 22 | P23: =_xlfn.LET(_xlpm.StartDay, WEEKDAY(DATE($A23, $B23, 1), 1),_xlpm.DayNum, (COLUMN() - COLUMN($K$20) + 1) + (ROW() - ROW($K$20)) * 7 - _xlpm.StartDay + 1,IF(AND(_xlpm.DayNum > 0, _xlpm.DayNum <= DAY(EOMONTH(DATE($A23, $B23, 1), 0))), _xlpm.DayNum, "")) -> 23 | Q23: =_xlfn.LET(_xlpm.StartDay, WEEKDAY(DATE($A23, $B23, 1), 1),_xlpm.DayNum, (COLUMN() - COLUMN($K$20) + 1) + (ROW() - ROW($K$20)) * 7 - _xlpm.StartDay + 1,IF(AND(_xlpm.DayNum > 0, _xlpm.DayNum <= DAY(EOMONTH(DATE($A23, $B23, 1), 0))), _xlpm.DayNum, "")) -> 24
A24: 2027 | B24: 4 | C24: 5 | D24: 3 | E24: 3 | F24: 2 | G24: 3 | H24: 2 | I24: 2 | J24: 1 | K24: =_xlfn.LET(_xlpm.StartDay, WEEKDAY(DATE($A24, $B24, 1), 1),_xlpm.DayNum, (COLUMN() - COLUMN($K$20) + 1) + (ROW() - ROW($K$20)) * 7 - _xlpm.StartDay + 1,IF(AND(_xlpm.DayNum > 0, _xlpm.DayNum <= DAY(EOMONTH(DATE($A24, $B24, 1), 0))), _xlpm.DayNum, "")) -> 25 | L24: =_xlfn.LET(_xlpm.StartDay, WEEKDAY(DATE($A24, $B24, 1), 1),_xlpm.DayNum, (COLUMN() - COLUMN($K$20) + 1) + (ROW() - ROW($K$20)) * 7 - _xlpm.StartDay + 1,IF(AND(_xlpm.DayNum > 0, _xlpm.DayNum <= DAY(EOMONTH(DATE($A24, $B24, 1), 0))), _xlpm.DayNum, "")) -> 26 | M24: =_xlfn.LET(_xlpm.StartDay, WEEKDAY(DATE($A24, $B24, 1), 1),_xlpm.DayNum, (COLUMN() - COLUMN($K$20) + 1) + (ROW() - ROW($K$20)) * 7 - _xlpm.StartDay + 1,IF(AND(_xlpm.DayNum > 0, _xlpm.DayNum <= DAY(EOMONTH(DATE($A24, $B24, 1), 0))), _xlpm.DayNum, "")) -> 27 | N24: =_xlfn.LET(_xlpm.StartDay, WEEKDAY(DATE($A24, $B24, 1), 1),_xlpm.DayNum, (COLUMN() - COLUMN($K$20) + 1) + (ROW() - ROW($K$20)) * 7 - _xlpm.StartDay + 1,IF(AND(_xlpm.DayNum > 0, _xlpm.DayNum <= DAY(EOMONTH(DATE($A24, $B24, 1), 0))), _xlpm.DayNum, "")) -> 28 | O24: =_xlfn.LET(_xlpm.StartDay, WEEKDAY(DATE($A24, $B24, 1), 1),_xlpm.DayNum, (COLUMN() - COLUMN($K$20) + 1) + (ROW() - ROW($K$20)) * 7 - _xlpm.StartDay + 1,IF(AND(_xlpm.DayNum > 0, _xlpm.DayNum <= DAY(EOMONTH(DATE($A24, $B24, 1), 0))), _xlpm.DayNum, "")) -> 29 | P24: =_xlfn.LET(_xlpm.StartDay, WEEKDAY(DATE($A24, $B24, 1), 1),_xlpm.DayNum, (COLUMN() - COLUMN($K$20) + 1) + (ROW() - ROW($K$20)) * 7 - _xlpm.StartDay + 1,IF(AND(_xlpm.DayNum > 0, _xlpm.DayNum <= DAY(EOMONTH(DATE($A24, $B24, 1), 0))), _xlpm.DayNum, "")) -> 30 | Q24: =IF(J24<>1,"ERROR!!!","")
A25: 2027 | B25: 4 | C25: 6 | D25: 1 | E25: 1 | F25: 1 | G25: 1 | H25: 1 | I25: 1 | J25: 1 | K25: =IF(D25<>1,"ERROR!!!","") | L25: =IF(E25<>1,"ERROR!!!","") | M25: =IF(F25<>1,"ERROR!!!","") | N25: =IF(G25<>1,"ERROR!!!","") | O25: =IF(H25<>1,"ERROR!!!","") | P25: =IF(I25<>1,"ERROR!!!","") | Q25: =IF(J25<>1,"ERROR!!!","")
A26: 2027 | B26: 5 | C26: 1 | D26: 1 | E26: 1 | F26: 1 | G26: 1 | H26: 1 | I26: 1 | J26: 3 | K26: =IF(D26<>1,"ERROR!!!","") | L26: =IF(E26<>1,"ERROR!!!","") | M26: =IF(F26<>1,"ERROR!!!","") | N26: =IF(G26<>1,"ERROR!!!","") | O26: =IF(H26<>1,"ERROR!!!","") | P26: =IF(I26<>1,"ERROR!!!","") | Q26: =_xlfn.LET(_xlpm.StartDay, WEEKDAY(DATE($A26, $B26, 1), 1),_xlpm.DayNum, (COLUMN() - COLUMN($K$26) + 1) + (ROW() - ROW($K$26)) * 7 - _xlpm.StartDay + 1,IF(AND(_xlpm.DayNum > 0, _xlpm.DayNum <= DAY(EOMONTH(DATE($A26, $B26, 1), 0))), _xlpm.DayNum, "")) -> 1
A27: 2027 | B27: 5 | C27: 2 | D27: 3 | E27: 4 | F27: 2 | G27: 2 | H27: 3 | I27: 2 | J27: 4 | K27: =_xlfn.LET(_xlpm.StartDay, WEEKDAY(DATE($A27, $B27, 1), 1),_xlpm.DayNum, (COLUMN() - COLUMN($K$26) + 1) + (ROW() - ROW($K$26)) * 7 - _xlpm.StartDay + 1,IF(AND(_xlpm.DayNum > 0, _xlpm.DayNum <= DAY(EOMONTH(DATE($A27, $B27, 1), 0))), _xlpm.DayNum, "")) -> 2 | L27: =_xlfn.LET(_xlpm.StartDay, WEEKDAY(DATE($A27, $B27, 1), 1),_xlpm.DayNum, (COLUMN() - COLUMN($K$26) + 1) + (ROW() - ROW($K$26)) * 7 - _xlpm.StartDay + 1,IF(AND(_xlpm.DayNum > 0, _xlpm.DayNum <= DAY(EOMONTH(DATE($A27, $B27, 1), 0))), _xlpm.DayNum, "")) -> 3 | M27: =_xlfn.LET(_xlpm.StartDay, WEEKDAY(DATE($A27, $B27, 1), 1),_xlpm.DayNum, (COLUMN() - COLUMN($K$26) + 1) + (ROW() - ROW($K$26)) * 7 - _xlpm.StartDay + 1,IF(AND(_xlpm.DayNum > 0, _xlpm.DayNum <= DAY(EOMONTH(DATE($A27, $B27, 1), 0))), _xlpm.DayNum, "")) -> 4 | N27: =_xlfn.LET(_xlpm.StartDay, WEEKDAY(DATE($A27, $B27, 1), 1),_xlpm.DayNum, (COLUMN() - COLUMN($K$26) + 1) + (ROW() - ROW($K$26)) * 7 - _xlpm.StartDay + 1,IF(AND(_xlpm.DayNum > 0, _xlpm.DayNum <= DAY(EOMONTH(DATE($A27, $B27, 1), 0))), _xlpm.DayNum, "")) -> 5 | O27: =_xlfn.LET(_xlpm.StartDay, WEEKDAY(DATE($A27, $B27, 1), 1),_xlpm.DayNum, (COLUMN() - COLUMN($K$26) + 1) + (ROW() - ROW($K$26)) * 7 - _xlpm.StartDay + 1,IF(AND(_xlpm.DayNum > 0, _xlpm.DayNum <= DAY(EOMONTH(DATE($A27, $B27, 1), 0))), _xlpm.DayNum, "")) -> 6 | P27: =_xlfn.LET(_xlpm.StartDay, WEEKDAY(DATE($A27, $B27, 1), 1),_xlpm.DayNum, (COLUMN() - COLUMN($K$26) + 1) + (ROW() - ROW($K$26)) * 7 - _xlpm.StartDay + 1,IF(AND(_xlpm.DayNum > 0, _xlpm.DayNum <= DAY(EOMONTH(DATE($A27, $B27, 1), 0))), _xlpm.DayNum, "")) -> 7 | Q27: =_xlfn.LET(_xlpm.StartDay, WEEKDAY(DATE($A27, $B27, 1), 1),_xlpm.DayNum, (COLUMN() - COLUMN($K$26) + 1) + (ROW() - ROW($K$26)) * 7 - _xlpm.StartDay + 1,IF(AND(_xlpm.DayNum > 0, _xlpm.DayNum <= DAY(EOMONTH(DATE($A27, $B27, 1), 0))), _xlpm.DayNum, "")) -> 8
A28: 2027 | B28: 5 | C28: 3 | D28: 2 | E28: 3 | F28: 3 | G28: 2 | H28: 3 | I28: 3 | J28: 3 | K28: =_xlfn.LET(_xlpm.StartDay, WEEKDAY(DATE($A28, $B28, 1), 1),_xlpm.DayNum, (COLUMN() - COLUMN($K$26) + 1) + (ROW() - ROW($K$26)) * 7 - _xlpm.StartDay + 1,IF(AND(_xlpm.DayNum > 0, _xlpm.DayNum <= DAY(EOMONTH(DATE($A28, $B28, 1), 0))), _xlpm.DayNum, "")) -> 9 | L28: =_xlfn.LET(_xlpm.StartDay, WEEKDAY(DATE($A28, $B28, 1), 1),_xlpm.DayNum, (COLUMN() - COLUMN($K$26) + 1) + (ROW() - ROW($K$26)) * 7 - _xlpm.StartDay + 1,IF(AND(_xlpm.DayNum > 0, _xlpm.DayNum <= DAY(EOMONTH(DATE($A28, $B28, 1), 0))), _xlpm.DayNum, "")) -> 10 | M28: =_xlfn.LET(_xlpm.StartDay, WEEKDAY(DATE($A28, $B28, 1), 1),_xlpm.DayNum, (COLUMN() - COLUMN($K$26) + 1) + (ROW() - ROW($K$26)) * 7 - _xlpm.StartDay + 1,IF(AND(_xlpm.DayNum > 0, _xlpm.DayNum <= DAY(EOMONTH(DATE($A28, $B28, 1), 0))), _xlpm.DayNum, "")) -> 11 | N28: =_xlfn.LET(_xlpm.StartDay, WEEKDAY(DATE($A28, $B28, 1), 1),_xlpm.DayNum, (COLUMN() - COLUMN($K$26) + 1) + (ROW() - ROW($K$26)) * 7 - _xlpm.StartDay + 1,IF(AND(_xlpm.DayNum > 0, _xlpm.DayNum <= DAY(EOMONTH(DATE($A28, $B28, 1), 0))), _xlpm.DayNum, "")) -> 12 | O28: =_xlfn.LET(_xlpm.StartDay, WEEKDAY(DATE($A28, $B28, 1), 1),_xlpm.DayNum, (COLUMN() - COLUMN($K$26) + 1) + (ROW() - ROW($K$26)) * 7 - _xlpm.StartDay + 1,IF(AND(_xlpm.DayNum > 0, _xlpm.DayNum <= DAY(EOMONTH(DATE($A28, $B28, 1), 0))), _xlpm.DayNum, "")) -> 13 | P28: =_xlfn.LET(_xlpm.StartDay, WEEKDAY(DATE($A28, $B28, 1), 1),_xlpm.DayNum, (COLUMN() - COLUMN($K$26) + 1) + (ROW() - ROW($K$26)) * 7 - _xlpm.StartDay + 1,IF(AND(_xlpm.DayNum > 0, _xlpm.DayNum <= DAY(EOMONTH(DATE($A28, $B28, 1), 0))), _xlpm.DayNum, "")) -> 14 | Q28: =_xlfn.LET(_xlpm.StartDay, WEEKDAY(DATE($A28, $B28, 1), 1),_xlpm.DayNum, (COLUMN() - COLUMN($K$26) + 1) + (ROW() - ROW($K$26)) * 7 - _xlpm.StartDay + 1,IF(AND(_xlpm.DayNum > 0, _xlpm.DayNum <= DAY(EOMONTH(DATE($A28, $B28, 1), 0))), _xlpm.DayNum, "")) -> 15
A29: 2027 | B29: 5 | C29: 4 | D29: 2 | E29: 2 | F29: 4 | G29: 3 | H29: 3 | I29: 4 | J29: 2 | K29: =_xlfn.LET(_xlpm.StartDay, WEEKDAY(DATE($A29, $B29, 1), 1),_xlpm.DayNum, (COLUMN() - COLUMN($K$26) + 1) + (ROW() - ROW($K$26)) * 7 - _xlpm.StartDay + 1,IF(AND(_xlpm.DayNum > 0, _xlpm.DayNum <= DAY(EOMONTH(DATE($A29, $B29, 1), 0))), _xlpm.DayNum, "")) -> 16 | L29: =_xlfn.LET(_xlpm.StartDay, WEEKDAY(DATE($A29, $B29, 1), 1),_xlpm.DayNum, (COLUMN() - COLUMN($K$26) + 1) + (ROW() - ROW($K$26)) * 7 - _xlpm.StartDay + 1,IF(AND(_xlpm.DayNum > 0, _xlpm.DayNum <= DAY(EOMONTH(DATE($A29, $B29, 1), 0))), _xlpm.DayNum, "")) -> 17 | M29: =_xlfn.LET(_xlpm.StartDay, WEEKDAY(DATE($A29, $B29, 1), 1),_xlpm.DayNum, (COLUMN() - COLUMN($K$26) + 1) + (ROW() - ROW($K$26)) * 7 - _xlpm.StartDay + 1,IF(AND(_xlpm.DayNum > 0, _xlpm.DayNum <= DAY(EOMONTH(DATE($A29, $B29, 1), 0))), _xlpm.DayNum, "")) -> 18 | N29: =_xlfn.LET(_xlpm.StartDay, WEEKDAY(DATE($A29, $B29, 1), 1),_xlpm.DayNum, (COLUMN() - COLUMN($K$26) + 1) + (ROW() - ROW($K$26)) * 7 - _xlpm.StartDay + 1,IF(AND(_xlpm.DayNum > 0, _xlpm.DayNum <= DAY(EOMONTH(DATE($A29, $B29, 1), 0))), _xlpm.DayNum, "")) -> 19 | O29: =_xlfn.LET(_xlpm.StartDay, WEEKDAY(DATE($A29, $B29, 1), 1),_xlpm.DayNum, (COLUMN() - COLUMN($K$26) + 1) + (ROW() - ROW($K$26)) * 7 - _xlpm.StartDay + 1,IF(AND(_xlpm.DayNum > 0, _xlpm.DayNum <= DAY(EOMONTH(DATE($A29, $B29, 1), 0))), _xlpm.DayNum, "")) -> 20 | P29: =_xlfn.LET(_xlpm.StartDay, WEEKDAY(DATE($A29, $B29, 1), 1),_xlpm.DayNum, (COLUMN() - COLUMN($K$26) + 1) + (ROW() - ROW($K$26)) * 7 - _xlpm.StartDay + 1,IF(AND(_xlpm.DayNum > 0, _xlpm.DayNum <= DAY(EOMONTH(DATE($A29, $B29, 1), 0))), _xlpm.DayNum, "")) -> 21 | Q29: =_xlfn.LET(_xlpm.StartDay, WEEKDAY(DATE($A29, $B29, 1), 1),_xlpm.DayNum, (COLUMN() - COLUMN($K$26) + 1) + (ROW() - ROW($K$26)) * 7 - _xlpm.StartDay + 1,IF(AND(_xlpm.DayNum > 0, _xlpm.DayNum <= DAY(EOMONTH(DATE($A29, $B29, 1), 0))), _xlpm.DayNum, "")) -> 22
A30: 2027 | B30: 5 | C30: 5 | D30: 2 | E30: 2 | F30: 2 | G30: 2 | H30: 2 | I30: 2 | J30: 2 | K30: =_xlfn.LET(_xlpm.StartDay, WEEKDAY(DATE($A30, $B30, 1), 1),_xlpm.DayNum, (COLUMN() - COLUMN($K$26) + 1) + (ROW() - ROW($K$26)) * 7 - _xlpm.StartDay + 1,IF(AND(_xlpm.DayNum > 0, _xlpm.DayNum <= DAY(EOMONTH(DATE($A30, $B30, 1), 0))), _xlpm.DayNum, "")) -> 23 | L30: =_xlfn.LET(_xlpm.StartDay, WEEKDAY(DATE($A30, $B30, 1), 1),_xlpm.DayNum, (COLUMN() - COLUMN($K$26) + 1) + (ROW() - ROW($K$26)) * 7 - _xlpm.StartDay + 1,IF(AND(_xlpm.DayNum > 0, _xlpm.DayNum <= DAY(EOMONTH(DATE($A30, $B30, 1), 0))), _xlpm.DayNum, "")) -> 24 | M30: =_xlfn.LET(_xlpm.StartDay, WEEKDAY(DATE($A30, $B30, 1), 1),_xlpm.DayNum, (COLUMN() - COLUMN($K$26) + 1) + (ROW() - ROW($K$26)) * 7 - _xlpm.StartDay + 1,IF(AND(_xlpm.DayNum > 0, _xlpm.DayNum <= DAY(EOMONTH(DATE($A30, $B30, 1), 0))), _xlpm.DayNum, "")) -> 25 | N30: =_xlfn.LET(_xlpm.StartDay, WEEKDAY(DATE($A30, $B30, 1), 1),_xlpm.DayNum, (COLUMN() - COLUMN($K$26) + 1) + (ROW() - ROW($K$26)) * 7 - _xlpm.StartDay + 1,IF(AND(_xlpm.DayNum > 0, _xlpm.DayNum <= DAY(EOMONTH(DATE($A30, $B30, 1), 0))), _xlpm.DayNum, "")) -> 26 | O30: =_xlfn.LET(_xlpm.StartDay, WEEKDAY(DATE($A30, $B30, 1), 1),_xlpm.DayNum, (COLUMN() - COLUMN($K$26) + 1) + (ROW() - ROW($K$26)) * 7 - _xlpm.StartDay + 1,IF(AND(_xlpm.DayNum > 0, _xlpm.DayNum <= DAY(EOMONTH(DATE($A30, $B30, 1), 0))), _xlpm.DayNum, "")) -> 27 | P30: =_xlfn.LET(_xlpm.StartDay, WEEKDAY(DATE($A30, $B30, 1), 1),_xlpm.DayNum, (COLUMN() - COLUMN($K$26) + 1) + (ROW() - ROW($K$26)) * 7 - _xlpm.StartDay + 1,IF(AND(_xlpm.DayNum > 0, _xlpm.DayNum <= DAY(EOMONTH(DATE($A30, $B30, 1), 0))), _xlpm.DayNum, "")) -> 28 | Q30: =_xlfn.LET(_xlpm.StartDay, WEEKDAY(DATE($A30, $B30, 1), 1),_xlpm.DayNum, (COLUMN() - COLUMN($K$26) + 1) + (ROW() - ROW($K$26)) * 7 - _xlpm.StartDay + 1,IF(AND(_xlpm.DayNum > 0, _xlpm.DayNum <= DAY(EOMONTH(DATE($A30, $B30, 1), 0))), _xlpm.DayNum, "")) -> 29
A31: 2027 | B31: 5 | C31: 6 | D31: 2 | E31: 2 | F31: 1 | G31: 1 | H31: 1 | I31: 1 | J31: 1 | K31: =_xlfn.LET(_xlpm.StartDay, WEEKDAY(DATE($A31, $B31, 1), 1),_xlpm.DayNum, (COLUMN() - COLUMN($K$26) + 1) + (ROW() - ROW($K$26)) * 7 - _xlpm.StartDay + 1,IF(AND(_xlpm.DayNum > 0, _xlpm.DayNum <= DAY(EOMONTH(DATE($A31, $B31, 1), 0))), _xlpm.DayNum, "")) -> 30 | L31: =_xlfn.LET(_xlpm.StartDay, WEEKDAY(DATE($A31, $B31, 1), 1),_xlpm.DayNum, (COLUMN() - COLUMN($K$26) + 1) + (ROW() - ROW($K$26)) * 7 - _xlpm.StartDay + 1,IF(AND(_xlpm.DayNum > 0, _xlpm.DayNum <= DAY(EOMONTH(DATE($A31, $B31, 1), 0))), _xlpm.DayNum, "")) -> 31 | M31: =IF(F31<>1,"ERROR!!!","") | N31: =IF(G31<>1,"ERROR!!!","") | O31: =IF(H31<>1,"ERROR!!!","") | P31: =IF(I31<>1,"ERROR!!!","") | Q31: =IF(J31<>1,"ERROR!!!","")
A32: 2027 | B32: 6 | C32: 1 | D32: 1 | E32: 1 | F32: 3 | G32: 2 | H32: 2 | I32: 2 | J32: 3 | K32: =IF(D32<>1,"ERROR!!!","") | L32: =IF(E32<>1,"ERROR!!!","") | M32: =_xlfn.LET(_xlpm.StartDay, WEEKDAY(DATE($A32, $B32, 1), 1),_xlpm.DayNum, (COLUMN() - COLUMN($K$32) + 1) + (ROW() - ROW($K$32)) * 7 - _xlpm.StartDay + 1,IF(AND(_xlpm.DayNum > 0, _xlpm.DayNum <= DAY(EOMONTH(DATE($A32, $B32, 1), 0))), _xlpm.DayNum, "")) -> 1 | N32: =_xlfn.LET(_xlpm.StartDay, WEEKDAY(DATE($A32, $B32, 1), 1),_xlpm.DayNum, (COLUMN() - COLUMN($K$32) + 1) + (ROW() - ROW($K$32)) * 7 - _xlpm.StartDay + 1,IF(AND(_xlpm.DayNum > 0, _xlpm.DayNum <= DAY(EOMONTH(DATE($A32, $B32, 1), 0))), _xlpm.DayNum, "")) -> 2 | O32: =_xlfn.LET(_xlpm.StartDay, WEEKDAY(DATE($A32, $B32, 1), 1),_xlpm.DayNum, (COLUMN() - COLUMN($K$32) + 1) + (ROW() - ROW($K$32)) * 7 - _xlpm.StartDay + 1,IF(AND(_xlpm.DayNum > 0, _xlpm.DayNum <= DAY(EOMONTH(DATE($A32, $B32, 1), 0))), _xlpm.DayNum, "")) -> 3 | P32: =_xlfn.LET(_xlpm.StartDay, WEEKDAY(DATE($A32, $B32, 1), 1),_xlpm.DayNum, (COLUMN() - COLUMN($K$32) + 1) + (ROW() - ROW($K$32)) * 7 - _xlpm.StartDay + 1,IF(AND(_xlpm.DayNum > 0, _xlpm.DayNum <= DAY(EOMONTH(DATE($A32, $B32, 1), 0))), _xlpm.DayNum, "")) -> 4 | Q32: =_xlfn.LET(_xlpm.StartDay, WEEKDAY(DATE($A32, $B32, 1), 1),_xlpm.DayNum, (COLUMN() - COLUMN($K$32) + 1) + (ROW() - ROW($K$32)) * 7 - _xlpm.StartDay + 1,IF(AND(_xlpm.DayNum > 0, _xlpm.DayNum <= DAY(EOMONTH(DATE($A32, $B32, 1), 0))), _xlpm.DayNum, "")) -> 5
A33: 2027 | B33: 6 | C33: 2 | D33: 3 | E33: 2 | F33: 2 | G33: 4 | H33: 2 | I33: 3 | J33: 3 | K33: =_xlfn.LET(_xlpm.StartDay, WEEKDAY(DATE($A33, $B33, 1), 1),_xlpm.DayNum, (COLUMN() - COLUMN($K$32) + 1) + (ROW() - ROW($K$32)) * 7 - _xlpm.StartDay + 1,IF(AND(_xlpm.DayNum > 0, _xlpm.DayNum <= DAY(EOMONTH(DATE($A33, $B33, 1), 0))), _xlpm.DayNum, "")) -> 6 | L33: =_xlfn.LET(_xlpm.StartDay, WEEKDAY(DATE($A33, $B33, 1), 1),_xlpm.DayNum, (COLUMN() - COLUMN($K$32) + 1) + (ROW() - ROW($K$32)) * 7 - _xlpm.StartDay + 1,IF(AND(_xlpm.DayNum > 0, _xlpm.DayNum <= DAY(EOMONTH(DATE($A33, $B33, 1), 0))), _xlpm.DayNum, "")) -> 7 | M33: =_xlfn.LET(_xlpm.StartDay, WEEKDAY(DATE($A33, $B33, 1), 1),_xlpm.DayNum, (COLUMN() - COLUMN($K$32) + 1) + (ROW() - ROW($K$32)) * 7 - _xlpm.StartDay + 1,IF(AND(_xlpm.DayNum > 0, _xlpm.DayNum <= DAY(EOMONTH(DATE($A33, $B33, 1), 0))), _xlpm.DayNum, "")) -> 8 | N33: =_xlfn.LET(_xlpm.StartDay, WEEKDAY(DATE($A33, $B33, 1), 1),_xlpm.DayNum, (COLUMN() - COLUMN($K$32) + 1) + (ROW() - ROW($K$32)) * 7 - _xlpm.StartDay + 1,IF(AND(_xlpm.DayNum > 0, _xlpm.DayNum <= DAY(EOMONTH(DATE($A33, $B33, 1), 0))), _xlpm.DayNum, "")) -> 9 | O33: =_xlfn.LET(_xlpm.StartDay, WEEKDAY(DATE($A33, $B33, 1), 1),_xlpm.DayNum, (COLUMN() - COLUMN($K$32) + 1) + (ROW() - ROW($K$32)) * 7 - _xlpm.StartDay + 1,IF(AND(_xlpm.DayNum > 0, _xlpm.DayNum <= DAY(EOMONTH(DATE($A33, $B33, 1), 0))), _xlpm.DayNum, "")) -> 10 | P33: =_xlfn.LET(_xlpm.StartDay, WEEKDAY(DATE($A33, $B33, 1), 1),_xlpm.DayNum, (COLUMN() - COLUMN($K$32) + 1) + (ROW() - ROW($K$32)) * 7 - _xlpm.StartDay + 1,IF(AND(_xlpm.DayNum > 0, _xlpm.DayNum <= DAY(EOMONTH(DATE($A33, $B33, 1), 0))), _xlpm.DayNum, "")) -> 11 | Q33: =_xlfn.LET(_xlpm.StartDay, WEEKDAY(DATE($A33, $B33, 1), 1),_xlpm.DayNum, (COLUMN() - COLUMN($K$32) + 1) + (ROW() - ROW($K$32)) * 7 - _xlpm.StartDay + 1,IF(AND(_xlpm.DayNum > 0, _xlpm.DayNum <= DAY(EOMONTH(DATE($A33, $B33, 1), 0))), _xlpm.DayNum, "")) -> 12
A34: 2027 | B34: 6 | C34: 3 | D34: 2 | E34: 3 | F34: 3 | G34: 4 | H34: 2 | I34: 3 | J34: 2 | K34: =_xlfn.LET(_xlpm.StartDay, WEEKDAY(DATE($A34, $B34, 1), 1),_xlpm.DayNum, (COLUMN() - COLUMN($K$32) + 1) + (ROW() - ROW($K$32)) * 7 - _xlpm.StartDay + 1,IF(AND(_xlpm.DayNum > 0, _xlpm.DayNum <= DAY(EOMONTH(DATE($A34, $B34, 1), 0))), _xlpm.DayNum, "")) -> 13 | L34: =_xlfn.LET(_xlpm.StartDay, WEEKDAY(DATE($A34, $B34, 1), 1),_xlpm.DayNum, (COLUMN() - COLUMN($K$32) + 1) + (ROW() - ROW($K$32)) * 7 - _xlpm.StartDay + 1,IF(AND(_xlpm.DayNum > 0, _xlpm.DayNum <= DAY(EOMONTH(DATE($A34, $B34, 1), 0))), _xlpm.DayNum, "")) -> 14 | M34: =_xlfn.LET(_xlpm.StartDay, WEEKDAY(DATE($A34, $B34, 1), 1),_xlpm.DayNum, (COLUMN() - COLUMN($K$32) + 1) + (ROW() - ROW($K$32)) * 7 - _xlpm.StartDay + 1,IF(AND(_xlpm.DayNum > 0, _xlpm.DayNum <= DAY(EOMONTH(DATE($A34, $B34, 1), 0))), _xlpm.DayNum, "")) -> 15 | N34: =_xlfn.LET(_xlpm.StartDay, WEEKDAY(DATE($A34, $B34, 1), 1),_xlpm.DayNum, (COLUMN() - COLUMN($K$32) + 1) + (ROW() - ROW($K$32)) * 7 - _xlpm.StartDay + 1,IF(AND(_xlpm.DayNum > 0, _xlpm.DayNum <= DAY(EOMONTH(DATE($A34, $B34, 1), 0))), _xlpm.DayNum, "")) -> 16 | O34: =_xlfn.LET(_xlpm.StartDay, WEEKDAY(DATE($A34, $B34, 1), 1),_xlpm.DayNum, (COLUMN() - COLUMN($K$32) + 1) + (ROW() - ROW($K$32)) * 7 - _xlpm.StartDay + 1,IF(AND(_xlpm.DayNum > 0, _xlpm.DayNum <= DAY(EOMONTH(DATE($A34, $B34, 1), 0))), _xlpm.DayNum, "")) -> 17 | P34: =_xlfn.LET(_xlpm.StartDay, WEEKDAY(DATE($A34, $B34, 1), 1),_xlpm.DayNum, (COLUMN() - COLUMN($K$32) + 1) + (ROW() - ROW($K$32)) * 7 - _xlpm.StartDay + 1,IF(AND(_xlpm.DayNum > 0, _xlpm.DayNum <= DAY(EOMONTH(DATE($A34, $B34, 1), 0))), _xlpm.DayNum, "")) -> 18 | Q34: =_xlfn.LET(_xlpm.StartDay, WEEKDAY(DATE($A34, $B34, 1), 1),_xlpm.DayNum, (COLUMN() - COLUMN($K$32) + 1) + (ROW() - ROW($K$32)) * 7 - _xlpm.StartDay + 1,IF(AND(_xlpm.DayNum > 0, _xlpm.DayNum <= DAY(EOMONTH(DATE($A34, $B34, 1), 0))), _xlpm.DayNum, "")) -> 19
A35: 2027 | B35: 6 | C35: 4 | D35: 2 | E35: 3 | F35: 2 | G35: 3 | H35: 3 | I35: 3 | J35: 2 | K35: =_xlfn.LET(_xlpm.StartDay, WEEKDAY(DATE($A35, $B35, 1), 1),_xlpm.DayNum, (COLUMN() - COLUMN($K$32) + 1) + (ROW() - ROW($K$32)) * 7 - _xlpm.StartDay + 1,IF(AND(_xlpm.DayNum > 0, _xlpm.DayNum <= DAY(EOMONTH(DATE($A35, $B35, 1), 0))), _xlpm.DayNum, "")) -> 20 | L35: =_xlfn.LET(_xlpm.StartDay, WEEKDAY(DATE($A35, $B35, 1), 1),_xlpm.DayNum, (COLUMN() - COLUMN($K$32) + 1) + (ROW() - ROW($K$32)) * 7 - _xlpm.StartDay + 1,IF(AND(_xlpm.DayNum > 0, _xlpm.DayNum <= DAY(EOMONTH(DATE($A35, $B35, 1), 0))), _xlpm.DayNum, "")) -> 21 | M35: =_xlfn.LET(_xlpm.StartDay, WEEKDAY(DATE($A35, $B35, 1), 1),_xlpm.DayNum, (COLUMN() - COLUMN($K$32) + 1) + (ROW() - ROW($K$32)) * 7 - _xlpm.StartDay + 1,IF(AND(_xlpm.DayNum > 0, _xlpm.DayNum <= DAY(EOMONTH(DATE($A35, $B35, 1), 0))), _xlpm.DayNum, "")) -> 22 | N35: =_xlfn.LET(_xlpm.StartDay, WEEKDAY(DATE($A35, $B35, 1), 1),_xlpm.DayNum, (COLUMN() - COLUMN($K$32) + 1) + (ROW() - ROW($K$32)) * 7 - _xlpm.StartDay + 1,IF(AND(_xlpm.DayNum > 0, _xlpm.DayNum <= DAY(EOMONTH(DATE($A35, $B35, 1), 0))), _xlpm.DayNum, "")) -> 23 | O35: =_xlfn.LET(_xlpm.StartDay, WEEKDAY(DATE($A35, $B35, 1), 1),_xlpm.DayNum, (COLUMN() - COLUMN($K$32) + 1) + (ROW() - ROW($K$32)) * 7 - _xlpm.StartDay + 1,IF(AND(_xlpm.DayNum > 0, _xlpm.DayNum <= DAY(EOMONTH(DATE($A35, $B35, 1), 0))), _xlpm.DayNum, "")) -> 24 | P35: =_xlfn.LET(_xlpm.StartDay, WEEKDAY(DATE($A35, $B35, 1), 1),_xlpm.DayNum, (COLUMN() - COLUMN($K$32) + 1) + (ROW() - ROW($K$32)) * 7 - _xlpm.StartDay + 1,IF(AND(_xlpm.DayNum > 0, _xlpm.DayNum <= DAY(EOMONTH(DATE($A35, $B35, 1), 0))), _xlpm.DayNum, "")) -> 25 | Q35: =_xlfn.LET(_xlpm.StartDay, WEEKDAY(DATE($A35, $B35, 1), 1),_xlpm.DayNum, (COLUMN() - COLUMN($K$32) + 1) + (ROW() - ROW($K$32)) * 7 - _xlpm.StartDay + 1,IF(AND(_xlpm.DayNum > 0, _xlpm.DayNum <= DAY(EOMONTH(DATE($A35, $B35, 1), 0))), _xlpm.DayNum, "")) -> 26
A36: 2027 | B36: 6 | C36: 5 | D36: 4 | E36: 3 | F36: 2 | G36: 2 | H36: 1 | I36: 1 | J36: 1 | K36: =_xlfn.LET(_xlpm.StartDay, WEEKDAY(DATE($A36, $B36, 1), 1),_xlpm.DayNum, (COLUMN() - COLUMN($K$32) + 1) + (ROW() - ROW($K$32)) * 7 - _xlpm.StartDay + 1,IF(AND(_xlpm.DayNum > 0, _xlpm.DayNum <= DAY(EOMONTH(DATE($A36, $B36, 1), 0))), _xlpm.DayNum, "")) -> 27 | L36: =_xlfn.LET(_xlpm.StartDay, WEEKDAY(DATE($A36, $B36, 1), 1),_xlpm.DayNum, (COLUMN() - COLUMN($K$32) + 1) + (ROW() - ROW($K$32)) * 7 - _xlpm.StartDay + 1,IF(AND(_xlpm.DayNum > 0, _xlpm.DayNum <= DAY(EOMONTH(DATE($A36, $B36, 1), 0))), _xlpm.DayNum, "")) -> 28 | M36: =_xlfn.LET(_xlpm.StartDay, WEEKDAY(DATE($A36, $B36, 1), 1),_xlpm.DayNum, (COLUMN() - COLUMN($K$32) + 1) + (ROW() - ROW($K$32)) * 7 - _xlpm.StartDay + 1,IF(AND(_xlpm.DayNum > 0, _xlpm.DayNum <= DAY(EOMONTH(DATE($A36, $B36, 1), 0))), _xlpm.DayNum, "")) -> 29 | N36: =_xlfn.LET(_xlpm.StartDay, WEEKDAY(DATE($A36, $B36, 1), 1),_xlpm.DayNum, (COLUMN() - COLUMN($K$32) + 1) + (ROW() - ROW($K$32)) * 7 - _xlpm.StartDay + 1,IF(AND(_xlpm.DayNum > 0, _xlpm.DayNum <= DAY(EOMONTH(DATE($A36, $B36, 1), 0))), _xlpm.DayNum, "")) -> 30 | O36: =IF(H36<>1,"ERROR!!!","") | P36: =IF(I36<>1,"ERROR!!!","") | Q36: =IF(J36<>1,"ERROR!!!","")
A37: 2027 | B37: 6 | C37: 6 | D37: 1 | E37: 1 | F37: 1 | G37: 1 | H37: 1 | I37: 1 | J37: 1 | K37: =IF(D37<>1,"ERROR!!!","") | L37: =IF(E37<>1,"ERROR!!!","") | M37: =IF(F37<>1,"ERROR!!!","") | N37: =IF(G37<>1,"ERROR!!!","") | O37: =IF(H37<>1,"ERROR!!!","") | P37: =IF(I37<>1,"ERROR!!!","") | Q37: =IF(J37<>1,"ERROR!!!","")
A38: 2027 | B38: 7 | C38: 1 | D38: 1 | E38: 1 | F38: 1 | G38: 1 | H38: 4 | I38: 3 | J38: 3 | K38: =IF(D38<>1,"ERROR!!!","") | L38: =IF(E38<>1,"ERROR!!!","") | M38: =IF(F38<>1,"ERROR!!!","") | N38: =IF(G38<>1,"ERROR!!!","") | O38: =_xlfn.LET(_xlpm.StartDay, WEEKDAY(DATE($A38, $B38, 1), 1),_xlpm.DayNum, (COLUMN() - COLUMN($K$38) + 1) + (ROW() - ROW($K$38)) * 7 - _xlpm.StartDay + 1,IF(AND(_xlpm.DayNum > 0, _xlpm.DayNum <= DAY(EOMONTH(DATE($A38, $B38, 1), 0))), _xlpm.DayNum, "")) -> 1 | P38: =_xlfn.LET(_xlpm.StartDay, WEEKDAY(DATE($A38, $B38, 1), 1),_xlpm.DayNum, (COLUMN() - COLUMN($K$38) + 1) + (ROW() - ROW($K$38)) * 7 - _xlpm.StartDay + 1,IF(AND(_xlpm.DayNum > 0, _xlpm.DayNum <= DAY(EOMONTH(DATE($A38, $B38, 1), 0))), _xlpm.DayNum, "")) -> 2 | Q38: =_xlfn.LET(_xlpm.StartDay, WEEKDAY(DATE($A38, $B38, 1), 1),_xlpm.DayNum, (COLUMN() - COLUMN($K$38) + 1) + (ROW() - ROW($K$38)) * 7 - _xlpm.StartDay + 1,IF(AND(_xlpm.DayNum > 0, _xlpm.DayNum <= DAY(EOMONTH(DATE($A38, $B38, 1), 0))), _xlpm.DayNum, "")) -> 3
A39: 2027 | B39: 7 | C39: 2 | D39: 3 | E39: 2 | F39: 2 | G39: 3 | H39: 3 | I39: 3 | J39: 3 | K39: =_xlfn.LET(_xlpm.StartDay, WEEKDAY(DATE($A39, $B39, 1), 1),_xlpm.DayNum, (COLUMN() - COLUMN($K$38) + 1) + (ROW() - ROW($K$38)) * 7 - _xlpm.StartDay + 1,IF(AND(_xlpm.DayNum > 0, _xlpm.DayNum <= DAY(EOMONTH(DATE($A39, $B39, 1), 0))), _xlpm.DayNum, "")) -> 4 | L39: =_xlfn.LET(_xlpm.StartDay, WEEKDAY(DATE($A39, $B39, 1), 1),_xlpm.DayNum, (COLUMN() - COLUMN($K$38) + 1) + (ROW() - ROW($K$38)) * 7 - _xlpm.StartDay + 1,IF(AND(_xlpm.DayNum > 0, _xlpm.DayNum <= DAY(EOMONTH(DATE($A39, $B39, 1), 0))), _xlpm.DayNum, "")) -> 5 | M39: =_xlfn.LET(_xlpm.StartDay, WEEKDAY(DATE($A39, $B39, 1), 1),_xlpm.DayNum, (COLUMN() - COLUMN($K$38) + 1) + (ROW() - ROW($K$38)) * 7 - _xlpm.StartDay + 1,IF(AND(_xlpm.DayNum > 0, _xlpm.DayNum <= DAY(EOMONTH(DATE($A39, $B39, 1), 0))), _xlpm.DayNum, "")) -> 6 | N39: =_xlfn.LET(_xlpm.StartDay, WEEKDAY(DATE($A39, $B39, 1), 1),_xlpm.DayNum, (COLUMN() - COLUMN($K$38) + 1) + (ROW() - ROW($K$38)) * 7 - _xlpm.StartDay + 1,IF(AND(_xlpm.DayNum > 0, _xlpm.DayNum <= DAY(EOMONTH(DATE($A39, $B39, 1), 0))), _xlpm.DayNum, "")) -> 7 | O39: =_xlfn.LET(_xlpm.StartDay, WEEKDAY(DATE($A39, $B39, 1), 1),_xlpm.DayNum, (COLUMN() - COLUMN($K$38) + 1) + (ROW() - ROW($K$38)) * 7 - _xlpm.StartDay + 1,IF(AND(_xlpm.DayNum > 0, _xlpm.DayNum <= DAY(EOMONTH(DATE($A39, $B39, 1), 0))), _xlpm.DayNum, "")) -> 8 | P39: =_xlfn.LET(_xlpm.StartDay, WEEKDAY(DATE($A39, $B39, 1), 1),_xlpm.DayNum, (COLUMN() - COLUMN($K$38) + 1) + (ROW() - ROW($K$38)) * 7 - _xlpm.StartDay + 1,IF(AND(_xlpm.DayNum > 0, _xlpm.DayNum <= DAY(EOMONTH(DATE($A39, $B39, 1), 0))), _xlpm.DayNum, "")) -> 9 | Q39: =_xlfn.LET(_xlpm.StartDay, WEEKDAY(DATE($A39, $B39, 1), 1),_xlpm.DayNum, (COLUMN() - COLUMN($K$38) + 1) + (ROW() - ROW($K$38)) * 7 - _xlpm.StartDay + 1,IF(AND(_xlpm.DayNum > 0, _xlpm.DayNum <= DAY(EOMONTH(DATE($A39, $B39, 1), 0))), _xlpm.DayNum, "")) -> 10
A40: 2027 | B40: 7 | C40: 3 | D40: 2 | E40: 2 | F40: 2 | G40: 2 | H40: 3 | I40: 2 | J40: 2 | K40: =_xlfn.LET(_xlpm.StartDay, WEEKDAY(DATE($A40, $B40, 1), 1),_xlpm.DayNum, (COLUMN() - COLUMN($K$38) + 1) + (ROW() - ROW($K$38)) * 7 - _xlpm.StartDay + 1,IF(AND(_xlpm.DayNum > 0, _xlpm.DayNum <= DAY(EOMONTH(DATE($A40, $B40, 1), 0))), _xlpm.DayNum, "")) -> 11 | L40: =_xlfn.LET(_xlpm.StartDay, WEEKDAY(DATE($A40, $B40, 1), 1),_xlpm.DayNum, (COLUMN() - COLUMN($K$38) + 1) + (ROW() - ROW($K$38)) * 7 - _xlpm.StartDay + 1,IF(AND(_xlpm.DayNum > 0, _xlpm.DayNum <= DAY(EOMONTH(DATE($A40, $B40, 1), 0))), _xlpm.DayNum, "")) -> 12 | M40: =_xlfn.LET(_xlpm.StartDay, WEEKDAY(DATE($A40, $B40, 1), 1),_xlpm.DayNum, (COLUMN() - COLUMN($K$38) + 1) + (ROW() - ROW($K$38)) * 7 - _xlpm.StartDay + 1,IF(AND(_xlpm.DayNum > 0, _xlpm.DayNum <= DAY(EOMONTH(DATE($A40, $B40, 1), 0))), _xlpm.DayNum, "")) -> 13 | N40: =_xlfn.LET(_xlpm.StartDay, WEEKDAY(DATE($A40, $B40, 1), 1),_xlpm.DayNum, (COLUMN() - COLUMN($K$38) + 1) + (ROW() - ROW($K$38)) * 7 - _xlpm.StartDay + 1,IF(AND(_xlpm.DayNum > 0, _xlpm.DayNum <= DAY(EOMONTH(DATE($A40, $B40, 1), 0))), _xlpm.DayNum, "")) -> 14 | O40: =_xlfn.LET(_xlpm.StartDay, WEEKDAY(DATE($A40, $B40, 1), 1),_xlpm.DayNum, (COLUMN() - COLUMN($K$38) + 1) + (ROW() - ROW($K$38)) * 7 - _xlpm.StartDay + 1,IF(AND(_xlpm.DayNum > 0, _xlpm.DayNum <= DAY(EOMONTH(DATE($A40, $B40, 1), 0))), _xlpm.DayNum, "")) -> 15 | P40: =_xlfn.LET(_xlpm.StartDay, WEEKDAY(DATE($A40, $B40, 1), 1),_xlpm.DayNum, (COLUMN() - COLUMN($K$38) + 1) + (ROW() - ROW($K$38)) * 7 - _xlpm.StartDay + 1,IF(AND(_xlpm.DayNum > 0, _xlpm.DayNum <= DAY(EOMONTH(DATE($A40, $B40, 1), 0))), _xlpm.DayNum, "")) -> 16 | Q40: =_xlfn.LET(_xlpm.StartDay, WEEKDAY(DATE($A40, $B40, 1), 1),_xlpm.DayNum, (COLUMN() - COLUMN($K$38) + 1) + (ROW() - ROW($K$38)) * 7 - _xlpm.StartDay + 1,IF(AND(_xlpm.DayNum > 0, _xlpm.DayNum <= DAY(EOMONTH(DATE($A40, $B40, 1), 0))), _xlpm.DayNum, "")) -> 17
A41: 2027 | B41: 7 | C41: 4 | D41: 2 | E41: 2 | F41: 3 | G41: 4 | H41: 3 | I41: 2 | J41: 2 | K41: =_xlfn.LET(_xlpm.StartDay, WEEKDAY(DATE($A41, $B41, 1), 1),_xlpm.DayNum, (COLUMN() - COLUMN($K$38) + 1) + (ROW() - ROW($K$38)) * 7 - _xlpm.StartDay + 1,IF(AND(_xlpm.DayNum > 0, _xlpm.DayNum <= DAY(EOMONTH(DATE($A41, $B41, 1), 0))), _xlpm.DayNum, "")) -> 18 | L41: =_xlfn.LET(_xlpm.StartDay, WEEKDAY(DATE($A41, $B41, 1), 1),_xlpm.DayNum, (COLUMN() - COLUMN($K$38) + 1) + (ROW() - ROW($K$38)) * 7 - _xlpm.StartDay + 1,IF(AND(_xlpm.DayNum > 0, _xlpm.DayNum <= DAY(EOMONTH(DATE($A41, $B41, 1), 0))), _xlpm.DayNum, "")) -> 19 | M41: =_xlfn.LET(_xlpm.StartDay, WEEKDAY(DATE($A41, $B41, 1), 1),_xlpm.DayNum, (COLUMN() - COLUMN($K$38) + 1) + (ROW() - ROW($K$38)) * 7 - _xlpm.StartDay + 1,IF(AND(_xlpm.DayNum > 0, _xlpm.DayNum <= DAY(EOMONTH(DATE($A41, $B41, 1), 0))), _xlpm.DayNum, "")) -> 20 | N41: =_xlfn.LET(_xlpm.StartDay, WEEKDAY(DATE($A41, $B41, 1), 1),_xlpm.DayNum, (COLUMN() - COLUMN($K$38) + 1) + (ROW() - ROW($K$38)) * 7 - _xlpm.StartDay + 1,IF(AND(_xlpm.DayNum > 0, _xlpm.DayNum <= DAY(EOMONTH(DATE($A41, $B41, 1), 0))), _xlpm.DayNum, "")) -> 21 | O41: =_xlfn.LET(_xlpm.StartDay, WEEKDAY(DATE($A41, $B41, 1), 1),_xlpm.DayNum, (COLUMN() - COLUMN($K$38) + 1) + (ROW() - ROW($K$38)) * 7 - _xlpm.StartDay + 1,IF(AND(_xlpm.DayNum > 0, _xlpm.DayNum <= DAY(EOMONTH(DATE($A41, $B41, 1), 0))), _xlpm.DayNum, "")) -> 22 | P41: =_xlfn.LET(_xlpm.StartDay, WEEKDAY(DATE($A41, $B41, 1), 1),_xlpm.DayNum, (COLUMN() - COLUMN($K$38) + 1) + (ROW() - ROW($K$38)) * 7 - _xlpm.StartDay + 1,IF(AND(_xlpm.DayNum > 0, _xlpm.DayNum <= DAY(EOMONTH(DATE($A41, $B41, 1), 0))), _xlpm.DayNum, "")) -> 23 | Q41: =_xlfn.LET(_xlpm.StartDay, WEEKDAY(DATE($A41, $B41, 1), 1),_xlpm.DayNum, (COLUMN() - COLUMN($K$38) + 1) + (ROW() - ROW($K$38)) * 7 - _xlpm.StartDay + 1,IF(AND(_xlpm.DayNum > 0, _xlpm.DayNum <= DAY(EOMONTH(DATE($A41, $B41, 1), 0))), _xlpm.DayNum, "")) -> 24
A42: 2027 | B42: 7 | C42: 5 | D42: 3 | E42: 2 | F42: 2 | G42: 4 | H42: 3 | I42: 2 | J42: 2 | K42: =_xlfn.LET(_xlpm.StartDay, WEEKDAY(DATE($A42, $B42, 1), 1),_xlpm.DayNum, (COLUMN() - COLUMN($K$38) + 1) + (ROW() - ROW($K$38)) * 7 - _xlpm.StartDay + 1,IF(AND(_xlpm.DayNum > 0, _xlpm.DayNum <= DAY(EOMONTH(DATE($A42, $B42, 1), 0))), _xlpm.DayNum, "")) -> 25 | L42: =_xlfn.LET(_xlpm.StartDay, WEEKDAY(DATE($A42, $B42, 1), 1),_xlpm.DayNum, (COLUMN() - COLUMN($K$38) + 1) + (ROW() - ROW($K$38)) * 7 - _xlpm.StartDay + 1,IF(AND(_xlpm.DayNum > 0, _xlpm.DayNum <= DAY(EOMONTH(DATE($A42, $B42, 1), 0))), _xlpm.DayNum, "")) -> 26 | M42: =_xlfn.LET(_xlpm.StartDay, WEEKDAY(DATE($A42, $B42, 1), 1),_xlpm.DayNum, (COLUMN() - COLUMN($K$38) + 1) + (ROW() - ROW($K$38)) * 7 - _xlpm.StartDay + 1,IF(AND(_xlpm.DayNum > 0, _xlpm.DayNum <= DAY(EOMONTH(DATE($A42, $B42, 1), 0))), _xlpm.DayNum, "")) -> 27 | N42: =_xlfn.LET(_xlpm.StartDay, WEEKDAY(DATE($A42, $B42, 1), 1),_xlpm.DayNum, (COLUMN() - COLUMN($K$38) + 1) + (ROW() - ROW($K$38)) * 7 - _xlpm.StartDay + 1,IF(AND(_xlpm.DayNum > 0, _xlpm.DayNum <= DAY(EOMONTH(DATE($A42, $B42, 1), 0))), _xlpm.DayNum, "")) -> 28 | O42: =_xlfn.LET(_xlpm.StartDay, WEEKDAY(DATE($A42, $B42, 1), 1),_xlpm.DayNum, (COLUMN() - COLUMN($K$38) + 1) + (ROW() - ROW($K$38)) * 7 - _xlpm.StartDay + 1,IF(AND(_xlpm.DayNum > 0, _xlpm.DayNum <= DAY(EOMONTH(DATE($A42, $B42, 1), 0))), _xlpm.DayNum, "")) -> 29 | P42: =_xlfn.LET(_xlpm.StartDay, WEEKDAY(DATE($A42, $B42, 1), 1),_xlpm.DayNum, (COLUMN() - COLUMN($K$38) + 1) + (ROW() - ROW($K$38)) * 7 - _xlpm.StartDay + 1,IF(AND(_xlpm.DayNum > 0, _xlpm.DayNum <= DAY(EOMONTH(DATE($A42, $B42, 1), 0))), _xlpm.DayNum, "")) -> 30 | Q42: =_xlfn.LET(_xlpm.StartDay, WEEKDAY(DATE($A42, $B42, 1), 1),_xlpm.DayNum, (COLUMN() - COLUMN($K$38) + 1) + (ROW() - ROW($K$38)) * 7 - _xlpm.StartDay + 1,IF(AND(_xlpm.DayNum > 0, _xlpm.DayNum <= DAY(EOMONTH(DATE($A42, $B42, 1), 0))), _xlpm.DayNum, "")) -> 31
A43: 2027 | B43: 7 | C43: 6 | D43: 1 | E43: 1 | F43: 1 | G43: 1 | H43: 1 | I43: 1 | J43: 1 | K43: =IF(D43<>1,"ERROR!!!","") | L43: =IF(E43<>1,"ERROR!!!","") | M43: =IF(F43<>1,"ERROR!!!","") | N43: =IF(G43<>1,"ERROR!!!","") | O43: =IF(H43<>1,"ERROR!!!","") | P43: =IF(I43<>1,"ERROR!!!","") | Q43: =IF(J43<>1,"ERROR!!!","")
A44: 2027 | B44: 8 | C44: 1 | D44: 2 | E44: 2 | F44: 2 | G44: 2 | H44: 2 | I44: 2 | J44: 3 | K44: =_xlfn.LET(_xlpm.StartDay, WEEKDAY(DATE($A44, $B44, 1), 1),_xlpm.DayNum, (COLUMN() - COLUMN($K$44) + 1) + (ROW() - ROW($K$44)) * 7 - _xlpm.StartDay + 1,IF(AND(_xlpm.DayNum > 0, _xlpm.DayNum <= DAY(EOMONTH(DATE($A44, $B44, 1), 0))), _xlpm.DayNum, "")) -> 1 | L44: =_xlfn.LET(_xlpm.StartDay, WEEKDAY(DATE($A44, $B44, 1), 1),_xlpm.DayNum, (COLUMN() - COLUMN($K$44) + 1) + (ROW() - ROW($K$44)) * 7 - _xlpm.StartDay + 1,IF(AND(_xlpm.DayNum > 0, _xlpm.DayNum <= DAY(EOMONTH(DATE($A44, $B44, 1), 0))), _xlpm.DayNum, "")) -> 2 | M44: =_xlfn.LET(_xlpm.StartDay, WEEKDAY(DATE($A44, $B44, 1), 1),_xlpm.DayNum, (COLUMN() - COLUMN($K$44) + 1) + (ROW() - ROW($K$44)) * 7 - _xlpm.StartDay + 1,IF(AND(_xlpm.DayNum > 0, _xlpm.DayNum <= DAY(EOMONTH(DATE($A44, $B44, 1), 0))), _xlpm.DayNum, "")) -> 3 | N44: =_xlfn.LET(_xlpm.StartDay, WEEKDAY(DATE($A44, $B44, 1), 1),_xlpm.DayNum, (COLUMN() - COLUMN($K$44) + 1) + (ROW() - ROW($K$44)) * 7 - _xlpm.StartDay + 1,IF(AND(_xlpm.DayNum > 0, _xlpm.DayNum <= DAY(EOMONTH(DATE($A44, $B44, 1), 0))), _xlpm.DayNum, "")) -> 4 | O44: =_xlfn.LET(_xlpm.StartDay, WEEKDAY(DATE($A44, $B44, 1), 1),_xlpm.DayNum, (COLUMN() - COLUMN($K$44) + 1) + (ROW() - ROW($K$44)) * 7 - _xlpm.StartDay + 1,IF(AND(_xlpm.DayNum > 0, _xlpm.DayNum <= DAY(EOMONTH(DATE($A44, $B44, 1), 0))), _xlpm.DayNum, "")) -> 5 | P44: =_xlfn.LET(_xlpm.StartDay, WEEKDAY(DATE($A44, $B44, 1), 1),_xlpm.DayNum, (COLUMN() - COLUMN($K$44) + 1) + (ROW() - ROW($K$44)) * 7 - _xlpm.StartDay + 1,IF(AND(_xlpm.DayNum > 0, _xlpm.DayNum <= DAY(EOMONTH(DATE($A44, $B44, 1), 0))), _xlpm.DayNum, "")) -> 6 | Q44: =_xlfn.LET(_xlpm.StartDay, WEEKDAY(DATE($A44, $B44, 1), 1),_xlpm.DayNum, (COLUMN() - COLUMN($K$44) + 1) + (ROW() - ROW($K$44)) * 7 - _xlpm.StartDay + 1,IF(AND(_xlpm.DayNum > 0, _xlpm.DayNum <= DAY(EOMONTH(DATE($A44, $B44, 1), 0))), _xlpm.DayNum, "")) -> 7
A45: 2027 | B45: 8 | C45: 2 | D45: 2 | E45: 3 | F45: 2 | G45: 3 | H45: 2 | I45: 4 | J45: 3 | K45: =_xlfn.LET(_xlpm.StartDay, WEEKDAY(DATE($A45, $B45, 1), 1),_xlpm.DayNum, (COLUMN() - COLUMN($K$44) + 1) + (ROW() - ROW($K$44)) * 7 - _xlpm.StartDay + 1,IF(AND(_xlpm.DayNum > 0, _xlpm.DayNum <= DAY(EOMONTH(DATE($A45, $B45, 1), 0))), _xlpm.DayNum, "")) -> 8 | L45: =_xlfn.LET(_xlpm.StartDay, WEEKDAY(DATE($A45, $B45, 1), 1),_xlpm.DayNum, (COLUMN() - COLUMN($K$44) + 1) + (ROW() - ROW($K$44)) * 7 - _xlpm.StartDay + 1,IF(AND(_xlpm.DayNum > 0, _xlpm.DayNum <= DAY(EOMONTH(DATE($A45, $B45, 1), 0))), _xlpm.DayNum, "")) -> 9 | M45: =_xlfn.LET(_xlpm.StartDay, WEEKDAY(DATE($A45, $B45, 1), 1),_xlpm.DayNum, (COLUMN() - COLUMN($K$44) + 1) + (ROW() - ROW($K$44)) * 7 - _xlpm.StartDay + 1,IF(AND(_xlpm.DayNum > 0, _xlpm.DayNum <= DAY(EOMONTH(DATE($A45, $B45, 1), 0))), _xlpm.DayNum, "")) -> 10 | N45: =_xlfn.LET(_xlpm.StartDay, WEEKDAY(DATE($A45, $B45, 1), 1),_xlpm.DayNum, (COLUMN() - COLUMN($K$44) + 1) + (ROW() - ROW($K$44)) * 7 - _xlpm.StartDay + 1,IF(AND(_xlpm.DayNum > 0, _xlpm.DayNum <= DAY(EOMONTH(DATE($A45, $B45, 1), 0))), _xlpm.DayNum, "")) -> 11 | O45: =_xlfn.LET(_xlpm.StartDay, WEEKDAY(DATE($A45, $B45, 1), 1),_xlpm.DayNum, (COLUMN() - COLUMN($K$44) + 1) + (ROW() - ROW($K$44)) * 7 - _xlpm.StartDay + 1,IF(AND(_xlpm.DayNum > 0, _xlpm.DayNum <= DAY(EOMONTH(DATE($A45, $B45, 1), 0))), _xlpm.DayNum, "")) -> 12 | P45: =_xlfn.LET(_xlpm.StartDay, WEEKDAY(DATE($A45, $B45, 1), 1),_xlpm.DayNum, (COLUMN() - COLUMN($K$44) + 1) + (ROW() - ROW($K$44)) * 7 - _xlpm.StartDay + 1,IF(AND(_xlpm.DayNum > 0, _xlpm.DayNum <= DAY(EOMONTH(DATE($A45, $B45, 1), 0))), _xlpm.DayNum, "")) -> 13 | Q45: =_xlfn.LET(_xlpm.StartDay, WEEKDAY(DATE($A45, $B45, 1), 1),_xlpm.DayNum, (COLUMN() - COLUMN($K$44) + 1) + (ROW() - ROW($K$44)) * 7 - _xlpm.StartDay + 1,IF(AND(_xlpm.DayNum > 0, _xlpm.DayNum <= DAY(EOMONTH(DATE($A45, $B45, 1), 0))), _xlpm.DayNum, "")) -> 14
A46: 2027 | B46: 8 | C46: 3 | D46: 3 | E46: 4 | F46: 2 | G46: 4 | H46: 3 | I46: 4 | J46: 3 | K46: =_xlfn.LET(_xlpm.StartDay, WEEKDAY(DATE($A46, $B46, 1), 1),_xlpm.DayNum, (COLUMN() - COLUMN($K$44) + 1) + (ROW() - ROW($K$44)) * 7 - _xlpm.StartDay + 1,IF(AND(_xlpm.DayNum > 0, _xlpm.DayNum <= DAY(EOMONTH(DATE($A46, $B46, 1), 0))), _xlpm.DayNum, "")) -> 15 | L46: =_xlfn.LET(_xlpm.StartDay, WEEKDAY(DATE($A46, $B46, 1), 1),_xlpm.DayNum, (COLUMN() - COLUMN($K$44) + 1) + (ROW() - ROW($K$44)) * 7 - _xlpm.StartDay + 1,IF(AND(_xlpm.DayNum > 0, _xlpm.DayNum <= DAY(EOMONTH(DATE($A46, $B46, 1), 0))), _xlpm.DayNum, "")) -> 16 | M46: =_xlfn.LET(_xlpm.StartDay, WEEKDAY(DATE($A46, $B46, 1), 1),_xlpm.DayNum, (COLUMN() - COLUMN($K$44) + 1) + (ROW() - ROW($K$44)) * 7 - _xlpm.StartDay + 1,IF(AND(_xlpm.DayNum > 0, _xlpm.DayNum <= DAY(EOMONTH(DATE($A46, $B46, 1), 0))), _xlpm.DayNum, "")) -> 17 | N46: =_xlfn.LET(_xlpm.StartDay, WEEKDAY(DATE($A46, $B46, 1), 1),_xlpm.DayNum, (COLUMN() - COLUMN($K$44) + 1) + (ROW() - ROW($K$44)) * 7 - _xlpm.StartDay + 1,IF(AND(_xlpm.DayNum > 0, _xlpm.DayNum <= DAY(EOMONTH(DATE($A46, $B46, 1), 0))), _xlpm.DayNum, "")) -> 18 | O46: =_xlfn.LET(_xlpm.StartDay, WEEKDAY(DATE($A46, $B46, 1), 1),_xlpm.DayNum, (COLUMN() - COLUMN($K$44) + 1) + (ROW() - ROW($K$44)) * 7 - _xlpm.StartDay + 1,IF(AND(_xlpm.DayNum > 0, _xlpm.DayNum <= DAY(EOMONTH(DATE($A46, $B46, 1), 0))), _xlpm.DayNum, "")) -> 19 | P46: =_xlfn.LET(_xlpm.StartDay, WEEKDAY(DATE($A46, $B46, 1), 1),_xlpm.DayNum, (COLUMN() - COLUMN($K$44) + 1) + (ROW() - ROW($K$44)) * 7 - _xlpm.StartDay + 1,IF(AND(_xlpm.DayNum > 0, _xlpm.DayNum <= DAY(EOMONTH(DATE($A46, $B46, 1), 0))), _xlpm.DayNum, "")) -> 20 | Q46: =_xlfn.LET(_xlpm.StartDay, WEEKDAY(DATE($A46, $B46, 1), 1),_xlpm.DayNum, (COLUMN() - COLUMN($K$44) + 1) + (ROW() - ROW($K$44)) * 7 - _xlpm.StartDay + 1,IF(AND(_xlpm.DayNum > 0, _xlpm.DayNum <= DAY(EOMONTH(DATE($A46, $B46, 1), 0))), _xlpm.DayNum, "")) -> 21
A47: 2027 | B47: 8 | C47: 4 | D47: 3 | E47: 2 | F47: 3 | G47: 2 | H47: 2 | I47: 2 | J47: 2 | K47: =_xlfn.LET(_xlpm.StartDay, WEEKDAY(DATE($A47, $B47, 1), 1),_xlpm.DayNum, (COLUMN() - COLUMN($K$44) + 1) + (ROW() - ROW($K$44)) * 7 - _xlpm.StartDay + 1,IF(AND(_xlpm.DayNum > 0, _xlpm.DayNum <= DAY(EOMONTH(DATE($A47, $B47, 1), 0))), _xlpm.DayNum, "")) -> 22 | L47: =_xlfn.LET(_xlpm.StartDay, WEEKDAY(DATE($A47, $B47, 1), 1),_xlpm.DayNum, (COLUMN() - COLUMN($K$44) + 1) + (ROW() - ROW($K$44)) * 7 - _xlpm.StartDay + 1,IF(AND(_xlpm.DayNum > 0, _xlpm.DayNum <= DAY(EOMONTH(DATE($A47, $B47, 1), 0))), _xlpm.DayNum, "")) -> 23 | M47: =_xlfn.LET(_xlpm.StartDay, WEEKDAY(DATE($A47, $B47, 1), 1),_xlpm.DayNum, (COLUMN() - COLUMN($K$44) + 1) + (ROW() - ROW($K$44)) * 7 - _xlpm.StartDay + 1,IF(AND(_xlpm.DayNum > 0, _xlpm.DayNum <= DAY(EOMONTH(DATE($A47, $B47, 1), 0))), _xlpm.DayNum, "")) -> 24 | N47: =_xlfn.LET(_xlpm.StartDay, WEEKDAY(DATE($A47, $B47, 1), 1),_xlpm.DayNum, (COLUMN() - COLUMN($K$44) + 1) + (ROW() - ROW($K$44)) * 7 - _xlpm.StartDay + 1,IF(AND(_xlpm.DayNum > 0, _xlpm.DayNum <= DAY(EOMONTH(DATE($A47, $B47, 1), 0))), _xlpm.DayNum, "")) -> 25 | O47: =_xlfn.LET(_xlpm.StartDay, WEEKDAY(DATE($A47, $B47, 1), 1),_xlpm.DayNum, (COLUMN() - COLUMN($K$44) + 1) + (ROW() - ROW($K$44)) * 7 - _xlpm.StartDay + 1,IF(AND(_xlpm.DayNum > 0, _xlpm.DayNum <= DAY(EOMONTH(DATE($A47, $B47, 1), 0))), _xlpm.DayNum, "")) -> 26 | P47: =_xlfn.LET(_xlpm.StartDay, WEEKDAY(DATE($A47, $B47, 1), 1),_xlpm.DayNum, (COLUMN() - COLUMN($K$44) + 1) + (ROW() - ROW($K$44)) * 7 - _xlpm.StartDay + 1,IF(AND(_xlpm.DayNum > 0, _xlpm.DayNum <= DAY(EOMONTH(DATE($A47, $B47, 1), 0))), _xlpm.DayNum, "")) -> 27 | Q47: =_xlfn.LET(_xlpm.StartDay, WEEKDAY(DATE($A47, $B47, 1), 1),_xlpm.DayNum, (COLUMN() - COLUMN($K$44) + 1) + (ROW() - ROW($K$44)) * 7 - _xlpm.StartDay + 1,IF(AND(_xlpm.DayNum > 0, _xlpm.DayNum <= DAY(EOMONTH(DATE($A47, $B47, 1), 0))), _xlpm.DayNum, "")) -> 28
A48: 2027 | B48: 8 | C48: 5 | D48: 2 | E48: 3 | F48: 3 | G48: 1 | H48: 1 | I48: 1 | J48: 1 | K48: =_xlfn.LET(_xlpm.StartDay, WEEKDAY(DATE($A48, $B48, 1), 1),_xlpm.DayNum, (COLUMN() - COLUMN($K$44) + 1) + (ROW() - ROW($K$44)) * 7 - _xlpm.StartDay + 1,IF(AND(_xlpm.DayNum > 0, _xlpm.DayNum <= DAY(EOMONTH(DATE($A48, $B48, 1), 0))), _xlpm.DayNum, "")) -> 29 | L48: =_xlfn.LET(_xlpm.StartDay, WEEKDAY(DATE($A48, $B48, 1), 1),_xlpm.DayNum, (COLUMN() - COLUMN($K$44) + 1) + (ROW() - ROW($K$44)) * 7 - _xlpm.StartDay + 1,IF(AND(_xlpm.DayNum > 0, _xlpm.DayNum <= DAY(EOMONTH(DATE($A48, $B48, 1), 0))), _xlpm.DayNum, "")) -> 30 | M48: =_xlfn.LET(_xlpm.StartDay, WEEKDAY(DATE($A48, $B48, 1), 1),_xlpm.DayNum, (COLUMN() - COLUMN($K$44) + 1) + (ROW() - ROW($K$44)) * 7 - _xlpm.StartDay + 1,IF(AND(_xlpm.DayNum > 0, _xlpm.DayNum <= DAY(EOMONTH(DATE($A48, $B48, 1), 0))), _xlpm.DayNum, "")) -> 31 | N48: =IF(G48<>1,"ERROR!!!","") | O48: =IF(H48<>1,"ERROR!!!","") | P48: =IF(I48<>1,"ERROR!!!","") | Q48: =IF(J48<>1,"ERROR!!!","")
A49: 2027 | B49: 8 | C49: 6 | D49: 1 | E49: 1 | F49: 1 | G49: 1 | H49: 1 | I49: 1 | J49: 1 | K49: =IF(D49<>1,"ERROR!!!","") | L49: =IF(E49<>1,"ERROR!!!","") | M49: =IF(F49<>1,"ERROR!!!","") | N49: =IF(G49<>1,"ERROR!!!","") | O49: =IF(H49<>1,"ERROR!!!","") | P49: =IF(I49<>1,"ERROR!!!","") | Q49: =IF(J49<>1,"ERROR!!!","")
A50: 2027 | B50: 9 | C50: 1 | D50: 1 | E50: 1 | F50: 1 | G50: 2 | H50: 2 | I50: 4 | J50: 4 | K50: =IF(D50<>1,"ERROR!!!","") | L50: =IF(E50<>1,"ERROR!!!","") | M50: =IF(F50<>1,"ERROR!!!","") | N50: =_xlfn.LET(_xlpm.StartDay, WEEKDAY(DATE($A50, $B50, 1), 1),_xlpm.DayNum, (COLUMN() - COLUMN($K$50) + 1) + (ROW() - ROW($K$50)) * 7 - _xlpm.StartDay + 1,IF(AND(_xlpm.DayNum > 0, _xlpm.DayNum <= DAY(EOMONTH(DATE($A50, $B50, 1), 0))), _xlpm.DayNum, "")) -> 1 | O50: =_xlfn.LET(_xlpm.StartDay, WEEKDAY(DATE($A50, $B50, 1), 1),_xlpm.DayNum, (COLUMN() - COLUMN($K$50) + 1) + (ROW() - ROW($K$50)) * 7 - _xlpm.StartDay + 1,IF(AND(_xlpm.DayNum > 0, _xlpm.DayNum <= DAY(EOMONTH(DATE($A50, $B50, 1), 0))), _xlpm.DayNum, "")) -> 2 | P50: =_xlfn.LET(_xlpm.StartDay, WEEKDAY(DATE($A50, $B50, 1), 1),_xlpm.DayNum, (COLUMN() - COLUMN($K$50) + 1) + (ROW() - ROW($K$50)) * 7 - _xlpm.StartDay + 1,IF(AND(_xlpm.DayNum > 0, _xlpm.DayNum <= DAY(EOMONTH(DATE($A50, $B50, 1), 0))), _xlpm.DayNum, "")) -> 3 | Q50: =_xlfn.LET(_xlpm.StartDay, WEEKDAY(DATE($A50, $B50, 1), 1),_xlpm.DayNum, (COLUMN() - COLUMN($K$50) + 1) + (ROW() - ROW($K$50)) * 7 - _xlpm.StartDay + 1,IF(AND(_xlpm.DayNum > 0, _xlpm.DayNum <= DAY(EOMONTH(DATE($A50, $B50, 1), 0))), _xlpm.DayNum, "")) -> 4
A51: 2027 | B51: 9 | C51: 2 | D51: 2 | E51: 3 | F51: 3 | G51: 4 | H51: 3 | I51: 2 | J51: 4 | K51: =_xlfn.LET(_xlpm.StartDay, WEEKDAY(DATE($A51, $B51, 1), 1),_xlpm.DayNum, (COLUMN() - COLUMN($K$50) + 1) + (ROW() - ROW($K$50)) * 7 - _xlpm.StartDay + 1,IF(AND(_xlpm.DayNum > 0, _xlpm.DayNum <= DAY(EOMONTH(DATE($A51, $B51, 1), 0))), _xlpm.DayNum, "")) -> 5 | L51: =_xlfn.LET(_xlpm.StartDay, WEEKDAY(DATE($A51, $B51, 1), 1),_xlpm.DayNum, (COLUMN() - COLUMN($K$50) + 1) + (ROW() - ROW($K$50)) * 7 - _xlpm.StartDay + 1,IF(AND(_xlpm.DayNum > 0, _xlpm.DayNum <= DAY(EOMONTH(DATE($A51, $B51, 1), 0))), _xlpm.DayNum, "")) -> 6 | M51: =_xlfn.LET(_xlpm.StartDay, WEEKDAY(DATE($A51, $B51, 1), 1),_xlpm.DayNum, (COLUMN() - COLUMN($K$50) + 1) + (ROW() - ROW($K$50)) * 7 - _xlpm.StartDay + 1,IF(AND(_xlpm.DayNum > 0, _xlpm.DayNum <= DAY(EOMONTH(DATE($A51, $B51, 1), 0))), _xlpm.DayNum, "")) -> 7 | N51: =_xlfn.LET(_xlpm.StartDay, WEEKDAY(DATE($A51, $B51, 1), 1),_xlpm.DayNum, (COLUMN() - COLUMN($K$50) + 1) + (ROW() - ROW($K$50)) * 7 - _xlpm.StartDay + 1,IF(AND(_xlpm.DayNum > 0, _xlpm.DayNum <= DAY(EOMONTH(DATE($A51, $B51, 1), 0))), _xlpm.DayNum, "")) -> 8 | O51: =_xlfn.LET(_xlpm.StartDay, WEEKDAY(DATE($A51, $B51, 1), 1),_xlpm.DayNum, (COLUMN() - COLUMN($K$50) + 1) + (ROW() - ROW($K$50)) * 7 - _xlpm.StartDay + 1,IF(AND(_xlpm.DayNum > 0, _xlpm.DayNum <= DAY(EOMONTH(DATE($A51, $B51, 1), 0))), _xlpm.DayNum, "")) -> 9 | P51: =_xlfn.LET(_xlpm.StartDay, WEEKDAY(DATE($A51, $B51, 1), 1),_xlpm.DayNum, (COLUMN() - COLUMN($K$50) + 1) + (ROW() - ROW($K$50)) * 7 - _xlpm.StartDay + 1,IF(AND(_xlpm.DayNum > 0, _xlpm.DayNum <= DAY(EOMONTH(DATE($A51, $B51, 1), 0))), _xlpm.DayNum, "")) -> 10 | Q51: =_xlfn.LET(_xlpm.StartDay, WEEKDAY(DATE($A51, $B51, 1), 1),_xlpm.DayNum, (COLUMN() - COLUMN($K$50) + 1) + (ROW() - ROW($K$50)) * 7 - _xlpm.StartDay + 1,IF(AND(_xlpm.DayNum > 0, _xlpm.DayNum <= DAY(EOMONTH(DATE($A51, $B51, 1), 0))), _xlpm.DayNum, "")) -> 11
A52: 2027 | B52: 9 | C52: 3 | D52: 3 | E52: 3 | F52: 2 | G52: 2 | H52: 2 | I52: 2 | J52: 3 | K52: =_xlfn.LET(_xlpm.StartDay, WEEKDAY(DATE($A52, $B52, 1), 1),_xlpm.DayNum, (COLUMN() - COLUMN($K$50) + 1) + (ROW() - ROW($K$50)) * 7 - _xlpm.StartDay + 1,IF(AND(_xlpm.DayNum > 0, _xlpm.DayNum <= DAY(EOMONTH(DATE($A52, $B52, 1), 0))), _xlpm.DayNum, "")) -> 12 | L52: =_xlfn.LET(_xlpm.StartDay, WEEKDAY(DATE($A52, $B52, 1), 1),_xlpm.DayNum, (COLUMN() - COLUMN($K$50) + 1) + (ROW() - ROW($K$50)) * 7 - _xlpm.StartDay + 1,IF(AND(_xlpm.DayNum > 0, _xlpm.DayNum <= DAY(EOMONTH(DATE($A52, $B52, 1), 0))), _xlpm.DayNum, "")) -> 13 | M52: =_xlfn.LET(_xlpm.StartDay, WEEKDAY(DATE($A52, $B52, 1), 1),_xlpm.DayNum, (COLUMN() - COLUMN($K$50) + 1) + (ROW() - ROW($K$50)) * 7 - _xlpm.StartDay + 1,IF(AND(_xlpm.DayNum > 0, _xlpm.DayNum <= DAY(EOMONTH(DATE($A52, $B52, 1), 0))), _xlpm.DayNum, "")) -> 14 | N52: =_xlfn.LET(_xlpm.StartDay, WEEKDAY(DATE($A52, $B52, 1), 1),_xlpm.DayNum, (COLUMN() - COLUMN($K$50) + 1) + (ROW() - ROW($K$50)) * 7 - _xlpm.StartDay + 1,IF(AND(_xlpm.DayNum > 0, _xlpm.DayNum <= DAY(EOMONTH(DATE($A52, $B52, 1), 0))), _xlpm.DayNum, "")) -> 15 | O52: =_xlfn.LET(_xlpm.StartDay, WEEKDAY(DATE($A52, $B52, 1), 1),_xlpm.DayNum, (COLUMN() - COLUMN($K$50) + 1) + (ROW() - ROW($K$50)) * 7 - _xlpm.StartDay + 1,IF(AND(_xlpm.DayNum > 0, _xlpm.DayNum <= DAY(EOMONTH(DATE($A52, $B52, 1), 0))), _xlpm.DayNum, "")) -> 16 | P52: =_xlfn.LET(_xlpm.StartDay, WEEKDAY(DATE($A52, $B52, 1), 1),_xlpm.DayNum, (COLUMN() - COLUMN($K$50) + 1) + (ROW() - ROW($K$50)) * 7 - _xlpm.StartDay + 1,IF(AND(_xlpm.DayNum > 0, _xlpm.DayNum <= DAY(EOMONTH(DATE($A52, $B52, 1), 0))), _xlpm.DayNum, "")) -> 17 | Q52: =_xlfn.LET(_xlpm.StartDay, WEEKDAY(DATE($A52, $B52, 1), 1),_xlpm.DayNum, (COLUMN() - COLUMN($K$50) + 1) + (ROW() - ROW($K$50)) * 7 - _xlpm.StartDay + 1,IF(AND(_xlpm.DayNum > 0, _xlpm.DayNum <= DAY(EOMONTH(DATE($A52, $B52, 1), 0))), _xlpm.DayNum, "")) -> 18
A53: 2027 | B53: 9 | C53: 4 | D53: 3 | E53: 3 | F53: 3 | G53: 3 | H53: 2 | I53: 2 | J53: 2 | K53: =_xlfn.LET(_xlpm.StartDay, WEEKDAY(DATE($A53, $B53, 1), 1),_xlpm.DayNum, (COLUMN() - COLUMN($K$50) + 1) + (ROW() - ROW($K$50)) * 7 - _xlpm.StartDay + 1,IF(AND(_xlpm.DayNum > 0, _xlpm.DayNum <= DAY(EOMONTH(DATE($A53, $B53, 1), 0))), _xlpm.DayNum, "")) -> 19 | L53: =_xlfn.LET(_xlpm.StartDay, WEEKDAY(DATE($A53, $B53, 1), 1),_xlpm.DayNum, (COLUMN() - COLUMN($K$50) + 1) + (ROW() - ROW($K$50)) * 7 - _xlpm.StartDay + 1,IF(AND(_xlpm.DayNum > 0, _xlpm.DayNum <= DAY(EOMONTH(DATE($A53, $B53, 1), 0))), _xlpm.DayNum, "")) -> 20 | M53: =_xlfn.LET(_xlpm.StartDay, WEEKDAY(DATE($A53, $B53, 1), 1),_xlpm.DayNum, (COLUMN() - COLUMN($K$50) + 1) + (ROW() - ROW($K$50)) * 7 - _xlpm.StartDay + 1,IF(AND(_xlpm.DayNum > 0, _xlpm.DayNum <= DAY(EOMONTH(DATE($A53, $B53, 1), 0))), _xlpm.DayNum, "")) -> 21 | N53: =_xlfn.LET(_xlpm.StartDay, WEEKDAY(DATE($A53, $B53, 1), 1),_xlpm.DayNum, (COLUMN() - COLUMN($K$50) + 1) + (ROW() - ROW($K$50)) * 7 - _xlpm.StartDay + 1,IF(AND(_xlpm.DayNum > 0, _xlpm.DayNum <= DAY(EOMONTH(DATE($A53, $B53, 1), 0))), _xlpm.DayNum, "")) -> 22 | O53: =_xlfn.LET(_xlpm.StartDay, WEEKDAY(DATE($A53, $B53, 1), 1),_xlpm.DayNum, (COLUMN() - COLUMN($K$50) + 1) + (ROW() - ROW($K$50)) * 7 - _xlpm.StartDay + 1,IF(AND(_xlpm.DayNum > 0, _xlpm.DayNum <= DAY(EOMONTH(DATE($A53, $B53, 1), 0))), _xlpm.DayNum, "")) -> 23 | P53: =_xlfn.LET(_xlpm.StartDay, WEEKDAY(DATE($A53, $B53, 1), 1),_xlpm.DayNum, (COLUMN() - COLUMN($K$50) + 1) + (ROW() - ROW($K$50)) * 7 - _xlpm.StartDay + 1,IF(AND(_xlpm.DayNum > 0, _xlpm.DayNum <= DAY(EOMONTH(DATE($A53, $B53, 1), 0))), _xlpm.DayNum, "")) -> 24 | Q53: =_xlfn.LET(_xlpm.StartDay, WEEKDAY(DATE($A53, $B53, 1), 1),_xlpm.DayNum, (COLUMN() - COLUMN($K$50) + 1) + (ROW() - ROW($K$50)) * 7 - _xlpm.StartDay + 1,IF(AND(_xlpm.DayNum > 0, _xlpm.DayNum <= DAY(EOMONTH(DATE($A53, $B53, 1), 0))), _xlpm.DayNum, "")) -> 25
A54: 2027 | B54: 9 | C54: 5 | D54: 3 | E54: 3 | F54: 2 | G54: 2 | H54: 2 | I54: 1 | J54: 1 | K54: =_xlfn.LET(_xlpm.StartDay, WEEKDAY(DATE($A54, $B54, 1), 1),_xlpm.DayNum, (COLUMN() - COLUMN($K$50) + 1) + (ROW() - ROW($K$50)) * 7 - _xlpm.StartDay + 1,IF(AND(_xlpm.DayNum > 0, _xlpm.DayNum <= DAY(EOMONTH(DATE($A54, $B54, 1), 0))), _xlpm.DayNum, "")) -> 26 | L54: =_xlfn.LET(_xlpm.StartDay, WEEKDAY(DATE($A54, $B54, 1), 1),_xlpm.DayNum, (COLUMN() - COLUMN($K$50) + 1) + (ROW() - ROW($K$50)) * 7 - _xlpm.StartDay + 1,IF(AND(_xlpm.DayNum > 0, _xlpm.DayNum <= DAY(EOMONTH(DATE($A54, $B54, 1), 0))), _xlpm.DayNum, "")) -> 27 | M54: =_xlfn.LET(_xlpm.StartDay, WEEKDAY(DATE($A54, $B54, 1), 1),_xlpm.DayNum, (COLUMN() - COLUMN($K$50) + 1) + (ROW() - ROW($K$50)) * 7 - _xlpm.StartDay + 1,IF(AND(_xlpm.DayNum > 0, _xlpm.DayNum <= DAY(EOMONTH(DATE($A54, $B54, 1), 0))), _xlpm.DayNum, "")) -> 28 | N54: =_xlfn.LET(_xlpm.StartDay, WEEKDAY(DATE($A54, $B54, 1), 1),_xlpm.DayNum, (COLUMN() - COLUMN($K$50) + 1) + (ROW() - ROW($K$50)) * 7 - _xlpm.StartDay + 1,IF(AND(_xlpm.DayNum > 0, _xlpm.DayNum <= DAY(EOMONTH(DATE($A54, $B54, 1), 0))), _xlpm.DayNum, "")) -> 29 | O54: =_xlfn.LET(_xlpm.StartDay, WEEKDAY(DATE($A54, $B54, 1), 1),_xlpm.DayNum, (COLUMN() - COLUMN($K$50) + 1) + (ROW() - ROW($K$50)) * 7 - _xlpm.StartDay + 1,IF(AND(_xlpm.DayNum > 0, _xlpm.DayNum <= DAY(EOMONTH(DATE($A54, $B54, 1), 0))), _xlpm.DayNum, "")) -> 30 | P54: =IF(I54<>1,"ERROR!!!","") | Q54: =IF(J54<>1,"ERROR!!!","")
A55: 2027 | B55: 9 | C55: 6 | D55: 1 | E55: 1 | F55: 1 | G55: 1 | H55: 1 | I55: 1 | J55: 1 | K55: =IF(D55<>1,"ERROR!!!","") | L55: =IF(E55<>1,"ERROR!!!","") | M55: =IF(F55<>1,"ERROR!!!","") | N55: =IF(G55<>1,"ERROR!!!","") | O55: =IF(H55<>1,"ERROR!!!","") | P55: =IF(I55<>1,"ERROR!!!","") | Q55: =IF(J55<>1,"ERROR!!!","")
A56: 2027 | B56: 10 | C56: 1 | D56: 1 | E56: 1 | F56: 1 | G56: 1 | H56: 1 | I56: 2 | J56: 2 | K56: =IF(D56<>1,"ERROR!!!","") | L56: =IF(E56<>1,"ERROR!!!","") | M56: =IF(F56<>1,"ERROR!!!","") | N56: =IF(G56<>1,"ERROR!!!","") | O56: =IF(H56<>1,"ERROR!!!","") | P56: =_xlfn.LET(_xlpm.StartDay, WEEKDAY(DATE($A56, $B56, 1), 1),_xlpm.DayNum, (COLUMN() - COLUMN($K$56) + 1) + (ROW() - ROW($K$56)) * 7 - _xlpm.StartDay + 1,IF(AND(_xlpm.DayNum > 0, _xlpm.DayNum <= DAY(EOMONTH(DATE($A56, $B56, 1), 0))), _xlpm.DayNum, "")) -> 1 | Q56: =_xlfn.LET(_xlpm.StartDay, WEEKDAY(DATE($A56, $B56, 1), 1),_xlpm.DayNum, (COLUMN() - COLUMN($K$56) + 1) + (ROW() - ROW($K$56)) * 7 - _xlpm.StartDay + 1,IF(AND(_xlpm.DayNum > 0, _xlpm.DayNum <= DAY(EOMONTH(DATE($A56, $B56, 1), 0))), _xlpm.DayNum, "")) -> 2
A57: 2027 | B57: 10 | C57: 2 | D57: 2 | E57: 3 | F57: 3 | G57: 4 | H57: 2 | I57: 2 | J57: 2 | K57: =_xlfn.LET(_xlpm.StartDay, WEEKDAY(DATE($A57, $B57, 1), 1),_xlpm.DayNum, (COLUMN() - COLUMN($K$56) + 1) + (ROW() - ROW($K$56)) * 7 - _xlpm.StartDay + 1,IF(AND(_xlpm.DayNum > 0, _xlpm.DayNum <= DAY(EOMONTH(DATE($A57, $B57, 1), 0))), _xlpm.DayNum, "")) -> 3 | L57: =_xlfn.LET(_xlpm.StartDay, WEEKDAY(DATE($A57, $B57, 1), 1),_xlpm.DayNum, (COLUMN() - COLUMN($K$56) + 1) + (ROW() - ROW($K$56)) * 7 - _xlpm.StartDay + 1,IF(AND(_xlpm.DayNum > 0, _xlpm.DayNum <= DAY(EOMONTH(DATE($A57, $B57, 1), 0))), _xlpm.DayNum, "")) -> 4 | M57: =_xlfn.LET(_xlpm.StartDay, WEEKDAY(DATE($A57, $B57, 1), 1),_xlpm.DayNum, (COLUMN() - COLUMN($K$56) + 1) + (ROW() - ROW($K$56)) * 7 - _xlpm.StartDay + 1,IF(AND(_xlpm.DayNum > 0, _xlpm.DayNum <= DAY(EOMONTH(DATE($A57, $B57, 1), 0))), _xlpm.DayNum, "")) -> 5 | N57: =_xlfn.LET(_xlpm.StartDay, WEEKDAY(DATE($A57, $B57, 1), 1),_xlpm.DayNum, (COLUMN() - COLUMN($K$56) + 1) + (ROW() - ROW($K$56)) * 7 - _xlpm.StartDay + 1,IF(AND(_xlpm.DayNum > 0, _xlpm.DayNum <= DAY(EOMONTH(DATE($A57, $B57, 1), 0))), _xlpm.DayNum, "")) -> 6 | O57: =_xlfn.LET(_xlpm.StartDay, WEEKDAY(DATE($A57, $B57, 1), 1),_xlpm.DayNum, (COLUMN() - COLUMN($K$56) + 1) + (ROW() - ROW($K$56)) * 7 - _xlpm.StartDay + 1,IF(AND(_xlpm.DayNum > 0, _xlpm.DayNum <= DAY(EOMONTH(DATE($A57, $B57, 1), 0))), _xlpm.DayNum, "")) -> 7 | P57: =_xlfn.LET(_xlpm.StartDay, WEEKDAY(DATE($A57, $B57, 1), 1),_xlpm.DayNum, (COLUMN() - COLUMN($K$56) + 1) + (ROW() - ROW($K$56)) * 7 - _xlpm.StartDay + 1,IF(AND(_xlpm.DayNum > 0, _xlpm.DayNum <= DAY(EOMONTH(DATE($A57, $B57, 1), 0))), _xlpm.DayNum, "")) -> 8 | Q57: =_xlfn.LET(_xlpm.StartDay, WEEKDAY(DATE($A57, $B57, 1), 1),_xlpm.DayNum, (COLUMN() - COLUMN($K$56) + 1) + (ROW() - ROW($K$56)) * 7 - _xlpm.StartDay + 1,IF(AND(_xlpm.DayNum > 0, _xlpm.DayNum <= DAY(EOMONTH(DATE($A57, $B57, 1), 0))), _xlpm.DayNum, "")) -> 9
A58: 2027 | B58: 10 | C58: 3 | D58: 3 | E58: 3 | F58: 2 | G58: 3 | H58: 2 | I58: 4 | J58: 3 | K58: =_xlfn.LET(_xlpm.StartDay, WEEKDAY(DATE($A58, $B58, 1), 1),_xlpm.DayNum, (COLUMN() - COLUMN($K$56) + 1) + (ROW() - ROW($K$56)) * 7 - _xlpm.StartDay + 1,IF(AND(_xlpm.DayNum > 0, _xlpm.DayNum <= DAY(EOMONTH(DATE($A58, $B58, 1), 0))), _xlpm.DayNum, "")) -> 10 | L58: =_xlfn.LET(_xlpm.StartDay, WEEKDAY(DATE($A58, $B58, 1), 1),_xlpm.DayNum, (COLUMN() - COLUMN($K$56) + 1) + (ROW() - ROW($K$56)) * 7 - _xlpm.StartDay + 1,IF(AND(_xlpm.DayNum > 0, _xlpm.DayNum <= DAY(EOMONTH(DATE($A58, $B58, 1), 0))), _xlpm.DayNum, "")) -> 11 | M58: =_xlfn.LET(_xlpm.StartDay, WEEKDAY(DATE($A58, $B58, 1), 1),_xlpm.DayNum, (COLUMN() - COLUMN($K$56) + 1) + (ROW() - ROW($K$56)) * 7 - _xlpm.StartDay + 1,IF(AND(_xlpm.DayNum > 0, _xlpm.DayNum <= DAY(EOMONTH(DATE($A58, $B58, 1), 0))), _xlpm.DayNum, "")) -> 12 | N58: =_xlfn.LET(_xlpm.StartDay, WEEKDAY(DATE($A58, $B58, 1), 1),_xlpm.DayNum, (COLUMN() - COLUMN($K$56) + 1) + (ROW() - ROW($K$56)) * 7 - _xlpm.StartDay + 1,IF(AND(_xlpm.DayNum > 0, _xlpm.DayNum <= DAY(EOMONTH(DATE($A58, $B58, 1), 0))), _xlpm.DayNum, "")) -> 13 | O58: =_xlfn.LET(_xlpm.StartDay, WEEKDAY(DATE($A58, $B58, 1), 1),_xlpm.DayNum, (COLUMN() - COLUMN($K$56) + 1) + (ROW() - ROW($K$56)) * 7 - _xlpm.StartDay + 1,IF(AND(_xlpm.DayNum > 0, _xlpm.DayNum <= DAY(EOMONTH(DATE($A58, $B58, 1), 0))), _xlpm.DayNum, "")) -> 14 | P58: =_xlfn.LET(_xlpm.StartDay, WEEKDAY(DATE($A58, $B58, 1), 1),_xlpm.DayNum, (COLUMN() - COLUMN($K$56) + 1) + (ROW() - ROW($K$56)) * 7 - _xlpm.StartDay + 1,IF(AND(_xlpm.DayNum > 0, _xlpm.DayNum <= DAY(EOMONTH(DATE($A58, $B58, 1), 0))), _xlpm.DayNum, "")) -> 15 | Q58: =_xlfn.LET(_xlpm.StartDay, WEEKDAY(DATE($A58, $B58, 1), 1),_xlpm.DayNum, (COLUMN() - COLUMN($K$56) + 1) + (ROW() - ROW($K$56)) * 7 - _xlpm.StartDay + 1,IF(AND(_xlpm.DayNum > 0, _xlpm.DayNum <= DAY(EOMONTH(DATE($A58, $B58, 1), 0))), _xlpm.DayNum, "")) -> 16
A59: 2027 | B59: 10 | C59: 4 | D59: 3 | E59: 3 | F59: 3 | G59: 3 | H59: 4 | I59: 3 | J59: 4 | K59: =_xlfn.LET(_xlpm.StartDay, WEEKDAY(DATE($A59, $B59, 1), 1),_xlpm.DayNum, (COLUMN() - COLUMN($K$56) + 1) + (ROW() - ROW($K$56)) * 7 - _xlpm.StartDay + 1,IF(AND(_xlpm.DayNum > 0, _xlpm.DayNum <= DAY(EOMONTH(DATE($A59, $B59, 1), 0))), _xlpm.DayNum, "")) -> 17 | L59: =_xlfn.LET(_xlpm.StartDay, WEEKDAY(DATE($A59, $B59, 1), 1),_xlpm.DayNum, (COLUMN() - COLUMN($K$56) + 1) + (ROW() - ROW($K$56)) * 7 - _xlpm.StartDay + 1,IF(AND(_xlpm.DayNum > 0, _xlpm.DayNum <= DAY(EOMONTH(DATE($A59, $B59, 1), 0))), _xlpm.DayNum, "")) -> 18 | M59: =_xlfn.LET(_xlpm.StartDay, WEEKDAY(DATE($A59, $B59, 1), 1),_xlpm.DayNum, (COLUMN() - COLUMN($K$56) + 1) + (ROW() - ROW($K$56)) * 7 - _xlpm.StartDay + 1,IF(AND(_xlpm.DayNum > 0, _xlpm.DayNum <= DAY(EOMONTH(DATE($A59, $B59, 1), 0))), _xlpm.DayNum, "")) -> 19 | N59: =_xlfn.LET(_xlpm.StartDay, WEEKDAY(DATE($A59, $B59, 1), 1),_xlpm.DayNum, (COLUMN() - COLUMN($K$56) + 1) + (ROW() - ROW($K$56)) * 7 - _xlpm.StartDay + 1,IF(AND(_xlpm.DayNum > 0, _xlpm.DayNum <= DAY(EOMONTH(DATE($A59, $B59, 1), 0))), _xlpm.DayNum, "")) -> 20 | O59: =_xlfn.LET(_xlpm.StartDay, WEEKDAY(DATE($A59, $B59, 1), 1),_xlpm.DayNum, (COLUMN() - COLUMN($K$56) + 1) + (ROW() - ROW($K$56)) * 7 - _xlpm.StartDay + 1,IF(AND(_xlpm.DayNum > 0, _xlpm.DayNum <= DAY(EOMONTH(DATE($A59, $B59, 1), 0))), _xlpm.DayNum, "")) -> 21 | P59: =_xlfn.LET(_xlpm.StartDay, WEEKDAY(DATE($A59, $B59, 1), 1),_xlpm.DayNum, (COLUMN() - COLUMN($K$56) + 1) + (ROW() - ROW($K$56)) * 7 - _xlpm.StartDay + 1,IF(AND(_xlpm.DayNum > 0, _xlpm.DayNum <= DAY(EOMONTH(DATE($A59, $B59, 1), 0))), _xlpm.DayNum, "")) -> 22 | Q59: =_xlfn.LET(_xlpm.StartDay, WEEKDAY(DATE($A59, $B59, 1), 1),_xlpm.DayNum, (COLUMN() - COLUMN($K$56) + 1) + (ROW() - ROW($K$56)) * 7 - _xlpm.StartDay + 1,IF(AND(_xlpm.DayNum > 0, _xlpm.DayNum <= DAY(EOMONTH(DATE($A59, $B59, 1), 0))), _xlpm.DayNum, "")) -> 23
A60: 2027 | B60: 10 | C60: 5 | D60: 3 | E60: 2 | F60: 3 | G60: 3 | H60: 2 | I60: 4 | J60: 2 | K60: =_xlfn.LET(_xlpm.StartDay, WEEKDAY(DATE($A60, $B60, 1), 1),_xlpm.DayNum, (COLUMN() - COLUMN($K$56) + 1) + (ROW() - ROW($K$56)) * 7 - _xlpm.StartDay + 1,IF(AND(_xlpm.DayNum > 0, _xlpm.DayNum <= DAY(EOMONTH(DATE($A60, $B60, 1), 0))), _xlpm.DayNum, "")) -> 24 | L60: =_xlfn.LET(_xlpm.StartDay, WEEKDAY(DATE($A60, $B60, 1), 1),_xlpm.DayNum, (COLUMN() - COLUMN($K$56) + 1) + (ROW() - ROW($K$56)) * 7 - _xlpm.StartDay + 1,IF(AND(_xlpm.DayNum > 0, _xlpm.DayNum <= DAY(EOMONTH(DATE($A60, $B60, 1), 0))), _xlpm.DayNum, "")) -> 25 | M60: =_xlfn.LET(_xlpm.StartDay, WEEKDAY(DATE($A60, $B60, 1), 1),_xlpm.DayNum, (COLUMN() - COLUMN($K$56) + 1) + (ROW() - ROW($K$56)) * 7 - _xlpm.StartDay + 1,IF(AND(_xlpm.DayNum > 0, _xlpm.DayNum <= DAY(EOMONTH(DATE($A60, $B60, 1), 0))), _xlpm.DayNum, "")) -> 26 | N60: =_xlfn.LET(_xlpm.StartDay, WEEKDAY(DATE($A60, $B60, 1), 1),_xlpm.DayNum, (COLUMN() - COLUMN($K$56) + 1) + (ROW() - ROW($K$56)) * 7 - _xlpm.StartDay + 1,IF(AND(_xlpm.DayNum > 0, _xlpm.DayNum <= DAY(EOMONTH(DATE($A60, $B60, 1), 0))), _xlpm.DayNum, "")) -> 27 | O60: =_xlfn.LET(_xlpm.StartDay, WEEKDAY(DATE($A60, $B60, 1), 1),_xlpm.DayNum, (COLUMN() - COLUMN($K$56) + 1) + (ROW() - ROW($K$56)) * 7 - _xlpm.StartDay + 1,IF(AND(_xlpm.DayNum > 0, _xlpm.DayNum <= DAY(EOMONTH(DATE($A60, $B60, 1), 0))), _xlpm.DayNum, "")) -> 28 | P60: =_xlfn.LET(_xlpm.StartDay, WEEKDAY(DATE($A60, $B60, 1), 1),_xlpm.DayNum, (COLUMN() - COLUMN($K$56) + 1) + (ROW() - ROW($K$56)) * 7 - _xlpm.StartDay + 1,IF(AND(_xlpm.DayNum > 0, _xlpm.DayNum <= DAY(EOMONTH(DATE($A60, $B60, 1), 0))), _xlpm.DayNum, "")) -> 29 | Q60: =_xlfn.LET(_xlpm.StartDay, WEEKDAY(DATE($A60, $B60, 1), 1),_xlpm.DayNum, (COLUMN() - COLUMN($K$56) + 1) + (ROW() - ROW($K$56)) * 7 - _xlpm.StartDay + 1,IF(AND(_xlpm.DayNum > 0, _xlpm.DayNum <= DAY(EOMONTH(DATE($A60, $B60, 1), 0))), _xlpm.DayNum, "")) -> 30
A61: 2027 | B61: 10 | C61: 6 | D61: 2 | E61: 1 | F61: 1 | G61: 1 | H61: 1 | I61: 1 | J61: 1 | K61: =_xlfn.LET(_xlpm.StartDay, WEEKDAY(DATE($A61, $B61, 1), 1),_xlpm.DayNum, (COLUMN() - COLUMN($K$56) + 1) + (ROW() - ROW($K$56)) * 7 - _xlpm.StartDay + 1,IF(AND(_xlpm.DayNum > 0, _xlpm.DayNum <= DAY(EOMONTH(DATE($A61, $B61, 1), 0))), _xlpm.DayNum, "")) -> 31 | L61: =IF(E61<>1,"ERROR!!!","") | M61: =IF(F61<>1,"ERROR!!!","") | N61: =IF(G61<>1,"ERROR!!!","") | O61: =IF(H61<>1,"ERROR!!!","") | P61: =IF(I61<>1,"ERROR!!!","") | Q61: =IF(J61<>1,"ERROR!!!","")
A62: 2027 | B62: 11 | C62: 1 | D62: 1 | E62: 2 | F62: 2 | G62: 2 | H62: 2 | I62: 2 | J62: 3 | K62: =IF(D62<>1,"ERROR!!!","") | L62: =_xlfn.LET(_xlpm.StartDay, WEEKDAY(DATE($A62, $B62, 1), 1),_xlpm.DayNum, (COLUMN() - COLUMN($K$62) + 1) + (ROW() - ROW($K$62)) * 7 - _xlpm.StartDay + 1,IF(AND(_xlpm.DayNum > 0, _xlpm.DayNum <= DAY(EOMONTH(DATE($A62, $B62, 1), 0))), _xlpm.DayNum, "")) -> 1 | M62: =_xlfn.LET(_xlpm.StartDay, WEEKDAY(DATE($A62, $B62, 1), 1),_xlpm.DayNum, (COLUMN() - COLUMN($K$62) + 1) + (ROW() - ROW($K$62)) * 7 - _xlpm.StartDay + 1,IF(AND(_xlpm.DayNum > 0, _xlpm.DayNum <= DAY(EOMONTH(DATE($A62, $B62, 1), 0))), _xlpm.DayNum, "")) -> 2 | N62: =_xlfn.LET(_xlpm.StartDay, WEEKDAY(DATE($A62, $B62, 1), 1),_xlpm.DayNum, (COLUMN() - COLUMN($K$62) + 1) + (ROW() - ROW($K$62)) * 7 - _xlpm.StartDay + 1,IF(AND(_xlpm.DayNum > 0, _xlpm.DayNum <= DAY(EOMONTH(DATE($A62, $B62, 1), 0))), _xlpm.DayNum, "")) -> 3 | O62: =_xlfn.LET(_xlpm.StartDay, WEEKDAY(DATE($A62, $B62, 1), 1),_xlpm.DayNum, (COLUMN() - COLUMN($K$62) + 1) + (ROW() - ROW($K$62)) * 7 - _xlpm.StartDay + 1,IF(AND(_xlpm.DayNum > 0, _xlpm.DayNum <= DAY(EOMONTH(DATE($A62, $B62, 1), 0))), _xlpm.DayNum, "")) -> 4 | P62: =_xlfn.LET(_xlpm.StartDay, WEEKDAY(DATE($A62, $B62, 1), 1),_xlpm.DayNum, (COLUMN() - COLUMN($K$62) + 1) + (ROW() - ROW($K$62)) * 7 - _xlpm.StartDay + 1,IF(AND(_xlpm.DayNum > 0, _xlpm.DayNum <= DAY(EOMONTH(DATE($A62, $B62, 1), 0))), _xlpm.DayNum, "")) -> 5 | Q62: =_xlfn.LET(_xlpm.StartDay, WEEKDAY(DATE($A62, $B62, 1), 1),_xlpm.DayNum, (COLUMN() - COLUMN($K$62) + 1) + (ROW() - ROW($K$62)) * 7 - _xlpm.StartDay + 1,IF(AND(_xlpm.DayNum > 0, _xlpm.DayNum <= DAY(EOMONTH(DATE($A62, $B62, 1), 0))), _xlpm.DayNum, "")) -> 6
A63: 2027 | B63: 11 | C63: 2 | D63: 3 | E63: 3 | F63: 3 | G63: 3 | H63: 2 | I63: 3 | J63: 4 | K63: =_xlfn.LET(_xlpm.StartDay, WEEKDAY(DATE($A63, $B63, 1), 1),_xlpm.DayNum, (COLUMN() - COLUMN($K$62) + 1) + (ROW() - ROW($K$62)) * 7 - _xlpm.StartDay + 1,IF(AND(_xlpm.DayNum > 0, _xlpm.DayNum <= DAY(EOMONTH(DATE($A63, $B63, 1), 0))), _xlpm.DayNum, "")) -> 7 | L63: =_xlfn.LET(_xlpm.StartDay, WEEKDAY(DATE($A63, $B63, 1), 1),_xlpm.DayNum, (COLUMN() - COLUMN($K$62) + 1) + (ROW() - ROW($K$62)) * 7 - _xlpm.StartDay + 1,IF(AND(_xlpm.DayNum > 0, _xlpm.DayNum <= DAY(EOMONTH(DATE($A63, $B63, 1), 0))), _xlpm.DayNum, "")) -> 8 | M63: =_xlfn.LET(_xlpm.StartDay, WEEKDAY(DATE($A63, $B63, 1), 1),_xlpm.DayNum, (COLUMN() - COLUMN($K$62) + 1) + (ROW() - ROW($K$62)) * 7 - _xlpm.StartDay + 1,IF(AND(_xlpm.DayNum > 0, _xlpm.DayNum <= DAY(EOMONTH(DATE($A63, $B63, 1), 0))), _xlpm.DayNum, "")) -> 9 | N63: =_xlfn.LET(_xlpm.StartDay, WEEKDAY(DATE($A63, $B63, 1), 1),_xlpm.DayNum, (COLUMN() - COLUMN($K$62) + 1) + (ROW() - ROW($K$62)) * 7 - _xlpm.StartDay + 1,IF(AND(_xlpm.DayNum > 0, _xlpm.DayNum <= DAY(EOMONTH(DATE($A63, $B63, 1), 0))), _xlpm.DayNum, "")) -> 10 | O63: =_xlfn.LET(_xlpm.StartDay, WEEKDAY(DATE($A63, $B63, 1), 1),_xlpm.DayNum, (COLUMN() - COLUMN($K$62) + 1) + (ROW() - ROW($K$62)) * 7 - _xlpm.StartDay + 1,IF(AND(_xlpm.DayNum > 0, _xlpm.DayNum <= DAY(EOMONTH(DATE($A63, $B63, 1), 0))), _xlpm.DayNum, "")) -> 11 | P63: =_xlfn.LET(_xlpm.StartDay, WEEKDAY(DATE($A63, $B63, 1), 1),_xlpm.DayNum, (COLUMN() - COLUMN($K$62) + 1) + (ROW() - ROW($K$62)) * 7 - _xlpm.StartDay + 1,IF(AND(_xlpm.DayNum > 0, _xlpm.DayNum <= DAY(EOMONTH(DATE($A63, $B63, 1), 0))), _xlpm.DayNum, "")) -> 12 | Q63: =_xlfn.LET(_xlpm.StartDay, WEEKDAY(DATE($A63, $B63, 1), 1),_xlpm.DayNum, (COLUMN() - COLUMN($K$62) + 1) + (ROW() - ROW($K$62)) * 7 - _xlpm.StartDay + 1,IF(AND(_xlpm.DayNum > 0, _xlpm.DayNum <= DAY(EOMONTH(DATE($A63, $B63, 1), 0))), _xlpm.DayNum, "")) -> 13
A64: 2027 | B64: 11 | C64: 3 | D64: 3 | E64: 4 | F64: 2 | G64: 2 | H64: 2 | I64: 3 | J64: 3 | K64: =_xlfn.LET(_xlpm.StartDay, WEEKDAY(DATE($A64, $B64, 1), 1),_xlpm.DayNum, (COLUMN() - COLUMN($K$62) + 1) + (ROW() - ROW($K$62)) * 7 - _xlpm.StartDay + 1,IF(AND(_xlpm.DayNum > 0, _xlpm.DayNum <= DAY(EOMONTH(DATE($A64, $B64, 1), 0))), _xlpm.DayNum, "")) -> 14 | L64: =_xlfn.LET(_xlpm.StartDay, WEEKDAY(DATE($A64, $B64, 1), 1),_xlpm.DayNum, (COLUMN() - COLUMN($K$62) + 1) + (ROW() - ROW($K$62)) * 7 - _xlpm.StartDay + 1,IF(AND(_xlpm.DayNum > 0, _xlpm.DayNum <= DAY(EOMONTH(DATE($A64, $B64, 1), 0))), _xlpm.DayNum, "")) -> 15 | M64: =_xlfn.LET(_xlpm.StartDay, WEEKDAY(DATE($A64, $B64, 1), 1),_xlpm.DayNum, (COLUMN() - COLUMN($K$62) + 1) + (ROW() - ROW($K$62)) * 7 - _xlpm.StartDay + 1,IF(AND(_xlpm.DayNum > 0, _xlpm.DayNum <= DAY(EOMONTH(DATE($A64, $B64, 1), 0))), _xlpm.DayNum, "")) -> 16 | N64: =_xlfn.LET(_xlpm.StartDay, WEEKDAY(DATE($A64, $B64, 1), 1),_xlpm.DayNum, (COLUMN() - COLUMN($K$62) + 1) + (ROW() - ROW($K$62)) * 7 - _xlpm.StartDay + 1,IF(AND(_xlpm.DayNum > 0, _xlpm.DayNum <= DAY(EOMONTH(DATE($A64, $B64, 1), 0))), _xlpm.DayNum, "")) -> 17 | O64: =_xlfn.LET(_xlpm.StartDay, WEEKDAY(DATE($A64, $B64, 1), 1),_xlpm.DayNum, (COLUMN() - COLUMN($K$62) + 1) + (ROW() - ROW($K$62)) * 7 - _xlpm.StartDay + 1,IF(AND(_xlpm.DayNum > 0, _xlpm.DayNum <= DAY(EOMONTH(DATE($A64, $B64, 1), 0))), _xlpm.DayNum, "")) -> 18 | P64: =_xlfn.LET(_xlpm.StartDay, WEEKDAY(DATE($A64, $B64, 1), 1),_xlpm.DayNum, (COLUMN() - COLUMN($K$62) + 1) + (ROW() - ROW($K$62)) * 7 - _xlpm.StartDay + 1,IF(AND(_xlpm.DayNum > 0, _xlpm.DayNum <= DAY(EOMONTH(DATE($A64, $B64, 1), 0))), _xlpm.DayNum, "")) -> 19 | Q64: =_xlfn.LET(_xlpm.StartDay, WEEKDAY(DATE($A64, $B64, 1), 1),_xlpm.DayNum, (COLUMN() - COLUMN($K$62) + 1) + (ROW() - ROW($K$62)) * 7 - _xlpm.StartDay + 1,IF(AND(_xlpm.DayNum > 0, _xlpm.DayNum <= DAY(EOMONTH(DATE($A64, $B64, 1), 0))), _xlpm.DayNum, "")) -> 20
A65: 2027 | B65: 11 | C65: 4 | D65: 3 | E65: 3 | F65: 2 | G65: 3 | H65: 2 | I65: 4 | J65: 2 | K65: =_xlfn.LET(_xlpm.StartDay, WEEKDAY(DATE($A65, $B65, 1), 1),_xlpm.DayNum, (COLUMN() - COLUMN($K$62) + 1) + (ROW() - ROW($K$62)) * 7 - _xlpm.StartDay + 1,IF(AND(_xlpm.DayNum > 0, _xlpm.DayNum <= DAY(EOMONTH(DATE($A65, $B65, 1), 0))), _xlpm.DayNum, "")) -> 21 | L65: =_xlfn.LET(_xlpm.StartDay, WEEKDAY(DATE($A65, $B65, 1), 1),_xlpm.DayNum, (COLUMN() - COLUMN($K$62) + 1) + (ROW() - ROW($K$62)) * 7 - _xlpm.StartDay + 1,IF(AND(_xlpm.DayNum > 0, _xlpm.DayNum <= DAY(EOMONTH(DATE($A65, $B65, 1), 0))), _xlpm.DayNum, "")) -> 22 | M65: =_xlfn.LET(_xlpm.StartDay, WEEKDAY(DATE($A65, $B65, 1), 1),_xlpm.DayNum, (COLUMN() - COLUMN($K$62) + 1) + (ROW() - ROW($K$62)) * 7 - _xlpm.StartDay + 1,IF(AND(_xlpm.DayNum > 0, _xlpm.DayNum <= DAY(EOMONTH(DATE($A65, $B65, 1), 0))), _xlpm.DayNum, "")) -> 23 | N65: =_xlfn.LET(_xlpm.StartDay, WEEKDAY(DATE($A65, $B65, 1), 1),_xlpm.DayNum, (COLUMN() - COLUMN($K$62) + 1) + (ROW() - ROW($K$62)) * 7 - _xlpm.StartDay + 1,IF(AND(_xlpm.DayNum > 0, _xlpm.DayNum <= DAY(EOMONTH(DATE($A65, $B65, 1), 0))), _xlpm.DayNum, "")) -> 24 | O65: =_xlfn.LET(_xlpm.StartDay, WEEKDAY(DATE($A65, $B65, 1), 1),_xlpm.DayNum, (COLUMN() - COLUMN($K$62) + 1) + (ROW() - ROW($K$62)) * 7 - _xlpm.StartDay + 1,IF(AND(_xlpm.DayNum > 0, _xlpm.DayNum <= DAY(EOMONTH(DATE($A65, $B65, 1), 0))), _xlpm.DayNum, "")) -> 25 | P65: =_xlfn.LET(_xlpm.StartDay, WEEKDAY(DATE($A65, $B65, 1), 1),_xlpm.DayNum, (COLUMN() - COLUMN($K$62) + 1) + (ROW() - ROW($K$62)) * 7 - _xlpm.StartDay + 1,IF(AND(_xlpm.DayNum > 0, _xlpm.DayNum <= DAY(EOMONTH(DATE($A65, $B65, 1), 0))), _xlpm.DayNum, "")) -> 26 | Q65: =_xlfn.LET(_xlpm.StartDay, WEEKDAY(DATE($A65, $B65, 1), 1),_xlpm.DayNum, (COLUMN() - COLUMN($K$62) + 1) + (ROW() - ROW($K$62)) * 7 - _xlpm.StartDay + 1,IF(AND(_xlpm.DayNum > 0, _xlpm.DayNum <= DAY(EOMONTH(DATE($A65, $B65, 1), 0))), _xlpm.DayNum, "")) -> 27
A66: 2027 | B66: 11 | C66: 5 | D66: 4 | E66: 2 | F66: 2 | G66: 1 | H66: 1 | I66: 1 | J66: 1 | K66: =_xlfn.LET(_xlpm.StartDay, WEEKDAY(DATE($A66, $B66, 1), 1),_xlpm.DayNum, (COLUMN() - COLUMN($K$62) + 1) + (ROW() - ROW($K$62)) * 7 - _xlpm.StartDay + 1,IF(AND(_xlpm.DayNum > 0, _xlpm.DayNum <= DAY(EOMONTH(DATE($A66, $B66, 1), 0))), _xlpm.DayNum, "")) -> 28 | L66: =_xlfn.LET(_xlpm.StartDay, WEEKDAY(DATE($A66, $B66, 1), 1),_xlpm.DayNum, (COLUMN() - COLUMN($K$62) + 1) + (ROW() - ROW($K$62)) * 7 - _xlpm.StartDay + 1,IF(AND(_xlpm.DayNum > 0, _xlpm.DayNum <= DAY(EOMONTH(DATE($A66, $B66, 1), 0))), _xlpm.DayNum, "")) -> 29 | M66: =_xlfn.LET(_xlpm.StartDay, WEEKDAY(DATE($A66, $B66, 1), 1),_xlpm.DayNum, (COLUMN() - COLUMN($K$62) + 1) + (ROW() - ROW($K$62)) * 7 - _xlpm.StartDay + 1,IF(AND(_xlpm.DayNum > 0, _xlpm.DayNum <= DAY(EOMONTH(DATE($A66, $B66, 1), 0))), _xlpm.DayNum, "")) -> 30 | N66: =IF(G66<>1,"ERROR!!!","") | O66: =IF(H66<>1,"ERROR!!!","") | P66: =IF(I66<>1,"ERROR!!!","") | Q66: =IF(J66<>1,"ERROR!!!","")
A67: 2027 | B67: 11 | C67: 6 | D67: 1 | E67: 1 | F67: 1 | G67: 1 | H67: 1 | I67: 1 | J67: 1 | K67: =IF(D67<>1,"ERROR!!!","") | L67: =IF(E67<>1,"ERROR!!!","") | M67: =IF(F67<>1,"ERROR!!!","") | N67: =IF(G67<>1,"ERROR!!!","") | O67: =IF(H67<>1,"ERROR!!!","") | P67: =IF(I67<>1,"ERROR!!!","") | Q67: =IF(J67<>1,"ERROR!!!","")
A68: 2027 | B68: 12 | C68: 1 | D68: 1 | E68: 1 | F68: 1 | G68: 2 | H68: 3 | I68: 3 | J68: 4 | K68: =IF(D68<>1,"ERROR!!!","") | L68: =IF(E68<>1,"ERROR!!!","") | M68: =IF(F68<>1,"ERROR!!!","") | N68: =_xlfn.LET(_xlpm.StartDay, WEEKDAY(DATE($A68, $B68, 1), 1),_xlpm.DayNum, (COLUMN() - COLUMN($K$68) + 1) + (ROW() - ROW($K$68)) * 7 - _xlpm.StartDay + 1,IF(AND(_xlpm.DayNum > 0, _xlpm.DayNum <= DAY(EOMONTH(DATE($A68, $B68, 1), 0))), _xlpm.DayNum, "")) -> 1 | O68: =_xlfn.LET(_xlpm.StartDay, WEEKDAY(DATE($A68, $B68, 1), 1),_xlpm.DayNum, (COLUMN() - COLUMN($K$68) + 1) + (ROW() - ROW($K$68)) * 7 - _xlpm.StartDay + 1,IF(AND(_xlpm.DayNum > 0, _xlpm.DayNum <= DAY(EOMONTH(DATE($A68, $B68, 1), 0))), _xlpm.DayNum, "")) -> 2 | P68: =_xlfn.LET(_xlpm.StartDay, WEEKDAY(DATE($A68, $B68, 1), 1),_xlpm.DayNum, (COLUMN() - COLUMN($K$68) + 1) + (ROW() - ROW($K$68)) * 7 - _xlpm.StartDay + 1,IF(AND(_xlpm.DayNum > 0, _xlpm.DayNum <= DAY(EOMONTH(DATE($A68, $B68, 1), 0))), _xlpm.DayNum, "")) -> 3 | Q68: =_xlfn.LET(_xlpm.StartDay, WEEKDAY(DATE($A68, $B68, 1), 1),_xlpm.DayNum, (COLUMN() - COLUMN($K$68) + 1) + (ROW() - ROW($K$68)) * 7 - _xlpm.StartDay + 1,IF(AND(_xlpm.DayNum > 0, _xlpm.DayNum <= DAY(EOMONTH(DATE($A68, $B68, 1), 0))), _xlpm.DayNum, "")) -> 4
A69: 2027 | B69: 12 | C69: 2 | D69: 2 | E69: 2 | F69: 2 | G69: 2 | H69: 3 | I69: 2 | J69: 4 | K69: =_xlfn.LET(_xlpm.StartDay, WEEKDAY(DATE($A69, $B69, 1), 1),_xlpm.DayNum, (COLUMN() - COLUMN($K$68) + 1) + (ROW() - ROW($K$68)) * 7 - _xlpm.StartDay + 1,IF(AND(_xlpm.DayNum > 0, _xlpm.DayNum <= DAY(EOMONTH(DATE($A69, $B69, 1), 0))), _xlpm.DayNum, "")) -> 5 | L69: =_xlfn.LET(_xlpm.StartDay, WEEKDAY(DATE($A69, $B69, 1), 1),_xlpm.DayNum, (COLUMN() - COLUMN($K$68) + 1) + (ROW() - ROW($K$68)) * 7 - _xlpm.StartDay + 1,IF(AND(_xlpm.DayNum > 0, _xlpm.DayNum <= DAY(EOMONTH(DATE($A69, $B69, 1), 0))), _xlpm.DayNum, "")) -> 6 | M69: =_xlfn.LET(_xlpm.StartDay, WEEKDAY(DATE($A69, $B69, 1), 1),_xlpm.DayNum, (COLUMN() - COLUMN($K$68) + 1) + (ROW() - ROW($K$68)) * 7 - _xlpm.StartDay + 1,IF(AND(_xlpm.DayNum > 0, _xlpm.DayNum <= DAY(EOMONTH(DATE($A69, $B69, 1), 0))), _xlpm.DayNum, "")) -> 7 | N69: =_xlfn.LET(_xlpm.StartDay, WEEKDAY(DATE($A69, $B69, 1), 1),_xlpm.DayNum, (COLUMN() - COLUMN($K$68) + 1) + (ROW() - ROW($K$68)) * 7 - _xlpm.StartDay + 1,IF(AND(_xlpm.DayNum > 0, _xlpm.DayNum <= DAY(EOMONTH(DATE($A69, $B69, 1), 0))), _xlpm.DayNum, "")) -> 8 | O69: =_xlfn.LET(_xlpm.StartDay, WEEKDAY(DATE($A69, $B69, 1), 1),_xlpm.DayNum, (COLUMN() - COLUMN($K$68) + 1) + (ROW() - ROW($K$68)) * 7 - _xlpm.StartDay + 1,IF(AND(_xlpm.DayNum > 0, _xlpm.DayNum <= DAY(EOMONTH(DATE($A69, $B69, 1), 0))), _xlpm.DayNum, "")) -> 9 | P69: =_xlfn.LET(_xlpm.StartDay, WEEKDAY(DATE($A69, $B69, 1), 1),_xlpm.DayNum, (COLUMN() - COLUMN($K$68) + 1) + (ROW() - ROW($K$68)) * 7 - _xlpm.StartDay + 1,IF(AND(_xlpm.DayNum > 0, _xlpm.DayNum <= DAY(EOMONTH(DATE($A69, $B69, 1), 0))), _xlpm.DayNum, "")) -> 10 | Q69: =_xlfn.LET(_xlpm.StartDay, WEEKDAY(DATE($A69, $B69, 1), 1),_xlpm.DayNum, (COLUMN() - COLUMN($K$68) + 1) + (ROW() - ROW($K$68)) * 7 - _xlpm.StartDay + 1,IF(AND(_xlpm.DayNum > 0, _xlpm.DayNum <= DAY(EOMONTH(DATE($A69, $B69, 1), 0))), _xlpm.DayNum, "")) -> 11
A70: 2027 | B70: 12 | C70: 3 | D70: 2 | E70: 3 | F70: 3 | G70: 3 | H70: 2 | I70: 2 | J70: 3 | K70: =_xlfn.LET(_xlpm.StartDay, WEEKDAY(DATE($A70, $B70, 1), 1),_xlpm.DayNum, (COLUMN() - COLUMN($K$68) + 1) + (ROW() - ROW($K$68)) * 7 - _xlpm.StartDay + 1,IF(AND(_xlpm.DayNum > 0, _xlpm.DayNum <= DAY(EOMONTH(DATE($A70, $B70, 1), 0))), _xlpm.DayNum, "")) -> 12 | L70: =_xlfn.LET(_xlpm.StartDay, WEEKDAY(DATE($A70, $B70, 1), 1),_xlpm.DayNum, (COLUMN() - COLUMN($K$68) + 1) + (ROW() - ROW($K$68)) * 7 - _xlpm.StartDay + 1,IF(AND(_xlpm.DayNum > 0, _xlpm.DayNum <= DAY(EOMONTH(DATE($A70, $B70, 1), 0))), _xlpm.DayNum, "")) -> 13 | M70: =_xlfn.LET(_xlpm.StartDay, WEEKDAY(DATE($A70, $B70, 1), 1),_xlpm.DayNum, (COLUMN() - COLUMN($K$68) + 1) + (ROW() - ROW($K$68)) * 7 - _xlpm.StartDay + 1,IF(AND(_xlpm.DayNum > 0, _xlpm.DayNum <= DAY(EOMONTH(DATE($A70, $B70, 1), 0))), _xlpm.DayNum, "")) -> 14 | N70: =_xlfn.LET(_xlpm.StartDay, WEEKDAY(DATE($A70, $B70, 1), 1),_xlpm.DayNum, (COLUMN() - COLUMN($K$68) + 1) + (ROW() - ROW($K$68)) * 7 - _xlpm.StartDay + 1,IF(AND(_xlpm.DayNum > 0, _xlpm.DayNum <= DAY(EOMONTH(DATE($A70, $B70, 1), 0))), _xlpm.DayNum, "")) -> 15 | O70: =_xlfn.LET(_xlpm.StartDay, WEEKDAY(DATE($A70, $B70, 1), 1),_xlpm.DayNum, (COLUMN() - COLUMN($K$68) + 1) + (ROW() - ROW($K$68)) * 7 - _xlpm.StartDay + 1,IF(AND(_xlpm.DayNum > 0, _xlpm.DayNum <= DAY(EOMONTH(DATE($A70, $B70, 1), 0))), _xlpm.DayNum, "")) -> 16 | P70: =_xlfn.LET(_xlpm.StartDay, WEEKDAY(DATE($A70, $B70, 1), 1),_xlpm.DayNum, (COLUMN() - COLUMN($K$68) + 1) + (ROW() - ROW($K$68)) * 7 - _xlpm.StartDay + 1,IF(AND(_xlpm.DayNum > 0, _xlpm.DayNum <= DAY(EOMONTH(DATE($A70, $B70, 1), 0))), _xlpm.DayNum, "")) -> 17 | Q70: =_xlfn.LET(_xlpm.StartDay, WEEKDAY(DATE($A70, $B70, 1), 1),_xlpm.DayNum, (COLUMN() - COLUMN($K$68) + 1) + (ROW() - ROW($K$68)) * 7 - _xlpm.StartDay + 1,IF(AND(_xlpm.DayNum > 0, _xlpm.DayNum <= DAY(EOMONTH(DATE($A70, $B70, 1), 0))), _xlpm.DayNum, "")) -> 18
A71: 2027 | B71: 12 | C71: 4 | D71: 2 | E71: 3 | F71: 2 | G71: 3 | H71: 3 | I71: 2 | J71: 3 | K71: =_xlfn.LET(_xlpm.StartDay, WEEKDAY(DATE($A71, $B71, 1), 1),_xlpm.DayNum, (COLUMN() - COLUMN($K$68) + 1) + (ROW() - ROW($K$68)) * 7 - _xlpm.StartDay + 1,IF(AND(_xlpm.DayNum > 0, _xlpm.DayNum <= DAY(EOMONTH(DATE($A71, $B71, 1), 0))), _xlpm.DayNum, "")) -> 19 | L71: =_xlfn.LET(_xlpm.StartDay, WEEKDAY(DATE($A71, $B71, 1), 1),_xlpm.DayNum, (COLUMN() - COLUMN($K$68) + 1) + (ROW() - ROW($K$68)) * 7 - _xlpm.StartDay + 1,IF(AND(_xlpm.DayNum > 0, _xlpm.DayNum <= DAY(EOMONTH(DATE($A71, $B71, 1), 0))), _xlpm.DayNum, "")) -> 20 | M71: =_xlfn.LET(_xlpm.StartDay, WEEKDAY(DATE($A71, $B71, 1), 1),_xlpm.DayNum, (COLUMN() - COLUMN($K$68) + 1) + (ROW() - ROW($K$68)) * 7 - _xlpm.StartDay + 1,IF(AND(_xlpm.DayNum > 0, _xlpm.DayNum <= DAY(EOMONTH(DATE($A71, $B71, 1), 0))), _xlpm.DayNum, "")) -> 21 | N71: =_xlfn.LET(_xlpm.StartDay, WEEKDAY(DATE($A71, $B71, 1), 1),_xlpm.DayNum, (COLUMN() - COLUMN($K$68) + 1) + (ROW() - ROW($K$68)) * 7 - _xlpm.StartDay + 1,IF(AND(_xlpm.DayNum > 0, _xlpm.DayNum <= DAY(EOMONTH(DATE($A71, $B71, 1), 0))), _xlpm.DayNum, "")) -> 22 | O71: =_xlfn.LET(_xlpm.StartDay, WEEKDAY(DATE($A71, $B71, 1), 1),_xlpm.DayNum, (COLUMN() - COLUMN($K$68) + 1) + (ROW() - ROW($K$68)) * 7 - _xlpm.StartDay + 1,IF(AND(_xlpm.DayNum > 0, _xlpm.DayNum <= DAY(EOMONTH(DATE($A71, $B71, 1), 0))), _xlpm.DayNum, "")) -> 23 | P71: =_xlfn.LET(_xlpm.StartDay, WEEKDAY(DATE($A71, $B71, 1), 1),_xlpm.DayNum, (COLUMN() - COLUMN($K$68) + 1) + (ROW() - ROW($K$68)) * 7 - _xlpm.StartDay + 1,IF(AND(_xlpm.DayNum > 0, _xlpm.DayNum <= DAY(EOMONTH(DATE($A71, $B71, 1), 0))), _xlpm.DayNum, "")) -> 24 | Q71: =_xlfn.LET(_xlpm.StartDay, WEEKDAY(DATE($A71, $B71, 1), 1),_xlpm.DayNum, (COLUMN() - COLUMN($K$68) + 1) + (ROW() - ROW($K$68)) * 7 - _xlpm.StartDay + 1,IF(AND(_xlpm.DayNum > 0, _xlpm.DayNum <= DAY(EOMONTH(DATE($A71, $B71, 1), 0))), _xlpm.DayNum, "")) -> 25
A72: 2027 | B72: 12 | C72: 5 | D72: 3 | E72: 3 | F72: 2 | G72: 2 | H72: 2 | I72: 2 | J72: 1 | K72: =_xlfn.LET(_xlpm.StartDay, WEEKDAY(DATE($A72, $B72, 1), 1),_xlpm.DayNum, (COLUMN() - COLUMN($K$68) + 1) + (ROW() - ROW($K$68)) * 7 - _xlpm.StartDay + 1,IF(AND(_xlpm.DayNum > 0, _xlpm.DayNum <= DAY(EOMONTH(DATE($A72, $B72, 1), 0))), _xlpm.DayNum, "")) -> 26 | L72: =_xlfn.LET(_xlpm.StartDay, WEEKDAY(DATE($A72, $B72, 1), 1),_xlpm.DayNum, (COLUMN() - COLUMN($K$68) + 1) + (ROW() - ROW($K$68)) * 7 - _xlpm.StartDay + 1,IF(AND(_xlpm.DayNum > 0, _xlpm.DayNum <= DAY(EOMONTH(DATE($A72, $B72, 1), 0))), _xlpm.DayNum, "")) -> 27 | M72: =_xlfn.LET(_xlpm.StartDay, WEEKDAY(DATE($A72, $B72, 1), 1),_xlpm.DayNum, (COLUMN() - COLUMN($K$68) + 1) + (ROW() - ROW($K$68)) * 7 - _xlpm.StartDay + 1,IF(AND(_xlpm.DayNum > 0, _xlpm.DayNum <= DAY(EOMONTH(DATE($A72, $B72, 1), 0))), _xlpm.DayNum, "")) -> 28 | N72: =_xlfn.LET(_xlpm.StartDay, WEEKDAY(DATE($A72, $B72, 1), 1),_xlpm.DayNum, (COLUMN() - COLUMN($K$68) + 1) + (ROW() - ROW($K$68)) * 7 - _xlpm.StartDay + 1,IF(AND(_xlpm.DayNum > 0, _xlpm.DayNum <= DAY(EOMONTH(DATE($A72, $B72, 1), 0))), _xlpm.DayNum, "")) -> 29 | O72: =_xlfn.LET(_xlpm.StartDay, WEEKDAY(DATE($A72, $B72, 1), 1),_xlpm.DayNum, (COLUMN() - COLUMN($K$68) + 1) + (ROW() - ROW($K$68)) * 7 - _xlpm.StartDay + 1,IF(AND(_xlpm.DayNum > 0, _xlpm.DayNum <= DAY(EOMONTH(DATE($A72, $B72, 1), 0))), _xlpm.DayNum, "")) -> 30 | P72: =_xlfn.LET(_xlpm.StartDay, WEEKDAY(DATE($A72, $B72, 1), 1),_xlpm.DayNum, (COLUMN() - COLUMN($K$68) + 1) + (ROW() - ROW($K$68)) * 7 - _xlpm.StartDay + 1,IF(AND(_xlpm.DayNum > 0, _xlpm.DayNum <= DAY(EOMONTH(DATE($A72, $B72, 1), 0))), _xlpm.DayNum, "")) -> 31 | Q72: =IF(J72<>1,"ERROR!!!","")
A73: 2027 | B73: 12 | C73: 6 | D73: 1 | E73: 1 | F73: 1 | G73: 1 | H73: 1 | I73: 1 | J73: 1 | K73: =IF(D73<>1,"ERROR!!!","") | L73: =IF(E73<>1,"ERROR!!!","") | M73: =IF(F73<>1,"ERROR!!!","") | N73: =IF(G73<>1,"ERROR!!!","") | O73: =IF(H73<>1,"ERROR!!!","") | P73: =IF(I73<>1,"ERROR!!!","") | Q73: =IF(J73<>1,"ERROR!!!","")
A74: 2028 | B74: 1 | C74: 1 | D74: 1 | E74: 1 | F74: 1 | G74: 1 | H74: 1 | I74: 1 | J74: 4 | K74: =IF(D74<>1,"ERROR!!!","") | L74: =IF(E74<>1,"ERROR!!!","") | M74: =IF(F74<>1,"ERROR!!!","") | N74: =IF(G74<>1,"ERROR!!!","") | O74: =IF(H74<>1,"ERROR!!!","") | P74: =IF(I74<>1,"ERROR!!!","") | Q74: =_xlfn.LET(_xlpm.StartDay, WEEKDAY(DATE($A74, $B74, 1), 1),_xlpm.DayNum, (COLUMN() - COLUMN($K$74) + 1) + (ROW() - ROW($K$74)) * 7 - _xlpm.StartDay + 1,IF(AND(_xlpm.DayNum > 0, _xlpm.DayNum <= DAY(EOMONTH(DATE($A74, $B74, 1), 0))), _xlpm.DayNum, "")) -> 1
A75: 2028 | B75: 1 | C75: 2 | D75: 4 | E75: 3 | F75: 3 | G75: 2 | H75: 3 | I75: 2 | J75: 3 | K75: =_xlfn.LET(_xlpm.StartDay, WEEKDAY(DATE($A75, $B75, 1), 1),_xlpm.DayNum, (COLUMN() - COLUMN($K$74) + 1) + (ROW() - ROW($K$74)) * 7 - _xlpm.StartDay + 1,IF(AND(_xlpm.DayNum > 0, _xlpm.DayNum <= DAY(EOMONTH(DATE($A75, $B75, 1), 0))), _xlpm.DayNum, "")) -> 2 | L75: =_xlfn.LET(_xlpm.StartDay, WEEKDAY(DATE($A75, $B75, 1), 1),_xlpm.DayNum, (COLUMN() - COLUMN($K$74) + 1) + (ROW() - ROW($K$74)) * 7 - _xlpm.StartDay + 1,IF(AND(_xlpm.DayNum > 0, _xlpm.DayNum <= DAY(EOMONTH(DATE($A75, $B75, 1), 0))), _xlpm.DayNum, "")) -> 3 | M75: =_xlfn.LET(_xlpm.StartDay, WEEKDAY(DATE($A75, $B75, 1), 1),_xlpm.DayNum, (COLUMN() - COLUMN($K$74) + 1) + (ROW() - ROW($K$74)) * 7 - _xlpm.StartDay + 1,IF(AND(_xlpm.DayNum > 0, _xlpm.DayNum <= DAY(EOMONTH(DATE($A75, $B75, 1), 0))), _xlpm.DayNum, "")) -> 4 | N75: =_xlfn.LET(_xlpm.StartDay, WEEKDAY(DATE($A75, $B75, 1), 1),_xlpm.DayNum, (COLUMN() - COLUMN($K$74) + 1) + (ROW() - ROW($K$74)) * 7 - _xlpm.StartDay + 1,IF(AND(_xlpm.DayNum > 0, _xlpm.DayNum <= DAY(EOMONTH(DATE($A75, $B75, 1), 0))), _xlpm.DayNum, "")) -> 5 | O75: =_xlfn.LET(_xlpm.StartDay, WEEKDAY(DATE($A75, $B75, 1), 1),_xlpm.DayNum, (COLUMN() - COLUMN($K$74) + 1) + (ROW() - ROW($K$74)) * 7 - _xlpm.StartDay + 1,IF(AND(_xlpm.DayNum > 0, _xlpm.DayNum <= DAY(EOMONTH(DATE($A75, $B75, 1), 0))), _xlpm.DayNum, "")) -> 6 | P75: =_xlfn.LET(_xlpm.StartDay, WEEKDAY(DATE($A75, $B75, 1), 1),_xlpm.DayNum, (COLUMN() - COLUMN($K$74) + 1) + (ROW() - ROW($K$74)) * 7 - _xlpm.StartDay + 1,IF(AND(_xlpm.DayNum > 0, _xlpm.DayNum <= DAY(EOMONTH(DATE($A75, $B75, 1), 0))), _xlpm.DayNum, "")) -> 7 | Q75: =_xlfn.LET(_xlpm.StartDay, WEEKDAY(DATE($A75, $B75, 1), 1),_xlpm.DayNum, (COLUMN() - COLUMN($K$74) + 1) + (ROW() - ROW($K$74)) * 7 - _xlpm.StartDay + 1,IF(AND(_xlpm.DayNum > 0, _xlpm.DayNum <= DAY(EOMONTH(DATE($A75, $B75, 1), 0))), _xlpm.DayNum, "")) -> 8
A76: 2028 | B76: 1 | C76: 3 | D76: 3 | E76: 2 | F76: 2 | G76: 2 | H76: 4 | I76: 4 | J76: 3 | K76: =_xlfn.LET(_xlpm.StartDay, WEEKDAY(DATE($A76, $B76, 1), 1),_xlpm.DayNum, (COLUMN() - COLUMN($K$74) + 1) + (ROW() - ROW($K$74)) * 7 - _xlpm.StartDay + 1,IF(AND(_xlpm.DayNum > 0, _xlpm.DayNum <= DAY(EOMONTH(DATE($A76, $B76, 1), 0))), _xlpm.DayNum, "")) -> 9 | L76: =_xlfn.LET(_xlpm.StartDay, WEEKDAY(DATE($A76, $B76, 1), 1),_xlpm.DayNum, (COLUMN() - COLUMN($K$74) + 1) + (ROW() - ROW($K$74)) * 7 - _xlpm.StartDay + 1,IF(AND(_xlpm.DayNum > 0, _xlpm.DayNum <= DAY(EOMONTH(DATE($A76, $B76, 1), 0))), _xlpm.DayNum, "")) -> 10 | M76: =_xlfn.LET(_xlpm.StartDay, WEEKDAY(DATE($A76, $B76, 1), 1),_xlpm.DayNum, (COLUMN() - COLUMN($K$74) + 1) + (ROW() - ROW($K$74)) * 7 - _xlpm.StartDay + 1,IF(AND(_xlpm.DayNum > 0, _xlpm.DayNum <= DAY(EOMONTH(DATE($A76, $B76, 1), 0))), _xlpm.DayNum, "")) -> 11 | N76: =_xlfn.LET(_xlpm.StartDay, WEEKDAY(DATE($A76, $B76, 1), 1),_xlpm.DayNum, (COLUMN() - COLUMN($K$74) + 1) + (ROW() - ROW($K$74)) * 7 - _xlpm.StartDay + 1,IF(AND(_xlpm.DayNum > 0, _xlpm.DayNum <= DAY(EOMONTH(DATE($A76, $B76, 1), 0))), _xlpm.DayNum, "")) -> 12 | O76: =_xlfn.LET(_xlpm.StartDay, WEEKDAY(DATE($A76, $B76, 1), 1),_xlpm.DayNum, (COLUMN() - COLUMN($K$74) + 1) + (ROW() - ROW($K$74)) * 7 - _xlpm.StartDay + 1,IF(AND(_xlpm.DayNum > 0, _xlpm.DayNum <= DAY(EOMONTH(DATE($A76, $B76, 1), 0))), _xlpm.DayNum, "")) -> 13 | P76: =_xlfn.LET(_xlpm.StartDay, WEEKDAY(DATE($A76, $B76, 1), 1),_xlpm.DayNum, (COLUMN() - COLUMN($K$74) + 1) + (ROW() - ROW($K$74)) * 7 - _xlpm.StartDay + 1,IF(AND(_xlpm.DayNum > 0, _xlpm.DayNum <= DAY(EOMONTH(DATE($A76, $B76, 1), 0))), _xlpm.DayNum, "")) -> 14 | Q76: =_xlfn.LET(_xlpm.StartDay, WEEKDAY(DATE($A76, $B76, 1), 1),_xlpm.DayNum, (COLUMN() - COLUMN($K$74) + 1) + (ROW() - ROW($K$74)) * 7 - _xlpm.StartDay + 1,IF(AND(_xlpm.DayNum > 0, _xlpm.DayNum <= DAY(EOMONTH(DATE($A76, $B76, 1), 0))), _xlpm.DayNum, "")) -> 15
A77: 2028 | B77: 1 | C77: 4 | D77: 2 | E77: 2 | F77: 4 | G77: 2 | H77: 3 | I77: 3 | J77: 4 | K77: =_xlfn.LET(_xlpm.StartDay, WEEKDAY(DATE($A77, $B77, 1), 1),_xlpm.DayNum, (COLUMN() - COLUMN($K$74) + 1) + (ROW() - ROW($K$74)) * 7 - _xlpm.StartDay + 1,IF(AND(_xlpm.DayNum > 0, _xlpm.DayNum <= DAY(EOMONTH(DATE($A77, $B77, 1), 0))), _xlpm.DayNum, "")) -> 16 | L77: =_xlfn.LET(_xlpm.StartDay, WEEKDAY(DATE($A77, $B77, 1), 1),_xlpm.DayNum, (COLUMN() - COLUMN($K$74) + 1) + (ROW() - ROW($K$74)) * 7 - _xlpm.StartDay + 1,IF(AND(_xlpm.DayNum > 0, _xlpm.DayNum <= DAY(EOMONTH(DATE($A77, $B77, 1), 0))), _xlpm.DayNum, "")) -> 17 | M77: =_xlfn.LET(_xlpm.StartDay, WEEKDAY(DATE($A77, $B77, 1), 1),_xlpm.DayNum, (COLUMN() - COLUMN($K$74) + 1) + (ROW() - ROW($K$74)) * 7 - _xlpm.StartDay + 1,IF(AND(_xlpm.DayNum > 0, _xlpm.DayNum <= DAY(EOMONTH(DATE($A77, $B77, 1), 0))), _xlpm.DayNum, "")) -> 18 | N77: =_xlfn.LET(_xlpm.StartDay, WEEKDAY(DATE($A77, $B77, 1), 1),_xlpm.DayNum, (COLUMN() - COLUMN($K$74) + 1) + (ROW() - ROW($K$74)) * 7 - _xlpm.StartDay + 1,IF(AND(_xlpm.DayNum > 0, _xlpm.DayNum <= DAY(EOMONTH(DATE($A77, $B77, 1), 0))), _xlpm.DayNum, "")) -> 19 | O77: =_xlfn.LET(_xlpm.StartDay, WEEKDAY(DATE($A77, $B77, 1), 1),_xlpm.DayNum, (COLUMN() - COLUMN($K$74) + 1) + (ROW() - ROW($K$74)) * 7 - _xlpm.StartDay + 1,IF(AND(_xlpm.DayNum > 0, _xlpm.DayNum <= DAY(EOMONTH(DATE($A77, $B77, 1), 0))), _xlpm.DayNum, "")) -> 20 | P77: =_xlfn.LET(_xlpm.StartDay, WEEKDAY(DATE($A77, $B77, 1), 1),_xlpm.DayNum, (COLUMN() - COLUMN($K$74) + 1) + (ROW() - ROW($K$74)) * 7 - _xlpm.StartDay + 1,IF(AND(_xlpm.DayNum > 0, _xlpm.DayNum <= DAY(EOMONTH(DATE($A77, $B77, 1), 0))), _xlpm.DayNum, "")) -> 21 | Q77: =_xlfn.LET(_xlpm.StartDay, WEEKDAY(DATE($A77, $B77, 1), 1),_xlpm.DayNum, (COLUMN() - COLUMN($K$74) + 1) + (ROW() - ROW($K$74)) * 7 - _xlpm.StartDay + 1,IF(AND(_xlpm.DayNum > 0, _xlpm.DayNum <= DAY(EOMONTH(DATE($A77, $B77, 1), 0))), _xlpm.DayNum, "")) -> 22
A78: 2028 | B78: 1 | C78: 5 | D78: 2 | E78: 2 | F78: 3 | G78: 4 | H78: 4 | I78: 2 | J78: 3 | K78: =_xlfn.LET(_xlpm.StartDay, WEEKDAY(DATE($A78, $B78, 1), 1),_xlpm.DayNum, (COLUMN() - COLUMN($K$74) + 1) + (ROW() - ROW($K$74)) * 7 - _xlpm.StartDay + 1,IF(AND(_xlpm.DayNum > 0, _xlpm.DayNum <= DAY(EOMONTH(DATE($A78, $B78, 1), 0))), _xlpm.DayNum, "")) -> 23 | L78: =_xlfn.LET(_xlpm.StartDay, WEEKDAY(DATE($A78, $B78, 1), 1),_xlpm.DayNum, (COLUMN() - COLUMN($K$74) + 1) + (ROW() - ROW($K$74)) * 7 - _xlpm.StartDay + 1,IF(AND(_xlpm.DayNum > 0, _xlpm.DayNum <= DAY(EOMONTH(DATE($A78, $B78, 1), 0))), _xlpm.DayNum, "")) -> 24 | M78: =_xlfn.LET(_xlpm.StartDay, WEEKDAY(DATE($A78, $B78, 1), 1),_xlpm.DayNum, (COLUMN() - COLUMN($K$74) + 1) + (ROW() - ROW($K$74)) * 7 - _xlpm.StartDay + 1,IF(AND(_xlpm.DayNum > 0, _xlpm.DayNum <= DAY(EOMONTH(DATE($A78, $B78, 1), 0))), _xlpm.DayNum, "")) -> 25 | N78: =_xlfn.LET(_xlpm.StartDay, WEEKDAY(DATE($A78, $B78, 1), 1),_xlpm.DayNum, (COLUMN() - COLUMN($K$74) + 1) + (ROW() - ROW($K$74)) * 7 - _xlpm.StartDay + 1,IF(AND(_xlpm.DayNum > 0, _xlpm.DayNum <= DAY(EOMONTH(DATE($A78, $B78, 1), 0))), _xlpm.DayNum, "")) -> 26 | O78: =_xlfn.LET(_xlpm.StartDay, WEEKDAY(DATE($A78, $B78, 1), 1),_xlpm.DayNum, (COLUMN() - COLUMN($K$74) + 1) + (ROW() - ROW($K$74)) * 7 - _xlpm.StartDay + 1,IF(AND(_xlpm.DayNum > 0, _xlpm.DayNum <= DAY(EOMONTH(DATE($A78, $B78, 1), 0))), _xlpm.DayNum, "")) -> 27 | P78: =_xlfn.LET(_xlpm.StartDay, WEEKDAY(DATE($A78, $B78, 1), 1),_xlpm.DayNum, (COLUMN() - COLUMN($K$74) + 1) + (ROW() - ROW($K$74)) * 7 - _xlpm.StartDay + 1,IF(AND(_xlpm.DayNum > 0, _xlpm.DayNum <= DAY(EOMONTH(DATE($A78, $B78, 1), 0))), _xlpm.DayNum, "")) -> 28 | Q78: =_xlfn.LET(_xlpm.StartDay, WEEKDAY(DATE($A78, $B78, 1), 1),_xlpm.DayNum, (COLUMN() - COLUMN($K$74) + 1) + (ROW() - ROW($K$74)) * 7 - _xlpm.StartDay + 1,IF(AND(_xlpm.DayNum > 0, _xlpm.DayNum <= DAY(EOMONTH(DATE($A78, $B78, 1), 0))), _xlpm.DayNum, "")) -> 29
A79: 2028 | B79: 1 | C79: 6 | D79: 2 | E79: 2 | F79: 1 | G79: 1 | H79: 1 | I79: 1 | J79: 1 | K79: =_xlfn.LET(_xlpm.StartDay, WEEKDAY(DATE($A79, $B79, 1), 1),_xlpm.DayNum, (COLUMN() - COLUMN($K$74) + 1) + (ROW() - ROW($K$74)) * 7 - _xlpm.StartDay + 1,IF(AND(_xlpm.DayNum > 0, _xlpm.DayNum <= DAY(EOMONTH(DATE($A79, $B79, 1), 0))), _xlpm.DayNum, "")) -> 30 | L79: =_xlfn.LET(_xlpm.StartDay, WEEKDAY(DATE($A79, $B79, 1), 1),_xlpm.DayNum, (COLUMN() - COLUMN($K$74) + 1) + (ROW() - ROW($K$74)) * 7 - _xlpm.StartDay + 1,IF(AND(_xlpm.DayNum > 0, _xlpm.DayNum <= DAY(EOMONTH(DATE($A79, $B79, 1), 0))), _xlpm.DayNum, "")) -> 31 | M79: =IF(F79<>1,"ERROR!!!","") | N79: =IF(G79<>1,"ERROR!!!","") | O79: =IF(H79<>1,"ERROR!!!","") | P79: =IF(I79<>1,"ERROR!!!","") | Q79: =IF(J79<>1,"ERROR!!!","")
A80: 2028 | B80: 2 | C80: 1 | D80: 1 | E80: 1 | F80: 2 | G80: 3 | H80: 2 | I80: 3 | J80: 2 | K80: =IF(D80<>1,"ERROR!!!","") | L80: =IF(E80<>1,"ERROR!!!","") | M80: =_xlfn.LET(_xlpm.StartDay, WEEKDAY(DATE($A80, $B80, 1), 1),_xlpm.DayNum, (COLUMN() - COLUMN($K$80) + 1) + (ROW() - ROW($K$80)) * 7 - _xlpm.StartDay + 1,IF(AND(_xlpm.DayNum > 0, _xlpm.DayNum <= DAY(EOMONTH(DATE($A80, $B80, 1), 0))), _xlpm.DayNum, "")) -> 1 | N80: =_xlfn.LET(_xlpm.StartDay, WEEKDAY(DATE($A80, $B80, 1), 1),_xlpm.DayNum, (COLUMN() - COLUMN($K$80) + 1) + (ROW() - ROW($K$80)) * 7 - _xlpm.StartDay + 1,IF(AND(_xlpm.DayNum > 0, _xlpm.DayNum <= DAY(EOMONTH(DATE($A80, $B80, 1), 0))), _xlpm.DayNum, "")) -> 2 | O80: =_xlfn.LET(_xlpm.StartDay, WEEKDAY(DATE($A80, $B80, 1), 1),_xlpm.DayNum, (COLUMN() - COLUMN($K$80) + 1) + (ROW() - ROW($K$80)) * 7 - _xlpm.StartDay + 1,IF(AND(_xlpm.DayNum > 0, _xlpm.DayNum <= DAY(EOMONTH(DATE($A80, $B80, 1), 0))), _xlpm.DayNum, "")) -> 3 | P80: =_xlfn.LET(_xlpm.StartDay, WEEKDAY(DATE($A80, $B80, 1), 1),_xlpm.DayNum, (COLUMN() - COLUMN($K$80) + 1) + (ROW() - ROW($K$80)) * 7 - _xlpm.StartDay + 1,IF(AND(_xlpm.DayNum > 0, _xlpm.DayNum <= DAY(EOMONTH(DATE($A80, $B80, 1), 0))), _xlpm.DayNum, "")) -> 4 | Q80: =_xlfn.LET(_xlpm.StartDay, WEEKDAY(DATE($A80, $B80, 1), 1),_xlpm.DayNum, (COLUMN() - COLUMN($K$80) + 1) + (ROW() - ROW($K$80)) * 7 - _xlpm.StartDay + 1,IF(AND(_xlpm.DayNum > 0, _xlpm.DayNum <= DAY(EOMONTH(DATE($A80, $B80, 1), 0))), _xlpm.DayNum, "")) -> 5
A81: 2028 | B81: 2 | C81: 2 | D81: 2 | E81: 2 | F81: 3 | G81: 3 | H81: 2 | I81: 2 | J81: 3 | K81: =_xlfn.LET(_xlpm.StartDay, WEEKDAY(DATE($A81, $B81, 1), 1),_xlpm.DayNum, (COLUMN() - COLUMN($K$80) + 1) + (ROW() - ROW($K$80)) * 7 - _xlpm.StartDay + 1,IF(AND(_xlpm.DayNum > 0, _xlpm.DayNum <= DAY(EOMONTH(DATE($A81, $B81, 1), 0))), _xlpm.DayNum, "")) -> 6 | L81: =_xlfn.LET(_xlpm.StartDay, WEEKDAY(DATE($A81, $B81, 1), 1),_xlpm.DayNum, (COLUMN() - COLUMN($K$80) + 1) + (ROW() - ROW($K$80)) * 7 - _xlpm.StartDay + 1,IF(AND(_xlpm.DayNum > 0, _xlpm.DayNum <= DAY(EOMONTH(DATE($A81, $B81, 1), 0))), _xlpm.DayNum, "")) -> 7 | M81: =_xlfn.LET(_xlpm.StartDay, WEEKDAY(DATE($A81, $B81, 1), 1),_xlpm.DayNum, (COLUMN() - COLUMN($K$80) + 1) + (ROW() - ROW($K$80)) * 7 - _xlpm.StartDay + 1,IF(AND(_xlpm.DayNum > 0, _xlpm.DayNum <= DAY(EOMONTH(DATE($A81, $B81, 1), 0))), _xlpm.DayNum, "")) -> 8 | N81: =_xlfn.LET(_xlpm.StartDay, WEEKDAY(DATE($A81, $B81, 1), 1),_xlpm.DayNum, (COLUMN() - COLUMN($K$80) + 1) + (ROW() - ROW($K$80)) * 7 - _xlpm.StartDay + 1,IF(AND(_xlpm.DayNum > 0, _xlpm.DayNum <= DAY(EOMONTH(DATE($A81, $B81, 1), 0))), _xlpm.DayNum, "")) -> 9 | O81: =_xlfn.LET(_xlpm.StartDay, WEEKDAY(DATE($A81, $B81, 1), 1),_xlpm.DayNum, (COLUMN() - COLUMN($K$80) + 1) + (ROW() - ROW($K$80)) * 7 - _xlpm.StartDay + 1,IF(AND(_xlpm.DayNum > 0, _xlpm.DayNum <= DAY(EOMONTH(DATE($A81, $B81, 1), 0))), _xlpm.DayNum, "")) -> 10 | P81: =_xlfn.LET(_xlpm.StartDay, WEEKDAY(DATE($A81, $B81, 1), 1),_xlpm.DayNum, (COLUMN() - COLUMN($K$80) + 1) + (ROW() - ROW($K$80)) * 7 - _xlpm.StartDay + 1,IF(AND(_xlpm.DayNum > 0, _xlpm.DayNum <= DAY(EOMONTH(DATE($A81, $B81, 1), 0))), _xlpm.DayNum, "")) -> 11 | Q81: =_xlfn.LET(_xlpm.StartDay, WEEKDAY(DATE($A81, $B81, 1), 1),_xlpm.DayNum, (COLUMN() - COLUMN($K$80) + 1) + (ROW() - ROW($K$80)) * 7 - _xlpm.StartDay + 1,IF(AND(_xlpm.DayNum > 0, _xlpm.DayNum <= DAY(EOMONTH(DATE($A81, $B81, 1), 0))), _xlpm.DayNum, "")) -> 12
A82: 2028 | B82: 2 | C82: 3 | D82: 3 | E82: 2 | F82: 2 | G82: 2 | H82: 2 | I82: 2 | J82: 4 | K82: =_xlfn.LET(_xlpm.StartDay, WEEKDAY(DATE($A82, $B82, 1), 1),_xlpm.DayNum, (COLUMN() - COLUMN($K$80) + 1) + (ROW() - ROW($K$80)) * 7 - _xlpm.StartDay + 1,IF(AND(_xlpm.DayNum > 0, _xlpm.DayNum <= DAY(EOMONTH(DATE($A82, $B82, 1), 0))), _xlpm.DayNum, "")) -> 13 | L82: =_xlfn.LET(_xlpm.StartDay, WEEKDAY(DATE($A82, $B82, 1), 1),_xlpm.DayNum, (COLUMN() - COLUMN($K$80) + 1) + (ROW() - ROW($K$80)) * 7 - _xlpm.StartDay + 1,IF(AND(_xlpm.DayNum > 0, _xlpm.DayNum <= DAY(EOMONTH(DATE($A82, $B82, 1), 0))), _xlpm.DayNum, "")) -> 14 | M82: =_xlfn.LET(_xlpm.StartDay, WEEKDAY(DATE($A82, $B82, 1), 1),_xlpm.DayNum, (COLUMN() - COLUMN($K$80) + 1) + (ROW() - ROW($K$80)) * 7 - _xlpm.StartDay + 1,IF(AND(_xlpm.DayNum > 0, _xlpm.DayNum <= DAY(EOMONTH(DATE($A82, $B82, 1), 0))), _xlpm.DayNum, "")) -> 15 | N82: =_xlfn.LET(_xlpm.StartDay, WEEKDAY(DATE($A82, $B82, 1), 1),_xlpm.DayNum, (COLUMN() - COLUMN($K$80) + 1) + (ROW() - ROW($K$80)) * 7 - _xlpm.StartDay + 1,IF(AND(_xlpm.DayNum > 0, _xlpm.DayNum <= DAY(EOMONTH(DATE($A82, $B82, 1), 0))), _xlpm.DayNum, "")) -> 16 | O82: =_xlfn.LET(_xlpm.StartDay, WEEKDAY(DATE($A82, $B82, 1), 1),_xlpm.DayNum, (COLUMN() - COLUMN($K$80) + 1) + (ROW() - ROW($K$80)) * 7 - _xlpm.StartDay + 1,IF(AND(_xlpm.DayNum > 0, _xlpm.DayNum <= DAY(EOMONTH(DATE($A82, $B82, 1), 0))), _xlpm.DayNum, "")) -> 17 | P82: =_xlfn.LET(_xlpm.StartDay, WEEKDAY(DATE($A82, $B82, 1), 1),_xlpm.DayNum, (COLUMN() - COLUMN($K$80) + 1) + (ROW() - ROW($K$80)) * 7 - _xlpm.StartDay + 1,IF(AND(_xlpm.DayNum > 0, _xlpm.DayNum <= DAY(EOMONTH(DATE($A82, $B82, 1), 0))), _xlpm.DayNum, "")) -> 18 | Q82: =_xlfn.LET(_xlpm.StartDay, WEEKDAY(DATE($A82, $B82, 1), 1),_xlpm.DayNum, (COLUMN() - COLUMN($K$80) + 1) + (ROW() - ROW($K$80)) * 7 - _xlpm.StartDay + 1,IF(AND(_xlpm.DayNum > 0, _xlpm.DayNum <= DAY(EOMONTH(DATE($A82, $B82, 1), 0))), _xlpm.DayNum, "")) -> 19
A83: 2028 | B83: 2 | C83: 4 | D83: 2 | E83: 2 | F83: 3 | G83: 3 | H83: 2 | I83: 3 | J83: 2 | K83: =_xlfn.LET(_xlpm.StartDay, WEEKDAY(DATE($A83, $B83, 1), 1),_xlpm.DayNum, (COLUMN() - COLUMN($K$80) + 1) + (ROW() - ROW($K$80)) * 7 - _xlpm.StartDay + 1,IF(AND(_xlpm.DayNum > 0, _xlpm.DayNum <= DAY(EOMONTH(DATE($A83, $B83, 1), 0))), _xlpm.DayNum, "")) -> 20 | L83: =_xlfn.LET(_xlpm.StartDay, WEEKDAY(DATE($A83, $B83, 1), 1),_xlpm.DayNum, (COLUMN() - COLUMN($K$80) + 1) + (ROW() - ROW($K$80)) * 7 - _xlpm.StartDay + 1,IF(AND(_xlpm.DayNum > 0, _xlpm.DayNum <= DAY(EOMONTH(DATE($A83, $B83, 1), 0))), _xlpm.DayNum, "")) -> 21 | M83: =_xlfn.LET(_xlpm.StartDay, WEEKDAY(DATE($A83, $B83, 1), 1),_xlpm.DayNum, (COLUMN() - COLUMN($K$80) + 1) + (ROW() - ROW($K$80)) * 7 - _xlpm.StartDay + 1,IF(AND(_xlpm.DayNum > 0, _xlpm.DayNum <= DAY(EOMONTH(DATE($A83, $B83, 1), 0))), _xlpm.DayNum, "")) -> 22 | N83: =_xlfn.LET(_xlpm.StartDay, WEEKDAY(DATE($A83, $B83, 1), 1),_xlpm.DayNum, (COLUMN() - COLUMN($K$80) + 1) + (ROW() - ROW($K$80)) * 7 - _xlpm.StartDay + 1,IF(AND(_xlpm.DayNum > 0, _xlpm.DayNum <= DAY(EOMONTH(DATE($A83, $B83, 1), 0))), _xlpm.DayNum, "")) -> 23 | O83: =_xlfn.LET(_xlpm.StartDay, WEEKDAY(DATE($A83, $B83, 1), 1),_xlpm.DayNum, (COLUMN() - COLUMN($K$80) + 1) + (ROW() - ROW($K$80)) * 7 - _xlpm.StartDay + 1,IF(AND(_xlpm.DayNum > 0, _xlpm.DayNum <= DAY(EOMONTH(DATE($A83, $B83, 1), 0))), _xlpm.DayNum, "")) -> 24 | P83: =_xlfn.LET(_xlpm.StartDay, WEEKDAY(DATE($A83, $B83, 1), 1),_xlpm.DayNum, (COLUMN() - COLUMN($K$80) + 1) + (ROW() - ROW($K$80)) * 7 - _xlpm.StartDay + 1,IF(AND(_xlpm.DayNum > 0, _xlpm.DayNum <= DAY(EOMONTH(DATE($A83, $B83, 1), 0))), _xlpm.DayNum, "")) -> 25 | Q83: =_xlfn.LET(_xlpm.StartDay, WEEKDAY(DATE($A83, $B83, 1), 1),_xlpm.DayNum, (COLUMN() - COLUMN($K$80) + 1) + (ROW() - ROW($K$80)) * 7 - _xlpm.StartDay + 1,IF(AND(_xlpm.DayNum > 0, _xlpm.DayNum <= DAY(EOMONTH(DATE($A83, $B83, 1), 0))), _xlpm.DayNum, "")) -> 26
A84: 2028 | B84: 2 | C84: 5 | D84: 2 | E84: 2 | F84: 2 | G84: 1 | H84: 1 | I84: 1 | J84: 1 | K84: =_xlfn.LET(_xlpm.StartDay, WEEKDAY(DATE($A84, $B84, 1), 1),_xlpm.DayNum, (COLUMN() - COLUMN($K$80) + 1) + (ROW() - ROW($K$80)) * 7 - _xlpm.StartDay + 1,IF(AND(_xlpm.DayNum > 0, _xlpm.DayNum <= DAY(EOMONTH(DATE($A84, $B84, 1), 0))), _xlpm.DayNum, "")) -> 27 | L84: =_xlfn.LET(_xlpm.StartDay, WEEKDAY(DATE($A84, $B84, 1), 1),_xlpm.DayNum, (COLUMN() - COLUMN($K$80) + 1) + (ROW() - ROW($K$80)) * 7 - _xlpm.StartDay + 1,IF(AND(_xlpm.DayNum > 0, _xlpm.DayNum <= DAY(EOMONTH(DATE($A84, $B84, 1), 0))), _xlpm.DayNum, "")) -> 28 | M84: =_xlfn.LET(_xlpm.StartDay, WEEKDAY(DATE($A84, $B84, 1), 1),_xlpm.DayNum, (COLUMN() - COLUMN($K$80) + 1) + (ROW() - ROW($K$80)) * 7 - _xlpm.StartDay + 1,IF(AND(_xlpm.DayNum > 0, _xlpm.DayNum <= DAY(EOMONTH(DATE($A84, $B84, 1), 0))), _xlpm.DayNum, "")) -> 29 | N84: =IF(G84<>1,"ERROR!!!","") | O84: =IF(H84<>1,"ERROR!!!","") | P84: =IF(I84<>1,"ERROR!!!","") | Q84: =IF(J84<>1,"ERROR!!!","")
A85: 2028 | B85: 2 | C85: 6 | D85: 1 | E85: 1 | F85: 1 | G85: 1 | H85: 1 | I85: 1 | J85: 1 | K85: =IF(D85<>1,"ERROR!!!","") | L85: =IF(E85<>1,"ERROR!!!","") | M85: =IF(F85<>1,"ERROR!!!","") | N85: =IF(G85<>1,"ERROR!!!","") | O85: =IF(H85<>1,"ERROR!!!","") | P85: =IF(I85<>1,"ERROR!!!","") | Q85: =IF(J85<>1,"ERROR!!!","")
A86: 2028 | B86: 3 | C86: 1 | D86: 1 | E86: 1 | F86: 1 | G86: 2 | H86: 2 | I86: 3 | J86: 2 | K86: =IF(D86<>1,"ERROR!!!","") | L86: =IF(E86<>1,"ERROR!!!","") | M86: =IF(F86<>1,"ERROR!!!","") | N86: =_xlfn.LET(_xlpm.StartDay, WEEKDAY(DATE($A86, $B86, 1), 1),_xlpm.DayNum, (COLUMN() - COLUMN($K$86) + 1) + (ROW() - ROW($K$86)) * 7 - _xlpm.StartDay + 1,IF(AND(_xlpm.DayNum > 0, _xlpm.DayNum <= DAY(EOMONTH(DATE($A86, $B86, 1), 0))), _xlpm.DayNum, "")) -> 1 | O86: =_xlfn.LET(_xlpm.StartDay, WEEKDAY(DATE($A86, $B86, 1), 1),_xlpm.DayNum, (COLUMN() - COLUMN($K$86) + 1) + (ROW() - ROW($K$86)) * 7 - _xlpm.StartDay + 1,IF(AND(_xlpm.DayNum > 0, _xlpm.DayNum <= DAY(EOMONTH(DATE($A86, $B86, 1), 0))), _xlpm.DayNum, "")) -> 2 | P86: =_xlfn.LET(_xlpm.StartDay, WEEKDAY(DATE($A86, $B86, 1), 1),_xlpm.DayNum, (COLUMN() - COLUMN($K$86) + 1) + (ROW() - ROW($K$86)) * 7 - _xlpm.StartDay + 1,IF(AND(_xlpm.DayNum > 0, _xlpm.DayNum <= DAY(EOMONTH(DATE($A86, $B86, 1), 0))), _xlpm.DayNum, "")) -> 3 | Q86: =_xlfn.LET(_xlpm.StartDay, WEEKDAY(DATE($A86, $B86, 1), 1),_xlpm.DayNum, (COLUMN() - COLUMN($K$86) + 1) + (ROW() - ROW($K$86)) * 7 - _xlpm.StartDay + 1,IF(AND(_xlpm.DayNum > 0, _xlpm.DayNum <= DAY(EOMONTH(DATE($A86, $B86, 1), 0))), _xlpm.DayNum, "")) -> 4
A87: 2028 | B87: 3 | C87: 2 | D87: 2 | E87: 3 | F87: 2 | G87: 2 | H87: 2 | I87: 2 | J87: 3 | K87: =_xlfn.LET(_xlpm.StartDay, WEEKDAY(DATE($A87, $B87, 1), 1),_xlpm.DayNum, (COLUMN() - COLUMN($K$86) + 1) + (ROW() - ROW($K$86)) * 7 - _xlpm.StartDay + 1,IF(AND(_xlpm.DayNum > 0, _xlpm.DayNum <= DAY(EOMONTH(DATE($A87, $B87, 1), 0))), _xlpm.DayNum, "")) -> 5 | L87: =_xlfn.LET(_xlpm.StartDay, WEEKDAY(DATE($A87, $B87, 1), 1),_xlpm.DayNum, (COLUMN() - COLUMN($K$86) + 1) + (ROW() - ROW($K$86)) * 7 - _xlpm.StartDay + 1,IF(AND(_xlpm.DayNum > 0, _xlpm.DayNum <= DAY(EOMONTH(DATE($A87, $B87, 1), 0))), _xlpm.DayNum, "")) -> 6 | M87: =_xlfn.LET(_xlpm.StartDay, WEEKDAY(DATE($A87, $B87, 1), 1),_xlpm.DayNum, (COLUMN() - COLUMN($K$86) + 1) + (ROW() - ROW($K$86)) * 7 - _xlpm.StartDay + 1,IF(AND(_xlpm.DayNum > 0, _xlpm.DayNum <= DAY(EOMONTH(DATE($A87, $B87, 1), 0))), _xlpm.DayNum, "")) -> 7 | N87: =_xlfn.LET(_xlpm.StartDay, WEEKDAY(DATE($A87, $B87, 1), 1),_xlpm.DayNum, (COLUMN() - COLUMN($K$86) + 1) + (ROW() - ROW($K$86)) * 7 - _xlpm.StartDay + 1,IF(AND(_xlpm.DayNum > 0, _xlpm.DayNum <= DAY(EOMONTH(DATE($A87, $B87, 1), 0))), _xlpm.DayNum, "")) -> 8 | O87: =_xlfn.LET(_xlpm.StartDay, WEEKDAY(DATE($A87, $B87, 1), 1),_xlpm.DayNum, (COLUMN() - COLUMN($K$86) + 1) + (ROW() - ROW($K$86)) * 7 - _xlpm.StartDay + 1,IF(AND(_xlpm.DayNum > 0, _xlpm.DayNum <= DAY(EOMONTH(DATE($A87, $B87, 1), 0))), _xlpm.DayNum, "")) -> 9 | P87: =_xlfn.LET(_xlpm.StartDay, WEEKDAY(DATE($A87, $B87, 1), 1),_xlpm.DayNum, (COLUMN() - COLUMN($K$86) + 1) + (ROW() - ROW($K$86)) * 7 - _xlpm.StartDay + 1,IF(AND(_xlpm.DayNum > 0, _xlpm.DayNum <= DAY(EOMONTH(DATE($A87, $B87, 1), 0))), _xlpm.DayNum, "")) -> 10 | Q87: =_xlfn.LET(_xlpm.StartDay, WEEKDAY(DATE($A87, $B87, 1), 1),_xlpm.DayNum, (COLUMN() - COLUMN($K$86) + 1) + (ROW() - ROW($K$86)) * 7 - _xlpm.StartDay + 1,IF(AND(_xlpm.DayNum > 0, _xlpm.DayNum <= DAY(EOMONTH(DATE($A87, $B87, 1), 0))), _xlpm.DayNum, "")) -> 11
A88: 2028 | B88: 3 | C88: 3 | D88: 4 | E88: 2 | F88: 2 | G88: 2 | H88: 3 | I88: 3 | J88: 2 | K88: =_xlfn.LET(_xlpm.StartDay, WEEKDAY(DATE($A88, $B88, 1), 1),_xlpm.DayNum, (COLUMN() - COLUMN($K$86) + 1) + (ROW() - ROW($K$86)) * 7 - _xlpm.StartDay + 1,IF(AND(_xlpm.DayNum > 0, _xlpm.DayNum <= DAY(EOMONTH(DATE($A88, $B88, 1), 0))), _xlpm.DayNum, "")) -> 12 | L88: =_xlfn.LET(_xlpm.StartDay, WEEKDAY(DATE($A88, $B88, 1), 1),_xlpm.DayNum, (COLUMN() - COLUMN($K$86) + 1) + (ROW() - ROW($K$86)) * 7 - _xlpm.StartDay + 1,IF(AND(_xlpm.DayNum > 0, _xlpm.DayNum <= DAY(EOMONTH(DATE($A88, $B88, 1), 0))), _xlpm.DayNum, "")) -> 13 | M88: =_xlfn.LET(_xlpm.StartDay, WEEKDAY(DATE($A88, $B88, 1), 1),_xlpm.DayNum, (COLUMN() - COLUMN($K$86) + 1) + (ROW() - ROW($K$86)) * 7 - _xlpm.StartDay + 1,IF(AND(_xlpm.DayNum > 0, _xlpm.DayNum <= DAY(EOMONTH(DATE($A88, $B88, 1), 0))), _xlpm.DayNum, "")) -> 14 | N88: =_xlfn.LET(_xlpm.StartDay, WEEKDAY(DATE($A88, $B88, 1), 1),_xlpm.DayNum, (COLUMN() - COLUMN($K$86) + 1) + (ROW() - ROW($K$86)) * 7 - _xlpm.StartDay + 1,IF(AND(_xlpm.DayNum > 0, _xlpm.DayNum <= DAY(EOMONTH(DATE($A88, $B88, 1), 0))), _xlpm.DayNum, "")) -> 15 | O88: =_xlfn.LET(_xlpm.StartDay, WEEKDAY(DATE($A88, $B88, 1), 1),_xlpm.DayNum, (COLUMN() - COLUMN($K$86) + 1) + (ROW() - ROW($K$86)) * 7 - _xlpm.StartDay + 1,IF(AND(_xlpm.DayNum > 0, _xlpm.DayNum <= DAY(EOMONTH(DATE($A88, $B88, 1), 0))), _xlpm.DayNum, "")) -> 16 | P88: =_xlfn.LET(_xlpm.StartDay, WEEKDAY(DATE($A88, $B88, 1), 1),_xlpm.DayNum, (COLUMN() - COLUMN($K$86) + 1) + (ROW() - ROW($K$86)) * 7 - _xlpm.StartDay + 1,IF(AND(_xlpm.DayNum > 0, _xlpm.DayNum <= DAY(EOMONTH(DATE($A88, $B88, 1), 0))), _xlpm.DayNum, "")) -> 17 | Q88: =_xlfn.LET(_xlpm.StartDay, WEEKDAY(DATE($A88, $B88, 1), 1),_xlpm.DayNum, (COLUMN() - COLUMN($K$86) + 1) + (ROW() - ROW($K$86)) * 7 - _xlpm.StartDay + 1,IF(AND(_xlpm.DayNum > 0, _xlpm.DayNum <= DAY(EOMONTH(DATE($A88, $B88, 1), 0))), _xlpm.DayNum, "")) -> 18
A89: 2028 | B89: 3 | C89: 4 | D89: 3 | E89: 3 | F89: 3 | G89: 3 | H89: 3 | I89: 3 | J89: 2 | K89: =_xlfn.LET(_xlpm.StartDay, WEEKDAY(DATE($A89, $B89, 1), 1),_xlpm.DayNum, (COLUMN() - COLUMN($K$86) + 1) + (ROW() - ROW($K$86)) * 7 - _xlpm.StartDay + 1,IF(AND(_xlpm.DayNum > 0, _xlpm.DayNum <= DAY(EOMONTH(DATE($A89, $B89, 1), 0))), _xlpm.DayNum, "")) -> 19 | L89: =_xlfn.LET(_xlpm.StartDay, WEEKDAY(DATE($A89, $B89, 1), 1),_xlpm.DayNum, (COLUMN() - COLUMN($K$86) + 1) + (ROW() - ROW($K$86)) * 7 - _xlpm.StartDay + 1,IF(AND(_xlpm.DayNum > 0, _xlpm.DayNum <= DAY(EOMONTH(DATE($A89, $B89, 1), 0))), _xlpm.DayNum, "")) -> 20 | M89: =_xlfn.LET(_xlpm.StartDay, WEEKDAY(DATE($A89, $B89, 1), 1),_xlpm.DayNum, (COLUMN() - COLUMN($K$86) + 1) + (ROW() - ROW($K$86)) * 7 - _xlpm.StartDay + 1,IF(AND(_xlpm.DayNum > 0, _xlpm.DayNum <= DAY(EOMONTH(DATE($A89, $B89, 1), 0))), _xlpm.DayNum, "")) -> 21 | N89: =_xlfn.LET(_xlpm.StartDay, WEEKDAY(DATE($A89, $B89, 1), 1),_xlpm.DayNum, (COLUMN() - COLUMN($K$86) + 1) + (ROW() - ROW($K$86)) * 7 - _xlpm.StartDay + 1,IF(AND(_xlpm.DayNum > 0, _xlpm.DayNum <= DAY(EOMONTH(DATE($A89, $B89, 1), 0))), _xlpm.DayNum, "")) -> 22 | O89: =_xlfn.LET(_xlpm.StartDay, WEEKDAY(DATE($A89, $B89, 1), 1),_xlpm.DayNum, (COLUMN() - COLUMN($K$86) + 1) + (ROW() - ROW($K$86)) * 7 - _xlpm.StartDay + 1,IF(AND(_xlpm.DayNum > 0, _xlpm.DayNum <= DAY(EOMONTH(DATE($A89, $B89, 1), 0))), _xlpm.DayNum, "")) -> 23 | P89: =_xlfn.LET(_xlpm.StartDay, WEEKDAY(DATE($A89, $B89, 1), 1),_xlpm.DayNum, (COLUMN() - COLUMN($K$86) + 1) + (ROW() - ROW($K$86)) * 7 - _xlpm.StartDay + 1,IF(AND(_xlpm.DayNum > 0, _xlpm.DayNum <= DAY(EOMONTH(DATE($A89, $B89, 1), 0))), _xlpm.DayNum, "")) -> 24 | Q89: =_xlfn.LET(_xlpm.StartDay, WEEKDAY(DATE($A89, $B89, 1), 1),_xlpm.DayNum, (COLUMN() - COLUMN($K$86) + 1) + (ROW() - ROW($K$86)) * 7 - _xlpm.StartDay + 1,IF(AND(_xlpm.DayNum > 0, _xlpm.DayNum <= DAY(EOMONTH(DATE($A89, $B89, 1), 0))), _xlpm.DayNum, "")) -> 25
A90: 2028 | B90: 3 | C90: 5 | D90: 4 | E90: 2 | F90: 4 | G90: 2 | H90: 2 | I90: 2 | J90: 1 | K90: =_xlfn.LET(_xlpm.StartDay, WEEKDAY(DATE($A90, $B90, 1), 1),_xlpm.DayNum, (COLUMN() - COLUMN($K$86) + 1) + (ROW() - ROW($K$86)) * 7 - _xlpm.StartDay + 1,IF(AND(_xlpm.DayNum > 0, _xlpm.DayNum <= DAY(EOMONTH(DATE($A90, $B90, 1), 0))), _xlpm.DayNum, "")) -> 26 | L90: =_xlfn.LET(_xlpm.StartDay, WEEKDAY(DATE($A90, $B90, 1), 1),_xlpm.DayNum, (COLUMN() - COLUMN($K$86) + 1) + (ROW() - ROW($K$86)) * 7 - _xlpm.StartDay + 1,IF(AND(_xlpm.DayNum > 0, _xlpm.DayNum <= DAY(EOMONTH(DATE($A90, $B90, 1), 0))), _xlpm.DayNum, "")) -> 27 | M90: =_xlfn.LET(_xlpm.StartDay, WEEKDAY(DATE($A90, $B90, 1), 1),_xlpm.DayNum, (COLUMN() - COLUMN($K$86) + 1) + (ROW() - ROW($K$86)) * 7 - _xlpm.StartDay + 1,IF(AND(_xlpm.DayNum > 0, _xlpm.DayNum <= DAY(EOMONTH(DATE($A90, $B90, 1), 0))), _xlpm.DayNum, "")) -> 28 | N90: =_xlfn.LET(_xlpm.StartDay, WEEKDAY(DATE($A90, $B90, 1), 1),_xlpm.DayNum, (COLUMN() - COLUMN($K$86) + 1) + (ROW() - ROW($K$86)) * 7 - _xlpm.StartDay + 1,IF(AND(_xlpm.DayNum > 0, _xlpm.DayNum <= DAY(EOMONTH(DATE($A90, $B90, 1), 0))), _xlpm.DayNum, "")) -> 29 | O90: =_xlfn.LET(_xlpm.StartDay, WEEKDAY(DATE($A90, $B90, 1), 1),_xlpm.DayNum, (COLUMN() - COLUMN($K$86) + 1) + (ROW() - ROW($K$86)) * 7 - _xlpm.StartDay + 1,IF(AND(_xlpm.DayNum > 0, _xlpm.DayNum <= DAY(EOMONTH(DATE($A90, $B90, 1), 0))), _xlpm.DayNum, "")) -> 30 | P90: =_xlfn.LET(_xlpm.StartDay, WEEKDAY(DATE($A90, $B90, 1), 1),_xlpm.DayNum, (COLUMN() - COLUMN($K$86) + 1) + (ROW() - ROW($K$86)) * 7 - _xlpm.StartDay + 1,IF(AND(_xlpm.DayNum > 0, _xlpm.DayNum <= DAY(EOMONTH(DATE($A90, $B90, 1), 0))), _xlpm.DayNum, "")) -> 31 | Q90: =IF(J90<>1,"ERROR!!!","")
A91: 2028 | B91: 3 | C91: 6 | D91: 1 | E91: 1 | F91: 1 | G91: 1 | H91: 1 | I91: 1 | J91: 1 | K91: =IF(D91<>1,"ERROR!!!","") | L91: =IF(E91<>1,"ERROR!!!","") | M91: =IF(F91<>1,"ERROR!!!","") | N91: =IF(G91<>1,"ERROR!!!","") | O91: =IF(H91<>1,"ERROR!!!","") | P91: =IF(I91<>1,"ERROR!!!","") | Q91: =IF(J91<>1,"ERROR!!!","")
