Workbook
Name Slicer_Budget_Plan: #N/A
Name Slicer_Month: #N/A

Sheet DASHBOARD

Sheet DASHBOARD Light

Sheet Budgeting

Sheet Budgeting Light

Sheet Income

Sheet Income Light

Sheet Expenses

Sheet Expenses Light

Sheet Investments

Sheet Investments Light

Sheet Debts

Sheet Debts Light

Sheet Fin Goals

Sheet Fin Goals Light

Sheet Processing
A1: Month Name | B1: Month | C1: indent | D1: Income | E1: Expenses | F1: indent Cursor | G1: Cursors I | H1: Cursors E | I1: Marker | J1: Label | K1: Income % | L1: Month N | M1: Income | N1: Expenses | O1: X | P1: Y
A2: JANUARY | B2: JAN | C2: =$C$14 -> 1449.24 | D2: =GETPIVOTDATA(""&D$1,Control!$A$20,"Month",""&$A2) -> 18166 | E2: =GETPIVOTDATA(""&E$1,Control!$A$20,"Month",""&$A2) -> 20397 | F2: =C2 -> 1449.24 | G2: =IFERROR(GETPIVOTDATA(""&D$1,Control!$A$3,"Month",""&$A2),NA()) -> #N/A | H2: =IFERROR(GETPIVOTDATA(""&E$1,Control!$A$3,"Month",""&$A2),NA()) -> #N/A | I2: =G2+C2 -> #N/A | J2: =IF(G2>=1000,TEXT(ROUND(G2/1000,0),"0")&"k",G2) -> #N/A | K2: =D2/SUM(D2:E2) -> 0.47107331 | L2: =GETPIVOTDATA("Max of Month N",Control!$A$3) -> 4 | M2: {=INDEX(K2:K13,L2)} -> 0.56579297 | N2: =1-M2 -> 0.43420703 | O2: 0 | P2: 1
A3: FEBRUARY | B3: FEB | C3: =$C$14 -> 1449.24 | D3: =GETPIVOTDATA(""&D$1,Control!$A$20,"Month",""&$A3) -> 19801 | E3: =GETPIVOTDATA(""&E$1,Control!$A$20,"Month",""&$A3) -> 26548 | F3: =C3 -> 1449.24 | G3: =IFERROR(GETPIVOTDATA(""&D$1,Control!$A$3,"Month",""&$A3),NA()) -> #N/A | H3: =IFERROR(GETPIVOTDATA(""&E$1,Control!$A$3,"Month",""&$A3),NA()) -> #N/A | I3: =G3+C3 -> #N/A | J3: =IF(G3>=1000,TEXT(ROUND(G3/1000,0),"0")&"k",G3) -> #N/A | K3: =D3/SUM(D3:E3) -> 0.42721526 | M3: Ratio Income | O3: =SIN(M2*2*PI()) -> -0.40171554 | P3: =COS(N2*2*PI()) -> -0.9157645
A4: MARCH | B4: MAR | C4: =$C$14 -> 1449.24 | D4: =GETPIVOTDATA(""&D$1,Control!$A$20,"Month",""&$A4) -> 22196 | E4: =GETPIVOTDATA(""&E$1,Control!$A$20,"Month",""&$A4) -> 22099 | F4: =C4 -> 1449.24 | G4: =IFERROR(GETPIVOTDATA(""&D$1,Control!$A$3,"Month",""&$A4),NA()) -> #N/A | H4: =IFERROR(GETPIVOTDATA(""&E$1,Control!$A$3,"Month",""&$A4),NA()) -> #N/A | I4: =G4+C4 -> #N/A | J4: =IF(G4>=1000,TEXT(ROUND(G4/1000,0),"0")&"k",G4) -> #N/A | K4: =D4/SUM(D4:E4) -> 0.50109493
A5: APRIL | B5: APR | C5: =$C$14 -> 1449.24 | D5: =GETPIVOTDATA(""&D$1,Control!$A$20,"Month",""&$A5) -> 25558 | E5: =GETPIVOTDATA(""&E$1,Control!$A$20,"Month",""&$A5) -> 19614 | F5: =C5 -> 1449.24 | G5: =IFERROR(GETPIVOTDATA(""&D$1,Control!$A$3,"Month",""&$A5),NA()) -> 25558 | H5: =IFERROR(GETPIVOTDATA(""&E$1,Control!$A$3,"Month",""&$A5),NA()) -> 19614 | I5: =G5+C5 -> 27007.24 | J5: =IF(G5>=1000,TEXT(ROUND(G5/1000,0),"0")&"k",G5) -> 26k | K5: =D5/SUM(D5:E5) -> 0.56579297 | M5: Balance: | N5: =GETPIVOTDATA("Average of Balance",Control!$A$3) -> 4806.6667
A6: MAY | B6: MAY | C6: =$C$14 -> 1449.24 | D6: =GETPIVOTDATA(""&D$1,Control!$A$20,"Month",""&$A6) -> 31043 | E6: =GETPIVOTDATA(""&E$1,Control!$A$20,"Month",""&$A6) -> 24519 | F6: =C6 -> 1449.24 | G6: =IFERROR(GETPIVOTDATA(""&D$1,Control!$A$3,"Month",""&$A6),NA()) -> #N/A | H6: =IFERROR(GETPIVOTDATA(""&E$1,Control!$A$3,"Month",""&$A6),NA()) -> #N/A | I6: =G6+C6 -> #N/A | J6: =IF(G6>=1000,TEXT(ROUND(G6/1000,0),"0")&"k",G6) -> #N/A | K6: =D6/SUM(D6:E6) -> 0.55870919
A7: JUNE | B7: JUN | C7: =$C$14 -> 1449.24 | D7: =GETPIVOTDATA(""&D$1,Control!$A$20,"Month",""&$A7) -> 31211 | E7: =GETPIVOTDATA(""&E$1,Control!$A$20,"Month",""&$A7) -> 24837 | F7: =C7 -> 1449.24 | G7: =IFERROR(GETPIVOTDATA(""&D$1,Control!$A$3,"Month",""&$A7),NA()) -> #N/A | H7: =IFERROR(GETPIVOTDATA(""&E$1,Control!$A$3,"Month",""&$A7),NA()) -> #N/A | I7: =G7+C7 -> #N/A | J7: =IF(G7>=1000,TEXT(ROUND(G7/1000,0),"0")&"k",G7) -> #N/A | K7: =D7/SUM(D7:E7) -> 0.55686198 | M7: Dashboard
A8: JULY | B8: JUL | C8: =$C$14 -> 1449.24 | D8: =GETPIVOTDATA(""&D$1,Control!$A$20,"Month",""&$A8) -> 30268 | E8: =GETPIVOTDATA(""&E$1,Control!$A$20,"Month",""&$A8) -> 21183 | F8: =C8 -> 1449.24 | G8: =IFERROR(GETPIVOTDATA(""&D$1,Control!$A$3,"Month",""&$A8),NA()) -> #N/A | H8: =IFERROR(GETPIVOTDATA(""&E$1,Control!$A$3,"Month",""&$A8),NA()) -> #N/A | I8: =G8+C8 -> #N/A | J8: =IF(G8>=1000,TEXT(ROUND(G8/1000,0),"0")&"k",G8) -> #N/A | K8: =D8/SUM(D8:E8) -> 0.58828789 | M8: Budgeting | N8: =A27 -> 88658
A9: AUGUST | B9: AUG | C9: =$C$14 -> 1449.24 | D9: =GETPIVOTDATA(""&D$1,Control!$A$20,"Month",""&$A9) -> 35419 | E9: =GETPIVOTDATA(""&E$1,Control!$A$20,"Month",""&$A9) -> 22263 | F9: =C9 -> 1449.24 | G9: =IFERROR(GETPIVOTDATA(""&D$1,Control!$A$3,"Month",""&$A9),NA()) -> #N/A | H9: =IFERROR(GETPIVOTDATA(""&E$1,Control!$A$3,"Month",""&$A9),NA()) -> #N/A | I9: =G9+C9 -> #N/A | J9: =IF(G9>=1000,TEXT(ROUND(G9/1000,0),"0")&"k",G9) -> #N/A | K9: =D9/SUM(D9:E9) -> 0.61403904 | M9: Income | N9: =G14 -> 25558
A10: SEPTEMBER | B10: SEP | C10: =$C$14 -> 1449.24 | D10: =GETPIVOTDATA(""&D$1,Control!$A$20,"Month",""&$A10) -> 35296 | E10: =GETPIVOTDATA(""&E$1,Control!$A$20,"Month",""&$A10) -> 25507 | F10: =C10 -> 1449.24 | G10: =IFERROR(GETPIVOTDATA(""&D$1,Control!$A$3,"Month",""&$A10),NA()) -> #N/A | H10: =IFERROR(GETPIVOTDATA(""&E$1,Control!$A$3,"Month",""&$A10),NA()) -> #N/A | I10: =G10+C10 -> #N/A | J10: =IF(G10>=1000,TEXT(ROUND(G10/1000,0),"0")&"k",G10) -> #N/A | K10: =D10/SUM(D10:E10) -> 0.58049767 | M10: Expenses | N10: =H14 -> 19614
A11: OCTOBER | B11: OCT | C11: =$C$14 -> 1449.24 | D11: =GETPIVOTDATA(""&D$1,Control!$A$20,"Month",""&$A11) -> 33397 | E11: =GETPIVOTDATA(""&E$1,Control!$A$20,"Month",""&$A11) -> 20455 | F11: =C11 -> 1449.24 | G11: =IFERROR(GETPIVOTDATA(""&D$1,Control!$A$3,"Month",""&$A11),NA()) -> #N/A | H11: =IFERROR(GETPIVOTDATA(""&E$1,Control!$A$3,"Month",""&$A11),NA()) -> #N/A | I11: =G11+C11 -> #N/A | J11: =IF(G11>=1000,TEXT(ROUND(G11/1000,0),"0")&"k",G11) -> #N/A | K11: =D11/SUM(D11:E11) -> 0.62016267 | M11: Investments | N11: =G22 -> 93339.405
A12: NOVEMBER | B12: NOV | C12: =$C$14 -> 1449.24 | D12: =GETPIVOTDATA(""&D$1,Control!$A$20,"Month",""&$A12) -> 33613 | E12: =GETPIVOTDATA(""&E$1,Control!$A$20,"Month",""&$A12) -> 26772 | F12: =C12 -> 1449.24 | G12: =IFERROR(GETPIVOTDATA(""&D$1,Control!$A$3,"Month",""&$A12),NA()) -> #N/A | H12: =IFERROR(GETPIVOTDATA(""&E$1,Control!$A$3,"Month",""&$A12),NA()) -> #N/A | I12: =G12+C12 -> #N/A | J12: =IF(G12>=1000,TEXT(ROUND(G12/1000,0),"0")&"k",G12) -> #N/A | K12: =D12/SUM(D12:E12) -> 0.55664486 | M12: Debts | N12: =O22 -> 83970.4
A13: DECEMBER | B13: DEC | C13: =$C$14 -> 1449.24 | D13: =GETPIVOTDATA(""&D$1,Control!$A$20,"Month",""&$A13) -> 36231 | E13: =GETPIVOTDATA(""&E$1,Control!$A$20,"Month",""&$A13) -> 24419 | F13: =C13 -> 1449.24 | G13: =IFERROR(GETPIVOTDATA(""&D$1,Control!$A$3,"Month",""&$A13),NA()) -> #N/A | H13: =IFERROR(GETPIVOTDATA(""&E$1,Control!$A$3,"Month",""&$A13),NA()) -> #N/A | I13: =G13+C13 -> #N/A | J13: =IF(G13>=1000,TEXT(ROUND(G13/1000,0),"0")&"k",G13) -> #N/A | K13: =D13/SUM(D13:E13) -> 0.5973784 | M13: Fin Goals | N13: =F31 -> 63894
A14: PERSONAL FINANCE | C14: =MAX(D2:E13)*4% -> 1449.24 | G14: {=SUM(IFERROR(G2:G13,0))} -> 25558 | H14: {=SUM(IFERROR(H2:H13,0))} -> 19614 | I14: =NA() -> #N/A
A16: Budget | B16: =B17-A27 -> 211342 | M16: Total Debt Amount
A17: Budget Plan | B17: 300000 | E17: Budgeting | M17: Debts | N17: Interest Rate | O17: Amount of Debt | P17: =SUM(P18:P21) -> 0.8152466 | Q17: =1-P17 -> 0.1847534
A18: Non-Fixed Incom | B18: =C18/($C$24+$C$25) -> 0.21732489 | C18: =GETPIVOTDATA(""&A18,Control!$A$3) -> 9817 | E18: {=TRANSPOSE(B18:B23)} -> 0.21732489 | F18: 0.26131232 | G18: 0.08715576 | H18: 0.14891968 | I18: 0.22972195 | J18: 0.055565394 | M18: Mortgage | N18: 0.03 | O18: =GETPIVOTDATA(""&M18,Control!$A$3) -> 37633.333 | P18: =O18/SUM($O$22:$O$23) -> 0.36537217
A19: Fixed Incom | B19: =C19/($C$24+$C$25) -> 0.26131232 | C19: =GETPIVOTDATA(""&A19,Control!$A$3) -> 11804 | E19: =E18 -> 0.21732489 | F19: =F18 -> 0.26131232 | G19: =G18 -> 0.08715576 | H19: =H18 -> 0.14891968 | I19: =I18 -> 0.22972195 | J19: =J18 -> 0.055565394 | M19: Credit Card | N19: 0.095 | O19: =GETPIVOTDATA(""&M19,Control!$A$3) -> 21284.6 | P19: =O19/SUM($O$22:$O$23) -> 0.2066466
A20: Other Income | B20: =C20/($C$24+$C$25) -> 0.08715576 | C20: =GETPIVOTDATA(""&A20,Control!$A$3) -> 3937 | D20: =A18&CHAR(10)&A19&CHAR(10)&A20&CHAR(10)&CHAR(10)&CHAR(10)&CHAR(10)&A21&CHAR(10)&A22&CHAR(10)&A23 -> Non-Fixed Incom Fixed Incom Other Income Non-Fixed Cost Fixed Costs Other Cost | E20: =E19 -> 0.21732489 | F20: =F19 -> 0.26131232 | G20: =G19 -> 0.08715576 | H20: =H19 -> 0.14891968 | I20: =I19 -> 0.22972195 | J20: =J19 -> 0.055565394 | M20: Car Leasing | N20: 0.05 | O20: =GETPIVOTDATA(""&M20,Control!$A$3) -> 14791.667 | P20: =O20/SUM($O$22:$O$23) -> 0.14360841
A21: Non-Fixed Cost | B21: =C21/($C$24+$C$25) -> 0.14891968 | C21: =GETPIVOTDATA(""&A21,Control!$A$3) -> 6727 | D21: =TEXT(B18,"0%")&CHAR(10)&TEXT(B19,"0%")&CHAR(10)&TEXT(B20,"0%")&CHAR(10)&CHAR(10)&CHAR(10)&CHAR(10)&TEXT(B21,"0%")&CHAR(10)&TEXT(B22,"0%")&CHAR(10)&TEXT(B23,"0%") -> 22% 26% 9% 15% 23% 6% | M21: Consumer Credit | N21: 0.07 | O21: =GETPIVOTDATA(""&M21,Control!$A$3) -> 10260.8 | P21: =O21/SUM($O$22:$O$23) -> 0.099619417
A22: Fixed Costs | B22: =C22/($C$24+$C$25) -> 0.22972195 | C22: =GETPIVOTDATA(""&A22,Control!$A$3) -> 10377 | D22: =TEXT(C18,"$# ### ###")&CHAR(10)&TEXT(C19,"$# ### ###")&CHAR(10)&TEXT(C20,"$# ### ###")&CHAR(10)&CHAR(10)&CHAR(10)&CHAR(10)&TEXT(C21,"$# ### ###")&CHAR(10)&TEXT(C22,"$# ### ###")&CHAR(10)&TEXT($C23,"$# ### ###") -> $ 9 817 $ 11 804 $ 3 937 $ 6 727 $ 10 377 $ 2 510 | E22: Investments | F22: Invest | G22: =SUM(F23:F27) -> 93339.405 | L22: Label | M22: Total: | N22: Credit Funds | O22: =SUM(O18:O21) -> 83970.4
A23: Other Cost | B23: =C23/($C$24+$C$25) -> 0.055565394 | C23: =GETPIVOTDATA(""&A23,Control!$A$3) -> 2510 | D23: Used Budget | E23: Business | F23: =GETPIVOTDATA($E$22&" "&E23,Control!$A$3) -> 28170.174 | G23: =F23/$G$22 -> 0.30180366 | H23: =G23 -> 0.30180366 | I23: =H23 -> 0.30180366 | J23: =I23 -> 0.30180366 | K23: =J23 -> 0.30180366 | L23: Business | M23: Repayment | N23: Redeemed | O23: =O24-O22 -> 19029.6 | P23: =O23/SUM(O22:O23) -> 0.1847534
A24: Total Incom | B24: =B18+B19+B20 -> 0.56579297 | C24: =C18+C19+C20 -> 25558 | E24: Securities | F24: =GETPIVOTDATA($E$22&" "&E24,Control!$A$3) -> 18431.367 | G24: =F24/$G$22 -> 0.19746608 | H24: =G24 -> 0.19746608 | I24: =H24 -> 0.19746608 | J24: =I24 -> 0.19746608 | K24: =J24 -> 0.19746608 | L24: Securities | N24: Start Debt | O24: =SUM(Data!BG2:'Data'!BJ2) -> 103000
A25: Total Expenses | B25: =B21+B22+B23 -> 0.43420703 | C25: =C21+C22+C23 -> 19614 | E25: Gold | F25: =GETPIVOTDATA($E$22&" "&E25,Control!$A$3) -> 14968.85 | G25: =F25/$G$22 -> 0.16037011 | H25: =G25 -> 0.16037011 | I25: =H25 -> 0.16037011 | J25: =I25 -> 0.16037011 | K25: =J25 -> 0.16037011 | L25: Gold | M25: Total Values | N25: Used Credit Funds
A26: Used Budget | B26: =SUM(E2:INDEX(E2:E13,L2))/B17 -> 0.29552667 | C26: =1-B26 -> 0.70447333 | E26: Real estate | F26: =GETPIVOTDATA($E$22&" "&E26,Control!$A$3) -> 14639.856 | G26: =F26/$G$22 -> 0.1568454 | H26: =G26 -> 0.1568454 | I26: =H26 -> 0.1568454 | J26: =I26 -> 0.1568454 | K26: =J26 -> 0.1568454 | L26: Rent
A27: =B17*B26 -> 88658 | E27: Cryptocurrency | F27: =GETPIVOTDATA($E$22&" "&E27,Control!$A$3) -> 17129.157 | G27: =F27/$G$22 -> 0.18351474 | H27: =G27 -> 0.18351474 | I27: =H27 -> 0.18351474 | J27: =I27 -> 0.18351474 | K27: =J27 -> 0.18351474 | L27: Crypto
G28: 1 | H28: 1 | I28: 1 | J28: 1 | K28: 1
A30: Implementation | B30: Goal 1 | C30: Goal 2 | D30: Goal 3 | E30: Goal 4 | F30: Total
A31: Done | B31: =GETPIVOTDATA(""&B30,Control!$A$3) -> 35764 | C31: =GETPIVOTDATA(""&C30,Control!$A$3) -> 13723 | D31: {=INDEX(Control!$B$36:$E$48,COUNT(Control!$B$36:$B$48)-1,COLUMN(C1))} -> 8643 | E31: {=INDEX(Control!$B$36:$E$48,COUNT(Control!$B$36:$B$48)-1,COLUMN(D1))} -> 5764 | F31: =SUM(B31:E31) -> 63894
A32: Left | B32: =B33-B31 -> 41236 | C32: =C33-C31 -> 51277 | D32: =D33-D31 -> 49357 | E32: =E33-E31 -> 24236 | F32: =SUM(B32:E32) -> 166106
A33: Plan | B33: 77000 | C33: 65000 | D33: 58000 | E33: 30000 | F33: =SUM(B33:E33) -> 230000
A34: Done % | B34: =B31/B33 -> 0.46446753 | C34: =C31/C33 -> 0.21112308 | D34: =D31/D33 -> 0.14901724 | E34: =E31/E33 -> 0.19213333
A35: Goals % | B35: =B33/$B$36 -> 1 | C35: =C33/$B$36 -> 0.84415584 | D35: =D33/$B$36 -> 0.75324675 | E35: =E33/$B$36 -> 0.38961039
A36: MAX Plan | B36: =MAX(B33:E33) -> 77000
B38: Goal 4 | D38: Goal 3 | F38: Goal 2 | H38: Goal 1 | I38: Sectors
A39: Done | B39: {=(100%-SUM(B41:B42))*INDEX($B$34:$E$34,1,B43)} -> 0.056142857 | C39: {=(100%-SUM(C41:C42))*INDEX($B$34:$E$34,1,C43)} -> 0.056142857 | D39: {=(100%-SUM(D41:D42))*INDEX($B$34:$E$34,1,D43)} -> 0.084185065 | E39: {=(100%-SUM(E41:E42))*INDEX($B$34:$E$34,1,E43)} -> 0.084185065 | F39: {=(100%-SUM(F41:F42))*INDEX($B$34:$E$34,1,F43)} -> 0.13366558 | G39: {=(100%-SUM(G41:G42))*INDEX($B$34:$E$34,1,G43)} -> 0.13366558 | H39: {=(100%-SUM(H41:H42))*INDEX($B$34:$E$34,1,H43)} -> 0.34835065 | I39: 0.75
A40: Running | B40: =100%-SUM(B41:B42)-B39 -> 0.23606494 | C40: =100%-SUM(C41:C42)-C39 -> 0.23606494 | D40: =100%-SUM(D41:D42)-D39 -> 0.48075 | E40: =100%-SUM(E41:E42)-E39 -> 0.48075 | F40: =100%-SUM(F41:F42)-F39 -> 0.4994513 | G40: =100%-SUM(G41:G42)-G39 -> 0.4994513 | H40: =100%-SUM(H41:H42)-H39 -> 0.40164935 | I40: 0
A41: Level Goal | B41: {=$I$39*(100%-INDEX($B$35:$E$35,1,B43))} -> 0.45779221 | C41: {=$I$39*(100%-INDEX($B$35:$E$35,1,C43))} -> 0.45779221 | D41: {=$I$39*(100%-INDEX($B$35:$E$35,1,D43))} -> 0.18506494 | E41: {=$I$39*(100%-INDEX($B$35:$E$35,1,E43))} -> 0.18506494 | F41: {=$I$39*(100%-INDEX($B$35:$E$35,1,F43))} -> 0.11688312 | G41: {=$I$39*(100%-INDEX($B$35:$E$35,1,G43))} -> 0.11688312 | H41: {=$I$39*(100%-INDEX($B$35:$E$35,1,H43))} -> 0 | I41: 0
A42: Financial Goals | B42: =$I$42 -> 0.25 | C42: =$I$42 -> 0.25 | D42: =$I$42 -> 0.25 | E42: =$I$42 -> 0.25 | F42: =$I$42 -> 0.25 | G42: =$I$42 -> 0.25 | H42: =$I$42 -> 0.25 | I42: 0.25
A43: =SUM(B31:E32) -> 230000 | B43: 4 | C43: 4 | D43: 3 | E43: 3 | F43: 2 | G43: 2 | H43: 1
I44: Goal Decomposition
A45: Total | B45: Label
A46: =AVERAGE(B34:E34) -> 0.2541853 | B46: =H38&CHAR(10)&F38&CHAR(10)&D38&CHAR(10)&B38 -> Goal 1 Goal 2 Goal 3 Goal 4
C48: =ISNUMBER(MATCH(C49,Control!$A$51:$A$56,0)) -> TRUE | D48: =ISNUMBER(MATCH(D49,Control!$A$51:$A$56,0)) -> FALSE | E48: =ISNUMBER(MATCH(E49,Control!$A$51:$A$56,0)) -> FALSE | F48: =ISNUMBER(MATCH(F49,Control!$A$51:$A$56,0)) -> TRUE | G48: =ISNUMBER(MATCH(G49,Control!$A$51:$A$56,0)) -> FALSE | H48: =ISNUMBER(MATCH(H49,Control!$A$51:$A$56,0)) -> FALSE
A49: Month Name | B49: Month | C49: Non-Fixed Incom | D49: Fixed Incom | E49: Other Income | F49: Non-Fixed Cost | G49: Fixed Costs | H49: Other Cost | I49: Cursor 1 | J49: Cursor 2 | K49: Cursor 3 | L49: Cursor 4 | M49: Cursor 5 | N49: Cursor 6
A50: JANUARY | B50: JAN | C50: =IF(C$48,GETPIVOTDATA(""&C$49,Control!$A$20,"Month",""&$A50),NA()) -> 6659 | D50: =IF(D$48,GETPIVOTDATA(""&D$49,Control!$A$20,"Month",""&$A50),NA()) -> #N/A | E50: =IF(E$48,GETPIVOTDATA(""&E$49,Control!$A$20,"Month",""&$A50),NA()) -> #N/A | F50: =IF(F$48,GETPIVOTDATA(""&F$49,Control!$A$20,"Month",""&$A50),NA()) -> 7456 | G50: =IF(G$48,GETPIVOTDATA(""&G$49,Control!$A$20,"Month",""&$A50),NA()) -> #N/A | H50: =IF(H$48,GETPIVOTDATA(""&H$49,Control!$A$20,"Month",""&$A50),NA()) -> #N/A | I50: =IF(C$48,IFERROR(GETPIVOTDATA(""&C$49,Control!$A$3,"Month",""&$A50),NA()),NA()) -> #N/A | J50: =IF(D$48,IFERROR(GETPIVOTDATA(""&D$49,Control!$A$3,"Month",""&$A50),NA()),NA()) -> #N/A | K50: =IF(E$48,IFERROR(GETPIVOTDATA(""&E$49,Control!$A$3,"Month",""&$A50),NA()),NA()) -> #N/A | L50: =IF(F$48,IFERROR(GETPIVOTDATA(""&F$49,Control!$A$3,"Month",""&$A50),NA()),NA()) -> #N/A | M50: =IF(G$48,IFERROR(GETPIVOTDATA(""&G$49,Control!$A$3,"Month",""&$A50),NA()),NA()) -> #N/A | N50: =IF(H$48,IFERROR(GETPIVOTDATA(""&H$49,Control!$A$3,"Month",""&$A50),NA()),NA()) -> #N/A
A51: FEBRUARY | B51: FEB | C51: =IF(C$48,GETPIVOTDATA(""&C$49,Control!$A$20,"Month",""&$A51),NA()) -> 7061 | D51: =IF(D$48,GETPIVOTDATA(""&D$49,Control!$A$20,"Month",""&$A51),NA()) -> #N/A | E51: =IF(E$48,GETPIVOTDATA(""&E$49,Control!$A$20,"Month",""&$A51),NA()) -> #N/A | F51: =IF(F$48,GETPIVOTDATA(""&F$49,Control!$A$20,"Month",""&$A51),NA()) -> 9714 | G51: =IF(G$48,GETPIVOTDATA(""&G$49,Control!$A$20,"Month",""&$A51),NA()) -> #N/A | H51: =IF(H$48,GETPIVOTDATA(""&H$49,Control!$A$20,"Month",""&$A51),NA()) -> #N/A | I51: =IF(C$48,IFERROR(GETPIVOTDATA(""&C$49,Control!$A$3,"Month",""&$A51),NA()),NA()) -> #N/A | J51: =IF(D$48,IFERROR(GETPIVOTDATA(""&D$49,Control!$A$3,"Month",""&$A51),NA()),NA()) -> #N/A | K51: =IF(E$48,IFERROR(GETPIVOTDATA(""&E$49,Control!$A$3,"Month",""&$A51),NA()),NA()) -> #N/A | L51: =IF(F$48,IFERROR(GETPIVOTDATA(""&F$49,Control!$A$3,"Month",""&$A51),NA()),NA()) -> #N/A | M51: =IF(G$48,IFERROR(GETPIVOTDATA(""&G$49,Control!$A$3,"Month",""&$A51),NA()),NA()) -> #N/A | N51: =IF(H$48,IFERROR(GETPIVOTDATA(""&H$49,Control!$A$3,"Month",""&$A51),NA()),NA()) -> #N/A
A52: MARCH | B52: MAR | C52: =IF(C$48,GETPIVOTDATA(""&C$49,Control!$A$20,"Month",""&$A52),NA()) -> 7857 | D52: =IF(D$48,GETPIVOTDATA(""&D$49,Control!$A$20,"Month",""&$A52),NA()) -> #N/A | E52: =IF(E$48,GETPIVOTDATA(""&E$49,Control!$A$20,"Month",""&$A52),NA()) -> #N/A | F52: =IF(F$48,GETPIVOTDATA(""&F$49,Control!$A$20,"Month",""&$A52),NA()) -> 8658 | G52: =IF(G$48,GETPIVOTDATA(""&G$49,Control!$A$20,"Month",""&$A52),NA()) -> #N/A | H52: =IF(H$48,GETPIVOTDATA(""&H$49,Control!$A$20,"Month",""&$A52),NA()) -> #N/A | I52: =IF(C$48,IFERROR(GETPIVOTDATA(""&C$49,Control!$A$3,"Month",""&$A52),NA()),NA()) -> #N/A | J52: =IF(D$48,IFERROR(GETPIVOTDATA(""&D$49,Control!$A$3,"Month",""&$A52),NA()),NA()) -> #N/A | K52: =IF(E$48,IFERROR(GETPIVOTDATA(""&E$49,Control!$A$3,"Month",""&$A52),NA()),NA()) -> #N/A | L52: =IF(F$48,IFERROR(GETPIVOTDATA(""&F$49,Control!$A$3,"Month",""&$A52),NA()),NA()) -> #N/A | M52: =IF(G$48,IFERROR(GETPIVOTDATA(""&G$49,Control!$A$3,"Month",""&$A52),NA()),NA()) -> #N/A | N52: =IF(H$48,IFERROR(GETPIVOTDATA(""&H$49,Control!$A$3,"Month",""&$A52),NA()),NA()) -> #N/A
A53: APRIL | B53: APR | C53: =IF(C$48,GETPIVOTDATA(""&C$49,Control!$A$20,"Month",""&$A53),NA()) -> 9817 | D53: =IF(D$48,GETPIVOTDATA(""&D$49,Control!$A$20,"Month",""&$A53),NA()) -> #N/A | E53: =IF(E$48,GETPIVOTDATA(""&E$49,Control!$A$20,"Month",""&$A53),NA()) -> #N/A | F53: =IF(F$48,GETPIVOTDATA(""&F$49,Control!$A$20,"Month",""&$A53),NA()) -> 6727 | G53: =IF(G$48,GETPIVOTDATA(""&G$49,Control!$A$20,"Month",""&$A53),NA()) -> #N/A | H53: =IF(H$48,GETPIVOTDATA(""&H$49,Control!$A$20,"Month",""&$A53),NA()) -> #N/A | I53: =IF(C$48,IFERROR(GETPIVOTDATA(""&C$49,Control!$A$3,"Month",""&$A53),NA()),NA()) -> 9817 | J53: =IF(D$48,IFERROR(GETPIVOTDATA(""&D$49,Control!$A$3,"Month",""&$A53),NA()),NA()) -> #N/A | K53: =IF(E$48,IFERROR(GETPIVOTDATA(""&E$49,Control!$A$3,"Month",""&$A53),NA()),NA()) -> #N/A | L53: =IF(F$48,IFERROR(GETPIVOTDATA(""&F$49,Control!$A$3,"Month",""&$A53),NA()),NA()) -> 6727 | M53: =IF(G$48,IFERROR(GETPIVOTDATA(""&G$49,Control!$A$3,"Month",""&$A53),NA()),NA()) -> #N/A | N53: =IF(H$48,IFERROR(GETPIVOTDATA(""&H$49,Control!$A$3,"Month",""&$A53),NA()),NA()) -> #N/A
A54: MAY | B54: MAY | C54: =IF(C$48,GETPIVOTDATA(""&C$49,Control!$A$20,"Month",""&$A54),NA()) -> 10953 | D54: =IF(D$48,GETPIVOTDATA(""&D$49,Control!$A$20,"Month",""&$A54),NA()) -> #N/A | E54: =IF(E$48,GETPIVOTDATA(""&E$49,Control!$A$20,"Month",""&$A54),NA()) -> #N/A | F54: =IF(F$48,GETPIVOTDATA(""&F$49,Control!$A$20,"Month",""&$A54),NA()) -> 9137 | G54: =IF(G$48,GETPIVOTDATA(""&G$49,Control!$A$20,"Month",""&$A54),NA()) -> #N/A | H54: =IF(H$48,GETPIVOTDATA(""&H$49,Control!$A$20,"Month",""&$A54),NA()) -> #N/A | I54: =IF(C$48,IFERROR(GETPIVOTDATA(""&C$49,Control!$A$3,"Month",""&$A54),NA()),NA()) -> #N/A | J54: =IF(D$48,IFERROR(GETPIVOTDATA(""&D$49,Control!$A$3,"Month",""&$A54),NA()),NA()) -> #N/A | K54: =IF(E$48,IFERROR(GETPIVOTDATA(""&E$49,Control!$A$3,"Month",""&$A54),NA()),NA()) -> #N/A | L54: =IF(F$48,IFERROR(GETPIVOTDATA(""&F$49,Control!$A$3,"Month",""&$A54),NA()),NA()) -> #N/A | M54: =IF(G$48,IFERROR(GETPIVOTDATA(""&G$49,Control!$A$3,"Month",""&$A54),NA()),NA()) -> #N/A | N54: =IF(H$48,IFERROR(GETPIVOTDATA(""&H$49,Control!$A$3,"Month",""&$A54),NA()),NA()) -> #N/A
A55: JUNE | B55: JUN | C55: =IF(C$48,GETPIVOTDATA(""&C$49,Control!$A$20,"Month",""&$A55),NA()) -> 11590 | D55: =IF(D$48,GETPIVOTDATA(""&D$49,Control!$A$20,"Month",""&$A55),NA()) -> #N/A | E55: =IF(E$48,GETPIVOTDATA(""&E$49,Control!$A$20,"Month",""&$A55),NA()) -> #N/A | F55: =IF(F$48,GETPIVOTDATA(""&F$49,Control!$A$20,"Month",""&$A55),NA()) -> 9032 | G55: =IF(G$48,GETPIVOTDATA(""&G$49,Control!$A$20,"Month",""&$A55),NA()) -> #N/A | H55: =IF(H$48,GETPIVOTDATA(""&H$49,Control!$A$20,"Month",""&$A55),NA()) -> #N/A | I55: =IF(C$48,IFERROR(GETPIVOTDATA(""&C$49,Control!$A$3,"Month",""&$A55),NA()),NA()) -> #N/A | J55: =IF(D$48,IFERROR(GETPIVOTDATA(""&D$49,Control!$A$3,"Month",""&$A55),NA()),NA()) -> #N/A | K55: =IF(E$48,IFERROR(GETPIVOTDATA(""&E$49,Control!$A$3,"Month",""&$A55),NA()),NA()) -> #N/A | L55: =IF(F$48,IFERROR(GETPIVOTDATA(""&F$49,Control!$A$3,"Month",""&$A55),NA()),NA()) -> #N/A | M55: =IF(G$48,IFERROR(GETPIVOTDATA(""&G$49,Control!$A$3,"Month",""&$A55),NA()),NA()) -> #N/A | N55: =IF(H$48,IFERROR(GETPIVOTDATA(""&H$49,Control!$A$3,"Month",""&$A55),NA()),NA()) -> #N/A
A56: JULY | B56: JUL | C56: =IF(C$48,GETPIVOTDATA(""&C$49,Control!$A$20,"Month",""&$A56),NA()) -> 10675 | D56: =IF(D$48,GETPIVOTDATA(""&D$49,Control!$A$20,"Month",""&$A56),NA()) -> #N/A | E56: =IF(E$48,GETPIVOTDATA(""&E$49,Control!$A$20,"Month",""&$A56),NA()) -> #N/A | F56: =IF(F$48,GETPIVOTDATA(""&F$49,Control!$A$20,"Month",""&$A56),NA()) -> 7342 | G56: =IF(G$48,GETPIVOTDATA(""&G$49,Control!$A$20,"Month",""&$A56),NA()) -> #N/A | H56: =IF(H$48,GETPIVOTDATA(""&H$49,Control!$A$20,"Month",""&$A56),NA()) -> #N/A | I56: =IF(C$48,IFERROR(GETPIVOTDATA(""&C$49,Control!$A$3,"Month",""&$A56),NA()),NA()) -> #N/A | J56: =IF(D$48,IFERROR(GETPIVOTDATA(""&D$49,Control!$A$3,"Month",""&$A56),NA()),NA()) -> #N/A | K56: =IF(E$48,IFERROR(GETPIVOTDATA(""&E$49,Control!$A$3,"Month",""&$A56),NA()),NA()) -> #N/A | L56: =IF(F$48,IFERROR(GETPIVOTDATA(""&F$49,Control!$A$3,"Month",""&$A56),NA()),NA()) -> #N/A | M56: =IF(G$48,IFERROR(GETPIVOTDATA(""&G$49,Control!$A$3,"Month",""&$A56),NA()),NA()) -> #N/A | N56: =IF(H$48,IFERROR(GETPIVOTDATA(""&H$49,Control!$A$3,"Month",""&$A56),NA()),NA()) -> #N/A
A57: AUGUST | B57: AUG | C57: =IF(C$48,GETPIVOTDATA(""&C$49,Control!$A$20,"Month",""&$A57),NA()) -> 11695 | D57: =IF(D$48,GETPIVOTDATA(""&D$49,Control!$A$20,"Month",""&$A57),NA()) -> #N/A | E57: =IF(E$48,GETPIVOTDATA(""&E$49,Control!$A$20,"Month",""&$A57),NA()) -> #N/A | F57: =IF(F$48,GETPIVOTDATA(""&F$49,Control!$A$20,"Month",""&$A57),NA()) -> 8546 | G57: =IF(G$48,GETPIVOTDATA(""&G$49,Control!$A$20,"Month",""&$A57),NA()) -> #N/A | H57: =IF(H$48,GETPIVOTDATA(""&H$49,Control!$A$20,"Month",""&$A57),NA()) -> #N/A | I57: =IF(C$48,IFERROR(GETPIVOTDATA(""&C$49,Control!$A$3,"Month",""&$A57),NA()),NA()) -> #N/A | J57: =IF(D$48,IFERROR(GETPIVOTDATA(""&D$49,Control!$A$3,"Month",""&$A57),NA()),NA()) -> #N/A | K57: =IF(E$48,IFERROR(GETPIVOTDATA(""&E$49,Control!$A$3,"Month",""&$A57),NA()),NA()) -> #N/A | L57: =IF(F$48,IFERROR(GETPIVOTDATA(""&F$49,Control!$A$3,"Month",""&$A57),NA()),NA()) -> #N/A | M57: =IF(G$48,IFERROR(GETPIVOTDATA(""&G$49,Control!$A$3,"Month",""&$A57),NA()),NA()) -> #N/A | N57: =IF(H$48,IFERROR(GETPIVOTDATA(""&H$49,Control!$A$3,"Month",""&$A57),NA()),NA()) -> #N/A
A58: SEPTEMBER | B58: SEP | C58: =IF(C$48,GETPIVOTDATA(""&C$49,Control!$A$20,"Month",""&$A58),NA()) -> 11859 | D58: =IF(D$48,GETPIVOTDATA(""&D$49,Control!$A$20,"Month",""&$A58),NA()) -> #N/A | E58: =IF(E$48,GETPIVOTDATA(""&E$49,Control!$A$20,"Month",""&$A58),NA()) -> #N/A | F58: =IF(F$48,GETPIVOTDATA(""&F$49,Control!$A$20,"Month",""&$A58),NA()) -> 8852 | G58: =IF(G$48,GETPIVOTDATA(""&G$49,Control!$A$20,"Month",""&$A58),NA()) -> #N/A | H58: =IF(H$48,GETPIVOTDATA(""&H$49,Control!$A$20,"Month",""&$A58),NA()) -> #N/A | I58: =IF(C$48,IFERROR(GETPIVOTDATA(""&C$49,Control!$A$3,"Month",""&$A58),NA()),NA()) -> #N/A | J58: =IF(D$48,IFERROR(GETPIVOTDATA(""&D$49,Control!$A$3,"Month",""&$A58),NA()),NA()) -> #N/A | K58: =IF(E$48,IFERROR(GETPIVOTDATA(""&E$49,Control!$A$3,"Month",""&$A58),NA()),NA()) -> #N/A | L58: =IF(F$48,IFERROR(GETPIVOTDATA(""&F$49,Control!$A$3,"Month",""&$A58),NA()),NA()) -> #N/A | M58: =IF(G$48,IFERROR(GETPIVOTDATA(""&G$49,Control!$A$3,"Month",""&$A58),NA()),NA()) -> #N/A | N58: =IF(H$48,IFERROR(GETPIVOTDATA(""&H$49,Control!$A$3,"Month",""&$A58),NA()),NA()) -> #N/A
A59: OCTOBER | B59: OCT | C59: =IF(C$48,GETPIVOTDATA(""&C$49,Control!$A$20,"Month",""&$A59),NA()) -> 12520 | D59: =IF(D$48,GETPIVOTDATA(""&D$49,Control!$A$20,"Month",""&$A59),NA()) -> #N/A | E59: =IF(E$48,GETPIVOTDATA(""&E$49,Control!$A$20,"Month",""&$A59),NA()) -> #N/A | F59: =IF(F$48,GETPIVOTDATA(""&F$49,Control!$A$20,"Month",""&$A59),NA()) -> 6763 | G59: =IF(G$48,GETPIVOTDATA(""&G$49,Control!$A$20,"Month",""&$A59),NA()) -> #N/A | H59: =IF(H$48,GETPIVOTDATA(""&H$49,Control!$A$20,"Month",""&$A59),NA()) -> #N/A | I59: =IF(C$48,IFERROR(GETPIVOTDATA(""&C$49,Control!$A$3,"Month",""&$A59),NA()),NA()) -> #N/A | J59: =IF(D$48,IFERROR(GETPIVOTDATA(""&D$49,Control!$A$3,"Month",""&$A59),NA()),NA()) -> #N/A | K59: =IF(E$48,IFERROR(GETPIVOTDATA(""&E$49,Control!$A$3,"Month",""&$A59),NA()),NA()) -> #N/A | L59: =IF(F$48,IFERROR(GETPIVOTDATA(""&F$49,Control!$A$3,"Month",""&$A59),NA()),NA()) -> #N/A | M59: =IF(G$48,IFERROR(GETPIVOTDATA(""&G$49,Control!$A$3,"Month",""&$A59),NA()),NA()) -> #N/A | N59: =IF(H$48,IFERROR(GETPIVOTDATA(""&H$49,Control!$A$3,"Month",""&$A59),NA()),NA()) -> #N/A
A60: NOVEMBER | B60: NOV | C60: =IF(C$48,GETPIVOTDATA(""&C$49,Control!$A$20,"Month",""&$A60),NA()) -> 12733 | D60: =IF(D$48,GETPIVOTDATA(""&D$49,Control!$A$20,"Month",""&$A60),NA()) -> #N/A | E60: =IF(E$48,GETPIVOTDATA(""&E$49,Control!$A$20,"Month",""&$A60),NA()) -> #N/A | F60: =IF(F$48,GETPIVOTDATA(""&F$49,Control!$A$20,"Month",""&$A60),NA()) -> 9890 | G60: =IF(G$48,GETPIVOTDATA(""&G$49,Control!$A$20,"Month",""&$A60),NA()) -> #N/A | H60: =IF(H$48,GETPIVOTDATA(""&H$49,Control!$A$20,"Month",""&$A60),NA()) -> #N/A | I60: =IF(C$48,IFERROR(GETPIVOTDATA(""&C$49,Control!$A$3,"Month",""&$A60),NA()),NA()) -> #N/A | J60: =IF(D$48,IFERROR(GETPIVOTDATA(""&D$49,Control!$A$3,"Month",""&$A60),NA()),NA()) -> #N/A | K60: =IF(E$48,IFERROR(GETPIVOTDATA(""&E$49,Control!$A$3,"Month",""&$A60),NA()),NA()) -> #N/A | L60: =IF(F$48,IFERROR(GETPIVOTDATA(""&F$49,Control!$A$3,"Month",""&$A60),NA()),NA()) -> #N/A | M60: =IF(G$48,IFERROR(GETPIVOTDATA(""&G$49,Control!$A$3,"Month",""&$A60),NA()),NA()) -> #N/A | N60: =IF(H$48,IFERROR(GETPIVOTDATA(""&H$49,Control!$A$3,"Month",""&$A60),NA()),NA()) -> #N/A
A61: DECEMBER | B61: DEC | C61: =IF(C$48,GETPIVOTDATA(""&C$49,Control!$A$20,"Month",""&$A61),NA()) -> 12742 | D61: =IF(D$48,GETPIVOTDATA(""&D$49,Control!$A$20,"Month",""&$A61),NA()) -> #N/A | E61: =IF(E$48,GETPIVOTDATA(""&E$49,Control!$A$20,"Month",""&$A61),NA()) -> #N/A | F61: =IF(F$48,GETPIVOTDATA(""&F$49,Control!$A$20,"Month",""&$A61),NA()) -> 8743 | G61: =IF(G$48,GETPIVOTDATA(""&G$49,Control!$A$20,"Month",""&$A61),NA()) -> #N/A | H61: =IF(H$48,GETPIVOTDATA(""&H$49,Control!$A$20,"Month",""&$A61),NA()) -> #N/A | I61: =IF(C$48,IFERROR(GETPIVOTDATA(""&C$49,Control!$A$3,"Month",""&$A61),NA()),NA()) -> #N/A | J61: =IF(D$48,IFERROR(GETPIVOTDATA(""&D$49,Control!$A$3,"Month",""&$A61),NA()),NA()) -> #N/A | K61: =IF(E$48,IFERROR(GETPIVOTDATA(""&E$49,Control!$A$3,"Month",""&$A61),NA()),NA()) -> #N/A | L61: =IF(F$48,IFERROR(GETPIVOTDATA(""&F$49,Control!$A$3,"Month",""&$A61),NA()),NA()) -> #N/A | M61: =IF(G$48,IFERROR(GETPIVOTDATA(""&G$49,Control!$A$3,"Month",""&$A61),NA()),NA()) -> #N/A | N61: =IF(H$48,IFERROR(GETPIVOTDATA(""&H$49,Control!$A$3,"Month",""&$A61),NA()),NA()) -> #N/A
B64: Income Type
B65: Business | C65: Securities | D65: Gold | E65: Real estate | F65: Cryptocurrency | G65: Total
A66: Fixed Incom | B66: =GETPIVOTDATA(""&$A66&" "&B$65,Control!$A$3) -> 6994 | C66: =GETPIVOTDATA(""&$A66&" "&C$65,Control!$A$3) -> 3362 | D66: =GETPIVOTDATA(""&$A66&" "&D$65,Control!$A$3) -> 1383 | E66: =GETPIVOTDATA(""&$A66&" "&E$65,Control!$A$3) -> 1861 | F66: =GETPIVOTDATA(""&$A66&" "&F$65,Control!$A$3) -> 910 | G66: =SUM(B66:F66) -> 14510 | I66: https://exceltable.com/
A67: Non-Fixed Incom | B67: =GETPIVOTDATA(""&$A67&" "&B$65,Control!$A$3) -> 3951 | C67: =GETPIVOTDATA(""&$A67&" "&C$65,Control!$A$3) -> 1820 | D67: =GETPIVOTDATA(""&$A67&" "&D$65,Control!$A$3) -> 1054 | E67: =GETPIVOTDATA(""&$A67&" "&E$65,Control!$A$3) -> 966 | F67: =GETPIVOTDATA(""&$A67&" "&F$65,Control!$A$3) -> 3257 | G67: =SUM(B67:F67) -> 11048
A68: Income Share | B68: =SUM(B66:B67) -> 10945 | C68: =SUM(C66:C67) -> 5182 | D68: =SUM(D66:D67) -> 2437 | E68: =SUM(E66:E67) -> 2827 | F68: =SUM(F66:F67) -> 4167 | G68: =SUM(G66:G67) -> 25558
A69: Income Ranking
A70: Business | B70: =INDEX($B$68:$F$68,1,MATCH(A70,$B$65:$F$65,0)) -> 10945 | C70: {=_xlfn._xlws.SORT($A$70:$B$74,2,-1)} -> Business | D70: 10945
A71: Securities | B71: =INDEX($B$68:$F$68,1,MATCH(A71,$B$65:$F$65,0)) -> 5182 | C71: Securities | D71: 5182
A72: Gold | B72: =INDEX($B$68:$F$68,1,MATCH(A72,$B$65:$F$65,0)) -> 2437 | C72: Cryptocurrency | D72: 4167
A73: Real estate | B73: =INDEX($B$68:$F$68,1,MATCH(A73,$B$65:$F$65,0)) -> 2827 | C73: Real estate | D73: 2827
A74: Cryptocurrency | B74: =INDEX($B$68:$F$68,1,MATCH(A74,$B$65:$F$65,0)) -> 4167 | C74: Gold | D74: 2437
B76: Expenses | C76: Non-Fixed Cost | F76: All Expenses
A77: Non-Fixed Cost | B77: Rest | C77: Holidays | D77: =GETPIVOTDATA(""&C77,Control!$A$3) -> 1600 | E77: Non-Fixed Cost | F77: {=_xlfn._xlws.SORT($C$77:$D$107,2,-1)} -> Loans | G77: 1762 | I77: Rest | J77: {=_xlfn._xlws.SORT($C$77:$D$83,2,-1)} -> Holidays | K77: 1600
C78: Excursions | D78: =GETPIVOTDATA(""&C78,Control!$A$3) -> 362 | F78: Food | G78: 1612 | J78: Restaurants | K78: 1175
C79: Restaurants | D79: =GETPIVOTDATA(""&C79,Control!$A$3) -> 1175 | F79: Holidays | G79: 1600 | J79: Snacks on the way | K79: 665
C80: Hotels | D80: =GETPIVOTDATA(""&C80,Control!$A$3) -> 611 | F80: Hairdresser | G80: 1477 | J80: Hotels | K80: 611
C81: Bags, packages, boxes | D81: =GETPIVOTDATA(""&C81,Control!$A$3) -> 122 | F81: Utility Payments | G81: 1401 | J81: Excursions | K81: 362
C82: Snacks on the way | D82: =GETPIVOTDATA(""&C82,Control!$A$3) -> 665 | F82: Restaurants | G82: 1175 | J82: Alcohol | K82: 344
C83: Alcohol | D83: =GETPIVOTDATA(""&C83,Control!$A$3) -> 344 | F83: Travel public transport | G83: 1014 | J83: Bags, packages, boxes | K83: 122
B84: Other | C84: Hobby | D84: =GETPIVOTDATA(""&C84,Control!$A$3) -> 475 | F84: Furniture & utensils | G84: 820 | I84: Other | J84: {=_xlfn._xlws.SORT(C84:D85,2,-1)} -> Unexpected expenses | K84: 599
C85: Unexpected expenses | D85: =GETPIVOTDATA(""&C85,Control!$A$3) -> 599 | F85: Cosmetics & perfum | G85: 790 | J85: Hobby | K85: 475
A86: Fixed Costs | B86: Business | C86: Loans | D86: =GETPIVOTDATA(""&C86,Control!$A$3) -> 1762 | E86: Fixed Costs | F86: Snacks on the way | G86: 665 | I86: Business | J86: {=_xlfn._xlws.SORT($C$86:$D$89,2,-1)} -> Loans | K86: 1762
C87: Training courses | D87: =GETPIVOTDATA(""&C87,Control!$A$3) -> 317 | F87: Fuel | G87: 631 | J87: Travel public transport | K87: 1014
C88: Travel public transport | D88: =GETPIVOTDATA(""&C88,Control!$A$3) -> 1014 | F88: Clothing & footwear | G88: 618 | J88: Training courses | K88: 317
C89: Mobile connection | D89: =GETPIVOTDATA(""&C89,Control!$A$3) -> 279 | F89: Hotels | G89: 611 | J89: Mobile connection | K89: 279
B90: Home | C90: Food | D90: =GETPIVOTDATA(""&C90,Control!$A$3) -> 1612 | F90: Unexpected expenses | G90: 599 | I90: Home | J90: {=_xlfn._xlws.SORT($C$90:$D$96,2,-1)} -> Food | K90: 1612
C91: Utility Payments | D91: =GETPIVOTDATA(""&C91,Control!$A$3) -> 1401 | F91: Insurance | G91: 498 | J91: Utility Payments | K91: 1401
C92: Internet & TV | D92: =GETPIVOTDATA(""&C92,Control!$A$3) -> 244 | F92: Hobby | G92: 475 | J92: Furniture & utensils | K92: 820
C93: Household chemicals | D93: =GETPIVOTDATA(""&C93,Control!$A$3) -> 252 | F93: Washing | G93: 430 | J93: BedLinen & tablecloth | K93: 288
C94: Furniture & utensils | D94: =GETPIVOTDATA(""&C94,Control!$A$3) -> 820 | F94: Excursions | G94: 362 | J94: Household chemicals | K94: 252
C95: BedLinen & tablecloth | D95: =GETPIVOTDATA(""&C95,Control!$A$3) -> 288 | F95: Alcohol | G95: 344 | J95: Internet & TV | K95: 244
C96: Cat food | D96: =GETPIVOTDATA(""&C96,Control!$A$3) -> 77 | F96: Training courses | G96: 317 | J96: Cat food | K96: 77
B97: Image | C97: Clothing & footwear | D97: =GETPIVOTDATA(""&C97,Control!$A$3) -> 618 | F97: BedLinen & tablecloth | G97: 288 | I97: Image | J97: {=_xlfn._xlws.SORT($C$97:$D$102,2,-1)} -> Hairdresser | K97: 1477
C98: Gym | D98: =GETPIVOTDATA(""&C98,Control!$A$3) -> 281 | F98: Gym | G98: 281 | J98: Cosmetics & perfum | K98: 790
C99: Hygiene products | D99: =GETPIVOTDATA(""&C99,Control!$A$3) -> 267 | F99: Mobile connection | G99: 279 | J99: Clothing & footwear | K99: 618
C100: Medications | D100: =GETPIVOTDATA(""&C100,Control!$A$3) -> 277 | F100: Medications | G100: 277 | J100: Gym | K100: 281
C101: Hairdresser | D101: =GETPIVOTDATA(""&C101,Control!$A$3) -> 1477 | F101: Hygiene products | G101: 267 | J101: Medications | K101: 277
C102: Cosmetics & perfum | D102: =GETPIVOTDATA(""&C102,Control!$A$3) -> 790 | F102: Household chemicals | G102: 252 | J102: Hygiene products | K102: 267
B103: Car | C103: Fuel | D103: =GETPIVOTDATA(""&C103,Control!$A$3) -> 631 | F103: Internet & TV | G103: 244 | I103: Car | J103: {=_xlfn._xlws.SORT($C$103:$D$107,2,-1)} -> Fuel | K103: 631
C104: Spare parts | D104: =GETPIVOTDATA(""&C104,Control!$A$3) -> 222 | F104: Spare parts | G104: 222 | J104: Insurance | K104: 498
C105: Parking | D105: =GETPIVOTDATA(""&C105,Control!$A$3) -> 104 | F105: Bags, packages, boxes | G105: 122 | J105: Washing | K105: 430
C106: Washing | D106: =GETPIVOTDATA(""&C106,Control!$A$3) -> 430 | F106: Parking | G106: 104 | J106: Spare parts | K106: 222
C107: Insurance | D107: =GETPIVOTDATA(""&C107,Control!$A$3) -> 498 | F107: Cat food | G107: 77 | J107: Parking | K107: 104
...

Sheet Control
A3: Row Labels | B3: Max of Month N | C3: Sum of Income | D3: Sum of Expenses | E3: Sum of Non-Fixed Incom | F3: Sum of Fixed Incom | G3: Sum of Other Income | H3: Sum of Non-Fixed Cost | I3: Sum of Fixed Costs | J3: Sum of Other Cost | K3: Average of Investments Business | L3: Average of Investments Securities | M3: Average of Investments Cryptocurrency | N3: Average of Investments Real estate | O3: Average of Investments Gold | P3: Average of Mortgage | Q3: Average of Car Leasing | R3: Average of Consumer Credit | S3: Average of Credit Card | T3: Sum of Fixed Incom Business | U3: Sum of Fixed Incom Securities | V3: Sum of Fixed Incom Real estate | W3: Sum of Fixed Incom Gold | X3: Sum of Fixed Incom Cryptocurrency | Y3: Sum of Non-Fixed Incom Business | Z3: Sum of Non-Fixed Incom Securities | AA3: Sum of Non-Fixed Incom Real estate | AB3: Sum of Non-Fixed Incom Gold | AC3: Sum of Non-Fixed Incom Cryptocurrency | AD3: Sum of Loans | AE3: Sum of Training courses | AF3: Sum of Travel public transport | AG3: Sum of Mobile connection | AH3: Sum of Food | AI3: Sum of Utility Payments | AJ3: Sum of Internet & TV | AK3: Sum of Household chemicals | AL3: Sum of Furniture & utensils | AM3: Sum of BedLinen & tablecloth | AN3: Sum of Cat food | AO3: Sum of Clothing & footwear | AP3: Sum of Gym | AQ3: Sum of Hygiene products | AR3: Sum of Medications | AS3: Sum of Hairdresser | AT3: Sum of Cosmetics & perfum | AU3: Sum of Fuel | AV3: Sum of Spare parts | AW3: Sum of Parking | AX3: Sum of Washing | AY3: Sum of Insurance | AZ3: Sum of Holidays | BA3: Sum of Excursions | BB3: Sum of Restaurants | BC3: Sum of Hotels | BD3: Sum of Bags, packages, boxes | BE3: Sum of Snacks on the way | BF3: Sum of Alcohol | BG3: Sum of Hobby | BH3: Sum of Unexpected expenses | BI3: Sum of Price Investments Portfolio | BJ3: Average of Balance | BK3: Average of Goal 1 | BL3: Average of Goal 2 | BM3: Average of Goal 3 | BN3: Average of Goal 4
A4: APRIL | B4: 4 | C4: 25558 | D4: 19614 | E4: 9817 | F4: 11804 | G4: 3937 | H4: 6727 | I4: 10377 | J4: 2510 | K4: 28170.174 | L4: 18431.367 | M4: 17129.157 | N4: 14639.856 | O4: 14968.85 | P4: 37633.333 | Q4: 14791.667 | R4: 10260.8 | S4: 21284.6 | T4: 6994 | U4: 3362 | V4: 1861 | W4: 1383 | X4: 910 | Y4: 3951 | Z4: 1820 | AA4: 966 | AB4: 1054 | AC4: 3257 | AD4: 1762 | AE4: 317 | AF4: 1014 | AG4: 279 | AH4: 1612 | AI4: 1401 | AJ4: 244 | AK4: 252 | AL4: 820 | AM4: 288 | AN4: 77 | AO4: 618 | AP4: 281 | AQ4: 267 | AR4: 277 | AS4: 1477 | AT4: 790 | AU4: 631 | AV4: 222 | AW4: 104 | AX4: 430 | AY4: 498 | AZ4: 1600 | BA4: 362 | BB4: 1175 | BC4: 611 | BD4: 122 | BE4: 665 | BF4: 344 | BG4: 475 | BH4: 599 | BI4: 2745.24 | BJ4: 4806.6667 | BK4: 35764 | BL4: 13723 | BM4: 8643 | BN4: 5764
A5: Grand Total | B5: 4 | C5: 25558 | D5: 19614 | E5: 9817 | F5: 11804 | G5: 3937 | H5: 6727 | I5: 10377 | J5: 2510 | K5: 28170.174 | L5: 18431.367 | M5: 17129.157 | N5: 14639.856 | O5: 14968.85 | P5: 37633.333 | Q5: 14791.667 | R5: 10260.8 | S5: 21284.6 | T5: 6994 | U5: 3362 | V5: 1861 | W5: 1383 | X5: 910 | Y5: 3951 | Z5: 1820 | AA5: 966 | AB5: 1054 | AC5: 3257 | AD5: 1762 | AE5: 317 | AF5: 1014 | AG5: 279 | AH5: 1612 | AI5: 1401 | AJ5: 244 | AK5: 252 | AL5: 820 | AM5: 288 | AN5: 77 | AO5: 618 | AP5: 281 | AQ5: 267 | AR5: 277 | AS5: 1477 | AT5: 790 | AU5: 631 | AV5: 222 | AW5: 104 | AX5: 430 | AY5: 498 | AZ5: 1600 | BA5: 362 | BB5: 1175 | BC5: 611 | BD5: 122 | BE5: 665 | BF5: 344 | BG5: 475 | BH5: 599 | BI5: 2745.24 | BJ5: 4806.6667 | BK5: 35764 | BL5: 13723 | BM5: 8643 | BN5: 5764
A20: Row Labels | B20: Sum of Income | C20: Sum of Expenses | D20: Sum of Non-Fixed Incom | E20: Sum of Fixed Incom | F20: Sum of Other Income | G20: Sum of Non-Fixed Cost | H20: Sum of Fixed Costs | I20: Sum of Other Cost | J20: Sum of Price Investments Portfolio | K20: Average of Goal 1 | L20: Average of Goal 2 | M20: Average of Goal 3 | N20: Average of Goal 4
A21: JANUARY | B21: 18166 | C21: 20397 | D21: 6659 | E21: 8992 | F21: 2515 | G21: 7456 | H21: 9847 | I21: 3094 | J21: 3300.57 | K21: 11891 | L21: 3480 | M21: 4930 | N21: 1741
A22: FEBRUARY | B22: 19801 | C22: 26548 | D22: 7061 | E22: 9806 | F22: 2934 | G22: 9714 | H22: 12628 | I22: 4206 | J22: 4376.56 | K22: 22162 | L22: 5741 | M22: 5321 | N22: 1902
A23: MARCH | B23: 22196 | C23: 22099 | D23: 7857 | E23: 11024 | F23: 3315 | G23: 8658 | H23: 10469 | I23: 2972 | J23: 3927.71 | K23: 30623 | L23: 8722 | M23: 6172 | N23: 2143
A24: APRIL | B24: 25558 | C24: 19614 | D24: 9817 | E24: 11804 | F24: 3937 | G24: 6727 | H24: 10377 | I24: 2510 | J24: 2745.24 | K24: 35764 | L24: 13723 | M24: 8643 | N24: 5764
A25: MAY | B25: 31043 | C25: 24519 | D25: 10953 | E25: 15158 | F25: 4932 | G25: 9137 | H25: 11921 | I25: 3461 | J25: 1954.4 | K25: 41565 | L25: 18624 | M25: 12724 | N25: 9545
A26: JUNE | B26: 31211 | C26: 24837 | D26: 11590 | E26: 15003 | F26: 4618 | G26: 9032 | H26: 12075 | I26: 3730 | J26: 3169.63 | K26: 48286 | L26: 22765 | M26: 21425 | N26: 11977
A27: JULY | B27: 30268 | C27: 21183 | D27: 10675 | E27: 14573 | F27: 5020 | G27: 7342 | H27: 10596 | I27: 3245 | J27: 2648.96 | K27: 49237 | L27: 30576 | M27: 23946 | N27: 13866
A28: AUGUST | B28: 35419 | C28: 22263 | D28: 11695 | E28: 18781 | F28: 4943 | G28: 8546 | H28: 10831 | I28: 2886 | J28: 3087.44 | K28: 51528 | L28: 40447 | M28: 28127 | N28: 18319
A29: SEPTEMBER | B29: 35296 | C29: 25507 | D29: 11859 | E29: 17735 | F29: 5702 | G29: 8852 | H29: 12996 | I29: 3659 | J29: 3593.72 | K29: 60889 | L29: 47668 | M29: 34859 | N29: 23168
A30: OCTOBER | B30: 33397 | C30: 20455 | D30: 12520 | E30: 15792 | F30: 5085 | G30: 6763 | H30: 10404 | I30: 3288 | J30: 2705.824 | K30: 64151 | L30: 49709 | M30: 39758 | N30: 24250
A31: NOVEMBER | B31: 33613 | C31: 26772 | D31: 12733 | E31: 16452 | F31: 4428 | G31: 9890 | H31: 12770 | I31: 4112 | J31: 3819.53 | K31: 70082 | L31: 53709 | M31: 45010 | N31: 28681
A32: DECEMBER | B32: 36231 | C32: 24419 | D32: 12742 | E32: 18313 | F32: 5176 | G32: 8743 | H32: 12115 | I32: 3561 | J32: 6230.507 | K32: 75603 | L32: 63201 | M32: 55501 | N32: 30000
A33: Grand Total | B33: 352199 | C33: 278613 | D33: 126161 | E33: 173433 | F33: 52605 | G33: 100860 | H33: 137029 | I33: 40724 | J33: 41560.091 | K33: 46873.951 | L33: 29945.268 | M33: 23929.828 | N33: 14313.23
A35: Row Labels | B35: Average of Goal 1 | C35: Average of Goal 2 | D35: Average of Goal 3 | E35: Average of Goal 4
A36: APRIL | B36: 35764 | C36: 13723 | D36: 8643 | E36: 5764
A37: Grand Total | B37: 35764 | C37: 13723 | D37: 8643 | E37: 5764
A50: Row Labels
A51: Non-Fixed Cost
A52: Non-Fixed Incom
A53: Grand Total

Sheet Data
A1: Date | B1: Month | C1: Month N | D1: Income | E1: Expenses | F1: Non-Fixed Incom | G1: Fixed Incom | H1: Other Income | I1: Non-Fixed Cost | J1: Fixed Costs | K1: Other Cost | L1: Fixed Incom Business | M1: Fixed Incom Securities | N1: Fixed Incom Real estate | O1: Fixed Incom Gold | P1: Fixed Incom Cryptocurrency | Q1: Non-Fixed Incom Business | R1: Non-Fixed Incom Securities | S1: Non-Fixed Incom Real estate | T1: Non-Fixed Incom Gold | U1: Non-Fixed Incom Cryptocurrency | V1: Loans | W1: Training courses | X1: Travel public transport | Y1: Mobile connection | Z1: Food | AA1: Utility Payments | AB1: Internet & TV | AC1: Household chemicals | AD1: Furniture & utensils | AE1: BedLinen & tablecloth | AF1: Cat food | AG1: Clothing & footwear | AH1: Gym | AI1: Hygiene products | AJ1: Medications | AK1: Hairdresser | AL1: Cosmetics & perfum | AM1: Fuel | AN1: Spare parts | AO1: Parking | AP1: Washing | AQ1: Insurance | AR1: Holidays | AS1: Excursions | AT1: Restaurants | AU1: Hotels | AV1: Bags, packages, boxes | AW1: Snacks on the way | AX1: Alcohol | AY1: Hobby | AZ1: Unexpected expenses | BA1: Price Investments Portfolio | BB1: Investments Business | BC1: Investments Securities | BD1: Investments Cryptocurrency | BE1: Investments Real estate | BF1: Investments Gold | BG1: Mortgage | BH1: Car Leasing | BI1: Consumer Credit | BJ1: Credit Card | BK1: Goal 1 | BL1: Goal 2 | BM1: Goal 3 | BN1: Goal 4 | BO1: Monthly Plan | BP1: Balance
A2: 45292 | B2: =CHOOSE(C2, "JANUARY", "FEBRUARY", "MARCH", "APRIL", "MAY", "JUNE", "JULY", "AUGUST", "SEPTEMBER", "OCTOBER", "NOVEMBER", "DECEMBER") -> JANUARY | C2: =MONTH(mydata[[#This Row],[Date]]) -> 1 | D2: 496 | E2: 575 | F2: 243 | G2: 189 | H2: 64 | I2: 172 | J2: 271 | K2: 132 | L2: 104 | M2: 58 | N2: 27 | O2: 46 | P2: 9 | Q2: 82 | R2: 62 | S2: 22 | T2: 24 | U2: 62 | V2: 46 | W2: 0 | X2: 23 | Y2: 11 | Z2: 34 | AA2: 34 | AB2: 11 | AC2: 5 | AD2: 28 | AE2: 0 | AF2: 0 | AG2: 5 | AH2: 5 | AI2: 17 | AJ2: 17 | AK2: 23 | AL2: 34 | AM2: 11 | AN2: 17 | AO2: 0 | AP2: 0 | AQ2: 17 | AR2: 51 | AS2: 5 | AT2: 17 | AU2: 11 | AV2: 5 | AW2: 17 | AX2: 0 | AY2: 17 | AZ2: 114 | BA2: 0 | BB2: 0 | BC2: 0 | BD2: 0 | BE2: 0 | BF2: 0 | BG2: 50000 | BH2: 20000 | BI2: 8000 | BJ2: 25000 | BK2: 11891 | BL2: 3480 | BM2: 4930 | BN2: 1741 | BO2: 29000 | BP2: 3796
A3: 45293 | B3: =CHOOSE(C3, "JANUARY", "FEBRUARY", "MARCH", "APRIL", "MAY", "JUNE", "JULY", "AUGUST", "SEPTEMBER", "OCTOBER", "NOVEMBER", "DECEMBER") -> JANUARY | C3: =MONTH(mydata[[#This Row],[Date]]) -> 1 | D3: 516 | E3: 585 | F3: 268 | G3: 218 | H3: 30 | I3: 286 | J3: 259 | K3: 40 | L3: 118 | M3: 19 | N3: 38 | O3: 19 | P3: 6 | Q3: 88 | R3: 27 | S3: 19 | T3: 29 | U3: 153 | V3: 76 | W3: 17 | X3: 29 | Y3: 0 | Z3: 46 | AA3: 29 | AB3: 0 | AC3: 17 | AD3: 29 | AE3: 11 | AF3: 5 | AG3: 23 | AH3: 11 | AI3: 0 | AJ3: 0 | AK3: 23 | AL3: 23 | AM3: 5 | AN3: 11 | AO3: 5 | AP3: 17 | AQ3: 17 | AR3: 64 | AS3: 17 | AT3: 40 | AU3: 29 | AV3: 0 | AW3: 23 | AX3: 11 | AY3: 5 | AZ3: 2 | BA3: 0 | BB3: 0 | BC3: 0 | BD3: 0 | BE3: 0 | BF3: 0 | BG3: 50000 | BH3: 20000 | BI3: 8000 | BJ3: 25000 | BK3: 11891 | BL3: 3480 | BM3: 4930 | BN3: 1741 | BO3: 29000 | BP3: 4881
A4: 45294 | B4: =CHOOSE(C4, "JANUARY", "FEBRUARY", "MARCH", "APRIL", "MAY", "JUNE", "JULY", "AUGUST", "SEPTEMBER", "OCTOBER", "NOVEMBER", "DECEMBER") -> JANUARY | C4: =MONTH(mydata[[#This Row],[Date]]) -> 1 | D4: 539 | E4: 610 | F4: 285 | G4: 131 | H4: 123 | I4: 244 | J4: 318 | K4: 48 | L4: 177 | M4: 106 | N4: 23 | O4: 16 | P4: 20 | Q4: 83 | R4: 18 | S4: 28 | T4: 28 | U4: 40 | V4: 61 | W4: 6 | X4: 36 | Y4: 6 | Z4: 61 | AA4: 48 | AB4: 0 | AC4: 18 | AD4: 36 | AE4: 6 | AF4: 6 | AG4: 24 | AH4: 12 | AI4: 12 | AJ4: 12 | AK4: 54 | AL4: 30 | AM4: 30 | AN4: 18 | AO4: 6 | AP4: 6 | AQ4: 24 | AR4: 0 | AS4: 18 | AT4: 14 | AU4: 24 | AV4: 0 | AW4: 30 | AX4: 12 | AY4: 0 | AZ4: 0 | BA4: 0 | BB4: 0 | BC4: 0 | BD4: 0 | BE4: 0 | BF4: 0 | BG4: 50000 | BH4: 20000 | BI4: 8000 | BJ4: 25000 | BK4: 11891 | BL4: 3480 | BM4: 4930 | BN4: 1741 | BO4: 29000 | BP4: 4766
A5: 45295 | B5: =CHOOSE(C5, "JANUARY", "FEBRUARY", "MARCH", "APRIL", "MAY", "JUNE", "JULY", "AUGUST", "SEPTEMBER", "OCTOBER", "NOVEMBER", "DECEMBER") -> JANUARY | C5: =MONTH(mydata[[#This Row],[Date]]) -> 1 | D5: 557 | E5: 641 | F5: 150 | G5: 307 | H5: 100 | I5: 262 | J5: 219 | K5: 160 | L5: 176 | M5: 69 | N5: 31 | O5: 24 | P5: 31 | Q5: 103 | R5: 52 | S5: 27 | T5: 29 | U5: 15 | V5: 44 | W5: 12 | X5: 38 | Y5: 6 | Z5: 44 | AA5: 57 | AB5: 19 | AC5: 0 | AD5: 38 | AE5: 6 | AF5: 0 | AG5: 19 | AH5: 19 | AI5: 19 | AJ5: 0 | AK5: 38 | AL5: 19 | AM5: 32 | AN5: 12 | AO5: 6 | AP5: 12 | AQ5: 6 | AR5: 57 | AS5: 19 | AT5: 25 | AU5: 19 | AV5: 6 | AW5: 19 | AX5: 19 | AY5: 19 | AZ5: 12 | BA5: 0 | BB5: 0 | BC5: 0 | BD5: 0 | BE5: 0 | BF5: 0 | BG5: 50000 | BH5: 20000 | BI5: 8000 | BJ5: 25000 | BK5: 11891 | BL5: 3480 | BM5: 4930 | BN5: 1741 | BO5: 29000 | BP5: 788
A6: 45296 | B6: =CHOOSE(C6, "JANUARY", "FEBRUARY", "MARCH", "APRIL", "MAY", "JUNE", "JULY", "AUGUST", "SEPTEMBER", "OCTOBER", "NOVEMBER", "DECEMBER") -> JANUARY | C6: =MONTH(mydata[[#This Row],[Date]]) -> 1 | D6: 575 | E6: 667 | F6: 132 | G6: 415 | H6: 28 | I6: 153 | J6: 374 | K6: 140 | L6: 171 | M6: 99 | N6: 42 | O6: 35 | P6: 21 | Q6: 93 | R6: 43 | S6: 24 | T6: 21 | U6: 26 | V6: 60 | W6: 0 | X6: 46 | Y6: 20 | Z6: 93 | AA6: 53 | AB6: 20 | AC6: 0 | AD6: 13 | AE6: 20 | AF6: 0 | AG6: 6 | AH6: 13 | AI6: 0 | AJ6: 0 | AK6: 26 | AL6: 46 | AM6: 13 | AN6: 0 | AO6: 0 | AP6: 26 | AQ6: 20 | AR6: 73 | AS6: 6 | AT6: 20 | AU6: 20 | AV6: 0 | AW6: 26 | AX6: 0 | AY6: 20 | AZ6: 27 | BA6: 104.1755 | BB6: 0 | BC6: 0 | BD6: 0 | BE6: 0 | BF6: 0 | BG6: 50000 | BH6: 20000 | BI6: 8000 | BJ6: 23668 | BK6: 11891 | BL6: 3480 | BM6: 4930 | BN6: 1741 | BO6: 29000 | BP6: 4853
A7: 45297 | B7: =CHOOSE(C7, "JANUARY", "FEBRUARY", "MARCH", "APRIL", "MAY", "JUNE", "JULY", "AUGUST", "SEPTEMBER", "OCTOBER", "NOVEMBER", "DECEMBER") -> JANUARY | C7: =MONTH(mydata[[#This Row],[Date]]) -> 1 | D7: 586 | E7: 685 | F7: 175 | G7: 335 | H7: 76 | I7: 212 | J7: 336 | K7: 137 | L7: 134 | M7: 21 | N7: 47 | O7: 29 | P7: 14 | Q7: 120 | R7: 77 | S7: 28 | T7: 11 | U7: 105 | V7: 75 | W7: 6 | X7: 34 | Y7: 13 | Z7: 63 | AA7: 47 | AB7: 20 | AC7: 0 | AD7: 34 | AE7: 6 | AF7: 0 | AG7: 27 | AH7: 0 | AI7: 6 | AJ7: 13 | AK7: 47 | AL7: 47 | AM7: 27 | AN7: 6 | AO7: 0 | AP7: 6 | AQ7: 13 | AR7: 68 | AS7: 13 | AT7: 34 | AU7: 13 | AV7: 6 | AW7: 41 | AX7: 0 | AY7: 20 | AZ7: 0 | BA7: 100.9205 | BB7: 0 | BC7: 0 | BD7: 0 | BE7: 0 | BF7: 0 | BG7: 50000 | BH7: 20000 | BI7: 8000 | BJ7: 23668 | BK7: 11891 | BL7: 3480 | BM7: 4930 | BN7: 1741 | BO7: 29000 | BP7: 3534
A8: 45298 | B8: =CHOOSE(C8, "JANUARY", "FEBRUARY", "MARCH", "APRIL", "MAY", "JUNE", "JULY", "AUGUST", "SEPTEMBER", "OCTOBER", "NOVEMBER", "DECEMBER") -> JANUARY | C8: =MONTH(mydata[[#This Row],[Date]]) -> 1 | D8: 597 | E8: 690 | F8: 310 | G8: 162 | H8: 125 | I8: 282 | J8: 353 | K8: 55 | L8: 166 | M8: 122 | N8: 37 | O8: 22 | P8: 18 | Q8: 77 | R8: 74 | S8: 27 | T8: 34 | U8: 20 | V8: 75 | W8: 0 | X8: 27 | Y8: 6 | Z8: 75 | AA8: 48 | AB8: 6 | AC8: 13 | AD8: 41 | AE8: 20 | AF8: 0 | AG8: 6 | AH8: 20 | AI8: 0 | AJ8: 13 | AK8: 48 | AL8: 6 | AM8: 6 | AN8: 0 | AO8: 0 | AP8: 13 | AQ8: 6 | AR8: 55 | AS8: 6 | AT8: 48 | AU8: 6 | AV8: 6 | AW8: 20 | AX8: 0 | AY8: 0 | AZ8: 120 | BA8: 97.5105 | BB8: 0 | BC8: 0 | BD8: 0 | BE8: 0 | BF8: 0 | BG8: 50000 | BH8: 20000 | BI8: 8000 | BJ8: 23668 | BK8: 11891 | BL8: 3480 | BM8: 4930 | BN8: 1741 | BO8: 29000 | BP8: 7918
A9: 45299 | B9: =CHOOSE(C9, "JANUARY", "FEBRUARY", "MARCH", "APRIL", "MAY", "JUNE", "JULY", "AUGUST", "SEPTEMBER", "OCTOBER", "NOVEMBER", "DECEMBER") -> JANUARY | C9: =MONTH(mydata[[#This Row],[Date]]) -> 1 | D9: 604 | E9: 684 | F9: 217 | G9: 273 | H9: 114 | I9: 307 | J9: 316 | K9: 61 | L9: 149 | M9: 101 | N9: 48 | O9: 37 | P9: 7 | Q9: 126 | R9: 59 | S9: 25 | T9: 11 | U9: 41 | V9: 54 | W9: 13 | X9: 47 | Y9: 13 | Z9: 9 | AA9: 54 | AB9: 13 | AC9: 20 | AD9: 13 | AE9: 13 | AF9: 0 | AG9: 34 | AH9: 20 | AI9: 6 | AJ9: 20 | AK9: 41 | AL9: 34 | AM9: 34 | AN9: 20 | AO9: 6 | AP9: 13 | AQ9: 13 | AR9: 61 | AS9: 13 | AT9: 27 | AU9: 34 | AV9: 6 | AW9: 41 | AX9: 6 | AY9: 6 | AZ9: 0 | BA9: 96.6115 | BB9: 0 | BC9: 0 | BD9: 0 | BE9: 0 | BF9: 0 | BG9: 50000 | BH9: 20000 | BI9: 8000 | BJ9: 23668 | BK9: 11891 | BL9: 3480 | BM9: 4930 | BN9: 1741 | BO9: 29000 | BP9: 520
A10: 45300 | B10: =CHOOSE(C10, "JANUARY", "FEBRUARY", "MARCH", "APRIL", "MAY", "JUNE", "JULY", "AUGUST", "SEPTEMBER", "OCTOBER", "NOVEMBER", "DECEMBER") -> JANUARY | C10: =MONTH(mydata[[#This Row],[Date]]) -> 1 | D10: 606 | E10: 664 | F10: 284 | G10: 262 | H10: 60 | I10: 232 | J10: 346 | K10: 86 | L10: 157 | M10: 127 | N10: 56 | O10: 26 | P10: 33 | Q10: 89 | R10: 64 | S10: 20 | T10: 34 | U10: 0 | V10: 86 | W10: 0 | X10: 19 | Y10: 19 | Z10: 59 | AA10: 59 | AB10: 19 | AC10: 6 | AD10: 39 | AE10: 0 | AF10: 0 | AG10: 19 | AH10: 19 | AI10: 19 | AJ10: 6 | AK10: 46 | AL10: 6 | AM10: 26 | AN10: 0 | AO10: 6 | AP10: 19 | AQ10: 13 | AR10: 66 | AS10: 19 | AT10: 19 | AU10: 13 | AV10: 0 | AW10: 13 | AX10: 19 | AY10: 0 | AZ10: 30 | BA10: 95.7435 | BB10: 0 | BC10: 0 | BD10: 0 | BE10: 0 | BF10: 0 | BG10: 50000 | BH10: 20000 | BI10: 8000 | BJ10: 23668 | BK10: 11891 | BL10: 3480 | BM10: 4930 | BN10: 1741 | BO10: 29000 | BP10: 6207
A11: 45301 | B11: =CHOOSE(C11, "JANUARY", "FEBRUARY", "MARCH", "APRIL", "MAY", "JUNE", "JULY", "AUGUST", "SEPTEMBER", "OCTOBER", "NOVEMBER", "DECEMBER") -> JANUARY | C11: =MONTH(mydata[[#This Row],[Date]]) -> 1 | D11: 602 | E11: 625 | F11: 258 | G11: 314 | H11: 30 | I11: 131 | J11: 451 | K11: 43 | L11: 160 | M11: 97 | N11: 52 | O11: 18 | P11: 14 | Q11: 86 | R11: 16 | S11: 18 | T11: 13 | U11: 128 | V11: 25 | W11: 0 | X11: 43 | Y11: 18 | Z11: 75 | AA11: 56 | AB11: 18 | AC11: 0 | AD11: 12 | AE11: 0 | AF11: 0 | AG11: 6 | AH11: 6 | AI11: 0 | AJ11: 6 | AK11: 43 | AL11: 43 | AM11: 6 | AN11: 12 | AO11: 0 | AP11: 12 | AQ11: 18 | AR11: 62 | AS11: 12 | AT11: 50 | AU11: 31 | AV11: 0 | AW11: 25 | AX11: 0 | AY11: 12 | AZ11: 34 | BA11: 96.3325 | BB11: 0 | BC11: 0 | BD11: 0 | BE11: 0 | BF11: 0 | BG11: 50000 | BH11: 20000 | BI11: 8000 | BJ11: 23668 | BK11: 11891 | BL11: 3480 | BM11: 4930 | BN11: 1741 | BO11: 29000 | BP11: 4999
A12: 45302 | B12: =CHOOSE(C12, "JANUARY", "FEBRUARY", "MARCH", "APRIL", "MAY", "JUNE", "JULY", "AUGUST", "SEPTEMBER", "OCTOBER", "NOVEMBER", "DECEMBER") -> JANUARY | C12: =MONTH(mydata[[#This Row],[Date]]) -> 1 | D12: 584 | E12: 588 | F12: 186 | G12: 334 | H12: 64 | I12: 158 | J12: 313 | K12: 117 | L12: 188 | M12: 86 | N12: 36 | O12: 18 | P12: 18 | Q12: 79 | R12: 17 | S12: 33 | T12: 19 | U12: 90 | V12: 58 | W12: 0 | X12: 35 | Y12: 17 | Z12: 23 | AA12: 35 | AB12: 11 | AC12: 5 | AD12: 17 | AE12: 17 | AF12: 5 | AG12: 17 | AH12: 5 | AI12: 5 | AJ12: 17 | AK12: 52 | AL12: 23 | AM12: 23 | AN12: 11 | AO12: 0 | AP12: 23 | AQ12: 17 | AR12: 41 | AS12: 5 | AT12: 52 | AU12: 11 | AV12: 0 | AW12: 29 | AX12: 17 | AY12: 17 | AZ12: 0 | BA12: 98.6575 | BB12: 0 | BC12: 0 | BD12: 0 | BE12: 0 | BF12: 0 | BG12: 50000 | BH12: 20000 | BI12: 8000 | BJ12: 23668 | BK12: 11891 | BL12: 3480 | BM12: 4930 | BN12: 1741 | BO12: 29000 | BP12: 1124
A13: 45303 | B13: =CHOOSE(C13, "JANUARY", "FEBRUARY", "MARCH", "APRIL", "MAY", "JUNE", "JULY", "AUGUST", "SEPTEMBER", "OCTOBER", "NOVEMBER", "DECEMBER") -> JANUARY | C13: =MONTH(mydata[[#This Row],[Date]]) -> 1 | D13: 560 | E13: 575 | F13: 123 | G13: 348 | H13: 89 | I13: 149 | J13: 369 | K13: 57 | L13: 156 | M13: 27 | N13: 34 | O13: 24 | P13: 24 | Q13: 85 | R13: 36 | S13: 19 | T13: 29 | U13: 126 | V13: 63 | W13: 17 | X13: 40 | Y13: 5 | Z13: 33 | AA13: 51 | AB13: 17 | AC13: 17 | AD13: 11 | AE13: 5 | AF13: 0 | AG13: 17 | AH13: 11 | AI13: 17 | AJ13: 0 | AK13: 28 | AL13: 23 | AM13: 28 | AN13: 0 | AO13: 0 | AP13: 5 | AQ13: 17 | AR13: 40 | AS13: 17 | AT13: 51 | AU13: 11 | AV13: 0 | AW13: 11 | AX13: 17 | AY13: 23 | AZ13: 0 | BA13: 104.067 | BB13: 0 | BC13: 0 | BD13: 0 | BE13: 0 | BF13: 0 | BG13: 50000 | BH13: 10000 | BI13: 5000 | BJ13: 12386 | BK13: 11891 | BL13: 3480 | BM13: 4930 | BN13: 1741 | BO13: 29000 | BP13: 5206
... A367: 45657 | B367: =CHOOSE(C367, "JANUARY", "FEBRUARY", "MARCH", "APRIL", "MAY", "JUNE", "JULY", "AUGUST", "SEPTEMBER", "OCTOBER", "NOVEMBER", "DECEMBER") -> DECEMBER | C367: =MONTH(mydata[[#This Row],[Date]]) -> 12 | D367: 1140 | E367: 881 | F367: 319 | G367: 628 | H367: 193 | I367: 308 | J367: 415 | K367: 158 | L367: 348 | M367: 226 | N367: 63 | O367: 84 | P367: 35 | Q367: 186 | R367: 95 | S367: 60 | T367: 43 | U367: 0 | V367: 35 | W367: 0 | X367: 26 | Y367: 0 | Z367: 61 | AA367: 79 | AB367: 0 | AC367: 17 | AD367: 44 | AE367: 0 | AF367: 8 | AG367: 26 | AH367: 0 | AI367: 17 | AJ367: 17 | AK367: 79 | AL367: 61 | AM367: 17 | AN367: 0 | AO367: 0 | AP367: 8 | AQ367: 26 | AR367: 61 | AS367: 26 | AT367: 35 | AU367: 17 | AV367: 8 | AW367: 61 | AX367: 35 | AY367: 26 | AZ367: 91 | BA367: 200.277 | BB367: 47336.27 | BC367: 41874.39 | BD367: 45515.64 | BE367: 45515.64 | BF367: 1820.63 | BG367: 8000 | BH367: 6250 | BI367: 3353 | BJ367: 7058 | BK367: 75603 | BL367: 63201 | BM367: 55501 | BN367: 30000 | BO367: 230000 | BP367: 8202

Sheet Resources
B1: Colors | C1: Position | D1: Angle | E1: Transparency | G1: Shadow | H1: 0.2 | I1: 100 | J1: 35 | K1: 135 | L1: 15 | P1: $#,##0;-$#,##0;0 | R1: [>=1000]0,"k";[<=-1000]-0,"k";0
B2: #12143D | G2: Shadow | H2: 0.2 | I2: 100 | J2: 35 | K2: 135 | L2: 8
B3: #1F2357 | C3: 0 | D3: 135 | G3: Shadow | H3: 0.2 | I3: 100 | J3: 15 | K3: 135 | L3: 15
B4: #10123B | C4: 75 | D4: 135
A5: Line | B5: #4647A6 | C5: 0 | D5: 135
A6: Line | B6: #333787 | C6: 100 | D6: 135
B8: #20245A | C8: 0 | D8: 135
B9: #10123B | C9: 75 | D9: 135
A10: Line | B10: #B9C1FF | C10: 0 | D10: 150
A11: Line | B11: #3D4098 | C11: 33 | D11: 150
A12: Line | B12: #333787 | C12: 100 | D12: 150
B14: #323687 | C14: 0 | D14: 110
B15: #10123A | C15: 75 | D15: 110
A16: Line | B16: #A2D8F0 | C16: 0 | D16: 135
A17: Line | B17: #5D63D1 | C17: 38 | D17: 135
A18: Line | B18: #2E327A | C18: 100 | D18: 135
B20: #CEC5FF
B21: #6372A4
B22: #0575F1
B24: #22255C | C24: 0 | D24: 0
B25: #2C3076 | C25: 5 | D25: 0
B26: #2C3076 | C26: 97 | D26: 0
B27: #323687 | C27: 100 | D27: 0
A28: Line | B28: #A2D8F0 | C28: 0 | D28: 135
A29: Line | B29: #5D63D1 | C29: 38 | D29: 135
A30: Line | B30: #2E327A | C30: 100 | D30: 135
B31: #2069F0
B32: #9933FF
B34: #22248D | C34: 10 | D34: 135
B35: #060839 | C35: 67 | D35: 135
A36: Line | B36: #7079FF | C36: 25 | D36: 135
A37: Line | B37: #1C1D86 | C37: 100 | D37: 135
B39: #374AEC
B40: #1B2399
B41: #7C93FD
B42: #4641D1
B43: #0093CE
B44: #FF00FF
B46: #808AEC | C46: 10 | D46: 90
B47: #4A59E4 | C47: 80 | D47: 90
B48: #FF00FF | C48: 0 | D48: 90 | E48: 0
B49: #FF00FF | C49: 88 | D49: 90 | E49: 50
B51: #0070B1 | C51: 0 | D51: 90
B52: #00B7D2 | C52: 100 | D52: 90
B53: #3647E3 | C53: 0 | D53: 90
B54: #8D76FC | C54: 100 | D54: 90
B55: #3A5CE2 | C55: 0 | D55: 90
B56: #476BEE | C56: 100 | D56: 90
B57: #8701DA | C57: 0 | D57: 90
B58: #AD27FE | C58: 100 | D58: 90
B59: #34349E | C59: 0 | D59: 90
B60: #212469 | C60: 100 | D60: 90
B62: #476BEE
B63: #3A5CE2
B64: #8199F3
B65: #CAD4FA
